package com.amap.api.mapcore2d;

class ad
  implements Runnable
{
  ad(ac paramac) {}
  
  /* Error */
  public void run()
  {
    // Byte code:
    //   0: aload_0
    //   1: monitorenter
    //   2: aload_0
    //   3: getfield 12	com/amap/api/mapcore2d/ad:a	Lcom/amap/api/mapcore2d/ac;
    //   6: invokestatic 24	com/amap/api/mapcore2d/ac:a	(Lcom/amap/api/mapcore2d/ac;)Ljava/util/concurrent/CopyOnWriteArrayList;
    //   9: invokevirtual 30	java/util/concurrent/CopyOnWriteArrayList:toArray	()[Ljava/lang/Object;
    //   12: astore_3
    //   13: aload_3
    //   14: aload_0
    //   15: getfield 12	com/amap/api/mapcore2d/ad:a	Lcom/amap/api/mapcore2d/ac;
    //   18: invokestatic 34	com/amap/api/mapcore2d/ac:b	(Lcom/amap/api/mapcore2d/ac;)Lcom/amap/api/mapcore2d/ac$a;
    //   21: invokestatic 40	java/util/Arrays:sort	([Ljava/lang/Object;Ljava/util/Comparator;)V
    //   24: aload_0
    //   25: getfield 12	com/amap/api/mapcore2d/ad:a	Lcom/amap/api/mapcore2d/ac;
    //   28: invokestatic 24	com/amap/api/mapcore2d/ac:a	(Lcom/amap/api/mapcore2d/ac;)Ljava/util/concurrent/CopyOnWriteArrayList;
    //   31: invokevirtual 43	java/util/concurrent/CopyOnWriteArrayList:clear	()V
    //   34: aload_3
    //   35: arraylength
    //   36: istore_2
    //   37: iconst_0
    //   38: istore_1
    //   39: iload_1
    //   40: iload_2
    //   41: if_icmpge +40 -> 81
    //   44: aload_3
    //   45: iload_1
    //   46: aaload
    //   47: astore 4
    //   49: aload_0
    //   50: getfield 12	com/amap/api/mapcore2d/ad:a	Lcom/amap/api/mapcore2d/ac;
    //   53: invokestatic 24	com/amap/api/mapcore2d/ac:a	(Lcom/amap/api/mapcore2d/ac;)Ljava/util/concurrent/CopyOnWriteArrayList;
    //   56: aload 4
    //   58: checkcast 45	com/amap/api/mapcore2d/am
    //   61: invokevirtual 49	java/util/concurrent/CopyOnWriteArrayList:add	(Ljava/lang/Object;)Z
    //   64: pop
    //   65: iload_1
    //   66: iconst_1
    //   67: iadd
    //   68: istore_1
    //   69: goto -30 -> 39
    //   72: astore_3
    //   73: aload_3
    //   74: ldc 51
    //   76: ldc 53
    //   78: invokestatic 58	com/amap/api/mapcore2d/ed:a	(Ljava/lang/Throwable;Ljava/lang/String;Ljava/lang/String;)V
    //   81: aload_0
    //   82: monitorexit
    //   83: return
    //   84: astore_3
    //   85: aload_0
    //   86: monitorexit
    //   87: aload_3
    //   88: athrow
    // Local variable table:
    //   start	length	slot	name	signature
    //   0	89	0	this	ad
    //   38	31	1	i	int
    //   36	6	2	j	int
    //   12	33	3	arrayOfObject	Object[]
    //   72	2	3	localThrowable	Throwable
    //   84	4	3	localObject1	Object
    //   47	10	4	localObject2	Object
    // Exception table:
    //   from	to	target	type
    //   2	37	72	java/lang/Throwable
    //   49	65	72	java/lang/Throwable
    //   2	37	84	finally
    //   49	65	84	finally
    //   73	81	84	finally
  }
}

/* Location:
 * Qualified Name:     com.amap.api.mapcore2d.ad
 * Java Class Version: 6 (50.0)
 * JD-Core Version:    0.7.1
 */