package com.amap.api.mapcore2d;

import java.io.IOException;
import java.util.Arrays;

public class di
{
  public static String a(String paramString)
  {
    int i = 0;
    if (paramString == null) {
      return null;
    }
    try
    {
      Object localObject = paramString.split("&");
      Arrays.sort((Object[])localObject);
      StringBuffer localStringBuffer = new StringBuffer();
      int j = localObject.length;
      while (i < j)
      {
        localStringBuffer.append(localObject[i]);
        localStringBuffer.append("&");
        i += 1;
      }
      localObject = localStringBuffer.toString();
      if (((String)localObject).length() > 1)
      {
        localObject = (String)((String)localObject).subSequence(0, ((String)localObject).length() - 1);
        return (String)localObject;
      }
    }
    catch (Throwable localThrowable)
    {
      localThrowable.printStackTrace();
      ed.a(localThrowable, "Utils", "sortParams");
    }
    return paramString;
  }
  
  /* Error */
  static java.security.PublicKey a(android.content.Context paramContext)
  {
    // Byte code:
    //   0: new 61	java/io/ByteArrayInputStream
    //   3: dup
    //   4: sipush 674
    //   7: newarray <illegal type>
    //   9: dup
    //   10: iconst_0
    //   11: ldc 62
    //   13: bastore
    //   14: dup
    //   15: iconst_1
    //   16: ldc 63
    //   18: bastore
    //   19: dup
    //   20: iconst_2
    //   21: ldc 64
    //   23: bastore
    //   24: dup
    //   25: iconst_3
    //   26: ldc 65
    //   28: bastore
    //   29: dup
    //   30: iconst_4
    //   31: ldc 62
    //   33: bastore
    //   34: dup
    //   35: iconst_5
    //   36: ldc 63
    //   38: bastore
    //   39: dup
    //   40: bipush 6
    //   42: ldc 64
    //   44: bastore
    //   45: dup
    //   46: bipush 7
    //   48: ldc 66
    //   50: bastore
    //   51: dup
    //   52: bipush 8
    //   54: ldc 67
    //   56: bastore
    //   57: dup
    //   58: bipush 9
    //   60: ldc 68
    //   62: bastore
    //   63: dup
    //   64: bipush 10
    //   66: ldc 64
    //   68: bastore
    //   69: dup
    //   70: bipush 11
    //   72: ldc 69
    //   74: bastore
    //   75: dup
    //   76: bipush 12
    //   78: ldc 64
    //   80: bastore
    //   81: dup
    //   82: bipush 13
    //   84: ldc 64
    //   86: bastore
    //   87: dup
    //   88: bipush 14
    //   90: ldc 70
    //   92: bastore
    //   93: dup
    //   94: bipush 15
    //   96: ldc 71
    //   98: bastore
    //   99: dup
    //   100: bipush 16
    //   102: ldc 72
    //   104: bastore
    //   105: dup
    //   106: bipush 17
    //   108: ldc 73
    //   110: bastore
    //   111: dup
    //   112: bipush 18
    //   114: ldc 74
    //   116: bastore
    //   117: dup
    //   118: bipush 19
    //   120: ldc 75
    //   122: bastore
    //   123: dup
    //   124: bipush 20
    //   126: ldc 76
    //   128: bastore
    //   129: dup
    //   130: bipush 21
    //   132: ldc 77
    //   134: bastore
    //   135: dup
    //   136: bipush 22
    //   138: ldc 78
    //   140: bastore
    //   141: dup
    //   142: bipush 23
    //   144: ldc 79
    //   146: bastore
    //   147: dup
    //   148: bipush 24
    //   150: ldc 62
    //   152: bastore
    //   153: dup
    //   154: bipush 25
    //   156: ldc 80
    //   158: bastore
    //   159: dup
    //   160: bipush 26
    //   162: ldc 81
    //   164: bastore
    //   165: dup
    //   166: bipush 27
    //   168: ldc 70
    //   170: bastore
    //   171: dup
    //   172: bipush 28
    //   174: ldc 82
    //   176: bastore
    //   177: dup
    //   178: bipush 29
    //   180: ldc 83
    //   182: bastore
    //   183: dup
    //   184: bipush 30
    //   186: ldc 84
    //   188: bastore
    //   189: dup
    //   190: bipush 31
    //   192: ldc 83
    //   194: bastore
    //   195: dup
    //   196: bipush 32
    //   198: ldc 85
    //   200: bastore
    //   201: dup
    //   202: bipush 33
    //   204: ldc 80
    //   206: bastore
    //   207: dup
    //   208: bipush 34
    //   210: ldc 69
    //   212: bastore
    //   213: dup
    //   214: bipush 35
    //   216: ldc 69
    //   218: bastore
    //   219: dup
    //   220: bipush 36
    //   222: ldc 86
    //   224: bastore
    //   225: dup
    //   226: bipush 37
    //   228: ldc 86
    //   230: bastore
    //   231: dup
    //   232: bipush 38
    //   234: ldc 71
    //   236: bastore
    //   237: dup
    //   238: bipush 39
    //   240: ldc 62
    //   242: bastore
    //   243: dup
    //   244: bipush 40
    //   246: ldc 87
    //   248: bastore
    //   249: dup
    //   250: bipush 41
    //   252: ldc 88
    //   254: bastore
    //   255: dup
    //   256: bipush 42
    //   258: ldc 89
    //   260: bastore
    //   261: dup
    //   262: bipush 43
    //   264: ldc 62
    //   266: bastore
    //   267: dup
    //   268: bipush 44
    //   270: ldc 70
    //   272: bastore
    //   273: dup
    //   274: bipush 45
    //   276: ldc 81
    //   278: bastore
    //   279: dup
    //   280: bipush 46
    //   282: ldc 68
    //   284: bastore
    //   285: dup
    //   286: bipush 47
    //   288: ldc 90
    //   290: bastore
    //   291: dup
    //   292: bipush 48
    //   294: ldc 91
    //   296: bastore
    //   297: dup
    //   298: bipush 49
    //   300: ldc 81
    //   302: bastore
    //   303: dup
    //   304: bipush 50
    //   306: ldc 92
    //   308: bastore
    //   309: dup
    //   310: bipush 51
    //   312: ldc 64
    //   314: bastore
    //   315: dup
    //   316: bipush 52
    //   318: ldc 93
    //   320: bastore
    //   321: dup
    //   322: bipush 53
    //   324: ldc 94
    //   326: bastore
    //   327: dup
    //   328: bipush 54
    //   330: ldc 88
    //   332: bastore
    //   333: dup
    //   334: bipush 55
    //   336: ldc 92
    //   338: bastore
    //   339: dup
    //   340: bipush 56
    //   342: ldc 62
    //   344: bastore
    //   345: dup
    //   346: bipush 57
    //   348: ldc 95
    //   350: bastore
    //   351: dup
    //   352: bipush 58
    //   354: ldc 81
    //   356: bastore
    //   357: dup
    //   358: bipush 59
    //   360: ldc 68
    //   362: bastore
    //   363: dup
    //   364: bipush 60
    //   366: ldc 90
    //   368: bastore
    //   369: dup
    //   370: bipush 61
    //   372: ldc 91
    //   374: bastore
    //   375: dup
    //   376: bipush 62
    //   378: ldc 96
    //   380: bastore
    //   381: dup
    //   382: bipush 63
    //   384: ldc 97
    //   386: bastore
    //   387: dup
    //   388: bipush 64
    //   390: ldc 98
    //   392: bastore
    //   393: dup
    //   394: bipush 65
    //   396: ldc 99
    //   398: bastore
    //   399: dup
    //   400: bipush 66
    //   402: ldc 100
    //   404: bastore
    //   405: dup
    //   406: bipush 67
    //   408: ldc 101
    //   410: bastore
    //   411: dup
    //   412: bipush 68
    //   414: ldc 102
    //   416: bastore
    //   417: dup
    //   418: bipush 69
    //   420: ldc 103
    //   422: bastore
    //   423: dup
    //   424: bipush 70
    //   426: ldc 99
    //   428: bastore
    //   429: dup
    //   430: bipush 71
    //   432: ldc 104
    //   434: bastore
    //   435: dup
    //   436: bipush 72
    //   438: ldc 105
    //   440: bastore
    //   441: dup
    //   442: bipush 73
    //   444: ldc 104
    //   446: bastore
    //   447: dup
    //   448: bipush 74
    //   450: ldc 102
    //   452: bastore
    //   453: dup
    //   454: bipush 75
    //   456: ldc 88
    //   458: bastore
    //   459: dup
    //   460: bipush 76
    //   462: ldc 106
    //   464: bastore
    //   465: dup
    //   466: bipush 77
    //   468: ldc 62
    //   470: bastore
    //   471: dup
    //   472: bipush 78
    //   474: ldc 107
    //   476: bastore
    //   477: dup
    //   478: bipush 79
    //   480: ldc 81
    //   482: bastore
    //   483: dup
    //   484: bipush 80
    //   486: ldc 68
    //   488: bastore
    //   489: dup
    //   490: bipush 81
    //   492: ldc 90
    //   494: bastore
    //   495: dup
    //   496: bipush 82
    //   498: ldc 91
    //   500: bastore
    //   501: dup
    //   502: bipush 83
    //   504: ldc 66
    //   506: bastore
    //   507: dup
    //   508: bipush 84
    //   510: ldc 97
    //   512: bastore
    //   513: dup
    //   514: bipush 85
    //   516: ldc 66
    //   518: bastore
    //   519: dup
    //   520: bipush 86
    //   522: ldc 108
    //   524: bastore
    //   525: dup
    //   526: bipush 87
    //   528: ldc 102
    //   530: bastore
    //   531: dup
    //   532: bipush 88
    //   534: ldc 109
    //   536: bastore
    //   537: dup
    //   538: bipush 89
    //   540: ldc 110
    //   542: bastore
    //   543: dup
    //   544: bipush 90
    //   546: ldc 109
    //   548: bastore
    //   549: dup
    //   550: bipush 91
    //   552: ldc 111
    //   554: bastore
    //   555: dup
    //   556: bipush 92
    //   558: ldc 112
    //   560: bastore
    //   561: dup
    //   562: bipush 93
    //   564: ldc 88
    //   566: bastore
    //   567: dup
    //   568: bipush 94
    //   570: ldc 95
    //   572: bastore
    //   573: dup
    //   574: bipush 95
    //   576: ldc 62
    //   578: bastore
    //   579: dup
    //   580: bipush 96
    //   582: ldc 73
    //   584: bastore
    //   585: dup
    //   586: bipush 97
    //   588: ldc 81
    //   590: bastore
    //   591: dup
    //   592: bipush 98
    //   594: ldc 68
    //   596: bastore
    //   597: dup
    //   598: bipush 99
    //   600: ldc 90
    //   602: bastore
    //   603: dup
    //   604: bipush 100
    //   606: ldc 91
    //   608: bastore
    //   609: dup
    //   610: bipush 101
    //   612: ldc 98
    //   614: bastore
    //   615: dup
    //   616: bipush 102
    //   618: ldc 97
    //   620: bastore
    //   621: dup
    //   622: bipush 103
    //   624: ldc 96
    //   626: bastore
    //   627: dup
    //   628: bipush 104
    //   630: ldc 113
    //   632: bastore
    //   633: dup
    //   634: bipush 105
    //   636: ldc 114
    //   638: bastore
    //   639: dup
    //   640: bipush 106
    //   642: ldc 104
    //   644: bastore
    //   645: dup
    //   646: bipush 107
    //   648: ldc 100
    //   650: bastore
    //   651: dup
    //   652: bipush 108
    //   654: ldc 111
    //   656: bastore
    //   657: dup
    //   658: bipush 109
    //   660: ldc 105
    //   662: bastore
    //   663: dup
    //   664: bipush 110
    //   666: ldc 115
    //   668: bastore
    //   669: dup
    //   670: bipush 111
    //   672: ldc 109
    //   674: bastore
    //   675: dup
    //   676: bipush 112
    //   678: ldc 88
    //   680: bastore
    //   681: dup
    //   682: bipush 113
    //   684: ldc 116
    //   686: bastore
    //   687: dup
    //   688: bipush 114
    //   690: ldc 62
    //   692: bastore
    //   693: dup
    //   694: bipush 115
    //   696: ldc 117
    //   698: bastore
    //   699: dup
    //   700: bipush 116
    //   702: ldc 81
    //   704: bastore
    //   705: dup
    //   706: bipush 117
    //   708: ldc 68
    //   710: bastore
    //   711: dup
    //   712: bipush 118
    //   714: ldc 90
    //   716: bastore
    //   717: dup
    //   718: bipush 119
    //   720: ldc 91
    //   722: bastore
    //   723: dup
    //   724: bipush 120
    //   726: ldc 68
    //   728: bastore
    //   729: dup
    //   730: bipush 121
    //   732: ldc 97
    //   734: bastore
    //   735: dup
    //   736: bipush 122
    //   738: ldc 118
    //   740: bastore
    //   741: dup
    //   742: bipush 123
    //   744: ldc 119
    //   746: bastore
    //   747: dup
    //   748: bipush 124
    //   750: ldc 100
    //   752: bastore
    //   753: dup
    //   754: bipush 125
    //   756: ldc 101
    //   758: bastore
    //   759: dup
    //   760: bipush 126
    //   762: ldc 120
    //   764: bastore
    //   765: dup
    //   766: bipush 127
    //   768: ldc 105
    //   770: bastore
    //   771: dup
    //   772: sipush 128
    //   775: ldc 114
    //   777: bastore
    //   778: dup
    //   779: sipush 129
    //   782: ldc 104
    //   784: bastore
    //   785: dup
    //   786: sipush 130
    //   789: ldc 100
    //   791: bastore
    //   792: dup
    //   793: sipush 131
    //   796: ldc 111
    //   798: bastore
    //   799: dup
    //   800: sipush 132
    //   803: ldc 105
    //   805: bastore
    //   806: dup
    //   807: sipush 133
    //   810: ldc 115
    //   812: bastore
    //   813: dup
    //   814: sipush 134
    //   817: ldc 109
    //   819: bastore
    //   820: dup
    //   821: sipush 135
    //   824: ldc 120
    //   826: bastore
    //   827: dup
    //   828: sipush 136
    //   831: ldc 105
    //   833: bastore
    //   834: dup
    //   835: sipush 137
    //   838: ldc 121
    //   840: bastore
    //   841: dup
    //   842: sipush 138
    //   845: ldc 109
    //   847: bastore
    //   848: dup
    //   849: sipush 139
    //   852: ldc 122
    //   854: bastore
    //   855: dup
    //   856: sipush 140
    //   859: ldc 102
    //   861: bastore
    //   862: dup
    //   863: sipush 141
    //   866: ldc 123
    //   868: bastore
    //   869: dup
    //   870: sipush 142
    //   873: ldc 115
    //   875: bastore
    //   876: dup
    //   877: sipush 143
    //   880: ldc 102
    //   882: bastore
    //   883: dup
    //   884: sipush 144
    //   887: ldc 123
    //   889: bastore
    //   890: dup
    //   891: sipush 145
    //   894: ldc 62
    //   896: bastore
    //   897: dup
    //   898: sipush 146
    //   901: ldc 124
    //   903: bastore
    //   904: dup
    //   905: sipush 147
    //   908: ldc 125
    //   910: bastore
    //   911: dup
    //   912: sipush 148
    //   915: ldc 80
    //   917: bastore
    //   918: dup
    //   919: sipush 149
    //   922: ldc 88
    //   924: bastore
    //   925: dup
    //   926: sipush 150
    //   929: ldc 126
    //   931: bastore
    //   932: dup
    //   933: sipush 151
    //   936: ldc 62
    //   938: bastore
    //   939: dup
    //   940: sipush 152
    //   943: ldc 127
    //   945: bastore
    //   946: dup
    //   947: sipush 153
    //   950: ldc 88
    //   952: bastore
    //   953: dup
    //   954: sipush 154
    //   957: ldc -128
    //   959: bastore
    //   960: dup
    //   961: sipush 155
    //   964: ldc 62
    //   966: bastore
    //   967: dup
    //   968: sipush 156
    //   971: ldc -127
    //   973: bastore
    //   974: dup
    //   975: sipush 157
    //   978: ldc -128
    //   980: bastore
    //   981: dup
    //   982: sipush 158
    //   985: ldc -126
    //   987: bastore
    //   988: dup
    //   989: sipush 159
    //   992: ldc -128
    //   994: bastore
    //   995: dup
    //   996: sipush 160
    //   999: ldc -128
    //   1001: bastore
    //   1002: dup
    //   1003: sipush 161
    //   1006: ldc -125
    //   1008: bastore
    //   1009: dup
    //   1010: sipush 162
    //   1013: ldc 125
    //   1015: bastore
    //   1016: dup
    //   1017: sipush 163
    //   1020: ldc 80
    //   1022: bastore
    //   1023: dup
    //   1024: sipush 164
    //   1027: ldc -124
    //   1029: bastore
    //   1030: dup
    //   1031: sipush 165
    //   1034: ldc 126
    //   1036: bastore
    //   1037: dup
    //   1038: sipush 166
    //   1041: ldc 62
    //   1043: bastore
    //   1044: dup
    //   1045: sipush 167
    //   1048: ldc 127
    //   1050: bastore
    //   1051: dup
    //   1052: sipush 168
    //   1055: ldc 88
    //   1057: bastore
    //   1058: dup
    //   1059: sipush 169
    //   1062: ldc 126
    //   1064: bastore
    //   1065: dup
    //   1066: sipush 170
    //   1069: ldc 62
    //   1071: bastore
    //   1072: dup
    //   1073: sipush 171
    //   1076: ldc -127
    //   1078: bastore
    //   1079: dup
    //   1080: sipush 172
    //   1083: ldc -128
    //   1085: bastore
    //   1086: dup
    //   1087: sipush 173
    //   1090: ldc -126
    //   1092: bastore
    //   1093: dup
    //   1094: sipush 174
    //   1097: ldc -128
    //   1099: bastore
    //   1100: dup
    //   1101: sipush 175
    //   1104: ldc -128
    //   1106: bastore
    //   1107: dup
    //   1108: sipush 176
    //   1111: ldc -125
    //   1113: bastore
    //   1114: dup
    //   1115: sipush 177
    //   1118: ldc 62
    //   1120: bastore
    //   1121: dup
    //   1122: sipush 178
    //   1125: ldc 87
    //   1127: bastore
    //   1128: dup
    //   1129: sipush 179
    //   1132: ldc 88
    //   1134: bastore
    //   1135: dup
    //   1136: sipush 180
    //   1139: ldc 89
    //   1141: bastore
    //   1142: dup
    //   1143: sipush 181
    //   1146: ldc 62
    //   1148: bastore
    //   1149: dup
    //   1150: sipush 182
    //   1153: ldc 70
    //   1155: bastore
    //   1156: dup
    //   1157: sipush 183
    //   1160: ldc 81
    //   1162: bastore
    //   1163: dup
    //   1164: sipush 184
    //   1167: ldc 68
    //   1169: bastore
    //   1170: dup
    //   1171: sipush 185
    //   1174: ldc 90
    //   1176: bastore
    //   1177: dup
    //   1178: sipush 186
    //   1181: ldc 91
    //   1183: bastore
    //   1184: dup
    //   1185: sipush 187
    //   1188: ldc 81
    //   1190: bastore
    //   1191: dup
    //   1192: sipush 188
    //   1195: ldc 92
    //   1197: bastore
    //   1198: dup
    //   1199: sipush 189
    //   1202: ldc 64
    //   1204: bastore
    //   1205: dup
    //   1206: sipush 190
    //   1209: ldc 93
    //   1211: bastore
    //   1212: dup
    //   1213: sipush 191
    //   1216: ldc 94
    //   1218: bastore
    //   1219: dup
    //   1220: sipush 192
    //   1223: ldc 88
    //   1225: bastore
    //   1226: dup
    //   1227: sipush 193
    //   1230: ldc 92
    //   1232: bastore
    //   1233: dup
    //   1234: sipush 194
    //   1237: ldc 62
    //   1239: bastore
    //   1240: dup
    //   1241: sipush 195
    //   1244: ldc 95
    //   1246: bastore
    //   1247: dup
    //   1248: sipush 196
    //   1251: ldc 81
    //   1253: bastore
    //   1254: dup
    //   1255: sipush 197
    //   1258: ldc 68
    //   1260: bastore
    //   1261: dup
    //   1262: sipush 198
    //   1265: ldc 90
    //   1267: bastore
    //   1268: dup
    //   1269: sipush 199
    //   1272: ldc 91
    //   1274: bastore
    //   1275: dup
    //   1276: sipush 200
    //   1279: ldc 96
    //   1281: bastore
    //   1282: dup
    //   1283: sipush 201
    //   1286: ldc 97
    //   1288: bastore
    //   1289: dup
    //   1290: sipush 202
    //   1293: ldc 98
    //   1295: bastore
    //   1296: dup
    //   1297: sipush 203
    //   1300: ldc 99
    //   1302: bastore
    //   1303: dup
    //   1304: sipush 204
    //   1307: ldc 100
    //   1309: bastore
    //   1310: dup
    //   1311: sipush 205
    //   1314: ldc 101
    //   1316: bastore
    //   1317: dup
    //   1318: sipush 206
    //   1321: ldc 102
    //   1323: bastore
    //   1324: dup
    //   1325: sipush 207
    //   1328: ldc 103
    //   1330: bastore
    //   1331: dup
    //   1332: sipush 208
    //   1335: ldc 99
    //   1337: bastore
    //   1338: dup
    //   1339: sipush 209
    //   1342: ldc 104
    //   1344: bastore
    //   1345: dup
    //   1346: sipush 210
    //   1349: ldc 105
    //   1351: bastore
    //   1352: dup
    //   1353: sipush 211
    //   1356: ldc 104
    //   1358: bastore
    //   1359: dup
    //   1360: sipush 212
    //   1363: ldc 102
    //   1365: bastore
    //   1366: dup
    //   1367: sipush 213
    //   1370: ldc 88
    //   1372: bastore
    //   1373: dup
    //   1374: sipush 214
    //   1377: ldc 106
    //   1379: bastore
    //   1380: dup
    //   1381: sipush 215
    //   1384: ldc 62
    //   1386: bastore
    //   1387: dup
    //   1388: sipush 216
    //   1391: ldc 107
    //   1393: bastore
    //   1394: dup
    //   1395: sipush 217
    //   1398: ldc 81
    //   1400: bastore
    //   1401: dup
    //   1402: sipush 218
    //   1405: ldc 68
    //   1407: bastore
    //   1408: dup
    //   1409: sipush 219
    //   1412: ldc 90
    //   1414: bastore
    //   1415: dup
    //   1416: sipush 220
    //   1419: ldc 91
    //   1421: bastore
    //   1422: dup
    //   1423: sipush 221
    //   1426: ldc 66
    //   1428: bastore
    //   1429: dup
    //   1430: sipush 222
    //   1433: ldc 97
    //   1435: bastore
    //   1436: dup
    //   1437: sipush 223
    //   1440: ldc 66
    //   1442: bastore
    //   1443: dup
    //   1444: sipush 224
    //   1447: ldc 108
    //   1449: bastore
    //   1450: dup
    //   1451: sipush 225
    //   1454: ldc 102
    //   1456: bastore
    //   1457: dup
    //   1458: sipush 226
    //   1461: ldc 109
    //   1463: bastore
    //   1464: dup
    //   1465: sipush 227
    //   1468: ldc 110
    //   1470: bastore
    //   1471: dup
    //   1472: sipush 228
    //   1475: ldc 109
    //   1477: bastore
    //   1478: dup
    //   1479: sipush 229
    //   1482: ldc 111
    //   1484: bastore
    //   1485: dup
    //   1486: sipush 230
    //   1489: ldc 112
    //   1491: bastore
    //   1492: dup
    //   1493: sipush 231
    //   1496: ldc 88
    //   1498: bastore
    //   1499: dup
    //   1500: sipush 232
    //   1503: ldc 95
    //   1505: bastore
    //   1506: dup
    //   1507: sipush 233
    //   1510: ldc 62
    //   1512: bastore
    //   1513: dup
    //   1514: sipush 234
    //   1517: ldc 73
    //   1519: bastore
    //   1520: dup
    //   1521: sipush 235
    //   1524: ldc 81
    //   1526: bastore
    //   1527: dup
    //   1528: sipush 236
    //   1531: ldc 68
    //   1533: bastore
    //   1534: dup
    //   1535: sipush 237
    //   1538: ldc 90
    //   1540: bastore
    //   1541: dup
    //   1542: sipush 238
    //   1545: ldc 91
    //   1547: bastore
    //   1548: dup
    //   1549: sipush 239
    //   1552: ldc 98
    //   1554: bastore
    //   1555: dup
    //   1556: sipush 240
    //   1559: ldc 97
    //   1561: bastore
    //   1562: dup
    //   1563: sipush 241
    //   1566: ldc 96
    //   1568: bastore
    //   1569: dup
    //   1570: sipush 242
    //   1573: ldc 113
    //   1575: bastore
    //   1576: dup
    //   1577: sipush 243
    //   1580: ldc 114
    //   1582: bastore
    //   1583: dup
    //   1584: sipush 244
    //   1587: ldc 104
    //   1589: bastore
    //   1590: dup
    //   1591: sipush 245
    //   1594: ldc 100
    //   1596: bastore
    //   1597: dup
    //   1598: sipush 246
    //   1601: ldc 111
    //   1603: bastore
    //   1604: dup
    //   1605: sipush 247
    //   1608: ldc 105
    //   1610: bastore
    //   1611: dup
    //   1612: sipush 248
    //   1615: ldc 115
    //   1617: bastore
    //   1618: dup
    //   1619: sipush 249
    //   1622: ldc 109
    //   1624: bastore
    //   1625: dup
    //   1626: sipush 250
    //   1629: ldc 88
    //   1631: bastore
    //   1632: dup
    //   1633: sipush 251
    //   1636: ldc 116
    //   1638: bastore
    //   1639: dup
    //   1640: sipush 252
    //   1643: ldc 62
    //   1645: bastore
    //   1646: dup
    //   1647: sipush 253
    //   1650: ldc 117
    //   1652: bastore
    //   1653: dup
    //   1654: sipush 254
    //   1657: ldc 81
    //   1659: bastore
    //   1660: dup
    //   1661: sipush 255
    //   1664: ldc 68
    //   1666: bastore
    //   1667: dup
    //   1668: sipush 256
    //   1671: ldc 90
    //   1673: bastore
    //   1674: dup
    //   1675: sipush 257
    //   1678: ldc 91
    //   1680: bastore
    //   1681: dup
    //   1682: sipush 258
    //   1685: ldc 68
    //   1687: bastore
    //   1688: dup
    //   1689: sipush 259
    //   1692: ldc 97
    //   1694: bastore
    //   1695: dup
    //   1696: sipush 260
    //   1699: ldc 118
    //   1701: bastore
    //   1702: dup
    //   1703: sipush 261
    //   1706: ldc 119
    //   1708: bastore
    //   1709: dup
    //   1710: sipush 262
    //   1713: ldc 100
    //   1715: bastore
    //   1716: dup
    //   1717: sipush 263
    //   1720: ldc 101
    //   1722: bastore
    //   1723: dup
    //   1724: sipush 264
    //   1727: ldc 120
    //   1729: bastore
    //   1730: dup
    //   1731: sipush 265
    //   1734: ldc 105
    //   1736: bastore
    //   1737: dup
    //   1738: sipush 266
    //   1741: ldc 114
    //   1743: bastore
    //   1744: dup
    //   1745: sipush 267
    //   1748: ldc 104
    //   1750: bastore
    //   1751: dup
    //   1752: sipush 268
    //   1755: ldc 100
    //   1757: bastore
    //   1758: dup
    //   1759: sipush 269
    //   1762: ldc 111
    //   1764: bastore
    //   1765: dup
    //   1766: sipush 270
    //   1769: ldc 105
    //   1771: bastore
    //   1772: dup
    //   1773: sipush 271
    //   1776: ldc 115
    //   1778: bastore
    //   1779: dup
    //   1780: sipush 272
    //   1783: ldc 109
    //   1785: bastore
    //   1786: dup
    //   1787: sipush 273
    //   1790: ldc 120
    //   1792: bastore
    //   1793: dup
    //   1794: sipush 274
    //   1797: ldc 105
    //   1799: bastore
    //   1800: dup
    //   1801: sipush 275
    //   1804: ldc 121
    //   1806: bastore
    //   1807: dup
    //   1808: sipush 276
    //   1811: ldc 109
    //   1813: bastore
    //   1814: dup
    //   1815: sipush 277
    //   1818: ldc 122
    //   1820: bastore
    //   1821: dup
    //   1822: sipush 278
    //   1825: ldc 102
    //   1827: bastore
    //   1828: dup
    //   1829: sipush 279
    //   1832: ldc 123
    //   1834: bastore
    //   1835: dup
    //   1836: sipush 280
    //   1839: ldc 115
    //   1841: bastore
    //   1842: dup
    //   1843: sipush 281
    //   1846: ldc 102
    //   1848: bastore
    //   1849: dup
    //   1850: sipush 282
    //   1853: ldc 123
    //   1855: bastore
    //   1856: dup
    //   1857: sipush 283
    //   1860: ldc 62
    //   1862: bastore
    //   1863: dup
    //   1864: sipush 284
    //   1867: ldc -123
    //   1869: bastore
    //   1870: dup
    //   1871: sipush 285
    //   1874: ldc -122
    //   1876: bastore
    //   1877: dup
    //   1878: sipush 286
    //   1881: ldc 62
    //   1883: bastore
    //   1884: dup
    //   1885: sipush 287
    //   1888: ldc 80
    //   1890: bastore
    //   1891: dup
    //   1892: sipush 288
    //   1895: ldc 81
    //   1897: bastore
    //   1898: dup
    //   1899: sipush 289
    //   1902: ldc 70
    //   1904: bastore
    //   1905: dup
    //   1906: sipush 290
    //   1909: ldc 82
    //   1911: bastore
    //   1912: dup
    //   1913: sipush 291
    //   1916: ldc 83
    //   1918: bastore
    //   1919: dup
    //   1920: sipush 292
    //   1923: ldc 84
    //   1925: bastore
    //   1926: dup
    //   1927: sipush 293
    //   1930: ldc 83
    //   1932: bastore
    //   1933: dup
    //   1934: sipush 294
    //   1937: ldc 85
    //   1939: bastore
    //   1940: dup
    //   1941: sipush 295
    //   1944: ldc 80
    //   1946: bastore
    //   1947: dup
    //   1948: sipush 296
    //   1951: ldc 69
    //   1953: bastore
    //   1954: dup
    //   1955: sipush 297
    //   1958: ldc 69
    //   1960: bastore
    //   1961: dup
    //   1962: sipush 298
    //   1965: ldc 69
    //   1967: bastore
    //   1968: dup
    //   1969: sipush 299
    //   1972: ldc 86
    //   1974: bastore
    //   1975: dup
    //   1976: sipush 300
    //   1979: ldc 71
    //   1981: bastore
    //   1982: dup
    //   1983: sipush 301
    //   1986: ldc 68
    //   1988: bastore
    //   1989: dup
    //   1990: sipush 302
    //   1993: ldc -123
    //   1995: bastore
    //   1996: dup
    //   1997: sipush 303
    //   2000: ldc -121
    //   2002: bastore
    //   2003: dup
    //   2004: sipush 304
    //   2007: ldc 71
    //   2009: bastore
    //   2010: dup
    //   2011: sipush 305
    //   2014: ldc 62
    //   2016: bastore
    //   2017: dup
    //   2018: sipush 306
    //   2021: ldc -123
    //   2023: bastore
    //   2024: dup
    //   2025: sipush 307
    //   2028: ldc -120
    //   2030: bastore
    //   2031: dup
    //   2032: sipush 308
    //   2035: ldc 64
    //   2037: bastore
    //   2038: dup
    //   2039: sipush 309
    //   2042: ldc -123
    //   2044: bastore
    //   2045: dup
    //   2046: sipush 310
    //   2049: ldc -123
    //   2051: bastore
    //   2052: dup
    //   2053: sipush 311
    //   2056: ldc 71
    //   2058: bastore
    //   2059: dup
    //   2060: sipush 312
    //   2063: ldc -119
    //   2065: bastore
    //   2066: dup
    //   2067: sipush 313
    //   2070: ldc -118
    //   2072: bastore
    //   2073: dup
    //   2074: sipush 314
    //   2077: ldc -117
    //   2079: bastore
    //   2080: dup
    //   2081: sipush 315
    //   2084: ldc -116
    //   2086: bastore
    //   2087: dup
    //   2088: sipush 316
    //   2091: ldc 115
    //   2093: bastore
    //   2094: dup
    //   2095: sipush 317
    //   2098: ldc -115
    //   2100: bastore
    //   2101: dup
    //   2102: sipush 318
    //   2105: ldc -114
    //   2107: bastore
    //   2108: dup
    //   2109: sipush 319
    //   2112: ldc -123
    //   2114: bastore
    //   2115: dup
    //   2116: sipush 320
    //   2119: ldc -113
    //   2121: bastore
    //   2122: dup
    //   2123: sipush 321
    //   2126: ldc -112
    //   2128: bastore
    //   2129: dup
    //   2130: sipush 322
    //   2133: ldc -111
    //   2135: bastore
    //   2136: dup
    //   2137: sipush 323
    //   2140: ldc -110
    //   2142: bastore
    //   2143: dup
    //   2144: sipush 324
    //   2147: ldc 71
    //   2149: bastore
    //   2150: dup
    //   2151: sipush 325
    //   2154: ldc -109
    //   2156: bastore
    //   2157: dup
    //   2158: sipush 326
    //   2161: ldc -108
    //   2163: bastore
    //   2164: dup
    //   2165: sipush 327
    //   2168: ldc -107
    //   2170: bastore
    //   2171: dup
    //   2172: sipush 328
    //   2175: ldc 115
    //   2177: bastore
    //   2178: dup
    //   2179: sipush 329
    //   2182: ldc 86
    //   2184: bastore
    //   2185: dup
    //   2186: sipush 330
    //   2189: ldc -106
    //   2191: bastore
    //   2192: dup
    //   2193: sipush 331
    //   2196: ldc -105
    //   2198: bastore
    //   2199: dup
    //   2200: sipush 332
    //   2203: ldc -104
    //   2205: bastore
    //   2206: dup
    //   2207: sipush 333
    //   2210: ldc -103
    //   2212: bastore
    //   2213: dup
    //   2214: sipush 334
    //   2217: ldc -125
    //   2219: bastore
    //   2220: dup
    //   2221: sipush 335
    //   2224: ldc -102
    //   2226: bastore
    //   2227: dup
    //   2228: sipush 336
    //   2231: ldc 84
    //   2233: bastore
    //   2234: dup
    //   2235: sipush 337
    //   2238: ldc 63
    //   2240: bastore
    //   2241: dup
    //   2242: sipush 338
    //   2245: ldc -101
    //   2247: bastore
    //   2248: dup
    //   2249: sipush 339
    //   2252: ldc -100
    //   2254: bastore
    //   2255: dup
    //   2256: sipush 340
    //   2259: ldc -99
    //   2261: bastore
    //   2262: dup
    //   2263: sipush 341
    //   2266: ldc -98
    //   2268: bastore
    //   2269: dup
    //   2270: sipush 342
    //   2273: ldc -97
    //   2275: bastore
    //   2276: dup
    //   2277: sipush 343
    //   2280: ldc -96
    //   2282: bastore
    //   2283: dup
    //   2284: sipush 344
    //   2287: ldc -95
    //   2289: bastore
    //   2290: dup
    //   2291: sipush 345
    //   2294: ldc 125
    //   2296: bastore
    //   2297: dup
    //   2298: sipush 346
    //   2301: ldc -94
    //   2303: bastore
    //   2304: dup
    //   2305: sipush 347
    //   2308: ldc -105
    //   2310: bastore
    //   2311: dup
    //   2312: sipush 348
    //   2315: ldc -93
    //   2317: bastore
    //   2318: dup
    //   2319: sipush 349
    //   2322: ldc -102
    //   2324: bastore
    //   2325: dup
    //   2326: sipush 350
    //   2329: ldc -92
    //   2331: bastore
    //   2332: dup
    //   2333: sipush 351
    //   2336: ldc 118
    //   2338: bastore
    //   2339: dup
    //   2340: sipush 352
    //   2343: ldc -91
    //   2345: bastore
    //   2346: dup
    //   2347: sipush 353
    //   2350: ldc -90
    //   2352: bastore
    //   2353: dup
    //   2354: sipush 354
    //   2357: ldc -89
    //   2359: bastore
    //   2360: dup
    //   2361: sipush 355
    //   2364: ldc -88
    //   2366: bastore
    //   2367: dup
    //   2368: sipush 356
    //   2371: ldc 93
    //   2373: bastore
    //   2374: dup
    //   2375: sipush 357
    //   2378: ldc -87
    //   2380: bastore
    //   2381: dup
    //   2382: sipush 358
    //   2385: ldc 113
    //   2387: bastore
    //   2388: dup
    //   2389: sipush 359
    //   2392: ldc -86
    //   2394: bastore
    //   2395: dup
    //   2396: sipush 360
    //   2399: ldc -92
    //   2401: bastore
    //   2402: dup
    //   2403: sipush 361
    //   2406: ldc 89
    //   2408: bastore
    //   2409: dup
    //   2410: sipush 362
    //   2413: ldc -85
    //   2415: bastore
    //   2416: dup
    //   2417: sipush 363
    //   2420: ldc -84
    //   2422: bastore
    //   2423: dup
    //   2424: sipush 364
    //   2427: ldc -83
    //   2429: bastore
    //   2430: dup
    //   2431: sipush 365
    //   2434: ldc 106
    //   2436: bastore
    //   2437: dup
    //   2438: sipush 366
    //   2441: ldc -82
    //   2443: bastore
    //   2444: dup
    //   2445: sipush 367
    //   2448: ldc -81
    //   2450: bastore
    //   2451: dup
    //   2452: sipush 368
    //   2455: ldc -80
    //   2457: bastore
    //   2458: dup
    //   2459: sipush 369
    //   2462: ldc 75
    //   2464: bastore
    //   2465: dup
    //   2466: sipush 370
    //   2469: ldc -79
    //   2471: bastore
    //   2472: dup
    //   2473: sipush 371
    //   2476: ldc 107
    //   2478: bastore
    //   2479: dup
    //   2480: sipush 372
    //   2483: ldc 89
    //   2485: bastore
    //   2486: dup
    //   2487: sipush 373
    //   2490: ldc -78
    //   2492: bastore
    //   2493: dup
    //   2494: sipush 374
    //   2497: ldc -77
    //   2499: bastore
    //   2500: dup
    //   2501: sipush 375
    //   2504: ldc 80
    //   2506: bastore
    //   2507: dup
    //   2508: sipush 376
    //   2511: ldc -105
    //   2513: bastore
    //   2514: dup
    //   2515: sipush 377
    //   2518: ldc -76
    //   2520: bastore
    //   2521: dup
    //   2522: sipush 378
    //   2525: ldc 109
    //   2527: bastore
    //   2528: dup
    //   2529: sipush 379
    //   2532: ldc -75
    //   2534: bastore
    //   2535: dup
    //   2536: sipush 380
    //   2539: ldc -102
    //   2541: bastore
    //   2542: dup
    //   2543: sipush 381
    //   2546: ldc -74
    //   2548: bastore
    //   2549: dup
    //   2550: sipush 382
    //   2553: ldc 123
    //   2555: bastore
    //   2556: dup
    //   2557: sipush 383
    //   2560: ldc -73
    //   2562: bastore
    //   2563: dup
    //   2564: sipush 384
    //   2567: ldc -100
    //   2569: bastore
    //   2570: dup
    //   2571: sipush 385
    //   2574: ldc 97
    //   2576: bastore
    //   2577: dup
    //   2578: sipush 386
    //   2581: ldc -76
    //   2583: bastore
    //   2584: dup
    //   2585: sipush 387
    //   2588: ldc -72
    //   2590: bastore
    //   2591: dup
    //   2592: sipush 388
    //   2595: ldc -96
    //   2597: bastore
    //   2598: dup
    //   2599: sipush 389
    //   2602: ldc -109
    //   2604: bastore
    //   2605: dup
    //   2606: sipush 390
    //   2609: ldc -71
    //   2611: bastore
    //   2612: dup
    //   2613: sipush 391
    //   2616: ldc -83
    //   2618: bastore
    //   2619: dup
    //   2620: sipush 392
    //   2623: ldc 62
    //   2625: bastore
    //   2626: dup
    //   2627: sipush 393
    //   2630: ldc -127
    //   2632: bastore
    //   2633: dup
    //   2634: sipush 394
    //   2637: ldc -81
    //   2639: bastore
    //   2640: dup
    //   2641: sipush 395
    //   2644: ldc -70
    //   2646: bastore
    //   2647: dup
    //   2648: sipush 396
    //   2651: ldc -69
    //   2653: bastore
    //   2654: dup
    //   2655: sipush 397
    //   2658: ldc -68
    //   2660: bastore
    //   2661: dup
    //   2662: sipush 398
    //   2665: ldc -112
    //   2667: bastore
    //   2668: dup
    //   2669: sipush 399
    //   2672: ldc -67
    //   2674: bastore
    //   2675: dup
    //   2676: sipush 400
    //   2679: ldc -100
    //   2681: bastore
    //   2682: dup
    //   2683: sipush 401
    //   2686: ldc -66
    //   2688: bastore
    //   2689: dup
    //   2690: sipush 402
    //   2693: ldc 63
    //   2695: bastore
    //   2696: dup
    //   2697: sipush 403
    //   2700: ldc 115
    //   2702: bastore
    //   2703: dup
    //   2704: sipush 404
    //   2707: ldc -65
    //   2709: bastore
    //   2710: dup
    //   2711: sipush 405
    //   2714: ldc -64
    //   2716: bastore
    //   2717: dup
    //   2718: sipush 406
    //   2721: ldc -123
    //   2723: bastore
    //   2724: dup
    //   2725: sipush 407
    //   2728: ldc 70
    //   2730: bastore
    //   2731: dup
    //   2732: sipush 408
    //   2735: ldc -63
    //   2737: bastore
    //   2738: dup
    //   2739: sipush 409
    //   2742: ldc -62
    //   2744: bastore
    //   2745: dup
    //   2746: sipush 410
    //   2749: ldc -61
    //   2751: bastore
    //   2752: dup
    //   2753: sipush 411
    //   2756: ldc 77
    //   2758: bastore
    //   2759: dup
    //   2760: sipush 412
    //   2763: ldc -91
    //   2765: bastore
    //   2766: dup
    //   2767: sipush 413
    //   2770: ldc -100
    //   2772: bastore
    //   2773: dup
    //   2774: sipush 414
    //   2777: ldc 90
    //   2779: bastore
    //   2780: dup
    //   2781: sipush 415
    //   2784: ldc -60
    //   2786: bastore
    //   2787: dup
    //   2788: sipush 416
    //   2791: ldc -59
    //   2793: bastore
    //   2794: dup
    //   2795: sipush 417
    //   2798: ldc -70
    //   2800: bastore
    //   2801: dup
    //   2802: sipush 418
    //   2805: ldc 115
    //   2807: bastore
    //   2808: dup
    //   2809: sipush 419
    //   2812: ldc 84
    //   2814: bastore
    //   2815: dup
    //   2816: sipush 420
    //   2819: ldc -58
    //   2821: bastore
    //   2822: dup
    //   2823: sipush 421
    //   2826: ldc -112
    //   2828: bastore
    //   2829: dup
    //   2830: sipush 422
    //   2833: ldc -87
    //   2835: bastore
    //   2836: dup
    //   2837: sipush 423
    //   2840: ldc -57
    //   2842: bastore
    //   2843: dup
    //   2844: sipush 424
    //   2847: ldc -56
    //   2849: bastore
    //   2850: dup
    //   2851: sipush 425
    //   2854: ldc -109
    //   2856: bastore
    //   2857: dup
    //   2858: sipush 426
    //   2861: ldc -55
    //   2863: bastore
    //   2864: dup
    //   2865: sipush 427
    //   2868: ldc -54
    //   2870: bastore
    //   2871: dup
    //   2872: sipush 428
    //   2875: ldc -68
    //   2877: bastore
    //   2878: dup
    //   2879: sipush 429
    //   2882: ldc -53
    //   2884: bastore
    //   2885: dup
    //   2886: sipush 430
    //   2889: ldc -71
    //   2891: bastore
    //   2892: dup
    //   2893: sipush 431
    //   2896: ldc -52
    //   2898: bastore
    //   2899: dup
    //   2900: sipush 432
    //   2903: ldc -121
    //   2905: bastore
    //   2906: dup
    //   2907: sipush 433
    //   2910: ldc -77
    //   2912: bastore
    //   2913: dup
    //   2914: sipush 434
    //   2917: ldc -114
    //   2919: bastore
    //   2920: dup
    //   2921: sipush 435
    //   2924: ldc -51
    //   2926: bastore
    //   2927: dup
    //   2928: sipush 436
    //   2931: ldc -50
    //   2933: bastore
    //   2934: dup
    //   2935: sipush 437
    //   2938: ldc 69
    //   2940: bastore
    //   2941: dup
    //   2942: sipush 438
    //   2945: ldc -103
    //   2947: bastore
    //   2948: dup
    //   2949: sipush 439
    //   2952: ldc 92
    //   2954: bastore
    //   2955: dup
    //   2956: sipush 440
    //   2959: ldc 64
    //   2961: bastore
    //   2962: dup
    //   2963: sipush 441
    //   2966: ldc 68
    //   2968: bastore
    //   2969: dup
    //   2970: sipush 442
    //   2973: ldc 69
    //   2975: bastore
    //   2976: dup
    //   2977: sipush 443
    //   2980: ldc 71
    //   2982: bastore
    //   2983: dup
    //   2984: sipush 444
    //   2987: ldc 69
    //   2989: bastore
    //   2990: dup
    //   2991: sipush 445
    //   2994: ldc -49
    //   2996: bastore
    //   2997: dup
    //   2998: sipush 446
    //   3001: ldc -81
    //   3003: bastore
    //   3004: dup
    //   3005: sipush 447
    //   3008: ldc 62
    //   3010: bastore
    //   3011: dup
    //   3012: sipush 448
    //   3015: ldc 94
    //   3017: bastore
    //   3018: dup
    //   3019: sipush 449
    //   3022: ldc 62
    //   3024: bastore
    //   3025: dup
    //   3026: sipush 450
    //   3029: ldc 117
    //   3031: bastore
    //   3032: dup
    //   3033: sipush 451
    //   3036: ldc 81
    //   3038: bastore
    //   3039: dup
    //   3040: sipush 452
    //   3043: ldc 68
    //   3045: bastore
    //   3046: dup
    //   3047: sipush 453
    //   3050: ldc 90
    //   3052: bastore
    //   3053: dup
    //   3054: sipush 454
    //   3057: ldc 117
    //   3059: bastore
    //   3060: dup
    //   3061: sipush 455
    //   3064: ldc 107
    //   3066: bastore
    //   3067: dup
    //   3068: sipush 456
    //   3071: ldc 91
    //   3073: bastore
    //   3074: dup
    //   3075: sipush 457
    //   3078: ldc 118
    //   3080: bastore
    //   3081: dup
    //   3082: sipush 458
    //   3085: ldc 91
    //   3087: bastore
    //   3088: dup
    //   3089: sipush 459
    //   3092: ldc -48
    //   3094: bastore
    //   3095: dup
    //   3096: sipush 460
    //   3099: ldc -93
    //   3101: bastore
    //   3102: dup
    //   3103: sipush 461
    //   3106: ldc -109
    //   3108: bastore
    //   3109: dup
    //   3110: sipush 462
    //   3113: ldc 62
    //   3115: bastore
    //   3116: dup
    //   3117: sipush 463
    //   3120: ldc -47
    //   3122: bastore
    //   3123: dup
    //   3124: sipush 464
    //   3127: ldc -46
    //   3129: bastore
    //   3130: dup
    //   3131: sipush 465
    //   3134: ldc -45
    //   3136: bastore
    //   3137: dup
    //   3138: sipush 466
    //   3141: ldc -44
    //   3143: bastore
    //   3144: dup
    //   3145: sipush 467
    //   3148: ldc 90
    //   3150: bastore
    //   3151: dup
    //   3152: sipush 468
    //   3155: ldc 118
    //   3157: bastore
    //   3158: dup
    //   3159: sipush 469
    //   3162: ldc -118
    //   3164: bastore
    //   3165: dup
    //   3166: sipush 470
    //   3169: ldc -63
    //   3171: bastore
    //   3172: dup
    //   3173: sipush 471
    //   3176: ldc -43
    //   3178: bastore
    //   3179: dup
    //   3180: sipush 472
    //   3183: ldc -42
    //   3185: bastore
    //   3186: dup
    //   3187: sipush 473
    //   3190: ldc -60
    //   3192: bastore
    //   3193: dup
    //   3194: sipush 474
    //   3197: ldc -41
    //   3199: bastore
    //   3200: dup
    //   3201: sipush 475
    //   3204: ldc 107
    //   3206: bastore
    //   3207: dup
    //   3208: sipush 476
    //   3211: ldc -40
    //   3213: bastore
    //   3214: dup
    //   3215: sipush 477
    //   3218: ldc 81
    //   3220: bastore
    //   3221: dup
    //   3222: sipush 478
    //   3225: ldc -45
    //   3227: bastore
    //   3228: dup
    //   3229: sipush 479
    //   3232: ldc -41
    //   3234: bastore
    //   3235: dup
    //   3236: sipush 480
    //   3239: ldc 62
    //   3241: bastore
    //   3242: dup
    //   3243: sipush 481
    //   3246: ldc 116
    //   3248: bastore
    //   3249: dup
    //   3250: sipush 482
    //   3253: ldc 81
    //   3255: bastore
    //   3256: dup
    //   3257: sipush 483
    //   3260: ldc 68
    //   3262: bastore
    //   3263: dup
    //   3264: sipush 484
    //   3267: ldc 90
    //   3269: bastore
    //   3270: dup
    //   3271: sipush 485
    //   3274: ldc 117
    //   3276: bastore
    //   3277: dup
    //   3278: sipush 486
    //   3281: ldc -39
    //   3283: bastore
    //   3284: dup
    //   3285: sipush 487
    //   3288: ldc 91
    //   3290: bastore
    //   3291: dup
    //   3292: sipush 488
    //   3295: ldc -38
    //   3297: bastore
    //   3298: dup
    //   3299: sipush 489
    //   3302: ldc 62
    //   3304: bastore
    //   3305: dup
    //   3306: sipush 490
    //   3309: ldc 118
    //   3311: bastore
    //   3312: dup
    //   3313: sipush 491
    //   3316: ldc -117
    //   3318: bastore
    //   3319: dup
    //   3320: sipush 492
    //   3323: ldc -48
    //   3325: bastore
    //   3326: dup
    //   3327: sipush 493
    //   3330: ldc -93
    //   3332: bastore
    //   3333: dup
    //   3334: sipush 494
    //   3337: ldc -109
    //   3339: bastore
    //   3340: dup
    //   3341: sipush 495
    //   3344: ldc 62
    //   3346: bastore
    //   3347: dup
    //   3348: sipush 496
    //   3351: ldc -47
    //   3353: bastore
    //   3354: dup
    //   3355: sipush 497
    //   3358: ldc -46
    //   3360: bastore
    //   3361: dup
    //   3362: sipush 498
    //   3365: ldc -45
    //   3367: bastore
    //   3368: dup
    //   3369: sipush 499
    //   3372: ldc -44
    //   3374: bastore
    //   3375: dup
    //   3376: sipush 500
    //   3379: ldc 90
    //   3381: bastore
    //   3382: dup
    //   3383: sipush 501
    //   3386: ldc 118
    //   3388: bastore
    //   3389: dup
    //   3390: sipush 502
    //   3393: ldc -118
    //   3395: bastore
    //   3396: dup
    //   3397: sipush 503
    //   3400: ldc -63
    //   3402: bastore
    //   3403: dup
    //   3404: sipush 504
    //   3407: ldc -43
    //   3409: bastore
    //   3410: dup
    //   3411: sipush 505
    //   3414: ldc -42
    //   3416: bastore
    //   3417: dup
    //   3418: sipush 506
    //   3421: ldc -60
    //   3423: bastore
    //   3424: dup
    //   3425: sipush 507
    //   3428: ldc -41
    //   3430: bastore
    //   3431: dup
    //   3432: sipush 508
    //   3435: ldc 107
    //   3437: bastore
    //   3438: dup
    //   3439: sipush 509
    //   3442: ldc -40
    //   3444: bastore
    //   3445: dup
    //   3446: sipush 510
    //   3449: ldc 81
    //   3451: bastore
    //   3452: dup
    //   3453: sipush 511
    //   3456: ldc -45
    //   3458: bastore
    //   3459: dup
    //   3460: sipush 512
    //   3463: ldc -41
    //   3465: bastore
    //   3466: dup
    //   3467: sipush 513
    //   3470: ldc 62
    //   3472: bastore
    //   3473: dup
    //   3474: sipush 514
    //   3477: ldc 97
    //   3479: bastore
    //   3480: dup
    //   3481: sipush 515
    //   3484: ldc 81
    //   3486: bastore
    //   3487: dup
    //   3488: sipush 516
    //   3491: ldc 68
    //   3493: bastore
    //   3494: dup
    //   3495: sipush 517
    //   3498: ldc 90
    //   3500: bastore
    //   3501: dup
    //   3502: sipush 518
    //   3505: ldc 117
    //   3507: bastore
    //   3508: dup
    //   3509: sipush 519
    //   3512: ldc 92
    //   3514: bastore
    //   3515: dup
    //   3516: sipush 520
    //   3519: ldc 91
    //   3521: bastore
    //   3522: dup
    //   3523: sipush 521
    //   3526: ldc 86
    //   3528: bastore
    //   3529: dup
    //   3530: sipush 522
    //   3533: ldc 62
    //   3535: bastore
    //   3536: dup
    //   3537: sipush 523
    //   3540: ldc 68
    //   3542: bastore
    //   3543: dup
    //   3544: sipush 524
    //   3547: ldc 69
    //   3549: bastore
    //   3550: dup
    //   3551: sipush 525
    //   3554: ldc 69
    //   3556: bastore
    //   3557: dup
    //   3558: sipush 526
    //   3561: ldc -37
    //   3563: bastore
    //   3564: dup
    //   3565: sipush 527
    //   3568: ldc 62
    //   3570: bastore
    //   3571: dup
    //   3572: sipush 528
    //   3575: ldc 80
    //   3577: bastore
    //   3578: dup
    //   3579: sipush 529
    //   3582: ldc 81
    //   3584: bastore
    //   3585: dup
    //   3586: sipush 530
    //   3589: ldc 70
    //   3591: bastore
    //   3592: dup
    //   3593: sipush 531
    //   3596: ldc 82
    //   3598: bastore
    //   3599: dup
    //   3600: sipush 532
    //   3603: ldc 83
    //   3605: bastore
    //   3606: dup
    //   3607: sipush 533
    //   3610: ldc 84
    //   3612: bastore
    //   3613: dup
    //   3614: sipush 534
    //   3617: ldc 83
    //   3619: bastore
    //   3620: dup
    //   3621: sipush 535
    //   3624: ldc 85
    //   3626: bastore
    //   3627: dup
    //   3628: sipush 536
    //   3631: ldc 80
    //   3633: bastore
    //   3634: dup
    //   3635: sipush 537
    //   3638: ldc 69
    //   3640: bastore
    //   3641: dup
    //   3642: sipush 538
    //   3645: ldc 69
    //   3647: bastore
    //   3648: dup
    //   3649: sipush 539
    //   3652: ldc 86
    //   3654: bastore
    //   3655: dup
    //   3656: sipush 540
    //   3659: ldc 86
    //   3661: bastore
    //   3662: dup
    //   3663: sipush 541
    //   3666: ldc 71
    //   3668: bastore
    //   3669: dup
    //   3670: sipush 542
    //   3673: ldc 68
    //   3675: bastore
    //   3676: dup
    //   3677: sipush 543
    //   3680: ldc -123
    //   3682: bastore
    //   3683: dup
    //   3684: sipush 544
    //   3687: ldc -123
    //   3689: bastore
    //   3690: dup
    //   3691: sipush 545
    //   3694: ldc 71
    //   3696: bastore
    //   3697: dup
    //   3698: sipush 546
    //   3701: ldc -75
    //   3703: bastore
    //   3704: dup
    //   3705: sipush 547
    //   3708: ldc -36
    //   3710: bastore
    //   3711: dup
    //   3712: sipush 548
    //   3715: ldc -127
    //   3717: bastore
    //   3718: dup
    //   3719: sipush 549
    //   3722: ldc -108
    //   3724: bastore
    //   3725: dup
    //   3726: sipush 550
    //   3729: ldc -82
    //   3731: bastore
    //   3732: dup
    //   3733: sipush 551
    //   3736: ldc -117
    //   3738: bastore
    //   3739: dup
    //   3740: sipush 552
    //   3743: ldc 73
    //   3745: bastore
    //   3746: dup
    //   3747: sipush 553
    //   3750: ldc -35
    //   3752: bastore
    //   3753: dup
    //   3754: sipush 554
    //   3757: ldc -76
    //   3759: bastore
    //   3760: dup
    //   3761: sipush 555
    //   3764: ldc -34
    //   3766: bastore
    //   3767: dup
    //   3768: sipush 556
    //   3771: ldc 68
    //   3773: bastore
    //   3774: dup
    //   3775: sipush 557
    //   3778: ldc -51
    //   3780: bastore
    //   3781: dup
    //   3782: sipush 558
    //   3785: ldc -61
    //   3787: bastore
    //   3788: dup
    //   3789: sipush 559
    //   3792: ldc 121
    //   3794: bastore
    //   3795: dup
    //   3796: sipush 560
    //   3799: ldc -33
    //   3801: bastore
    //   3802: dup
    //   3803: sipush 561
    //   3806: ldc -116
    //   3808: bastore
    //   3809: dup
    //   3810: sipush 562
    //   3813: ldc -32
    //   3815: bastore
    //   3816: dup
    //   3817: sipush 563
    //   3820: ldc 63
    //   3822: bastore
    //   3823: dup
    //   3824: sipush 564
    //   3827: ldc 96
    //   3829: bastore
    //   3830: dup
    //   3831: sipush 565
    //   3834: ldc 119
    //   3836: bastore
    //   3837: dup
    //   3838: sipush 566
    //   3841: ldc -62
    //   3843: bastore
    //   3844: dup
    //   3845: sipush 567
    //   3848: ldc -54
    //   3850: bastore
    //   3851: dup
    //   3852: sipush 568
    //   3855: ldc -31
    //   3857: bastore
    //   3858: dup
    //   3859: sipush 569
    //   3862: ldc -116
    //   3864: bastore
    //   3865: dup
    //   3866: sipush 570
    //   3869: ldc 83
    //   3871: bastore
    //   3872: dup
    //   3873: sipush 571
    //   3876: ldc -112
    //   3878: bastore
    //   3879: dup
    //   3880: sipush 572
    //   3883: ldc 92
    //   3885: bastore
    //   3886: dup
    //   3887: sipush 573
    //   3890: ldc -30
    //   3892: bastore
    //   3893: dup
    //   3894: sipush 574
    //   3897: ldc -33
    //   3899: bastore
    //   3900: dup
    //   3901: sipush 575
    //   3904: ldc -125
    //   3906: bastore
    //   3907: dup
    //   3908: sipush 576
    //   3911: ldc 90
    //   3913: bastore
    //   3914: dup
    //   3915: sipush 577
    //   3918: ldc -29
    //   3920: bastore
    //   3921: dup
    //   3922: sipush 578
    //   3925: ldc -28
    //   3927: bastore
    //   3928: dup
    //   3929: sipush 579
    //   3932: ldc -83
    //   3934: bastore
    //   3935: dup
    //   3936: sipush 580
    //   3939: ldc -60
    //   3941: bastore
    //   3942: dup
    //   3943: sipush 581
    //   3946: ldc 109
    //   3948: bastore
    //   3949: dup
    //   3950: sipush 582
    //   3953: ldc -27
    //   3955: bastore
    //   3956: dup
    //   3957: sipush 583
    //   3960: ldc -75
    //   3962: bastore
    //   3963: dup
    //   3964: sipush 584
    //   3967: ldc -53
    //   3969: bastore
    //   3970: dup
    //   3971: sipush 585
    //   3974: ldc -35
    //   3976: bastore
    //   3977: dup
    //   3978: sipush 586
    //   3981: ldc -26
    //   3983: bastore
    //   3984: dup
    //   3985: sipush 587
    //   3988: ldc 93
    //   3990: bastore
    //   3991: dup
    //   3992: sipush 588
    //   3995: ldc -26
    //   3997: bastore
    //   3998: dup
    //   3999: sipush 589
    //   4002: ldc -25
    //   4004: bastore
    //   4005: dup
    //   4006: sipush 590
    //   4009: ldc 104
    //   4011: bastore
    //   4012: dup
    //   4013: sipush 591
    //   4016: ldc -24
    //   4018: bastore
    //   4019: dup
    //   4020: sipush 592
    //   4023: ldc -23
    //   4025: bastore
    //   4026: dup
    //   4027: sipush 593
    //   4030: ldc -94
    //   4032: bastore
    //   4033: dup
    //   4034: sipush 594
    //   4037: ldc -72
    //   4039: bastore
    //   4040: dup
    //   4041: sipush 595
    //   4044: ldc 80
    //   4046: bastore
    //   4047: dup
    //   4048: sipush 596
    //   4051: ldc -22
    //   4053: bastore
    //   4054: dup
    //   4055: sipush 597
    //   4058: ldc 120
    //   4060: bastore
    //   4061: dup
    //   4062: sipush 598
    //   4065: ldc -43
    //   4067: bastore
    //   4068: dup
    //   4069: sipush 599
    //   4072: ldc -21
    //   4074: bastore
    //   4075: dup
    //   4076: sipush 600
    //   4079: ldc 68
    //   4081: bastore
    //   4082: dup
    //   4083: sipush 601
    //   4086: ldc -73
    //   4088: bastore
    //   4089: dup
    //   4090: sipush 602
    //   4093: ldc -108
    //   4095: bastore
    //   4096: dup
    //   4097: sipush 603
    //   4100: ldc -121
    //   4102: bastore
    //   4103: dup
    //   4104: sipush 604
    //   4107: ldc -20
    //   4109: bastore
    //   4110: dup
    //   4111: sipush 605
    //   4114: ldc -19
    //   4116: bastore
    //   4117: dup
    //   4118: sipush 606
    //   4121: ldc 75
    //   4123: bastore
    //   4124: dup
    //   4125: sipush 607
    //   4128: ldc -81
    //   4130: bastore
    //   4131: dup
    //   4132: sipush 608
    //   4135: ldc -18
    //   4137: bastore
    //   4138: dup
    //   4139: sipush 609
    //   4142: ldc -17
    //   4144: bastore
    //   4145: dup
    //   4146: sipush 610
    //   4149: ldc -16
    //   4151: bastore
    //   4152: dup
    //   4153: sipush 611
    //   4156: ldc 81
    //   4158: bastore
    //   4159: dup
    //   4160: sipush 612
    //   4163: ldc -15
    //   4165: bastore
    //   4166: dup
    //   4167: sipush 613
    //   4170: ldc -103
    //   4172: bastore
    //   4173: dup
    //   4174: sipush 614
    //   4177: ldc -14
    //   4179: bastore
    //   4180: dup
    //   4181: sipush 615
    //   4184: ldc -37
    //   4186: bastore
    //   4187: dup
    //   4188: sipush 616
    //   4191: ldc 90
    //   4193: bastore
    //   4194: dup
    //   4195: sipush 617
    //   4198: ldc -82
    //   4200: bastore
    //   4201: dup
    //   4202: sipush 618
    //   4205: ldc -16
    //   4207: bastore
    //   4208: dup
    //   4209: sipush 619
    //   4212: ldc -121
    //   4214: bastore
    //   4215: dup
    //   4216: sipush 620
    //   4219: ldc 74
    //   4221: bastore
    //   4222: dup
    //   4223: sipush 621
    //   4226: ldc 80
    //   4228: bastore
    //   4229: dup
    //   4230: sipush 622
    //   4233: ldc -13
    //   4235: bastore
    //   4236: dup
    //   4237: sipush 623
    //   4240: ldc -75
    //   4242: bastore
    //   4243: dup
    //   4244: sipush 624
    //   4247: ldc 71
    //   4249: bastore
    //   4250: dup
    //   4251: sipush 625
    //   4254: ldc 65
    //   4256: bastore
    //   4257: dup
    //   4258: sipush 626
    //   4261: ldc -76
    //   4263: bastore
    //   4264: dup
    //   4265: sipush 627
    //   4268: ldc -100
    //   4270: bastore
    //   4271: dup
    //   4272: sipush 628
    //   4275: ldc -12
    //   4277: bastore
    //   4278: dup
    //   4279: sipush 629
    //   4282: ldc -11
    //   4284: bastore
    //   4285: dup
    //   4286: sipush 630
    //   4289: ldc -10
    //   4291: bastore
    //   4292: dup
    //   4293: sipush 631
    //   4296: ldc -60
    //   4298: bastore
    //   4299: dup
    //   4300: sipush 632
    //   4303: ldc -71
    //   4305: bastore
    //   4306: dup
    //   4307: sipush 633
    //   4310: ldc -50
    //   4312: bastore
    //   4313: dup
    //   4314: sipush 634
    //   4317: ldc 90
    //   4319: bastore
    //   4320: dup
    //   4321: sipush 635
    //   4324: ldc -9
    //   4326: bastore
    //   4327: dup
    //   4328: sipush 636
    //   4331: ldc -118
    //   4333: bastore
    //   4334: dup
    //   4335: sipush 637
    //   4338: ldc -77
    //   4340: bastore
    //   4341: dup
    //   4342: sipush 638
    //   4345: ldc 109
    //   4347: bastore
    //   4348: dup
    //   4349: sipush 639
    //   4352: ldc -69
    //   4354: bastore
    //   4355: dup
    //   4356: sipush 640
    //   4359: ldc -118
    //   4361: bastore
    //   4362: dup
    //   4363: sipush 641
    //   4366: ldc -8
    //   4368: bastore
    //   4369: dup
    //   4370: sipush 642
    //   4373: ldc -119
    //   4375: bastore
    //   4376: dup
    //   4377: sipush 643
    //   4380: ldc 65
    //   4382: bastore
    //   4383: dup
    //   4384: sipush 644
    //   4387: ldc 112
    //   4389: bastore
    //   4390: dup
    //   4391: sipush 645
    //   4394: ldc -7
    //   4396: bastore
    //   4397: dup
    //   4398: sipush 646
    //   4401: ldc -41
    //   4403: bastore
    //   4404: dup
    //   4405: sipush 647
    //   4408: ldc -39
    //   4410: bastore
    //   4411: dup
    //   4412: sipush 648
    //   4415: ldc -120
    //   4417: bastore
    //   4418: dup
    //   4419: sipush 649
    //   4422: ldc -118
    //   4424: bastore
    //   4425: dup
    //   4426: sipush 650
    //   4429: ldc -6
    //   4431: bastore
    //   4432: dup
    //   4433: sipush 651
    //   4436: ldc 83
    //   4438: bastore
    //   4439: dup
    //   4440: sipush 652
    //   4443: ldc -5
    //   4445: bastore
    //   4446: dup
    //   4447: sipush 653
    //   4450: ldc -109
    //   4452: bastore
    //   4453: dup
    //   4454: sipush 654
    //   4457: ldc -39
    //   4459: bastore
    //   4460: dup
    //   4461: sipush 655
    //   4464: ldc -79
    //   4466: bastore
    //   4467: dup
    //   4468: sipush 656
    //   4471: ldc -4
    //   4473: bastore
    //   4474: dup
    //   4475: sipush 657
    //   4478: ldc 125
    //   4480: bastore
    //   4481: dup
    //   4482: sipush 658
    //   4485: ldc -72
    //   4487: bastore
    //   4488: dup
    //   4489: sipush 659
    //   4492: ldc -3
    //   4494: bastore
    //   4495: dup
    //   4496: sipush 660
    //   4499: ldc 108
    //   4501: bastore
    //   4502: dup
    //   4503: sipush 661
    //   4506: ldc -2
    //   4508: bastore
    //   4509: dup
    //   4510: sipush 662
    //   4513: ldc 127
    //   4515: bastore
    //   4516: dup
    //   4517: sipush 663
    //   4520: ldc 121
    //   4522: bastore
    //   4523: dup
    //   4524: sipush 664
    //   4527: ldc 120
    //   4529: bastore
    //   4530: dup
    //   4531: sipush 665
    //   4534: ldc -106
    //   4536: bastore
    //   4537: dup
    //   4538: sipush 666
    //   4541: ldc -83
    //   4543: bastore
    //   4544: dup
    //   4545: sipush 667
    //   4548: ldc -83
    //   4550: bastore
    //   4551: dup
    //   4552: sipush 668
    //   4555: ldc -72
    //   4557: bastore
    //   4558: dup
    //   4559: sipush 669
    //   4562: ldc 115
    //   4564: bastore
    //   4565: dup
    //   4566: sipush 670
    //   4569: ldc -1
    //   4571: bastore
    //   4572: dup
    //   4573: sipush 671
    //   4576: ldc_w 256
    //   4579: bastore
    //   4580: dup
    //   4581: sipush 672
    //   4584: ldc -92
    //   4586: bastore
    //   4587: dup
    //   4588: sipush 673
    //   4591: ldc -60
    //   4593: bastore
    //   4594: invokespecial 259	java/io/ByteArrayInputStream:<init>	([B)V
    //   4597: astore_3
    //   4598: aload_3
    //   4599: astore_1
    //   4600: ldc_w 261
    //   4603: invokestatic 267	java/security/cert/CertificateFactory:getInstance	(Ljava/lang/String;)Ljava/security/cert/CertificateFactory;
    //   4606: astore_2
    //   4607: aload_3
    //   4608: astore_1
    //   4609: ldc_w 269
    //   4612: invokestatic 274	java/security/KeyFactory:getInstance	(Ljava/lang/String;)Ljava/security/KeyFactory;
    //   4615: astore_0
    //   4616: aload_3
    //   4617: astore_1
    //   4618: aload_2
    //   4619: aload_3
    //   4620: invokevirtual 278	java/security/cert/CertificateFactory:generateCertificate	(Ljava/io/InputStream;)Ljava/security/cert/Certificate;
    //   4623: astore_2
    //   4624: aload_2
    //   4625: astore_1
    //   4626: aload_0
    //   4627: astore 4
    //   4629: aload_3
    //   4630: ifnull +12 -> 4642
    //   4633: aload_3
    //   4634: invokevirtual 283	java/io/InputStream:close	()V
    //   4637: aload_0
    //   4638: astore 4
    //   4640: aload_2
    //   4641: astore_1
    //   4642: aload_1
    //   4643: ifnull +8 -> 4651
    //   4646: aload 4
    //   4648: ifnonnull +45 -> 4693
    //   4651: aconst_null
    //   4652: areturn
    //   4653: astore_2
    //   4654: aconst_null
    //   4655: astore_0
    //   4656: aconst_null
    //   4657: astore_3
    //   4658: aload_3
    //   4659: astore_1
    //   4660: aload_2
    //   4661: invokevirtual 49	java/lang/Throwable:printStackTrace	()V
    //   4664: aload_3
    //   4665: ifnull +64 -> 4729
    //   4668: aload_3
    //   4669: invokevirtual 283	java/io/InputStream:close	()V
    //   4672: aconst_null
    //   4673: astore_1
    //   4674: aload_0
    //   4675: astore 4
    //   4677: goto -35 -> 4642
    //   4680: astore_0
    //   4681: aconst_null
    //   4682: astore_1
    //   4683: aload_1
    //   4684: ifnull +7 -> 4691
    //   4687: aload_1
    //   4688: invokevirtual 283	java/io/InputStream:close	()V
    //   4691: aload_0
    //   4692: athrow
    //   4693: aload 4
    //   4695: new 285	java/security/spec/X509EncodedKeySpec
    //   4698: dup
    //   4699: aload_1
    //   4700: invokevirtual 291	java/security/cert/Certificate:getPublicKey	()Ljava/security/PublicKey;
    //   4703: invokeinterface 297 1 0
    //   4708: invokespecial 298	java/security/spec/X509EncodedKeySpec:<init>	([B)V
    //   4711: invokevirtual 302	java/security/KeyFactory:generatePublic	(Ljava/security/spec/KeySpec;)Ljava/security/PublicKey;
    //   4714: areturn
    //   4715: astore_0
    //   4716: goto -33 -> 4683
    //   4719: astore_2
    //   4720: aconst_null
    //   4721: astore_0
    //   4722: goto -64 -> 4658
    //   4725: astore_2
    //   4726: goto -68 -> 4658
    //   4729: aconst_null
    //   4730: astore_1
    //   4731: aload_0
    //   4732: astore 4
    //   4734: goto -92 -> 4642
    // Local variable table:
    //   start	length	slot	name	signature
    //   0	4737	0	paramContext	android.content.Context
    //   4599	132	1	localObject1	Object
    //   4606	35	2	localObject2	Object
    //   4653	8	2	localThrowable1	Throwable
    //   4719	1	2	localThrowable2	Throwable
    //   4725	1	2	localThrowable3	Throwable
    //   4597	72	3	localByteArrayInputStream	java.io.ByteArrayInputStream
    //   4627	106	4	localContext	android.content.Context
    // Exception table:
    //   from	to	target	type
    //   0	4598	4653	java/lang/Throwable
    //   0	4598	4680	finally
    //   4600	4607	4715	finally
    //   4609	4616	4715	finally
    //   4618	4624	4715	finally
    //   4660	4664	4715	finally
    //   4600	4607	4719	java/lang/Throwable
    //   4609	4616	4719	java/lang/Throwable
    //   4618	4624	4725	java/lang/Throwable
  }
  
  public static byte[] a(byte[] paramArrayOfByte)
  {
    try
    {
      paramArrayOfByte = f(paramArrayOfByte);
      return paramArrayOfByte;
    }
    catch (IOException paramArrayOfByte)
    {
      ed.a(paramArrayOfByte, "Utils", "gZip");
      paramArrayOfByte.printStackTrace();
      return new byte[0];
    }
    catch (Throwable paramArrayOfByte)
    {
      for (;;)
      {
        ed.a(paramArrayOfByte, "Utils", "gZip");
        paramArrayOfByte.printStackTrace();
      }
    }
  }
  
  /* Error */
  public static byte[] b(byte[] paramArrayOfByte)
  {
    // Byte code:
    //   0: aconst_null
    //   1: astore 6
    //   3: aconst_null
    //   4: astore 7
    //   6: aload 7
    //   8: astore_2
    //   9: aload_0
    //   10: ifnull +11 -> 21
    //   13: aload_0
    //   14: arraylength
    //   15: ifne +8 -> 23
    //   18: aload 7
    //   20: astore_2
    //   21: aload_2
    //   22: areturn
    //   23: new 314	java/io/ByteArrayOutputStream
    //   26: dup
    //   27: invokespecial 315	java/io/ByteArrayOutputStream:<init>	()V
    //   30: astore_1
    //   31: new 317	java/util/zip/ZipOutputStream
    //   34: dup
    //   35: aload_1
    //   36: invokespecial 320	java/util/zip/ZipOutputStream:<init>	(Ljava/io/OutputStream;)V
    //   39: astore 5
    //   41: aload_1
    //   42: astore_3
    //   43: aload 5
    //   45: astore_2
    //   46: aload 5
    //   48: new 322	java/util/zip/ZipEntry
    //   51: dup
    //   52: ldc_w 324
    //   55: invokespecial 327	java/util/zip/ZipEntry:<init>	(Ljava/lang/String;)V
    //   58: invokevirtual 331	java/util/zip/ZipOutputStream:putNextEntry	(Ljava/util/zip/ZipEntry;)V
    //   61: aload_1
    //   62: astore_3
    //   63: aload 5
    //   65: astore_2
    //   66: aload 5
    //   68: aload_0
    //   69: invokevirtual 334	java/util/zip/ZipOutputStream:write	([B)V
    //   72: aload_1
    //   73: astore_3
    //   74: aload 5
    //   76: astore_2
    //   77: aload 5
    //   79: invokevirtual 337	java/util/zip/ZipOutputStream:closeEntry	()V
    //   82: aload_1
    //   83: astore_3
    //   84: aload 5
    //   86: astore_2
    //   87: aload 5
    //   89: invokevirtual 340	java/util/zip/ZipOutputStream:finish	()V
    //   92: aload_1
    //   93: astore_3
    //   94: aload 5
    //   96: astore_2
    //   97: aload_1
    //   98: invokevirtual 343	java/io/ByteArrayOutputStream:toByteArray	()[B
    //   101: astore_0
    //   102: aload 5
    //   104: ifnull +8 -> 112
    //   107: aload 5
    //   109: invokevirtual 344	java/util/zip/ZipOutputStream:close	()V
    //   112: aload_0
    //   113: astore_2
    //   114: aload_1
    //   115: ifnull -94 -> 21
    //   118: aload_1
    //   119: invokevirtual 345	java/io/ByteArrayOutputStream:close	()V
    //   122: aload_0
    //   123: areturn
    //   124: astore_3
    //   125: invokestatic 348	com/amap/api/mapcore2d/ed:b	()Lcom/amap/api/mapcore2d/ed;
    //   128: astore 4
    //   130: aload_0
    //   131: astore_1
    //   132: aload_3
    //   133: astore_2
    //   134: aload 4
    //   136: ifnull +18 -> 154
    //   139: aload 4
    //   141: aload_3
    //   142: ldc 51
    //   144: ldc_w 350
    //   147: invokevirtual 352	com/amap/api/mapcore2d/ed:b	(Ljava/lang/Throwable;Ljava/lang/String;Ljava/lang/String;)V
    //   150: aload_3
    //   151: astore_2
    //   152: aload_0
    //   153: astore_1
    //   154: aload_2
    //   155: invokevirtual 49	java/lang/Throwable:printStackTrace	()V
    //   158: aload_1
    //   159: areturn
    //   160: astore 4
    //   162: aconst_null
    //   163: astore_1
    //   164: aconst_null
    //   165: astore_0
    //   166: aload_1
    //   167: astore_3
    //   168: aload_0
    //   169: astore_2
    //   170: aload 4
    //   172: invokevirtual 49	java/lang/Throwable:printStackTrace	()V
    //   175: aload_1
    //   176: astore_3
    //   177: aload_0
    //   178: astore_2
    //   179: aload 4
    //   181: ldc 51
    //   183: ldc_w 354
    //   186: invokestatic 58	com/amap/api/mapcore2d/ed:a	(Ljava/lang/Throwable;Ljava/lang/String;Ljava/lang/String;)V
    //   189: aload_0
    //   190: ifnull +7 -> 197
    //   193: aload_0
    //   194: invokevirtual 344	java/util/zip/ZipOutputStream:close	()V
    //   197: aload 7
    //   199: astore_2
    //   200: aload_1
    //   201: ifnull -180 -> 21
    //   204: aload_1
    //   205: invokevirtual 345	java/io/ByteArrayOutputStream:close	()V
    //   208: aconst_null
    //   209: areturn
    //   210: astore_0
    //   211: invokestatic 348	com/amap/api/mapcore2d/ed:b	()Lcom/amap/api/mapcore2d/ed;
    //   214: astore_3
    //   215: aload 6
    //   217: astore_1
    //   218: aload_0
    //   219: astore_2
    //   220: aload_3
    //   221: ifnull -67 -> 154
    //   224: aload_3
    //   225: aload_0
    //   226: ldc 51
    //   228: ldc_w 350
    //   231: invokevirtual 352	com/amap/api/mapcore2d/ed:b	(Ljava/lang/Throwable;Ljava/lang/String;Ljava/lang/String;)V
    //   234: aload 6
    //   236: astore_1
    //   237: aload_0
    //   238: astore_2
    //   239: goto -85 -> 154
    //   242: astore_0
    //   243: aconst_null
    //   244: astore_1
    //   245: aconst_null
    //   246: astore_2
    //   247: aload_2
    //   248: ifnull +7 -> 255
    //   251: aload_2
    //   252: invokevirtual 344	java/util/zip/ZipOutputStream:close	()V
    //   255: aload_1
    //   256: ifnull +7 -> 263
    //   259: aload_1
    //   260: invokevirtual 345	java/io/ByteArrayOutputStream:close	()V
    //   263: aload_0
    //   264: athrow
    //   265: astore_2
    //   266: invokestatic 348	com/amap/api/mapcore2d/ed:b	()Lcom/amap/api/mapcore2d/ed;
    //   269: astore_3
    //   270: aload_3
    //   271: ifnull +13 -> 284
    //   274: aload_3
    //   275: aload_2
    //   276: ldc 51
    //   278: ldc_w 356
    //   281: invokevirtual 352	com/amap/api/mapcore2d/ed:b	(Ljava/lang/Throwable;Ljava/lang/String;Ljava/lang/String;)V
    //   284: aload_2
    //   285: invokevirtual 49	java/lang/Throwable:printStackTrace	()V
    //   288: goto -33 -> 255
    //   291: astore_1
    //   292: invokestatic 348	com/amap/api/mapcore2d/ed:b	()Lcom/amap/api/mapcore2d/ed;
    //   295: astore_2
    //   296: aload_2
    //   297: ifnull +13 -> 310
    //   300: aload_2
    //   301: aload_1
    //   302: ldc 51
    //   304: ldc_w 350
    //   307: invokevirtual 352	com/amap/api/mapcore2d/ed:b	(Ljava/lang/Throwable;Ljava/lang/String;Ljava/lang/String;)V
    //   310: aload_1
    //   311: invokevirtual 49	java/lang/Throwable:printStackTrace	()V
    //   314: goto -51 -> 263
    //   317: astore_0
    //   318: invokestatic 348	com/amap/api/mapcore2d/ed:b	()Lcom/amap/api/mapcore2d/ed;
    //   321: astore_2
    //   322: aload_2
    //   323: ifnull +13 -> 336
    //   326: aload_2
    //   327: aload_0
    //   328: ldc 51
    //   330: ldc_w 356
    //   333: invokevirtual 352	com/amap/api/mapcore2d/ed:b	(Ljava/lang/Throwable;Ljava/lang/String;Ljava/lang/String;)V
    //   336: aload_0
    //   337: invokevirtual 49	java/lang/Throwable:printStackTrace	()V
    //   340: goto -143 -> 197
    //   343: astore_2
    //   344: invokestatic 348	com/amap/api/mapcore2d/ed:b	()Lcom/amap/api/mapcore2d/ed;
    //   347: astore_3
    //   348: aload_3
    //   349: ifnull +13 -> 362
    //   352: aload_3
    //   353: aload_2
    //   354: ldc 51
    //   356: ldc_w 356
    //   359: invokevirtual 352	com/amap/api/mapcore2d/ed:b	(Ljava/lang/Throwable;Ljava/lang/String;Ljava/lang/String;)V
    //   362: aload_2
    //   363: invokevirtual 49	java/lang/Throwable:printStackTrace	()V
    //   366: goto -254 -> 112
    //   369: astore_0
    //   370: aconst_null
    //   371: astore_2
    //   372: goto -125 -> 247
    //   375: astore_0
    //   376: aload_3
    //   377: astore_1
    //   378: goto -131 -> 247
    //   381: astore 4
    //   383: aconst_null
    //   384: astore_0
    //   385: goto -219 -> 166
    //   388: astore 4
    //   390: aload 5
    //   392: astore_0
    //   393: goto -227 -> 166
    // Local variable table:
    //   start	length	slot	name	signature
    //   0	396	0	paramArrayOfByte	byte[]
    //   30	230	1	localObject1	Object
    //   291	20	1	localThrowable1	Throwable
    //   377	1	1	localObject2	Object
    //   8	244	2	localObject3	Object
    //   265	20	2	localThrowable2	Throwable
    //   295	32	2	localed1	ed
    //   343	20	2	localThrowable3	Throwable
    //   371	1	2	localObject4	Object
    //   42	52	3	localObject5	Object
    //   124	27	3	localThrowable4	Throwable
    //   167	210	3	localObject6	Object
    //   128	12	4	localed2	ed
    //   160	20	4	localThrowable5	Throwable
    //   381	1	4	localThrowable6	Throwable
    //   388	1	4	localThrowable7	Throwable
    //   39	352	5	localZipOutputStream	java.util.zip.ZipOutputStream
    //   1	234	6	localObject7	Object
    //   4	194	7	localObject8	Object
    // Exception table:
    //   from	to	target	type
    //   118	122	124	java/lang/Throwable
    //   23	31	160	java/lang/Throwable
    //   204	208	210	java/lang/Throwable
    //   23	31	242	finally
    //   251	255	265	java/lang/Throwable
    //   259	263	291	java/lang/Throwable
    //   193	197	317	java/lang/Throwable
    //   107	112	343	java/lang/Throwable
    //   31	41	369	finally
    //   46	61	375	finally
    //   66	72	375	finally
    //   77	82	375	finally
    //   87	92	375	finally
    //   97	102	375	finally
    //   170	175	375	finally
    //   179	189	375	finally
    //   31	41	381	java/lang/Throwable
    //   46	61	388	java/lang/Throwable
    //   66	72	388	java/lang/Throwable
    //   77	82	388	java/lang/Throwable
    //   87	92	388	java/lang/Throwable
    //   97	102	388	java/lang/Throwable
  }
  
  static String c(byte[] paramArrayOfByte)
  {
    try
    {
      paramArrayOfByte = e(paramArrayOfByte);
      return paramArrayOfByte;
    }
    catch (Throwable paramArrayOfByte)
    {
      ed.a(paramArrayOfByte, "Utils", "HexString");
      paramArrayOfByte.printStackTrace();
    }
    return null;
  }
  
  static String d(byte[] paramArrayOfByte)
  {
    try
    {
      paramArrayOfByte = e(paramArrayOfByte);
      return paramArrayOfByte;
    }
    catch (Throwable paramArrayOfByte)
    {
      paramArrayOfByte.printStackTrace();
    }
    return null;
  }
  
  private static String e(byte[] paramArrayOfByte)
  {
    StringBuilder localStringBuilder = new StringBuilder();
    if (paramArrayOfByte == null) {
      return null;
    }
    int i = 0;
    while (i < paramArrayOfByte.length)
    {
      String str2 = Integer.toHexString(paramArrayOfByte[i] & 0xFF);
      String str1 = str2;
      if (str2.length() == 1) {
        str1 = '0' + str2;
      }
      localStringBuilder.append(str1);
      i += 1;
    }
    return localStringBuilder.toString();
  }
  
  /* Error */
  private static byte[] f(byte[] paramArrayOfByte)
  {
    // Byte code:
    //   0: aconst_null
    //   1: astore_2
    //   2: aload_0
    //   3: ifnonnull +5 -> 8
    //   6: aload_2
    //   7: areturn
    //   8: new 314	java/io/ByteArrayOutputStream
    //   11: dup
    //   12: invokespecial 315	java/io/ByteArrayOutputStream:<init>	()V
    //   15: astore_1
    //   16: new 382	java/util/zip/GZIPOutputStream
    //   19: dup
    //   20: aload_1
    //   21: invokespecial 383	java/util/zip/GZIPOutputStream:<init>	(Ljava/io/OutputStream;)V
    //   24: astore 4
    //   26: aload 4
    //   28: astore_2
    //   29: aload_1
    //   30: astore_3
    //   31: aload 4
    //   33: aload_0
    //   34: invokevirtual 384	java/util/zip/GZIPOutputStream:write	([B)V
    //   37: aload 4
    //   39: astore_2
    //   40: aload_1
    //   41: astore_3
    //   42: aload 4
    //   44: invokevirtual 385	java/util/zip/GZIPOutputStream:finish	()V
    //   47: aload 4
    //   49: astore_2
    //   50: aload_1
    //   51: astore_3
    //   52: aload_1
    //   53: invokevirtual 343	java/io/ByteArrayOutputStream:toByteArray	()[B
    //   56: astore_0
    //   57: aload 4
    //   59: ifnull +8 -> 67
    //   62: aload 4
    //   64: invokevirtual 386	java/util/zip/GZIPOutputStream:close	()V
    //   67: aload_0
    //   68: astore_2
    //   69: aload_1
    //   70: ifnull -64 -> 6
    //   73: aload_1
    //   74: invokevirtual 345	java/io/ByteArrayOutputStream:close	()V
    //   77: aload_0
    //   78: areturn
    //   79: astore_0
    //   80: aload_0
    //   81: athrow
    //   82: astore_0
    //   83: aconst_null
    //   84: astore_1
    //   85: aconst_null
    //   86: astore_2
    //   87: aload_1
    //   88: astore_3
    //   89: aload_0
    //   90: athrow
    //   91: astore_0
    //   92: aload_3
    //   93: astore_1
    //   94: aload_2
    //   95: ifnull +7 -> 102
    //   98: aload_2
    //   99: invokevirtual 386	java/util/zip/GZIPOutputStream:close	()V
    //   102: aload_1
    //   103: ifnull +7 -> 110
    //   106: aload_1
    //   107: invokevirtual 345	java/io/ByteArrayOutputStream:close	()V
    //   110: aload_0
    //   111: athrow
    //   112: astore_0
    //   113: aconst_null
    //   114: astore_1
    //   115: aconst_null
    //   116: astore_2
    //   117: aload_1
    //   118: astore_3
    //   119: aload_0
    //   120: athrow
    //   121: astore_0
    //   122: aload_0
    //   123: athrow
    //   124: astore_0
    //   125: aload_0
    //   126: athrow
    //   127: astore_0
    //   128: aload_0
    //   129: athrow
    //   130: astore_0
    //   131: aconst_null
    //   132: astore_1
    //   133: aconst_null
    //   134: astore_2
    //   135: goto -41 -> 94
    //   138: astore_0
    //   139: aconst_null
    //   140: astore_2
    //   141: goto -47 -> 94
    //   144: astore_0
    //   145: aconst_null
    //   146: astore_2
    //   147: goto -30 -> 117
    //   150: astore_0
    //   151: aload 4
    //   153: astore_2
    //   154: goto -37 -> 117
    //   157: astore_0
    //   158: aconst_null
    //   159: astore_2
    //   160: goto -73 -> 87
    //   163: astore_0
    //   164: aload 4
    //   166: astore_2
    //   167: goto -80 -> 87
    // Local variable table:
    //   start	length	slot	name	signature
    //   0	170	0	paramArrayOfByte	byte[]
    //   15	118	1	localObject1	Object
    //   1	166	2	localObject2	Object
    //   30	89	3	localObject3	Object
    //   24	141	4	localGZIPOutputStream	java.util.zip.GZIPOutputStream
    // Exception table:
    //   from	to	target	type
    //   73	77	79	java/lang/Throwable
    //   8	16	82	java/io/IOException
    //   31	37	91	finally
    //   42	47	91	finally
    //   52	57	91	finally
    //   89	91	91	finally
    //   119	121	91	finally
    //   8	16	112	java/lang/Throwable
    //   98	102	121	java/lang/Throwable
    //   106	110	124	java/lang/Throwable
    //   62	67	127	java/lang/Throwable
    //   8	16	130	finally
    //   16	26	138	finally
    //   16	26	144	java/lang/Throwable
    //   31	37	150	java/lang/Throwable
    //   42	47	150	java/lang/Throwable
    //   52	57	150	java/lang/Throwable
    //   16	26	157	java/io/IOException
    //   31	37	163	java/io/IOException
    //   42	47	163	java/io/IOException
    //   52	57	163	java/io/IOException
  }
}

/* Location:
 * Qualified Name:     com.amap.api.mapcore2d.di
 * Java Class Version: 6 (50.0)
 * JD-Core Version:    0.7.1
 */