package com.android.mms.service;

import android.net.Uri;
import java.util.concurrent.Callable;

class MmsService$3
  implements Callable<Boolean>
{
  MmsService$3(MmsService paramMmsService, Uri paramUri, byte[] paramArrayOfByte) {}
  
  /* Error */
  public Boolean call()
  {
    // Byte code:
    //   0: aconst_null
    //   1: astore_1
    //   2: aconst_null
    //   3: astore_3
    //   4: new 36	android/os/ParcelFileDescriptor$AutoCloseOutputStream
    //   7: dup
    //   8: aload_0
    //   9: getfield 22	com/android/mms/service/MmsService$3:this$0	Lcom/android/mms/service/MmsService;
    //   12: invokevirtual 40	com/android/mms/service/MmsService:getContentResolver	()Landroid/content/ContentResolver;
    //   15: aload_0
    //   16: getfield 24	com/android/mms/service/MmsService$3:val$contentUri	Landroid/net/Uri;
    //   19: ldc 42
    //   21: invokevirtual 48	android/content/ContentResolver:openFileDescriptor	(Landroid/net/Uri;Ljava/lang/String;)Landroid/os/ParcelFileDescriptor;
    //   24: invokespecial 51	android/os/ParcelFileDescriptor$AutoCloseOutputStream:<init>	(Landroid/os/ParcelFileDescriptor;)V
    //   27: astore_2
    //   28: aload_2
    //   29: aload_0
    //   30: getfield 26	com/android/mms/service/MmsService$3:val$pdu	[B
    //   33: invokevirtual 55	android/os/ParcelFileDescriptor$AutoCloseOutputStream:write	([B)V
    //   36: getstatic 61	java/lang/Boolean:TRUE	Ljava/lang/Boolean;
    //   39: astore_1
    //   40: aload_2
    //   41: ifnull +7 -> 48
    //   44: aload_2
    //   45: invokevirtual 64	android/os/ParcelFileDescriptor$AutoCloseOutputStream:close	()V
    //   48: aload_1
    //   49: areturn
    //   50: astore_1
    //   51: aload_3
    //   52: astore_2
    //   53: aload_2
    //   54: astore_1
    //   55: getstatic 67	java/lang/Boolean:FALSE	Ljava/lang/Boolean;
    //   58: astore_3
    //   59: aload_3
    //   60: astore_1
    //   61: aload_2
    //   62: ifnull -14 -> 48
    //   65: aload_2
    //   66: invokevirtual 64	android/os/ParcelFileDescriptor$AutoCloseOutputStream:close	()V
    //   69: aload_3
    //   70: areturn
    //   71: astore_1
    //   72: aload_3
    //   73: areturn
    //   74: astore_2
    //   75: aload_1
    //   76: ifnull +7 -> 83
    //   79: aload_1
    //   80: invokevirtual 64	android/os/ParcelFileDescriptor$AutoCloseOutputStream:close	()V
    //   83: aload_2
    //   84: athrow
    //   85: astore_2
    //   86: goto -38 -> 48
    //   89: astore_1
    //   90: goto -7 -> 83
    //   93: astore_3
    //   94: aload_2
    //   95: astore_1
    //   96: aload_3
    //   97: astore_2
    //   98: goto -23 -> 75
    //   101: astore_1
    //   102: goto -49 -> 53
    // Local variable table:
    //   start	length	slot	name	signature
    //   0	105	0	this	3
    //   1	48	1	localBoolean1	Boolean
    //   50	1	1	localIOException1	java.io.IOException
    //   54	7	1	localObject1	Object
    //   71	9	1	localIOException2	java.io.IOException
    //   89	1	1	localIOException3	java.io.IOException
    //   95	1	1	localObject2	Object
    //   101	1	1	localIOException4	java.io.IOException
    //   27	39	2	localObject3	Object
    //   74	10	2	localObject4	Object
    //   85	10	2	localIOException5	java.io.IOException
    //   97	1	2	localObject5	Object
    //   3	70	3	localBoolean2	Boolean
    //   93	4	3	localObject6	Object
    // Exception table:
    //   from	to	target	type
    //   4	28	50	java/io/IOException
    //   65	69	71	java/io/IOException
    //   4	28	74	finally
    //   55	59	74	finally
    //   44	48	85	java/io/IOException
    //   79	83	89	java/io/IOException
    //   28	40	93	finally
    //   28	40	101	java/io/IOException
  }
}

/* Location:
 * Qualified Name:     com.android.mms.service.MmsService.3
 * Java Class Version: 6 (50.0)
 * JD-Core Version:    0.7.1
 */