final class agg
  extends Thread
{
  agg(agf paramagf, String paramString)
  {
    super(paramString);
  }
  
  /* Error */
  public final void run()
  {
    // Byte code:
    //   0: invokestatic 23	android/os/Looper:prepare	()V
    //   3: aload_0
    //   4: getfield 10	agg:a	Lagf;
    //   7: invokestatic 27	android/os/Looper:myLooper	()Landroid/os/Looper;
    //   10: invokestatic 32	agf:a	(Lagf;Landroid/os/Looper;)Landroid/os/Looper;
    //   13: pop
    //   14: aload_0
    //   15: getfield 10	agg:a	Lagf;
    //   18: new 34	java/util/Timer
    //   21: dup
    //   22: invokespecial 36	java/util/Timer:<init>	()V
    //   25: invokestatic 39	agf:a	(Lagf;Ljava/util/Timer;)Ljava/util/Timer;
    //   28: pop
    //   29: aload_0
    //   30: getfield 10	agg:a	Lagf;
    //   33: new 41	agh
    //   36: dup
    //   37: aload_0
    //   38: getfield 10	agg:a	Lagf;
    //   41: iconst_0
    //   42: invokespecial 44	agh:<init>	(Lagf;B)V
    //   45: invokestatic 47	agf:a	(Lagf;Lagh;)Lagh;
    //   48: pop
    //   49: aload_0
    //   50: getfield 10	agg:a	Lagf;
    //   53: aload_0
    //   54: getfield 10	agg:a	Lagf;
    //   57: invokestatic 50	agf:a	(Lagf;)Lagh;
    //   60: invokestatic 53	agf:a	(Lagf;Landroid/telephony/PhoneStateListener;)V
    //   63: aload_0
    //   64: getfield 10	agg:a	Lagf;
    //   67: new 55	agi
    //   70: dup
    //   71: aload_0
    //   72: getfield 10	agg:a	Lagf;
    //   75: iconst_0
    //   76: invokespecial 56	agi:<init>	(Lagf;B)V
    //   79: invokestatic 59	agf:a	(Lagf;Lagi;)Lagi;
    //   82: pop
    //   83: aload_0
    //   84: getfield 10	agg:a	Lagf;
    //   87: aload_0
    //   88: getfield 10	agg:a	Lagf;
    //   91: invokestatic 63	agf:b	(Lagf;)Lagi;
    //   94: invokestatic 66	agf:a	(Lagf;Landroid/location/GpsStatus$NmeaListener;)V
    //   97: invokestatic 69	android/os/Looper:loop	()V
    //   100: return
    //   101: astore_1
    //   102: return
    //   103: astore_1
    //   104: goto -7 -> 97
    // Local variable table:
    //   start	length	slot	name	signature
    //   0	107	0	this	agg
    //   101	1	1	localException1	Exception
    //   103	1	1	localException2	Exception
    // Exception table:
    //   from	to	target	type
    //   0	83	101	java/lang/Exception
    //   97	100	101	java/lang/Exception
    //   83	97	103	java/lang/Exception
  }
}

/* Location:
 * Qualified Name:     agg
 * Java Class Version: 6 (50.0)
 * JD-Core Version:    0.7.1
 */