import android.util.Pair;
import java.io.File;
import java.util.ArrayList;
import java.util.Iterator;
import java.util.List;

public class alu
  implements alw
{
  private String a;
  private String b;
  private List<Pair<String, String>> c;
  private List<Pair<String, String>> d;
  private boolean e;
  private alu.a f = null;
  private amm g;
  private long h = 200L;
  
  public alu(String paramString1, String paramString2, List<Pair<String, String>> paramList1, List<Pair<String, String>> paramList2)
  {
    a = paramString1;
    b = paramString2;
    c = paramList1;
    d = paramList2;
    e = false;
  }
  
  private long b(String paramString)
  {
    paramString = new File(paramString);
    if (paramString.exists()) {
      return paramString.length();
    }
    return 0L;
  }
  
  private void b()
  {
    if (e) {
      throw new alt();
    }
  }
  
  private void c()
  {
    File localFile = new File(b);
    if (!localFile.exists())
    {
      localFile = localFile.getParentFile();
      if (!localFile.exists()) {
        localFile.mkdirs();
      }
    }
  }
  
  private void c(String paramString)
  {
    paramString = new File(paramString);
    if (paramString.exists()) {
      paramString.delete();
    }
  }
  
  private void d(String paramString)
  {
    anf.d(paramString);
  }
  
  private void e(String paramString)
  {
    anf.c(paramString);
  }
  
  public void a()
  {
    e = true;
  }
  
  public void a(alu.a parama)
  {
    f = parama;
  }
  
  public void a(amm paramamm)
  {
    g = paramamm;
  }
  
  public void a(String paramString)
  {
    a = paramString;
  }
  
  public void a(List<Pair<String, String>> paramList)
  {
    if (d != null)
    {
      Iterator localIterator1 = paramList.iterator();
      for (;;)
      {
        if (!localIterator1.hasNext()) {
          break label110;
        }
        Pair localPair1 = (Pair)localIterator1.next();
        Iterator localIterator2 = d.iterator();
        if (localIterator2.hasNext())
        {
          Pair localPair2 = (Pair)localIterator2.next();
          if (!((String)first).equals(first)) {
            break;
          }
          d.remove(localPair2);
        }
      }
    }
    d = new ArrayList();
    label110:
    d.addAll(paramList);
  }
  
  /* Error */
  public boolean a(boolean paramBoolean)
  {
    // Byte code:
    //   0: aload_0
    //   1: invokespecial 138	alu:c	()V
    //   4: aconst_null
    //   5: astore 35
    //   7: aconst_null
    //   8: astore 30
    //   10: aconst_null
    //   11: astore 25
    //   13: aconst_null
    //   14: astore 26
    //   16: aconst_null
    //   17: astore 27
    //   19: aconst_null
    //   20: astore 28
    //   22: aconst_null
    //   23: astore 24
    //   25: aconst_null
    //   26: astore 36
    //   28: aconst_null
    //   29: astore 21
    //   31: aconst_null
    //   32: astore 31
    //   34: aconst_null
    //   35: astore 32
    //   37: aconst_null
    //   38: astore 33
    //   40: aconst_null
    //   41: astore 34
    //   43: aconst_null
    //   44: astore 29
    //   46: iload_1
    //   47: ifeq +272 -> 319
    //   50: ldc -116
    //   52: sipush 20000
    //   55: invokestatic 145	alz:b	(Ljava/lang/String;I)Lalz;
    //   58: astore 20
    //   60: aload 36
    //   62: astore 19
    //   64: aload 35
    //   66: astore 21
    //   68: aload 20
    //   70: astore 22
    //   72: aload_0
    //   73: getfield 40	alu:c	Ljava/util/List;
    //   76: ifnull +544 -> 620
    //   79: aload 36
    //   81: astore 19
    //   83: aload 35
    //   85: astore 21
    //   87: aload 20
    //   89: astore 22
    //   91: aload_0
    //   92: getfield 40	alu:c	Ljava/util/List;
    //   95: invokeinterface 149 1 0
    //   100: ifle +520 -> 620
    //   103: aload 36
    //   105: astore 19
    //   107: aload 35
    //   109: astore 21
    //   111: aload 20
    //   113: astore 22
    //   115: new 151	org/apache/http/client/methods/HttpPost
    //   118: dup
    //   119: aload_0
    //   120: getfield 36	alu:a	Ljava/lang/String;
    //   123: invokespecial 152	org/apache/http/client/methods/HttpPost:<init>	(Ljava/lang/String;)V
    //   126: astore 23
    //   128: aload 36
    //   130: astore 19
    //   132: aload 35
    //   134: astore 21
    //   136: aload 20
    //   138: astore 22
    //   140: new 117	java/util/ArrayList
    //   143: dup
    //   144: invokespecial 118	java/util/ArrayList:<init>	()V
    //   147: astore 37
    //   149: aload 36
    //   151: astore 19
    //   153: aload 35
    //   155: astore 21
    //   157: aload 20
    //   159: astore 22
    //   161: aload_0
    //   162: getfield 40	alu:c	Ljava/util/List;
    //   165: invokeinterface 91 1 0
    //   170: astore 38
    //   172: aload 36
    //   174: astore 19
    //   176: aload 35
    //   178: astore 21
    //   180: aload 20
    //   182: astore 22
    //   184: aload 38
    //   186: invokeinterface 96 1 0
    //   191: ifeq +141 -> 332
    //   194: aload 36
    //   196: astore 19
    //   198: aload 35
    //   200: astore 21
    //   202: aload 20
    //   204: astore 22
    //   206: aload 38
    //   208: invokeinterface 100 1 0
    //   213: checkcast 102	android/util/Pair
    //   216: astore 39
    //   218: aload 36
    //   220: astore 19
    //   222: aload 35
    //   224: astore 21
    //   226: aload 20
    //   228: astore 22
    //   230: aload 37
    //   232: new 154	org/apache/http/message/BasicNameValuePair
    //   235: dup
    //   236: aload 39
    //   238: getfield 106	android/util/Pair:first	Ljava/lang/Object;
    //   241: checkcast 108	java/lang/String
    //   244: aload 39
    //   246: getfield 157	android/util/Pair:second	Ljava/lang/Object;
    //   249: checkcast 108	java/lang/String
    //   252: invokespecial 160	org/apache/http/message/BasicNameValuePair:<init>	(Ljava/lang/String;Ljava/lang/String;)V
    //   255: invokeinterface 163 2 0
    //   260: pop
    //   261: goto -89 -> 172
    //   264: astore 22
    //   266: aconst_null
    //   267: astore 23
    //   269: aconst_null
    //   270: astore 21
    //   272: aload 20
    //   274: astore 19
    //   276: aload 23
    //   278: astore 20
    //   280: aload 22
    //   282: invokevirtual 166	java/io/IOException:printStackTrace	()V
    //   285: aload 19
    //   287: ifnull +8 -> 295
    //   290: aload 19
    //   292: invokevirtual 168	alz:a	()V
    //   295: aload 20
    //   297: ifnull +8 -> 305
    //   300: aload 20
    //   302: invokevirtual 173	java/io/InputStream:close	()V
    //   305: aload 21
    //   307: ifnull +8 -> 315
    //   310: aload 21
    //   312: invokevirtual 176	java/io/FileOutputStream:close	()V
    //   315: iconst_0
    //   316: istore_1
    //   317: iload_1
    //   318: ireturn
    //   319: ldc -116
    //   321: sipush 20000
    //   324: invokestatic 178	alz:a	(Ljava/lang/String;I)Lalz;
    //   327: astore 20
    //   329: goto -269 -> 60
    //   332: aload 36
    //   334: astore 19
    //   336: aload 35
    //   338: astore 21
    //   340: aload 20
    //   342: astore 22
    //   344: aload 23
    //   346: checkcast 151	org/apache/http/client/methods/HttpPost
    //   349: new 180	org/apache/http/client/entity/UrlEncodedFormEntity
    //   352: dup
    //   353: aload 37
    //   355: ldc -74
    //   357: invokespecial 185	org/apache/http/client/entity/UrlEncodedFormEntity:<init>	(Ljava/util/List;Ljava/lang/String;)V
    //   360: invokevirtual 189	org/apache/http/client/methods/HttpPost:setEntity	(Lorg/apache/http/HttpEntity;)V
    //   363: aload 36
    //   365: astore 19
    //   367: aload 35
    //   369: astore 21
    //   371: aload 20
    //   373: astore 22
    //   375: aload_0
    //   376: getfield 42	alu:d	Ljava/util/List;
    //   379: ifnull +286 -> 665
    //   382: aload 36
    //   384: astore 19
    //   386: aload 35
    //   388: astore 21
    //   390: aload 20
    //   392: astore 22
    //   394: aload_0
    //   395: getfield 42	alu:d	Ljava/util/List;
    //   398: invokeinterface 149 1 0
    //   403: ifle +262 -> 665
    //   406: aload 36
    //   408: astore 19
    //   410: aload 35
    //   412: astore 21
    //   414: aload 20
    //   416: astore 22
    //   418: aload_0
    //   419: getfield 42	alu:d	Ljava/util/List;
    //   422: invokeinterface 91 1 0
    //   427: astore 37
    //   429: aload 36
    //   431: astore 19
    //   433: aload 35
    //   435: astore 21
    //   437: aload 20
    //   439: astore 22
    //   441: aload 37
    //   443: invokeinterface 96 1 0
    //   448: ifeq +217 -> 665
    //   451: aload 36
    //   453: astore 19
    //   455: aload 35
    //   457: astore 21
    //   459: aload 20
    //   461: astore 22
    //   463: aload 37
    //   465: invokeinterface 100 1 0
    //   470: checkcast 102	android/util/Pair
    //   473: astore 38
    //   475: aload 36
    //   477: astore 19
    //   479: aload 35
    //   481: astore 21
    //   483: aload 20
    //   485: astore 22
    //   487: aload 23
    //   489: aload 38
    //   491: getfield 106	android/util/Pair:first	Ljava/lang/Object;
    //   494: checkcast 108	java/lang/String
    //   497: aload 38
    //   499: getfield 157	android/util/Pair:second	Ljava/lang/Object;
    //   502: checkcast 108	java/lang/String
    //   505: invokeinterface 194 3 0
    //   510: goto -81 -> 429
    //   513: astore 23
    //   515: aload 24
    //   517: astore 21
    //   519: aload 29
    //   521: astore 19
    //   523: aload 20
    //   525: astore 22
    //   527: aload 23
    //   529: athrow
    //   530: astore 23
    //   532: aload 22
    //   534: astore 20
    //   536: aload 21
    //   538: astore 22
    //   540: aload 19
    //   542: astore 21
    //   544: aload 23
    //   546: astore 19
    //   548: aload 20
    //   550: ifnull +8 -> 558
    //   553: aload 20
    //   555: invokevirtual 168	alz:a	()V
    //   558: aload 21
    //   560: ifnull +8 -> 568
    //   563: aload 21
    //   565: invokevirtual 173	java/io/InputStream:close	()V
    //   568: aload 22
    //   570: ifnull +8 -> 578
    //   573: aload 22
    //   575: invokevirtual 176	java/io/FileOutputStream:close	()V
    //   578: aload 19
    //   580: athrow
    //   581: astore 37
    //   583: aload 36
    //   585: astore 19
    //   587: aload 35
    //   589: astore 21
    //   591: aload 20
    //   593: astore 22
    //   595: aload 37
    //   597: invokevirtual 195	java/io/UnsupportedEncodingException:printStackTrace	()V
    //   600: goto -237 -> 363
    //   603: astore 23
    //   605: aload 25
    //   607: astore 21
    //   609: aload 31
    //   611: astore 19
    //   613: aload 20
    //   615: astore 22
    //   617: aload 23
    //   619: athrow
    //   620: aload 36
    //   622: astore 19
    //   624: aload 35
    //   626: astore 21
    //   628: aload 20
    //   630: astore 22
    //   632: new 197	org/apache/http/client/methods/HttpGet
    //   635: dup
    //   636: aload_0
    //   637: getfield 36	alu:a	Ljava/lang/String;
    //   640: invokespecial 198	org/apache/http/client/methods/HttpGet:<init>	(Ljava/lang/String;)V
    //   643: astore 23
    //   645: goto -282 -> 363
    //   648: astore 23
    //   650: aload 26
    //   652: astore 21
    //   654: aload 32
    //   656: astore 19
    //   658: aload 20
    //   660: astore 22
    //   662: aload 23
    //   664: athrow
    //   665: aload 36
    //   667: astore 19
    //   669: aload 35
    //   671: astore 21
    //   673: aload 20
    //   675: astore 22
    //   677: aload_0
    //   678: aload_0
    //   679: getfield 38	alu:b	Ljava/lang/String;
    //   682: invokespecial 200	alu:b	(Ljava/lang/String;)J
    //   685: lstore 13
    //   687: lload 13
    //   689: lconst_0
    //   690: lcmp
    //   691: ifle +85 -> 776
    //   694: aload 36
    //   696: astore 19
    //   698: aload 35
    //   700: astore 21
    //   702: aload 20
    //   704: astore 22
    //   706: aload_0
    //   707: new 202	java/lang/StringBuilder
    //   710: dup
    //   711: invokespecial 203	java/lang/StringBuilder:<init>	()V
    //   714: ldc -51
    //   716: invokevirtual 209	java/lang/StringBuilder:append	(Ljava/lang/String;)Ljava/lang/StringBuilder;
    //   719: lload 13
    //   721: invokevirtual 212	java/lang/StringBuilder:append	(J)Ljava/lang/StringBuilder;
    //   724: invokevirtual 216	java/lang/StringBuilder:toString	()Ljava/lang/String;
    //   727: invokespecial 217	alu:d	(Ljava/lang/String;)V
    //   730: aload 36
    //   732: astore 19
    //   734: aload 35
    //   736: astore 21
    //   738: aload 20
    //   740: astore 22
    //   742: aload 23
    //   744: ldc -37
    //   746: new 202	java/lang/StringBuilder
    //   749: dup
    //   750: invokespecial 203	java/lang/StringBuilder:<init>	()V
    //   753: ldc -35
    //   755: invokevirtual 209	java/lang/StringBuilder:append	(Ljava/lang/String;)Ljava/lang/StringBuilder;
    //   758: lload 13
    //   760: invokevirtual 212	java/lang/StringBuilder:append	(J)Ljava/lang/StringBuilder;
    //   763: ldc -33
    //   765: invokevirtual 209	java/lang/StringBuilder:append	(Ljava/lang/String;)Ljava/lang/StringBuilder;
    //   768: invokevirtual 216	java/lang/StringBuilder:toString	()Ljava/lang/String;
    //   771: invokeinterface 194 3 0
    //   776: aload 36
    //   778: astore 19
    //   780: aload 35
    //   782: astore 21
    //   784: aload 20
    //   786: astore 22
    //   788: aload_0
    //   789: ldc -31
    //   791: invokespecial 227	alu:e	(Ljava/lang/String;)V
    //   794: aload 36
    //   796: astore 19
    //   798: aload 35
    //   800: astore 21
    //   802: aload 20
    //   804: astore 22
    //   806: aload 20
    //   808: aload 23
    //   810: invokevirtual 231	alz:execute	(Lorg/apache/http/client/methods/HttpUriRequest;)Lorg/apache/http/HttpResponse;
    //   813: astore 37
    //   815: aload 36
    //   817: astore 19
    //   819: aload 35
    //   821: astore 21
    //   823: aload 20
    //   825: astore 22
    //   827: aload 37
    //   829: invokeinterface 237 1 0
    //   834: invokeinterface 242 1 0
    //   839: istore_2
    //   840: aload 36
    //   842: astore 19
    //   844: aload 35
    //   846: astore 21
    //   848: aload 20
    //   850: astore 22
    //   852: aload_0
    //   853: new 202	java/lang/StringBuilder
    //   856: dup
    //   857: invokespecial 203	java/lang/StringBuilder:<init>	()V
    //   860: ldc -12
    //   862: invokevirtual 209	java/lang/StringBuilder:append	(Ljava/lang/String;)Ljava/lang/StringBuilder;
    //   865: iload_2
    //   866: invokevirtual 247	java/lang/StringBuilder:append	(I)Ljava/lang/StringBuilder;
    //   869: invokevirtual 216	java/lang/StringBuilder:toString	()Ljava/lang/String;
    //   872: invokespecial 217	alu:d	(Ljava/lang/String;)V
    //   875: aload 36
    //   877: astore 19
    //   879: aload 35
    //   881: astore 21
    //   883: aload 20
    //   885: astore 22
    //   887: aload 37
    //   889: invokeinterface 251 1 0
    //   894: invokeinterface 257 1 0
    //   899: astore 23
    //   901: aload 36
    //   903: astore 19
    //   905: aload 35
    //   907: astore 21
    //   909: aload 20
    //   911: astore 22
    //   913: aload 37
    //   915: invokeinterface 251 1 0
    //   920: invokeinterface 260 1 0
    //   925: lstore 5
    //   927: aload 36
    //   929: astore 19
    //   931: aload 35
    //   933: astore 21
    //   935: aload 20
    //   937: astore 22
    //   939: aload_0
    //   940: new 202	java/lang/StringBuilder
    //   943: dup
    //   944: invokespecial 203	java/lang/StringBuilder:<init>	()V
    //   947: ldc_w 262
    //   950: invokevirtual 209	java/lang/StringBuilder:append	(Ljava/lang/String;)Ljava/lang/StringBuilder;
    //   953: lload 5
    //   955: invokevirtual 212	java/lang/StringBuilder:append	(J)Ljava/lang/StringBuilder;
    //   958: invokevirtual 216	java/lang/StringBuilder:toString	()Ljava/lang/String;
    //   961: invokespecial 227	alu:e	(Ljava/lang/String;)V
    //   964: aload 36
    //   966: astore 19
    //   968: aload 35
    //   970: astore 21
    //   972: aload 20
    //   974: astore 22
    //   976: aload_0
    //   977: new 202	java/lang/StringBuilder
    //   980: dup
    //   981: invokespecial 203	java/lang/StringBuilder:<init>	()V
    //   984: ldc_w 264
    //   987: invokevirtual 209	java/lang/StringBuilder:append	(Ljava/lang/String;)Ljava/lang/StringBuilder;
    //   990: aload 23
    //   992: invokevirtual 267	java/lang/StringBuilder:append	(Ljava/lang/Object;)Ljava/lang/StringBuilder;
    //   995: invokevirtual 216	java/lang/StringBuilder:toString	()Ljava/lang/String;
    //   998: invokespecial 227	alu:e	(Ljava/lang/String;)V
    //   1001: iload_2
    //   1002: sipush 200
    //   1005: if_icmpeq +331 -> 1336
    //   1008: iload_2
    //   1009: sipush 206
    //   1012: if_icmpeq +324 -> 1336
    //   1015: iload_2
    //   1016: sipush 301
    //   1019: if_icmpeq +10 -> 1029
    //   1022: iload_2
    //   1023: sipush 302
    //   1026: if_icmpne +232 -> 1258
    //   1029: aload 36
    //   1031: astore 19
    //   1033: aload 35
    //   1035: astore 21
    //   1037: aload 20
    //   1039: astore 22
    //   1041: aload 37
    //   1043: ldc_w 269
    //   1046: invokeinterface 273 2 0
    //   1051: astore 23
    //   1053: aload 23
    //   1055: ifnull +181 -> 1236
    //   1058: aload 36
    //   1060: astore 19
    //   1062: aload 35
    //   1064: astore 21
    //   1066: aload 20
    //   1068: astore 22
    //   1070: aload 23
    //   1072: invokeinterface 278 1 0
    //   1077: astore 23
    //   1079: aload 36
    //   1081: astore 19
    //   1083: aload 35
    //   1085: astore 21
    //   1087: aload 20
    //   1089: astore 22
    //   1091: aload 23
    //   1093: invokestatic 284	android/text/TextUtils:isEmpty	(Ljava/lang/CharSequence;)Z
    //   1096: ifne +43 -> 1139
    //   1099: aload 36
    //   1101: astore 19
    //   1103: aload 35
    //   1105: astore 21
    //   1107: aload 20
    //   1109: astore 22
    //   1111: new 130	ame
    //   1114: dup
    //   1115: iload_2
    //   1116: aload 23
    //   1118: invokespecial 287	ame:<init>	(ILjava/lang/String;)V
    //   1121: athrow
    //   1122: astore 23
    //   1124: aload 27
    //   1126: astore 21
    //   1128: aload 33
    //   1130: astore 19
    //   1132: aload 20
    //   1134: astore 22
    //   1136: aload 23
    //   1138: athrow
    //   1139: aload 36
    //   1141: astore 19
    //   1143: aload 35
    //   1145: astore 21
    //   1147: aload 20
    //   1149: astore 22
    //   1151: aload_0
    //   1152: ldc_w 289
    //   1155: invokespecial 217	alu:d	(Ljava/lang/String;)V
    //   1158: goto +947 -> 2105
    //   1161: aload 36
    //   1163: astore 19
    //   1165: aload 35
    //   1167: astore 21
    //   1169: aload 20
    //   1171: astore 22
    //   1173: new 128	alx
    //   1176: dup
    //   1177: iload_2
    //   1178: aload 23
    //   1180: invokespecial 290	alx:<init>	(ILjava/lang/String;)V
    //   1183: athrow
    //   1184: astore 23
    //   1186: aload 28
    //   1188: astore 25
    //   1190: aload 34
    //   1192: astore 24
    //   1194: aload 24
    //   1196: astore 19
    //   1198: aload 25
    //   1200: astore 21
    //   1202: aload 20
    //   1204: astore 22
    //   1206: aload 23
    //   1208: invokevirtual 291	java/lang/Exception:printStackTrace	()V
    //   1211: aload 24
    //   1213: astore 19
    //   1215: aload 25
    //   1217: astore 21
    //   1219: aload 20
    //   1221: astore 22
    //   1223: new 293	aly
    //   1226: dup
    //   1227: aload 23
    //   1229: invokevirtual 296	java/lang/Exception:getMessage	()Ljava/lang/String;
    //   1232: invokespecial 297	aly:<init>	(Ljava/lang/String;)V
    //   1235: athrow
    //   1236: aload 36
    //   1238: astore 19
    //   1240: aload 35
    //   1242: astore 21
    //   1244: aload 20
    //   1246: astore 22
    //   1248: aload_0
    //   1249: ldc_w 299
    //   1252: invokespecial 217	alu:d	(Ljava/lang/String;)V
    //   1255: goto +850 -> 2105
    //   1258: iload_2
    //   1259: sipush 416
    //   1262: if_icmpne +843 -> 2105
    //   1265: aload 36
    //   1267: astore 19
    //   1269: aload 35
    //   1271: astore 21
    //   1273: aload 20
    //   1275: astore 22
    //   1277: aload_0
    //   1278: ldc_w 301
    //   1281: invokespecial 217	alu:d	(Ljava/lang/String;)V
    //   1284: aload 36
    //   1286: astore 19
    //   1288: aload 35
    //   1290: astore 21
    //   1292: aload 20
    //   1294: astore 22
    //   1296: aload_0
    //   1297: aload_0
    //   1298: getfield 38	alu:b	Ljava/lang/String;
    //   1301: invokespecial 302	alu:c	(Ljava/lang/String;)V
    //   1304: goto +801 -> 2105
    //   1307: aload 36
    //   1309: astore 19
    //   1311: aload 35
    //   1313: astore 21
    //   1315: aload 20
    //   1317: astore 22
    //   1319: aload 37
    //   1321: invokeinterface 251 1 0
    //   1326: ldc -74
    //   1328: invokestatic 307	org/apache/http/util/EntityUtils:toString	(Lorg/apache/http/HttpEntity;Ljava/lang/String;)Ljava/lang/String;
    //   1331: astore 23
    //   1333: goto -172 -> 1161
    //   1336: aload 36
    //   1338: astore 19
    //   1340: aload 35
    //   1342: astore 21
    //   1344: aload 20
    //   1346: astore 22
    //   1348: aload 37
    //   1350: invokeinterface 251 1 0
    //   1355: invokeinterface 311 1 0
    //   1360: astore 23
    //   1362: aload 23
    //   1364: astore 19
    //   1366: aload 37
    //   1368: invokeinterface 251 1 0
    //   1373: invokeinterface 260 1 0
    //   1378: lstore 15
    //   1380: aload_0
    //   1381: getfield 84	alu:g	Lamm;
    //   1384: ifnull +66 -> 1450
    //   1387: aload_0
    //   1388: getfield 84	alu:g	Lamm;
    //   1391: lload 13
    //   1393: lload 15
    //   1395: invokeinterface 316 5 0
    //   1400: astore 21
    //   1402: aload 21
    //   1404: invokevirtual 320	aml:b	()Z
    //   1407: ifne +43 -> 1450
    //   1410: lload 13
    //   1412: lconst_0
    //   1413: lcmp
    //   1414: ifle +22 -> 1436
    //   1417: aload_0
    //   1418: aload_0
    //   1419: getfield 38	alu:b	Ljava/lang/String;
    //   1422: invokespecial 302	alu:c	(Ljava/lang/String;)V
    //   1425: new 293	aly
    //   1428: dup
    //   1429: ldc_w 322
    //   1432: invokespecial 297	aly:<init>	(Ljava/lang/String;)V
    //   1435: athrow
    //   1436: new 132	alv
    //   1439: dup
    //   1440: iload_2
    //   1441: aload 21
    //   1443: invokevirtual 324	aml:c	()Ljava/lang/String;
    //   1446: invokespecial 325	alv:<init>	(ILjava/lang/String;)V
    //   1449: athrow
    //   1450: sipush 4096
    //   1453: newarray <illegal type>
    //   1455: astore 22
    //   1457: lconst_0
    //   1458: lstore 9
    //   1460: new 50	java/io/File
    //   1463: dup
    //   1464: aload_0
    //   1465: getfield 38	alu:b	Ljava/lang/String;
    //   1468: invokespecial 53	java/io/File:<init>	(Ljava/lang/String;)V
    //   1471: astore 21
    //   1473: lload 13
    //   1475: lconst_0
    //   1476: lcmp
    //   1477: ifle +730 -> 2207
    //   1480: iconst_1
    //   1481: istore_1
    //   1482: new 175	java/io/FileOutputStream
    //   1485: dup
    //   1486: aload 21
    //   1488: iload_1
    //   1489: invokespecial 328	java/io/FileOutputStream:<init>	(Ljava/io/File;Z)V
    //   1492: astore 21
    //   1494: invokestatic 333	android/os/SystemClock:elapsedRealtime	()J
    //   1497: lstore 17
    //   1499: lconst_0
    //   1500: lstore 7
    //   1502: aload_0
    //   1503: invokespecial 335	alu:b	()V
    //   1506: aload 19
    //   1508: aload 22
    //   1510: invokevirtual 339	java/io/InputStream:read	([B)I
    //   1513: istore_3
    //   1514: lload 7
    //   1516: lstore 11
    //   1518: lload 9
    //   1520: lstore 5
    //   1522: iload_3
    //   1523: ifle +628 -> 2151
    //   1526: aload 21
    //   1528: aload 22
    //   1530: iconst_0
    //   1531: iload_3
    //   1532: invokevirtual 343	java/io/FileOutputStream:write	([BII)V
    //   1535: aload 21
    //   1537: invokevirtual 346	java/io/FileOutputStream:flush	()V
    //   1540: iload_3
    //   1541: i2l
    //   1542: lload 9
    //   1544: ladd
    //   1545: lstore 5
    //   1547: invokestatic 333	android/os/SystemClock:elapsedRealtime	()J
    //   1550: lload 17
    //   1552: lsub
    //   1553: ldc2_w 347
    //   1556: ldiv
    //   1557: lstore 11
    //   1559: lload 11
    //   1561: lstore 9
    //   1563: lload 11
    //   1565: lconst_1
    //   1566: lcmp
    //   1567: ifge +6 -> 1573
    //   1570: lconst_1
    //   1571: lstore 9
    //   1573: lload 5
    //   1575: lload 9
    //   1577: ldiv
    //   1578: lstore 9
    //   1580: lload 5
    //   1582: lload 13
    //   1584: ladd
    //   1585: ldc2_w 349
    //   1588: lmul
    //   1589: lload 15
    //   1591: lload 13
    //   1593: ladd
    //   1594: ldiv
    //   1595: l2i
    //   1596: istore 4
    //   1598: invokestatic 333	android/os/SystemClock:elapsedRealtime	()J
    //   1601: lstore 11
    //   1603: lload 11
    //   1605: lload 7
    //   1607: lsub
    //   1608: aload_0
    //   1609: getfield 34	alu:h	J
    //   1612: lcmp
    //   1613: ifgt +10 -> 1623
    //   1616: iload 4
    //   1618: bipush 100
    //   1620: if_icmpne +478 -> 2098
    //   1623: aload_0
    //   1624: getfield 30	alu:f	Lalu$a;
    //   1627: ifnull +524 -> 2151
    //   1630: aload_0
    //   1631: getfield 30	alu:f	Lalu$a;
    //   1634: iload 4
    //   1636: lload 9
    //   1638: invokeinterface 353 4 0
    //   1643: goto +508 -> 2151
    //   1646: lload 15
    //   1648: lconst_0
    //   1649: lcmp
    //   1650: ifle +87 -> 1737
    //   1653: lload 5
    //   1655: lload 15
    //   1657: lcmp
    //   1658: ifge +79 -> 1737
    //   1661: aload_0
    //   1662: new 202	java/lang/StringBuilder
    //   1665: dup
    //   1666: invokespecial 203	java/lang/StringBuilder:<init>	()V
    //   1669: ldc_w 355
    //   1672: invokevirtual 209	java/lang/StringBuilder:append	(Ljava/lang/String;)Ljava/lang/StringBuilder;
    //   1675: lload 5
    //   1677: invokevirtual 212	java/lang/StringBuilder:append	(J)Ljava/lang/StringBuilder;
    //   1680: ldc_w 357
    //   1683: invokevirtual 209	java/lang/StringBuilder:append	(Ljava/lang/String;)Ljava/lang/StringBuilder;
    //   1686: lload 15
    //   1688: invokevirtual 212	java/lang/StringBuilder:append	(J)Ljava/lang/StringBuilder;
    //   1691: invokevirtual 216	java/lang/StringBuilder:toString	()Ljava/lang/String;
    //   1694: invokespecial 217	alu:d	(Ljava/lang/String;)V
    //   1697: new 293	aly
    //   1700: dup
    //   1701: new 202	java/lang/StringBuilder
    //   1704: dup
    //   1705: invokespecial 203	java/lang/StringBuilder:<init>	()V
    //   1708: ldc_w 355
    //   1711: invokevirtual 209	java/lang/StringBuilder:append	(Ljava/lang/String;)Ljava/lang/StringBuilder;
    //   1714: lload 5
    //   1716: invokevirtual 212	java/lang/StringBuilder:append	(J)Ljava/lang/StringBuilder;
    //   1719: ldc_w 357
    //   1722: invokevirtual 209	java/lang/StringBuilder:append	(Ljava/lang/String;)Ljava/lang/StringBuilder;
    //   1725: lload 15
    //   1727: invokevirtual 212	java/lang/StringBuilder:append	(J)Ljava/lang/StringBuilder;
    //   1730: invokevirtual 216	java/lang/StringBuilder:toString	()Ljava/lang/String;
    //   1733: invokespecial 297	aly:<init>	(Ljava/lang/String;)V
    //   1736: athrow
    //   1737: aload_0
    //   1738: getfield 84	alu:g	Lamm;
    //   1741: ifnull +53 -> 1794
    //   1744: aload_0
    //   1745: getfield 84	alu:g	Lamm;
    //   1748: aload_0
    //   1749: getfield 38	alu:b	Ljava/lang/String;
    //   1752: invokeinterface 360 2 0
    //   1757: astore 22
    //   1759: aload 22
    //   1761: invokevirtual 320	aml:b	()Z
    //   1764: ifne +30 -> 1794
    //   1767: aload_0
    //   1768: aload_0
    //   1769: getfield 38	alu:b	Ljava/lang/String;
    //   1772: invokespecial 302	alu:c	(Ljava/lang/String;)V
    //   1775: new 132	alv
    //   1778: dup
    //   1779: iload_2
    //   1780: aload 22
    //   1782: invokevirtual 324	aml:c	()Ljava/lang/String;
    //   1785: invokespecial 325	alv:<init>	(ILjava/lang/String;)V
    //   1788: athrow
    //   1789: astore 23
    //   1791: goto -1268 -> 523
    //   1794: iconst_1
    //   1795: istore_1
    //   1796: aload 20
    //   1798: ifnull +8 -> 1806
    //   1801: aload 20
    //   1803: invokevirtual 168	alz:a	()V
    //   1806: aload 19
    //   1808: ifnull +8 -> 1816
    //   1811: aload 19
    //   1813: invokevirtual 173	java/io/InputStream:close	()V
    //   1816: aload 21
    //   1818: ifnull -1501 -> 317
    //   1821: aload 21
    //   1823: invokevirtual 176	java/io/FileOutputStream:close	()V
    //   1826: iconst_1
    //   1827: ireturn
    //   1828: astore 19
    //   1830: aload 19
    //   1832: invokevirtual 291	java/lang/Exception:printStackTrace	()V
    //   1835: iconst_1
    //   1836: ireturn
    //   1837: astore 19
    //   1839: aload 19
    //   1841: invokevirtual 291	java/lang/Exception:printStackTrace	()V
    //   1844: goto -1529 -> 315
    //   1847: astore 20
    //   1849: aload 20
    //   1851: invokevirtual 291	java/lang/Exception:printStackTrace	()V
    //   1854: goto -1276 -> 578
    //   1857: astore 19
    //   1859: aconst_null
    //   1860: astore 20
    //   1862: aload 30
    //   1864: astore 22
    //   1866: goto -1318 -> 548
    //   1869: astore 22
    //   1871: aload 19
    //   1873: astore 21
    //   1875: aload 22
    //   1877: astore 19
    //   1879: aload 30
    //   1881: astore 22
    //   1883: goto -1335 -> 548
    //   1886: astore 24
    //   1888: aload 19
    //   1890: astore 22
    //   1892: aload 21
    //   1894: astore 23
    //   1896: aload 24
    //   1898: astore 19
    //   1900: aload 22
    //   1902: astore 21
    //   1904: aload 23
    //   1906: astore 22
    //   1908: goto -1360 -> 548
    //   1911: astore 24
    //   1913: aload 21
    //   1915: astore 22
    //   1917: aload 19
    //   1919: astore 23
    //   1921: aload 24
    //   1923: astore 19
    //   1925: aload 20
    //   1927: astore 21
    //   1929: aload 23
    //   1931: astore 20
    //   1933: goto -1385 -> 548
    //   1936: astore 23
    //   1938: aconst_null
    //   1939: astore 20
    //   1941: aload 34
    //   1943: astore 24
    //   1945: aload 28
    //   1947: astore 25
    //   1949: goto -755 -> 1194
    //   1952: astore 23
    //   1954: aload 19
    //   1956: astore 24
    //   1958: aload 28
    //   1960: astore 25
    //   1962: goto -768 -> 1194
    //   1965: astore 23
    //   1967: aload 19
    //   1969: astore 24
    //   1971: aload 21
    //   1973: astore 25
    //   1975: goto -781 -> 1194
    //   1978: astore 23
    //   1980: aconst_null
    //   1981: astore 20
    //   1983: aload 33
    //   1985: astore 19
    //   1987: aload 27
    //   1989: astore 21
    //   1991: goto -859 -> 1132
    //   1994: astore 23
    //   1996: aload 27
    //   1998: astore 21
    //   2000: goto -868 -> 1132
    //   2003: astore 23
    //   2005: goto -873 -> 1132
    //   2008: astore 23
    //   2010: aconst_null
    //   2011: astore 20
    //   2013: aload 32
    //   2015: astore 19
    //   2017: aload 26
    //   2019: astore 21
    //   2021: goto -1363 -> 658
    //   2024: astore 23
    //   2026: aload 26
    //   2028: astore 21
    //   2030: goto -1372 -> 658
    //   2033: astore 23
    //   2035: goto -1377 -> 658
    //   2038: astore 23
    //   2040: aconst_null
    //   2041: astore 20
    //   2043: aload 31
    //   2045: astore 19
    //   2047: aload 25
    //   2049: astore 21
    //   2051: goto -1438 -> 613
    //   2054: astore 23
    //   2056: aload 25
    //   2058: astore 21
    //   2060: goto -1447 -> 613
    //   2063: astore 23
    //   2065: goto -1452 -> 613
    //   2068: astore 23
    //   2070: aconst_null
    //   2071: astore 20
    //   2073: aload 29
    //   2075: astore 19
    //   2077: aload 24
    //   2079: astore 21
    //   2081: goto -1558 -> 523
    //   2084: astore 22
    //   2086: aconst_null
    //   2087: astore 21
    //   2089: aconst_null
    //   2090: astore 19
    //   2092: aconst_null
    //   2093: astore 20
    //   2095: goto -1815 -> 280
    //   2098: lload 7
    //   2100: lstore 11
    //   2102: goto +49 -> 2151
    //   2105: lload 5
    //   2107: ldc2_w 361
    //   2110: lcmp
    //   2111: ifle -804 -> 1307
    //   2114: ldc_w 364
    //   2117: astore 23
    //   2119: goto -958 -> 1161
    //   2122: astore 22
    //   2124: aconst_null
    //   2125: astore 21
    //   2127: aload 20
    //   2129: astore 23
    //   2131: aload 19
    //   2133: astore 20
    //   2135: aload 23
    //   2137: astore 19
    //   2139: goto -1859 -> 280
    //   2142: astore 23
    //   2144: aload 24
    //   2146: astore 21
    //   2148: goto -1625 -> 523
    //   2151: iload_3
    //   2152: iconst_m1
    //   2153: if_icmpeq -507 -> 1646
    //   2156: lload 11
    //   2158: lstore 7
    //   2160: lload 5
    //   2162: lstore 9
    //   2164: lload 15
    //   2166: lconst_0
    //   2167: lcmp
    //   2168: ifle -666 -> 1502
    //   2171: lload 11
    //   2173: lstore 7
    //   2175: lload 5
    //   2177: lstore 9
    //   2179: lload 5
    //   2181: lload 15
    //   2183: lcmp
    //   2184: iflt -682 -> 1502
    //   2187: goto -541 -> 1646
    //   2190: astore 22
    //   2192: aload 20
    //   2194: astore 23
    //   2196: aload 19
    //   2198: astore 20
    //   2200: aload 23
    //   2202: astore 19
    //   2204: goto -1924 -> 280
    //   2207: iconst_0
    //   2208: istore_1
    //   2209: goto -727 -> 1482
    // Local variable table:
    //   start	length	slot	name	signature
    //   0	2212	0	this	alu
    //   0	2212	1	paramBoolean	boolean
    //   839	941	2	i	int
    //   1513	641	3	j	int
    //   1596	39	4	k	int
    //   925	1255	5	l1	long
    //   1500	674	7	l2	long
    //   1458	720	9	l3	long
    //   1516	656	11	l4	long
    //   685	907	13	l5	long
    //   1378	804	15	l6	long
    //   1497	54	17	l7	long
    //   62	1750	19	localObject1	Object
    //   1828	3	19	localException1	Exception
    //   1837	3	19	localException2	Exception
    //   1857	15	19	localObject2	Object
    //   1877	326	19	localObject3	Object
    //   58	1744	20	localObject4	Object
    //   1847	3	20	localException3	Exception
    //   1860	339	20	localObject5	Object
    //   29	2118	21	localObject6	Object
    //   70	159	22	localObject7	Object
    //   264	17	22	localIOException1	java.io.IOException
    //   342	1523	22	localObject8	Object
    //   1869	7	22	localObject9	Object
    //   1881	35	22	localObject10	Object
    //   2084	1	22	localIOException2	java.io.IOException
    //   2122	1	22	localIOException3	java.io.IOException
    //   2190	1	22	localIOException4	java.io.IOException
    //   126	362	23	localHttpPost	org.apache.http.client.methods.HttpPost
    //   513	15	23	localalt1	alt
    //   530	15	23	localObject11	Object
    //   603	15	23	localalx1	alx
    //   643	1	23	localHttpGet	org.apache.http.client.methods.HttpGet
    //   648	161	23	localame1	ame
    //   899	218	23	localObject12	Object
    //   1122	57	23	localalv1	alv
    //   1184	44	23	localException4	Exception
    //   1331	32	23	localObject13	Object
    //   1789	1	23	localalt2	alt
    //   1894	36	23	localObject14	Object
    //   1936	1	23	localException5	Exception
    //   1952	1	23	localException6	Exception
    //   1965	1	23	localException7	Exception
    //   1978	1	23	localalv2	alv
    //   1994	1	23	localalv3	alv
    //   2003	1	23	localalv4	alv
    //   2008	1	23	localame2	ame
    //   2024	1	23	localame3	ame
    //   2033	1	23	localame4	ame
    //   2038	1	23	localalx2	alx
    //   2054	1	23	localalx3	alx
    //   2063	1	23	localalx4	alx
    //   2068	1	23	localalt3	alt
    //   2117	19	23	localObject15	Object
    //   2142	1	23	localalt4	alt
    //   2194	7	23	localObject16	Object
    //   23	1189	24	localObject17	Object
    //   1886	11	24	localObject18	Object
    //   1911	11	24	localObject19	Object
    //   1943	202	24	localObject20	Object
    //   11	2046	25	localObject21	Object
    //   14	2013	26	localObject22	Object
    //   17	1980	27	localObject23	Object
    //   20	1939	28	localObject24	Object
    //   44	2030	29	localObject25	Object
    //   8	1872	30	localObject26	Object
    //   32	2012	31	localObject27	Object
    //   35	1979	32	localObject28	Object
    //   38	1946	33	localObject29	Object
    //   41	1901	34	localObject30	Object
    //   5	1336	35	localObject31	Object
    //   26	1311	36	localObject32	Object
    //   147	317	37	localObject33	Object
    //   581	15	37	localUnsupportedEncodingException	java.io.UnsupportedEncodingException
    //   813	554	37	localHttpResponse	org.apache.http.HttpResponse
    //   170	328	38	localObject34	Object
    //   216	29	39	localPair	Pair
    // Exception table:
    //   from	to	target	type
    //   72	79	264	java/io/IOException
    //   91	103	264	java/io/IOException
    //   115	128	264	java/io/IOException
    //   140	149	264	java/io/IOException
    //   161	172	264	java/io/IOException
    //   184	194	264	java/io/IOException
    //   206	218	264	java/io/IOException
    //   230	261	264	java/io/IOException
    //   344	363	264	java/io/IOException
    //   375	382	264	java/io/IOException
    //   394	406	264	java/io/IOException
    //   418	429	264	java/io/IOException
    //   441	451	264	java/io/IOException
    //   463	475	264	java/io/IOException
    //   487	510	264	java/io/IOException
    //   595	600	264	java/io/IOException
    //   632	645	264	java/io/IOException
    //   677	687	264	java/io/IOException
    //   706	730	264	java/io/IOException
    //   742	776	264	java/io/IOException
    //   788	794	264	java/io/IOException
    //   806	815	264	java/io/IOException
    //   827	840	264	java/io/IOException
    //   852	875	264	java/io/IOException
    //   887	901	264	java/io/IOException
    //   913	927	264	java/io/IOException
    //   939	964	264	java/io/IOException
    //   976	1001	264	java/io/IOException
    //   1041	1053	264	java/io/IOException
    //   1070	1079	264	java/io/IOException
    //   1091	1099	264	java/io/IOException
    //   1111	1122	264	java/io/IOException
    //   1151	1158	264	java/io/IOException
    //   1173	1184	264	java/io/IOException
    //   1248	1255	264	java/io/IOException
    //   1277	1284	264	java/io/IOException
    //   1296	1304	264	java/io/IOException
    //   1319	1333	264	java/io/IOException
    //   1348	1362	264	java/io/IOException
    //   72	79	513	alt
    //   91	103	513	alt
    //   115	128	513	alt
    //   140	149	513	alt
    //   161	172	513	alt
    //   184	194	513	alt
    //   206	218	513	alt
    //   230	261	513	alt
    //   344	363	513	alt
    //   375	382	513	alt
    //   394	406	513	alt
    //   418	429	513	alt
    //   441	451	513	alt
    //   463	475	513	alt
    //   487	510	513	alt
    //   595	600	513	alt
    //   632	645	513	alt
    //   677	687	513	alt
    //   706	730	513	alt
    //   742	776	513	alt
    //   788	794	513	alt
    //   806	815	513	alt
    //   827	840	513	alt
    //   852	875	513	alt
    //   887	901	513	alt
    //   913	927	513	alt
    //   939	964	513	alt
    //   976	1001	513	alt
    //   1041	1053	513	alt
    //   1070	1079	513	alt
    //   1091	1099	513	alt
    //   1111	1122	513	alt
    //   1151	1158	513	alt
    //   1173	1184	513	alt
    //   1248	1255	513	alt
    //   1277	1284	513	alt
    //   1296	1304	513	alt
    //   1319	1333	513	alt
    //   1348	1362	513	alt
    //   72	79	530	finally
    //   91	103	530	finally
    //   115	128	530	finally
    //   140	149	530	finally
    //   161	172	530	finally
    //   184	194	530	finally
    //   206	218	530	finally
    //   230	261	530	finally
    //   344	363	530	finally
    //   375	382	530	finally
    //   394	406	530	finally
    //   418	429	530	finally
    //   441	451	530	finally
    //   463	475	530	finally
    //   487	510	530	finally
    //   527	530	530	finally
    //   595	600	530	finally
    //   617	620	530	finally
    //   632	645	530	finally
    //   662	665	530	finally
    //   677	687	530	finally
    //   706	730	530	finally
    //   742	776	530	finally
    //   788	794	530	finally
    //   806	815	530	finally
    //   827	840	530	finally
    //   852	875	530	finally
    //   887	901	530	finally
    //   913	927	530	finally
    //   939	964	530	finally
    //   976	1001	530	finally
    //   1041	1053	530	finally
    //   1070	1079	530	finally
    //   1091	1099	530	finally
    //   1111	1122	530	finally
    //   1136	1139	530	finally
    //   1151	1158	530	finally
    //   1173	1184	530	finally
    //   1206	1211	530	finally
    //   1223	1236	530	finally
    //   1248	1255	530	finally
    //   1277	1284	530	finally
    //   1296	1304	530	finally
    //   1319	1333	530	finally
    //   1348	1362	530	finally
    //   344	363	581	java/io/UnsupportedEncodingException
    //   72	79	603	alx
    //   91	103	603	alx
    //   115	128	603	alx
    //   140	149	603	alx
    //   161	172	603	alx
    //   184	194	603	alx
    //   206	218	603	alx
    //   230	261	603	alx
    //   344	363	603	alx
    //   375	382	603	alx
    //   394	406	603	alx
    //   418	429	603	alx
    //   441	451	603	alx
    //   463	475	603	alx
    //   487	510	603	alx
    //   595	600	603	alx
    //   632	645	603	alx
    //   677	687	603	alx
    //   706	730	603	alx
    //   742	776	603	alx
    //   788	794	603	alx
    //   806	815	603	alx
    //   827	840	603	alx
    //   852	875	603	alx
    //   887	901	603	alx
    //   913	927	603	alx
    //   939	964	603	alx
    //   976	1001	603	alx
    //   1041	1053	603	alx
    //   1070	1079	603	alx
    //   1091	1099	603	alx
    //   1111	1122	603	alx
    //   1151	1158	603	alx
    //   1173	1184	603	alx
    //   1248	1255	603	alx
    //   1277	1284	603	alx
    //   1296	1304	603	alx
    //   1319	1333	603	alx
    //   1348	1362	603	alx
    //   72	79	648	ame
    //   91	103	648	ame
    //   115	128	648	ame
    //   140	149	648	ame
    //   161	172	648	ame
    //   184	194	648	ame
    //   206	218	648	ame
    //   230	261	648	ame
    //   344	363	648	ame
    //   375	382	648	ame
    //   394	406	648	ame
    //   418	429	648	ame
    //   441	451	648	ame
    //   463	475	648	ame
    //   487	510	648	ame
    //   595	600	648	ame
    //   632	645	648	ame
    //   677	687	648	ame
    //   706	730	648	ame
    //   742	776	648	ame
    //   788	794	648	ame
    //   806	815	648	ame
    //   827	840	648	ame
    //   852	875	648	ame
    //   887	901	648	ame
    //   913	927	648	ame
    //   939	964	648	ame
    //   976	1001	648	ame
    //   1041	1053	648	ame
    //   1070	1079	648	ame
    //   1091	1099	648	ame
    //   1111	1122	648	ame
    //   1151	1158	648	ame
    //   1173	1184	648	ame
    //   1248	1255	648	ame
    //   1277	1284	648	ame
    //   1296	1304	648	ame
    //   1319	1333	648	ame
    //   1348	1362	648	ame
    //   72	79	1122	alv
    //   91	103	1122	alv
    //   115	128	1122	alv
    //   140	149	1122	alv
    //   161	172	1122	alv
    //   184	194	1122	alv
    //   206	218	1122	alv
    //   230	261	1122	alv
    //   344	363	1122	alv
    //   375	382	1122	alv
    //   394	406	1122	alv
    //   418	429	1122	alv
    //   441	451	1122	alv
    //   463	475	1122	alv
    //   487	510	1122	alv
    //   595	600	1122	alv
    //   632	645	1122	alv
    //   677	687	1122	alv
    //   706	730	1122	alv
    //   742	776	1122	alv
    //   788	794	1122	alv
    //   806	815	1122	alv
    //   827	840	1122	alv
    //   852	875	1122	alv
    //   887	901	1122	alv
    //   913	927	1122	alv
    //   939	964	1122	alv
    //   976	1001	1122	alv
    //   1041	1053	1122	alv
    //   1070	1079	1122	alv
    //   1091	1099	1122	alv
    //   1111	1122	1122	alv
    //   1151	1158	1122	alv
    //   1173	1184	1122	alv
    //   1248	1255	1122	alv
    //   1277	1284	1122	alv
    //   1296	1304	1122	alv
    //   1319	1333	1122	alv
    //   1348	1362	1122	alv
    //   72	79	1184	java/lang/Exception
    //   91	103	1184	java/lang/Exception
    //   115	128	1184	java/lang/Exception
    //   140	149	1184	java/lang/Exception
    //   161	172	1184	java/lang/Exception
    //   184	194	1184	java/lang/Exception
    //   206	218	1184	java/lang/Exception
    //   230	261	1184	java/lang/Exception
    //   344	363	1184	java/lang/Exception
    //   375	382	1184	java/lang/Exception
    //   394	406	1184	java/lang/Exception
    //   418	429	1184	java/lang/Exception
    //   441	451	1184	java/lang/Exception
    //   463	475	1184	java/lang/Exception
    //   487	510	1184	java/lang/Exception
    //   595	600	1184	java/lang/Exception
    //   632	645	1184	java/lang/Exception
    //   677	687	1184	java/lang/Exception
    //   706	730	1184	java/lang/Exception
    //   742	776	1184	java/lang/Exception
    //   788	794	1184	java/lang/Exception
    //   806	815	1184	java/lang/Exception
    //   827	840	1184	java/lang/Exception
    //   852	875	1184	java/lang/Exception
    //   887	901	1184	java/lang/Exception
    //   913	927	1184	java/lang/Exception
    //   939	964	1184	java/lang/Exception
    //   976	1001	1184	java/lang/Exception
    //   1041	1053	1184	java/lang/Exception
    //   1070	1079	1184	java/lang/Exception
    //   1091	1099	1184	java/lang/Exception
    //   1111	1122	1184	java/lang/Exception
    //   1151	1158	1184	java/lang/Exception
    //   1173	1184	1184	java/lang/Exception
    //   1248	1255	1184	java/lang/Exception
    //   1277	1284	1184	java/lang/Exception
    //   1296	1304	1184	java/lang/Exception
    //   1319	1333	1184	java/lang/Exception
    //   1348	1362	1184	java/lang/Exception
    //   1494	1499	1789	alt
    //   1502	1514	1789	alt
    //   1526	1540	1789	alt
    //   1547	1559	1789	alt
    //   1573	1616	1789	alt
    //   1623	1643	1789	alt
    //   1661	1737	1789	alt
    //   1737	1789	1789	alt
    //   1801	1806	1828	java/lang/Exception
    //   1811	1816	1828	java/lang/Exception
    //   1821	1826	1828	java/lang/Exception
    //   290	295	1837	java/lang/Exception
    //   300	305	1837	java/lang/Exception
    //   310	315	1837	java/lang/Exception
    //   553	558	1847	java/lang/Exception
    //   563	568	1847	java/lang/Exception
    //   573	578	1847	java/lang/Exception
    //   50	60	1857	finally
    //   319	329	1857	finally
    //   1366	1410	1869	finally
    //   1417	1436	1869	finally
    //   1436	1450	1869	finally
    //   1450	1457	1869	finally
    //   1460	1473	1869	finally
    //   1482	1494	1869	finally
    //   1494	1499	1886	finally
    //   1502	1514	1886	finally
    //   1526	1540	1886	finally
    //   1547	1559	1886	finally
    //   1573	1616	1886	finally
    //   1623	1643	1886	finally
    //   1661	1737	1886	finally
    //   1737	1789	1886	finally
    //   280	285	1911	finally
    //   50	60	1936	java/lang/Exception
    //   319	329	1936	java/lang/Exception
    //   1366	1410	1952	java/lang/Exception
    //   1417	1436	1952	java/lang/Exception
    //   1436	1450	1952	java/lang/Exception
    //   1450	1457	1952	java/lang/Exception
    //   1460	1473	1952	java/lang/Exception
    //   1482	1494	1952	java/lang/Exception
    //   1494	1499	1965	java/lang/Exception
    //   1502	1514	1965	java/lang/Exception
    //   1526	1540	1965	java/lang/Exception
    //   1547	1559	1965	java/lang/Exception
    //   1573	1616	1965	java/lang/Exception
    //   1623	1643	1965	java/lang/Exception
    //   1661	1737	1965	java/lang/Exception
    //   1737	1789	1965	java/lang/Exception
    //   50	60	1978	alv
    //   319	329	1978	alv
    //   1366	1410	1994	alv
    //   1417	1436	1994	alv
    //   1436	1450	1994	alv
    //   1450	1457	1994	alv
    //   1460	1473	1994	alv
    //   1482	1494	1994	alv
    //   1494	1499	2003	alv
    //   1502	1514	2003	alv
    //   1526	1540	2003	alv
    //   1547	1559	2003	alv
    //   1573	1616	2003	alv
    //   1623	1643	2003	alv
    //   1661	1737	2003	alv
    //   1737	1789	2003	alv
    //   50	60	2008	ame
    //   319	329	2008	ame
    //   1366	1410	2024	ame
    //   1417	1436	2024	ame
    //   1436	1450	2024	ame
    //   1450	1457	2024	ame
    //   1460	1473	2024	ame
    //   1482	1494	2024	ame
    //   1494	1499	2033	ame
    //   1502	1514	2033	ame
    //   1526	1540	2033	ame
    //   1547	1559	2033	ame
    //   1573	1616	2033	ame
    //   1623	1643	2033	ame
    //   1661	1737	2033	ame
    //   1737	1789	2033	ame
    //   50	60	2038	alx
    //   319	329	2038	alx
    //   1366	1410	2054	alx
    //   1417	1436	2054	alx
    //   1436	1450	2054	alx
    //   1450	1457	2054	alx
    //   1460	1473	2054	alx
    //   1482	1494	2054	alx
    //   1494	1499	2063	alx
    //   1502	1514	2063	alx
    //   1526	1540	2063	alx
    //   1547	1559	2063	alx
    //   1573	1616	2063	alx
    //   1623	1643	2063	alx
    //   1661	1737	2063	alx
    //   1737	1789	2063	alx
    //   50	60	2068	alt
    //   319	329	2068	alt
    //   50	60	2084	java/io/IOException
    //   319	329	2084	java/io/IOException
    //   1366	1410	2122	java/io/IOException
    //   1417	1436	2122	java/io/IOException
    //   1436	1450	2122	java/io/IOException
    //   1450	1457	2122	java/io/IOException
    //   1460	1473	2122	java/io/IOException
    //   1482	1494	2122	java/io/IOException
    //   1366	1410	2142	alt
    //   1417	1436	2142	alt
    //   1436	1450	2142	alt
    //   1450	1457	2142	alt
    //   1460	1473	2142	alt
    //   1482	1494	2142	alt
    //   1494	1499	2190	java/io/IOException
    //   1502	1514	2190	java/io/IOException
    //   1526	1540	2190	java/io/IOException
    //   1547	1559	2190	java/io/IOException
    //   1573	1616	2190	java/io/IOException
    //   1623	1643	2190	java/io/IOException
    //   1661	1737	2190	java/io/IOException
    //   1737	1789	2190	java/io/IOException
  }
  
  public static abstract interface a
  {
    public abstract void a(int paramInt, long paramLong);
  }
}

/* Location:
 * Qualified Name:     alu
 * Java Class Version: 6 (50.0)
 * JD-Core Version:    0.7.1
 */