import android.util.Pair;
import java.util.List;

public class ank
{
  public static String a(String paramString, List<Pair<String, String>> paramList)
  {
    try
    {
      paramString = b(paramString, paramList);
      return paramString;
    }
    catch (ane paramString)
    {
      paramString.printStackTrace();
    }
    return null;
  }
  
  /* Error */
  public static String b(String paramString, List<Pair<String, String>> paramList)
  {
    // Byte code:
    //   0: ldc 22
    //   2: sipush 30000
    //   5: iconst_1
    //   6: invokestatic 27	alz:a	(Ljava/lang/String;IZ)Lalz;
    //   9: astore_3
    //   10: new 29	org/apache/http/client/methods/HttpPost
    //   13: dup
    //   14: aload_0
    //   15: invokespecial 33	org/apache/http/client/methods/HttpPost:<init>	(Ljava/lang/String;)V
    //   18: astore_0
    //   19: new 35	java/util/ArrayList
    //   22: dup
    //   23: invokespecial 37	java/util/ArrayList:<init>	()V
    //   26: astore 4
    //   28: aload_1
    //   29: invokeinterface 43 1 0
    //   34: astore_1
    //   35: aload_1
    //   36: invokeinterface 49 1 0
    //   41: ifeq +62 -> 103
    //   44: aload_1
    //   45: invokeinterface 53 1 0
    //   50: checkcast 55	android/util/Pair
    //   53: astore 5
    //   55: aload 4
    //   57: new 57	org/apache/http/message/BasicNameValuePair
    //   60: dup
    //   61: aload 5
    //   63: getfield 61	android/util/Pair:first	Ljava/lang/Object;
    //   66: checkcast 63	java/lang/String
    //   69: aload 5
    //   71: getfield 66	android/util/Pair:second	Ljava/lang/Object;
    //   74: checkcast 63	java/lang/String
    //   77: invokespecial 69	org/apache/http/message/BasicNameValuePair:<init>	(Ljava/lang/String;Ljava/lang/String;)V
    //   80: invokeinterface 73 2 0
    //   85: pop
    //   86: goto -51 -> 35
    //   89: astore_0
    //   90: aload_0
    //   91: athrow
    //   92: astore_0
    //   93: aload_3
    //   94: ifnull +7 -> 101
    //   97: aload_3
    //   98: invokevirtual 75	alz:a	()V
    //   101: aload_0
    //   102: athrow
    //   103: aload_0
    //   104: new 77	org/apache/http/client/entity/UrlEncodedFormEntity
    //   107: dup
    //   108: aload 4
    //   110: ldc 79
    //   112: invokespecial 82	org/apache/http/client/entity/UrlEncodedFormEntity:<init>	(Ljava/util/List;Ljava/lang/String;)V
    //   115: invokevirtual 86	org/apache/http/client/methods/HttpPost:setEntity	(Lorg/apache/http/HttpEntity;)V
    //   118: aload_3
    //   119: aload_0
    //   120: invokevirtual 90	alz:execute	(Lorg/apache/http/client/methods/HttpUriRequest;)Lorg/apache/http/HttpResponse;
    //   123: astore_0
    //   124: aload_0
    //   125: invokeinterface 96 1 0
    //   130: invokeinterface 102 1 0
    //   135: istore_2
    //   136: iload_2
    //   137: sipush 200
    //   140: if_icmpne +106 -> 246
    //   143: aload_0
    //   144: invokeinterface 106 1 0
    //   149: invokeinterface 112 1 0
    //   154: astore_0
    //   155: new 114	java/io/BufferedReader
    //   158: dup
    //   159: new 116	java/io/InputStreamReader
    //   162: dup
    //   163: aload_0
    //   164: ldc 79
    //   166: invokespecial 119	java/io/InputStreamReader:<init>	(Ljava/io/InputStream;Ljava/lang/String;)V
    //   169: invokespecial 122	java/io/BufferedReader:<init>	(Ljava/io/Reader;)V
    //   172: astore_1
    //   173: new 124	java/lang/StringBuffer
    //   176: dup
    //   177: invokespecial 125	java/lang/StringBuffer:<init>	()V
    //   180: astore 4
    //   182: aload_1
    //   183: invokevirtual 129	java/io/BufferedReader:readLine	()Ljava/lang/String;
    //   186: astore 5
    //   188: aload 5
    //   190: ifnull +36 -> 226
    //   193: aload 4
    //   195: aload 5
    //   197: invokevirtual 133	java/lang/StringBuffer:append	(Ljava/lang/String;)Ljava/lang/StringBuffer;
    //   200: ldc -121
    //   202: invokevirtual 133	java/lang/StringBuffer:append	(Ljava/lang/String;)Ljava/lang/StringBuffer;
    //   205: pop
    //   206: goto -24 -> 182
    //   209: astore_0
    //   210: aload_0
    //   211: invokevirtual 136	java/lang/Exception:printStackTrace	()V
    //   214: new 8	ane
    //   217: dup
    //   218: aload_0
    //   219: invokevirtual 139	java/lang/Exception:getMessage	()Ljava/lang/String;
    //   222: invokespecial 140	ane:<init>	(Ljava/lang/String;)V
    //   225: athrow
    //   226: aload_0
    //   227: invokevirtual 145	java/io/InputStream:close	()V
    //   230: aload 4
    //   232: invokevirtual 148	java/lang/StringBuffer:toString	()Ljava/lang/String;
    //   235: astore_0
    //   236: aload_3
    //   237: ifnull +7 -> 244
    //   240: aload_3
    //   241: invokevirtual 75	alz:a	()V
    //   244: aload_0
    //   245: areturn
    //   246: new 8	ane
    //   249: dup
    //   250: iload_2
    //   251: new 150	java/lang/StringBuilder
    //   254: dup
    //   255: invokespecial 151	java/lang/StringBuilder:<init>	()V
    //   258: ldc -103
    //   260: invokevirtual 156	java/lang/StringBuilder:append	(Ljava/lang/String;)Ljava/lang/StringBuilder;
    //   263: iload_2
    //   264: invokevirtual 159	java/lang/StringBuilder:append	(I)Ljava/lang/StringBuilder;
    //   267: invokevirtual 160	java/lang/StringBuilder:toString	()Ljava/lang/String;
    //   270: invokespecial 163	ane:<init>	(ILjava/lang/String;)V
    //   273: athrow
    // Local variable table:
    //   start	length	slot	name	signature
    //   0	274	0	paramString	String
    //   0	274	1	paramList	List<Pair<String, String>>
    //   135	129	2	i	int
    //   9	232	3	localalz	alz
    //   26	205	4	localObject1	Object
    //   53	143	5	localObject2	Object
    // Exception table:
    //   from	to	target	type
    //   10	35	89	ane
    //   35	86	89	ane
    //   103	136	89	ane
    //   143	182	89	ane
    //   182	188	89	ane
    //   193	206	89	ane
    //   226	236	89	ane
    //   246	274	89	ane
    //   10	35	92	finally
    //   35	86	92	finally
    //   90	92	92	finally
    //   103	136	92	finally
    //   143	182	92	finally
    //   182	188	92	finally
    //   193	206	92	finally
    //   210	226	92	finally
    //   226	236	92	finally
    //   246	274	92	finally
    //   10	35	209	java/lang/Exception
    //   35	86	209	java/lang/Exception
    //   103	136	209	java/lang/Exception
    //   143	182	209	java/lang/Exception
    //   182	188	209	java/lang/Exception
    //   193	206	209	java/lang/Exception
    //   226	236	209	java/lang/Exception
    //   246	274	209	java/lang/Exception
  }
}

/* Location:
 * Qualified Name:     ank
 * Java Class Version: 6 (50.0)
 * JD-Core Version:    0.7.1
 */