import android.view.View.OnClickListener;
import org.json.JSONArray;

class dc
  implements View.OnClickListener
{
  dc(cw paramcw, JSONArray paramJSONArray) {}
  
  /* Error */
  public void onClick(android.view.View paramView)
  {
    // Byte code:
    //   0: invokestatic 29	cw:b	()Z
    //   3: ifeq +4 -> 7
    //   6: return
    //   7: aload_0
    //   8: getfield 14	dc:b	Lcw;
    //   11: getfield 33	cw:g	Lcn/com/xy/sms/sdk/smsmessage/BusinessSmsMessage;
    //   14: new 35	java/lang/StringBuilder
    //   17: dup
    //   18: invokespecial 36	java/lang/StringBuilder:<init>	()V
    //   21: ldc 38
    //   23: invokevirtual 42	java/lang/StringBuilder:append	(Ljava/lang/String;)Ljava/lang/StringBuilder;
    //   26: aload_0
    //   27: getfield 14	dc:b	Lcw;
    //   30: invokestatic 46	cw:e	(Lcw;)I
    //   33: invokevirtual 49	java/lang/StringBuilder:append	(I)Ljava/lang/StringBuilder;
    //   36: invokevirtual 53	java/lang/StringBuilder:toString	()Ljava/lang/String;
    //   39: invokevirtual 59	cn/com/xy/sms/sdk/smsmessage/BusinessSmsMessage:getValue	(Ljava/lang/String;)Ljava/lang/Object;
    //   42: checkcast 61	java/lang/String
    //   45: astore 5
    //   47: aload_0
    //   48: getfield 16	dc:a	Lorg/json/JSONArray;
    //   51: ifnonnull +28 -> 79
    //   54: aload_0
    //   55: getfield 14	dc:b	Lcw;
    //   58: getfield 65	cw:f	Landroid/app/Activity;
    //   61: invokestatic 68	cw:c	()Ljava/lang/String;
    //   64: ldc 70
    //   66: aload 5
    //   68: invokevirtual 74	java/lang/String:replace	(Ljava/lang/CharSequence;Ljava/lang/CharSequence;)Ljava/lang/String;
    //   71: iconst_0
    //   72: invokestatic 80	android/widget/Toast:makeText	(Landroid/content/Context;Ljava/lang/CharSequence;I)Landroid/widget/Toast;
    //   75: invokevirtual 83	android/widget/Toast:show	()V
    //   78: return
    //   79: aload_0
    //   80: getfield 14	dc:b	Lcw;
    //   83: aload_0
    //   84: getfield 14	dc:b	Lcw;
    //   87: getfield 33	cw:g	Lcn/com/xy/sms/sdk/smsmessage/BusinessSmsMessage;
    //   90: invokestatic 86	cw:c	(Lcw;Lcn/com/xy/sms/sdk/smsmessage/BusinessSmsMessage;)Lorg/json/JSONObject;
    //   93: astore_3
    //   94: aload_3
    //   95: ldc 88
    //   97: invokestatic 94	cn/com/xy/sms/sdk/util/JsonUtil:getValueFromJsonObject	(Lorg/json/JSONObject;Ljava/lang/String;)Ljava/lang/Object;
    //   100: checkcast 61	java/lang/String
    //   103: astore_1
    //   104: aload_3
    //   105: ldc 96
    //   107: invokestatic 94	cn/com/xy/sms/sdk/util/JsonUtil:getValueFromJsonObject	(Lorg/json/JSONObject;Ljava/lang/String;)Ljava/lang/Object;
    //   110: checkcast 61	java/lang/String
    //   113: astore_3
    //   114: aload_1
    //   115: astore 4
    //   117: aload_3
    //   118: astore_1
    //   119: aload_0
    //   120: getfield 16	dc:a	Lorg/json/JSONArray;
    //   123: aload 4
    //   125: aload_1
    //   126: invokestatic 99	cw:a	(Lorg/json/JSONArray;Ljava/lang/String;Ljava/lang/String;)Lorg/json/JSONArray;
    //   129: astore_3
    //   130: aload_3
    //   131: ifnull +10 -> 141
    //   134: aload_3
    //   135: invokevirtual 105	org/json/JSONArray:length	()I
    //   138: ifne +51 -> 189
    //   141: aload_0
    //   142: getfield 14	dc:b	Lcw;
    //   145: getfield 65	cw:f	Landroid/app/Activity;
    //   148: invokestatic 68	cw:c	()Ljava/lang/String;
    //   151: ldc 70
    //   153: aload 5
    //   155: invokevirtual 74	java/lang/String:replace	(Ljava/lang/CharSequence;Ljava/lang/CharSequence;)Ljava/lang/String;
    //   158: iconst_0
    //   159: invokestatic 80	android/widget/Toast:makeText	(Landroid/content/Context;Ljava/lang/CharSequence;I)Landroid/widget/Toast;
    //   162: invokevirtual 83	android/widget/Toast:show	()V
    //   165: return
    //   166: astore_3
    //   167: ldc 107
    //   169: astore_1
    //   170: aload_3
    //   171: invokevirtual 110	java/lang/Exception:printStackTrace	()V
    //   174: aload_1
    //   175: astore 4
    //   177: ldc 107
    //   179: astore_1
    //   180: goto -61 -> 119
    //   183: astore_1
    //   184: aload_1
    //   185: invokevirtual 110	java/lang/Exception:printStackTrace	()V
    //   188: return
    //   189: iconst_1
    //   190: invokestatic 113	cw:a	(Z)Z
    //   193: pop
    //   194: aload_0
    //   195: getfield 14	dc:b	Lcw;
    //   198: invokestatic 116	cw:c	(Lcw;)Landroid/widget/TextView;
    //   201: ifnull +105 -> 306
    //   204: aload_0
    //   205: getfield 14	dc:b	Lcw;
    //   208: invokestatic 116	cw:c	(Lcw;)Landroid/widget/TextView;
    //   211: invokevirtual 122	android/widget/TextView:getText	()Ljava/lang/CharSequence;
    //   214: invokeinterface 125 1 0
    //   219: invokevirtual 128	java/lang/String:trim	()Ljava/lang/String;
    //   222: astore_1
    //   223: new 130	es
    //   226: dup
    //   227: aload_0
    //   228: getfield 14	dc:b	Lcw;
    //   231: getfield 133	cw:c	Lfd;
    //   234: aload_3
    //   235: aload_0
    //   236: getfield 14	dc:b	Lcw;
    //   239: getfield 65	cw:f	Landroid/app/Activity;
    //   242: getstatic 139	br$g:ShareDialog	I
    //   245: aload_1
    //   246: invokespecial 142	es:<init>	(Lfd;Lorg/json/JSONArray;Landroid/content/Context;ILjava/lang/String;)V
    //   249: astore_1
    //   250: aload_1
    //   251: invokevirtual 146	es:getWindow	()Landroid/view/Window;
    //   254: astore_3
    //   255: aload_0
    //   256: getfield 14	dc:b	Lcw;
    //   259: getfield 65	cw:f	Landroid/app/Activity;
    //   262: bipush 18
    //   264: invokestatic 152	cn/com/xy/sms/sdk/ui/popu/util/ViewUtil:dp2px	(Landroid/content/Context;I)I
    //   267: istore_2
    //   268: aload_3
    //   269: invokevirtual 158	android/view/Window:getDecorView	()Landroid/view/View;
    //   272: iload_2
    //   273: iconst_0
    //   274: iload_2
    //   275: iconst_0
    //   276: invokevirtual 164	android/view/View:setPadding	(IIII)V
    //   279: aload_3
    //   280: invokevirtual 168	android/view/Window:getAttributes	()Landroid/view/WindowManager$LayoutParams;
    //   283: astore 4
    //   285: aload 4
    //   287: iconst_m1
    //   288: putfield 173	android/view/WindowManager$LayoutParams:width	I
    //   291: aload_3
    //   292: aload 4
    //   294: invokevirtual 177	android/view/Window:setAttributes	(Landroid/view/WindowManager$LayoutParams;)V
    //   297: aload_1
    //   298: invokevirtual 178	es:show	()V
    //   301: return
    //   302: astore_3
    //   303: goto -133 -> 170
    //   306: goto -83 -> 223
    // Local variable table:
    //   start	length	slot	name	signature
    //   0	309	0	this	dc
    //   0	309	1	paramView	android.view.View
    //   267	8	2	i	int
    //   93	42	3	localObject1	Object
    //   166	69	3	localException1	Exception
    //   254	38	3	localWindow	android.view.Window
    //   302	1	3	localException2	Exception
    //   115	178	4	localObject2	Object
    //   45	109	5	str	String
    // Exception table:
    //   from	to	target	type
    //   94	104	166	java/lang/Exception
    //   119	130	183	java/lang/Exception
    //   104	114	302	java/lang/Exception
  }
}

/* Location:
 * Qualified Name:     dc
 * Java Class Version: 6 (50.0)
 * JD-Core Version:    0.7.1
 */