import android.content.Context;
import android.net.Uri;
import android.util.Log;
import com.google.android.mms.MmsException;
import com.meizu.android.mms.pdu.MzNotificationInd;
import com.meizu.android.mms.pdu.MzPduPersister;

public class pb
  extends ow
  implements Runnable
{
  private MzNotificationInd a;
  private String p;
  private long q;
  
  public pb(Context paramContext, int paramInt, oz paramoz, String paramString)
  {
    super(paramContext, paramInt, paramoz);
    g = Uri.parse(paramString);
    try
    {
      a = ((MzNotificationInd)MzPduPersister.getPduPersister(paramContext).load(g));
      p = new String(a.getContentLocation());
      c = p;
      q = a.getMessageSize();
      h = 2;
      l = a(g);
      b(g);
      return;
    }
    catch (MmsException paramContext)
    {
      Log.e("FlymeNotificationTransaction", "Failed to load MzNotificationInd from: " + paramString, paramContext);
      throw new IllegalArgumentException();
    }
  }
  
  public void a()
  {
    new Thread(this, "FlymeNotificationTransaction").start();
  }
  
  public int c()
  {
    return 0;
  }
  
  /* Error */
  public void run()
  {
    // Byte code:
    //   0: invokestatic 123	zn:a	()Lzn;
    //   3: astore 13
    //   5: aload_0
    //   6: getfield 126	pb:b	Landroid/content/Context;
    //   9: invokevirtual 132	android/content/Context:getContentResolver	()Landroid/content/ContentResolver;
    //   12: aload_0
    //   13: getfield 29	pb:g	Landroid/net/Uri;
    //   16: iconst_3
    //   17: anewarray 45	java/lang/String
    //   20: dup
    //   21: iconst_0
    //   22: ldc -122
    //   24: aastore
    //   25: dup
    //   26: iconst_1
    //   27: ldc -120
    //   29: aastore
    //   30: dup
    //   31: iconst_2
    //   32: ldc -118
    //   34: aastore
    //   35: aconst_null
    //   36: aconst_null
    //   37: aconst_null
    //   38: invokevirtual 144	android/content/ContentResolver:query	(Landroid/net/Uri;[Ljava/lang/String;Ljava/lang/String;[Ljava/lang/String;Ljava/lang/String;)Landroid/database/Cursor;
    //   41: astore 8
    //   43: aload 8
    //   45: ifnull +2745 -> 2790
    //   48: aload 8
    //   50: invokeinterface 149 1 0
    //   55: ifle +2723 -> 2778
    //   58: aload 8
    //   60: invokeinterface 153 1 0
    //   65: ifeq +2713 -> 2778
    //   68: aload 8
    //   70: aload 8
    //   72: ldc -120
    //   74: invokeinterface 157 2 0
    //   79: invokeinterface 161 2 0
    //   84: astore 7
    //   86: aload 8
    //   88: aload 8
    //   90: ldc -118
    //   92: invokeinterface 157 2 0
    //   97: invokeinterface 165 2 0
    //   102: lstore_3
    //   103: aload 8
    //   105: invokeinterface 168 1 0
    //   110: aload_0
    //   111: getfield 126	pb:b	Landroid/content/Context;
    //   114: lload_3
    //   115: invokestatic 173	wd:b	(Landroid/content/Context;J)Z
    //   118: istore 6
    //   120: sipush 131
    //   123: istore_2
    //   124: aload 7
    //   126: astore 8
    //   128: aload 7
    //   130: astore 9
    //   132: ldc 79
    //   134: new 81	java/lang/StringBuilder
    //   137: dup
    //   138: invokespecial 84	java/lang/StringBuilder:<init>	()V
    //   141: ldc -81
    //   143: invokevirtual 90	java/lang/StringBuilder:append	(Ljava/lang/String;)Ljava/lang/StringBuilder;
    //   146: aload_0
    //   147: invokevirtual 178	java/lang/StringBuilder:append	(Ljava/lang/Object;)Ljava/lang/StringBuilder;
    //   150: invokevirtual 94	java/lang/StringBuilder:toString	()Ljava/lang/String;
    //   153: invokestatic 182	android/util/Log:v	(Ljava/lang/String;Ljava/lang/String;)I
    //   156: pop
    //   157: iload 6
    //   159: ifne +323 -> 482
    //   162: aload 7
    //   164: astore 8
    //   166: aload 7
    //   168: astore 9
    //   170: aload 13
    //   172: aload_0
    //   173: getfield 29	pb:g	Landroid/net/Uri;
    //   176: sipush 128
    //   179: aload_0
    //   180: getfield 185	pb:o	I
    //   183: invokevirtual 188	zn:a	(Landroid/net/Uri;II)V
    //   186: aload_0
    //   187: getfield 191	pb:k	I
    //   190: sipush 9528
    //   193: if_icmpne +208 -> 401
    //   196: aload 13
    //   198: aload_0
    //   199: getfield 29	pb:g	Landroid/net/Uri;
    //   202: sipush 132
    //   205: iconst_m1
    //   206: invokevirtual 193	zn:b	(Landroid/net/Uri;II)V
    //   209: aload_0
    //   210: getfield 29	pb:g	Landroid/net/Uri;
    //   213: ifnull +95 -> 308
    //   216: aload_0
    //   217: invokevirtual 196	pb:m	()J
    //   220: lconst_0
    //   221: lcmp
    //   222: ifle +86 -> 308
    //   225: new 198	android/content/ContentValues
    //   228: dup
    //   229: iconst_1
    //   230: invokespecial 201	android/content/ContentValues:<init>	(I)V
    //   233: astore 8
    //   235: aload 8
    //   237: ldc -53
    //   239: aload_0
    //   240: invokevirtual 196	pb:m	()J
    //   243: invokestatic 209	java/lang/Long:valueOf	(J)Ljava/lang/Long;
    //   246: invokevirtual 213	android/content/ContentValues:put	(Ljava/lang/String;Ljava/lang/Long;)V
    //   249: ldc 79
    //   251: new 81	java/lang/StringBuilder
    //   254: dup
    //   255: invokespecial 84	java/lang/StringBuilder:<init>	()V
    //   258: ldc -41
    //   260: invokevirtual 90	java/lang/StringBuilder:append	(Ljava/lang/String;)Ljava/lang/StringBuilder;
    //   263: aload_0
    //   264: invokevirtual 196	pb:m	()J
    //   267: invokevirtual 218	java/lang/StringBuilder:append	(J)Ljava/lang/StringBuilder;
    //   270: ldc -36
    //   272: invokevirtual 90	java/lang/StringBuilder:append	(Ljava/lang/String;)Ljava/lang/StringBuilder;
    //   275: aload_0
    //   276: getfield 29	pb:g	Landroid/net/Uri;
    //   279: invokevirtual 178	java/lang/StringBuilder:append	(Ljava/lang/Object;)Ljava/lang/StringBuilder;
    //   282: invokevirtual 94	java/lang/StringBuilder:toString	()Ljava/lang/String;
    //   285: invokestatic 223	android/util/Log:d	(Ljava/lang/String;Ljava/lang/String;)I
    //   288: pop
    //   289: aload_0
    //   290: getfield 126	pb:b	Landroid/content/Context;
    //   293: invokevirtual 132	android/content/Context:getContentResolver	()Landroid/content/ContentResolver;
    //   296: aload_0
    //   297: getfield 29	pb:g	Landroid/net/Uri;
    //   300: aload 8
    //   302: aconst_null
    //   303: aconst_null
    //   304: invokevirtual 227	android/content/ContentResolver:update	(Landroid/net/Uri;Landroid/content/ContentValues;Ljava/lang/String;[Ljava/lang/String;)I
    //   307: pop
    //   308: aload_0
    //   309: getfield 230	pb:d	Lpa;
    //   312: aload_0
    //   313: getfield 29	pb:g	Landroid/net/Uri;
    //   316: invokevirtual 234	pa:a	(Landroid/net/Uri;)V
    //   319: iload 6
    //   321: ifne +11 -> 332
    //   324: aload_0
    //   325: getfield 230	pb:d	Lpa;
    //   328: iconst_1
    //   329: invokevirtual 236	pa:a	(I)V
    //   332: aload_0
    //   333: getfield 230	pb:d	Lpa;
    //   336: invokevirtual 238	pa:a	()I
    //   339: iconst_1
    //   340: if_icmpeq +77 -> 417
    //   343: aload_0
    //   344: getfield 230	pb:d	Lpa;
    //   347: iconst_2
    //   348: invokevirtual 236	pa:a	(I)V
    //   351: ldc 79
    //   353: new 81	java/lang/StringBuilder
    //   356: dup
    //   357: invokespecial 84	java/lang/StringBuilder:<init>	()V
    //   360: ldc -16
    //   362: invokevirtual 90	java/lang/StringBuilder:append	(Ljava/lang/String;)Ljava/lang/StringBuilder;
    //   365: aload_0
    //   366: getfield 242	pb:m	I
    //   369: invokevirtual 245	java/lang/StringBuilder:append	(I)Ljava/lang/StringBuilder;
    //   372: ldc -9
    //   374: invokevirtual 90	java/lang/StringBuilder:append	(Ljava/lang/String;)Ljava/lang/StringBuilder;
    //   377: invokevirtual 94	java/lang/StringBuilder:toString	()Ljava/lang/String;
    //   380: invokestatic 223	android/util/Log:d	(Ljava/lang/String;Ljava/lang/String;)I
    //   383: pop
    //   384: aload_0
    //   385: invokevirtual 249	pb:d	()V
    //   388: return
    //   389: astore 7
    //   391: aload 8
    //   393: invokeinterface 168 1 0
    //   398: aload 7
    //   400: athrow
    //   401: aload 13
    //   403: aload_0
    //   404: getfield 29	pb:g	Landroid/net/Uri;
    //   407: sipush 130
    //   410: iconst_m1
    //   411: invokevirtual 193	zn:b	(Landroid/net/Uri;II)V
    //   414: goto -205 -> 209
    //   417: aload_0
    //   418: getfield 126	pb:b	Landroid/content/Context;
    //   421: new 251	android/content/Intent
    //   424: dup
    //   425: ldc -3
    //   427: new 255	java/io/File
    //   430: dup
    //   431: aload 7
    //   433: invokespecial 258	java/io/File:<init>	(Ljava/lang/String;)V
    //   436: invokestatic 262	android/net/Uri:fromFile	(Ljava/io/File;)Landroid/net/Uri;
    //   439: invokespecial 265	android/content/Intent:<init>	(Ljava/lang/String;Landroid/net/Uri;)V
    //   442: invokevirtual 269	android/content/Context:sendBroadcast	(Landroid/content/Intent;)V
    //   445: ldc 79
    //   447: new 81	java/lang/StringBuilder
    //   450: dup
    //   451: invokespecial 84	java/lang/StringBuilder:<init>	()V
    //   454: ldc -16
    //   456: invokevirtual 90	java/lang/StringBuilder:append	(Ljava/lang/String;)Ljava/lang/StringBuilder;
    //   459: aload_0
    //   460: getfield 242	pb:m	I
    //   463: invokevirtual 245	java/lang/StringBuilder:append	(I)Ljava/lang/StringBuilder;
    //   466: ldc_w 271
    //   469: invokevirtual 90	java/lang/StringBuilder:append	(Ljava/lang/String;)Ljava/lang/StringBuilder;
    //   472: invokevirtual 94	java/lang/StringBuilder:toString	()Ljava/lang/String;
    //   475: invokestatic 223	android/util/Log:d	(Ljava/lang/String;Ljava/lang/String;)I
    //   478: pop
    //   479: goto -95 -> 384
    //   482: aload 7
    //   484: astore 8
    //   486: aload 7
    //   488: astore 9
    //   490: aload 13
    //   492: aload_0
    //   493: getfield 29	pb:g	Landroid/net/Uri;
    //   496: sipush 129
    //   499: aload_0
    //   500: getfield 185	pb:o	I
    //   503: invokevirtual 193	zn:b	(Landroid/net/Uri;II)V
    //   506: aload 7
    //   508: astore 8
    //   510: aload 7
    //   512: astore 9
    //   514: ldc 79
    //   516: new 81	java/lang/StringBuilder
    //   519: dup
    //   520: invokespecial 84	java/lang/StringBuilder:<init>	()V
    //   523: ldc_w 273
    //   526: invokevirtual 90	java/lang/StringBuilder:append	(Ljava/lang/String;)Ljava/lang/StringBuilder;
    //   529: aload_0
    //   530: getfield 54	pb:p	Ljava/lang/String;
    //   533: invokevirtual 90	java/lang/StringBuilder:append	(Ljava/lang/String;)Ljava/lang/StringBuilder;
    //   536: invokevirtual 94	java/lang/StringBuilder:toString	()Ljava/lang/String;
    //   539: invokestatic 182	android/util/Log:v	(Ljava/lang/String;Ljava/lang/String;)I
    //   542: pop
    //   543: aload 7
    //   545: astore 8
    //   547: aload 7
    //   549: astore 9
    //   551: ldc 79
    //   553: new 81	java/lang/StringBuilder
    //   556: dup
    //   557: invokespecial 84	java/lang/StringBuilder:<init>	()V
    //   560: ldc_w 275
    //   563: invokevirtual 90	java/lang/StringBuilder:append	(Ljava/lang/String;)Ljava/lang/StringBuilder;
    //   566: aload_0
    //   567: getfield 242	pb:m	I
    //   570: invokevirtual 245	java/lang/StringBuilder:append	(I)Ljava/lang/StringBuilder;
    //   573: ldc_w 277
    //   576: invokevirtual 90	java/lang/StringBuilder:append	(Ljava/lang/String;)Ljava/lang/StringBuilder;
    //   579: aload_0
    //   580: getfield 54	pb:p	Ljava/lang/String;
    //   583: invokevirtual 90	java/lang/StringBuilder:append	(Ljava/lang/String;)Ljava/lang/StringBuilder;
    //   586: invokevirtual 94	java/lang/StringBuilder:toString	()Ljava/lang/String;
    //   589: invokestatic 223	android/util/Log:d	(Ljava/lang/String;Ljava/lang/String;)I
    //   592: pop
    //   593: aload 7
    //   595: astore 8
    //   597: aload 7
    //   599: astore 9
    //   601: aload_0
    //   602: getfield 54	pb:p	Ljava/lang/String;
    //   605: ldc_w 279
    //   608: invokestatic 285	android/text/TextUtils:split	(Ljava/lang/String;Ljava/lang/String;)[Ljava/lang/String;
    //   611: astore 10
    //   613: aload 7
    //   615: astore 8
    //   617: aload 7
    //   619: astore 9
    //   621: aload 10
    //   623: arraylength
    //   624: iconst_1
    //   625: if_icmpge +20 -> 645
    //   628: aload 7
    //   630: astore 8
    //   632: aload 7
    //   634: astore 9
    //   636: ldc 79
    //   638: ldc_w 287
    //   641: invokestatic 289	android/util/Log:e	(Ljava/lang/String;Ljava/lang/String;)I
    //   644: pop
    //   645: aload 7
    //   647: astore 8
    //   649: aload 7
    //   651: astore 9
    //   653: invokestatic 294	aba:a	()Laba;
    //   656: astore 11
    //   658: aload 10
    //   660: iconst_0
    //   661: aaload
    //   662: astore 12
    //   664: aload 7
    //   666: astore 8
    //   668: aload 7
    //   670: astore 9
    //   672: aload 10
    //   674: arraylength
    //   675: iconst_1
    //   676: if_icmple +648 -> 1324
    //   679: aload 10
    //   681: iconst_1
    //   682: aaload
    //   683: astore 10
    //   685: aload 7
    //   687: astore 8
    //   689: aload 7
    //   691: astore 9
    //   693: aload 11
    //   695: aload 12
    //   697: aload 10
    //   699: aload_0
    //   700: getfield 73	pb:l	Ljava/lang/String;
    //   703: aload 7
    //   705: aload_0
    //   706: getfield 63	pb:q	J
    //   709: invokevirtual 297	aba:a	(Ljava/lang/String;Ljava/lang/String;Ljava/lang/String;Ljava/lang/String;J)Z
    //   712: istore 5
    //   714: aload 7
    //   716: astore 8
    //   718: aload 7
    //   720: astore 9
    //   722: ldc 79
    //   724: new 81	java/lang/StringBuilder
    //   727: dup
    //   728: invokespecial 84	java/lang/StringBuilder:<init>	()V
    //   731: ldc_w 299
    //   734: invokevirtual 90	java/lang/StringBuilder:append	(Ljava/lang/String;)Ljava/lang/StringBuilder;
    //   737: aload_0
    //   738: getfield 242	pb:m	I
    //   741: invokevirtual 245	java/lang/StringBuilder:append	(I)Ljava/lang/StringBuilder;
    //   744: ldc_w 277
    //   747: invokevirtual 90	java/lang/StringBuilder:append	(Ljava/lang/String;)Ljava/lang/StringBuilder;
    //   750: aload_0
    //   751: getfield 54	pb:p	Ljava/lang/String;
    //   754: invokevirtual 90	java/lang/StringBuilder:append	(Ljava/lang/String;)Ljava/lang/StringBuilder;
    //   757: ldc_w 301
    //   760: invokevirtual 90	java/lang/StringBuilder:append	(Ljava/lang/String;)Ljava/lang/StringBuilder;
    //   763: iload 5
    //   765: invokevirtual 304	java/lang/StringBuilder:append	(Z)Ljava/lang/StringBuilder;
    //   768: invokevirtual 94	java/lang/StringBuilder:toString	()Ljava/lang/String;
    //   771: invokestatic 223	android/util/Log:d	(Ljava/lang/String;Ljava/lang/String;)I
    //   774: pop
    //   775: iload 5
    //   777: ifeq +38 -> 815
    //   780: aload 7
    //   782: astore 8
    //   784: aload 7
    //   786: astore 9
    //   788: aload_0
    //   789: getfield 308	pb:i	Ljava/lang/Object;
    //   792: astore 10
    //   794: aload 7
    //   796: astore 8
    //   798: aload 7
    //   800: astore 9
    //   802: aload 10
    //   804: monitorenter
    //   805: aload_0
    //   806: getfield 308	pb:i	Ljava/lang/Object;
    //   809: invokevirtual 313	java/lang/Object:wait	()V
    //   812: aload 10
    //   814: monitorexit
    //   815: aload 7
    //   817: astore 8
    //   819: aload 7
    //   821: astore 9
    //   823: aload_0
    //   824: aload_0
    //   825: getfield 316	pb:j	I
    //   828: invokevirtual 318	pb:c	(I)V
    //   831: aload 7
    //   833: astore 8
    //   835: aload 7
    //   837: astore 9
    //   839: aload_0
    //   840: getfield 230	pb:d	Lpa;
    //   843: invokevirtual 320	pa:c	()[B
    //   846: astore 10
    //   848: aload 10
    //   850: ifnull +1921 -> 2771
    //   853: aload 7
    //   855: astore 8
    //   857: aload 7
    //   859: astore 9
    //   861: new 322	com/meizu/android/mms/pdu/MzPduParser
    //   864: dup
    //   865: aload 10
    //   867: iconst_2
    //   868: invokespecial 325	com/meizu/android/mms/pdu/MzPduParser:<init>	([BI)V
    //   871: invokevirtual 328	com/meizu/android/mms/pdu/MzPduParser:parse	()Lcom/meizu/android/mms/pdu/MzGenericPdu;
    //   874: astore 14
    //   876: aload 14
    //   878: ifnull +22 -> 900
    //   881: aload 7
    //   883: astore 8
    //   885: aload 7
    //   887: astore 9
    //   889: aload 14
    //   891: invokevirtual 333	com/meizu/android/mms/pdu/MzGenericPdu:getMessageType	()I
    //   894: sipush 132
    //   897: if_icmpeq +720 -> 1617
    //   900: aload 7
    //   902: astore 8
    //   904: aload 7
    //   906: astore 9
    //   908: new 81	java/lang/StringBuilder
    //   911: dup
    //   912: invokespecial 84	java/lang/StringBuilder:<init>	()V
    //   915: ldc_w 335
    //   918: invokevirtual 90	java/lang/StringBuilder:append	(Ljava/lang/String;)Ljava/lang/StringBuilder;
    //   921: astore 11
    //   923: aload 14
    //   925: ifnull +684 -> 1609
    //   928: aload 7
    //   930: astore 8
    //   932: aload 7
    //   934: astore 9
    //   936: new 81	java/lang/StringBuilder
    //   939: dup
    //   940: invokespecial 84	java/lang/StringBuilder:<init>	()V
    //   943: ldc_w 337
    //   946: invokevirtual 90	java/lang/StringBuilder:append	(Ljava/lang/String;)Ljava/lang/StringBuilder;
    //   949: aload 14
    //   951: invokevirtual 333	com/meizu/android/mms/pdu/MzGenericPdu:getMessageType	()I
    //   954: invokevirtual 245	java/lang/StringBuilder:append	(I)Ljava/lang/StringBuilder;
    //   957: invokevirtual 94	java/lang/StringBuilder:toString	()Ljava/lang/String;
    //   960: astore 10
    //   962: aload 7
    //   964: astore 8
    //   966: aload 7
    //   968: astore 9
    //   970: ldc 79
    //   972: aload 11
    //   974: aload 10
    //   976: invokevirtual 90	java/lang/StringBuilder:append	(Ljava/lang/String;)Ljava/lang/StringBuilder;
    //   979: invokevirtual 94	java/lang/StringBuilder:toString	()Ljava/lang/String;
    //   982: invokestatic 289	android/util/Log:e	(Ljava/lang/String;Ljava/lang/String;)I
    //   985: pop
    //   986: aload 7
    //   988: astore 8
    //   990: aload 7
    //   992: astore 9
    //   994: aload_0
    //   995: getfield 230	pb:d	Lpa;
    //   998: iconst_2
    //   999: invokevirtual 236	pa:a	(I)V
    //   1002: sipush 132
    //   1005: istore_1
    //   1006: iload_1
    //   1007: istore_2
    //   1008: aload 7
    //   1010: astore 8
    //   1012: ldc 79
    //   1014: new 81	java/lang/StringBuilder
    //   1017: dup
    //   1018: invokespecial 84	java/lang/StringBuilder:<init>	()V
    //   1021: ldc_w 339
    //   1024: invokevirtual 90	java/lang/StringBuilder:append	(Ljava/lang/String;)Ljava/lang/StringBuilder;
    //   1027: iload_1
    //   1028: invokestatic 344	java/lang/Integer:toHexString	(I)Ljava/lang/String;
    //   1031: invokevirtual 90	java/lang/StringBuilder:append	(Ljava/lang/String;)Ljava/lang/StringBuilder;
    //   1034: invokevirtual 94	java/lang/StringBuilder:toString	()Ljava/lang/String;
    //   1037: invokestatic 182	android/util/Log:v	(Ljava/lang/String;Ljava/lang/String;)I
    //   1040: pop
    //   1041: iload_1
    //   1042: tableswitch	default:+1760->2802, 129:+1387->2429, 130:+26->1068, 131:+1404->2446
    //   1068: iload_1
    //   1069: istore_2
    //   1070: aload 7
    //   1072: astore 8
    //   1074: invokestatic 349	aat:b	()Laat$a;
    //   1077: aload_0
    //   1078: getfield 126	pb:b	Landroid/content/Context;
    //   1081: aload_0
    //   1082: getfield 29	pb:g	Landroid/net/Uri;
    //   1085: invokevirtual 354	aat$a:a	(Landroid/content/Context;Landroid/net/Uri;)V
    //   1088: iload_1
    //   1089: istore_2
    //   1090: aload 7
    //   1092: astore 8
    //   1094: aload_0
    //   1095: getfield 126	pb:b	Landroid/content/Context;
    //   1098: invokestatic 357	aat:c	(Landroid/content/Context;)V
    //   1101: iload_1
    //   1102: istore_2
    //   1103: aload 7
    //   1105: astore 8
    //   1107: aload_0
    //   1108: getfield 126	pb:b	Landroid/content/Context;
    //   1111: invokestatic 361	aev:a	(Landroid/content/Context;)V
    //   1114: iload_1
    //   1115: sipush 129
    //   1118: if_icmpeq +125 -> 1243
    //   1121: aload_0
    //   1122: getfield 191	pb:k	I
    //   1125: sipush 9528
    //   1128: if_icmpne +1358 -> 2486
    //   1131: aload 13
    //   1133: aload_0
    //   1134: getfield 29	pb:g	Landroid/net/Uri;
    //   1137: sipush 132
    //   1140: iconst_m1
    //   1141: invokevirtual 193	zn:b	(Landroid/net/Uri;II)V
    //   1144: aload_0
    //   1145: getfield 29	pb:g	Landroid/net/Uri;
    //   1148: ifnull +95 -> 1243
    //   1151: aload_0
    //   1152: invokevirtual 196	pb:m	()J
    //   1155: lconst_0
    //   1156: lcmp
    //   1157: ifle +86 -> 1243
    //   1160: new 198	android/content/ContentValues
    //   1163: dup
    //   1164: iconst_1
    //   1165: invokespecial 201	android/content/ContentValues:<init>	(I)V
    //   1168: astore 8
    //   1170: aload 8
    //   1172: ldc -53
    //   1174: aload_0
    //   1175: invokevirtual 196	pb:m	()J
    //   1178: invokestatic 209	java/lang/Long:valueOf	(J)Ljava/lang/Long;
    //   1181: invokevirtual 213	android/content/ContentValues:put	(Ljava/lang/String;Ljava/lang/Long;)V
    //   1184: ldc 79
    //   1186: new 81	java/lang/StringBuilder
    //   1189: dup
    //   1190: invokespecial 84	java/lang/StringBuilder:<init>	()V
    //   1193: ldc -41
    //   1195: invokevirtual 90	java/lang/StringBuilder:append	(Ljava/lang/String;)Ljava/lang/StringBuilder;
    //   1198: aload_0
    //   1199: invokevirtual 196	pb:m	()J
    //   1202: invokevirtual 218	java/lang/StringBuilder:append	(J)Ljava/lang/StringBuilder;
    //   1205: ldc -36
    //   1207: invokevirtual 90	java/lang/StringBuilder:append	(Ljava/lang/String;)Ljava/lang/StringBuilder;
    //   1210: aload_0
    //   1211: getfield 29	pb:g	Landroid/net/Uri;
    //   1214: invokevirtual 178	java/lang/StringBuilder:append	(Ljava/lang/Object;)Ljava/lang/StringBuilder;
    //   1217: invokevirtual 94	java/lang/StringBuilder:toString	()Ljava/lang/String;
    //   1220: invokestatic 223	android/util/Log:d	(Ljava/lang/String;Ljava/lang/String;)I
    //   1223: pop
    //   1224: aload_0
    //   1225: getfield 126	pb:b	Landroid/content/Context;
    //   1228: invokevirtual 132	android/content/Context:getContentResolver	()Landroid/content/ContentResolver;
    //   1231: aload_0
    //   1232: getfield 29	pb:g	Landroid/net/Uri;
    //   1235: aload 8
    //   1237: aconst_null
    //   1238: aconst_null
    //   1239: invokevirtual 227	android/content/ContentResolver:update	(Landroid/net/Uri;Landroid/content/ContentValues;Ljava/lang/String;[Ljava/lang/String;)I
    //   1242: pop
    //   1243: aload_0
    //   1244: getfield 230	pb:d	Lpa;
    //   1247: aload_0
    //   1248: getfield 29	pb:g	Landroid/net/Uri;
    //   1251: invokevirtual 234	pa:a	(Landroid/net/Uri;)V
    //   1254: iload 6
    //   1256: ifne +11 -> 1267
    //   1259: aload_0
    //   1260: getfield 230	pb:d	Lpa;
    //   1263: iconst_1
    //   1264: invokevirtual 236	pa:a	(I)V
    //   1267: aload_0
    //   1268: getfield 230	pb:d	Lpa;
    //   1271: invokevirtual 238	pa:a	()I
    //   1274: iconst_1
    //   1275: if_icmpeq +1227 -> 2502
    //   1278: aload_0
    //   1279: getfield 230	pb:d	Lpa;
    //   1282: iconst_2
    //   1283: invokevirtual 236	pa:a	(I)V
    //   1286: ldc 79
    //   1288: new 81	java/lang/StringBuilder
    //   1291: dup
    //   1292: invokespecial 84	java/lang/StringBuilder:<init>	()V
    //   1295: ldc -16
    //   1297: invokevirtual 90	java/lang/StringBuilder:append	(Ljava/lang/String;)Ljava/lang/StringBuilder;
    //   1300: aload_0
    //   1301: getfield 242	pb:m	I
    //   1304: invokevirtual 245	java/lang/StringBuilder:append	(I)Ljava/lang/StringBuilder;
    //   1307: ldc -9
    //   1309: invokevirtual 90	java/lang/StringBuilder:append	(Ljava/lang/String;)Ljava/lang/StringBuilder;
    //   1312: invokevirtual 94	java/lang/StringBuilder:toString	()Ljava/lang/String;
    //   1315: invokestatic 223	android/util/Log:d	(Ljava/lang/String;Ljava/lang/String;)I
    //   1318: pop
    //   1319: aload_0
    //   1320: invokevirtual 249	pb:d	()V
    //   1323: return
    //   1324: ldc_w 363
    //   1327: astore 10
    //   1329: goto -644 -> 685
    //   1332: astore 8
    //   1334: aload 7
    //   1336: astore 8
    //   1338: aload 7
    //   1340: astore 9
    //   1342: aload_0
    //   1343: getfield 230	pb:d	Lpa;
    //   1346: iconst_2
    //   1347: invokevirtual 236	pa:a	(I)V
    //   1350: iconst_0
    //   1351: istore 5
    //   1353: goto -639 -> 714
    //   1356: astore 11
    //   1358: aload 10
    //   1360: monitorexit
    //   1361: aload 7
    //   1363: astore 8
    //   1365: aload 7
    //   1367: astore 9
    //   1369: aload 11
    //   1371: athrow
    //   1372: astore 9
    //   1374: sipush 131
    //   1377: istore_1
    //   1378: aload 8
    //   1380: astore 7
    //   1382: iload_1
    //   1383: istore_2
    //   1384: aload 7
    //   1386: astore 8
    //   1388: ldc 79
    //   1390: aload 9
    //   1392: invokestatic 367	android/util/Log:getStackTraceString	(Ljava/lang/Throwable;)Ljava/lang/String;
    //   1395: invokestatic 289	android/util/Log:e	(Ljava/lang/String;Ljava/lang/String;)I
    //   1398: pop
    //   1399: iload_1
    //   1400: sipush 129
    //   1403: if_icmpeq +125 -> 1528
    //   1406: aload_0
    //   1407: getfield 191	pb:k	I
    //   1410: sipush 9528
    //   1413: if_icmpne +1154 -> 2567
    //   1416: aload 13
    //   1418: aload_0
    //   1419: getfield 29	pb:g	Landroid/net/Uri;
    //   1422: sipush 132
    //   1425: iconst_m1
    //   1426: invokevirtual 193	zn:b	(Landroid/net/Uri;II)V
    //   1429: aload_0
    //   1430: getfield 29	pb:g	Landroid/net/Uri;
    //   1433: ifnull +95 -> 1528
    //   1436: aload_0
    //   1437: invokevirtual 196	pb:m	()J
    //   1440: lconst_0
    //   1441: lcmp
    //   1442: ifle +86 -> 1528
    //   1445: new 198	android/content/ContentValues
    //   1448: dup
    //   1449: iconst_1
    //   1450: invokespecial 201	android/content/ContentValues:<init>	(I)V
    //   1453: astore 8
    //   1455: aload 8
    //   1457: ldc -53
    //   1459: aload_0
    //   1460: invokevirtual 196	pb:m	()J
    //   1463: invokestatic 209	java/lang/Long:valueOf	(J)Ljava/lang/Long;
    //   1466: invokevirtual 213	android/content/ContentValues:put	(Ljava/lang/String;Ljava/lang/Long;)V
    //   1469: ldc 79
    //   1471: new 81	java/lang/StringBuilder
    //   1474: dup
    //   1475: invokespecial 84	java/lang/StringBuilder:<init>	()V
    //   1478: ldc -41
    //   1480: invokevirtual 90	java/lang/StringBuilder:append	(Ljava/lang/String;)Ljava/lang/StringBuilder;
    //   1483: aload_0
    //   1484: invokevirtual 196	pb:m	()J
    //   1487: invokevirtual 218	java/lang/StringBuilder:append	(J)Ljava/lang/StringBuilder;
    //   1490: ldc -36
    //   1492: invokevirtual 90	java/lang/StringBuilder:append	(Ljava/lang/String;)Ljava/lang/StringBuilder;
    //   1495: aload_0
    //   1496: getfield 29	pb:g	Landroid/net/Uri;
    //   1499: invokevirtual 178	java/lang/StringBuilder:append	(Ljava/lang/Object;)Ljava/lang/StringBuilder;
    //   1502: invokevirtual 94	java/lang/StringBuilder:toString	()Ljava/lang/String;
    //   1505: invokestatic 223	android/util/Log:d	(Ljava/lang/String;Ljava/lang/String;)I
    //   1508: pop
    //   1509: aload_0
    //   1510: getfield 126	pb:b	Landroid/content/Context;
    //   1513: invokevirtual 132	android/content/Context:getContentResolver	()Landroid/content/ContentResolver;
    //   1516: aload_0
    //   1517: getfield 29	pb:g	Landroid/net/Uri;
    //   1520: aload 8
    //   1522: aconst_null
    //   1523: aconst_null
    //   1524: invokevirtual 227	android/content/ContentResolver:update	(Landroid/net/Uri;Landroid/content/ContentValues;Ljava/lang/String;[Ljava/lang/String;)I
    //   1527: pop
    //   1528: aload_0
    //   1529: getfield 230	pb:d	Lpa;
    //   1532: aload_0
    //   1533: getfield 29	pb:g	Landroid/net/Uri;
    //   1536: invokevirtual 234	pa:a	(Landroid/net/Uri;)V
    //   1539: iload 6
    //   1541: ifne +11 -> 1552
    //   1544: aload_0
    //   1545: getfield 230	pb:d	Lpa;
    //   1548: iconst_1
    //   1549: invokevirtual 236	pa:a	(I)V
    //   1552: aload_0
    //   1553: getfield 230	pb:d	Lpa;
    //   1556: invokevirtual 238	pa:a	()I
    //   1559: iconst_1
    //   1560: if_icmpeq +1023 -> 2583
    //   1563: aload_0
    //   1564: getfield 230	pb:d	Lpa;
    //   1567: iconst_2
    //   1568: invokevirtual 236	pa:a	(I)V
    //   1571: ldc 79
    //   1573: new 81	java/lang/StringBuilder
    //   1576: dup
    //   1577: invokespecial 84	java/lang/StringBuilder:<init>	()V
    //   1580: ldc -16
    //   1582: invokevirtual 90	java/lang/StringBuilder:append	(Ljava/lang/String;)Ljava/lang/StringBuilder;
    //   1585: aload_0
    //   1586: getfield 242	pb:m	I
    //   1589: invokevirtual 245	java/lang/StringBuilder:append	(I)Ljava/lang/StringBuilder;
    //   1592: ldc -9
    //   1594: invokevirtual 90	java/lang/StringBuilder:append	(Ljava/lang/String;)Ljava/lang/StringBuilder;
    //   1597: invokevirtual 94	java/lang/StringBuilder:toString	()Ljava/lang/String;
    //   1600: invokestatic 223	android/util/Log:d	(Ljava/lang/String;Ljava/lang/String;)I
    //   1603: pop
    //   1604: aload_0
    //   1605: invokevirtual 249	pb:d	()V
    //   1608: return
    //   1609: ldc_w 369
    //   1612: astore 10
    //   1614: goto -652 -> 962
    //   1617: aload 7
    //   1619: astore 8
    //   1621: aload 7
    //   1623: astore 9
    //   1625: aload_0
    //   1626: getfield 126	pb:b	Landroid/content/Context;
    //   1629: invokestatic 35	com/meizu/android/mms/pdu/MzPduPersister:getPduPersister	(Landroid/content/Context;)Lcom/meizu/android/mms/pdu/MzPduPersister;
    //   1632: astore 15
    //   1634: ldc_w 371
    //   1637: astore 11
    //   1639: ldc_w 363
    //   1642: astore 12
    //   1644: iconst_m1
    //   1645: istore_1
    //   1646: aload 7
    //   1648: astore 8
    //   1650: aload 7
    //   1652: astore 9
    //   1654: aload_0
    //   1655: getfield 126	pb:b	Landroid/content/Context;
    //   1658: invokevirtual 132	android/content/Context:getContentResolver	()Landroid/content/ContentResolver;
    //   1661: aload_0
    //   1662: getfield 29	pb:g	Landroid/net/Uri;
    //   1665: bipush 6
    //   1667: anewarray 45	java/lang/String
    //   1670: dup
    //   1671: iconst_0
    //   1672: ldc -122
    //   1674: aastore
    //   1675: dup
    //   1676: iconst_1
    //   1677: ldc -118
    //   1679: aastore
    //   1680: dup
    //   1681: iconst_2
    //   1682: ldc -120
    //   1684: aastore
    //   1685: dup
    //   1686: iconst_3
    //   1687: ldc_w 373
    //   1690: aastore
    //   1691: dup
    //   1692: iconst_4
    //   1693: ldc_w 375
    //   1696: aastore
    //   1697: dup
    //   1698: iconst_5
    //   1699: ldc_w 377
    //   1702: aastore
    //   1703: aconst_null
    //   1704: aconst_null
    //   1705: aconst_null
    //   1706: invokevirtual 144	android/content/ContentResolver:query	(Landroid/net/Uri;[Ljava/lang/String;Ljava/lang/String;[Ljava/lang/String;Ljava/lang/String;)Landroid/database/Cursor;
    //   1709: astore 16
    //   1711: aload 16
    //   1713: ifnull +1049 -> 2762
    //   1716: aload 7
    //   1718: astore 10
    //   1720: aload 16
    //   1722: invokeinterface 149 1 0
    //   1727: ifle +1026 -> 2753
    //   1730: aload 7
    //   1732: astore 10
    //   1734: aload 16
    //   1736: invokeinterface 153 1 0
    //   1741: ifeq +1012 -> 2753
    //   1744: aload 7
    //   1746: astore 10
    //   1748: aload 16
    //   1750: aload 16
    //   1752: ldc -118
    //   1754: invokeinterface 157 2 0
    //   1759: invokeinterface 165 2 0
    //   1764: lstore_3
    //   1765: aload 7
    //   1767: astore 10
    //   1769: aload 16
    //   1771: aload 16
    //   1773: ldc -120
    //   1775: invokeinterface 157 2 0
    //   1780: invokeinterface 161 2 0
    //   1785: astore 7
    //   1787: aload 7
    //   1789: astore 10
    //   1791: aload 16
    //   1793: aload 16
    //   1795: ldc_w 373
    //   1798: invokeinterface 157 2 0
    //   1803: invokeinterface 161 2 0
    //   1808: astore 11
    //   1810: aload 7
    //   1812: astore 10
    //   1814: aload 16
    //   1816: aload 16
    //   1818: ldc_w 375
    //   1821: invokeinterface 157 2 0
    //   1826: invokeinterface 161 2 0
    //   1831: astore 8
    //   1833: aload 7
    //   1835: astore 10
    //   1837: aload 16
    //   1839: aload 16
    //   1841: ldc_w 377
    //   1844: invokeinterface 157 2 0
    //   1849: invokeinterface 381 2 0
    //   1854: istore_1
    //   1855: aload 8
    //   1857: astore 10
    //   1859: aload 7
    //   1861: astore 8
    //   1863: aload 7
    //   1865: astore 9
    //   1867: aload 16
    //   1869: invokeinterface 168 1 0
    //   1874: new 198	android/content/ContentValues
    //   1877: dup
    //   1878: invokespecial 382	android/content/ContentValues:<init>	()V
    //   1881: astore 8
    //   1883: aload 8
    //   1885: ldc -118
    //   1887: lload_3
    //   1888: invokestatic 209	java/lang/Long:valueOf	(J)Ljava/lang/Long;
    //   1891: invokevirtual 213	android/content/ContentValues:put	(Ljava/lang/String;Ljava/lang/Long;)V
    //   1894: aload 8
    //   1896: ldc -120
    //   1898: aload 7
    //   1900: invokevirtual 385	android/content/ContentValues:put	(Ljava/lang/String;Ljava/lang/String;)V
    //   1903: aload 8
    //   1905: ldc_w 387
    //   1908: iconst_2
    //   1909: invokestatic 390	java/lang/Integer:valueOf	(I)Ljava/lang/Integer;
    //   1912: invokevirtual 393	android/content/ContentValues:put	(Ljava/lang/String;Ljava/lang/Integer;)V
    //   1915: aload 8
    //   1917: ldc_w 373
    //   1920: aload 11
    //   1922: invokevirtual 385	android/content/ContentValues:put	(Ljava/lang/String;Ljava/lang/String;)V
    //   1925: aload 8
    //   1927: ldc_w 395
    //   1930: aload_0
    //   1931: getfield 54	pb:p	Ljava/lang/String;
    //   1934: invokevirtual 385	android/content/ContentValues:put	(Ljava/lang/String;Ljava/lang/String;)V
    //   1937: aload 8
    //   1939: ldc -53
    //   1941: aload_0
    //   1942: invokevirtual 196	pb:m	()J
    //   1945: invokestatic 209	java/lang/Long:valueOf	(J)Ljava/lang/Long;
    //   1948: invokevirtual 213	android/content/ContentValues:put	(Ljava/lang/String;Ljava/lang/Long;)V
    //   1951: aload 8
    //   1953: ldc_w 397
    //   1956: invokestatic 402	java/lang/System:currentTimeMillis	()J
    //   1959: invokestatic 209	java/lang/Long:valueOf	(J)Ljava/lang/Long;
    //   1962: invokevirtual 213	android/content/ContentValues:put	(Ljava/lang/String;Ljava/lang/Long;)V
    //   1965: aload 8
    //   1967: ldc_w 375
    //   1970: aload 10
    //   1972: invokevirtual 385	android/content/ContentValues:put	(Ljava/lang/String;Ljava/lang/String;)V
    //   1975: aload 8
    //   1977: ldc_w 377
    //   1980: iload_1
    //   1981: invokestatic 390	java/lang/Integer:valueOf	(I)Ljava/lang/Integer;
    //   1984: invokevirtual 393	android/content/ContentValues:put	(Ljava/lang/String;Ljava/lang/Integer;)V
    //   1987: ldc 79
    //   1989: new 81	java/lang/StringBuilder
    //   1992: dup
    //   1993: invokespecial 84	java/lang/StringBuilder:<init>	()V
    //   1996: ldc_w 404
    //   1999: invokevirtual 90	java/lang/StringBuilder:append	(Ljava/lang/String;)Ljava/lang/StringBuilder;
    //   2002: aload_0
    //   2003: invokevirtual 196	pb:m	()J
    //   2006: invokevirtual 218	java/lang/StringBuilder:append	(J)Ljava/lang/StringBuilder;
    //   2009: ldc_w 406
    //   2012: invokevirtual 90	java/lang/StringBuilder:append	(Ljava/lang/String;)Ljava/lang/StringBuilder;
    //   2015: lload_3
    //   2016: invokevirtual 218	java/lang/StringBuilder:append	(J)Ljava/lang/StringBuilder;
    //   2019: invokevirtual 94	java/lang/StringBuilder:toString	()Ljava/lang/String;
    //   2022: invokestatic 223	android/util/Log:d	(Ljava/lang/String;Ljava/lang/String;)I
    //   2025: pop
    //   2026: aload_0
    //   2027: getfield 126	pb:b	Landroid/content/Context;
    //   2030: invokevirtual 132	android/content/Context:getContentResolver	()Landroid/content/ContentResolver;
    //   2033: aload_0
    //   2034: getfield 29	pb:g	Landroid/net/Uri;
    //   2037: new 81	java/lang/StringBuilder
    //   2040: dup
    //   2041: invokespecial 84	java/lang/StringBuilder:<init>	()V
    //   2044: ldc_w 408
    //   2047: invokevirtual 90	java/lang/StringBuilder:append	(Ljava/lang/String;)Ljava/lang/StringBuilder;
    //   2050: aload_0
    //   2051: getfield 54	pb:p	Ljava/lang/String;
    //   2054: invokevirtual 90	java/lang/StringBuilder:append	(Ljava/lang/String;)Ljava/lang/StringBuilder;
    //   2057: ldc_w 410
    //   2060: invokevirtual 90	java/lang/StringBuilder:append	(Ljava/lang/String;)Ljava/lang/StringBuilder;
    //   2063: invokevirtual 94	java/lang/StringBuilder:toString	()Ljava/lang/String;
    //   2066: aconst_null
    //   2067: invokevirtual 414	android/content/ContentResolver:delete	(Landroid/net/Uri;Ljava/lang/String;[Ljava/lang/String;)I
    //   2070: pop
    //   2071: aload 15
    //   2073: aload 14
    //   2075: getstatic 419	android/provider/Telephony$Mms$Inbox:CONTENT_URI	Landroid/net/Uri;
    //   2078: iconst_1
    //   2079: aload_0
    //   2080: getfield 126	pb:b	Landroid/content/Context;
    //   2083: invokestatic 424	com/android/mms/ui/MessagingPreferenceActivity:b	(Landroid/content/Context;)Z
    //   2086: aconst_null
    //   2087: aload_0
    //   2088: getfield 67	pb:h	I
    //   2091: aload 8
    //   2093: invokevirtual 428	com/meizu/android/mms/pdu/MzPduPersister:persist	(Lcom/meizu/android/mms/pdu/MzGenericPdu;Landroid/net/Uri;ZZLjava/util/HashMap;ILandroid/content/ContentValues;)Landroid/net/Uri;
    //   2096: astore 8
    //   2098: ldc 79
    //   2100: new 81	java/lang/StringBuilder
    //   2103: dup
    //   2104: invokespecial 84	java/lang/StringBuilder:<init>	()V
    //   2107: ldc_w 430
    //   2110: invokevirtual 90	java/lang/StringBuilder:append	(Ljava/lang/String;)Ljava/lang/StringBuilder;
    //   2113: aload 8
    //   2115: invokevirtual 178	java/lang/StringBuilder:append	(Ljava/lang/Object;)Ljava/lang/StringBuilder;
    //   2118: invokevirtual 94	java/lang/StringBuilder:toString	()Ljava/lang/String;
    //   2121: invokestatic 182	android/util/Log:v	(Ljava/lang/String;Ljava/lang/String;)I
    //   2124: pop
    //   2125: aload_0
    //   2126: getfield 126	pb:b	Landroid/content/Context;
    //   2129: invokevirtual 132	android/content/Context:getContentResolver	()Landroid/content/ContentResolver;
    //   2132: getstatic 435	android/provider/Telephony$Threads:OBSOLETE_THREADS_URI	Landroid/net/Uri;
    //   2135: aconst_null
    //   2136: aconst_null
    //   2137: invokevirtual 414	android/content/ContentResolver:delete	(Landroid/net/Uri;Ljava/lang/String;[Ljava/lang/String;)I
    //   2140: pop
    //   2141: ldc 79
    //   2143: new 81	java/lang/StringBuilder
    //   2146: dup
    //   2147: invokespecial 84	java/lang/StringBuilder:<init>	()V
    //   2150: ldc_w 430
    //   2153: invokevirtual 90	java/lang/StringBuilder:append	(Ljava/lang/String;)Ljava/lang/StringBuilder;
    //   2156: aload 8
    //   2158: invokevirtual 178	java/lang/StringBuilder:append	(Ljava/lang/Object;)Ljava/lang/StringBuilder;
    //   2161: invokevirtual 94	java/lang/StringBuilder:toString	()Ljava/lang/String;
    //   2164: invokestatic 182	android/util/Log:v	(Ljava/lang/String;Ljava/lang/String;)I
    //   2167: pop
    //   2168: aload_0
    //   2169: aload 8
    //   2171: putfield 29	pb:g	Landroid/net/Uri;
    //   2174: sipush 129
    //   2177: istore_1
    //   2178: goto -1172 -> 1006
    //   2181: astore 7
    //   2183: aload 10
    //   2185: astore 8
    //   2187: aload 10
    //   2189: astore 9
    //   2191: aload 16
    //   2193: invokeinterface 168 1 0
    //   2198: aload 10
    //   2200: astore 8
    //   2202: aload 10
    //   2204: astore 9
    //   2206: aload 7
    //   2208: athrow
    //   2209: astore 7
    //   2211: iload_2
    //   2212: istore_1
    //   2213: aload 9
    //   2215: astore 8
    //   2217: iload_1
    //   2218: sipush 129
    //   2221: if_icmpeq +125 -> 2346
    //   2224: aload_0
    //   2225: getfield 191	pb:k	I
    //   2228: sipush 9528
    //   2231: if_icmpne +417 -> 2648
    //   2234: aload 13
    //   2236: aload_0
    //   2237: getfield 29	pb:g	Landroid/net/Uri;
    //   2240: sipush 132
    //   2243: iconst_m1
    //   2244: invokevirtual 193	zn:b	(Landroid/net/Uri;II)V
    //   2247: aload_0
    //   2248: getfield 29	pb:g	Landroid/net/Uri;
    //   2251: ifnull +95 -> 2346
    //   2254: aload_0
    //   2255: invokevirtual 196	pb:m	()J
    //   2258: lconst_0
    //   2259: lcmp
    //   2260: ifle +86 -> 2346
    //   2263: new 198	android/content/ContentValues
    //   2266: dup
    //   2267: iconst_1
    //   2268: invokespecial 201	android/content/ContentValues:<init>	(I)V
    //   2271: astore 9
    //   2273: aload 9
    //   2275: ldc -53
    //   2277: aload_0
    //   2278: invokevirtual 196	pb:m	()J
    //   2281: invokestatic 209	java/lang/Long:valueOf	(J)Ljava/lang/Long;
    //   2284: invokevirtual 213	android/content/ContentValues:put	(Ljava/lang/String;Ljava/lang/Long;)V
    //   2287: ldc 79
    //   2289: new 81	java/lang/StringBuilder
    //   2292: dup
    //   2293: invokespecial 84	java/lang/StringBuilder:<init>	()V
    //   2296: ldc -41
    //   2298: invokevirtual 90	java/lang/StringBuilder:append	(Ljava/lang/String;)Ljava/lang/StringBuilder;
    //   2301: aload_0
    //   2302: invokevirtual 196	pb:m	()J
    //   2305: invokevirtual 218	java/lang/StringBuilder:append	(J)Ljava/lang/StringBuilder;
    //   2308: ldc -36
    //   2310: invokevirtual 90	java/lang/StringBuilder:append	(Ljava/lang/String;)Ljava/lang/StringBuilder;
    //   2313: aload_0
    //   2314: getfield 29	pb:g	Landroid/net/Uri;
    //   2317: invokevirtual 178	java/lang/StringBuilder:append	(Ljava/lang/Object;)Ljava/lang/StringBuilder;
    //   2320: invokevirtual 94	java/lang/StringBuilder:toString	()Ljava/lang/String;
    //   2323: invokestatic 223	android/util/Log:d	(Ljava/lang/String;Ljava/lang/String;)I
    //   2326: pop
    //   2327: aload_0
    //   2328: getfield 126	pb:b	Landroid/content/Context;
    //   2331: invokevirtual 132	android/content/Context:getContentResolver	()Landroid/content/ContentResolver;
    //   2334: aload_0
    //   2335: getfield 29	pb:g	Landroid/net/Uri;
    //   2338: aload 9
    //   2340: aconst_null
    //   2341: aconst_null
    //   2342: invokevirtual 227	android/content/ContentResolver:update	(Landroid/net/Uri;Landroid/content/ContentValues;Ljava/lang/String;[Ljava/lang/String;)I
    //   2345: pop
    //   2346: aload_0
    //   2347: getfield 230	pb:d	Lpa;
    //   2350: aload_0
    //   2351: getfield 29	pb:g	Landroid/net/Uri;
    //   2354: invokevirtual 234	pa:a	(Landroid/net/Uri;)V
    //   2357: iload 6
    //   2359: ifne +11 -> 2370
    //   2362: aload_0
    //   2363: getfield 230	pb:d	Lpa;
    //   2366: iconst_1
    //   2367: invokevirtual 236	pa:a	(I)V
    //   2370: aload_0
    //   2371: getfield 230	pb:d	Lpa;
    //   2374: invokevirtual 238	pa:a	()I
    //   2377: iconst_1
    //   2378: if_icmpeq +286 -> 2664
    //   2381: aload_0
    //   2382: getfield 230	pb:d	Lpa;
    //   2385: iconst_2
    //   2386: invokevirtual 236	pa:a	(I)V
    //   2389: ldc 79
    //   2391: new 81	java/lang/StringBuilder
    //   2394: dup
    //   2395: invokespecial 84	java/lang/StringBuilder:<init>	()V
    //   2398: ldc -16
    //   2400: invokevirtual 90	java/lang/StringBuilder:append	(Ljava/lang/String;)Ljava/lang/StringBuilder;
    //   2403: aload_0
    //   2404: getfield 242	pb:m	I
    //   2407: invokevirtual 245	java/lang/StringBuilder:append	(I)Ljava/lang/StringBuilder;
    //   2410: ldc -9
    //   2412: invokevirtual 90	java/lang/StringBuilder:append	(Ljava/lang/String;)Ljava/lang/StringBuilder;
    //   2415: invokevirtual 94	java/lang/StringBuilder:toString	()Ljava/lang/String;
    //   2418: invokestatic 223	android/util/Log:d	(Ljava/lang/String;Ljava/lang/String;)I
    //   2421: pop
    //   2422: aload_0
    //   2423: invokevirtual 249	pb:d	()V
    //   2426: aload 7
    //   2428: athrow
    //   2429: iload_1
    //   2430: istore_2
    //   2431: aload 7
    //   2433: astore 8
    //   2435: aload_0
    //   2436: getfield 230	pb:d	Lpa;
    //   2439: iconst_1
    //   2440: invokevirtual 236	pa:a	(I)V
    //   2443: goto -1375 -> 1068
    //   2446: iload_1
    //   2447: istore_2
    //   2448: aload 7
    //   2450: astore 8
    //   2452: aload_0
    //   2453: getfield 230	pb:d	Lpa;
    //   2456: invokevirtual 238	pa:a	()I
    //   2459: ifne -1391 -> 1068
    //   2462: iload_1
    //   2463: istore_2
    //   2464: aload 7
    //   2466: astore 8
    //   2468: aload_0
    //   2469: getfield 230	pb:d	Lpa;
    //   2472: iconst_2
    //   2473: invokevirtual 236	pa:a	(I)V
    //   2476: goto -1408 -> 1068
    //   2479: astore 7
    //   2481: iload_2
    //   2482: istore_1
    //   2483: goto -266 -> 2217
    //   2486: aload 13
    //   2488: aload_0
    //   2489: getfield 29	pb:g	Landroid/net/Uri;
    //   2492: sipush 130
    //   2495: iconst_m1
    //   2496: invokevirtual 193	zn:b	(Landroid/net/Uri;II)V
    //   2499: goto -1355 -> 1144
    //   2502: aload_0
    //   2503: getfield 126	pb:b	Landroid/content/Context;
    //   2506: new 251	android/content/Intent
    //   2509: dup
    //   2510: ldc -3
    //   2512: new 255	java/io/File
    //   2515: dup
    //   2516: aload 7
    //   2518: invokespecial 258	java/io/File:<init>	(Ljava/lang/String;)V
    //   2521: invokestatic 262	android/net/Uri:fromFile	(Ljava/io/File;)Landroid/net/Uri;
    //   2524: invokespecial 265	android/content/Intent:<init>	(Ljava/lang/String;Landroid/net/Uri;)V
    //   2527: invokevirtual 269	android/content/Context:sendBroadcast	(Landroid/content/Intent;)V
    //   2530: ldc 79
    //   2532: new 81	java/lang/StringBuilder
    //   2535: dup
    //   2536: invokespecial 84	java/lang/StringBuilder:<init>	()V
    //   2539: ldc -16
    //   2541: invokevirtual 90	java/lang/StringBuilder:append	(Ljava/lang/String;)Ljava/lang/StringBuilder;
    //   2544: aload_0
    //   2545: getfield 242	pb:m	I
    //   2548: invokevirtual 245	java/lang/StringBuilder:append	(I)Ljava/lang/StringBuilder;
    //   2551: ldc_w 271
    //   2554: invokevirtual 90	java/lang/StringBuilder:append	(Ljava/lang/String;)Ljava/lang/StringBuilder;
    //   2557: invokevirtual 94	java/lang/StringBuilder:toString	()Ljava/lang/String;
    //   2560: invokestatic 223	android/util/Log:d	(Ljava/lang/String;Ljava/lang/String;)I
    //   2563: pop
    //   2564: goto -1245 -> 1319
    //   2567: aload 13
    //   2569: aload_0
    //   2570: getfield 29	pb:g	Landroid/net/Uri;
    //   2573: sipush 130
    //   2576: iconst_m1
    //   2577: invokevirtual 193	zn:b	(Landroid/net/Uri;II)V
    //   2580: goto -1151 -> 1429
    //   2583: aload_0
    //   2584: getfield 126	pb:b	Landroid/content/Context;
    //   2587: new 251	android/content/Intent
    //   2590: dup
    //   2591: ldc -3
    //   2593: new 255	java/io/File
    //   2596: dup
    //   2597: aload 7
    //   2599: invokespecial 258	java/io/File:<init>	(Ljava/lang/String;)V
    //   2602: invokestatic 262	android/net/Uri:fromFile	(Ljava/io/File;)Landroid/net/Uri;
    //   2605: invokespecial 265	android/content/Intent:<init>	(Ljava/lang/String;Landroid/net/Uri;)V
    //   2608: invokevirtual 269	android/content/Context:sendBroadcast	(Landroid/content/Intent;)V
    //   2611: ldc 79
    //   2613: new 81	java/lang/StringBuilder
    //   2616: dup
    //   2617: invokespecial 84	java/lang/StringBuilder:<init>	()V
    //   2620: ldc -16
    //   2622: invokevirtual 90	java/lang/StringBuilder:append	(Ljava/lang/String;)Ljava/lang/StringBuilder;
    //   2625: aload_0
    //   2626: getfield 242	pb:m	I
    //   2629: invokevirtual 245	java/lang/StringBuilder:append	(I)Ljava/lang/StringBuilder;
    //   2632: ldc_w 271
    //   2635: invokevirtual 90	java/lang/StringBuilder:append	(Ljava/lang/String;)Ljava/lang/StringBuilder;
    //   2638: invokevirtual 94	java/lang/StringBuilder:toString	()Ljava/lang/String;
    //   2641: invokestatic 223	android/util/Log:d	(Ljava/lang/String;Ljava/lang/String;)I
    //   2644: pop
    //   2645: goto -1041 -> 1604
    //   2648: aload 13
    //   2650: aload_0
    //   2651: getfield 29	pb:g	Landroid/net/Uri;
    //   2654: sipush 130
    //   2657: iconst_m1
    //   2658: invokevirtual 193	zn:b	(Landroid/net/Uri;II)V
    //   2661: goto -414 -> 2247
    //   2664: aload_0
    //   2665: getfield 126	pb:b	Landroid/content/Context;
    //   2668: new 251	android/content/Intent
    //   2671: dup
    //   2672: ldc -3
    //   2674: new 255	java/io/File
    //   2677: dup
    //   2678: aload 8
    //   2680: invokespecial 258	java/io/File:<init>	(Ljava/lang/String;)V
    //   2683: invokestatic 262	android/net/Uri:fromFile	(Ljava/io/File;)Landroid/net/Uri;
    //   2686: invokespecial 265	android/content/Intent:<init>	(Ljava/lang/String;Landroid/net/Uri;)V
    //   2689: invokevirtual 269	android/content/Context:sendBroadcast	(Landroid/content/Intent;)V
    //   2692: ldc 79
    //   2694: new 81	java/lang/StringBuilder
    //   2697: dup
    //   2698: invokespecial 84	java/lang/StringBuilder:<init>	()V
    //   2701: ldc -16
    //   2703: invokevirtual 90	java/lang/StringBuilder:append	(Ljava/lang/String;)Ljava/lang/StringBuilder;
    //   2706: aload_0
    //   2707: getfield 242	pb:m	I
    //   2710: invokevirtual 245	java/lang/StringBuilder:append	(I)Ljava/lang/StringBuilder;
    //   2713: ldc_w 271
    //   2716: invokevirtual 90	java/lang/StringBuilder:append	(Ljava/lang/String;)Ljava/lang/StringBuilder;
    //   2719: invokevirtual 94	java/lang/StringBuilder:toString	()Ljava/lang/String;
    //   2722: invokestatic 223	android/util/Log:d	(Ljava/lang/String;Ljava/lang/String;)I
    //   2725: pop
    //   2726: goto -304 -> 2422
    //   2729: astore 9
    //   2731: aload 7
    //   2733: astore 8
    //   2735: aload 9
    //   2737: astore 7
    //   2739: iload_2
    //   2740: istore_1
    //   2741: goto -524 -> 2217
    //   2744: astore 9
    //   2746: sipush 131
    //   2749: istore_1
    //   2750: goto -1368 -> 1382
    //   2753: lconst_0
    //   2754: lstore_3
    //   2755: aload 12
    //   2757: astore 10
    //   2759: goto -900 -> 1859
    //   2762: lconst_0
    //   2763: lstore_3
    //   2764: aload 12
    //   2766: astore 10
    //   2768: goto -894 -> 1874
    //   2771: sipush 131
    //   2774: istore_1
    //   2775: goto -1769 -> 1006
    //   2778: ldc2_w 436
    //   2781: lstore_3
    //   2782: ldc_w 363
    //   2785: astore 7
    //   2787: goto -2684 -> 103
    //   2790: ldc2_w 436
    //   2793: lstore_3
    //   2794: ldc_w 363
    //   2797: astore 7
    //   2799: goto -2689 -> 110
    //   2802: goto -1734 -> 1068
    //   2805: astore 9
    //   2807: goto -1425 -> 1382
    // Local variable table:
    //   start	length	slot	name	signature
    //   0	2810	0	this	pb
    //   1005	1770	1	i	int
    //   123	2617	2	j	int
    //   102	2692	3	l	long
    //   712	640	5	bool1	boolean
    //   118	2240	6	bool2	boolean
    //   84	83	7	str1	String
    //   389	977	7	str2	String
    //   1380	519	7	localObject1	Object
    //   2181	26	7	localObject2	Object
    //   2209	256	7	localObject3	Object
    //   2479	253	7	str3	String
    //   2737	61	7	localObject4	Object
    //   41	1195	8	localObject5	Object
    //   1332	1	8	localException	Exception
    //   1336	1398	8	localObject6	Object
    //   130	1238	9	str4	String
    //   1372	19	9	localThrowable1	Throwable
    //   1623	716	9	localObject7	Object
    //   2729	7	9	localObject8	Object
    //   2744	1	9	localThrowable2	Throwable
    //   2805	1	9	localThrowable3	Throwable
    //   611	2156	10	localObject9	Object
    //   656	317	11	localObject10	Object
    //   1356	14	11	localObject11	Object
    //   1637	284	11	str5	String
    //   662	2103	12	str6	String
    //   3	2646	13	localzn	zn
    //   874	1200	14	localMzGenericPdu	com.meizu.android.mms.pdu.MzGenericPdu
    //   1632	440	15	localMzPduPersister	MzPduPersister
    //   1709	483	16	localCursor	android.database.Cursor
    // Exception table:
    //   from	to	target	type
    //   48	103	389	finally
    //   601	613	1332	java/lang/Exception
    //   621	628	1332	java/lang/Exception
    //   636	645	1332	java/lang/Exception
    //   653	658	1332	java/lang/Exception
    //   672	679	1332	java/lang/Exception
    //   693	714	1332	java/lang/Exception
    //   805	815	1356	finally
    //   1358	1361	1356	finally
    //   132	157	1372	java/lang/Throwable
    //   170	186	1372	java/lang/Throwable
    //   490	506	1372	java/lang/Throwable
    //   514	543	1372	java/lang/Throwable
    //   551	593	1372	java/lang/Throwable
    //   601	613	1372	java/lang/Throwable
    //   621	628	1372	java/lang/Throwable
    //   636	645	1372	java/lang/Throwable
    //   653	658	1372	java/lang/Throwable
    //   672	679	1372	java/lang/Throwable
    //   693	714	1372	java/lang/Throwable
    //   722	775	1372	java/lang/Throwable
    //   788	794	1372	java/lang/Throwable
    //   802	805	1372	java/lang/Throwable
    //   823	831	1372	java/lang/Throwable
    //   839	848	1372	java/lang/Throwable
    //   861	876	1372	java/lang/Throwable
    //   889	900	1372	java/lang/Throwable
    //   908	923	1372	java/lang/Throwable
    //   936	962	1372	java/lang/Throwable
    //   970	986	1372	java/lang/Throwable
    //   994	1002	1372	java/lang/Throwable
    //   1342	1350	1372	java/lang/Throwable
    //   1369	1372	1372	java/lang/Throwable
    //   1625	1634	1372	java/lang/Throwable
    //   1654	1711	1372	java/lang/Throwable
    //   1867	1874	1372	java/lang/Throwable
    //   2191	2198	1372	java/lang/Throwable
    //   2206	2209	1372	java/lang/Throwable
    //   1720	1730	2181	finally
    //   1734	1744	2181	finally
    //   1748	1765	2181	finally
    //   1769	1787	2181	finally
    //   1791	1810	2181	finally
    //   1814	1833	2181	finally
    //   1837	1855	2181	finally
    //   132	157	2209	finally
    //   170	186	2209	finally
    //   490	506	2209	finally
    //   514	543	2209	finally
    //   551	593	2209	finally
    //   601	613	2209	finally
    //   621	628	2209	finally
    //   636	645	2209	finally
    //   653	658	2209	finally
    //   672	679	2209	finally
    //   693	714	2209	finally
    //   722	775	2209	finally
    //   788	794	2209	finally
    //   802	805	2209	finally
    //   823	831	2209	finally
    //   839	848	2209	finally
    //   861	876	2209	finally
    //   889	900	2209	finally
    //   908	923	2209	finally
    //   936	962	2209	finally
    //   970	986	2209	finally
    //   994	1002	2209	finally
    //   1342	1350	2209	finally
    //   1369	1372	2209	finally
    //   1625	1634	2209	finally
    //   1654	1711	2209	finally
    //   1867	1874	2209	finally
    //   2191	2198	2209	finally
    //   2206	2209	2209	finally
    //   1012	1041	2479	finally
    //   1074	1088	2479	finally
    //   1094	1101	2479	finally
    //   1107	1114	2479	finally
    //   1388	1399	2479	finally
    //   2435	2443	2479	finally
    //   2452	2462	2479	finally
    //   2468	2476	2479	finally
    //   1874	2174	2729	finally
    //   1874	2174	2744	java/lang/Throwable
    //   1012	1041	2805	java/lang/Throwable
    //   1074	1088	2805	java/lang/Throwable
    //   1094	1101	2805	java/lang/Throwable
    //   1107	1114	2805	java/lang/Throwable
    //   2435	2443	2805	java/lang/Throwable
    //   2452	2462	2805	java/lang/Throwable
    //   2468	2476	2805	java/lang/Throwable
  }
}

/* Location:
 * Qualified Name:     pb
 * Java Class Version: 6 (50.0)
 * JD-Core Version:    0.7.1
 */