import android.content.Context;
import android.net.Uri;

public class pd
  extends ow
  implements Runnable
{
  private Thread a;
  
  public pd(Context paramContext, int paramInt, oz paramoz, String paramString)
  {
    super(paramContext, paramInt, paramoz);
    g = Uri.parse(paramString);
    c = paramString;
    h = 2;
    l = a(g);
    b(g);
  }
  
  public void a()
  {
    a = new Thread(this, "FlymeSendTransaction");
    a.start();
  }
  
  public int c()
  {
    return 2;
  }
  
  /* Error */
  public void run()
  {
    // Byte code:
    //   0: aload_0
    //   1: getfield 62	pd:b	Landroid/content/Context;
    //   4: invokestatic 68	com/meizu/android/mms/pdu/MzPduPersister:getPduPersister	(Landroid/content/Context;)Lcom/meizu/android/mms/pdu/MzPduPersister;
    //   7: astore 8
    //   9: aload 8
    //   11: aload_0
    //   12: getfield 23	pd:g	Landroid/net/Uri;
    //   15: invokevirtual 72	com/meizu/android/mms/pdu/MzPduPersister:load	(Landroid/net/Uri;)Lcom/meizu/android/mms/pdu/MzGenericPdu;
    //   18: checkcast 74	com/meizu/android/mms/pdu/MzSendReq
    //   21: astore 9
    //   23: invokestatic 80	java/lang/System:currentTimeMillis	()J
    //   26: ldc2_w 81
    //   29: ldiv
    //   30: lstore_3
    //   31: aload 9
    //   33: lload_3
    //   34: invokevirtual 86	com/meizu/android/mms/pdu/MzSendReq:setDate	(J)V
    //   37: new 88	android/content/ContentValues
    //   40: dup
    //   41: iconst_1
    //   42: invokespecial 91	android/content/ContentValues:<init>	(I)V
    //   45: astore 6
    //   47: aload 6
    //   49: ldc 93
    //   51: lload_3
    //   52: invokestatic 99	java/lang/Long:valueOf	(J)Ljava/lang/Long;
    //   55: invokevirtual 103	android/content/ContentValues:put	(Ljava/lang/String;Ljava/lang/Long;)V
    //   58: aload_0
    //   59: getfield 62	pd:b	Landroid/content/Context;
    //   62: invokevirtual 109	android/content/Context:getContentResolver	()Landroid/content/ContentResolver;
    //   65: aload_0
    //   66: getfield 23	pd:g	Landroid/net/Uri;
    //   69: aload 6
    //   71: aconst_null
    //   72: aconst_null
    //   73: invokevirtual 115	android/content/ContentResolver:update	(Landroid/net/Uri;Landroid/content/ContentValues;Ljava/lang/String;[Ljava/lang/String;)I
    //   76: pop
    //   77: invokestatic 120	wd:a	()Ljava/lang/String;
    //   80: astore 6
    //   82: aload 6
    //   84: invokestatic 126	android/text/TextUtils:isEmpty	(Ljava/lang/CharSequence;)Z
    //   87: ifne +17 -> 104
    //   90: aload 9
    //   92: new 128	com/meizu/android/mms/pdu/MzEncodedStringValue
    //   95: dup
    //   96: aload 6
    //   98: invokespecial 131	com/meizu/android/mms/pdu/MzEncodedStringValue:<init>	(Ljava/lang/String;)V
    //   101: invokevirtual 135	com/meizu/android/mms/pdu/MzSendReq:setFrom	(Lcom/meizu/android/mms/pdu/MzEncodedStringValue;)V
    //   104: aload_0
    //   105: getfield 23	pd:g	Landroid/net/Uri;
    //   108: invokestatic 141	android/content/ContentUris:parseId	(Landroid/net/Uri;)J
    //   111: lstore_3
    //   112: ldc 47
    //   114: new 143	java/lang/StringBuilder
    //   117: dup
    //   118: invokespecial 145	java/lang/StringBuilder:<init>	()V
    //   121: ldc -109
    //   123: invokevirtual 151	java/lang/StringBuilder:append	(Ljava/lang/String;)Ljava/lang/StringBuilder;
    //   126: aload_0
    //   127: getfield 154	pd:m	I
    //   130: invokevirtual 157	java/lang/StringBuilder:append	(I)Ljava/lang/StringBuilder;
    //   133: ldc -97
    //   135: invokevirtual 151	java/lang/StringBuilder:append	(Ljava/lang/String;)Ljava/lang/StringBuilder;
    //   138: aload_0
    //   139: getfield 23	pd:g	Landroid/net/Uri;
    //   142: invokevirtual 162	android/net/Uri:toString	()Ljava/lang/String;
    //   145: invokevirtual 151	java/lang/StringBuilder:append	(Ljava/lang/String;)Ljava/lang/StringBuilder;
    //   148: invokevirtual 163	java/lang/StringBuilder:toString	()Ljava/lang/String;
    //   151: invokestatic 169	android/util/Log:d	(Ljava/lang/String;Ljava/lang/String;)I
    //   154: pop
    //   155: aload_0
    //   156: getfield 62	pd:b	Landroid/content/Context;
    //   159: invokevirtual 109	android/content/Context:getContentResolver	()Landroid/content/ContentResolver;
    //   162: aload_0
    //   163: getfield 23	pd:g	Landroid/net/Uri;
    //   166: iconst_5
    //   167: anewarray 171	java/lang/String
    //   170: dup
    //   171: iconst_0
    //   172: ldc -83
    //   174: aastore
    //   175: dup
    //   176: iconst_1
    //   177: ldc -81
    //   179: aastore
    //   180: dup
    //   181: iconst_2
    //   182: ldc -79
    //   184: aastore
    //   185: dup
    //   186: iconst_3
    //   187: ldc -77
    //   189: aastore
    //   190: dup
    //   191: iconst_4
    //   192: ldc -75
    //   194: aastore
    //   195: aconst_null
    //   196: aconst_null
    //   197: aconst_null
    //   198: invokevirtual 185	android/content/ContentResolver:query	(Landroid/net/Uri;[Ljava/lang/String;Ljava/lang/String;[Ljava/lang/String;Ljava/lang/String;)Landroid/database/Cursor;
    //   201: astore 10
    //   203: aload 10
    //   205: ifnull +1580 -> 1785
    //   208: aload 10
    //   210: invokeinterface 190 1 0
    //   215: ifle +1553 -> 1768
    //   218: aload 10
    //   220: invokeinterface 194 1 0
    //   225: ifeq +1543 -> 1768
    //   228: aload 10
    //   230: aload 10
    //   232: ldc -81
    //   234: invokeinterface 198 2 0
    //   239: invokeinterface 202 2 0
    //   244: astore 7
    //   246: aload 10
    //   248: aload 10
    //   250: ldc -79
    //   252: invokeinterface 198 2 0
    //   257: invokeinterface 202 2 0
    //   262: astore 6
    //   264: aload 10
    //   266: aload 10
    //   268: ldc -77
    //   270: invokeinterface 198 2 0
    //   275: invokeinterface 206 2 0
    //   280: istore_1
    //   281: aload 10
    //   283: aload 10
    //   285: ldc -75
    //   287: invokeinterface 198 2 0
    //   292: invokeinterface 206 2 0
    //   297: istore_2
    //   298: aload 10
    //   300: invokeinterface 209 1 0
    //   305: iload_1
    //   306: ifle +57 -> 363
    //   309: ldc 47
    //   311: new 143	java/lang/StringBuilder
    //   314: dup
    //   315: invokespecial 145	java/lang/StringBuilder:<init>	()V
    //   318: ldc -45
    //   320: invokevirtual 151	java/lang/StringBuilder:append	(Ljava/lang/String;)Ljava/lang/StringBuilder;
    //   323: iload_1
    //   324: invokevirtual 157	java/lang/StringBuilder:append	(I)Ljava/lang/StringBuilder;
    //   327: ldc -43
    //   329: invokevirtual 151	java/lang/StringBuilder:append	(Ljava/lang/String;)Ljava/lang/StringBuilder;
    //   332: iload_2
    //   333: invokevirtual 157	java/lang/StringBuilder:append	(I)Ljava/lang/StringBuilder;
    //   336: invokevirtual 163	java/lang/StringBuilder:toString	()Ljava/lang/String;
    //   339: invokestatic 169	android/util/Log:d	(Ljava/lang/String;Ljava/lang/String;)I
    //   342: pop
    //   343: aload_0
    //   344: iload_1
    //   345: i2l
    //   346: invokevirtual 215	pd:a	(J)V
    //   349: invokestatic 220	com/android/mms/MmsApp:c	()Lcom/android/mms/MmsApp;
    //   352: aload_0
    //   353: getfield 23	pd:g	Landroid/net/Uri;
    //   356: iload_1
    //   357: i2l
    //   358: iload_2
    //   359: i2l
    //   360: invokevirtual 223	com/android/mms/MmsApp:a	(Landroid/net/Uri;JJ)V
    //   363: aload 9
    //   365: invokevirtual 226	com/meizu/android/mms/pdu/MzSendReq:getDeliveryReport	()I
    //   368: sipush 128
    //   371: if_icmpne +560 -> 931
    //   374: iconst_1
    //   375: istore 5
    //   377: invokestatic 231	aba:a	()Laba;
    //   380: aload 9
    //   382: invokevirtual 235	com/meizu/android/mms/pdu/MzSendReq:getTo	()[Lcom/meizu/android/mms/pdu/MzEncodedStringValue;
    //   385: invokestatic 239	com/meizu/android/mms/pdu/MzEncodedStringValue:concat	([Lcom/meizu/android/mms/pdu/MzEncodedStringValue;)Ljava/lang/String;
    //   388: ldc -15
    //   390: invokestatic 245	android/text/TextUtils:split	(Ljava/lang/String;Ljava/lang/String;)[Ljava/lang/String;
    //   393: aload_0
    //   394: getfield 37	pd:l	Ljava/lang/String;
    //   397: new 247	com/meizu/android/mms/pdu/MzPduComposer
    //   400: dup
    //   401: aload_0
    //   402: getfield 62	pd:b	Landroid/content/Context;
    //   405: aload 9
    //   407: iconst_2
    //   408: invokespecial 250	com/meizu/android/mms/pdu/MzPduComposer:<init>	(Landroid/content/Context;Lcom/meizu/android/mms/pdu/MzGenericPdu;I)V
    //   411: invokevirtual 254	com/meizu/android/mms/pdu/MzPduComposer:make	()[B
    //   414: aload 7
    //   416: iload 5
    //   418: aload 6
    //   420: invokevirtual 257	aba:a	([Ljava/lang/String;Ljava/lang/String;[BLjava/lang/String;ZLjava/lang/String;)Z
    //   423: istore 5
    //   425: iload 5
    //   427: ifeq +22 -> 449
    //   430: aload_0
    //   431: getfield 261	pd:i	Ljava/lang/Object;
    //   434: astore 6
    //   436: aload 6
    //   438: monitorenter
    //   439: aload_0
    //   440: getfield 261	pd:i	Ljava/lang/Object;
    //   443: invokevirtual 266	java/lang/Object:wait	()V
    //   446: aload 6
    //   448: monitorexit
    //   449: new 268	com/meizu/android/mms/pdu/MzSendConf
    //   452: dup
    //   453: invokespecial 269	com/meizu/android/mms/pdu/MzSendConf:<init>	()V
    //   456: astore 6
    //   458: aload 6
    //   460: aload 9
    //   462: invokevirtual 272	com/meizu/android/mms/pdu/MzSendReq:getTransactionId	()[B
    //   465: invokevirtual 276	com/meizu/android/mms/pdu/MzSendConf:setTransactionId	([B)V
    //   468: aload 6
    //   470: aload_0
    //   471: getfield 37	pd:l	Ljava/lang/String;
    //   474: invokevirtual 279	java/lang/String:getBytes	()[B
    //   477: invokevirtual 282	com/meizu/android/mms/pdu/MzSendConf:setMessageId	([B)V
    //   480: aload_0
    //   481: aload_0
    //   482: getfield 285	pd:j	I
    //   485: invokevirtual 287	pd:c	(I)V
    //   488: aload 6
    //   490: aload_0
    //   491: getfield 285	pd:j	I
    //   494: invokevirtual 290	com/meizu/android/mms/pdu/MzSendConf:setResponseStatus	(I)V
    //   497: ldc 47
    //   499: new 143	java/lang/StringBuilder
    //   502: dup
    //   503: invokespecial 145	java/lang/StringBuilder:<init>	()V
    //   506: ldc_w 292
    //   509: invokevirtual 151	java/lang/StringBuilder:append	(Ljava/lang/String;)Ljava/lang/StringBuilder;
    //   512: aload_0
    //   513: getfield 154	pd:m	I
    //   516: invokevirtual 157	java/lang/StringBuilder:append	(I)Ljava/lang/StringBuilder;
    //   519: ldc -97
    //   521: invokevirtual 151	java/lang/StringBuilder:append	(Ljava/lang/String;)Ljava/lang/StringBuilder;
    //   524: aload_0
    //   525: getfield 23	pd:g	Landroid/net/Uri;
    //   528: invokevirtual 162	android/net/Uri:toString	()Ljava/lang/String;
    //   531: invokevirtual 151	java/lang/StringBuilder:append	(Ljava/lang/String;)Ljava/lang/StringBuilder;
    //   534: ldc_w 294
    //   537: invokevirtual 151	java/lang/StringBuilder:append	(Ljava/lang/String;)Ljava/lang/StringBuilder;
    //   540: iload 5
    //   542: invokevirtual 297	java/lang/StringBuilder:append	(Z)Ljava/lang/StringBuilder;
    //   545: invokevirtual 163	java/lang/StringBuilder:toString	()Ljava/lang/String;
    //   548: invokestatic 169	android/util/Log:d	(Ljava/lang/String;Ljava/lang/String;)I
    //   551: pop
    //   552: lload_3
    //   553: invokestatic 99	java/lang/Long:valueOf	(J)Ljava/lang/Long;
    //   556: invokestatic 302	aav:a	(Ljava/lang/Object;)V
    //   559: aload 9
    //   561: invokevirtual 272	com/meizu/android/mms/pdu/MzSendReq:getTransactionId	()[B
    //   564: astore 7
    //   566: aload 6
    //   568: invokevirtual 303	com/meizu/android/mms/pdu/MzSendConf:getTransactionId	()[B
    //   571: astore 9
    //   573: aload 7
    //   575: aload 9
    //   577: invokestatic 309	java/util/Arrays:equals	([B[B)Z
    //   580: ifne +509 -> 1089
    //   583: ldc 47
    //   585: new 143	java/lang/StringBuilder
    //   588: dup
    //   589: invokespecial 145	java/lang/StringBuilder:<init>	()V
    //   592: ldc_w 311
    //   595: invokevirtual 151	java/lang/StringBuilder:append	(Ljava/lang/String;)Ljava/lang/StringBuilder;
    //   598: new 171	java/lang/String
    //   601: dup
    //   602: aload 7
    //   604: invokespecial 313	java/lang/String:<init>	([B)V
    //   607: invokevirtual 151	java/lang/StringBuilder:append	(Ljava/lang/String;)Ljava/lang/StringBuilder;
    //   610: ldc_w 315
    //   613: invokevirtual 151	java/lang/StringBuilder:append	(Ljava/lang/String;)Ljava/lang/StringBuilder;
    //   616: new 171	java/lang/String
    //   619: dup
    //   620: aload 9
    //   622: invokespecial 313	java/lang/String:<init>	([B)V
    //   625: invokevirtual 151	java/lang/StringBuilder:append	(Ljava/lang/String;)Ljava/lang/StringBuilder;
    //   628: invokevirtual 163	java/lang/StringBuilder:toString	()Ljava/lang/String;
    //   631: invokestatic 318	android/util/Log:e	(Ljava/lang/String;Ljava/lang/String;)I
    //   634: pop
    //   635: aload_0
    //   636: getfield 321	pd:d	Lpa;
    //   639: invokevirtual 325	pa:a	()I
    //   642: iconst_1
    //   643: if_icmpeq +386 -> 1029
    //   646: aload_0
    //   647: getfield 321	pd:d	Lpa;
    //   650: iconst_2
    //   651: invokevirtual 327	pa:a	(I)V
    //   654: aload_0
    //   655: getfield 321	pd:d	Lpa;
    //   658: aload_0
    //   659: getfield 23	pd:g	Landroid/net/Uri;
    //   662: invokevirtual 329	pa:a	(Landroid/net/Uri;)V
    //   665: ldc 47
    //   667: new 143	java/lang/StringBuilder
    //   670: dup
    //   671: invokespecial 145	java/lang/StringBuilder:<init>	()V
    //   674: ldc_w 331
    //   677: invokevirtual 151	java/lang/StringBuilder:append	(Ljava/lang/String;)Ljava/lang/StringBuilder;
    //   680: aload_0
    //   681: getfield 154	pd:m	I
    //   684: invokevirtual 157	java/lang/StringBuilder:append	(I)Ljava/lang/StringBuilder;
    //   687: ldc_w 333
    //   690: invokevirtual 151	java/lang/StringBuilder:append	(Ljava/lang/String;)Ljava/lang/StringBuilder;
    //   693: aload_0
    //   694: getfield 23	pd:g	Landroid/net/Uri;
    //   697: invokevirtual 162	android/net/Uri:toString	()Ljava/lang/String;
    //   700: invokevirtual 151	java/lang/StringBuilder:append	(Ljava/lang/String;)Ljava/lang/StringBuilder;
    //   703: invokevirtual 163	java/lang/StringBuilder:toString	()Ljava/lang/String;
    //   706: invokestatic 169	android/util/Log:d	(Ljava/lang/String;Ljava/lang/String;)I
    //   709: pop
    //   710: aload_0
    //   711: invokevirtual 335	pd:d	()V
    //   714: return
    //   715: astore 6
    //   717: aload 10
    //   719: invokeinterface 209 1 0
    //   724: aload 6
    //   726: athrow
    //   727: astore 6
    //   729: ldc 47
    //   731: aload 6
    //   733: invokestatic 339	android/util/Log:getStackTraceString	(Ljava/lang/Throwable;)Ljava/lang/String;
    //   736: invokestatic 318	android/util/Log:e	(Ljava/lang/String;Ljava/lang/String;)I
    //   739: pop
    //   740: new 88	android/content/ContentValues
    //   743: dup
    //   744: iconst_2
    //   745: invokespecial 91	android/content/ContentValues:<init>	(I)V
    //   748: astore 6
    //   750: aload 6
    //   752: ldc_w 341
    //   755: sipush 134
    //   758: invokestatic 346	java/lang/Integer:valueOf	(I)Ljava/lang/Integer;
    //   761: invokevirtual 349	android/content/ContentValues:put	(Ljava/lang/String;Ljava/lang/Integer;)V
    //   764: aload_0
    //   765: getfield 62	pd:b	Landroid/content/Context;
    //   768: invokevirtual 109	android/content/Context:getContentResolver	()Landroid/content/ContentResolver;
    //   771: aload_0
    //   772: getfield 23	pd:g	Landroid/net/Uri;
    //   775: aload 6
    //   777: aconst_null
    //   778: aconst_null
    //   779: invokevirtual 115	android/content/ContentResolver:update	(Landroid/net/Uri;Landroid/content/ContentValues;Ljava/lang/String;[Ljava/lang/String;)I
    //   782: pop
    //   783: new 88	android/content/ContentValues
    //   786: dup
    //   787: iconst_1
    //   788: invokespecial 91	android/content/ContentValues:<init>	(I)V
    //   791: astore 6
    //   793: aload_0
    //   794: getfield 23	pd:g	Landroid/net/Uri;
    //   797: invokestatic 141	android/content/ContentUris:parseId	(Landroid/net/Uri;)J
    //   800: lstore_3
    //   801: aload 6
    //   803: ldc_w 351
    //   806: bipush 19
    //   808: invokestatic 346	java/lang/Integer:valueOf	(I)Ljava/lang/Integer;
    //   811: invokevirtual 349	android/content/ContentValues:put	(Ljava/lang/String;Ljava/lang/Integer;)V
    //   814: aload_0
    //   815: getfield 62	pd:b	Landroid/content/Context;
    //   818: invokevirtual 109	android/content/Context:getContentResolver	()Landroid/content/ContentResolver;
    //   821: getstatic 356	android/provider/Telephony$MmsSms$PendingMessages:CONTENT_URI	Landroid/net/Uri;
    //   824: aload 6
    //   826: new 143	java/lang/StringBuilder
    //   829: dup
    //   830: invokespecial 145	java/lang/StringBuilder:<init>	()V
    //   833: ldc_w 358
    //   836: invokevirtual 151	java/lang/StringBuilder:append	(Ljava/lang/String;)Ljava/lang/StringBuilder;
    //   839: lload_3
    //   840: invokevirtual 361	java/lang/StringBuilder:append	(J)Ljava/lang/StringBuilder;
    //   843: invokevirtual 163	java/lang/StringBuilder:toString	()Ljava/lang/String;
    //   846: aconst_null
    //   847: invokevirtual 115	android/content/ContentResolver:update	(Landroid/net/Uri;Landroid/content/ContentValues;Ljava/lang/String;[Ljava/lang/String;)I
    //   850: pop
    //   851: aload_0
    //   852: getfield 321	pd:d	Lpa;
    //   855: invokevirtual 325	pa:a	()I
    //   858: iconst_1
    //   859: if_icmpeq +789 -> 1648
    //   862: aload_0
    //   863: getfield 321	pd:d	Lpa;
    //   866: iconst_2
    //   867: invokevirtual 327	pa:a	(I)V
    //   870: aload_0
    //   871: getfield 321	pd:d	Lpa;
    //   874: aload_0
    //   875: getfield 23	pd:g	Landroid/net/Uri;
    //   878: invokevirtual 329	pa:a	(Landroid/net/Uri;)V
    //   881: ldc 47
    //   883: new 143	java/lang/StringBuilder
    //   886: dup
    //   887: invokespecial 145	java/lang/StringBuilder:<init>	()V
    //   890: ldc_w 331
    //   893: invokevirtual 151	java/lang/StringBuilder:append	(Ljava/lang/String;)Ljava/lang/StringBuilder;
    //   896: aload_0
    //   897: getfield 154	pd:m	I
    //   900: invokevirtual 157	java/lang/StringBuilder:append	(I)Ljava/lang/StringBuilder;
    //   903: ldc_w 333
    //   906: invokevirtual 151	java/lang/StringBuilder:append	(Ljava/lang/String;)Ljava/lang/StringBuilder;
    //   909: aload_0
    //   910: getfield 23	pd:g	Landroid/net/Uri;
    //   913: invokevirtual 162	android/net/Uri:toString	()Ljava/lang/String;
    //   916: invokevirtual 151	java/lang/StringBuilder:append	(Ljava/lang/String;)Ljava/lang/StringBuilder;
    //   919: invokevirtual 163	java/lang/StringBuilder:toString	()Ljava/lang/String;
    //   922: invokestatic 169	android/util/Log:d	(Ljava/lang/String;Ljava/lang/String;)I
    //   925: pop
    //   926: aload_0
    //   927: invokevirtual 335	pd:d	()V
    //   930: return
    //   931: iconst_0
    //   932: istore 5
    //   934: goto -557 -> 377
    //   937: astore 7
    //   939: aload 6
    //   941: monitorexit
    //   942: aload 7
    //   944: athrow
    //   945: astore 6
    //   947: aload_0
    //   948: getfield 321	pd:d	Lpa;
    //   951: invokevirtual 325	pa:a	()I
    //   954: iconst_1
    //   955: if_icmpeq +753 -> 1708
    //   958: aload_0
    //   959: getfield 321	pd:d	Lpa;
    //   962: iconst_2
    //   963: invokevirtual 327	pa:a	(I)V
    //   966: aload_0
    //   967: getfield 321	pd:d	Lpa;
    //   970: aload_0
    //   971: getfield 23	pd:g	Landroid/net/Uri;
    //   974: invokevirtual 329	pa:a	(Landroid/net/Uri;)V
    //   977: ldc 47
    //   979: new 143	java/lang/StringBuilder
    //   982: dup
    //   983: invokespecial 145	java/lang/StringBuilder:<init>	()V
    //   986: ldc_w 331
    //   989: invokevirtual 151	java/lang/StringBuilder:append	(Ljava/lang/String;)Ljava/lang/StringBuilder;
    //   992: aload_0
    //   993: getfield 154	pd:m	I
    //   996: invokevirtual 157	java/lang/StringBuilder:append	(I)Ljava/lang/StringBuilder;
    //   999: ldc_w 333
    //   1002: invokevirtual 151	java/lang/StringBuilder:append	(Ljava/lang/String;)Ljava/lang/StringBuilder;
    //   1005: aload_0
    //   1006: getfield 23	pd:g	Landroid/net/Uri;
    //   1009: invokevirtual 162	android/net/Uri:toString	()Ljava/lang/String;
    //   1012: invokevirtual 151	java/lang/StringBuilder:append	(Ljava/lang/String;)Ljava/lang/StringBuilder;
    //   1015: invokevirtual 163	java/lang/StringBuilder:toString	()Ljava/lang/String;
    //   1018: invokestatic 169	android/util/Log:d	(Ljava/lang/String;Ljava/lang/String;)I
    //   1021: pop
    //   1022: aload_0
    //   1023: invokevirtual 335	pd:d	()V
    //   1026: aload 6
    //   1028: athrow
    //   1029: invokestatic 220	com/android/mms/MmsApp:c	()Lcom/android/mms/MmsApp;
    //   1032: invokestatic 364	com/android/mms/MmsApp:a	()Landroid/net/Uri;
    //   1035: ldc_w 365
    //   1038: invokestatic 370	com/android/mms/transaction/MessagingNotification:a	(Landroid/content/Context;Landroid/net/Uri;F)V
    //   1041: ldc 47
    //   1043: new 143	java/lang/StringBuilder
    //   1046: dup
    //   1047: invokespecial 145	java/lang/StringBuilder:<init>	()V
    //   1050: ldc_w 331
    //   1053: invokevirtual 151	java/lang/StringBuilder:append	(Ljava/lang/String;)Ljava/lang/StringBuilder;
    //   1056: aload_0
    //   1057: getfield 154	pd:m	I
    //   1060: invokevirtual 157	java/lang/StringBuilder:append	(I)Ljava/lang/StringBuilder;
    //   1063: ldc_w 372
    //   1066: invokevirtual 151	java/lang/StringBuilder:append	(Ljava/lang/String;)Ljava/lang/StringBuilder;
    //   1069: aload_0
    //   1070: getfield 23	pd:g	Landroid/net/Uri;
    //   1073: invokevirtual 162	android/net/Uri:toString	()Ljava/lang/String;
    //   1076: invokevirtual 151	java/lang/StringBuilder:append	(Ljava/lang/String;)Ljava/lang/StringBuilder;
    //   1079: invokevirtual 163	java/lang/StringBuilder:toString	()Ljava/lang/String;
    //   1082: invokestatic 169	android/util/Log:d	(Ljava/lang/String;Ljava/lang/String;)I
    //   1085: pop
    //   1086: goto -376 -> 710
    //   1089: new 88	android/content/ContentValues
    //   1092: dup
    //   1093: iconst_2
    //   1094: invokespecial 91	android/content/ContentValues:<init>	(I)V
    //   1097: astore 7
    //   1099: aload_0
    //   1100: invokevirtual 375	pd:k	()I
    //   1103: istore_2
    //   1104: iload_2
    //   1105: istore_1
    //   1106: iload_2
    //   1107: sipush 9528
    //   1110: if_icmpne +692 -> 1802
    //   1113: sipush 130
    //   1116: istore_1
    //   1117: goto +685 -> 1802
    //   1120: aload 7
    //   1122: ldc_w 341
    //   1125: iload_1
    //   1126: invokestatic 346	java/lang/Integer:valueOf	(I)Ljava/lang/Integer;
    //   1129: invokevirtual 349	android/content/ContentValues:put	(Ljava/lang/String;Ljava/lang/Integer;)V
    //   1132: aload 7
    //   1134: ldc -77
    //   1136: aload_0
    //   1137: invokevirtual 377	pd:m	()J
    //   1140: invokestatic 99	java/lang/Long:valueOf	(J)Ljava/lang/Long;
    //   1143: invokevirtual 103	android/content/ContentValues:put	(Ljava/lang/String;Ljava/lang/Long;)V
    //   1146: ldc 47
    //   1148: new 143	java/lang/StringBuilder
    //   1151: dup
    //   1152: invokespecial 145	java/lang/StringBuilder:<init>	()V
    //   1155: ldc_w 379
    //   1158: invokevirtual 151	java/lang/StringBuilder:append	(Ljava/lang/String;)Ljava/lang/StringBuilder;
    //   1161: aload_0
    //   1162: invokevirtual 377	pd:m	()J
    //   1165: invokevirtual 361	java/lang/StringBuilder:append	(J)Ljava/lang/StringBuilder;
    //   1168: invokevirtual 163	java/lang/StringBuilder:toString	()Ljava/lang/String;
    //   1171: invokestatic 169	android/util/Log:d	(Ljava/lang/String;Ljava/lang/String;)I
    //   1174: pop
    //   1175: iload_1
    //   1176: sipush 128
    //   1179: if_icmpeq +263 -> 1442
    //   1182: aload_0
    //   1183: getfield 62	pd:b	Landroid/content/Context;
    //   1186: invokevirtual 109	android/content/Context:getContentResolver	()Landroid/content/ContentResolver;
    //   1189: aload_0
    //   1190: getfield 23	pd:g	Landroid/net/Uri;
    //   1193: aload 7
    //   1195: aconst_null
    //   1196: aconst_null
    //   1197: invokevirtual 115	android/content/ContentResolver:update	(Landroid/net/Uri;Landroid/content/ContentValues;Ljava/lang/String;[Ljava/lang/String;)I
    //   1200: pop
    //   1201: iload_1
    //   1202: invokestatic 382	wd:a	(I)Z
    //   1205: ifeq +71 -> 1276
    //   1208: new 88	android/content/ContentValues
    //   1211: dup
    //   1212: iconst_1
    //   1213: invokespecial 91	android/content/ContentValues:<init>	(I)V
    //   1216: astore 6
    //   1218: aload_0
    //   1219: getfield 23	pd:g	Landroid/net/Uri;
    //   1222: invokestatic 141	android/content/ContentUris:parseId	(Landroid/net/Uri;)J
    //   1225: lstore_3
    //   1226: aload 6
    //   1228: ldc_w 351
    //   1231: bipush 19
    //   1233: invokestatic 346	java/lang/Integer:valueOf	(I)Ljava/lang/Integer;
    //   1236: invokevirtual 349	android/content/ContentValues:put	(Ljava/lang/String;Ljava/lang/Integer;)V
    //   1239: aload_0
    //   1240: getfield 62	pd:b	Landroid/content/Context;
    //   1243: invokevirtual 109	android/content/Context:getContentResolver	()Landroid/content/ContentResolver;
    //   1246: getstatic 356	android/provider/Telephony$MmsSms$PendingMessages:CONTENT_URI	Landroid/net/Uri;
    //   1249: aload 6
    //   1251: new 143	java/lang/StringBuilder
    //   1254: dup
    //   1255: invokespecial 145	java/lang/StringBuilder:<init>	()V
    //   1258: ldc_w 358
    //   1261: invokevirtual 151	java/lang/StringBuilder:append	(Ljava/lang/String;)Ljava/lang/StringBuilder;
    //   1264: lload_3
    //   1265: invokevirtual 361	java/lang/StringBuilder:append	(J)Ljava/lang/StringBuilder;
    //   1268: invokevirtual 163	java/lang/StringBuilder:toString	()Ljava/lang/String;
    //   1271: aconst_null
    //   1272: invokevirtual 115	android/content/ContentResolver:update	(Landroid/net/Uri;Landroid/content/ContentValues;Ljava/lang/String;[Ljava/lang/String;)I
    //   1275: pop
    //   1276: ldc 47
    //   1278: new 143	java/lang/StringBuilder
    //   1281: dup
    //   1282: invokespecial 145	java/lang/StringBuilder:<init>	()V
    //   1285: ldc_w 384
    //   1288: invokevirtual 151	java/lang/StringBuilder:append	(Ljava/lang/String;)Ljava/lang/StringBuilder;
    //   1291: iload_1
    //   1292: invokevirtual 157	java/lang/StringBuilder:append	(I)Ljava/lang/StringBuilder;
    //   1295: invokevirtual 163	java/lang/StringBuilder:toString	()Ljava/lang/String;
    //   1298: invokestatic 318	android/util/Log:e	(Ljava/lang/String;Ljava/lang/String;)I
    //   1301: pop
    //   1302: aload_0
    //   1303: getfield 321	pd:d	Lpa;
    //   1306: invokevirtual 325	pa:a	()I
    //   1309: iconst_1
    //   1310: if_icmpeq +72 -> 1382
    //   1313: aload_0
    //   1314: getfield 321	pd:d	Lpa;
    //   1317: iconst_2
    //   1318: invokevirtual 327	pa:a	(I)V
    //   1321: aload_0
    //   1322: getfield 321	pd:d	Lpa;
    //   1325: aload_0
    //   1326: getfield 23	pd:g	Landroid/net/Uri;
    //   1329: invokevirtual 329	pa:a	(Landroid/net/Uri;)V
    //   1332: ldc 47
    //   1334: new 143	java/lang/StringBuilder
    //   1337: dup
    //   1338: invokespecial 145	java/lang/StringBuilder:<init>	()V
    //   1341: ldc_w 331
    //   1344: invokevirtual 151	java/lang/StringBuilder:append	(Ljava/lang/String;)Ljava/lang/StringBuilder;
    //   1347: aload_0
    //   1348: getfield 154	pd:m	I
    //   1351: invokevirtual 157	java/lang/StringBuilder:append	(I)Ljava/lang/StringBuilder;
    //   1354: ldc_w 333
    //   1357: invokevirtual 151	java/lang/StringBuilder:append	(Ljava/lang/String;)Ljava/lang/StringBuilder;
    //   1360: aload_0
    //   1361: getfield 23	pd:g	Landroid/net/Uri;
    //   1364: invokevirtual 162	android/net/Uri:toString	()Ljava/lang/String;
    //   1367: invokevirtual 151	java/lang/StringBuilder:append	(Ljava/lang/String;)Ljava/lang/StringBuilder;
    //   1370: invokevirtual 163	java/lang/StringBuilder:toString	()Ljava/lang/String;
    //   1373: invokestatic 169	android/util/Log:d	(Ljava/lang/String;Ljava/lang/String;)I
    //   1376: pop
    //   1377: aload_0
    //   1378: invokevirtual 335	pd:d	()V
    //   1381: return
    //   1382: invokestatic 220	com/android/mms/MmsApp:c	()Lcom/android/mms/MmsApp;
    //   1385: invokestatic 364	com/android/mms/MmsApp:a	()Landroid/net/Uri;
    //   1388: ldc_w 365
    //   1391: invokestatic 370	com/android/mms/transaction/MessagingNotification:a	(Landroid/content/Context;Landroid/net/Uri;F)V
    //   1394: ldc 47
    //   1396: new 143	java/lang/StringBuilder
    //   1399: dup
    //   1400: invokespecial 145	java/lang/StringBuilder:<init>	()V
    //   1403: ldc_w 331
    //   1406: invokevirtual 151	java/lang/StringBuilder:append	(Ljava/lang/String;)Ljava/lang/StringBuilder;
    //   1409: aload_0
    //   1410: getfield 154	pd:m	I
    //   1413: invokevirtual 157	java/lang/StringBuilder:append	(I)Ljava/lang/StringBuilder;
    //   1416: ldc_w 372
    //   1419: invokevirtual 151	java/lang/StringBuilder:append	(Ljava/lang/String;)Ljava/lang/StringBuilder;
    //   1422: aload_0
    //   1423: getfield 23	pd:g	Landroid/net/Uri;
    //   1426: invokevirtual 162	android/net/Uri:toString	()Ljava/lang/String;
    //   1429: invokevirtual 151	java/lang/StringBuilder:append	(Ljava/lang/String;)Ljava/lang/StringBuilder;
    //   1432: invokevirtual 163	java/lang/StringBuilder:toString	()Ljava/lang/String;
    //   1435: invokestatic 169	android/util/Log:d	(Ljava/lang/String;Ljava/lang/String;)I
    //   1438: pop
    //   1439: goto -62 -> 1377
    //   1442: aload 7
    //   1444: ldc_w 386
    //   1447: aload 6
    //   1449: invokevirtual 389	com/meizu/android/mms/pdu/MzSendConf:getMessageId	()[B
    //   1452: invokestatic 393	com/meizu/android/mms/pdu/MzPduPersister:toIsoString	([B)Ljava/lang/String;
    //   1455: invokevirtual 396	android/content/ContentValues:put	(Ljava/lang/String;Ljava/lang/String;)V
    //   1458: aload_0
    //   1459: getfield 62	pd:b	Landroid/content/Context;
    //   1462: invokevirtual 109	android/content/Context:getContentResolver	()Landroid/content/ContentResolver;
    //   1465: aload_0
    //   1466: getfield 23	pd:g	Landroid/net/Uri;
    //   1469: aload 7
    //   1471: aconst_null
    //   1472: aconst_null
    //   1473: invokevirtual 115	android/content/ContentResolver:update	(Landroid/net/Uri;Landroid/content/ContentValues;Ljava/lang/String;[Ljava/lang/String;)I
    //   1476: pop
    //   1477: aload 8
    //   1479: aload_0
    //   1480: getfield 23	pd:g	Landroid/net/Uri;
    //   1483: getstatic 399	android/provider/Telephony$Mms$Sent:CONTENT_URI	Landroid/net/Uri;
    //   1486: invokevirtual 403	com/meizu/android/mms/pdu/MzPduPersister:move	(Landroid/net/Uri;Landroid/net/Uri;)Landroid/net/Uri;
    //   1489: astore 6
    //   1491: aload_0
    //   1492: getfield 321	pd:d	Lpa;
    //   1495: iconst_1
    //   1496: invokevirtual 327	pa:a	(I)V
    //   1499: aload_0
    //   1500: getfield 321	pd:d	Lpa;
    //   1503: aload 6
    //   1505: invokevirtual 329	pa:a	(Landroid/net/Uri;)V
    //   1508: aload_0
    //   1509: getfield 321	pd:d	Lpa;
    //   1512: invokevirtual 325	pa:a	()I
    //   1515: iconst_1
    //   1516: if_icmpeq +72 -> 1588
    //   1519: aload_0
    //   1520: getfield 321	pd:d	Lpa;
    //   1523: iconst_2
    //   1524: invokevirtual 327	pa:a	(I)V
    //   1527: aload_0
    //   1528: getfield 321	pd:d	Lpa;
    //   1531: aload_0
    //   1532: getfield 23	pd:g	Landroid/net/Uri;
    //   1535: invokevirtual 329	pa:a	(Landroid/net/Uri;)V
    //   1538: ldc 47
    //   1540: new 143	java/lang/StringBuilder
    //   1543: dup
    //   1544: invokespecial 145	java/lang/StringBuilder:<init>	()V
    //   1547: ldc_w 331
    //   1550: invokevirtual 151	java/lang/StringBuilder:append	(Ljava/lang/String;)Ljava/lang/StringBuilder;
    //   1553: aload_0
    //   1554: getfield 154	pd:m	I
    //   1557: invokevirtual 157	java/lang/StringBuilder:append	(I)Ljava/lang/StringBuilder;
    //   1560: ldc_w 333
    //   1563: invokevirtual 151	java/lang/StringBuilder:append	(Ljava/lang/String;)Ljava/lang/StringBuilder;
    //   1566: aload_0
    //   1567: getfield 23	pd:g	Landroid/net/Uri;
    //   1570: invokevirtual 162	android/net/Uri:toString	()Ljava/lang/String;
    //   1573: invokevirtual 151	java/lang/StringBuilder:append	(Ljava/lang/String;)Ljava/lang/StringBuilder;
    //   1576: invokevirtual 163	java/lang/StringBuilder:toString	()Ljava/lang/String;
    //   1579: invokestatic 169	android/util/Log:d	(Ljava/lang/String;Ljava/lang/String;)I
    //   1582: pop
    //   1583: aload_0
    //   1584: invokevirtual 335	pd:d	()V
    //   1587: return
    //   1588: invokestatic 220	com/android/mms/MmsApp:c	()Lcom/android/mms/MmsApp;
    //   1591: invokestatic 364	com/android/mms/MmsApp:a	()Landroid/net/Uri;
    //   1594: ldc_w 365
    //   1597: invokestatic 370	com/android/mms/transaction/MessagingNotification:a	(Landroid/content/Context;Landroid/net/Uri;F)V
    //   1600: ldc 47
    //   1602: new 143	java/lang/StringBuilder
    //   1605: dup
    //   1606: invokespecial 145	java/lang/StringBuilder:<init>	()V
    //   1609: ldc_w 331
    //   1612: invokevirtual 151	java/lang/StringBuilder:append	(Ljava/lang/String;)Ljava/lang/StringBuilder;
    //   1615: aload_0
    //   1616: getfield 154	pd:m	I
    //   1619: invokevirtual 157	java/lang/StringBuilder:append	(I)Ljava/lang/StringBuilder;
    //   1622: ldc_w 372
    //   1625: invokevirtual 151	java/lang/StringBuilder:append	(Ljava/lang/String;)Ljava/lang/StringBuilder;
    //   1628: aload_0
    //   1629: getfield 23	pd:g	Landroid/net/Uri;
    //   1632: invokevirtual 162	android/net/Uri:toString	()Ljava/lang/String;
    //   1635: invokevirtual 151	java/lang/StringBuilder:append	(Ljava/lang/String;)Ljava/lang/StringBuilder;
    //   1638: invokevirtual 163	java/lang/StringBuilder:toString	()Ljava/lang/String;
    //   1641: invokestatic 169	android/util/Log:d	(Ljava/lang/String;Ljava/lang/String;)I
    //   1644: pop
    //   1645: goto -62 -> 1583
    //   1648: invokestatic 220	com/android/mms/MmsApp:c	()Lcom/android/mms/MmsApp;
    //   1651: invokestatic 364	com/android/mms/MmsApp:a	()Landroid/net/Uri;
    //   1654: ldc_w 365
    //   1657: invokestatic 370	com/android/mms/transaction/MessagingNotification:a	(Landroid/content/Context;Landroid/net/Uri;F)V
    //   1660: ldc 47
    //   1662: new 143	java/lang/StringBuilder
    //   1665: dup
    //   1666: invokespecial 145	java/lang/StringBuilder:<init>	()V
    //   1669: ldc_w 331
    //   1672: invokevirtual 151	java/lang/StringBuilder:append	(Ljava/lang/String;)Ljava/lang/StringBuilder;
    //   1675: aload_0
    //   1676: getfield 154	pd:m	I
    //   1679: invokevirtual 157	java/lang/StringBuilder:append	(I)Ljava/lang/StringBuilder;
    //   1682: ldc_w 372
    //   1685: invokevirtual 151	java/lang/StringBuilder:append	(Ljava/lang/String;)Ljava/lang/StringBuilder;
    //   1688: aload_0
    //   1689: getfield 23	pd:g	Landroid/net/Uri;
    //   1692: invokevirtual 162	android/net/Uri:toString	()Ljava/lang/String;
    //   1695: invokevirtual 151	java/lang/StringBuilder:append	(Ljava/lang/String;)Ljava/lang/StringBuilder;
    //   1698: invokevirtual 163	java/lang/StringBuilder:toString	()Ljava/lang/String;
    //   1701: invokestatic 169	android/util/Log:d	(Ljava/lang/String;Ljava/lang/String;)I
    //   1704: pop
    //   1705: goto -779 -> 926
    //   1708: invokestatic 220	com/android/mms/MmsApp:c	()Lcom/android/mms/MmsApp;
    //   1711: invokestatic 364	com/android/mms/MmsApp:a	()Landroid/net/Uri;
    //   1714: ldc_w 365
    //   1717: invokestatic 370	com/android/mms/transaction/MessagingNotification:a	(Landroid/content/Context;Landroid/net/Uri;F)V
    //   1720: ldc 47
    //   1722: new 143	java/lang/StringBuilder
    //   1725: dup
    //   1726: invokespecial 145	java/lang/StringBuilder:<init>	()V
    //   1729: ldc_w 331
    //   1732: invokevirtual 151	java/lang/StringBuilder:append	(Ljava/lang/String;)Ljava/lang/StringBuilder;
    //   1735: aload_0
    //   1736: getfield 154	pd:m	I
    //   1739: invokevirtual 157	java/lang/StringBuilder:append	(I)Ljava/lang/StringBuilder;
    //   1742: ldc_w 372
    //   1745: invokevirtual 151	java/lang/StringBuilder:append	(Ljava/lang/String;)Ljava/lang/StringBuilder;
    //   1748: aload_0
    //   1749: getfield 23	pd:g	Landroid/net/Uri;
    //   1752: invokevirtual 162	android/net/Uri:toString	()Ljava/lang/String;
    //   1755: invokevirtual 151	java/lang/StringBuilder:append	(Ljava/lang/String;)Ljava/lang/StringBuilder;
    //   1758: invokevirtual 163	java/lang/StringBuilder:toString	()Ljava/lang/String;
    //   1761: invokestatic 169	android/util/Log:d	(Ljava/lang/String;Ljava/lang/String;)I
    //   1764: pop
    //   1765: goto -743 -> 1022
    //   1768: iconst_0
    //   1769: istore_2
    //   1770: iconst_0
    //   1771: istore_1
    //   1772: ldc_w 405
    //   1775: astore 7
    //   1777: ldc_w 407
    //   1780: astore 6
    //   1782: goto -1484 -> 298
    //   1785: iconst_0
    //   1786: istore_2
    //   1787: iconst_0
    //   1788: istore_1
    //   1789: ldc_w 407
    //   1792: astore 6
    //   1794: ldc_w 405
    //   1797: astore 7
    //   1799: goto -1494 -> 305
    //   1802: iload 5
    //   1804: ifne -684 -> 1120
    //   1807: sipush 9527
    //   1810: istore_1
    //   1811: goto -691 -> 1120
    // Local variable table:
    //   start	length	slot	name	signature
    //   0	1814	0	this	pd
    //   280	1531	1	i	int
    //   297	1490	2	j	int
    //   30	1235	3	l	long
    //   375	1428	5	bool	boolean
    //   715	10	6	localObject2	Object
    //   727	5	6	localThrowable	Throwable
    //   748	192	6	localContentValues	android.content.ContentValues
    //   945	82	6	localObject3	Object
    //   1216	577	6	localObject4	Object
    //   244	359	7	localObject5	Object
    //   937	6	7	localObject6	Object
    //   1097	701	7	localObject7	Object
    //   7	1471	8	localMzPduPersister	com.meizu.android.mms.pdu.MzPduPersister
    //   21	600	9	localObject8	Object
    //   201	517	10	localCursor	android.database.Cursor
    // Exception table:
    //   from	to	target	type
    //   208	298	715	finally
    //   0	104	727	java/lang/Throwable
    //   104	203	727	java/lang/Throwable
    //   298	305	727	java/lang/Throwable
    //   309	363	727	java/lang/Throwable
    //   363	374	727	java/lang/Throwable
    //   377	425	727	java/lang/Throwable
    //   430	439	727	java/lang/Throwable
    //   449	635	727	java/lang/Throwable
    //   717	727	727	java/lang/Throwable
    //   942	945	727	java/lang/Throwable
    //   1089	1104	727	java/lang/Throwable
    //   1120	1175	727	java/lang/Throwable
    //   1182	1276	727	java/lang/Throwable
    //   1276	1302	727	java/lang/Throwable
    //   1442	1508	727	java/lang/Throwable
    //   439	449	937	finally
    //   939	942	937	finally
    //   0	104	945	finally
    //   104	203	945	finally
    //   298	305	945	finally
    //   309	363	945	finally
    //   363	374	945	finally
    //   377	425	945	finally
    //   430	439	945	finally
    //   449	635	945	finally
    //   717	727	945	finally
    //   729	851	945	finally
    //   942	945	945	finally
    //   1089	1104	945	finally
    //   1120	1175	945	finally
    //   1182	1276	945	finally
    //   1276	1302	945	finally
    //   1442	1508	945	finally
  }
}

/* Location:
 * Qualified Name:     pd
 * Java Class Version: 6 (50.0)
 * JD-Core Version:    0.7.1
 */