package cn.com.xy.sms.sdk.util;

import cn.com.xy.sms.sdk.Iservice.XyCallBack;
import java.util.List;

final class s
  implements XyCallBack
{
  s(List paramList, int paramInt, boolean paramBoolean) {}
  
  /* Error */
  public final void execute(Object... paramVarArgs)
  {
    // Byte code:
    //   0: aload_1
    //   1: ifnull +292 -> 293
    //   4: aload_1
    //   5: iconst_0
    //   6: aaload
    //   7: invokevirtual 32	java/lang/Object:toString	()Ljava/lang/String;
    //   10: ldc 34
    //   12: invokevirtual 40	java/lang/String:equals	(Ljava/lang/Object;)Z
    //   15: ifeq +278 -> 293
    //   18: aload_1
    //   19: arraylength
    //   20: iconst_2
    //   21: if_icmpne +272 -> 293
    //   24: aload_1
    //   25: iconst_1
    //   26: aaload
    //   27: invokevirtual 32	java/lang/Object:toString	()Ljava/lang/String;
    //   30: astore_1
    //   31: aload_0
    //   32: getfield 16	cn/com/xy/sms/sdk/util/s:a	Ljava/util/List;
    //   35: ifnull +30 -> 65
    //   38: aload_0
    //   39: getfield 16	cn/com/xy/sms/sdk/util/s:a	Ljava/util/List;
    //   42: invokeinterface 46 1 0
    //   47: ifne +18 -> 65
    //   50: aload_0
    //   51: getfield 16	cn/com/xy/sms/sdk/util/s:a	Ljava/util/List;
    //   54: invokeinterface 50 1 0
    //   59: istore_3
    //   60: iconst_0
    //   61: istore_2
    //   62: goto +223 -> 285
    //   65: aload_1
    //   66: invokestatic 56	cn/com/xy/sms/sdk/net/util/h:e	(Ljava/lang/String;)Ljava/util/HashMap;
    //   69: astore_1
    //   70: aload_1
    //   71: ifnull +222 -> 293
    //   74: aload_1
    //   75: ldc 58
    //   77: invokevirtual 64	java/util/HashMap:get	(Ljava/lang/Object;)Ljava/lang/Object;
    //   80: checkcast 66	java/util/ArrayList
    //   83: astore 5
    //   85: new 68	java/lang/StringBuilder
    //   88: dup
    //   89: ldc 70
    //   91: invokespecial 73	java/lang/StringBuilder:<init>	(Ljava/lang/String;)V
    //   94: aload 5
    //   96: invokevirtual 77	java/lang/StringBuilder:append	(Ljava/lang/Object;)Ljava/lang/StringBuilder;
    //   99: pop
    //   100: aload 5
    //   102: aload_0
    //   103: getfield 18	cn/com/xy/sms/sdk/util/s:b	I
    //   106: invokestatic 83	cn/com/xy/sms/sdk/util/SceneconfigUtil:handleSceneconfig	(Ljava/util/List;I)V
    //   109: aload_1
    //   110: ldc 85
    //   112: invokevirtual 64	java/util/HashMap:get	(Ljava/lang/Object;)Ljava/lang/Object;
    //   115: checkcast 66	java/util/ArrayList
    //   118: astore_1
    //   119: new 68	java/lang/StringBuilder
    //   122: dup
    //   123: ldc 87
    //   125: invokespecial 73	java/lang/StringBuilder:<init>	(Ljava/lang/String;)V
    //   128: aload_1
    //   129: invokevirtual 77	java/lang/StringBuilder:append	(Ljava/lang/Object;)Ljava/lang/StringBuilder;
    //   132: pop
    //   133: aload_0
    //   134: getfield 16	cn/com/xy/sms/sdk/util/s:a	Ljava/util/List;
    //   137: aload_1
    //   138: aload_0
    //   139: getfield 18	cn/com/xy/sms/sdk/util/s:b	I
    //   142: invokestatic 91	cn/com/xy/sms/sdk/util/SceneconfigUtil:handleSceneUrllist	(Ljava/util/List;Ljava/util/ArrayList;I)V
    //   145: return
    //   146: aload_0
    //   147: getfield 16	cn/com/xy/sms/sdk/util/s:a	Ljava/util/List;
    //   150: iload_2
    //   151: invokeinterface 94 2 0
    //   156: checkcast 96	cn/com/xy/sms/sdk/db/entity/p
    //   159: astore 5
    //   161: aload 5
    //   163: getfield 99	cn/com/xy/sms/sdk/db/entity/p:a	Ljava/lang/String;
    //   166: astore 6
    //   168: aload_0
    //   169: getfield 18	cn/com/xy/sms/sdk/util/s:b	I
    //   172: istore 4
    //   174: new 101	android/content/ContentValues
    //   177: dup
    //   178: invokespecial 102	android/content/ContentValues:<init>	()V
    //   181: astore 7
    //   183: aload 7
    //   185: ldc 104
    //   187: aload 6
    //   189: invokevirtual 108	android/content/ContentValues:put	(Ljava/lang/String;Ljava/lang/String;)V
    //   192: aload 7
    //   194: ldc 110
    //   196: iload 4
    //   198: invokestatic 116	java/lang/Integer:valueOf	(I)Ljava/lang/Integer;
    //   201: invokevirtual 119	android/content/ContentValues:put	(Ljava/lang/String;Ljava/lang/Integer;)V
    //   204: aload 7
    //   206: ldc 121
    //   208: iconst_1
    //   209: invokestatic 116	java/lang/Integer:valueOf	(I)Ljava/lang/Integer;
    //   212: invokevirtual 119	android/content/ContentValues:put	(Ljava/lang/String;Ljava/lang/Integer;)V
    //   215: ldc 123
    //   217: aload 7
    //   219: ldc 125
    //   221: iconst_2
    //   222: anewarray 36	java/lang/String
    //   225: dup
    //   226: iconst_0
    //   227: aload 6
    //   229: aastore
    //   230: dup
    //   231: iconst_1
    //   232: new 68	java/lang/StringBuilder
    //   235: dup
    //   236: iload 4
    //   238: invokestatic 128	java/lang/String:valueOf	(I)Ljava/lang/String;
    //   241: invokespecial 73	java/lang/StringBuilder:<init>	(Ljava/lang/String;)V
    //   244: invokevirtual 129	java/lang/StringBuilder:toString	()Ljava/lang/String;
    //   247: aastore
    //   248: invokestatic 135	cn/com/xy/sms/sdk/db/DBManager:update	(Ljava/lang/String;Landroid/content/ContentValues;Ljava/lang/String;[Ljava/lang/String;)I
    //   251: pop
    //   252: aload_0
    //   253: getfield 20	cn/com/xy/sms/sdk/util/s:c	Z
    //   256: ifeq +11 -> 267
    //   259: aload 5
    //   261: getfield 99	cn/com/xy/sms/sdk/db/entity/p:a	Ljava/lang/String;
    //   264: invokestatic 139	cn/com/xy/sms/sdk/db/entity/q:a	(Ljava/lang/String;)V
    //   267: iload_2
    //   268: iconst_1
    //   269: iadd
    //   270: istore_2
    //   271: goto +14 -> 285
    //   274: astore_1
    //   275: aload_1
    //   276: invokevirtual 142	java/lang/Throwable:printStackTrace	()V
    //   279: return
    //   280: astore 6
    //   282: goto -30 -> 252
    //   285: iload_2
    //   286: iload_3
    //   287: if_icmplt -141 -> 146
    //   290: goto -225 -> 65
    //   293: return
    // Local variable table:
    //   start	length	slot	name	signature
    //   0	294	0	this	s
    //   0	294	1	paramVarArgs	Object[]
    //   61	227	2	i	int
    //   59	229	3	j	int
    //   172	65	4	k	int
    //   83	177	5	localObject	Object
    //   166	62	6	str	String
    //   280	1	6	localThrowable	Throwable
    //   181	37	7	localContentValues	android.content.ContentValues
    // Exception table:
    //   from	to	target	type
    //   4	60	274	java/lang/Throwable
    //   65	70	274	java/lang/Throwable
    //   74	145	274	java/lang/Throwable
    //   146	174	274	java/lang/Throwable
    //   252	267	274	java/lang/Throwable
    //   174	252	280	java/lang/Throwable
  }
}

/* Location:
 * Qualified Name:     cn.com.xy.sms.sdk.util.s
 * Java Class Version: 6 (50.0)
 * JD-Core Version:    0.7.1
 */