package cn.com.xy.sms.sdk.util;

import android.content.Context;
import android.net.ConnectivityManager;
import android.net.NetworkInfo;
import android.os.Build;
import android.telephony.TelephonyManager;
import cn.com.xy.sms.sdk.Iservice.XyCallBack;
import cn.com.xy.sms.sdk.action.AbsSdkDoAction;
import cn.com.xy.sms.sdk.log.LogManager;
import java.io.ByteArrayOutputStream;
import java.io.File;
import java.io.IOException;
import java.io.InputStream;
import java.io.LineNumberReader;
import java.io.StringReader;
import java.util.HashMap;
import java.util.Iterator;
import java.util.List;
import java.util.Map;
import java.util.Map.Entry;
import java.util.Set;
import java.util.zip.Inflater;
import org.json.JSONArray;
import org.json.JSONObject;

public class XyUtil
{
  public static final String DEFAULT_IMEI = "360_DEFAULT_IMEI";
  private static String a = null;
  private static String b = null;
  
  private static String a(Map<String, Object> paramMap, String paramString)
  {
    for (;;)
    {
      JSONArray localJSONArray;
      int j;
      int i;
      try
      {
        localJSONArray = new JSONArray();
        paramString = new JSONArray(paramString);
        if (paramString.length() > 0)
        {
          j = paramString.length();
          i = 0;
          break label85;
        }
        paramMap = localJSONArray.toString();
        if (StringUtils.isNull(paramMap)) {
          break label82;
        }
        return paramMap;
      }
      catch (Throwable paramMap) {}
      JSONObject localJSONObject = a(paramMap, paramString.getJSONObject(i));
      if (localJSONObject != null) {
        localJSONArray.put(localJSONObject);
      }
      i += 1;
      break label85;
      label82:
      return "";
      label85:
      if (i < j) {}
    }
  }
  
  private static String a(JSONObject paramJSONObject)
  {
    String str = "";
    if (paramJSONObject != null) {
      str = StringUtils.encode(paramJSONObject.toString());
    }
    return str;
  }
  
  /* Error */
  private static JSONObject a(Map<String, Object> paramMap, JSONObject paramJSONObject)
  {
    // Byte code:
    //   0: aload_1
    //   1: ifnull +1495 -> 1496
    //   4: aload_0
    //   5: ldc 68
    //   7: invokeinterface 74 2 0
    //   12: checkcast 76	java/lang/String
    //   15: astore 6
    //   17: aload_1
    //   18: ldc 78
    //   20: invokevirtual 81	org/json/JSONObject:get	(Ljava/lang/String;)Ljava/lang/Object;
    //   23: checkcast 76	java/lang/String
    //   26: astore 7
    //   28: ldc 83
    //   30: aload 7
    //   32: invokevirtual 86	java/lang/String:equalsIgnoreCase	(Ljava/lang/String;)Z
    //   35: ifeq +123 -> 158
    //   38: aload_1
    //   39: ldc 88
    //   41: invokevirtual 81	org/json/JSONObject:get	(Ljava/lang/String;)Ljava/lang/Object;
    //   44: checkcast 76	java/lang/String
    //   47: astore 8
    //   49: aload_1
    //   50: ldc 90
    //   52: invokestatic 96	cn/com/xy/sms/sdk/util/JsonUtil:getValueFromJsonObject	(Lorg/json/JSONObject;Ljava/lang/String;)Ljava/lang/Object;
    //   55: checkcast 76	java/lang/String
    //   58: astore 5
    //   60: aload 5
    //   62: astore 4
    //   64: aload 5
    //   66: invokestatic 43	cn/com/xy/sms/sdk/util/StringUtils:isNull	(Ljava/lang/String;)Z
    //   69: ifeq +14 -> 83
    //   72: aload_0
    //   73: ldc 98
    //   75: invokestatic 102	cn/com/xy/sms/sdk/util/JsonUtil:getValueWithMap	(Ljava/util/Map;Ljava/lang/String;)Ljava/lang/Object;
    //   78: checkcast 76	java/lang/String
    //   81: astore 4
    //   83: bipush 8
    //   85: anewarray 76	java/lang/String
    //   88: dup
    //   89: iconst_0
    //   90: ldc 104
    //   92: aastore
    //   93: dup
    //   94: iconst_1
    //   95: aload 7
    //   97: aastore
    //   98: dup
    //   99: iconst_2
    //   100: ldc 88
    //   102: aastore
    //   103: dup
    //   104: iconst_3
    //   105: aload 8
    //   107: aastore
    //   108: dup
    //   109: iconst_4
    //   110: ldc 90
    //   112: aastore
    //   113: dup
    //   114: iconst_5
    //   115: aload 4
    //   117: aastore
    //   118: dup
    //   119: bipush 6
    //   121: ldc 106
    //   123: aastore
    //   124: dup
    //   125: bipush 7
    //   127: aload 6
    //   129: aastore
    //   130: invokestatic 109	cn/com/xy/sms/sdk/util/XyUtil:b	([Ljava/lang/String;)Ljava/lang/String;
    //   133: astore_0
    //   134: aload_1
    //   135: ldc 88
    //   137: invokevirtual 112	org/json/JSONObject:remove	(Ljava/lang/String;)Ljava/lang/Object;
    //   140: pop
    //   141: aload_1
    //   142: ldc 90
    //   144: invokevirtual 112	org/json/JSONObject:remove	(Ljava/lang/String;)Ljava/lang/Object;
    //   147: pop
    //   148: aload_1
    //   149: ldc 114
    //   151: aload_0
    //   152: invokevirtual 117	org/json/JSONObject:put	(Ljava/lang/String;Ljava/lang/Object;)Lorg/json/JSONObject;
    //   155: pop
    //   156: aload_1
    //   157: areturn
    //   158: ldc 119
    //   160: aload 7
    //   162: invokevirtual 86	java/lang/String:equalsIgnoreCase	(Ljava/lang/String;)Z
    //   165: ifeq +92 -> 257
    //   168: bipush 8
    //   170: anewarray 76	java/lang/String
    //   173: dup
    //   174: iconst_0
    //   175: ldc 104
    //   177: aastore
    //   178: dup
    //   179: iconst_1
    //   180: aload 7
    //   182: aastore
    //   183: dup
    //   184: iconst_2
    //   185: ldc 88
    //   187: aastore
    //   188: dup
    //   189: iconst_3
    //   190: aload_1
    //   191: ldc 88
    //   193: invokevirtual 81	org/json/JSONObject:get	(Ljava/lang/String;)Ljava/lang/Object;
    //   196: checkcast 76	java/lang/String
    //   199: aastore
    //   200: dup
    //   201: iconst_4
    //   202: ldc 90
    //   204: aastore
    //   205: dup
    //   206: iconst_5
    //   207: aload_1
    //   208: ldc 90
    //   210: invokevirtual 81	org/json/JSONObject:get	(Ljava/lang/String;)Ljava/lang/Object;
    //   213: checkcast 76	java/lang/String
    //   216: aastore
    //   217: dup
    //   218: bipush 6
    //   220: ldc 106
    //   222: aastore
    //   223: dup
    //   224: bipush 7
    //   226: aload 6
    //   228: aastore
    //   229: invokestatic 109	cn/com/xy/sms/sdk/util/XyUtil:b	([Ljava/lang/String;)Ljava/lang/String;
    //   232: astore_0
    //   233: aload_1
    //   234: ldc 88
    //   236: invokevirtual 112	org/json/JSONObject:remove	(Ljava/lang/String;)Ljava/lang/Object;
    //   239: pop
    //   240: aload_1
    //   241: ldc 90
    //   243: invokevirtual 112	org/json/JSONObject:remove	(Ljava/lang/String;)Ljava/lang/Object;
    //   246: pop
    //   247: aload_1
    //   248: ldc 114
    //   250: aload_0
    //   251: invokevirtual 117	org/json/JSONObject:put	(Ljava/lang/String;Ljava/lang/Object;)Lorg/json/JSONObject;
    //   254: pop
    //   255: aload_1
    //   256: areturn
    //   257: ldc 121
    //   259: aload 7
    //   261: invokevirtual 86	java/lang/String:equalsIgnoreCase	(Ljava/lang/String;)Z
    //   264: ifeq +66 -> 330
    //   267: bipush 6
    //   269: anewarray 76	java/lang/String
    //   272: dup
    //   273: iconst_0
    //   274: ldc 104
    //   276: aastore
    //   277: dup
    //   278: iconst_1
    //   279: aload 7
    //   281: aastore
    //   282: dup
    //   283: iconst_2
    //   284: ldc 123
    //   286: aastore
    //   287: dup
    //   288: iconst_3
    //   289: aload_1
    //   290: ldc 123
    //   292: invokevirtual 81	org/json/JSONObject:get	(Ljava/lang/String;)Ljava/lang/Object;
    //   295: checkcast 76	java/lang/String
    //   298: aastore
    //   299: dup
    //   300: iconst_4
    //   301: ldc 106
    //   303: aastore
    //   304: dup
    //   305: iconst_5
    //   306: aload 6
    //   308: aastore
    //   309: invokestatic 109	cn/com/xy/sms/sdk/util/XyUtil:b	([Ljava/lang/String;)Ljava/lang/String;
    //   312: astore_0
    //   313: aload_1
    //   314: ldc 123
    //   316: invokevirtual 112	org/json/JSONObject:remove	(Ljava/lang/String;)Ljava/lang/Object;
    //   319: pop
    //   320: aload_1
    //   321: ldc 114
    //   323: aload_0
    //   324: invokevirtual 117	org/json/JSONObject:put	(Ljava/lang/String;Ljava/lang/Object;)Lorg/json/JSONObject;
    //   327: pop
    //   328: aload_1
    //   329: areturn
    //   330: ldc 125
    //   332: aload 7
    //   334: invokevirtual 86	java/lang/String:equalsIgnoreCase	(Ljava/lang/String;)Z
    //   337: ifne +13 -> 350
    //   340: ldc 127
    //   342: aload 7
    //   344: invokevirtual 86	java/lang/String:equalsIgnoreCase	(Ljava/lang/String;)Z
    //   347: ifeq +66 -> 413
    //   350: bipush 6
    //   352: anewarray 76	java/lang/String
    //   355: dup
    //   356: iconst_0
    //   357: ldc 104
    //   359: aastore
    //   360: dup
    //   361: iconst_1
    //   362: aload 7
    //   364: aastore
    //   365: dup
    //   366: iconst_2
    //   367: ldc 123
    //   369: aastore
    //   370: dup
    //   371: iconst_3
    //   372: aload_1
    //   373: ldc 123
    //   375: invokevirtual 81	org/json/JSONObject:get	(Ljava/lang/String;)Ljava/lang/Object;
    //   378: checkcast 76	java/lang/String
    //   381: aastore
    //   382: dup
    //   383: iconst_4
    //   384: ldc 106
    //   386: aastore
    //   387: dup
    //   388: iconst_5
    //   389: aload 6
    //   391: aastore
    //   392: invokestatic 109	cn/com/xy/sms/sdk/util/XyUtil:b	([Ljava/lang/String;)Ljava/lang/String;
    //   395: astore_0
    //   396: aload_1
    //   397: ldc 123
    //   399: invokevirtual 112	org/json/JSONObject:remove	(Ljava/lang/String;)Ljava/lang/Object;
    //   402: pop
    //   403: aload_1
    //   404: ldc 114
    //   406: aload_0
    //   407: invokevirtual 117	org/json/JSONObject:put	(Ljava/lang/String;Ljava/lang/Object;)Lorg/json/JSONObject;
    //   410: pop
    //   411: aload_1
    //   412: areturn
    //   413: ldc -127
    //   415: aload 7
    //   417: invokevirtual 86	java/lang/String:equalsIgnoreCase	(Ljava/lang/String;)Z
    //   420: ifeq +66 -> 486
    //   423: bipush 6
    //   425: anewarray 76	java/lang/String
    //   428: dup
    //   429: iconst_0
    //   430: ldc 104
    //   432: aastore
    //   433: dup
    //   434: iconst_1
    //   435: aload 7
    //   437: aastore
    //   438: dup
    //   439: iconst_2
    //   440: ldc 123
    //   442: aastore
    //   443: dup
    //   444: iconst_3
    //   445: aload_1
    //   446: ldc 123
    //   448: invokevirtual 81	org/json/JSONObject:get	(Ljava/lang/String;)Ljava/lang/Object;
    //   451: checkcast 76	java/lang/String
    //   454: aastore
    //   455: dup
    //   456: iconst_4
    //   457: ldc 106
    //   459: aastore
    //   460: dup
    //   461: iconst_5
    //   462: aload 6
    //   464: aastore
    //   465: invokestatic 109	cn/com/xy/sms/sdk/util/XyUtil:b	([Ljava/lang/String;)Ljava/lang/String;
    //   468: astore_0
    //   469: aload_1
    //   470: ldc 123
    //   472: invokevirtual 112	org/json/JSONObject:remove	(Ljava/lang/String;)Ljava/lang/Object;
    //   475: pop
    //   476: aload_1
    //   477: ldc 114
    //   479: aload_0
    //   480: invokevirtual 117	org/json/JSONObject:put	(Ljava/lang/String;Ljava/lang/Object;)Lorg/json/JSONObject;
    //   483: pop
    //   484: aload_1
    //   485: areturn
    //   486: ldc -125
    //   488: aload 7
    //   490: invokevirtual 86	java/lang/String:equalsIgnoreCase	(Ljava/lang/String;)Z
    //   493: ifne +13 -> 506
    //   496: ldc -123
    //   498: aload 7
    //   500: invokevirtual 86	java/lang/String:equalsIgnoreCase	(Ljava/lang/String;)Z
    //   503: ifeq +66 -> 569
    //   506: bipush 6
    //   508: anewarray 76	java/lang/String
    //   511: dup
    //   512: iconst_0
    //   513: ldc 104
    //   515: aastore
    //   516: dup
    //   517: iconst_1
    //   518: aload 7
    //   520: aastore
    //   521: dup
    //   522: iconst_2
    //   523: ldc 90
    //   525: aastore
    //   526: dup
    //   527: iconst_3
    //   528: aload_1
    //   529: ldc 90
    //   531: invokevirtual 81	org/json/JSONObject:get	(Ljava/lang/String;)Ljava/lang/Object;
    //   534: checkcast 76	java/lang/String
    //   537: aastore
    //   538: dup
    //   539: iconst_4
    //   540: ldc 106
    //   542: aastore
    //   543: dup
    //   544: iconst_5
    //   545: aload 6
    //   547: aastore
    //   548: invokestatic 109	cn/com/xy/sms/sdk/util/XyUtil:b	([Ljava/lang/String;)Ljava/lang/String;
    //   551: astore_0
    //   552: aload_1
    //   553: ldc 90
    //   555: invokevirtual 112	org/json/JSONObject:remove	(Ljava/lang/String;)Ljava/lang/Object;
    //   558: pop
    //   559: aload_1
    //   560: ldc 114
    //   562: aload_0
    //   563: invokevirtual 117	org/json/JSONObject:put	(Ljava/lang/String;Ljava/lang/Object;)Lorg/json/JSONObject;
    //   566: pop
    //   567: aload_1
    //   568: areturn
    //   569: ldc -121
    //   571: aload 7
    //   573: invokevirtual 86	java/lang/String:equalsIgnoreCase	(Ljava/lang/String;)Z
    //   576: ifne +13 -> 589
    //   579: ldc -119
    //   581: aload 7
    //   583: invokevirtual 86	java/lang/String:equalsIgnoreCase	(Ljava/lang/String;)Z
    //   586: ifeq +82 -> 668
    //   589: bipush 6
    //   591: anewarray 76	java/lang/String
    //   594: dup
    //   595: iconst_0
    //   596: ldc 104
    //   598: aastore
    //   599: dup
    //   600: iconst_1
    //   601: ldc -117
    //   603: aastore
    //   604: dup
    //   605: iconst_2
    //   606: ldc -115
    //   608: aastore
    //   609: dup
    //   610: iconst_3
    //   611: aload_1
    //   612: ldc -115
    //   614: invokevirtual 81	org/json/JSONObject:get	(Ljava/lang/String;)Ljava/lang/Object;
    //   617: checkcast 76	java/lang/String
    //   620: aastore
    //   621: dup
    //   622: iconst_4
    //   623: ldc 106
    //   625: aastore
    //   626: dup
    //   627: iconst_5
    //   628: aload 6
    //   630: aastore
    //   631: invokestatic 109	cn/com/xy/sms/sdk/util/XyUtil:b	([Ljava/lang/String;)Ljava/lang/String;
    //   634: astore_0
    //   635: aload_1
    //   636: ldc -115
    //   638: invokevirtual 112	org/json/JSONObject:remove	(Ljava/lang/String;)Ljava/lang/Object;
    //   641: pop
    //   642: aload_1
    //   643: ldc 78
    //   645: invokevirtual 112	org/json/JSONObject:remove	(Ljava/lang/String;)Ljava/lang/Object;
    //   648: pop
    //   649: aload_1
    //   650: ldc 78
    //   652: ldc -117
    //   654: invokevirtual 117	org/json/JSONObject:put	(Ljava/lang/String;Ljava/lang/Object;)Lorg/json/JSONObject;
    //   657: pop
    //   658: aload_1
    //   659: ldc 114
    //   661: aload_0
    //   662: invokevirtual 117	org/json/JSONObject:put	(Ljava/lang/String;Ljava/lang/Object;)Lorg/json/JSONObject;
    //   665: pop
    //   666: aload_1
    //   667: areturn
    //   668: ldc -113
    //   670: aload 7
    //   672: invokevirtual 86	java/lang/String:equalsIgnoreCase	(Ljava/lang/String;)Z
    //   675: ifeq +57 -> 732
    //   678: aload_1
    //   679: ldc 114
    //   681: bipush 6
    //   683: anewarray 76	java/lang/String
    //   686: dup
    //   687: iconst_0
    //   688: ldc 104
    //   690: aastore
    //   691: dup
    //   692: iconst_1
    //   693: aload 7
    //   695: aastore
    //   696: dup
    //   697: iconst_2
    //   698: ldc 106
    //   700: aastore
    //   701: dup
    //   702: iconst_3
    //   703: aload 6
    //   705: aastore
    //   706: dup
    //   707: iconst_4
    //   708: ldc 90
    //   710: aastore
    //   711: dup
    //   712: iconst_5
    //   713: aload_1
    //   714: ldc 90
    //   716: invokevirtual 81	org/json/JSONObject:get	(Ljava/lang/String;)Ljava/lang/Object;
    //   719: checkcast 76	java/lang/String
    //   722: aastore
    //   723: invokestatic 109	cn/com/xy/sms/sdk/util/XyUtil:b	([Ljava/lang/String;)Ljava/lang/String;
    //   726: invokevirtual 117	org/json/JSONObject:put	(Ljava/lang/String;Ljava/lang/Object;)Lorg/json/JSONObject;
    //   729: pop
    //   730: aload_1
    //   731: areturn
    //   732: ldc -111
    //   734: aload 7
    //   736: invokevirtual 86	java/lang/String:equalsIgnoreCase	(Ljava/lang/String;)Z
    //   739: ifeq +66 -> 805
    //   742: bipush 6
    //   744: anewarray 76	java/lang/String
    //   747: dup
    //   748: iconst_0
    //   749: ldc 104
    //   751: aastore
    //   752: dup
    //   753: iconst_1
    //   754: aload 7
    //   756: aastore
    //   757: dup
    //   758: iconst_2
    //   759: ldc 106
    //   761: aastore
    //   762: dup
    //   763: iconst_3
    //   764: aload 6
    //   766: aastore
    //   767: dup
    //   768: iconst_4
    //   769: ldc -109
    //   771: aastore
    //   772: dup
    //   773: iconst_5
    //   774: aload_1
    //   775: ldc -109
    //   777: invokevirtual 81	org/json/JSONObject:get	(Ljava/lang/String;)Ljava/lang/Object;
    //   780: checkcast 76	java/lang/String
    //   783: aastore
    //   784: invokestatic 109	cn/com/xy/sms/sdk/util/XyUtil:b	([Ljava/lang/String;)Ljava/lang/String;
    //   787: astore_0
    //   788: aload_1
    //   789: ldc -109
    //   791: invokevirtual 112	org/json/JSONObject:remove	(Ljava/lang/String;)Ljava/lang/Object;
    //   794: pop
    //   795: aload_1
    //   796: ldc 114
    //   798: aload_0
    //   799: invokevirtual 117	org/json/JSONObject:put	(Ljava/lang/String;Ljava/lang/Object;)Lorg/json/JSONObject;
    //   802: pop
    //   803: aload_1
    //   804: areturn
    //   805: ldc -107
    //   807: aload 7
    //   809: invokevirtual 86	java/lang/String:equalsIgnoreCase	(Ljava/lang/String;)Z
    //   812: istore_3
    //   813: iload_3
    //   814: ifeq +69 -> 883
    //   817: iconst_4
    //   818: anewarray 76	java/lang/String
    //   821: dup
    //   822: iconst_0
    //   823: ldc 104
    //   825: aastore
    //   826: dup
    //   827: iconst_1
    //   828: aload 7
    //   830: aastore
    //   831: dup
    //   832: iconst_2
    //   833: ldc 106
    //   835: aastore
    //   836: dup
    //   837: iconst_3
    //   838: aload 6
    //   840: aastore
    //   841: invokestatic 152	cn/com/xy/sms/sdk/util/XyUtil:a	([Ljava/lang/String;)Lorg/json/JSONObject;
    //   844: astore_0
    //   845: aload_0
    //   846: ldc -102
    //   848: aload_1
    //   849: ldc -102
    //   851: invokevirtual 81	org/json/JSONObject:get	(Ljava/lang/String;)Ljava/lang/Object;
    //   854: invokevirtual 117	org/json/JSONObject:put	(Ljava/lang/String;Ljava/lang/Object;)Lorg/json/JSONObject;
    //   857: pop
    //   858: aload_0
    //   859: invokestatic 156	cn/com/xy/sms/sdk/util/XyUtil:a	(Lorg/json/JSONObject;)Ljava/lang/String;
    //   862: astore_0
    //   863: aload_1
    //   864: ldc -102
    //   866: invokevirtual 112	org/json/JSONObject:remove	(Ljava/lang/String;)Ljava/lang/Object;
    //   869: pop
    //   870: aload_1
    //   871: ldc 114
    //   873: aload_0
    //   874: invokevirtual 117	org/json/JSONObject:put	(Ljava/lang/String;Ljava/lang/Object;)Lorg/json/JSONObject;
    //   877: pop
    //   878: aload_1
    //   879: areturn
    //   880: astore_0
    //   881: aload_1
    //   882: areturn
    //   883: ldc -98
    //   885: aload 7
    //   887: invokevirtual 86	java/lang/String:equalsIgnoreCase	(Ljava/lang/String;)Z
    //   890: istore_3
    //   891: iload_3
    //   892: ifeq +196 -> 1088
    //   895: fconst_0
    //   896: invokestatic 164	java/lang/Float:valueOf	(F)Ljava/lang/Float;
    //   899: astore 5
    //   901: iconst_0
    //   902: invokestatic 169	java/lang/Integer:valueOf	(I)Ljava/lang/Integer;
    //   905: astore_0
    //   906: aload_1
    //   907: ldc -85
    //   909: invokevirtual 81	org/json/JSONObject:get	(Ljava/lang/String;)Ljava/lang/Object;
    //   912: checkcast 166	java/lang/Integer
    //   915: astore 4
    //   917: aload 4
    //   919: astore_0
    //   920: aload_0
    //   921: invokevirtual 174	java/lang/Integer:intValue	()I
    //   924: istore_2
    //   925: aload 5
    //   927: astore 4
    //   929: iload_2
    //   930: ifne +14 -> 944
    //   933: aload_1
    //   934: ldc -85
    //   936: invokevirtual 81	org/json/JSONObject:get	(Ljava/lang/String;)Ljava/lang/Object;
    //   939: checkcast 160	java/lang/Float
    //   942: astore 4
    //   944: aload_0
    //   945: invokevirtual 174	java/lang/Integer:intValue	()I
    //   948: ifeq +539 -> 1487
    //   951: aload_0
    //   952: invokestatic 177	java/lang/String:valueOf	(Ljava/lang/Object;)Ljava/lang/String;
    //   955: astore_0
    //   956: aload 4
    //   958: invokevirtual 181	java/lang/Float:floatValue	()F
    //   961: fconst_0
    //   962: fcmpl
    //   963: ifeq +9 -> 972
    //   966: aload 4
    //   968: invokestatic 177	java/lang/String:valueOf	(Ljava/lang/Object;)Ljava/lang/String;
    //   971: astore_0
    //   972: bipush 6
    //   974: anewarray 76	java/lang/String
    //   977: dup
    //   978: iconst_0
    //   979: ldc 104
    //   981: aastore
    //   982: dup
    //   983: iconst_1
    //   984: aload 7
    //   986: aastore
    //   987: dup
    //   988: iconst_2
    //   989: ldc 106
    //   991: aastore
    //   992: dup
    //   993: iconst_3
    //   994: aload 6
    //   996: aastore
    //   997: dup
    //   998: iconst_4
    //   999: ldc -85
    //   1001: aastore
    //   1002: dup
    //   1003: iconst_5
    //   1004: aload_0
    //   1005: aastore
    //   1006: invokestatic 152	cn/com/xy/sms/sdk/util/XyUtil:a	([Ljava/lang/String;)Lorg/json/JSONObject;
    //   1009: astore_0
    //   1010: aload_0
    //   1011: ldc -102
    //   1013: aload_1
    //   1014: ldc -102
    //   1016: invokevirtual 81	org/json/JSONObject:get	(Ljava/lang/String;)Ljava/lang/Object;
    //   1019: invokevirtual 117	org/json/JSONObject:put	(Ljava/lang/String;Ljava/lang/Object;)Lorg/json/JSONObject;
    //   1022: pop
    //   1023: aload_0
    //   1024: ldc -73
    //   1026: aload_1
    //   1027: ldc -73
    //   1029: invokestatic 96	cn/com/xy/sms/sdk/util/JsonUtil:getValueFromJsonObject	(Lorg/json/JSONObject;Ljava/lang/String;)Ljava/lang/Object;
    //   1032: invokevirtual 117	org/json/JSONObject:put	(Ljava/lang/String;Ljava/lang/Object;)Lorg/json/JSONObject;
    //   1035: pop
    //   1036: aload_0
    //   1037: ldc 90
    //   1039: aload_1
    //   1040: ldc 90
    //   1042: invokestatic 96	cn/com/xy/sms/sdk/util/JsonUtil:getValueFromJsonObject	(Lorg/json/JSONObject;Ljava/lang/String;)Ljava/lang/Object;
    //   1045: invokevirtual 117	org/json/JSONObject:put	(Ljava/lang/String;Ljava/lang/Object;)Lorg/json/JSONObject;
    //   1048: pop
    //   1049: aload_0
    //   1050: invokestatic 156	cn/com/xy/sms/sdk/util/XyUtil:a	(Lorg/json/JSONObject;)Ljava/lang/String;
    //   1053: astore_0
    //   1054: aload_1
    //   1055: ldc -73
    //   1057: invokevirtual 112	org/json/JSONObject:remove	(Ljava/lang/String;)Ljava/lang/Object;
    //   1060: pop
    //   1061: aload_1
    //   1062: ldc 90
    //   1064: invokevirtual 112	org/json/JSONObject:remove	(Ljava/lang/String;)Ljava/lang/Object;
    //   1067: pop
    //   1068: aload_1
    //   1069: ldc -102
    //   1071: invokevirtual 112	org/json/JSONObject:remove	(Ljava/lang/String;)Ljava/lang/Object;
    //   1074: pop
    //   1075: aload_1
    //   1076: ldc 114
    //   1078: aload_0
    //   1079: invokevirtual 117	org/json/JSONObject:put	(Ljava/lang/String;Ljava/lang/Object;)Lorg/json/JSONObject;
    //   1082: pop
    //   1083: aload_1
    //   1084: areturn
    //   1085: astore_0
    //   1086: aload_1
    //   1087: areturn
    //   1088: ldc -71
    //   1090: aload 7
    //   1092: invokevirtual 86	java/lang/String:equalsIgnoreCase	(Ljava/lang/String;)Z
    //   1095: istore_3
    //   1096: iload_3
    //   1097: ifeq +142 -> 1239
    //   1100: aload_1
    //   1101: ldc -69
    //   1103: invokevirtual 81	org/json/JSONObject:get	(Ljava/lang/String;)Ljava/lang/Object;
    //   1106: checkcast 76	java/lang/String
    //   1109: astore_0
    //   1110: aload_1
    //   1111: ldc -67
    //   1113: invokevirtual 81	org/json/JSONObject:get	(Ljava/lang/String;)Ljava/lang/Object;
    //   1116: checkcast 76	java/lang/String
    //   1119: astore 4
    //   1121: bipush 8
    //   1123: anewarray 76	java/lang/String
    //   1126: dup
    //   1127: iconst_0
    //   1128: ldc 104
    //   1130: aastore
    //   1131: dup
    //   1132: iconst_1
    //   1133: aload 7
    //   1135: aastore
    //   1136: dup
    //   1137: iconst_2
    //   1138: ldc 106
    //   1140: aastore
    //   1141: dup
    //   1142: iconst_3
    //   1143: aload 6
    //   1145: aastore
    //   1146: dup
    //   1147: iconst_4
    //   1148: ldc -69
    //   1150: aastore
    //   1151: dup
    //   1152: iconst_5
    //   1153: aload_0
    //   1154: aastore
    //   1155: dup
    //   1156: bipush 6
    //   1158: ldc -67
    //   1160: aastore
    //   1161: dup
    //   1162: bipush 7
    //   1164: aload 4
    //   1166: aastore
    //   1167: invokestatic 152	cn/com/xy/sms/sdk/util/XyUtil:a	([Ljava/lang/String;)Lorg/json/JSONObject;
    //   1170: astore 5
    //   1172: aload 5
    //   1174: ldc -65
    //   1176: iconst_4
    //   1177: anewarray 76	java/lang/String
    //   1180: dup
    //   1181: iconst_0
    //   1182: ldc -69
    //   1184: aastore
    //   1185: dup
    //   1186: iconst_1
    //   1187: aload_0
    //   1188: aastore
    //   1189: dup
    //   1190: iconst_2
    //   1191: ldc -67
    //   1193: aastore
    //   1194: dup
    //   1195: iconst_3
    //   1196: aload 4
    //   1198: aastore
    //   1199: invokestatic 152	cn/com/xy/sms/sdk/util/XyUtil:a	([Ljava/lang/String;)Lorg/json/JSONObject;
    //   1202: invokevirtual 117	org/json/JSONObject:put	(Ljava/lang/String;Ljava/lang/Object;)Lorg/json/JSONObject;
    //   1205: pop
    //   1206: aload 5
    //   1208: invokestatic 156	cn/com/xy/sms/sdk/util/XyUtil:a	(Lorg/json/JSONObject;)Ljava/lang/String;
    //   1211: astore_0
    //   1212: aload_1
    //   1213: ldc -69
    //   1215: invokevirtual 112	org/json/JSONObject:remove	(Ljava/lang/String;)Ljava/lang/Object;
    //   1218: pop
    //   1219: aload_1
    //   1220: ldc -67
    //   1222: invokevirtual 112	org/json/JSONObject:remove	(Ljava/lang/String;)Ljava/lang/Object;
    //   1225: pop
    //   1226: aload_1
    //   1227: ldc 114
    //   1229: aload_0
    //   1230: invokevirtual 117	org/json/JSONObject:put	(Ljava/lang/String;Ljava/lang/Object;)Lorg/json/JSONObject;
    //   1233: pop
    //   1234: aload_1
    //   1235: areturn
    //   1236: astore_0
    //   1237: aload_1
    //   1238: areturn
    //   1239: ldc -63
    //   1241: aload 7
    //   1243: invokevirtual 86	java/lang/String:equalsIgnoreCase	(Ljava/lang/String;)Z
    //   1246: istore_3
    //   1247: iload_3
    //   1248: ifeq +245 -> 1493
    //   1251: aload_1
    //   1252: ldc -61
    //   1254: invokevirtual 81	org/json/JSONObject:get	(Ljava/lang/String;)Ljava/lang/Object;
    //   1257: checkcast 76	java/lang/String
    //   1260: astore_0
    //   1261: aload_1
    //   1262: ldc -59
    //   1264: invokevirtual 81	org/json/JSONObject:get	(Ljava/lang/String;)Ljava/lang/Object;
    //   1267: checkcast 76	java/lang/String
    //   1270: astore 4
    //   1272: aload_1
    //   1273: ldc -57
    //   1275: invokevirtual 81	org/json/JSONObject:get	(Ljava/lang/String;)Ljava/lang/Object;
    //   1278: checkcast 76	java/lang/String
    //   1281: astore 5
    //   1283: aload_1
    //   1284: ldc -55
    //   1286: invokevirtual 81	org/json/JSONObject:get	(Ljava/lang/String;)Ljava/lang/Object;
    //   1289: checkcast 76	java/lang/String
    //   1292: astore 8
    //   1294: bipush 12
    //   1296: anewarray 76	java/lang/String
    //   1299: dup
    //   1300: iconst_0
    //   1301: ldc 104
    //   1303: aastore
    //   1304: dup
    //   1305: iconst_1
    //   1306: aload 7
    //   1308: aastore
    //   1309: dup
    //   1310: iconst_2
    //   1311: ldc 106
    //   1313: aastore
    //   1314: dup
    //   1315: iconst_3
    //   1316: aload 6
    //   1318: aastore
    //   1319: dup
    //   1320: iconst_4
    //   1321: ldc -61
    //   1323: aastore
    //   1324: dup
    //   1325: iconst_5
    //   1326: aload_0
    //   1327: aastore
    //   1328: dup
    //   1329: bipush 6
    //   1331: ldc -59
    //   1333: aastore
    //   1334: dup
    //   1335: bipush 7
    //   1337: aload 4
    //   1339: aastore
    //   1340: dup
    //   1341: bipush 8
    //   1343: ldc -57
    //   1345: aastore
    //   1346: dup
    //   1347: bipush 9
    //   1349: aload 5
    //   1351: aastore
    //   1352: dup
    //   1353: bipush 10
    //   1355: ldc -55
    //   1357: aastore
    //   1358: dup
    //   1359: bipush 11
    //   1361: aload 8
    //   1363: aastore
    //   1364: invokestatic 152	cn/com/xy/sms/sdk/util/XyUtil:a	([Ljava/lang/String;)Lorg/json/JSONObject;
    //   1367: astore 6
    //   1369: aload 6
    //   1371: ldc -65
    //   1373: bipush 8
    //   1375: anewarray 76	java/lang/String
    //   1378: dup
    //   1379: iconst_0
    //   1380: ldc -61
    //   1382: aastore
    //   1383: dup
    //   1384: iconst_1
    //   1385: aload_0
    //   1386: aastore
    //   1387: dup
    //   1388: iconst_2
    //   1389: ldc -59
    //   1391: aastore
    //   1392: dup
    //   1393: iconst_3
    //   1394: aload 4
    //   1396: aastore
    //   1397: dup
    //   1398: iconst_4
    //   1399: ldc -57
    //   1401: aastore
    //   1402: dup
    //   1403: iconst_5
    //   1404: aload 5
    //   1406: aastore
    //   1407: dup
    //   1408: bipush 6
    //   1410: ldc -55
    //   1412: aastore
    //   1413: dup
    //   1414: bipush 7
    //   1416: aload 8
    //   1418: aastore
    //   1419: invokestatic 152	cn/com/xy/sms/sdk/util/XyUtil:a	([Ljava/lang/String;)Lorg/json/JSONObject;
    //   1422: invokevirtual 117	org/json/JSONObject:put	(Ljava/lang/String;Ljava/lang/Object;)Lorg/json/JSONObject;
    //   1425: pop
    //   1426: aload 6
    //   1428: invokestatic 156	cn/com/xy/sms/sdk/util/XyUtil:a	(Lorg/json/JSONObject;)Ljava/lang/String;
    //   1431: astore_0
    //   1432: aload_1
    //   1433: ldc -61
    //   1435: invokevirtual 112	org/json/JSONObject:remove	(Ljava/lang/String;)Ljava/lang/Object;
    //   1438: pop
    //   1439: aload_1
    //   1440: ldc -59
    //   1442: invokevirtual 112	org/json/JSONObject:remove	(Ljava/lang/String;)Ljava/lang/Object;
    //   1445: pop
    //   1446: aload_1
    //   1447: ldc -57
    //   1449: invokevirtual 112	org/json/JSONObject:remove	(Ljava/lang/String;)Ljava/lang/Object;
    //   1452: pop
    //   1453: aload_1
    //   1454: ldc -55
    //   1456: invokevirtual 112	org/json/JSONObject:remove	(Ljava/lang/String;)Ljava/lang/Object;
    //   1459: pop
    //   1460: aload_1
    //   1461: ldc 114
    //   1463: aload_0
    //   1464: invokevirtual 117	org/json/JSONObject:put	(Ljava/lang/String;Ljava/lang/Object;)Lorg/json/JSONObject;
    //   1467: pop
    //   1468: aload_1
    //   1469: areturn
    //   1470: astore_0
    //   1471: aload_1
    //   1472: areturn
    //   1473: astore 4
    //   1475: aload 5
    //   1477: astore 4
    //   1479: goto -535 -> 944
    //   1482: astore 4
    //   1484: goto -564 -> 920
    //   1487: ldc 56
    //   1489: astore_0
    //   1490: goto -534 -> 956
    //   1493: aload_1
    //   1494: areturn
    //   1495: astore_0
    //   1496: aconst_null
    //   1497: areturn
    // Local variable table:
    //   start	length	slot	name	signature
    //   0	1498	0	paramMap	Map<String, Object>
    //   0	1498	1	paramJSONObject	JSONObject
    //   924	6	2	i	int
    //   812	436	3	bool	boolean
    //   62	1333	4	localObject1	Object
    //   1473	1	4	localThrowable1	Throwable
    //   1477	1	4	localObject2	Object
    //   1482	1	4	localThrowable2	Throwable
    //   58	1418	5	localObject3	Object
    //   15	1412	6	localObject4	Object
    //   26	1281	7	str1	String
    //   47	1370	8	str2	String
    // Exception table:
    //   from	to	target	type
    //   817	878	880	java/lang/Throwable
    //   895	901	1085	java/lang/Throwable
    //   920	925	1085	java/lang/Throwable
    //   944	956	1085	java/lang/Throwable
    //   956	972	1085	java/lang/Throwable
    //   972	1083	1085	java/lang/Throwable
    //   1100	1234	1236	java/lang/Throwable
    //   1251	1468	1470	java/lang/Throwable
    //   933	944	1473	java/lang/Throwable
    //   906	917	1482	java/lang/Throwable
    //   4	60	1495	java/lang/Throwable
    //   64	83	1495	java/lang/Throwable
    //   83	156	1495	java/lang/Throwable
    //   158	255	1495	java/lang/Throwable
    //   257	328	1495	java/lang/Throwable
    //   330	350	1495	java/lang/Throwable
    //   350	411	1495	java/lang/Throwable
    //   413	484	1495	java/lang/Throwable
    //   486	506	1495	java/lang/Throwable
    //   506	567	1495	java/lang/Throwable
    //   569	589	1495	java/lang/Throwable
    //   589	666	1495	java/lang/Throwable
    //   668	730	1495	java/lang/Throwable
    //   732	803	1495	java/lang/Throwable
    //   805	813	1495	java/lang/Throwable
    //   883	891	1495	java/lang/Throwable
    //   1088	1096	1495	java/lang/Throwable
    //   1239	1247	1495	java/lang/Throwable
  }
  
  private static JSONObject a(String... paramVarArgs)
  {
    if (paramVarArgs.length % 2 != 0) {
      return null;
    }
    JSONObject localJSONObject = new JSONObject();
    int i = 0;
    for (;;)
    {
      if (i >= paramVarArgs.length) {
        return localJSONObject;
      }
      try
      {
        localJSONObject.put(paramVarArgs[i], paramVarArgs[(i + 1)]);
        i += 2;
      }
      catch (Throwable localThrowable)
      {
        for (;;) {}
      }
    }
  }
  
  private static boolean a(int paramInt)
  {
    return paramInt == 1;
  }
  
  private static String b(String... paramVarArgs)
  {
    try
    {
      JSONObject localJSONObject = new JSONObject();
      int i = paramVarArgs.length;
      if (i % 2 != 0) {
        return "";
      }
      i = 0;
      for (;;)
      {
        if (i >= paramVarArgs.length) {
          return StringUtils.encode(localJSONObject.toString());
        }
        localJSONObject.put(paramVarArgs[i], paramVarArgs[(i + 1)]);
        i += 2;
      }
      return "";
    }
    catch (Throwable paramVarArgs) {}
  }
  
  private static boolean b(int paramInt)
  {
    return (paramInt == 0) || (paramInt == 4) || (paramInt == 5) || (paramInt == 2) || (paramInt == 3);
  }
  
  public static Map<String, String> changeObjMapToStrMap(HashMap<String, Object> paramHashMap)
  {
    try
    {
      HashMap localHashMap = new HashMap();
      if ((paramHashMap != null) && (!paramHashMap.isEmpty()))
      {
        paramHashMap = paramHashMap.entrySet().iterator();
        while (paramHashMap.hasNext())
        {
          Map.Entry localEntry = (Map.Entry)paramHashMap.next();
          if ((localEntry.getValue() instanceof String)) {
            localHashMap.put((String)localEntry.getKey(), (String)localEntry.getValue());
          }
        }
      }
      return localHashMap;
    }
    catch (Throwable paramHashMap)
    {
      return null;
    }
  }
  
  public static int checkNetWork(Context paramContext)
  {
    return checkNetWork(paramContext, 1);
  }
  
  public static int checkNetWork(Context paramContext, int paramInt)
  {
    if (paramContext == null) {
      return -1;
    }
    NetworkInfo localNetworkInfo = ((ConnectivityManager)paramContext.getSystemService("connectivity")).getActiveNetworkInfo();
    int i;
    if ((localNetworkInfo != null) && (localNetworkInfo.isAvailable())) {
      i = localNetworkInfo.getType();
    }
    switch (paramInt)
    {
    default: 
      return -1;
    case 0: 
      if (b(i)) {
        return 0;
      }
      return 1;
    case 1: 
      if (DuoquUtils.getSdkDoAction().getWifiType(paramContext) == 1) {
        return 1;
      }
      if (a(i)) {
        return 0;
      }
      return 1;
    }
    if ((a(i)) || (b(i))) {
      return 0;
    }
    return 1;
  }
  
  public static void chmod(String paramString1, String paramString2)
  {
    try
    {
      if (StringUtils.isNull(paramString2)) {
        return;
      }
      paramString1 = "chmod " + paramString1 + " " + paramString2;
      Runtime.getRuntime().exec(paramString1);
      return;
    }
    catch (IOException paramString1)
    {
      paramString1.printStackTrace();
      return;
    }
    catch (Throwable paramString1)
    {
      paramString1.printStackTrace();
    }
  }
  
  public static byte[] decompressBytes(byte[] paramArrayOfByte)
  {
    int i = 0;
    if ((paramArrayOfByte == null) || (paramArrayOfByte.length == 0)) {
      return null;
    }
    byte[] arrayOfByte1 = new byte[0];
    Inflater localInflater = new Inflater();
    localInflater.reset();
    localInflater.setInput(paramArrayOfByte);
    paramArrayOfByte = new ByteArrayOutputStream(paramArrayOfByte.length);
    try
    {
      byte[] arrayOfByte2 = new byte['਀'];
      long l = System.currentTimeMillis();
      if ((localInflater.finished()) || (localInflater.needsInput())) {}
      for (;;)
      {
        LogManager.e("duoqu_test", "decompressBytes: cnt " + i, null);
        arrayOfByte2 = paramArrayOfByte.toByteArray();
        try
        {
          localInflater.reset();
          d.a(paramArrayOfByte);
          localInflater.end();
          return arrayOfByte2;
        }
        catch (Throwable paramArrayOfByte)
        {
          paramArrayOfByte.printStackTrace();
          return arrayOfByte2;
        }
        int j = localInflater.inflate(arrayOfByte2);
        if (j > 0) {
          paramArrayOfByte.write(arrayOfByte2, 0, j);
        }
        if (i % 200 == 1) {
          Thread.sleep(1L);
        }
        if (System.currentTimeMillis() - l <= 10000L) {
          break;
        }
        LogManager.e("duoqu_test", "decompressBytes: > 5000", null);
      }
    }
    catch (Throwable localThrowable)
    {
      for (;;)
      {
        localThrowable = localThrowable;
        localThrowable.printStackTrace();
        try
        {
          localInflater.reset();
          d.a(paramArrayOfByte);
          localInflater.end();
          return arrayOfByte1;
        }
        catch (Throwable paramArrayOfByte)
        {
          paramArrayOfByte.printStackTrace();
          return arrayOfByte1;
        }
        i += 1;
      }
    }
    finally {}
    try
    {
      localInflater.reset();
      d.a(paramArrayOfByte);
      localInflater.end();
      throw ((Throwable)localObject);
    }
    catch (Throwable paramArrayOfByte)
    {
      for (;;)
      {
        paramArrayOfByte.printStackTrace();
      }
    }
  }
  
  public static void doXycallBack(XyCallBack paramXyCallBack, String paramString)
  {
    if (paramXyCallBack != null) {}
    try
    {
      paramXyCallBack.execute(new Object[] { paramString });
      return;
    }
    catch (Throwable paramXyCallBack) {}
  }
  
  public static void doXycallBackResult(XyCallBack paramXyCallBack, Object... paramVarArgs)
  {
    if (paramXyCallBack != null) {}
    try
    {
      paramXyCallBack.execute(paramVarArgs);
      return;
    }
    catch (Throwable paramXyCallBack) {}
  }
  
  public static String getImei(Context paramContext)
  {
    if (paramContext != null)
    {
      paramContext = (TelephonyManager)paramContext.getSystemService("phone");
      if (paramContext != null) {
        try
        {
          if (paramContext.getDeviceId() != null)
          {
            paramContext = paramContext.getDeviceId();
            return paramContext;
          }
        }
        catch (Throwable paramContext) {}
      }
    }
    return "360_DEFAULT_IMEI";
  }
  
  public static String getImeiAndXinghao(Context paramContext)
  {
    return getImei(paramContext) + ";" + getPhoneModel(paramContext);
  }
  
  public static LineNumberReader getLineByCompressFile(String paramString)
  {
    try
    {
      paramString = new LineNumberReader(new StringReader(new String(decompressBytes(d.e(paramString)), "UTF-8")));
      return paramString;
    }
    catch (Throwable paramString) {}
    return null;
  }
  
  public static String getPhoneModel(Context paramContext)
  {
    return Build.MODEL + "," + Build.BRAND;
  }
  
  public static String getPhoneNumber(Context paramContext)
  {
    try
    {
      paramContext = ((TelephonyManager)paramContext.getSystemService("phone")).getLine1Number();
      return paramContext;
    }
    catch (Throwable paramContext) {}
    return "";
  }
  
  public static String getSceneServiceAction(Map<String, Object> paramMap)
  {
    StringBuffer localStringBuffer;
    Object localObject1;
    int j;
    int i;
    label474:
    int k;
    for (;;)
    {
      try
      {
        JSONObject localJSONObject = new JSONObject();
        localJSONObject.put("action", "display_scene_result");
        localJSONObject.put("btn_name", (String)paramMap.get("title_name") + "服务");
        paramMap.remove("is_return");
        paramMap.remove("mactchs_id");
        paramMap.remove("province");
        paramMap.remove("popup_type");
        paramMap.remove("version");
        paramMap.remove("RECOGNIZE_LEVEL");
        paramMap.remove("channel");
        paramMap.remove("power");
        paramMap.remove("smsCenterNum");
        paramMap.remove("phoneNum");
        localStringBuffer = new StringBuffer();
        Iterator localIterator = paramMap.entrySet().iterator();
        if (!localIterator.hasNext())
        {
          localJSONObject.put("action_data", b(new String[] { "type", "display_scene_result", "dataresult", localStringBuffer.toString(), "titleNo", (String)paramMap.get("title_num") }));
          paramMap = new JSONArray();
          paramMap.put(localJSONObject);
          return paramMap.toString();
        }
        localObject2 = (Map.Entry)localIterator.next();
        if ((((Map.Entry)localObject2).getValue() instanceof String))
        {
          localStringBuffer.append((String)((Map.Entry)localObject2).getKey() + ": " + ((Map.Entry)localObject2).getValue() + "<br/>");
          continue;
        }
        if (!(((Map.Entry)localObject2).getValue() instanceof String[])) {
          break label474;
        }
      }
      catch (Throwable paramMap)
      {
        paramMap.printStackTrace();
        return null;
      }
      localObject1 = (String[])((Map.Entry)localObject2).getValue();
      if (localObject1 != null)
      {
        localStringBuffer.append((String)((Map.Entry)localObject2).getKey() + ":[");
        j = localObject1.length;
        i = 0;
        if (i >= j)
        {
          localStringBuffer.append("]<br/>");
        }
        else
        {
          localStringBuffer.append(localObject1[i]);
          if (i == j - 1) {
            break label712;
          }
          localStringBuffer.append(",");
          break label712;
          if ((((Map.Entry)localObject2).getValue() instanceof List))
          {
            localObject1 = (List)((Map.Entry)localObject2).getValue();
            if (localObject1 != null)
            {
              localStringBuffer.append((String)((Map.Entry)localObject2).getKey() + ":[");
              k = ((List)localObject1).size();
              i = 0;
              label549:
              if (i < k) {
                break;
              }
              localStringBuffer.append("]<br/>");
            }
          }
        }
      }
    }
    Object localObject2 = ((List)localObject1).get(i);
    label600:
    int m;
    if (localObject2 != null) {
      if ((localObject2 instanceof String))
      {
        localStringBuffer.append(localObject2.toString());
        if (i != k - 1) {
          localStringBuffer.append(",");
        }
      }
      else if ((localObject2 instanceof String[]))
      {
        localObject2 = (String[])localObject2;
        m = localObject2.length;
        localStringBuffer.append("[");
        j = 0;
      }
    }
    for (;;)
    {
      if (j >= m)
      {
        localStringBuffer.append("]");
        break label600;
      }
      localStringBuffer.append(localObject2[j]);
      if (j != m - 1)
      {
        localStringBuffer.append(",");
        break label726;
        localStringBuffer.append(localObject2.toString());
        break label600;
        label712:
        i += 1;
        break;
        i += 1;
        break label549;
      }
      label726:
      j += 1;
    }
  }
  
  public static int getSimIndex(Map<String, Object> paramMap)
  {
    if (paramMap == null) {
      return -1;
    }
    paramMap = (String)paramMap.get("simIndex");
    if (paramMap != null) {}
    for (;;)
    {
      try
      {
        i = Integer.valueOf(paramMap).intValue();
        return i;
      }
      catch (Throwable paramMap)
      {
        paramMap.printStackTrace();
      }
      int i = -1;
    }
  }
  
  public static String getXyValue(int paramInt)
  {
    if (paramInt == 1)
    {
      if (a == null) {
        a = PopupUtil.getValue(paramInt);
      }
      return a;
    }
    if (b == null) {
      b = PopupUtil.getValue(paramInt);
    }
    return b;
  }
  
  public static void handleMapAction(Map<String, Object> paramMap)
  {
    if ((paramMap != null) && (!paramMap.isEmpty()))
    {
      String str = (String)paramMap.get("ADACTION");
      if (!StringUtils.isNull(str))
      {
        str = a(paramMap, str);
        if (!StringUtils.isNull(str)) {
          paramMap.put("ADACTION", str);
        }
      }
    }
  }
  
  public static boolean isProvinceUsable(String paramString1, String paramString2)
  {
    boolean bool2 = true;
    boolean bool1;
    try
    {
      if (StringUtils.isNull(paramString1)) {
        return true;
      }
      if (!StringUtils.isNull(paramString1))
      {
        bool1 = bool2;
        if (paramString1.equals("*")) {}
      }
      else
      {
        if (StringUtils.isNull(paramString2)) {
          return false;
        }
        if (!StringUtils.isNull(paramString1))
        {
          int i = paramString1.replaceAll("，", ",").replaceAll("；", ";").replaceAll("市", "").indexOf(paramString2);
          bool1 = bool2;
          if (i != -1) {}
        }
        else
        {
          return false;
        }
      }
    }
    catch (Throwable paramString1)
    {
      paramString1.printStackTrace();
      bool1 = false;
    }
    return bool1;
  }
  
  public static void unZip(InputStream paramInputStream, String paramString1, String paramString2)
  {
    unZip(paramInputStream, paramString1, paramString2, false, "", false);
  }
  
  /* Error */
  public static void unZip(InputStream paramInputStream, String paramString1, String paramString2, boolean paramBoolean1, String paramString3, boolean paramBoolean2)
  {
    // Byte code:
    //   0: aconst_null
    //   1: astore 10
    //   3: aconst_null
    //   4: astore 9
    //   6: new 565	java/io/File
    //   9: dup
    //   10: new 291	java/lang/StringBuilder
    //   13: dup
    //   14: aload_2
    //   15: invokestatic 177	java/lang/String:valueOf	(Ljava/lang/Object;)Ljava/lang/String;
    //   18: invokespecial 294	java/lang/StringBuilder:<init>	(Ljava/lang/String;)V
    //   21: aload_1
    //   22: invokevirtual 298	java/lang/StringBuilder:append	(Ljava/lang/String;)Ljava/lang/StringBuilder;
    //   25: invokevirtual 301	java/lang/StringBuilder:toString	()Ljava/lang/String;
    //   28: invokespecial 566	java/io/File:<init>	(Ljava/lang/String;)V
    //   31: astore 7
    //   33: aload 7
    //   35: invokevirtual 569	java/io/File:exists	()Z
    //   38: ifne +9 -> 47
    //   41: aload 7
    //   43: invokevirtual 572	java/io/File:createNewFile	()Z
    //   46: pop
    //   47: new 574	java/io/FileOutputStream
    //   50: dup
    //   51: aload 7
    //   53: invokespecial 577	java/io/FileOutputStream:<init>	(Ljava/io/File;)V
    //   56: astore 8
    //   58: sipush 1024
    //   61: newarray <illegal type>
    //   63: astore 9
    //   65: aload_0
    //   66: aload 9
    //   68: invokevirtual 582	java/io/InputStream:read	([B)I
    //   71: istore 6
    //   73: iload 6
    //   75: iconst_m1
    //   76: if_icmpne +66 -> 142
    //   79: aload 8
    //   81: invokevirtual 585	java/io/FileOutputStream:close	()V
    //   84: aload 7
    //   86: aload_2
    //   87: iload_3
    //   88: aload 4
    //   90: iload 5
    //   92: invokestatic 589	cn/com/xy/sms/sdk/util/XyUtil:upZipFile	(Ljava/io/File;Ljava/lang/String;ZLjava/lang/String;Z)V
    //   95: aload 7
    //   97: invokevirtual 592	java/io/File:delete	()Z
    //   100: pop
    //   101: new 291	java/lang/StringBuilder
    //   104: dup
    //   105: ldc_w 594
    //   108: invokespecial 294	java/lang/StringBuilder:<init>	(Ljava/lang/String;)V
    //   111: aload_1
    //   112: invokevirtual 298	java/lang/StringBuilder:append	(Ljava/lang/String;)Ljava/lang/StringBuilder;
    //   115: ldc_w 596
    //   118: invokevirtual 298	java/lang/StringBuilder:append	(Ljava/lang/String;)Ljava/lang/StringBuilder;
    //   121: pop
    //   122: aload 7
    //   124: invokevirtual 569	java/io/File:exists	()Z
    //   127: ifeq +9 -> 136
    //   130: aload 7
    //   132: invokevirtual 592	java/io/File:delete	()Z
    //   135: pop
    //   136: aload 8
    //   138: invokestatic 366	cn/com/xy/sms/sdk/util/d:a	(Ljava/io/Closeable;)V
    //   141: return
    //   142: aload 8
    //   144: aload 9
    //   146: iconst_0
    //   147: iload 6
    //   149: invokevirtual 597	java/io/FileOutputStream:write	([BII)V
    //   152: aload 8
    //   154: invokevirtual 600	java/io/FileOutputStream:flush	()V
    //   157: goto -92 -> 65
    //   160: astore 4
    //   162: aload 8
    //   164: astore_2
    //   165: aload 7
    //   167: astore_0
    //   168: aload 4
    //   170: invokevirtual 315	java/lang/Throwable:printStackTrace	()V
    //   173: new 291	java/lang/StringBuilder
    //   176: dup
    //   177: ldc_w 594
    //   180: invokespecial 294	java/lang/StringBuilder:<init>	(Ljava/lang/String;)V
    //   183: aload_1
    //   184: invokevirtual 298	java/lang/StringBuilder:append	(Ljava/lang/String;)Ljava/lang/StringBuilder;
    //   187: ldc_w 602
    //   190: invokevirtual 298	java/lang/StringBuilder:append	(Ljava/lang/String;)Ljava/lang/StringBuilder;
    //   193: aload 4
    //   195: invokevirtual 605	java/lang/Throwable:getMessage	()Ljava/lang/String;
    //   198: invokevirtual 298	java/lang/StringBuilder:append	(Ljava/lang/String;)Ljava/lang/StringBuilder;
    //   201: pop
    //   202: new 607	java/lang/Exception
    //   205: dup
    //   206: new 291	java/lang/StringBuilder
    //   209: dup
    //   210: ldc_w 609
    //   213: invokespecial 294	java/lang/StringBuilder:<init>	(Ljava/lang/String;)V
    //   216: aload_1
    //   217: invokevirtual 298	java/lang/StringBuilder:append	(Ljava/lang/String;)Ljava/lang/StringBuilder;
    //   220: ldc_w 602
    //   223: invokevirtual 298	java/lang/StringBuilder:append	(Ljava/lang/String;)Ljava/lang/StringBuilder;
    //   226: aload 4
    //   228: invokevirtual 605	java/lang/Throwable:getMessage	()Ljava/lang/String;
    //   231: invokevirtual 298	java/lang/StringBuilder:append	(Ljava/lang/String;)Ljava/lang/StringBuilder;
    //   234: invokevirtual 301	java/lang/StringBuilder:toString	()Ljava/lang/String;
    //   237: invokespecial 610	java/lang/Exception:<init>	(Ljava/lang/String;)V
    //   240: athrow
    //   241: astore 4
    //   243: aload_0
    //   244: astore_1
    //   245: aload 4
    //   247: astore_0
    //   248: aload_1
    //   249: ifnull +15 -> 264
    //   252: aload_1
    //   253: invokevirtual 569	java/io/File:exists	()Z
    //   256: ifeq +8 -> 264
    //   259: aload_1
    //   260: invokevirtual 592	java/io/File:delete	()Z
    //   263: pop
    //   264: aload_2
    //   265: invokestatic 366	cn/com/xy/sms/sdk/util/d:a	(Ljava/io/Closeable;)V
    //   268: aload_0
    //   269: athrow
    //   270: astore_0
    //   271: aconst_null
    //   272: astore_1
    //   273: aload 10
    //   275: astore_2
    //   276: goto -28 -> 248
    //   279: astore_0
    //   280: aload 7
    //   282: astore_1
    //   283: aload 10
    //   285: astore_2
    //   286: goto -38 -> 248
    //   289: astore_0
    //   290: aload 8
    //   292: astore_2
    //   293: aload 7
    //   295: astore_1
    //   296: goto -48 -> 248
    //   299: astore 4
    //   301: aconst_null
    //   302: astore_0
    //   303: aload 9
    //   305: astore_2
    //   306: goto -138 -> 168
    //   309: astore 4
    //   311: aload 7
    //   313: astore_0
    //   314: aload 9
    //   316: astore_2
    //   317: goto -149 -> 168
    // Local variable table:
    //   start	length	slot	name	signature
    //   0	320	0	paramInputStream	InputStream
    //   0	320	1	paramString1	String
    //   0	320	2	paramString2	String
    //   0	320	3	paramBoolean1	boolean
    //   0	320	4	paramString3	String
    //   0	320	5	paramBoolean2	boolean
    //   71	77	6	i	int
    //   31	281	7	localFile	File
    //   56	235	8	localFileOutputStream	java.io.FileOutputStream
    //   4	311	9	arrayOfByte	byte[]
    //   1	283	10	localObject	Object
    // Exception table:
    //   from	to	target	type
    //   58	65	160	java/lang/Throwable
    //   65	73	160	java/lang/Throwable
    //   79	122	160	java/lang/Throwable
    //   142	157	160	java/lang/Throwable
    //   168	241	241	finally
    //   6	33	270	finally
    //   33	47	279	finally
    //   47	58	279	finally
    //   58	65	289	finally
    //   65	73	289	finally
    //   79	122	289	finally
    //   142	157	289	finally
    //   6	33	299	java/lang/Throwable
    //   33	47	309	java/lang/Throwable
    //   47	58	309	java/lang/Throwable
  }
  
  public static void upZipFile(File paramFile, String paramString)
  {
    upZipFile(paramFile, paramString, false, "", false);
  }
  
  /* Error */
  public static void upZipFile(File paramFile, String paramString1, boolean paramBoolean1, String paramString2, boolean paramBoolean2)
  {
    // Byte code:
    //   0: aconst_null
    //   1: astore 9
    //   3: aconst_null
    //   4: astore 8
    //   6: aconst_null
    //   7: astore 10
    //   9: new 565	java/io/File
    //   12: dup
    //   13: aload_1
    //   14: invokespecial 566	java/io/File:<init>	(Ljava/lang/String;)V
    //   17: astore 7
    //   19: aload 7
    //   21: invokevirtual 569	java/io/File:exists	()Z
    //   24: ifne +9 -> 33
    //   27: aload 7
    //   29: invokevirtual 614	java/io/File:mkdirs	()Z
    //   32: pop
    //   33: new 616	java/util/zip/ZipFile
    //   36: dup
    //   37: aload_0
    //   38: invokespecial 617	java/util/zip/ZipFile:<init>	(Ljava/io/File;)V
    //   41: astore 7
    //   43: aload 7
    //   45: invokevirtual 621	java/util/zip/ZipFile:entries	()Ljava/util/Enumeration;
    //   48: astore 11
    //   50: aconst_null
    //   51: astore_0
    //   52: aload 10
    //   54: astore 8
    //   56: aload 11
    //   58: invokeinterface 626 1 0
    //   63: istore 6
    //   65: iload 6
    //   67: ifne +18 -> 85
    //   70: aload 7
    //   72: invokestatic 629	cn/com/xy/sms/sdk/util/d:a	(Ljava/util/zip/ZipFile;)V
    //   75: aload_0
    //   76: invokestatic 366	cn/com/xy/sms/sdk/util/d:a	(Ljava/io/Closeable;)V
    //   79: aload 8
    //   81: invokestatic 366	cn/com/xy/sms/sdk/util/d:a	(Ljava/io/Closeable;)V
    //   84: return
    //   85: aload 11
    //   87: invokeinterface 632 1 0
    //   92: checkcast 634	java/util/zip/ZipEntry
    //   95: astore 12
    //   97: aload 7
    //   99: aload 12
    //   101: invokevirtual 638	java/util/zip/ZipFile:getInputStream	(Ljava/util/zip/ZipEntry;)Ljava/io/InputStream;
    //   104: astore 9
    //   106: aload 9
    //   108: astore_0
    //   109: aload 12
    //   111: invokevirtual 641	java/util/zip/ZipEntry:getName	()Ljava/lang/String;
    //   114: invokestatic 43	cn/com/xy/sms/sdk/util/StringUtils:isNull	(Ljava/lang/String;)Z
    //   117: ifne +455 -> 572
    //   120: new 76	java/lang/String
    //   123: dup
    //   124: aload 12
    //   126: invokevirtual 641	java/util/zip/ZipEntry:getName	()Ljava/lang/String;
    //   129: ldc_w 643
    //   132: invokevirtual 646	java/lang/String:getBytes	(Ljava/lang/String;)[B
    //   135: ldc_w 648
    //   138: invokespecial 428	java/lang/String:<init>	([BLjava/lang/String;)V
    //   141: astore 10
    //   143: iload 4
    //   145: ifeq +45 -> 190
    //   148: aload 10
    //   150: invokestatic 43	cn/com/xy/sms/sdk/util/StringUtils:isNull	(Ljava/lang/String;)Z
    //   153: ifne +37 -> 190
    //   156: aload 10
    //   158: ldc_w 650
    //   161: invokevirtual 653	java/lang/String:endsWith	(Ljava/lang/String;)Z
    //   164: ifeq +26 -> 190
    //   167: aload 10
    //   169: ldc_w 655
    //   172: ldc 56
    //   174: invokevirtual 659	java/lang/String:replace	(Ljava/lang/CharSequence;Ljava/lang/CharSequence;)Ljava/lang/String;
    //   177: astore 9
    //   179: aload 9
    //   181: aload_3
    //   182: aload 9
    //   184: invokestatic 664	cn/com/xy/sms/sdk/db/entity/e:c	(Ljava/lang/String;)I
    //   187: invokestatic 667	cn/com/xy/sms/sdk/db/entity/e:a	(Ljava/lang/String;Ljava/lang/String;I)V
    //   190: aload 10
    //   192: astore 9
    //   194: iload_2
    //   195: ifeq +71 -> 266
    //   198: aload 10
    //   200: astore 9
    //   202: aload 10
    //   204: invokestatic 43	cn/com/xy/sms/sdk/util/StringUtils:isNull	(Ljava/lang/String;)Z
    //   207: ifne +59 -> 266
    //   210: aload 10
    //   212: astore 9
    //   214: aload 10
    //   216: ldc_w 650
    //   219: invokevirtual 653	java/lang/String:endsWith	(Ljava/lang/String;)Z
    //   222: ifeq +44 -> 266
    //   225: aload 10
    //   227: ldc_w 655
    //   230: new 291	java/lang/StringBuilder
    //   233: dup
    //   234: ldc_w 669
    //   237: invokespecial 294	java/lang/StringBuilder:<init>	(Ljava/lang/String;)V
    //   240: aload_3
    //   241: invokevirtual 298	java/lang/StringBuilder:append	(Ljava/lang/String;)Ljava/lang/StringBuilder;
    //   244: ldc_w 655
    //   247: invokevirtual 298	java/lang/StringBuilder:append	(Ljava/lang/String;)Ljava/lang/StringBuilder;
    //   250: invokevirtual 301	java/lang/StringBuilder:toString	()Ljava/lang/String;
    //   253: invokevirtual 659	java/lang/String:replace	(Ljava/lang/CharSequence;Ljava/lang/CharSequence;)Ljava/lang/String;
    //   256: ldc_w 671
    //   259: ldc 56
    //   261: invokevirtual 550	java/lang/String:replaceAll	(Ljava/lang/String;Ljava/lang/String;)Ljava/lang/String;
    //   264: astore 9
    //   266: new 291	java/lang/StringBuilder
    //   269: dup
    //   270: aload_1
    //   271: invokestatic 177	java/lang/String:valueOf	(Ljava/lang/Object;)Ljava/lang/String;
    //   274: invokespecial 294	java/lang/StringBuilder:<init>	(Ljava/lang/String;)V
    //   277: getstatic 674	java/io/File:separator	Ljava/lang/String;
    //   280: invokevirtual 298	java/lang/StringBuilder:append	(Ljava/lang/String;)Ljava/lang/StringBuilder;
    //   283: aload 9
    //   285: invokevirtual 298	java/lang/StringBuilder:append	(Ljava/lang/String;)Ljava/lang/StringBuilder;
    //   288: invokevirtual 301	java/lang/StringBuilder:toString	()Ljava/lang/String;
    //   291: astore 9
    //   293: getstatic 678	cn/com/xy/sms/sdk/log/LogManager:debug	Z
    //   296: ifeq +43 -> 339
    //   299: new 291	java/lang/StringBuilder
    //   302: dup
    //   303: ldc_w 680
    //   306: invokespecial 294	java/lang/StringBuilder:<init>	(Ljava/lang/String;)V
    //   309: aload 9
    //   311: invokevirtual 298	java/lang/StringBuilder:append	(Ljava/lang/String;)Ljava/lang/StringBuilder;
    //   314: ldc_w 682
    //   317: invokevirtual 298	java/lang/StringBuilder:append	(Ljava/lang/String;)Ljava/lang/StringBuilder;
    //   320: aload_1
    //   321: invokevirtual 298	java/lang/StringBuilder:append	(Ljava/lang/String;)Ljava/lang/StringBuilder;
    //   324: ldc_w 684
    //   327: invokevirtual 298	java/lang/StringBuilder:append	(Ljava/lang/String;)Ljava/lang/StringBuilder;
    //   330: aload 12
    //   332: invokevirtual 641	java/util/zip/ZipEntry:getName	()Ljava/lang/String;
    //   335: invokevirtual 298	java/lang/StringBuilder:append	(Ljava/lang/String;)Ljava/lang/StringBuilder;
    //   338: pop
    //   339: new 565	java/io/File
    //   342: dup
    //   343: aload 9
    //   345: invokespecial 566	java/io/File:<init>	(Ljava/lang/String;)V
    //   348: astore 9
    //   350: aload 9
    //   352: invokevirtual 569	java/io/File:exists	()Z
    //   355: ifne +77 -> 432
    //   358: aload 9
    //   360: invokevirtual 688	java/io/File:getParentFile	()Ljava/io/File;
    //   363: astore 10
    //   365: aload 10
    //   367: invokevirtual 569	java/io/File:exists	()Z
    //   370: ifne +9 -> 379
    //   373: aload 10
    //   375: invokevirtual 614	java/io/File:mkdirs	()Z
    //   378: pop
    //   379: aload 9
    //   381: invokevirtual 572	java/io/File:createNewFile	()Z
    //   384: pop
    //   385: new 574	java/io/FileOutputStream
    //   388: dup
    //   389: aload 9
    //   391: invokespecial 577	java/io/FileOutputStream:<init>	(Ljava/io/File;)V
    //   394: astore 9
    //   396: sipush 1024
    //   399: newarray <illegal type>
    //   401: astore 8
    //   403: aload_0
    //   404: aload 8
    //   406: invokevirtual 582	java/io/InputStream:read	([B)I
    //   409: istore 5
    //   411: iload 5
    //   413: ifgt +50 -> 463
    //   416: aload_0
    //   417: invokestatic 366	cn/com/xy/sms/sdk/util/d:a	(Ljava/io/Closeable;)V
    //   420: aload 9
    //   422: invokestatic 366	cn/com/xy/sms/sdk/util/d:a	(Ljava/io/Closeable;)V
    //   425: aload 9
    //   427: astore 8
    //   429: goto -373 -> 56
    //   432: aload 9
    //   434: invokevirtual 592	java/io/File:delete	()Z
    //   437: pop
    //   438: goto -53 -> 385
    //   441: astore_3
    //   442: aload 7
    //   444: astore_1
    //   445: aload_3
    //   446: invokevirtual 315	java/lang/Throwable:printStackTrace	()V
    //   449: aload_1
    //   450: invokestatic 629	cn/com/xy/sms/sdk/util/d:a	(Ljava/util/zip/ZipFile;)V
    //   453: aload_0
    //   454: invokestatic 366	cn/com/xy/sms/sdk/util/d:a	(Ljava/io/Closeable;)V
    //   457: aload 8
    //   459: invokestatic 366	cn/com/xy/sms/sdk/util/d:a	(Ljava/io/Closeable;)V
    //   462: return
    //   463: aload 9
    //   465: aload 8
    //   467: iconst_0
    //   468: iload 5
    //   470: invokevirtual 691	java/io/OutputStream:write	([BII)V
    //   473: goto -70 -> 403
    //   476: astore_3
    //   477: aload 9
    //   479: astore 8
    //   481: aload 7
    //   483: astore_1
    //   484: goto -39 -> 445
    //   487: astore_1
    //   488: aconst_null
    //   489: astore_0
    //   490: aconst_null
    //   491: astore 7
    //   493: aload 7
    //   495: invokestatic 629	cn/com/xy/sms/sdk/util/d:a	(Ljava/util/zip/ZipFile;)V
    //   498: aload_0
    //   499: invokestatic 366	cn/com/xy/sms/sdk/util/d:a	(Ljava/io/Closeable;)V
    //   502: aload 8
    //   504: invokestatic 366	cn/com/xy/sms/sdk/util/d:a	(Ljava/io/Closeable;)V
    //   507: aload_1
    //   508: athrow
    //   509: astore_1
    //   510: aconst_null
    //   511: astore_0
    //   512: goto -19 -> 493
    //   515: astore_1
    //   516: aload 9
    //   518: astore 8
    //   520: goto -27 -> 493
    //   523: astore_1
    //   524: goto -31 -> 493
    //   527: astore_1
    //   528: goto -35 -> 493
    //   531: astore_3
    //   532: aload_1
    //   533: astore 7
    //   535: aload_3
    //   536: astore_1
    //   537: goto -44 -> 493
    //   540: astore_3
    //   541: aconst_null
    //   542: astore_0
    //   543: aconst_null
    //   544: astore_1
    //   545: aload 9
    //   547: astore 8
    //   549: goto -104 -> 445
    //   552: astore_3
    //   553: aconst_null
    //   554: astore_0
    //   555: aload 7
    //   557: astore_1
    //   558: aload 9
    //   560: astore 8
    //   562: goto -117 -> 445
    //   565: astore_3
    //   566: aload 7
    //   568: astore_1
    //   569: goto -124 -> 445
    //   572: goto -516 -> 56
    // Local variable table:
    //   start	length	slot	name	signature
    //   0	575	0	paramFile	File
    //   0	575	1	paramString1	String
    //   0	575	2	paramBoolean1	boolean
    //   0	575	3	paramString2	String
    //   0	575	4	paramBoolean2	boolean
    //   409	60	5	i	int
    //   63	3	6	bool	boolean
    //   17	550	7	localObject1	Object
    //   4	557	8	localObject2	Object
    //   1	558	9	localObject3	Object
    //   7	367	10	localObject4	Object
    //   48	38	11	localEnumeration	java.util.Enumeration
    //   95	236	12	localZipEntry	java.util.zip.ZipEntry
    // Exception table:
    //   from	to	target	type
    //   109	143	441	java/lang/Throwable
    //   148	190	441	java/lang/Throwable
    //   202	210	441	java/lang/Throwable
    //   214	266	441	java/lang/Throwable
    //   266	339	441	java/lang/Throwable
    //   339	379	441	java/lang/Throwable
    //   379	385	441	java/lang/Throwable
    //   385	396	441	java/lang/Throwable
    //   432	438	441	java/lang/Throwable
    //   396	403	476	java/lang/Throwable
    //   403	411	476	java/lang/Throwable
    //   416	425	476	java/lang/Throwable
    //   463	473	476	java/lang/Throwable
    //   9	33	487	finally
    //   33	43	487	finally
    //   43	50	509	finally
    //   396	403	515	finally
    //   403	411	515	finally
    //   416	425	515	finally
    //   463	473	515	finally
    //   56	65	523	finally
    //   85	106	523	finally
    //   109	143	527	finally
    //   148	190	527	finally
    //   202	210	527	finally
    //   214	266	527	finally
    //   266	339	527	finally
    //   339	379	527	finally
    //   379	385	527	finally
    //   385	396	527	finally
    //   432	438	527	finally
    //   445	449	531	finally
    //   9	33	540	java/lang/Throwable
    //   33	43	540	java/lang/Throwable
    //   43	50	552	java/lang/Throwable
    //   56	65	565	java/lang/Throwable
    //   85	106	565	java/lang/Throwable
  }
  
  /* Error */
  public static void upZipFile(String paramString1, String paramString2)
  {
    // Byte code:
    //   0: aconst_null
    //   1: astore 5
    //   3: new 565	java/io/File
    //   6: dup
    //   7: aload_1
    //   8: invokespecial 566	java/io/File:<init>	(Ljava/lang/String;)V
    //   11: astore 4
    //   13: aload 4
    //   15: invokevirtual 569	java/io/File:exists	()Z
    //   18: ifne +9 -> 27
    //   21: aload 4
    //   23: invokevirtual 614	java/io/File:mkdirs	()Z
    //   26: pop
    //   27: new 616	java/util/zip/ZipFile
    //   30: dup
    //   31: new 565	java/io/File
    //   34: dup
    //   35: aload_0
    //   36: invokespecial 566	java/io/File:<init>	(Ljava/lang/String;)V
    //   39: invokespecial 617	java/util/zip/ZipFile:<init>	(Ljava/io/File;)V
    //   42: astore 4
    //   44: aload 4
    //   46: invokevirtual 621	java/util/zip/ZipFile:entries	()Ljava/util/Enumeration;
    //   49: astore 9
    //   51: aconst_null
    //   52: astore_0
    //   53: aconst_null
    //   54: astore 5
    //   56: aload_0
    //   57: astore 8
    //   59: aload_0
    //   60: astore 6
    //   62: aload 9
    //   64: invokeinterface 626 1 0
    //   69: istore_3
    //   70: iload_3
    //   71: ifne +18 -> 89
    //   74: aload 4
    //   76: invokestatic 629	cn/com/xy/sms/sdk/util/d:a	(Ljava/util/zip/ZipFile;)V
    //   79: aload_0
    //   80: invokestatic 366	cn/com/xy/sms/sdk/util/d:a	(Ljava/io/Closeable;)V
    //   83: aload 5
    //   85: invokestatic 366	cn/com/xy/sms/sdk/util/d:a	(Ljava/io/Closeable;)V
    //   88: return
    //   89: aload_0
    //   90: astore 8
    //   92: aload_0
    //   93: astore 6
    //   95: aload 9
    //   97: invokeinterface 632 1 0
    //   102: checkcast 634	java/util/zip/ZipEntry
    //   105: astore 7
    //   107: aload_0
    //   108: astore 8
    //   110: aload_0
    //   111: astore 6
    //   113: aload 7
    //   115: invokevirtual 641	java/util/zip/ZipEntry:getName	()Ljava/lang/String;
    //   118: invokestatic 43	cn/com/xy/sms/sdk/util/StringUtils:isNull	(Ljava/lang/String;)Z
    //   121: ifne -65 -> 56
    //   124: aload_0
    //   125: astore 8
    //   127: aload_0
    //   128: astore 6
    //   130: aload 4
    //   132: aload 7
    //   134: invokevirtual 638	java/util/zip/ZipFile:getInputStream	(Ljava/util/zip/ZipEntry;)Ljava/io/InputStream;
    //   137: astore_0
    //   138: aload_0
    //   139: astore 8
    //   141: aload_0
    //   142: astore 6
    //   144: new 565	java/io/File
    //   147: dup
    //   148: new 291	java/lang/StringBuilder
    //   151: dup
    //   152: aload_1
    //   153: invokestatic 177	java/lang/String:valueOf	(Ljava/lang/Object;)Ljava/lang/String;
    //   156: invokespecial 294	java/lang/StringBuilder:<init>	(Ljava/lang/String;)V
    //   159: getstatic 674	java/io/File:separator	Ljava/lang/String;
    //   162: invokevirtual 298	java/lang/StringBuilder:append	(Ljava/lang/String;)Ljava/lang/StringBuilder;
    //   165: new 76	java/lang/String
    //   168: dup
    //   169: aload 7
    //   171: invokevirtual 641	java/util/zip/ZipEntry:getName	()Ljava/lang/String;
    //   174: ldc_w 643
    //   177: invokevirtual 646	java/lang/String:getBytes	(Ljava/lang/String;)[B
    //   180: ldc_w 648
    //   183: invokespecial 428	java/lang/String:<init>	([BLjava/lang/String;)V
    //   186: ldc_w 671
    //   189: ldc 56
    //   191: invokevirtual 659	java/lang/String:replace	(Ljava/lang/CharSequence;Ljava/lang/CharSequence;)Ljava/lang/String;
    //   194: invokevirtual 298	java/lang/StringBuilder:append	(Ljava/lang/String;)Ljava/lang/StringBuilder;
    //   197: invokevirtual 301	java/lang/StringBuilder:toString	()Ljava/lang/String;
    //   200: invokespecial 566	java/io/File:<init>	(Ljava/lang/String;)V
    //   203: astore 7
    //   205: aload_0
    //   206: astore 8
    //   208: aload_0
    //   209: astore 6
    //   211: aload 7
    //   213: invokevirtual 569	java/io/File:exists	()Z
    //   216: ifne +105 -> 321
    //   219: aload_0
    //   220: astore 8
    //   222: aload_0
    //   223: astore 6
    //   225: aload 7
    //   227: invokevirtual 688	java/io/File:getParentFile	()Ljava/io/File;
    //   230: astore 10
    //   232: aload_0
    //   233: astore 8
    //   235: aload_0
    //   236: astore 6
    //   238: aload 10
    //   240: invokevirtual 569	java/io/File:exists	()Z
    //   243: ifne +15 -> 258
    //   246: aload_0
    //   247: astore 8
    //   249: aload_0
    //   250: astore 6
    //   252: aload 10
    //   254: invokevirtual 614	java/io/File:mkdirs	()Z
    //   257: pop
    //   258: aload_0
    //   259: astore 8
    //   261: aload_0
    //   262: astore 6
    //   264: aload 7
    //   266: invokevirtual 572	java/io/File:createNewFile	()Z
    //   269: pop
    //   270: aload_0
    //   271: astore 8
    //   273: aload_0
    //   274: astore 6
    //   276: new 574	java/io/FileOutputStream
    //   279: dup
    //   280: aload 7
    //   282: invokespecial 577	java/io/FileOutputStream:<init>	(Ljava/io/File;)V
    //   285: astore 7
    //   287: sipush 1024
    //   290: newarray <illegal type>
    //   292: astore 5
    //   294: aload_0
    //   295: aload 5
    //   297: invokevirtual 582	java/io/InputStream:read	([B)I
    //   300: istore_2
    //   301: iload_2
    //   302: ifgt +59 -> 361
    //   305: aload_0
    //   306: invokestatic 366	cn/com/xy/sms/sdk/util/d:a	(Ljava/io/Closeable;)V
    //   309: aload 7
    //   311: invokestatic 366	cn/com/xy/sms/sdk/util/d:a	(Ljava/io/Closeable;)V
    //   314: aload 7
    //   316: astore 5
    //   318: goto -262 -> 56
    //   321: aload_0
    //   322: astore 8
    //   324: aload_0
    //   325: astore 6
    //   327: aload 7
    //   329: invokevirtual 592	java/io/File:delete	()Z
    //   332: pop
    //   333: goto -63 -> 270
    //   336: astore_0
    //   337: aload 5
    //   339: astore_0
    //   340: aload 4
    //   342: astore_1
    //   343: aload 8
    //   345: astore 4
    //   347: aload_1
    //   348: invokestatic 629	cn/com/xy/sms/sdk/util/d:a	(Ljava/util/zip/ZipFile;)V
    //   351: aload 4
    //   353: invokestatic 366	cn/com/xy/sms/sdk/util/d:a	(Ljava/io/Closeable;)V
    //   356: aload_0
    //   357: invokestatic 366	cn/com/xy/sms/sdk/util/d:a	(Ljava/io/Closeable;)V
    //   360: return
    //   361: aload 7
    //   363: aload 5
    //   365: iconst_0
    //   366: iload_2
    //   367: invokevirtual 691	java/io/OutputStream:write	([BII)V
    //   370: goto -76 -> 294
    //   373: astore_1
    //   374: aload 4
    //   376: astore_1
    //   377: aload_0
    //   378: astore 4
    //   380: aload 7
    //   382: astore_0
    //   383: goto -36 -> 347
    //   386: astore_1
    //   387: aconst_null
    //   388: astore 5
    //   390: aconst_null
    //   391: astore 4
    //   393: aconst_null
    //   394: astore_0
    //   395: aload 4
    //   397: invokestatic 629	cn/com/xy/sms/sdk/util/d:a	(Ljava/util/zip/ZipFile;)V
    //   400: aload_0
    //   401: invokestatic 366	cn/com/xy/sms/sdk/util/d:a	(Ljava/io/Closeable;)V
    //   404: aload 5
    //   406: invokestatic 366	cn/com/xy/sms/sdk/util/d:a	(Ljava/io/Closeable;)V
    //   409: aload_1
    //   410: athrow
    //   411: astore_1
    //   412: aconst_null
    //   413: astore 5
    //   415: aconst_null
    //   416: astore_0
    //   417: goto -22 -> 395
    //   420: astore_1
    //   421: aload 7
    //   423: astore 5
    //   425: goto -30 -> 395
    //   428: astore_1
    //   429: aload 6
    //   431: astore_0
    //   432: goto -37 -> 395
    //   435: astore_0
    //   436: aconst_null
    //   437: astore_0
    //   438: aconst_null
    //   439: astore_1
    //   440: aload 5
    //   442: astore 4
    //   444: goto -97 -> 347
    //   447: astore_0
    //   448: aconst_null
    //   449: astore_0
    //   450: aload 4
    //   452: astore_1
    //   453: aload 5
    //   455: astore 4
    //   457: goto -110 -> 347
    // Local variable table:
    //   start	length	slot	name	signature
    //   0	460	0	paramString1	String
    //   0	460	1	paramString2	String
    //   300	67	2	i	int
    //   69	2	3	bool	boolean
    //   11	445	4	localObject1	Object
    //   1	453	5	localObject2	Object
    //   60	370	6	str1	String
    //   105	317	7	localObject3	Object
    //   57	287	8	str2	String
    //   49	47	9	localEnumeration	java.util.Enumeration
    //   230	23	10	localFile	File
    // Exception table:
    //   from	to	target	type
    //   62	70	336	java/lang/Throwable
    //   95	107	336	java/lang/Throwable
    //   113	124	336	java/lang/Throwable
    //   130	138	336	java/lang/Throwable
    //   144	205	336	java/lang/Throwable
    //   211	219	336	java/lang/Throwable
    //   225	232	336	java/lang/Throwable
    //   238	246	336	java/lang/Throwable
    //   252	258	336	java/lang/Throwable
    //   264	270	336	java/lang/Throwable
    //   276	287	336	java/lang/Throwable
    //   327	333	336	java/lang/Throwable
    //   287	294	373	java/lang/Throwable
    //   294	301	373	java/lang/Throwable
    //   305	314	373	java/lang/Throwable
    //   361	370	373	java/lang/Throwable
    //   3	27	386	finally
    //   27	44	386	finally
    //   44	51	411	finally
    //   287	294	420	finally
    //   294	301	420	finally
    //   305	314	420	finally
    //   361	370	420	finally
    //   62	70	428	finally
    //   95	107	428	finally
    //   113	124	428	finally
    //   130	138	428	finally
    //   144	205	428	finally
    //   211	219	428	finally
    //   225	232	428	finally
    //   238	246	428	finally
    //   252	258	428	finally
    //   264	270	428	finally
    //   276	287	428	finally
    //   327	333	428	finally
    //   3	27	435	java/lang/Throwable
    //   27	44	435	java/lang/Throwable
    //   44	51	447	java/lang/Throwable
  }
}

/* Location:
 * Qualified Name:     cn.com.xy.sms.sdk.util.XyUtil
 * Java Class Version: 6 (50.0)
 * JD-Core Version:    0.7.1
 */