package cn.com.xy.sms.sdk.db.entity;

import android.content.ContentValues;
import cn.com.xy.sms.sdk.db.DBManager;
import java.util.List;

public final class o
{
  private static String a = "id";
  private static String b = "sceneRuleVersion";
  private static String c = "scene_id";
  private static String d = "province";
  private static String e = "operator";
  private static String f = "expire_date";
  private static String g = "Func_call";
  private static String h = "Func_acc_url";
  private static String i = "Func_reply_sms";
  private static String j = "Func_config";
  private static String k = "res_urls";
  private static String l = "s_version";
  private static String m = "Scene_page_config";
  private static String n = "isdownload";
  private static String o = "tb_scenerule_config";
  private static String p = "sceneType";
  private static String q = " DROP TABLE IF EXISTS tb_scenerule_config";
  private static String r = "create table  if not exists tb_scenerule_config (id TEXT,sceneRuleVersion TEXT,scene_id TEXT,province TEXT,operator TEXT,expire_date TEXT,Func_call INTEGER,Func_acc_url INTEGER,Func_reply_sms INTEGER,Func_config TEXT,res_urls TEXT,s_version TEXT,Scene_page_config TEXT,sceneType INTEGER DEFAULT '-1',isdownload INTEGER DEFAULT '0')";
  private static String s = "ALTER TABLE tb_scenerule_config ADD COLUMN isdownload INTEGER DEFAULT '0'";
  
  /* Error */
  public static List<SceneRule> a(int paramInt)
  {
    // Byte code:
    //   0: new 72	java/util/ArrayList
    //   3: dup
    //   4: invokespecial 73	java/util/ArrayList:<init>	()V
    //   7: astore 20
    //   9: aconst_null
    //   10: astore 19
    //   12: aconst_null
    //   13: astore 18
    //   15: iload_0
    //   16: iconst_1
    //   17: if_icmpne +414 -> 431
    //   20: aload 18
    //   22: astore 16
    //   24: aload 19
    //   26: astore 15
    //   28: new 75	java/lang/StringBuilder
    //   31: dup
    //   32: ldc 77
    //   34: invokespecial 80	java/lang/StringBuilder:<init>	(Ljava/lang/String;)V
    //   37: iload_0
    //   38: invokevirtual 84	java/lang/StringBuilder:append	(I)Ljava/lang/StringBuilder;
    //   41: invokevirtual 88	java/lang/StringBuilder:toString	()Ljava/lang/String;
    //   44: astore 17
    //   46: aload 18
    //   48: astore 16
    //   50: aload 19
    //   52: astore 15
    //   54: ldc 50
    //   56: bipush 14
    //   58: anewarray 90	java/lang/String
    //   61: dup
    //   62: iconst_0
    //   63: ldc 8
    //   65: aastore
    //   66: dup
    //   67: iconst_1
    //   68: ldc 14
    //   70: aastore
    //   71: dup
    //   72: iconst_2
    //   73: ldc 17
    //   75: aastore
    //   76: dup
    //   77: iconst_3
    //   78: ldc 20
    //   80: aastore
    //   81: dup
    //   82: iconst_4
    //   83: ldc 23
    //   85: aastore
    //   86: dup
    //   87: iconst_5
    //   88: ldc 26
    //   90: aastore
    //   91: dup
    //   92: bipush 6
    //   94: ldc 29
    //   96: aastore
    //   97: dup
    //   98: bipush 7
    //   100: ldc 32
    //   102: aastore
    //   103: dup
    //   104: bipush 8
    //   106: ldc 35
    //   108: aastore
    //   109: dup
    //   110: bipush 9
    //   112: ldc 38
    //   114: aastore
    //   115: dup
    //   116: bipush 10
    //   118: ldc 41
    //   120: aastore
    //   121: dup
    //   122: bipush 11
    //   124: ldc 44
    //   126: aastore
    //   127: dup
    //   128: bipush 12
    //   130: ldc 47
    //   132: aastore
    //   133: dup
    //   134: bipush 13
    //   136: ldc 11
    //   138: aastore
    //   139: aload 17
    //   141: aconst_null
    //   142: invokestatic 96	cn/com/xy/sms/sdk/db/DBManager:query	(Ljava/lang/String;[Ljava/lang/String;Ljava/lang/String;[Ljava/lang/String;)Lcn/com/xy/sms/sdk/db/XyCursor;
    //   145: astore 17
    //   147: aload 17
    //   149: ifnull +273 -> 422
    //   152: aload 17
    //   154: astore 16
    //   156: aload 17
    //   158: astore 15
    //   160: aload 17
    //   162: invokevirtual 102	cn/com/xy/sms/sdk/db/XyCursor:getCount	()I
    //   165: ifle +257 -> 422
    //   168: aload 17
    //   170: astore 16
    //   172: aload 17
    //   174: astore 15
    //   176: aload 17
    //   178: ldc 8
    //   180: invokevirtual 106	cn/com/xy/sms/sdk/db/XyCursor:getColumnIndex	(Ljava/lang/String;)I
    //   183: istore_0
    //   184: aload 17
    //   186: astore 16
    //   188: aload 17
    //   190: astore 15
    //   192: aload 17
    //   194: ldc 14
    //   196: invokevirtual 106	cn/com/xy/sms/sdk/db/XyCursor:getColumnIndex	(Ljava/lang/String;)I
    //   199: istore_1
    //   200: aload 17
    //   202: astore 16
    //   204: aload 17
    //   206: astore 15
    //   208: aload 17
    //   210: ldc 17
    //   212: invokevirtual 106	cn/com/xy/sms/sdk/db/XyCursor:getColumnIndex	(Ljava/lang/String;)I
    //   215: istore_2
    //   216: aload 17
    //   218: astore 16
    //   220: aload 17
    //   222: astore 15
    //   224: aload 17
    //   226: ldc 20
    //   228: invokevirtual 106	cn/com/xy/sms/sdk/db/XyCursor:getColumnIndex	(Ljava/lang/String;)I
    //   231: istore_3
    //   232: aload 17
    //   234: astore 16
    //   236: aload 17
    //   238: astore 15
    //   240: aload 17
    //   242: ldc 23
    //   244: invokevirtual 106	cn/com/xy/sms/sdk/db/XyCursor:getColumnIndex	(Ljava/lang/String;)I
    //   247: istore 4
    //   249: aload 17
    //   251: astore 16
    //   253: aload 17
    //   255: astore 15
    //   257: aload 17
    //   259: ldc 26
    //   261: invokevirtual 106	cn/com/xy/sms/sdk/db/XyCursor:getColumnIndex	(Ljava/lang/String;)I
    //   264: istore 5
    //   266: aload 17
    //   268: astore 16
    //   270: aload 17
    //   272: astore 15
    //   274: aload 17
    //   276: ldc 29
    //   278: invokevirtual 106	cn/com/xy/sms/sdk/db/XyCursor:getColumnIndex	(Ljava/lang/String;)I
    //   281: istore 6
    //   283: aload 17
    //   285: astore 16
    //   287: aload 17
    //   289: astore 15
    //   291: aload 17
    //   293: ldc 32
    //   295: invokevirtual 106	cn/com/xy/sms/sdk/db/XyCursor:getColumnIndex	(Ljava/lang/String;)I
    //   298: istore 7
    //   300: aload 17
    //   302: astore 16
    //   304: aload 17
    //   306: astore 15
    //   308: aload 17
    //   310: ldc 35
    //   312: invokevirtual 106	cn/com/xy/sms/sdk/db/XyCursor:getColumnIndex	(Ljava/lang/String;)I
    //   315: istore 8
    //   317: aload 17
    //   319: astore 16
    //   321: aload 17
    //   323: astore 15
    //   325: aload 17
    //   327: ldc 38
    //   329: invokevirtual 106	cn/com/xy/sms/sdk/db/XyCursor:getColumnIndex	(Ljava/lang/String;)I
    //   332: istore 9
    //   334: aload 17
    //   336: astore 16
    //   338: aload 17
    //   340: astore 15
    //   342: aload 17
    //   344: ldc 41
    //   346: invokevirtual 106	cn/com/xy/sms/sdk/db/XyCursor:getColumnIndex	(Ljava/lang/String;)I
    //   349: istore 10
    //   351: aload 17
    //   353: astore 16
    //   355: aload 17
    //   357: astore 15
    //   359: aload 17
    //   361: ldc 44
    //   363: invokevirtual 106	cn/com/xy/sms/sdk/db/XyCursor:getColumnIndex	(Ljava/lang/String;)I
    //   366: istore 11
    //   368: aload 17
    //   370: astore 16
    //   372: aload 17
    //   374: astore 15
    //   376: aload 17
    //   378: ldc 47
    //   380: invokevirtual 106	cn/com/xy/sms/sdk/db/XyCursor:getColumnIndex	(Ljava/lang/String;)I
    //   383: istore 12
    //   385: aload 17
    //   387: astore 16
    //   389: aload 17
    //   391: astore 15
    //   393: aload 17
    //   395: ldc 11
    //   397: invokevirtual 106	cn/com/xy/sms/sdk/db/XyCursor:getColumnIndex	(Ljava/lang/String;)I
    //   400: istore 13
    //   402: aload 17
    //   404: astore 16
    //   406: aload 17
    //   408: astore 15
    //   410: aload 17
    //   412: invokevirtual 110	cn/com/xy/sms/sdk/db/XyCursor:moveToNext	()Z
    //   415: istore 14
    //   417: iload 14
    //   419: ifne +19 -> 438
    //   422: aload 17
    //   424: iconst_1
    //   425: invokestatic 114	cn/com/xy/sms/sdk/db/XyCursor:closeCursor	(Lcn/com/xy/sms/sdk/db/XyCursor;Z)V
    //   428: aload 20
    //   430: areturn
    //   431: ldc 116
    //   433: astore 17
    //   435: goto -389 -> 46
    //   438: aload 17
    //   440: astore 16
    //   442: aload 17
    //   444: astore 15
    //   446: new 118	cn/com/xy/sms/sdk/db/entity/SceneRule
    //   449: dup
    //   450: invokespecial 119	cn/com/xy/sms/sdk/db/entity/SceneRule:<init>	()V
    //   453: astore 18
    //   455: aload 17
    //   457: astore 16
    //   459: aload 17
    //   461: astore 15
    //   463: aload 18
    //   465: aload 17
    //   467: iload_0
    //   468: invokevirtual 123	cn/com/xy/sms/sdk/db/XyCursor:getString	(I)Ljava/lang/String;
    //   471: putfield 125	cn/com/xy/sms/sdk/db/entity/SceneRule:id	Ljava/lang/String;
    //   474: aload 17
    //   476: astore 16
    //   478: aload 17
    //   480: astore 15
    //   482: aload 18
    //   484: aload 17
    //   486: iload_1
    //   487: invokevirtual 123	cn/com/xy/sms/sdk/db/XyCursor:getString	(I)Ljava/lang/String;
    //   490: putfield 127	cn/com/xy/sms/sdk/db/entity/SceneRule:scene_id	Ljava/lang/String;
    //   493: aload 17
    //   495: astore 16
    //   497: aload 17
    //   499: astore 15
    //   501: aload 18
    //   503: aload 17
    //   505: iload_2
    //   506: invokevirtual 123	cn/com/xy/sms/sdk/db/XyCursor:getString	(I)Ljava/lang/String;
    //   509: putfield 129	cn/com/xy/sms/sdk/db/entity/SceneRule:province	Ljava/lang/String;
    //   512: aload 17
    //   514: astore 16
    //   516: aload 17
    //   518: astore 15
    //   520: aload 18
    //   522: aload 17
    //   524: iload_3
    //   525: invokevirtual 123	cn/com/xy/sms/sdk/db/XyCursor:getString	(I)Ljava/lang/String;
    //   528: putfield 131	cn/com/xy/sms/sdk/db/entity/SceneRule:operator	Ljava/lang/String;
    //   531: aload 17
    //   533: astore 16
    //   535: aload 17
    //   537: astore 15
    //   539: aload 18
    //   541: aload 17
    //   543: iload 4
    //   545: invokevirtual 123	cn/com/xy/sms/sdk/db/XyCursor:getString	(I)Ljava/lang/String;
    //   548: putfield 133	cn/com/xy/sms/sdk/db/entity/SceneRule:expire_date	Ljava/lang/String;
    //   551: aload 17
    //   553: astore 16
    //   555: aload 17
    //   557: astore 15
    //   559: aload 18
    //   561: aload 17
    //   563: iload 5
    //   565: invokevirtual 137	cn/com/xy/sms/sdk/db/XyCursor:getInt	(I)I
    //   568: putfield 140	cn/com/xy/sms/sdk/db/entity/SceneRule:Func_call	I
    //   571: aload 17
    //   573: astore 16
    //   575: aload 17
    //   577: astore 15
    //   579: aload 18
    //   581: aload 17
    //   583: iload 6
    //   585: invokevirtual 137	cn/com/xy/sms/sdk/db/XyCursor:getInt	(I)I
    //   588: putfield 142	cn/com/xy/sms/sdk/db/entity/SceneRule:Func_acc_url	I
    //   591: aload 17
    //   593: astore 16
    //   595: aload 17
    //   597: astore 15
    //   599: aload 18
    //   601: aload 17
    //   603: iload 7
    //   605: invokevirtual 137	cn/com/xy/sms/sdk/db/XyCursor:getInt	(I)I
    //   608: putfield 144	cn/com/xy/sms/sdk/db/entity/SceneRule:Func_reply_sms	I
    //   611: aload 17
    //   613: astore 16
    //   615: aload 17
    //   617: astore 15
    //   619: aload 18
    //   621: aload 17
    //   623: iload 8
    //   625: invokevirtual 123	cn/com/xy/sms/sdk/db/XyCursor:getString	(I)Ljava/lang/String;
    //   628: putfield 146	cn/com/xy/sms/sdk/db/entity/SceneRule:Func_config	Ljava/lang/String;
    //   631: aload 17
    //   633: astore 16
    //   635: aload 17
    //   637: astore 15
    //   639: aload 18
    //   641: aload 17
    //   643: iload 9
    //   645: invokevirtual 123	cn/com/xy/sms/sdk/db/XyCursor:getString	(I)Ljava/lang/String;
    //   648: putfield 148	cn/com/xy/sms/sdk/db/entity/SceneRule:res_urls	Ljava/lang/String;
    //   651: aload 17
    //   653: astore 16
    //   655: aload 17
    //   657: astore 15
    //   659: aload 18
    //   661: aload 17
    //   663: iload 10
    //   665: invokevirtual 123	cn/com/xy/sms/sdk/db/XyCursor:getString	(I)Ljava/lang/String;
    //   668: putfield 150	cn/com/xy/sms/sdk/db/entity/SceneRule:s_version	Ljava/lang/String;
    //   671: aload 17
    //   673: astore 16
    //   675: aload 17
    //   677: astore 15
    //   679: aload 18
    //   681: aload 17
    //   683: iload 11
    //   685: invokevirtual 123	cn/com/xy/sms/sdk/db/XyCursor:getString	(I)Ljava/lang/String;
    //   688: putfield 152	cn/com/xy/sms/sdk/db/entity/SceneRule:Scene_page_config	Ljava/lang/String;
    //   691: aload 17
    //   693: astore 16
    //   695: aload 17
    //   697: astore 15
    //   699: aload 18
    //   701: aload 17
    //   703: iload 12
    //   705: invokevirtual 137	cn/com/xy/sms/sdk/db/XyCursor:getInt	(I)I
    //   708: putfield 155	cn/com/xy/sms/sdk/db/entity/SceneRule:isDownload	I
    //   711: aload 17
    //   713: astore 16
    //   715: aload 17
    //   717: astore 15
    //   719: aload 18
    //   721: aload 17
    //   723: iload 13
    //   725: invokevirtual 123	cn/com/xy/sms/sdk/db/XyCursor:getString	(I)Ljava/lang/String;
    //   728: putfield 158	cn/com/xy/sms/sdk/db/entity/SceneRule:sceneruleVersion	Ljava/lang/String;
    //   731: aload 17
    //   733: astore 16
    //   735: aload 17
    //   737: astore 15
    //   739: aload 20
    //   741: aload 18
    //   743: invokeinterface 164 2 0
    //   748: pop
    //   749: goto -347 -> 402
    //   752: astore 17
    //   754: aload 16
    //   756: astore 15
    //   758: aload 17
    //   760: invokevirtual 167	java/lang/Throwable:printStackTrace	()V
    //   763: aload 16
    //   765: iconst_1
    //   766: invokestatic 114	cn/com/xy/sms/sdk/db/XyCursor:closeCursor	(Lcn/com/xy/sms/sdk/db/XyCursor;Z)V
    //   769: aload 20
    //   771: areturn
    //   772: astore 16
    //   774: aload 15
    //   776: iconst_1
    //   777: invokestatic 114	cn/com/xy/sms/sdk/db/XyCursor:closeCursor	(Lcn/com/xy/sms/sdk/db/XyCursor;Z)V
    //   780: aload 16
    //   782: athrow
    // Local variable table:
    //   start	length	slot	name	signature
    //   0	783	0	paramInt	int
    //   199	288	1	i1	int
    //   215	291	2	i2	int
    //   231	294	3	i3	int
    //   247	297	4	i4	int
    //   264	300	5	i5	int
    //   281	303	6	i6	int
    //   298	306	7	i7	int
    //   315	309	8	i8	int
    //   332	312	9	i9	int
    //   349	315	10	i10	int
    //   366	318	11	i11	int
    //   383	321	12	i12	int
    //   400	324	13	i13	int
    //   415	3	14	bool	boolean
    //   26	749	15	localObject1	Object
    //   22	742	16	localObject2	Object
    //   772	9	16	localObject3	Object
    //   44	692	17	localObject4	Object
    //   752	7	17	localThrowable	Throwable
    //   13	729	18	localSceneRule	SceneRule
    //   10	41	19	localObject5	Object
    //   7	763	20	localArrayList	java.util.ArrayList
    // Exception table:
    //   from	to	target	type
    //   28	46	752	java/lang/Throwable
    //   54	147	752	java/lang/Throwable
    //   160	168	752	java/lang/Throwable
    //   176	184	752	java/lang/Throwable
    //   192	200	752	java/lang/Throwable
    //   208	216	752	java/lang/Throwable
    //   224	232	752	java/lang/Throwable
    //   240	249	752	java/lang/Throwable
    //   257	266	752	java/lang/Throwable
    //   274	283	752	java/lang/Throwable
    //   291	300	752	java/lang/Throwable
    //   308	317	752	java/lang/Throwable
    //   325	334	752	java/lang/Throwable
    //   342	351	752	java/lang/Throwable
    //   359	368	752	java/lang/Throwable
    //   376	385	752	java/lang/Throwable
    //   393	402	752	java/lang/Throwable
    //   410	417	752	java/lang/Throwable
    //   446	455	752	java/lang/Throwable
    //   463	474	752	java/lang/Throwable
    //   482	493	752	java/lang/Throwable
    //   501	512	752	java/lang/Throwable
    //   520	531	752	java/lang/Throwable
    //   539	551	752	java/lang/Throwable
    //   559	571	752	java/lang/Throwable
    //   579	591	752	java/lang/Throwable
    //   599	611	752	java/lang/Throwable
    //   619	631	752	java/lang/Throwable
    //   639	651	752	java/lang/Throwable
    //   659	671	752	java/lang/Throwable
    //   679	691	752	java/lang/Throwable
    //   699	711	752	java/lang/Throwable
    //   719	731	752	java/lang/Throwable
    //   739	749	752	java/lang/Throwable
    //   28	46	772	finally
    //   54	147	772	finally
    //   160	168	772	finally
    //   176	184	772	finally
    //   192	200	772	finally
    //   208	216	772	finally
    //   224	232	772	finally
    //   240	249	772	finally
    //   257	266	772	finally
    //   274	283	772	finally
    //   291	300	772	finally
    //   308	317	772	finally
    //   325	334	772	finally
    //   342	351	772	finally
    //   359	368	772	finally
    //   376	385	772	finally
    //   393	402	772	finally
    //   410	417	772	finally
    //   446	455	772	finally
    //   463	474	772	finally
    //   482	493	772	finally
    //   501	512	772	finally
    //   520	531	772	finally
    //   539	551	772	finally
    //   559	571	772	finally
    //   579	591	772	finally
    //   599	611	772	finally
    //   619	631	772	finally
    //   639	651	772	finally
    //   659	671	772	finally
    //   679	691	772	finally
    //   699	711	772	finally
    //   719	731	772	finally
    //   739	749	772	finally
    //   758	763	772	finally
  }
  
  public static List<SceneRule> a(String paramString, int paramInt)
  {
    return a(paramString, paramInt, false);
  }
  
  /* Error */
  public static List<SceneRule> a(String paramString, int paramInt, boolean paramBoolean)
  {
    // Byte code:
    //   0: new 72	java/util/ArrayList
    //   3: dup
    //   4: invokespecial 73	java/util/ArrayList:<init>	()V
    //   7: astore 20
    //   9: aconst_null
    //   10: astore 19
    //   12: aconst_null
    //   13: astore 18
    //   15: iload_2
    //   16: ifeq +445 -> 461
    //   19: aload 18
    //   21: astore 17
    //   23: aload 19
    //   25: astore 16
    //   27: aload_0
    //   28: invokevirtual 177	java/lang/String:length	()I
    //   31: bipush 8
    //   33: if_icmpne +428 -> 461
    //   36: aload 18
    //   38: astore 17
    //   40: aload 19
    //   42: astore 16
    //   44: new 75	java/lang/StringBuilder
    //   47: dup
    //   48: ldc -77
    //   50: invokespecial 80	java/lang/StringBuilder:<init>	(Ljava/lang/String;)V
    //   53: aload_0
    //   54: iconst_0
    //   55: iconst_2
    //   56: invokevirtual 183	java/lang/String:substring	(II)Ljava/lang/String;
    //   59: invokevirtual 186	java/lang/StringBuilder:append	(Ljava/lang/String;)Ljava/lang/StringBuilder;
    //   62: ldc -68
    //   64: invokevirtual 186	java/lang/StringBuilder:append	(Ljava/lang/String;)Ljava/lang/StringBuilder;
    //   67: aload_0
    //   68: iconst_5
    //   69: bipush 8
    //   71: invokevirtual 183	java/lang/String:substring	(II)Ljava/lang/String;
    //   74: invokevirtual 186	java/lang/StringBuilder:append	(Ljava/lang/String;)Ljava/lang/StringBuilder;
    //   77: ldc -66
    //   79: invokevirtual 186	java/lang/StringBuilder:append	(Ljava/lang/String;)Ljava/lang/StringBuilder;
    //   82: invokevirtual 88	java/lang/StringBuilder:toString	()Ljava/lang/String;
    //   85: astore_0
    //   86: iload_1
    //   87: iconst_1
    //   88: if_icmpne +406 -> 494
    //   91: aload 18
    //   93: astore 17
    //   95: aload 19
    //   97: astore 16
    //   99: new 75	java/lang/StringBuilder
    //   102: dup
    //   103: aload_0
    //   104: invokestatic 194	java/lang/String:valueOf	(Ljava/lang/Object;)Ljava/lang/String;
    //   107: invokespecial 80	java/lang/StringBuilder:<init>	(Ljava/lang/String;)V
    //   110: ldc -60
    //   112: invokevirtual 186	java/lang/StringBuilder:append	(Ljava/lang/String;)Ljava/lang/StringBuilder;
    //   115: ldc -58
    //   117: invokevirtual 186	java/lang/StringBuilder:append	(Ljava/lang/String;)Ljava/lang/StringBuilder;
    //   120: iload_1
    //   121: invokevirtual 84	java/lang/StringBuilder:append	(I)Ljava/lang/StringBuilder;
    //   124: invokevirtual 88	java/lang/StringBuilder:toString	()Ljava/lang/String;
    //   127: astore_0
    //   128: aload 18
    //   130: astore 17
    //   132: aload 19
    //   134: astore 16
    //   136: ldc 50
    //   138: bipush 14
    //   140: anewarray 90	java/lang/String
    //   143: dup
    //   144: iconst_0
    //   145: ldc 8
    //   147: aastore
    //   148: dup
    //   149: iconst_1
    //   150: ldc 14
    //   152: aastore
    //   153: dup
    //   154: iconst_2
    //   155: ldc 17
    //   157: aastore
    //   158: dup
    //   159: iconst_3
    //   160: ldc 20
    //   162: aastore
    //   163: dup
    //   164: iconst_4
    //   165: ldc 23
    //   167: aastore
    //   168: dup
    //   169: iconst_5
    //   170: ldc 26
    //   172: aastore
    //   173: dup
    //   174: bipush 6
    //   176: ldc 29
    //   178: aastore
    //   179: dup
    //   180: bipush 7
    //   182: ldc 32
    //   184: aastore
    //   185: dup
    //   186: bipush 8
    //   188: ldc 35
    //   190: aastore
    //   191: dup
    //   192: bipush 9
    //   194: ldc 38
    //   196: aastore
    //   197: dup
    //   198: bipush 10
    //   200: ldc 41
    //   202: aastore
    //   203: dup
    //   204: bipush 11
    //   206: ldc 44
    //   208: aastore
    //   209: dup
    //   210: bipush 12
    //   212: ldc 47
    //   214: aastore
    //   215: dup
    //   216: bipush 13
    //   218: ldc 11
    //   220: aastore
    //   221: aload_0
    //   222: aconst_null
    //   223: invokestatic 96	cn/com/xy/sms/sdk/db/DBManager:query	(Ljava/lang/String;[Ljava/lang/String;Ljava/lang/String;[Ljava/lang/String;)Lcn/com/xy/sms/sdk/db/XyCursor;
    //   226: astore_0
    //   227: aload_0
    //   228: ifnull +225 -> 453
    //   231: aload_0
    //   232: astore 17
    //   234: aload_0
    //   235: astore 16
    //   237: aload_0
    //   238: invokevirtual 102	cn/com/xy/sms/sdk/db/XyCursor:getCount	()I
    //   241: ifle +212 -> 453
    //   244: aload_0
    //   245: astore 17
    //   247: aload_0
    //   248: astore 16
    //   250: aload_0
    //   251: ldc 8
    //   253: invokevirtual 106	cn/com/xy/sms/sdk/db/XyCursor:getColumnIndex	(Ljava/lang/String;)I
    //   256: istore_1
    //   257: aload_0
    //   258: astore 17
    //   260: aload_0
    //   261: astore 16
    //   263: aload_0
    //   264: ldc 14
    //   266: invokevirtual 106	cn/com/xy/sms/sdk/db/XyCursor:getColumnIndex	(Ljava/lang/String;)I
    //   269: istore_3
    //   270: aload_0
    //   271: astore 17
    //   273: aload_0
    //   274: astore 16
    //   276: aload_0
    //   277: ldc 17
    //   279: invokevirtual 106	cn/com/xy/sms/sdk/db/XyCursor:getColumnIndex	(Ljava/lang/String;)I
    //   282: istore 4
    //   284: aload_0
    //   285: astore 17
    //   287: aload_0
    //   288: astore 16
    //   290: aload_0
    //   291: ldc 20
    //   293: invokevirtual 106	cn/com/xy/sms/sdk/db/XyCursor:getColumnIndex	(Ljava/lang/String;)I
    //   296: istore 5
    //   298: aload_0
    //   299: astore 17
    //   301: aload_0
    //   302: astore 16
    //   304: aload_0
    //   305: ldc 23
    //   307: invokevirtual 106	cn/com/xy/sms/sdk/db/XyCursor:getColumnIndex	(Ljava/lang/String;)I
    //   310: istore 6
    //   312: aload_0
    //   313: astore 17
    //   315: aload_0
    //   316: astore 16
    //   318: aload_0
    //   319: ldc 26
    //   321: invokevirtual 106	cn/com/xy/sms/sdk/db/XyCursor:getColumnIndex	(Ljava/lang/String;)I
    //   324: istore 7
    //   326: aload_0
    //   327: astore 17
    //   329: aload_0
    //   330: astore 16
    //   332: aload_0
    //   333: ldc 29
    //   335: invokevirtual 106	cn/com/xy/sms/sdk/db/XyCursor:getColumnIndex	(Ljava/lang/String;)I
    //   338: istore 8
    //   340: aload_0
    //   341: astore 17
    //   343: aload_0
    //   344: astore 16
    //   346: aload_0
    //   347: ldc 32
    //   349: invokevirtual 106	cn/com/xy/sms/sdk/db/XyCursor:getColumnIndex	(Ljava/lang/String;)I
    //   352: istore 9
    //   354: aload_0
    //   355: astore 17
    //   357: aload_0
    //   358: astore 16
    //   360: aload_0
    //   361: ldc 35
    //   363: invokevirtual 106	cn/com/xy/sms/sdk/db/XyCursor:getColumnIndex	(Ljava/lang/String;)I
    //   366: istore 10
    //   368: aload_0
    //   369: astore 17
    //   371: aload_0
    //   372: astore 16
    //   374: aload_0
    //   375: ldc 38
    //   377: invokevirtual 106	cn/com/xy/sms/sdk/db/XyCursor:getColumnIndex	(Ljava/lang/String;)I
    //   380: istore 11
    //   382: aload_0
    //   383: astore 17
    //   385: aload_0
    //   386: astore 16
    //   388: aload_0
    //   389: ldc 41
    //   391: invokevirtual 106	cn/com/xy/sms/sdk/db/XyCursor:getColumnIndex	(Ljava/lang/String;)I
    //   394: istore 12
    //   396: aload_0
    //   397: astore 17
    //   399: aload_0
    //   400: astore 16
    //   402: aload_0
    //   403: ldc 44
    //   405: invokevirtual 106	cn/com/xy/sms/sdk/db/XyCursor:getColumnIndex	(Ljava/lang/String;)I
    //   408: istore 13
    //   410: aload_0
    //   411: astore 17
    //   413: aload_0
    //   414: astore 16
    //   416: aload_0
    //   417: ldc 47
    //   419: invokevirtual 106	cn/com/xy/sms/sdk/db/XyCursor:getColumnIndex	(Ljava/lang/String;)I
    //   422: istore 14
    //   424: aload_0
    //   425: astore 17
    //   427: aload_0
    //   428: astore 16
    //   430: aload_0
    //   431: ldc 11
    //   433: invokevirtual 106	cn/com/xy/sms/sdk/db/XyCursor:getColumnIndex	(Ljava/lang/String;)I
    //   436: istore 15
    //   438: aload_0
    //   439: astore 17
    //   441: aload_0
    //   442: astore 16
    //   444: aload_0
    //   445: invokevirtual 110	cn/com/xy/sms/sdk/db/XyCursor:moveToNext	()Z
    //   448: istore_2
    //   449: iload_2
    //   450: ifne +80 -> 530
    //   453: aload_0
    //   454: iconst_1
    //   455: invokestatic 114	cn/com/xy/sms/sdk/db/XyCursor:closeCursor	(Lcn/com/xy/sms/sdk/db/XyCursor;Z)V
    //   458: aload 20
    //   460: areturn
    //   461: aload 18
    //   463: astore 17
    //   465: aload 19
    //   467: astore 16
    //   469: new 75	java/lang/StringBuilder
    //   472: dup
    //   473: ldc -56
    //   475: invokespecial 80	java/lang/StringBuilder:<init>	(Ljava/lang/String;)V
    //   478: aload_0
    //   479: invokevirtual 186	java/lang/StringBuilder:append	(Ljava/lang/String;)Ljava/lang/StringBuilder;
    //   482: ldc -66
    //   484: invokevirtual 186	java/lang/StringBuilder:append	(Ljava/lang/String;)Ljava/lang/StringBuilder;
    //   487: invokevirtual 88	java/lang/StringBuilder:toString	()Ljava/lang/String;
    //   490: astore_0
    //   491: goto -405 -> 86
    //   494: aload 18
    //   496: astore 17
    //   498: aload 19
    //   500: astore 16
    //   502: new 75	java/lang/StringBuilder
    //   505: dup
    //   506: aload_0
    //   507: invokestatic 194	java/lang/String:valueOf	(Ljava/lang/Object;)Ljava/lang/String;
    //   510: invokespecial 80	java/lang/StringBuilder:<init>	(Ljava/lang/String;)V
    //   513: ldc -60
    //   515: invokevirtual 186	java/lang/StringBuilder:append	(Ljava/lang/String;)Ljava/lang/StringBuilder;
    //   518: ldc -54
    //   520: invokevirtual 186	java/lang/StringBuilder:append	(Ljava/lang/String;)Ljava/lang/StringBuilder;
    //   523: invokevirtual 88	java/lang/StringBuilder:toString	()Ljava/lang/String;
    //   526: astore_0
    //   527: goto -399 -> 128
    //   530: aload_0
    //   531: astore 17
    //   533: aload_0
    //   534: astore 16
    //   536: new 118	cn/com/xy/sms/sdk/db/entity/SceneRule
    //   539: dup
    //   540: invokespecial 119	cn/com/xy/sms/sdk/db/entity/SceneRule:<init>	()V
    //   543: astore 18
    //   545: aload_0
    //   546: astore 17
    //   548: aload_0
    //   549: astore 16
    //   551: aload 18
    //   553: aload_0
    //   554: iload_1
    //   555: invokevirtual 123	cn/com/xy/sms/sdk/db/XyCursor:getString	(I)Ljava/lang/String;
    //   558: putfield 125	cn/com/xy/sms/sdk/db/entity/SceneRule:id	Ljava/lang/String;
    //   561: aload_0
    //   562: astore 17
    //   564: aload_0
    //   565: astore 16
    //   567: aload 18
    //   569: aload_0
    //   570: iload_3
    //   571: invokevirtual 123	cn/com/xy/sms/sdk/db/XyCursor:getString	(I)Ljava/lang/String;
    //   574: putfield 127	cn/com/xy/sms/sdk/db/entity/SceneRule:scene_id	Ljava/lang/String;
    //   577: aload_0
    //   578: astore 17
    //   580: aload_0
    //   581: astore 16
    //   583: aload 18
    //   585: aload_0
    //   586: iload 4
    //   588: invokevirtual 123	cn/com/xy/sms/sdk/db/XyCursor:getString	(I)Ljava/lang/String;
    //   591: putfield 129	cn/com/xy/sms/sdk/db/entity/SceneRule:province	Ljava/lang/String;
    //   594: aload_0
    //   595: astore 17
    //   597: aload_0
    //   598: astore 16
    //   600: aload 18
    //   602: aload_0
    //   603: iload 5
    //   605: invokevirtual 123	cn/com/xy/sms/sdk/db/XyCursor:getString	(I)Ljava/lang/String;
    //   608: putfield 131	cn/com/xy/sms/sdk/db/entity/SceneRule:operator	Ljava/lang/String;
    //   611: aload_0
    //   612: astore 17
    //   614: aload_0
    //   615: astore 16
    //   617: aload 18
    //   619: aload_0
    //   620: iload 6
    //   622: invokevirtual 123	cn/com/xy/sms/sdk/db/XyCursor:getString	(I)Ljava/lang/String;
    //   625: putfield 133	cn/com/xy/sms/sdk/db/entity/SceneRule:expire_date	Ljava/lang/String;
    //   628: aload_0
    //   629: astore 17
    //   631: aload_0
    //   632: astore 16
    //   634: aload 18
    //   636: aload_0
    //   637: iload 7
    //   639: invokevirtual 137	cn/com/xy/sms/sdk/db/XyCursor:getInt	(I)I
    //   642: putfield 140	cn/com/xy/sms/sdk/db/entity/SceneRule:Func_call	I
    //   645: aload_0
    //   646: astore 17
    //   648: aload_0
    //   649: astore 16
    //   651: aload 18
    //   653: aload_0
    //   654: iload 8
    //   656: invokevirtual 137	cn/com/xy/sms/sdk/db/XyCursor:getInt	(I)I
    //   659: putfield 142	cn/com/xy/sms/sdk/db/entity/SceneRule:Func_acc_url	I
    //   662: aload_0
    //   663: astore 17
    //   665: aload_0
    //   666: astore 16
    //   668: aload 18
    //   670: aload_0
    //   671: iload 9
    //   673: invokevirtual 137	cn/com/xy/sms/sdk/db/XyCursor:getInt	(I)I
    //   676: putfield 144	cn/com/xy/sms/sdk/db/entity/SceneRule:Func_reply_sms	I
    //   679: aload_0
    //   680: astore 17
    //   682: aload_0
    //   683: astore 16
    //   685: aload 18
    //   687: aload_0
    //   688: iload 10
    //   690: invokevirtual 123	cn/com/xy/sms/sdk/db/XyCursor:getString	(I)Ljava/lang/String;
    //   693: putfield 146	cn/com/xy/sms/sdk/db/entity/SceneRule:Func_config	Ljava/lang/String;
    //   696: aload_0
    //   697: astore 17
    //   699: aload_0
    //   700: astore 16
    //   702: aload 18
    //   704: aload_0
    //   705: iload 11
    //   707: invokevirtual 123	cn/com/xy/sms/sdk/db/XyCursor:getString	(I)Ljava/lang/String;
    //   710: putfield 148	cn/com/xy/sms/sdk/db/entity/SceneRule:res_urls	Ljava/lang/String;
    //   713: aload_0
    //   714: astore 17
    //   716: aload_0
    //   717: astore 16
    //   719: aload 18
    //   721: aload_0
    //   722: iload 12
    //   724: invokevirtual 123	cn/com/xy/sms/sdk/db/XyCursor:getString	(I)Ljava/lang/String;
    //   727: putfield 150	cn/com/xy/sms/sdk/db/entity/SceneRule:s_version	Ljava/lang/String;
    //   730: aload_0
    //   731: astore 17
    //   733: aload_0
    //   734: astore 16
    //   736: aload 18
    //   738: aload_0
    //   739: iload 13
    //   741: invokevirtual 123	cn/com/xy/sms/sdk/db/XyCursor:getString	(I)Ljava/lang/String;
    //   744: putfield 152	cn/com/xy/sms/sdk/db/entity/SceneRule:Scene_page_config	Ljava/lang/String;
    //   747: aload_0
    //   748: astore 17
    //   750: aload_0
    //   751: astore 16
    //   753: aload 18
    //   755: aload_0
    //   756: iload 14
    //   758: invokevirtual 137	cn/com/xy/sms/sdk/db/XyCursor:getInt	(I)I
    //   761: putfield 155	cn/com/xy/sms/sdk/db/entity/SceneRule:isDownload	I
    //   764: aload_0
    //   765: astore 17
    //   767: aload_0
    //   768: astore 16
    //   770: aload 18
    //   772: aload_0
    //   773: iload 15
    //   775: invokevirtual 123	cn/com/xy/sms/sdk/db/XyCursor:getString	(I)Ljava/lang/String;
    //   778: putfield 158	cn/com/xy/sms/sdk/db/entity/SceneRule:sceneruleVersion	Ljava/lang/String;
    //   781: aload_0
    //   782: astore 17
    //   784: aload_0
    //   785: astore 16
    //   787: aload 20
    //   789: aload 18
    //   791: invokeinterface 164 2 0
    //   796: pop
    //   797: goto -359 -> 438
    //   800: astore_0
    //   801: aload 17
    //   803: astore 16
    //   805: aload_0
    //   806: invokevirtual 167	java/lang/Throwable:printStackTrace	()V
    //   809: aload 17
    //   811: iconst_1
    //   812: invokestatic 114	cn/com/xy/sms/sdk/db/XyCursor:closeCursor	(Lcn/com/xy/sms/sdk/db/XyCursor;Z)V
    //   815: aload 20
    //   817: areturn
    //   818: astore_0
    //   819: aload 16
    //   821: iconst_1
    //   822: invokestatic 114	cn/com/xy/sms/sdk/db/XyCursor:closeCursor	(Lcn/com/xy/sms/sdk/db/XyCursor;Z)V
    //   825: aload_0
    //   826: athrow
    // Local variable table:
    //   start	length	slot	name	signature
    //   0	827	0	paramString	String
    //   0	827	1	paramInt	int
    //   0	827	2	paramBoolean	boolean
    //   269	302	3	i1	int
    //   282	305	4	i2	int
    //   296	308	5	i3	int
    //   310	311	6	i4	int
    //   324	314	7	i5	int
    //   338	317	8	i6	int
    //   352	320	9	i7	int
    //   366	323	10	i8	int
    //   380	326	11	i9	int
    //   394	329	12	i10	int
    //   408	332	13	i11	int
    //   422	335	14	i12	int
    //   436	338	15	i13	int
    //   25	795	16	localObject1	Object
    //   21	789	17	localObject2	Object
    //   13	777	18	localSceneRule	SceneRule
    //   10	489	19	localObject3	Object
    //   7	809	20	localArrayList	java.util.ArrayList
    // Exception table:
    //   from	to	target	type
    //   27	36	800	java/lang/Throwable
    //   44	86	800	java/lang/Throwable
    //   99	128	800	java/lang/Throwable
    //   136	227	800	java/lang/Throwable
    //   237	244	800	java/lang/Throwable
    //   250	257	800	java/lang/Throwable
    //   263	270	800	java/lang/Throwable
    //   276	284	800	java/lang/Throwable
    //   290	298	800	java/lang/Throwable
    //   304	312	800	java/lang/Throwable
    //   318	326	800	java/lang/Throwable
    //   332	340	800	java/lang/Throwable
    //   346	354	800	java/lang/Throwable
    //   360	368	800	java/lang/Throwable
    //   374	382	800	java/lang/Throwable
    //   388	396	800	java/lang/Throwable
    //   402	410	800	java/lang/Throwable
    //   416	424	800	java/lang/Throwable
    //   430	438	800	java/lang/Throwable
    //   444	449	800	java/lang/Throwable
    //   469	491	800	java/lang/Throwable
    //   502	527	800	java/lang/Throwable
    //   536	545	800	java/lang/Throwable
    //   551	561	800	java/lang/Throwable
    //   567	577	800	java/lang/Throwable
    //   583	594	800	java/lang/Throwable
    //   600	611	800	java/lang/Throwable
    //   617	628	800	java/lang/Throwable
    //   634	645	800	java/lang/Throwable
    //   651	662	800	java/lang/Throwable
    //   668	679	800	java/lang/Throwable
    //   685	696	800	java/lang/Throwable
    //   702	713	800	java/lang/Throwable
    //   719	730	800	java/lang/Throwable
    //   736	747	800	java/lang/Throwable
    //   753	764	800	java/lang/Throwable
    //   770	781	800	java/lang/Throwable
    //   787	797	800	java/lang/Throwable
    //   27	36	818	finally
    //   44	86	818	finally
    //   99	128	818	finally
    //   136	227	818	finally
    //   237	244	818	finally
    //   250	257	818	finally
    //   263	270	818	finally
    //   276	284	818	finally
    //   290	298	818	finally
    //   304	312	818	finally
    //   318	326	818	finally
    //   332	340	818	finally
    //   346	354	818	finally
    //   360	368	818	finally
    //   374	382	818	finally
    //   388	396	818	finally
    //   402	410	818	finally
    //   416	424	818	finally
    //   430	438	818	finally
    //   444	449	818	finally
    //   469	491	818	finally
    //   502	527	818	finally
    //   536	545	818	finally
    //   551	561	818	finally
    //   567	577	818	finally
    //   583	594	818	finally
    //   600	611	818	finally
    //   617	628	818	finally
    //   634	645	818	finally
    //   651	662	818	finally
    //   668	679	818	finally
    //   685	696	818	finally
    //   702	713	818	finally
    //   719	730	818	finally
    //   736	747	818	finally
    //   753	764	818	finally
    //   770	781	818	finally
    //   787	797	818	finally
    //   805	809	818	finally
  }
  
  public static void a()
  {
    try
    {
      DBManager.delete("tb_scenerule_config", null, null);
      return;
    }
    catch (Throwable localThrowable)
    {
      localThrowable.printStackTrace();
    }
  }
  
  public static void a(SceneRule paramSceneRule, int paramInt)
  {
    if (paramSceneRule != null) {}
    try
    {
      ContentValues localContentValues = new ContentValues();
      localContentValues.put("isdownload", Integer.valueOf(1));
      DBManager.update("tb_scenerule_config", localContentValues, "id = ? ", new String[] { id });
      return;
    }
    catch (Throwable paramSceneRule)
    {
      paramSceneRule.printStackTrace();
    }
  }
  
  public static int b(int paramInt)
  {
    try
    {
      ContentValues localContentValues = new ContentValues();
      localContentValues.put("Func_call", Integer.valueOf(paramInt));
      paramInt = DBManager.update("tb_scenerule_config", localContentValues, null, null);
      return paramInt;
    }
    catch (Throwable localThrowable)
    {
      localThrowable.printStackTrace();
    }
    return -1;
  }
  
  /* Error */
  public static long b(SceneRule paramSceneRule, int paramInt)
  {
    // Byte code:
    //   0: new 210	android/content/ContentValues
    //   3: dup
    //   4: invokespecial 211	android/content/ContentValues:<init>	()V
    //   7: astore 9
    //   9: aload 9
    //   11: ldc 8
    //   13: aload_0
    //   14: getfield 125	cn/com/xy/sms/sdk/db/entity/SceneRule:id	Ljava/lang/String;
    //   17: invokevirtual 230	android/content/ContentValues:put	(Ljava/lang/String;Ljava/lang/String;)V
    //   20: aload 9
    //   22: ldc 11
    //   24: aload_0
    //   25: getfield 158	cn/com/xy/sms/sdk/db/entity/SceneRule:sceneruleVersion	Ljava/lang/String;
    //   28: invokevirtual 230	android/content/ContentValues:put	(Ljava/lang/String;Ljava/lang/String;)V
    //   31: aload 9
    //   33: ldc 14
    //   35: aload_0
    //   36: getfield 127	cn/com/xy/sms/sdk/db/entity/SceneRule:scene_id	Ljava/lang/String;
    //   39: invokevirtual 230	android/content/ContentValues:put	(Ljava/lang/String;Ljava/lang/String;)V
    //   42: aload 9
    //   44: ldc 17
    //   46: aload_0
    //   47: getfield 129	cn/com/xy/sms/sdk/db/entity/SceneRule:province	Ljava/lang/String;
    //   50: invokevirtual 230	android/content/ContentValues:put	(Ljava/lang/String;Ljava/lang/String;)V
    //   53: aload 9
    //   55: ldc 20
    //   57: aload_0
    //   58: getfield 131	cn/com/xy/sms/sdk/db/entity/SceneRule:operator	Ljava/lang/String;
    //   61: invokevirtual 230	android/content/ContentValues:put	(Ljava/lang/String;Ljava/lang/String;)V
    //   64: aload 9
    //   66: ldc 23
    //   68: aload_0
    //   69: getfield 133	cn/com/xy/sms/sdk/db/entity/SceneRule:expire_date	Ljava/lang/String;
    //   72: invokevirtual 230	android/content/ContentValues:put	(Ljava/lang/String;Ljava/lang/String;)V
    //   75: aload 9
    //   77: ldc 26
    //   79: aload_0
    //   80: getfield 140	cn/com/xy/sms/sdk/db/entity/SceneRule:Func_call	I
    //   83: invokestatic 216	java/lang/Integer:valueOf	(I)Ljava/lang/Integer;
    //   86: invokevirtual 220	android/content/ContentValues:put	(Ljava/lang/String;Ljava/lang/Integer;)V
    //   89: aload 9
    //   91: ldc 29
    //   93: aload_0
    //   94: getfield 142	cn/com/xy/sms/sdk/db/entity/SceneRule:Func_acc_url	I
    //   97: invokestatic 216	java/lang/Integer:valueOf	(I)Ljava/lang/Integer;
    //   100: invokevirtual 220	android/content/ContentValues:put	(Ljava/lang/String;Ljava/lang/Integer;)V
    //   103: aload 9
    //   105: ldc 32
    //   107: aload_0
    //   108: getfield 144	cn/com/xy/sms/sdk/db/entity/SceneRule:Func_reply_sms	I
    //   111: invokestatic 216	java/lang/Integer:valueOf	(I)Ljava/lang/Integer;
    //   114: invokevirtual 220	android/content/ContentValues:put	(Ljava/lang/String;Ljava/lang/Integer;)V
    //   117: aload 9
    //   119: ldc 35
    //   121: aload_0
    //   122: getfield 146	cn/com/xy/sms/sdk/db/entity/SceneRule:Func_config	Ljava/lang/String;
    //   125: invokevirtual 230	android/content/ContentValues:put	(Ljava/lang/String;Ljava/lang/String;)V
    //   128: aload 9
    //   130: ldc 38
    //   132: aload_0
    //   133: getfield 148	cn/com/xy/sms/sdk/db/entity/SceneRule:res_urls	Ljava/lang/String;
    //   136: invokevirtual 230	android/content/ContentValues:put	(Ljava/lang/String;Ljava/lang/String;)V
    //   139: aload 9
    //   141: ldc 41
    //   143: aload_0
    //   144: getfield 150	cn/com/xy/sms/sdk/db/entity/SceneRule:s_version	Ljava/lang/String;
    //   147: invokevirtual 230	android/content/ContentValues:put	(Ljava/lang/String;Ljava/lang/String;)V
    //   150: aload 9
    //   152: ldc 44
    //   154: aload_0
    //   155: getfield 152	cn/com/xy/sms/sdk/db/entity/SceneRule:Scene_page_config	Ljava/lang/String;
    //   158: invokevirtual 230	android/content/ContentValues:put	(Ljava/lang/String;Ljava/lang/String;)V
    //   161: aload 9
    //   163: ldc 47
    //   165: aload_0
    //   166: getfield 155	cn/com/xy/sms/sdk/db/entity/SceneRule:isDownload	I
    //   169: invokestatic 216	java/lang/Integer:valueOf	(I)Ljava/lang/Integer;
    //   172: invokevirtual 220	android/content/ContentValues:put	(Ljava/lang/String;Ljava/lang/Integer;)V
    //   175: aload 9
    //   177: ldc 53
    //   179: iload_1
    //   180: invokestatic 216	java/lang/Integer:valueOf	(I)Ljava/lang/Integer;
    //   183: invokevirtual 220	android/content/ContentValues:put	(Ljava/lang/String;Ljava/lang/Integer;)V
    //   186: aconst_null
    //   187: astore 7
    //   189: aconst_null
    //   190: astore 8
    //   192: aconst_null
    //   193: astore 4
    //   195: aload 7
    //   197: astore 6
    //   199: aload 8
    //   201: astore 5
    //   203: aload_0
    //   204: getfield 125	cn/com/xy/sms/sdk/db/entity/SceneRule:id	Ljava/lang/String;
    //   207: invokestatic 236	cn/com/xy/sms/sdk/util/StringUtils:isNull	(Ljava/lang/String;)Z
    //   210: ifne +57 -> 267
    //   213: aload 7
    //   215: astore 6
    //   217: aload 8
    //   219: astore 5
    //   221: aload_0
    //   222: getfield 125	cn/com/xy/sms/sdk/db/entity/SceneRule:id	Ljava/lang/String;
    //   225: astore 4
    //   227: aload 7
    //   229: astore 6
    //   231: aload 8
    //   233: astore 5
    //   235: ldc 50
    //   237: iconst_2
    //   238: anewarray 90	java/lang/String
    //   241: dup
    //   242: iconst_0
    //   243: ldc 8
    //   245: aastore
    //   246: dup
    //   247: iconst_1
    //   248: ldc 11
    //   250: aastore
    //   251: ldc -34
    //   253: iconst_1
    //   254: anewarray 90	java/lang/String
    //   257: dup
    //   258: iconst_0
    //   259: aload 4
    //   261: aastore
    //   262: invokestatic 96	cn/com/xy/sms/sdk/db/DBManager:query	(Ljava/lang/String;[Ljava/lang/String;Ljava/lang/String;[Ljava/lang/String;)Lcn/com/xy/sms/sdk/db/XyCursor;
    //   265: astore 4
    //   267: aload 4
    //   269: ifnull +59 -> 328
    //   272: aload 4
    //   274: astore 6
    //   276: aload 4
    //   278: astore 5
    //   280: aload 4
    //   282: invokevirtual 102	cn/com/xy/sms/sdk/db/XyCursor:getCount	()I
    //   285: ifle +43 -> 328
    //   288: aload 4
    //   290: astore 6
    //   292: aload 4
    //   294: astore 5
    //   296: ldc 50
    //   298: aload 9
    //   300: ldc -18
    //   302: iconst_1
    //   303: anewarray 90	java/lang/String
    //   306: dup
    //   307: iconst_0
    //   308: aload_0
    //   309: getfield 125	cn/com/xy/sms/sdk/db/entity/SceneRule:id	Ljava/lang/String;
    //   312: aastore
    //   313: invokestatic 226	cn/com/xy/sms/sdk/db/DBManager:update	(Ljava/lang/String;Landroid/content/ContentValues;Ljava/lang/String;[Ljava/lang/String;)I
    //   316: istore_1
    //   317: iload_1
    //   318: i2l
    //   319: lstore_2
    //   320: aload 4
    //   322: iconst_1
    //   323: invokestatic 114	cn/com/xy/sms/sdk/db/XyCursor:closeCursor	(Lcn/com/xy/sms/sdk/db/XyCursor;Z)V
    //   326: lload_2
    //   327: lreturn
    //   328: aload 4
    //   330: astore 6
    //   332: aload 4
    //   334: astore 5
    //   336: ldc 50
    //   338: aload 9
    //   340: invokestatic 242	cn/com/xy/sms/sdk/db/DBManager:insert	(Ljava/lang/String;Landroid/content/ContentValues;)J
    //   343: lstore_2
    //   344: goto -24 -> 320
    //   347: astore_0
    //   348: aload 6
    //   350: astore 5
    //   352: aload_0
    //   353: invokevirtual 167	java/lang/Throwable:printStackTrace	()V
    //   356: aload 6
    //   358: iconst_1
    //   359: invokestatic 114	cn/com/xy/sms/sdk/db/XyCursor:closeCursor	(Lcn/com/xy/sms/sdk/db/XyCursor;Z)V
    //   362: ldc2_w 243
    //   365: lreturn
    //   366: astore_0
    //   367: aload 5
    //   369: iconst_1
    //   370: invokestatic 114	cn/com/xy/sms/sdk/db/XyCursor:closeCursor	(Lcn/com/xy/sms/sdk/db/XyCursor;Z)V
    //   373: aload_0
    //   374: athrow
    // Local variable table:
    //   start	length	slot	name	signature
    //   0	375	0	paramSceneRule	SceneRule
    //   0	375	1	paramInt	int
    //   319	25	2	l1	long
    //   193	140	4	localObject1	Object
    //   201	167	5	localObject2	Object
    //   197	160	6	localObject3	Object
    //   187	41	7	localObject4	Object
    //   190	42	8	localObject5	Object
    //   7	332	9	localContentValues	ContentValues
    // Exception table:
    //   from	to	target	type
    //   203	213	347	java/lang/Throwable
    //   221	227	347	java/lang/Throwable
    //   235	267	347	java/lang/Throwable
    //   280	288	347	java/lang/Throwable
    //   296	317	347	java/lang/Throwable
    //   336	344	347	java/lang/Throwable
    //   203	213	366	finally
    //   221	227	366	finally
    //   235	267	366	finally
    //   280	288	366	finally
    //   296	317	366	finally
    //   336	344	366	finally
    //   352	356	366	finally
  }
  
  /* Error */
  public static void b()
  {
    // Byte code:
    //   0: getstatic 248	cn/com/xy/sms/sdk/db/DBManager:dblock	Ljava/lang/Object;
    //   3: astore_3
    //   4: aload_3
    //   5: monitorenter
    //   6: aconst_null
    //   7: astore_1
    //   8: aconst_null
    //   9: astore_0
    //   10: invokestatic 252	cn/com/xy/sms/sdk/db/DBManager:getSQLiteDatabase	()Landroid/database/sqlite/SQLiteDatabase;
    //   13: astore_2
    //   14: aload_2
    //   15: astore_0
    //   16: aload_2
    //   17: astore_1
    //   18: aload_2
    //   19: ldc -2
    //   21: invokevirtual 259	android/database/sqlite/SQLiteDatabase:execSQL	(Ljava/lang/String;)V
    //   24: aload_2
    //   25: invokestatic 263	cn/com/xy/sms/sdk/db/DBManager:close	(Landroid/database/sqlite/SQLiteDatabase;)V
    //   28: aload_3
    //   29: monitorexit
    //   30: return
    //   31: astore_2
    //   32: aload_0
    //   33: astore_1
    //   34: aload_2
    //   35: invokevirtual 167	java/lang/Throwable:printStackTrace	()V
    //   38: aload_0
    //   39: invokestatic 263	cn/com/xy/sms/sdk/db/DBManager:close	(Landroid/database/sqlite/SQLiteDatabase;)V
    //   42: goto -14 -> 28
    //   45: astore_0
    //   46: aload_3
    //   47: monitorexit
    //   48: aload_0
    //   49: athrow
    //   50: astore_0
    //   51: aload_1
    //   52: invokestatic 263	cn/com/xy/sms/sdk/db/DBManager:close	(Landroid/database/sqlite/SQLiteDatabase;)V
    //   55: aload_0
    //   56: athrow
    // Local variable table:
    //   start	length	slot	name	signature
    //   9	30	0	localObject1	Object
    //   45	4	0	localObject2	Object
    //   50	6	0	localObject3	Object
    //   7	45	1	localObject4	Object
    //   13	12	2	localSQLiteDatabase	android.database.sqlite.SQLiteDatabase
    //   31	4	2	localThrowable	Throwable
    //   3	44	3	localObject5	Object
    // Exception table:
    //   from	to	target	type
    //   10	14	31	java/lang/Throwable
    //   18	24	31	java/lang/Throwable
    //   24	28	45	finally
    //   28	30	45	finally
    //   38	42	45	finally
    //   51	57	45	finally
    //   10	14	50	finally
    //   18	24	50	finally
    //   34	38	50	finally
  }
  
  public static void b(String paramString, int paramInt)
  {
    if (paramInt == 1) {}
    for (;;)
    {
      try
      {
        str = "scene_id=? and sceneType = " + paramInt;
        DBManager.delete("tb_scenerule_config", str, new String[] { paramString });
        return;
      }
      catch (Throwable paramString)
      {
        String str;
        paramString.printStackTrace();
      }
      str = "scene_id=? and sceneType != 1";
    }
  }
  
  private static ContentValues c(SceneRule paramSceneRule, int paramInt)
  {
    ContentValues localContentValues = new ContentValues();
    localContentValues.put("id", id);
    localContentValues.put("sceneRuleVersion", sceneruleVersion);
    localContentValues.put("scene_id", scene_id);
    localContentValues.put("province", province);
    localContentValues.put("operator", operator);
    localContentValues.put("expire_date", expire_date);
    localContentValues.put("Func_call", Integer.valueOf(Func_call));
    localContentValues.put("Func_acc_url", Integer.valueOf(Func_acc_url));
    localContentValues.put("Func_reply_sms", Integer.valueOf(Func_reply_sms));
    localContentValues.put("Func_config", Func_config);
    localContentValues.put("res_urls", res_urls);
    localContentValues.put("s_version", s_version);
    localContentValues.put("Scene_page_config", Scene_page_config);
    localContentValues.put("isdownload", Integer.valueOf(isDownload));
    localContentValues.put("sceneType", Integer.valueOf(paramInt));
    return localContentValues;
  }
}

/* Location:
 * Qualified Name:     cn.com.xy.sms.sdk.db.entity.o
 * Java Class Version: 6 (50.0)
 * JD-Core Version:    0.7.1
 */