package cn.com.xy.sms.sdk.net.util;

import android.content.Context;
import java.util.Map;

final class b
{
  private static long a = -1L;
  private static boolean b = false;
  private static boolean c = false;
  
  /* Error */
  private static void a(Context paramContext, boolean paramBoolean)
  {
    // Byte code:
    //   0: aconst_null
    //   1: astore 4
    //   3: aconst_null
    //   4: astore_3
    //   5: aload 4
    //   7: astore_2
    //   8: invokestatic 32	java/lang/System:currentTimeMillis	()J
    //   11: putstatic 15	cn/com/xy/sms/sdk/net/util/b:a	J
    //   14: aload 4
    //   16: astore_2
    //   17: iload_1
    //   18: putstatic 17	cn/com/xy/sms/sdk/net/util/b:b	Z
    //   21: aload 4
    //   23: astore_2
    //   24: new 34	java/io/File
    //   27: dup
    //   28: new 36	java/lang/StringBuilder
    //   31: dup
    //   32: invokespecial 37	java/lang/StringBuilder:<init>	()V
    //   35: aload_0
    //   36: invokevirtual 43	android/content/Context:getApplicationContext	()Landroid/content/Context;
    //   39: invokevirtual 47	android/content/Context:getFilesDir	()Ljava/io/File;
    //   42: invokevirtual 51	java/lang/StringBuilder:append	(Ljava/lang/Object;)Ljava/lang/StringBuilder;
    //   45: getstatic 55	java/io/File:separator	Ljava/lang/String;
    //   48: invokevirtual 58	java/lang/StringBuilder:append	(Ljava/lang/String;)Ljava/lang/StringBuilder;
    //   51: ldc 60
    //   53: invokevirtual 58	java/lang/StringBuilder:append	(Ljava/lang/String;)Ljava/lang/StringBuilder;
    //   56: invokevirtual 64	java/lang/StringBuilder:toString	()Ljava/lang/String;
    //   59: invokespecial 67	java/io/File:<init>	(Ljava/lang/String;)V
    //   62: astore_0
    //   63: aload 4
    //   65: astore_2
    //   66: aload_0
    //   67: invokevirtual 71	java/io/File:exists	()Z
    //   70: ifeq +11 -> 81
    //   73: aload 4
    //   75: astore_2
    //   76: aload_0
    //   77: invokevirtual 74	java/io/File:delete	()Z
    //   80: pop
    //   81: aload 4
    //   83: astore_2
    //   84: aload_0
    //   85: invokevirtual 77	java/io/File:createNewFile	()Z
    //   88: pop
    //   89: aload 4
    //   91: astore_2
    //   92: new 79	java/io/FileOutputStream
    //   95: dup
    //   96: aload_0
    //   97: iconst_0
    //   98: invokespecial 82	java/io/FileOutputStream:<init>	(Ljava/io/File;Z)V
    //   101: astore_0
    //   102: aload_0
    //   103: new 36	java/lang/StringBuilder
    //   106: dup
    //   107: ldc 84
    //   109: invokespecial 85	java/lang/StringBuilder:<init>	(Ljava/lang/String;)V
    //   112: iload_1
    //   113: invokevirtual 88	java/lang/StringBuilder:append	(Z)Ljava/lang/StringBuilder;
    //   116: ldc 90
    //   118: invokevirtual 58	java/lang/StringBuilder:append	(Ljava/lang/String;)Ljava/lang/StringBuilder;
    //   121: invokevirtual 64	java/lang/StringBuilder:toString	()Ljava/lang/String;
    //   124: invokevirtual 96	java/lang/String:getBytes	()[B
    //   127: invokevirtual 100	java/io/FileOutputStream:write	([B)V
    //   130: aload_0
    //   131: new 36	java/lang/StringBuilder
    //   134: dup
    //   135: ldc 102
    //   137: invokespecial 85	java/lang/StringBuilder:<init>	(Ljava/lang/String;)V
    //   140: invokestatic 32	java/lang/System:currentTimeMillis	()J
    //   143: invokevirtual 105	java/lang/StringBuilder:append	(J)Ljava/lang/StringBuilder;
    //   146: ldc 90
    //   148: invokevirtual 58	java/lang/StringBuilder:append	(Ljava/lang/String;)Ljava/lang/StringBuilder;
    //   151: invokevirtual 64	java/lang/StringBuilder:toString	()Ljava/lang/String;
    //   154: invokevirtual 96	java/lang/String:getBytes	()[B
    //   157: invokevirtual 100	java/io/FileOutputStream:write	([B)V
    //   160: aload_0
    //   161: invokevirtual 108	java/io/FileOutputStream:flush	()V
    //   164: aload_0
    //   165: invokevirtual 111	java/io/FileOutputStream:close	()V
    //   168: return
    //   169: astore_2
    //   170: aload_3
    //   171: astore_0
    //   172: aload_2
    //   173: astore_3
    //   174: aload_0
    //   175: astore_2
    //   176: aload_3
    //   177: invokevirtual 114	java/lang/Throwable:printStackTrace	()V
    //   180: aload_0
    //   181: ifnull -13 -> 168
    //   184: aload_0
    //   185: invokevirtual 111	java/io/FileOutputStream:close	()V
    //   188: return
    //   189: astore_0
    //   190: aload_0
    //   191: invokevirtual 114	java/lang/Throwable:printStackTrace	()V
    //   194: return
    //   195: astore_0
    //   196: aload_2
    //   197: ifnull +7 -> 204
    //   200: aload_2
    //   201: invokevirtual 111	java/io/FileOutputStream:close	()V
    //   204: aload_0
    //   205: athrow
    //   206: astore_2
    //   207: aload_2
    //   208: invokevirtual 114	java/lang/Throwable:printStackTrace	()V
    //   211: goto -7 -> 204
    //   214: astore_0
    //   215: aload_0
    //   216: invokevirtual 114	java/lang/Throwable:printStackTrace	()V
    //   219: return
    //   220: astore_3
    //   221: aload_0
    //   222: astore_2
    //   223: aload_3
    //   224: astore_0
    //   225: goto -29 -> 196
    //   228: astore_3
    //   229: goto -55 -> 174
    // Local variable table:
    //   start	length	slot	name	signature
    //   0	232	0	paramContext	Context
    //   0	232	1	paramBoolean	boolean
    //   7	85	2	localObject1	Object
    //   169	4	2	localThrowable1	Throwable
    //   175	26	2	localContext1	Context
    //   206	2	2	localThrowable2	Throwable
    //   222	1	2	localContext2	Context
    //   4	173	3	localObject2	Object
    //   220	4	3	localObject3	Object
    //   228	1	3	localThrowable3	Throwable
    //   1	89	4	localObject4	Object
    // Exception table:
    //   from	to	target	type
    //   8	14	169	java/lang/Throwable
    //   17	21	169	java/lang/Throwable
    //   24	63	169	java/lang/Throwable
    //   66	73	169	java/lang/Throwable
    //   76	81	169	java/lang/Throwable
    //   84	89	169	java/lang/Throwable
    //   92	102	169	java/lang/Throwable
    //   184	188	189	java/lang/Throwable
    //   8	14	195	finally
    //   17	21	195	finally
    //   24	63	195	finally
    //   66	73	195	finally
    //   76	81	195	finally
    //   84	89	195	finally
    //   92	102	195	finally
    //   176	180	195	finally
    //   200	204	206	java/lang/Throwable
    //   164	168	214	java/lang/Throwable
    //   102	164	220	finally
    //   102	164	228	java/lang/Throwable
  }
  
  static boolean a(Context paramContext)
  {
    if (a == -1L)
    {
      Map localMap = c(paramContext);
      if (localMap == null) {
        break label108;
      }
      b = Boolean.valueOf((String)localMap.get("checkEnable")).booleanValue();
      a = Long.valueOf((String)localMap.get("checkTime")).longValue();
    }
    for (;;)
    {
      if ((!b) || (a == 0L) || (a + 86400000L < System.currentTimeMillis())) {
        new c(paramContext).start();
      }
      if (a != 0L) {
        break;
      }
      return true;
      label108:
      a = 0L;
      b = true;
    }
    if (!b) {
      throw new Exception(" PLEASE CHECK NETWORK IS OK.");
    }
    return b;
  }
  
  /* Error */
  private static Map<String, String> c(Context paramContext)
  {
    // Byte code:
    //   0: aconst_null
    //   1: astore_2
    //   2: new 34	java/io/File
    //   5: dup
    //   6: new 36	java/lang/StringBuilder
    //   9: dup
    //   10: invokespecial 37	java/lang/StringBuilder:<init>	()V
    //   13: aload_0
    //   14: invokevirtual 43	android/content/Context:getApplicationContext	()Landroid/content/Context;
    //   17: invokevirtual 47	android/content/Context:getFilesDir	()Ljava/io/File;
    //   20: invokevirtual 51	java/lang/StringBuilder:append	(Ljava/lang/Object;)Ljava/lang/StringBuilder;
    //   23: getstatic 55	java/io/File:separator	Ljava/lang/String;
    //   26: invokevirtual 58	java/lang/StringBuilder:append	(Ljava/lang/String;)Ljava/lang/StringBuilder;
    //   29: ldc 60
    //   31: invokevirtual 58	java/lang/StringBuilder:append	(Ljava/lang/String;)Ljava/lang/StringBuilder;
    //   34: invokevirtual 64	java/lang/StringBuilder:toString	()Ljava/lang/String;
    //   37: invokespecial 67	java/io/File:<init>	(Ljava/lang/String;)V
    //   40: astore_0
    //   41: aload_0
    //   42: invokevirtual 71	java/io/File:exists	()Z
    //   45: ifne +8 -> 53
    //   48: aload_0
    //   49: invokevirtual 77	java/io/File:createNewFile	()Z
    //   52: pop
    //   53: new 255	java/io/LineNumberReader
    //   56: dup
    //   57: new 257	java/io/FileReader
    //   60: dup
    //   61: aload_0
    //   62: invokespecial 260	java/io/FileReader:<init>	(Ljava/io/File;)V
    //   65: invokespecial 263	java/io/LineNumberReader:<init>	(Ljava/io/Reader;)V
    //   68: astore_1
    //   69: aconst_null
    //   70: astore_2
    //   71: aload_1
    //   72: astore_0
    //   73: aload_1
    //   74: invokevirtual 266	java/io/LineNumberReader:readLine	()Ljava/lang/String;
    //   77: astore 4
    //   79: aload 4
    //   81: ifnonnull +9 -> 90
    //   84: aload_1
    //   85: invokevirtual 267	java/io/LineNumberReader:close	()V
    //   88: aload_2
    //   89: areturn
    //   90: aload_2
    //   91: astore_3
    //   92: aload_2
    //   93: ifnonnull +13 -> 106
    //   96: aload_1
    //   97: astore_0
    //   98: new 269	java/util/HashMap
    //   101: dup
    //   102: invokespecial 270	java/util/HashMap:<init>	()V
    //   105: astore_3
    //   106: aload_1
    //   107: astore_0
    //   108: aload 4
    //   110: ldc_w 272
    //   113: invokevirtual 276	java/lang/String:split	(Ljava/lang/String;)[Ljava/lang/String;
    //   116: astore_2
    //   117: aload_1
    //   118: astore_0
    //   119: aload_3
    //   120: aload_2
    //   121: iconst_0
    //   122: aaload
    //   123: aload_2
    //   124: iconst_1
    //   125: aaload
    //   126: invokeinterface 280 3 0
    //   131: pop
    //   132: aload_3
    //   133: astore_2
    //   134: goto -63 -> 71
    //   137: astore_2
    //   138: aload_1
    //   139: astore_0
    //   140: aload_2
    //   141: invokevirtual 114	java/lang/Throwable:printStackTrace	()V
    //   144: aload_1
    //   145: ifnull +7 -> 152
    //   148: aload_1
    //   149: invokevirtual 267	java/io/LineNumberReader:close	()V
    //   152: aconst_null
    //   153: areturn
    //   154: astore_0
    //   155: aload_0
    //   156: invokevirtual 114	java/lang/Throwable:printStackTrace	()V
    //   159: aload_2
    //   160: areturn
    //   161: astore_0
    //   162: aload_0
    //   163: invokevirtual 114	java/lang/Throwable:printStackTrace	()V
    //   166: goto -14 -> 152
    //   169: astore_0
    //   170: aload_2
    //   171: astore_1
    //   172: aload_1
    //   173: ifnull +7 -> 180
    //   176: aload_1
    //   177: invokevirtual 267	java/io/LineNumberReader:close	()V
    //   180: aload_0
    //   181: athrow
    //   182: astore_1
    //   183: aload_1
    //   184: invokevirtual 114	java/lang/Throwable:printStackTrace	()V
    //   187: goto -7 -> 180
    //   190: astore_2
    //   191: aload_0
    //   192: astore_1
    //   193: aload_2
    //   194: astore_0
    //   195: goto -23 -> 172
    //   198: astore_2
    //   199: aconst_null
    //   200: astore_1
    //   201: goto -63 -> 138
    // Local variable table:
    //   start	length	slot	name	signature
    //   0	204	0	paramContext	Context
    //   68	109	1	localObject1	Object
    //   182	2	1	localThrowable1	Throwable
    //   192	9	1	localContext	Context
    //   1	133	2	localObject2	Object
    //   137	34	2	localThrowable2	Throwable
    //   190	4	2	localObject3	Object
    //   198	1	2	localThrowable3	Throwable
    //   91	42	3	localObject4	Object
    //   77	32	4	str	String
    // Exception table:
    //   from	to	target	type
    //   73	79	137	java/lang/Throwable
    //   98	106	137	java/lang/Throwable
    //   108	117	137	java/lang/Throwable
    //   119	132	137	java/lang/Throwable
    //   84	88	154	java/lang/Throwable
    //   148	152	161	java/lang/Throwable
    //   2	53	169	finally
    //   53	69	169	finally
    //   176	180	182	java/lang/Throwable
    //   73	79	190	finally
    //   98	106	190	finally
    //   108	117	190	finally
    //   119	132	190	finally
    //   140	144	190	finally
    //   2	53	198	java/lang/Throwable
    //   53	69	198	java/lang/Throwable
  }
  
  /* Error */
  private static void d(Context paramContext)
  {
    // Byte code:
    //   0: aconst_null
    //   1: astore 6
    //   3: aconst_null
    //   4: astore 7
    //   6: aconst_null
    //   7: astore 5
    //   9: iconst_1
    //   10: istore_2
    //   11: getstatic 19	cn/com/xy/sms/sdk/net/util/b:c	Z
    //   14: ifeq +4 -> 18
    //   17: return
    //   18: iconst_1
    //   19: putstatic 19	cn/com/xy/sms/sdk/net/util/b:c	Z
    //   22: invokestatic 165	cn/com/xy/sms/sdk/util/KeyManager:initAppKey	()V
    //   25: new 167	java/net/URL
    //   28: dup
    //   29: ldc -87
    //   31: invokespecial 170	java/net/URL:<init>	(Ljava/lang/String;)V
    //   34: invokevirtual 174	java/net/URL:openConnection	()Ljava/net/URLConnection;
    //   37: checkcast 176	java/net/HttpURLConnection
    //   40: astore 4
    //   42: aload 4
    //   44: ldc -79
    //   46: invokevirtual 181	java/net/HttpURLConnection:setConnectTimeout	(I)V
    //   49: aload 4
    //   51: iconst_1
    //   52: invokevirtual 185	java/net/HttpURLConnection:setDoInput	(Z)V
    //   55: aload 4
    //   57: iconst_1
    //   58: invokevirtual 188	java/net/HttpURLConnection:setDoOutput	(Z)V
    //   61: aload 4
    //   63: ldc -66
    //   65: invokevirtual 193	java/net/HttpURLConnection:setRequestMethod	(Ljava/lang/String;)V
    //   68: aload 4
    //   70: iconst_0
    //   71: invokevirtual 196	java/net/HttpURLConnection:setUseCaches	(Z)V
    //   74: aload 4
    //   76: iconst_1
    //   77: invokevirtual 199	java/net/HttpURLConnection:setInstanceFollowRedirects	(Z)V
    //   80: aload 4
    //   82: ldc -55
    //   84: getstatic 206	cn/com/xy/sms/sdk/net/i:e	Ljava/lang/String;
    //   87: invokevirtual 210	java/net/HttpURLConnection:setRequestProperty	(Ljava/lang/String;Ljava/lang/String;)V
    //   90: aload 4
    //   92: invokevirtual 213	java/net/HttpURLConnection:connect	()V
    //   95: aload 4
    //   97: invokevirtual 217	java/net/HttpURLConnection:getResponseCode	()I
    //   100: sipush 200
    //   103: if_icmpne +479 -> 582
    //   106: aload 4
    //   108: invokevirtual 221	java/net/HttpURLConnection:getInputStream	()Ljava/io/InputStream;
    //   111: astore 5
    //   113: sipush 1024
    //   116: newarray <illegal type>
    //   118: astore 9
    //   120: new 223	java/io/ByteArrayOutputStream
    //   123: dup
    //   124: invokespecial 224	java/io/ByteArrayOutputStream:<init>	()V
    //   127: astore 8
    //   129: aload 5
    //   131: aload 9
    //   133: invokevirtual 230	java/io/InputStream:read	([B)I
    //   136: istore_1
    //   137: iload_1
    //   138: iconst_m1
    //   139: if_icmpne +229 -> 368
    //   142: aload 8
    //   144: invokevirtual 231	java/io/ByteArrayOutputStream:flush	()V
    //   147: new 92	java/lang/String
    //   150: dup
    //   151: aload 8
    //   153: invokevirtual 234	java/io/ByteArrayOutputStream:toByteArray	()[B
    //   156: ldc -20
    //   158: invokespecial 239	java/lang/String:<init>	([BLjava/lang/String;)V
    //   161: ldc -15
    //   163: invokevirtual 245	java/lang/String:equals	(Ljava/lang/Object;)Z
    //   166: istore_3
    //   167: iload_3
    //   168: ifeq +409 -> 577
    //   171: aload 8
    //   173: invokevirtual 246	java/io/ByteArrayOutputStream:close	()V
    //   176: aload 5
    //   178: invokevirtual 247	java/io/InputStream:close	()V
    //   181: aload 4
    //   183: ifnull +279 -> 462
    //   186: aload 4
    //   188: invokevirtual 250	java/net/HttpURLConnection:disconnect	()V
    //   191: iload_2
    //   192: istore_3
    //   193: aload 7
    //   195: astore 4
    //   197: invokestatic 32	java/lang/System:currentTimeMillis	()J
    //   200: putstatic 15	cn/com/xy/sms/sdk/net/util/b:a	J
    //   203: aload 7
    //   205: astore 4
    //   207: iload_3
    //   208: putstatic 17	cn/com/xy/sms/sdk/net/util/b:b	Z
    //   211: aload 7
    //   213: astore 4
    //   215: new 34	java/io/File
    //   218: dup
    //   219: new 36	java/lang/StringBuilder
    //   222: dup
    //   223: invokespecial 37	java/lang/StringBuilder:<init>	()V
    //   226: aload_0
    //   227: invokevirtual 43	android/content/Context:getApplicationContext	()Landroid/content/Context;
    //   230: invokevirtual 47	android/content/Context:getFilesDir	()Ljava/io/File;
    //   233: invokevirtual 51	java/lang/StringBuilder:append	(Ljava/lang/Object;)Ljava/lang/StringBuilder;
    //   236: getstatic 55	java/io/File:separator	Ljava/lang/String;
    //   239: invokevirtual 58	java/lang/StringBuilder:append	(Ljava/lang/String;)Ljava/lang/StringBuilder;
    //   242: ldc 60
    //   244: invokevirtual 58	java/lang/StringBuilder:append	(Ljava/lang/String;)Ljava/lang/StringBuilder;
    //   247: invokevirtual 64	java/lang/StringBuilder:toString	()Ljava/lang/String;
    //   250: invokespecial 67	java/io/File:<init>	(Ljava/lang/String;)V
    //   253: astore_0
    //   254: aload 7
    //   256: astore 4
    //   258: aload_0
    //   259: invokevirtual 71	java/io/File:exists	()Z
    //   262: ifeq +12 -> 274
    //   265: aload 7
    //   267: astore 4
    //   269: aload_0
    //   270: invokevirtual 74	java/io/File:delete	()Z
    //   273: pop
    //   274: aload 7
    //   276: astore 4
    //   278: aload_0
    //   279: invokevirtual 77	java/io/File:createNewFile	()Z
    //   282: pop
    //   283: aload 7
    //   285: astore 4
    //   287: new 79	java/io/FileOutputStream
    //   290: dup
    //   291: aload_0
    //   292: iconst_0
    //   293: invokespecial 82	java/io/FileOutputStream:<init>	(Ljava/io/File;Z)V
    //   296: astore_0
    //   297: aload_0
    //   298: new 36	java/lang/StringBuilder
    //   301: dup
    //   302: ldc 84
    //   304: invokespecial 85	java/lang/StringBuilder:<init>	(Ljava/lang/String;)V
    //   307: iload_3
    //   308: invokevirtual 88	java/lang/StringBuilder:append	(Z)Ljava/lang/StringBuilder;
    //   311: ldc 90
    //   313: invokevirtual 58	java/lang/StringBuilder:append	(Ljava/lang/String;)Ljava/lang/StringBuilder;
    //   316: invokevirtual 64	java/lang/StringBuilder:toString	()Ljava/lang/String;
    //   319: invokevirtual 96	java/lang/String:getBytes	()[B
    //   322: invokevirtual 100	java/io/FileOutputStream:write	([B)V
    //   325: aload_0
    //   326: new 36	java/lang/StringBuilder
    //   329: dup
    //   330: ldc 102
    //   332: invokespecial 85	java/lang/StringBuilder:<init>	(Ljava/lang/String;)V
    //   335: invokestatic 32	java/lang/System:currentTimeMillis	()J
    //   338: invokevirtual 105	java/lang/StringBuilder:append	(J)Ljava/lang/StringBuilder;
    //   341: ldc 90
    //   343: invokevirtual 58	java/lang/StringBuilder:append	(Ljava/lang/String;)Ljava/lang/StringBuilder;
    //   346: invokevirtual 64	java/lang/StringBuilder:toString	()Ljava/lang/String;
    //   349: invokevirtual 96	java/lang/String:getBytes	()[B
    //   352: invokevirtual 100	java/io/FileOutputStream:write	([B)V
    //   355: aload_0
    //   356: invokevirtual 108	java/io/FileOutputStream:flush	()V
    //   359: aload_0
    //   360: invokevirtual 111	java/io/FileOutputStream:close	()V
    //   363: iconst_0
    //   364: putstatic 19	cn/com/xy/sms/sdk/net/util/b:c	Z
    //   367: return
    //   368: aload 8
    //   370: aload 9
    //   372: iconst_0
    //   373: iload_1
    //   374: invokevirtual 253	java/io/ByteArrayOutputStream:write	([BII)V
    //   377: goto -248 -> 129
    //   380: astore 9
    //   382: aload 9
    //   384: invokevirtual 114	java/lang/Throwable:printStackTrace	()V
    //   387: goto -245 -> 142
    //   390: astore 5
    //   392: iconst_0
    //   393: istore_2
    //   394: aload 5
    //   396: invokevirtual 114	java/lang/Throwable:printStackTrace	()V
    //   399: iload_2
    //   400: istore_3
    //   401: aload 4
    //   403: ifnull -210 -> 193
    //   406: aload 4
    //   408: invokevirtual 250	java/net/HttpURLConnection:disconnect	()V
    //   411: iload_2
    //   412: istore_3
    //   413: goto -220 -> 193
    //   416: astore 4
    //   418: aload 4
    //   420: invokevirtual 114	java/lang/Throwable:printStackTrace	()V
    //   423: iload_2
    //   424: istore_3
    //   425: goto -232 -> 193
    //   428: astore_0
    //   429: aload 5
    //   431: astore 4
    //   433: aload 4
    //   435: ifnull +8 -> 443
    //   438: aload 4
    //   440: invokevirtual 250	java/net/HttpURLConnection:disconnect	()V
    //   443: aload_0
    //   444: athrow
    //   445: astore 4
    //   447: aload 4
    //   449: invokevirtual 114	java/lang/Throwable:printStackTrace	()V
    //   452: goto -9 -> 443
    //   455: astore 4
    //   457: aload 4
    //   459: invokevirtual 114	java/lang/Throwable:printStackTrace	()V
    //   462: iload_2
    //   463: istore_3
    //   464: goto -271 -> 193
    //   467: astore 5
    //   469: aload 6
    //   471: astore_0
    //   472: aload_0
    //   473: astore 4
    //   475: aload 5
    //   477: invokevirtual 114	java/lang/Throwable:printStackTrace	()V
    //   480: aload_0
    //   481: ifnull -118 -> 363
    //   484: aload_0
    //   485: invokevirtual 111	java/io/FileOutputStream:close	()V
    //   488: goto -125 -> 363
    //   491: astore_0
    //   492: aload_0
    //   493: invokevirtual 114	java/lang/Throwable:printStackTrace	()V
    //   496: goto -133 -> 363
    //   499: astore_0
    //   500: aload_0
    //   501: invokevirtual 114	java/lang/Throwable:printStackTrace	()V
    //   504: goto -141 -> 363
    //   507: astore_0
    //   508: aload 4
    //   510: ifnull +8 -> 518
    //   513: aload 4
    //   515: invokevirtual 111	java/io/FileOutputStream:close	()V
    //   518: aload_0
    //   519: athrow
    //   520: astore 4
    //   522: aload 4
    //   524: invokevirtual 114	java/lang/Throwable:printStackTrace	()V
    //   527: goto -9 -> 518
    //   530: astore_0
    //   531: aload_0
    //   532: invokevirtual 114	java/lang/Throwable:printStackTrace	()V
    //   535: goto -172 -> 363
    //   538: astore 5
    //   540: aload_0
    //   541: astore 4
    //   543: aload 5
    //   545: astore_0
    //   546: goto -38 -> 508
    //   549: astore 5
    //   551: goto -79 -> 472
    //   554: astore_0
    //   555: goto -122 -> 433
    //   558: astore_0
    //   559: goto -126 -> 433
    //   562: astore 5
    //   564: aconst_null
    //   565: astore 4
    //   567: iconst_0
    //   568: istore_2
    //   569: goto -175 -> 394
    //   572: astore 5
    //   574: goto -180 -> 394
    //   577: iconst_0
    //   578: istore_2
    //   579: goto -408 -> 171
    //   582: iconst_0
    //   583: istore_2
    //   584: goto -403 -> 181
    // Local variable table:
    //   start	length	slot	name	signature
    //   0	587	0	paramContext	Context
    //   136	238	1	i	int
    //   10	574	2	bool1	boolean
    //   166	298	3	bool2	boolean
    //   40	367	4	localObject1	Object
    //   416	3	4	localThrowable1	Throwable
    //   431	8	4	localThrowable2	Throwable
    //   445	3	4	localThrowable3	Throwable
    //   455	3	4	localThrowable4	Throwable
    //   473	41	4	localContext1	Context
    //   520	3	4	localThrowable5	Throwable
    //   541	25	4	localContext2	Context
    //   7	170	5	localInputStream	java.io.InputStream
    //   390	40	5	localThrowable6	Throwable
    //   467	9	5	localThrowable7	Throwable
    //   538	6	5	localObject2	Object
    //   549	1	5	localThrowable8	Throwable
    //   562	1	5	localThrowable9	Throwable
    //   572	1	5	localThrowable10	Throwable
    //   1	469	6	localObject3	Object
    //   4	280	7	localObject4	Object
    //   127	242	8	localByteArrayOutputStream	java.io.ByteArrayOutputStream
    //   118	253	9	arrayOfByte	byte[]
    //   380	3	9	localThrowable11	Throwable
    // Exception table:
    //   from	to	target	type
    //   129	137	380	java/lang/Throwable
    //   368	377	380	java/lang/Throwable
    //   42	129	390	java/lang/Throwable
    //   142	167	390	java/lang/Throwable
    //   382	387	390	java/lang/Throwable
    //   406	411	416	java/lang/Throwable
    //   22	42	428	finally
    //   438	443	445	java/lang/Throwable
    //   186	191	455	java/lang/Throwable
    //   197	203	467	java/lang/Throwable
    //   207	211	467	java/lang/Throwable
    //   215	254	467	java/lang/Throwable
    //   258	265	467	java/lang/Throwable
    //   269	274	467	java/lang/Throwable
    //   278	283	467	java/lang/Throwable
    //   287	297	467	java/lang/Throwable
    //   484	488	491	java/lang/Throwable
    //   492	496	499	java/lang/Throwable
    //   518	520	499	java/lang/Throwable
    //   522	527	499	java/lang/Throwable
    //   531	535	499	java/lang/Throwable
    //   197	203	507	finally
    //   207	211	507	finally
    //   215	254	507	finally
    //   258	265	507	finally
    //   269	274	507	finally
    //   278	283	507	finally
    //   287	297	507	finally
    //   475	480	507	finally
    //   513	518	520	java/lang/Throwable
    //   359	363	530	java/lang/Throwable
    //   297	359	538	finally
    //   297	359	549	java/lang/Throwable
    //   42	129	554	finally
    //   129	137	554	finally
    //   142	167	554	finally
    //   171	181	554	finally
    //   368	377	554	finally
    //   382	387	554	finally
    //   394	399	558	finally
    //   22	42	562	java/lang/Throwable
    //   171	181	572	java/lang/Throwable
  }
}

/* Location:
 * Qualified Name:     cn.com.xy.sms.sdk.net.util.b
 * Java Class Version: 6 (50.0)
 * JD-Core Version:    0.7.1
 */