package cn.com.xy.sms.sdk.action;

import java.util.concurrent.Callable;

final class b
  implements Callable<String>
{
  b(String paramString) {}
  
  /* Error */
  private String a()
  {
    // Byte code:
    //   0: aconst_null
    //   1: astore 4
    //   3: new 24	java/net/URL
    //   6: dup
    //   7: aload_0
    //   8: getfield 13	cn/com/xy/sms/sdk/action/b:a	Ljava/lang/String;
    //   11: invokespecial 26	java/net/URL:<init>	(Ljava/lang/String;)V
    //   14: invokevirtual 30	java/net/URL:openConnection	()Ljava/net/URLConnection;
    //   17: checkcast 32	java/net/HttpURLConnection
    //   20: astore_1
    //   21: aload_1
    //   22: ldc 34
    //   24: ldc 36
    //   26: invokevirtual 40	java/net/HttpURLConnection:setRequestProperty	(Ljava/lang/String;Ljava/lang/String;)V
    //   29: aload_1
    //   30: ldc 42
    //   32: ldc 44
    //   34: invokevirtual 40	java/net/HttpURLConnection:setRequestProperty	(Ljava/lang/String;Ljava/lang/String;)V
    //   37: aload_1
    //   38: ldc 46
    //   40: ldc 48
    //   42: invokevirtual 40	java/net/HttpURLConnection:setRequestProperty	(Ljava/lang/String;Ljava/lang/String;)V
    //   45: aload_1
    //   46: ldc 50
    //   48: invokevirtual 53	java/net/HttpURLConnection:setRequestMethod	(Ljava/lang/String;)V
    //   51: aload_1
    //   52: sipush 5000
    //   55: invokevirtual 57	java/net/HttpURLConnection:setConnectTimeout	(I)V
    //   58: aload_1
    //   59: sipush 5000
    //   62: invokevirtual 60	java/net/HttpURLConnection:setReadTimeout	(I)V
    //   65: aload_1
    //   66: iconst_1
    //   67: invokevirtual 64	java/net/HttpURLConnection:setDoOutput	(Z)V
    //   70: aload_1
    //   71: iconst_1
    //   72: invokevirtual 67	java/net/HttpURLConnection:setDoInput	(Z)V
    //   75: new 69	java/io/PrintWriter
    //   78: dup
    //   79: aload_1
    //   80: invokevirtual 73	java/net/HttpURLConnection:getOutputStream	()Ljava/io/OutputStream;
    //   83: invokespecial 76	java/io/PrintWriter:<init>	(Ljava/io/OutputStream;)V
    //   86: astore_2
    //   87: aload_2
    //   88: invokevirtual 79	java/io/PrintWriter:flush	()V
    //   91: new 81	java/io/BufferedReader
    //   94: dup
    //   95: new 83	java/io/InputStreamReader
    //   98: dup
    //   99: aload_1
    //   100: invokevirtual 87	java/net/HttpURLConnection:getInputStream	()Ljava/io/InputStream;
    //   103: invokespecial 90	java/io/InputStreamReader:<init>	(Ljava/io/InputStream;)V
    //   106: invokespecial 93	java/io/BufferedReader:<init>	(Ljava/io/Reader;)V
    //   109: astore_1
    //   110: aload_1
    //   111: astore 4
    //   113: aload_2
    //   114: astore_3
    //   115: new 95	java/lang/StringBuffer
    //   118: dup
    //   119: invokespecial 96	java/lang/StringBuffer:<init>	()V
    //   122: astore 5
    //   124: aload_1
    //   125: astore 4
    //   127: aload_2
    //   128: astore_3
    //   129: aload_1
    //   130: invokevirtual 99	java/io/BufferedReader:readLine	()Ljava/lang/String;
    //   133: astore 6
    //   135: aload 6
    //   137: ifnonnull +26 -> 163
    //   140: aload_1
    //   141: astore 4
    //   143: aload_2
    //   144: astore_3
    //   145: aload 5
    //   147: invokevirtual 102	java/lang/StringBuffer:toString	()Ljava/lang/String;
    //   150: astore 5
    //   152: aload_2
    //   153: invokevirtual 105	java/io/PrintWriter:close	()V
    //   156: aload_1
    //   157: invokevirtual 106	java/io/BufferedReader:close	()V
    //   160: aload 5
    //   162: areturn
    //   163: aload_1
    //   164: astore 4
    //   166: aload_2
    //   167: astore_3
    //   168: aload 5
    //   170: aload 6
    //   172: invokevirtual 110	java/lang/StringBuffer:append	(Ljava/lang/String;)Ljava/lang/StringBuffer;
    //   175: pop
    //   176: goto -52 -> 124
    //   179: astore 5
    //   181: aload_1
    //   182: astore 4
    //   184: aload_2
    //   185: astore_3
    //   186: aload 5
    //   188: invokevirtual 113	java/lang/Throwable:printStackTrace	()V
    //   191: aload_2
    //   192: ifnull +7 -> 199
    //   195: aload_2
    //   196: invokevirtual 105	java/io/PrintWriter:close	()V
    //   199: aload_1
    //   200: ifnull +7 -> 207
    //   203: aload_1
    //   204: invokevirtual 106	java/io/BufferedReader:close	()V
    //   207: aconst_null
    //   208: areturn
    //   209: astore_1
    //   210: aload_1
    //   211: invokevirtual 114	java/io/IOException:printStackTrace	()V
    //   214: aload 5
    //   216: areturn
    //   217: astore_1
    //   218: aload_1
    //   219: invokevirtual 114	java/io/IOException:printStackTrace	()V
    //   222: goto -15 -> 207
    //   225: astore_1
    //   226: aconst_null
    //   227: astore_2
    //   228: aload_2
    //   229: ifnull +7 -> 236
    //   232: aload_2
    //   233: invokevirtual 105	java/io/PrintWriter:close	()V
    //   236: aload 4
    //   238: ifnull +8 -> 246
    //   241: aload 4
    //   243: invokevirtual 106	java/io/BufferedReader:close	()V
    //   246: aload_1
    //   247: athrow
    //   248: astore_2
    //   249: aload_2
    //   250: invokevirtual 114	java/io/IOException:printStackTrace	()V
    //   253: goto -7 -> 246
    //   256: astore_1
    //   257: goto -29 -> 228
    //   260: astore_1
    //   261: aload_3
    //   262: astore_2
    //   263: goto -35 -> 228
    //   266: astore 5
    //   268: aconst_null
    //   269: astore_1
    //   270: aconst_null
    //   271: astore_2
    //   272: goto -91 -> 181
    //   275: astore 5
    //   277: aconst_null
    //   278: astore_1
    //   279: goto -98 -> 181
    // Local variable table:
    //   start	length	slot	name	signature
    //   0	282	0	this	b
    //   20	184	1	localObject1	Object
    //   209	2	1	localIOException1	java.io.IOException
    //   217	2	1	localIOException2	java.io.IOException
    //   225	22	1	localObject2	Object
    //   256	1	1	localObject3	Object
    //   260	1	1	localObject4	Object
    //   269	10	1	localObject5	Object
    //   86	147	2	localPrintWriter1	java.io.PrintWriter
    //   248	2	2	localIOException3	java.io.IOException
    //   262	10	2	localObject6	Object
    //   114	148	3	localPrintWriter2	java.io.PrintWriter
    //   1	241	4	localObject7	Object
    //   122	47	5	localObject8	Object
    //   179	36	5	localThrowable1	Throwable
    //   266	1	5	localThrowable2	Throwable
    //   275	1	5	localThrowable3	Throwable
    //   133	38	6	str	String
    // Exception table:
    //   from	to	target	type
    //   115	124	179	java/lang/Throwable
    //   129	135	179	java/lang/Throwable
    //   145	152	179	java/lang/Throwable
    //   168	176	179	java/lang/Throwable
    //   156	160	209	java/io/IOException
    //   203	207	217	java/io/IOException
    //   3	87	225	finally
    //   241	246	248	java/io/IOException
    //   87	110	256	finally
    //   115	124	260	finally
    //   129	135	260	finally
    //   145	152	260	finally
    //   168	176	260	finally
    //   186	191	260	finally
    //   3	87	266	java/lang/Throwable
    //   87	110	275	java/lang/Throwable
  }
}

/* Location:
 * Qualified Name:     cn.com.xy.sms.sdk.action.b
 * Java Class Version: 6 (50.0)
 * JD-Core Version:    0.7.1
 */