import android.content.Context;
import android.text.TextUtils;

public class amf
{
  private amn a;
  private amm b;
  private alw c;
  private String d;
  private boolean e;
  private amo f;
  
  public amf(Context paramContext, String paramString, alw paramalw, amn paramamn)
  {
    if ((TextUtils.isEmpty(paramString)) || (paramalw == null) || (paramamn == null)) {
      throw new IllegalArgumentException("Params cant be null!");
    }
    d = paramString;
    c = paramalw;
    e = false;
    a = paramamn;
    f = new amo(paramContext);
  }
  
  private void a(String paramString)
  {
    anf.d(paramString);
  }
  
  private void b()
  {
    if (e) {
      throw new alt();
    }
  }
  
  private void b(String paramString)
  {
    anf.c(paramString);
  }
  
  public void a()
  {
    e = true;
    c.a();
  }
  
  public void a(amm paramamm)
  {
    b = paramamm;
    c.a(paramamm);
  }
  
  /* Error */
  public boolean a(Context paramContext)
  {
    // Byte code:
    //   0: aload_0
    //   1: getfield 42	amf:a	Lamn;
    //   4: astore 14
    //   6: aload_0
    //   7: getfield 36	amf:d	Ljava/lang/String;
    //   10: astore 10
    //   12: iconst_0
    //   13: istore 4
    //   15: iconst_0
    //   16: istore 5
    //   18: aconst_null
    //   19: astore 12
    //   21: iload 5
    //   23: istore_3
    //   24: aload 10
    //   26: astore 9
    //   28: iload 4
    //   30: istore_2
    //   31: aload_0
    //   32: getfield 66	amf:b	Lamm;
    //   35: ifnull +24 -> 59
    //   38: aload_0
    //   39: getfield 66	amf:b	Lamm;
    //   42: invokeinterface 84 1 0
    //   47: astore 12
    //   49: iload 4
    //   51: istore_2
    //   52: aload 10
    //   54: astore 9
    //   56: iload 5
    //   58: istore_3
    //   59: iload_3
    //   60: istore 4
    //   62: aload_0
    //   63: invokespecial 86	amf:b	()V
    //   66: aload 14
    //   68: ifnull +13 -> 81
    //   71: iload_3
    //   72: istore 4
    //   74: aload 14
    //   76: invokeinterface 89 1 0
    //   81: iconst_0
    //   82: istore 7
    //   84: iload_3
    //   85: istore 4
    //   87: aload_0
    //   88: getfield 38	amf:c	Lalw;
    //   91: aload 9
    //   93: invokeinterface 91 2 0
    //   98: iload_3
    //   99: istore 4
    //   101: aload_0
    //   102: getfield 38	amf:c	Lalw;
    //   105: iconst_1
    //   106: invokeinterface 94 2 0
    //   111: istore 8
    //   113: iload 8
    //   115: ifne +71 -> 186
    //   118: iconst_1
    //   119: istore 6
    //   121: iconst_1
    //   122: istore 4
    //   124: aload 9
    //   126: astore 11
    //   128: aload_0
    //   129: getfield 49	amf:f	Lamo;
    //   132: aload_1
    //   133: invokevirtual 99	android/content/Context:getPackageName	()Ljava/lang/String;
    //   136: aload_0
    //   137: getfield 36	amf:d	Ljava/lang/String;
    //   140: ldc 100
    //   142: aload 9
    //   144: ldc 102
    //   146: aload 12
    //   148: invokevirtual 105	amo:b	(Ljava/lang/String;Ljava/lang/String;ILjava/lang/String;Ljava/lang/String;Ljava/lang/String;)V
    //   151: iconst_1
    //   152: istore 4
    //   154: iload 4
    //   156: istore_3
    //   157: iload_2
    //   158: istore 5
    //   160: iconst_0
    //   161: istore 6
    //   163: aconst_null
    //   164: astore 10
    //   166: iload 7
    //   168: istore 4
    //   170: iload_3
    //   171: istore_2
    //   172: iload 5
    //   174: istore_3
    //   175: iload 6
    //   177: istore 5
    //   179: iload 8
    //   181: ifeq +890 -> 1071
    //   184: iconst_1
    //   185: ireturn
    //   186: iload_2
    //   187: ifne +10 -> 197
    //   190: iload_3
    //   191: istore 4
    //   193: iload_3
    //   194: ifeq -40 -> 154
    //   197: iload_3
    //   198: istore 4
    //   200: aload_0
    //   201: getfield 49	amf:f	Lamo;
    //   204: aload_1
    //   205: invokevirtual 99	android/content/Context:getPackageName	()Ljava/lang/String;
    //   208: aload_0
    //   209: getfield 36	amf:d	Ljava/lang/String;
    //   212: aload 9
    //   214: ldc 107
    //   216: aload 12
    //   218: invokevirtual 110	amo:a	(Ljava/lang/String;Ljava/lang/String;Ljava/lang/String;Ljava/lang/String;Ljava/lang/String;)V
    //   221: iload_3
    //   222: istore 4
    //   224: goto -70 -> 154
    //   227: astore 10
    //   229: aload_0
    //   230: getfield 49	amf:f	Lamo;
    //   233: aload_1
    //   234: invokevirtual 99	android/content/Context:getPackageName	()Ljava/lang/String;
    //   237: aload_0
    //   238: getfield 36	amf:d	Ljava/lang/String;
    //   241: ldc 100
    //   243: aload 9
    //   245: aload 10
    //   247: invokevirtual 113	aly:getMessage	()Ljava/lang/String;
    //   250: aload 12
    //   252: invokevirtual 105	amo:b	(Ljava/lang/String;Ljava/lang/String;ILjava/lang/String;Ljava/lang/String;Ljava/lang/String;)V
    //   255: iconst_0
    //   256: istore 5
    //   258: aconst_null
    //   259: astore 10
    //   261: iconst_1
    //   262: istore 4
    //   264: iload_2
    //   265: istore_3
    //   266: iload 4
    //   268: istore_2
    //   269: iload 7
    //   271: istore 4
    //   273: goto -94 -> 179
    //   276: astore 10
    //   278: iconst_0
    //   279: istore 8
    //   281: iload_3
    //   282: istore 4
    //   284: aload 10
    //   286: invokevirtual 116	alx:a	()I
    //   289: istore 5
    //   291: iload_3
    //   292: istore 4
    //   294: aload_0
    //   295: new 118	java/lang/StringBuilder
    //   298: dup
    //   299: invokespecial 119	java/lang/StringBuilder:<init>	()V
    //   302: ldc 121
    //   304: invokevirtual 125	java/lang/StringBuilder:append	(Ljava/lang/String;)Ljava/lang/StringBuilder;
    //   307: iload 5
    //   309: invokevirtual 128	java/lang/StringBuilder:append	(I)Ljava/lang/StringBuilder;
    //   312: invokevirtual 131	java/lang/StringBuilder:toString	()Ljava/lang/String;
    //   315: invokespecial 132	amf:a	(Ljava/lang/String;)V
    //   318: aload 9
    //   320: astore 11
    //   322: aload_0
    //   323: getfield 49	amf:f	Lamo;
    //   326: aload_1
    //   327: invokevirtual 99	android/content/Context:getPackageName	()Ljava/lang/String;
    //   330: aload_0
    //   331: getfield 36	amf:d	Ljava/lang/String;
    //   334: iload 5
    //   336: aload 9
    //   338: ldc -122
    //   340: aload 12
    //   342: invokevirtual 105	amo:b	(Ljava/lang/String;Ljava/lang/String;ILjava/lang/String;Ljava/lang/String;Ljava/lang/String;)V
    //   345: aload 9
    //   347: astore 11
    //   349: iload_2
    //   350: ifeq +167 -> 517
    //   353: aload 9
    //   355: astore 11
    //   357: iload 5
    //   359: sipush 401
    //   362: if_icmpne +155 -> 517
    //   365: aload 9
    //   367: astore 11
    //   369: aload_0
    //   370: new 118	java/lang/StringBuilder
    //   373: dup
    //   374: invokespecial 119	java/lang/StringBuilder:<init>	()V
    //   377: ldc -120
    //   379: invokevirtual 125	java/lang/StringBuilder:append	(Ljava/lang/String;)Ljava/lang/StringBuilder;
    //   382: iload 5
    //   384: invokevirtual 128	java/lang/StringBuilder:append	(I)Ljava/lang/StringBuilder;
    //   387: invokevirtual 131	java/lang/StringBuilder:toString	()Ljava/lang/String;
    //   390: invokespecial 132	amf:a	(Ljava/lang/String;)V
    //   393: aload 9
    //   395: astore 11
    //   397: aload_0
    //   398: getfield 42	amf:a	Lamn;
    //   401: invokeinterface 138 1 0
    //   406: aload 9
    //   408: astore 11
    //   410: aload_0
    //   411: invokespecial 86	amf:b	()V
    //   414: aload 9
    //   416: astore 11
    //   418: aload 14
    //   420: aload_1
    //   421: aload_0
    //   422: getfield 36	amf:d	Ljava/lang/String;
    //   425: invokeinterface 141 3 0
    //   430: astore 13
    //   432: aload 9
    //   434: astore 11
    //   436: aload_0
    //   437: invokespecial 86	amf:b	()V
    //   440: aload 9
    //   442: astore 11
    //   444: aload 13
    //   446: ifnull +71 -> 517
    //   449: aload 9
    //   451: astore 11
    //   453: aload 13
    //   455: aload_0
    //   456: getfield 66	amf:b	Lamm;
    //   459: invokevirtual 144	ami:a	(Lamm;)V
    //   462: aload 9
    //   464: astore 11
    //   466: aload 13
    //   468: getfield 146	ami:a	Ljava/lang/String;
    //   471: astore 9
    //   473: aload 9
    //   475: astore 11
    //   477: aload 13
    //   479: getfield 149	ami:b	Ljava/util/List;
    //   482: ifnull +21 -> 503
    //   485: aload 9
    //   487: astore 11
    //   489: aload_0
    //   490: getfield 38	amf:c	Lalw;
    //   493: aload 13
    //   495: getfield 149	ami:b	Ljava/util/List;
    //   498: invokeinterface 152 2 0
    //   503: aload 9
    //   505: astore 11
    //   507: aload_0
    //   508: ldc -102
    //   510: invokespecial 132	amf:a	(Ljava/lang/String;)V
    //   513: aload 9
    //   515: astore 11
    //   517: iconst_0
    //   518: istore 5
    //   520: iconst_1
    //   521: istore 4
    //   523: iload_2
    //   524: istore_3
    //   525: aload 11
    //   527: astore 9
    //   529: iload 4
    //   531: istore_2
    //   532: iload 7
    //   534: istore 4
    //   536: goto -357 -> 179
    //   539: astore 10
    //   541: iconst_0
    //   542: istore 8
    //   544: iload_3
    //   545: istore 4
    //   547: aload 9
    //   549: astore 11
    //   551: iload 4
    //   553: istore 6
    //   555: aload 10
    //   557: invokevirtual 155	ame:getMessage	()Ljava/lang/String;
    //   560: astore 13
    //   562: aload 9
    //   564: astore 11
    //   566: iload 4
    //   568: istore 6
    //   570: aload_0
    //   571: new 118	java/lang/StringBuilder
    //   574: dup
    //   575: invokespecial 119	java/lang/StringBuilder:<init>	()V
    //   578: ldc -99
    //   580: invokevirtual 125	java/lang/StringBuilder:append	(Ljava/lang/String;)Ljava/lang/StringBuilder;
    //   583: aload 13
    //   585: invokevirtual 125	java/lang/StringBuilder:append	(Ljava/lang/String;)Ljava/lang/StringBuilder;
    //   588: invokevirtual 131	java/lang/StringBuilder:toString	()Ljava/lang/String;
    //   591: invokespecial 132	amf:a	(Ljava/lang/String;)V
    //   594: aload 13
    //   596: astore 10
    //   598: aload 14
    //   600: ifnull +95 -> 695
    //   603: aload 13
    //   605: astore 10
    //   607: iload_2
    //   608: ifeq +87 -> 695
    //   611: aload 13
    //   613: astore 9
    //   615: aload 14
    //   617: aload_1
    //   618: aload 13
    //   620: invokeinterface 159 3 0
    //   625: astore 15
    //   627: aload 13
    //   629: astore 10
    //   631: aload 15
    //   633: ifnull +62 -> 695
    //   636: aload 13
    //   638: astore 9
    //   640: aload_0
    //   641: ldc -95
    //   643: invokespecial 132	amf:a	(Ljava/lang/String;)V
    //   646: aload 13
    //   648: astore 9
    //   650: aload 15
    //   652: getfield 146	ami:a	Ljava/lang/String;
    //   655: astore 11
    //   657: aload 11
    //   659: astore 10
    //   661: aload 11
    //   663: astore 9
    //   665: aload 15
    //   667: getfield 149	ami:b	Ljava/util/List;
    //   670: ifnull +25 -> 695
    //   673: aload 11
    //   675: astore 9
    //   677: aload_0
    //   678: getfield 38	amf:c	Lalw;
    //   681: aload 15
    //   683: getfield 149	ami:b	Ljava/util/List;
    //   686: invokeinterface 152 2 0
    //   691: aload 11
    //   693: astore 10
    //   695: aload 10
    //   697: astore 9
    //   699: iconst_1
    //   700: istore 5
    //   702: aconst_null
    //   703: astore 10
    //   705: iload_2
    //   706: istore_3
    //   707: iload 4
    //   709: istore_2
    //   710: iload 7
    //   712: istore 4
    //   714: goto -535 -> 179
    //   717: astore 10
    //   719: iconst_0
    //   720: istore 8
    //   722: iconst_1
    //   723: istore_3
    //   724: iconst_1
    //   725: istore 4
    //   727: iconst_1
    //   728: istore 7
    //   730: aload 9
    //   732: astore 11
    //   734: iload_3
    //   735: istore 6
    //   737: aload_0
    //   738: getfield 49	amf:f	Lamo;
    //   741: aload_1
    //   742: invokevirtual 99	android/content/Context:getPackageName	()Ljava/lang/String;
    //   745: aload_0
    //   746: getfield 36	amf:d	Ljava/lang/String;
    //   749: aload 10
    //   751: invokevirtual 162	alv:a	()I
    //   754: aload 9
    //   756: aload 10
    //   758: invokevirtual 163	alv:getMessage	()Ljava/lang/String;
    //   761: aload 12
    //   763: invokevirtual 165	amo:a	(Ljava/lang/String;Ljava/lang/String;ILjava/lang/String;Ljava/lang/String;Ljava/lang/String;)V
    //   766: aload 9
    //   768: astore 11
    //   770: iload_3
    //   771: istore 6
    //   773: aload_0
    //   774: ldc -89
    //   776: invokespecial 132	amf:a	(Ljava/lang/String;)V
    //   779: aload 14
    //   781: ifnull +218 -> 999
    //   784: aload 9
    //   786: astore 11
    //   788: iload_3
    //   789: istore 6
    //   791: aload 14
    //   793: invokeinterface 169 1 0
    //   798: astore 10
    //   800: aload 9
    //   802: astore 11
    //   804: iload_3
    //   805: istore 6
    //   807: aload 10
    //   809: invokestatic 27	android/text/TextUtils:isEmpty	(Ljava/lang/CharSequence;)Z
    //   812: ifne +18 -> 830
    //   815: iconst_1
    //   816: istore 4
    //   818: aload 10
    //   820: astore 9
    //   822: iload_2
    //   823: istore_3
    //   824: iload 4
    //   826: istore_2
    //   827: goto +727 -> 1554
    //   830: aload 9
    //   832: astore 11
    //   834: iload_3
    //   835: istore 6
    //   837: aload_0
    //   838: invokespecial 86	amf:b	()V
    //   841: aload 9
    //   843: astore 11
    //   845: iload_3
    //   846: istore 6
    //   848: aload 14
    //   850: aload_1
    //   851: aload_0
    //   852: getfield 36	amf:d	Ljava/lang/String;
    //   855: invokeinterface 141 3 0
    //   860: astore 10
    //   862: aload 9
    //   864: astore 11
    //   866: iload_3
    //   867: istore 6
    //   869: aload_0
    //   870: invokespecial 86	amf:b	()V
    //   873: aload 10
    //   875: ifnull +91 -> 966
    //   878: aload 9
    //   880: astore 11
    //   882: iload_3
    //   883: istore 6
    //   885: aload 10
    //   887: aload_0
    //   888: getfield 66	amf:b	Lamm;
    //   891: invokevirtual 144	ami:a	(Lamm;)V
    //   894: aload 9
    //   896: astore 11
    //   898: iload_3
    //   899: istore 6
    //   901: aload 10
    //   903: getfield 146	ami:a	Ljava/lang/String;
    //   906: astore 9
    //   908: aload 10
    //   910: getfield 149	ami:b	Ljava/util/List;
    //   913: ifnull +17 -> 930
    //   916: aload_0
    //   917: getfield 38	amf:c	Lalw;
    //   920: aload 10
    //   922: getfield 149	ami:b	Ljava/util/List;
    //   925: invokeinterface 152 2 0
    //   930: aload_0
    //   931: ldc -85
    //   933: invokespecial 132	amf:a	(Ljava/lang/String;)V
    //   936: aload_0
    //   937: getfield 66	amf:b	Lamm;
    //   940: ifnull +610 -> 1550
    //   943: aload_0
    //   944: ldc -83
    //   946: invokespecial 132	amf:a	(Ljava/lang/String;)V
    //   949: aload_0
    //   950: getfield 66	amf:b	Lamm;
    //   953: iconst_0
    //   954: invokeinterface 176 2 0
    //   959: iconst_1
    //   960: istore_3
    //   961: iconst_0
    //   962: istore_2
    //   963: goto +591 -> 1554
    //   966: aload 9
    //   968: astore 11
    //   970: iload_3
    //   971: istore 6
    //   973: aload_0
    //   974: getfield 49	amf:f	Lamo;
    //   977: aload_1
    //   978: invokevirtual 99	android/content/Context:getPackageName	()Ljava/lang/String;
    //   981: aload_0
    //   982: getfield 36	amf:d	Ljava/lang/String;
    //   985: ldc -79
    //   987: aload 9
    //   989: ldc -77
    //   991: aload 12
    //   993: invokevirtual 105	amo:b	(Ljava/lang/String;Ljava/lang/String;ILjava/lang/String;Ljava/lang/String;Ljava/lang/String;)V
    //   996: goto +573 -> 1569
    //   999: aload 9
    //   1001: astore 11
    //   1003: iload_3
    //   1004: istore 6
    //   1006: aload_0
    //   1007: getfield 49	amf:f	Lamo;
    //   1010: aload_1
    //   1011: invokevirtual 99	android/content/Context:getPackageName	()Ljava/lang/String;
    //   1014: aload_0
    //   1015: getfield 36	amf:d	Ljava/lang/String;
    //   1018: ldc -79
    //   1020: aload 9
    //   1022: ldc -77
    //   1024: aload 12
    //   1026: invokevirtual 105	amo:b	(Ljava/lang/String;Ljava/lang/String;ILjava/lang/String;Ljava/lang/String;Ljava/lang/String;)V
    //   1029: goto +540 -> 1569
    //   1032: astore 10
    //   1034: iload 6
    //   1036: istore 4
    //   1038: aload 11
    //   1040: astore 9
    //   1042: iload 4
    //   1044: ifeq +24 -> 1068
    //   1047: aload_0
    //   1048: getfield 49	amf:f	Lamo;
    //   1051: aload_1
    //   1052: invokevirtual 99	android/content/Context:getPackageName	()Ljava/lang/String;
    //   1055: aload_0
    //   1056: getfield 36	amf:d	Ljava/lang/String;
    //   1059: aload 9
    //   1061: ldc -75
    //   1063: aload 12
    //   1065: invokevirtual 183	amo:b	(Ljava/lang/String;Ljava/lang/String;Ljava/lang/String;Ljava/lang/String;Ljava/lang/String;)V
    //   1068: aload 10
    //   1070: athrow
    //   1071: aload 14
    //   1073: ifnull +379 -> 1452
    //   1076: aload 9
    //   1078: astore 11
    //   1080: iload_2
    //   1081: istore 6
    //   1083: aload 14
    //   1085: invokeinterface 186 1 0
    //   1090: ifne +61 -> 1151
    //   1093: aload 9
    //   1095: astore 11
    //   1097: iload_2
    //   1098: istore 6
    //   1100: aload_0
    //   1101: getfield 49	amf:f	Lamo;
    //   1104: aload_1
    //   1105: invokevirtual 99	android/content/Context:getPackageName	()Ljava/lang/String;
    //   1108: aload_0
    //   1109: getfield 36	amf:d	Ljava/lang/String;
    //   1112: ldc 100
    //   1114: aload 9
    //   1116: ldc -68
    //   1118: aload 12
    //   1120: invokevirtual 105	amo:b	(Ljava/lang/String;Ljava/lang/String;ILjava/lang/String;Ljava/lang/String;Ljava/lang/String;)V
    //   1123: aload 9
    //   1125: astore 11
    //   1127: iload_2
    //   1128: istore 6
    //   1130: aload_0
    //   1131: ldc -68
    //   1133: invokespecial 132	amf:a	(Ljava/lang/String;)V
    //   1136: aload 10
    //   1138: ifnull +431 -> 1569
    //   1141: aload 9
    //   1143: astore 11
    //   1145: iload_2
    //   1146: istore 6
    //   1148: aload 10
    //   1150: athrow
    //   1151: iload 5
    //   1153: ifne +282 -> 1435
    //   1156: aload 9
    //   1158: astore 10
    //   1160: iload 4
    //   1162: ifne +42 -> 1204
    //   1165: aload 9
    //   1167: astore 11
    //   1169: iload_2
    //   1170: istore 6
    //   1172: aload 14
    //   1174: invokeinterface 169 1 0
    //   1179: astore 13
    //   1181: aload 9
    //   1183: astore 11
    //   1185: iload_2
    //   1186: istore 6
    //   1188: aload 9
    //   1190: astore 10
    //   1192: aload 13
    //   1194: invokestatic 27	android/text/TextUtils:isEmpty	(Ljava/lang/CharSequence;)Z
    //   1197: ifne +7 -> 1204
    //   1200: aload 13
    //   1202: astore 10
    //   1204: aload 10
    //   1206: astore 11
    //   1208: iload_2
    //   1209: istore 6
    //   1211: aload_1
    //   1212: invokestatic 193	anl:i	(Landroid/content/Context;)Z
    //   1215: istore 8
    //   1217: iload 8
    //   1219: ifne +170 -> 1389
    //   1222: iconst_0
    //   1223: istore 8
    //   1225: iconst_0
    //   1226: istore 4
    //   1228: iload 4
    //   1230: bipush 10
    //   1232: if_icmpge +78 -> 1310
    //   1235: aload 10
    //   1237: astore 11
    //   1239: iload_2
    //   1240: istore 6
    //   1242: ldc2_w 194
    //   1245: invokestatic 201	java/lang/Thread:sleep	(J)V
    //   1248: aload 10
    //   1250: astore 11
    //   1252: iload_2
    //   1253: istore 6
    //   1255: aload_0
    //   1256: invokespecial 86	amf:b	()V
    //   1259: aload 10
    //   1261: astore 11
    //   1263: iload_2
    //   1264: istore 6
    //   1266: aload_1
    //   1267: invokestatic 193	anl:i	(Landroid/content/Context;)Z
    //   1270: istore 8
    //   1272: aload 10
    //   1274: astore 11
    //   1276: iload_2
    //   1277: istore 6
    //   1279: aload_0
    //   1280: new 118	java/lang/StringBuilder
    //   1283: dup
    //   1284: invokespecial 119	java/lang/StringBuilder:<init>	()V
    //   1287: ldc -53
    //   1289: invokevirtual 125	java/lang/StringBuilder:append	(Ljava/lang/String;)Ljava/lang/StringBuilder;
    //   1292: iload 4
    //   1294: iconst_1
    //   1295: iadd
    //   1296: invokevirtual 128	java/lang/StringBuilder:append	(I)Ljava/lang/StringBuilder;
    //   1299: invokevirtual 131	java/lang/StringBuilder:toString	()Ljava/lang/String;
    //   1302: invokespecial 205	amf:b	(Ljava/lang/String;)V
    //   1305: iload 8
    //   1307: ifeq +264 -> 1571
    //   1310: iload 8
    //   1312: ifne +49 -> 1361
    //   1315: aload 10
    //   1317: astore 11
    //   1319: iload_2
    //   1320: istore 6
    //   1322: aload_0
    //   1323: getfield 49	amf:f	Lamo;
    //   1326: aload_1
    //   1327: invokevirtual 99	android/content/Context:getPackageName	()Ljava/lang/String;
    //   1330: aload_0
    //   1331: getfield 36	amf:d	Ljava/lang/String;
    //   1334: ldc 100
    //   1336: aload 10
    //   1338: ldc -49
    //   1340: aload 12
    //   1342: invokevirtual 105	amo:b	(Ljava/lang/String;Ljava/lang/String;ILjava/lang/String;Ljava/lang/String;Ljava/lang/String;)V
    //   1345: aload 10
    //   1347: astore 11
    //   1349: iload_2
    //   1350: istore 6
    //   1352: aload_0
    //   1353: ldc -47
    //   1355: invokespecial 132	amf:a	(Ljava/lang/String;)V
    //   1358: goto +211 -> 1569
    //   1361: aload 10
    //   1363: astore 11
    //   1365: iload_2
    //   1366: istore 6
    //   1368: aload_0
    //   1369: ldc -45
    //   1371: invokespecial 205	amf:b	(Ljava/lang/String;)V
    //   1374: aload 10
    //   1376: astore 9
    //   1378: iload_3
    //   1379: istore 4
    //   1381: iload_2
    //   1382: istore_3
    //   1383: iload 4
    //   1385: istore_2
    //   1386: goto -1327 -> 59
    //   1389: iconst_0
    //   1390: istore 4
    //   1392: aload 10
    //   1394: astore 9
    //   1396: iload 4
    //   1398: iconst_3
    //   1399: if_icmpge -21 -> 1378
    //   1402: aload 10
    //   1404: astore 11
    //   1406: iload_2
    //   1407: istore 6
    //   1409: ldc2_w 194
    //   1412: invokestatic 201	java/lang/Thread:sleep	(J)V
    //   1415: aload 10
    //   1417: astore 11
    //   1419: iload_2
    //   1420: istore 6
    //   1422: aload_0
    //   1423: invokespecial 86	amf:b	()V
    //   1426: iload 4
    //   1428: iconst_1
    //   1429: iadd
    //   1430: istore 4
    //   1432: goto -40 -> 1392
    //   1435: aload 9
    //   1437: astore 11
    //   1439: iload_2
    //   1440: istore 6
    //   1442: aload 14
    //   1444: invokeinterface 213 1 0
    //   1449: goto -71 -> 1378
    //   1452: aload 10
    //   1454: ifnull +115 -> 1569
    //   1457: aload 9
    //   1459: astore 11
    //   1461: iload_2
    //   1462: istore 6
    //   1464: aload 10
    //   1466: athrow
    //   1467: astore 9
    //   1469: goto -221 -> 1248
    //   1472: astore 9
    //   1474: goto -59 -> 1415
    //   1477: astore 10
    //   1479: goto -437 -> 1042
    //   1482: astore 10
    //   1484: iconst_1
    //   1485: istore 4
    //   1487: goto -445 -> 1042
    //   1490: astore 10
    //   1492: iconst_1
    //   1493: istore 4
    //   1495: aload 11
    //   1497: astore 9
    //   1499: goto -457 -> 1042
    //   1502: astore 10
    //   1504: goto -462 -> 1042
    //   1507: astore 10
    //   1509: goto -467 -> 1042
    //   1512: astore 10
    //   1514: goto -792 -> 722
    //   1517: astore 10
    //   1519: goto -972 -> 547
    //   1522: astore 10
    //   1524: iload_3
    //   1525: istore 4
    //   1527: goto -980 -> 547
    //   1530: astore 10
    //   1532: iconst_1
    //   1533: istore_3
    //   1534: goto -1253 -> 281
    //   1537: astore 10
    //   1539: goto -1258 -> 281
    //   1542: astore 10
    //   1544: iconst_0
    //   1545: istore 8
    //   1547: goto -1318 -> 229
    //   1550: iconst_1
    //   1551: istore_3
    //   1552: iconst_0
    //   1553: istore_2
    //   1554: iload_2
    //   1555: istore 4
    //   1557: aconst_null
    //   1558: astore 10
    //   1560: iconst_0
    //   1561: istore 5
    //   1563: iload 7
    //   1565: istore_2
    //   1566: goto -1387 -> 179
    //   1569: iconst_0
    //   1570: ireturn
    //   1571: iload 4
    //   1573: iconst_1
    //   1574: iadd
    //   1575: istore 4
    //   1577: goto -349 -> 1228
    // Local variable table:
    //   start	length	slot	name	signature
    //   0	1580	0	this	amf
    //   0	1580	1	paramContext	Context
    //   30	1536	2	i	int
    //   23	1529	3	j	int
    //   13	1563	4	k	int
    //   16	1546	5	m	int
    //   119	1344	6	n	int
    //   82	1482	7	i1	int
    //   111	1435	8	bool	boolean
    //   26	1432	9	localObject1	Object
    //   1467	1	9	localInterruptedException1	InterruptedException
    //   1472	1	9	localInterruptedException2	InterruptedException
    //   1497	1	9	localObject2	Object
    //   10	155	10	str1	String
    //   227	19	10	localaly1	aly
    //   259	1	10	localObject3	Object
    //   276	9	10	localalx1	alx
    //   539	17	10	localame1	ame
    //   596	108	10	localObject4	Object
    //   717	40	10	localalv1	alv
    //   798	123	10	localObject5	Object
    //   1032	117	10	localalt1	alt
    //   1158	307	10	localObject6	Object
    //   1477	1	10	localalt2	alt
    //   1482	1	10	localalt3	alt
    //   1490	1	10	localalt4	alt
    //   1502	1	10	localalt5	alt
    //   1507	1	10	localalt6	alt
    //   1512	1	10	localalv2	alv
    //   1517	1	10	localame2	ame
    //   1522	1	10	localame3	ame
    //   1530	1	10	localalx2	alx
    //   1537	1	10	localalx3	alx
    //   1542	1	10	localaly2	aly
    //   1558	1	10	localObject7	Object
    //   126	1370	11	localObject8	Object
    //   19	1322	12	str2	String
    //   430	771	13	localObject9	Object
    //   4	1439	14	localamn	amn
    //   625	57	15	localami	ami
    // Exception table:
    //   from	to	target	type
    //   128	151	227	aly
    //   200	221	227	aly
    //   87	98	276	alx
    //   101	113	276	alx
    //   87	98	539	ame
    //   101	113	539	ame
    //   87	98	717	alv
    //   101	113	717	alv
    //   128	151	1032	alt
    //   555	562	1032	alt
    //   570	594	1032	alt
    //   737	766	1032	alt
    //   773	779	1032	alt
    //   791	800	1032	alt
    //   807	815	1032	alt
    //   837	841	1032	alt
    //   848	862	1032	alt
    //   869	873	1032	alt
    //   885	894	1032	alt
    //   901	908	1032	alt
    //   973	996	1032	alt
    //   1006	1029	1032	alt
    //   1083	1093	1032	alt
    //   1100	1123	1032	alt
    //   1130	1136	1032	alt
    //   1148	1151	1032	alt
    //   1172	1181	1032	alt
    //   1192	1200	1032	alt
    //   1211	1217	1032	alt
    //   1242	1248	1032	alt
    //   1255	1259	1032	alt
    //   1266	1272	1032	alt
    //   1279	1305	1032	alt
    //   1322	1345	1032	alt
    //   1352	1358	1032	alt
    //   1368	1374	1032	alt
    //   1409	1415	1032	alt
    //   1422	1426	1032	alt
    //   1442	1449	1032	alt
    //   1464	1467	1032	alt
    //   1242	1248	1467	java/lang/InterruptedException
    //   1409	1415	1472	java/lang/InterruptedException
    //   62	66	1477	alt
    //   74	81	1477	alt
    //   87	98	1477	alt
    //   101	113	1477	alt
    //   200	221	1477	alt
    //   284	291	1477	alt
    //   294	318	1477	alt
    //   229	255	1482	alt
    //   322	345	1490	alt
    //   369	393	1490	alt
    //   397	406	1490	alt
    //   410	414	1490	alt
    //   418	432	1490	alt
    //   436	440	1490	alt
    //   453	462	1490	alt
    //   466	473	1490	alt
    //   477	485	1490	alt
    //   489	503	1490	alt
    //   507	513	1490	alt
    //   615	627	1502	alt
    //   640	646	1502	alt
    //   650	657	1502	alt
    //   665	673	1502	alt
    //   677	691	1502	alt
    //   908	930	1507	alt
    //   930	959	1507	alt
    //   128	151	1512	alv
    //   200	221	1512	alv
    //   128	151	1517	ame
    //   200	221	1522	ame
    //   128	151	1530	alx
    //   200	221	1537	alx
    //   87	98	1542	aly
    //   101	113	1542	aly
  }
}

/* Location:
 * Qualified Name:     amf
 * Java Class Version: 6 (50.0)
 * JD-Core Version:    0.7.1
 */