final class bw
  implements Runnable
{
  /* Error */
  public final void run()
  {
    // Byte code:
    //   0: ldc2_w 15
    //   3: invokestatic 22	java/lang/Thread:sleep	(J)V
    //   6: ldc 24
    //   8: invokestatic 30	cn/com/xy/sms/sdk/db/entity/s:b	(Ljava/lang/String;)V
    //   11: getstatic 36	bx:a	Ljava/lang/Object;
    //   14: astore_1
    //   15: aload_1
    //   16: monitorenter
    //   17: iconst_0
    //   18: invokestatic 41	bs:a	(Z)V
    //   21: aload_1
    //   22: monitorexit
    //   23: return
    //   24: astore_1
    //   25: aload_1
    //   26: invokevirtual 44	java/lang/Exception:printStackTrace	()V
    //   29: goto -23 -> 6
    //   32: astore_2
    //   33: aload_1
    //   34: monitorexit
    //   35: aload_2
    //   36: athrow
    // Local variable table:
    //   start	length	slot	name	signature
    //   0	37	0	this	bw
    //   24	10	1	localException	Exception
    //   32	4	2	localObject2	Object
    // Exception table:
    //   from	to	target	type
    //   0	6	24	java/lang/Exception
    //   17	23	32	finally
  }
}

/* Location:
 * Qualified Name:     bw
 * Java Class Version: 6 (50.0)
 * JD-Core Version:    0.7.1
 */