import android.content.ContentResolver;
import android.content.ContentValues;
import android.content.Context;
import android.database.Cursor;
import android.net.Uri;
import android.provider.Telephony.Mms;
import android.text.TextUtils;
import android.util.Log;
import com.google.android.mms.MmsException;
import com.meizu.android.mms.pdu.MzEncodedStringValue;
import com.meizu.android.mms.pdu.MzPduPersister;
import com.meizu.android.mms.pdu.MzRetrieveConf;

public class pc
  extends ow
  implements Runnable
{
  static final String[] a = { "ct_l", "locked", "m_size" };
  private final String p;
  private boolean q;
  private long r;
  
  public pc(Context paramContext, int paramInt, oz paramoz, String paramString)
  {
    super(paramContext, paramInt, paramoz);
    h = 2;
    if (paramString.startsWith("content://"))
    {
      g = Uri.parse(paramString);
      paramContext = a(paramContext, g);
      p = paramContext;
      c = paramContext;
      Log.v("FlymeRetrieveTransaction", "X-Mms-Content-Location: " + p);
      l = a(g);
      b(g);
      return;
    }
    throw new IllegalArgumentException("Initializing from X-Mms-Content-Location is abandoned!");
  }
  
  private String a(Context paramContext, Uri paramUri)
  {
    paramContext = paramContext.getContentResolver().query(paramUri, a, null, null, null);
    q = false;
    if (paramContext != null) {}
    try
    {
      if ((paramContext.getCount() == 1) && (paramContext.moveToFirst()))
      {
        if (paramContext.getInt(1) == 1) {}
        for (boolean bool = true;; bool = false)
        {
          q = bool;
          r = paramContext.getInt(2);
          paramUri = paramContext.getString(0);
          return paramUri;
        }
      }
      throw new MmsException("Cannot get X-Mms-Content-Location from: " + paramUri);
    }
    finally
    {
      paramContext.close();
    }
  }
  
  private static void a(Context paramContext, Uri paramUri, String paramString, boolean paramBoolean)
  {
    ContentValues localContentValues = new ContentValues(2);
    localContentValues.put("ct_l", paramString);
    localContentValues.put("locked", Boolean.valueOf(paramBoolean));
    paramContext.getContentResolver().update(paramUri, localContentValues, null, null);
  }
  
  private static boolean a(Context paramContext, MzRetrieveConf paramMzRetrieveConf)
  {
    Object localObject = paramMzRetrieveConf.getMessageId();
    if (localObject != null)
    {
      localObject = new String((byte[])localObject);
      paramContext = paramContext.getContentResolver().query(Telephony.Mms.CONTENT_URI, new String[] { "_id", "sub", "sub_cs" }, "(m_id = ? AND m_type = ?)", new String[] { localObject, String.valueOf(132) }, null);
      if (paramContext == null) {}
    }
    try
    {
      if (paramContext.getCount() > 0)
      {
        boolean bool = a(paramContext, paramMzRetrieveConf);
        return bool;
      }
      return false;
    }
    finally
    {
      paramContext.close();
    }
  }
  
  private static boolean a(Cursor paramCursor, MzRetrieveConf paramMzRetrieveConf)
  {
    MzEncodedStringValue localMzEncodedStringValue1 = null;
    MzEncodedStringValue localMzEncodedStringValue2 = paramMzRetrieveConf.getSubject();
    if (localMzEncodedStringValue2 != null) {}
    for (paramMzRetrieveConf = localMzEncodedStringValue2.getString();; paramMzRetrieveConf = null)
    {
      paramCursor.moveToFirst();
      while (!paramCursor.isAfterLast())
      {
        int i = paramCursor.getColumnIndex("sub");
        int j = paramCursor.getColumnIndex("sub_cs");
        String str = paramCursor.getString(i);
        i = paramCursor.getInt(j);
        if (str != null) {
          localMzEncodedStringValue1 = new MzEncodedStringValue(i, MzPduPersister.getBytes(str));
        }
        if ((localMzEncodedStringValue1 == null) && (localMzEncodedStringValue2 == null)) {
          return true;
        }
        if ((localMzEncodedStringValue1 != null) && (localMzEncodedStringValue2 != null))
        {
          str = localMzEncodedStringValue1.getString();
          if ((!TextUtils.isEmpty(str)) && (!TextUtils.isEmpty(paramMzRetrieveConf))) {
            return str.equals(paramMzRetrieveConf);
          }
          if ((TextUtils.isEmpty(str)) && (TextUtils.isEmpty(paramMzRetrieveConf))) {
            return true;
          }
        }
        paramCursor.moveToNext();
      }
      return false;
    }
  }
  
  public void a()
  {
    new Thread(this, "FlymeRetrieveTransaction").start();
  }
  
  public int c()
  {
    return 1;
  }
  
  /* Error */
  public void run()
  {
    // Byte code:
    //   0: iconst_1
    //   1: istore_2
    //   2: lconst_0
    //   3: lstore_3
    //   4: ldc -11
    //   6: astore 10
    //   8: lload_3
    //   9: lstore 5
    //   11: lload_3
    //   12: lstore 7
    //   14: invokestatic 250	zn:a	()Lzn;
    //   17: aload_0
    //   18: getfield 52	pc:g	Landroid/net/Uri;
    //   21: sipush 129
    //   24: iconst_m1
    //   25: invokevirtual 253	zn:b	(Landroid/net/Uri;II)V
    //   28: lload_3
    //   29: lstore 5
    //   31: lload_3
    //   32: lstore 7
    //   34: ldc 62
    //   36: new 64	java/lang/StringBuilder
    //   39: dup
    //   40: invokespecial 66	java/lang/StringBuilder:<init>	()V
    //   43: ldc -1
    //   45: invokevirtual 72	java/lang/StringBuilder:append	(Ljava/lang/String;)Ljava/lang/StringBuilder;
    //   48: aload_0
    //   49: getfield 258	pc:m	I
    //   52: invokevirtual 261	java/lang/StringBuilder:append	(I)Ljava/lang/StringBuilder;
    //   55: ldc_w 263
    //   58: invokevirtual 72	java/lang/StringBuilder:append	(Ljava/lang/String;)Ljava/lang/StringBuilder;
    //   61: aload_0
    //   62: getfield 57	pc:p	Ljava/lang/String;
    //   65: invokevirtual 72	java/lang/StringBuilder:append	(Ljava/lang/String;)Ljava/lang/StringBuilder;
    //   68: ldc_w 265
    //   71: invokevirtual 72	java/lang/StringBuilder:append	(Ljava/lang/String;)Ljava/lang/StringBuilder;
    //   74: aload_0
    //   75: getfield 52	pc:g	Landroid/net/Uri;
    //   78: invokevirtual 143	java/lang/StringBuilder:append	(Ljava/lang/Object;)Ljava/lang/StringBuilder;
    //   81: invokevirtual 76	java/lang/StringBuilder:toString	()Ljava/lang/String;
    //   84: invokestatic 268	android/util/Log:d	(Ljava/lang/String;Ljava/lang/String;)I
    //   87: pop
    //   88: lload_3
    //   89: lstore 5
    //   91: lload_3
    //   92: lstore 7
    //   94: aload_0
    //   95: getfield 57	pc:p	Ljava/lang/String;
    //   98: ldc_w 270
    //   101: invokestatic 274	android/text/TextUtils:split	(Ljava/lang/String;Ljava/lang/String;)[Ljava/lang/String;
    //   104: astore 14
    //   106: lload_3
    //   107: lstore 5
    //   109: lload_3
    //   110: lstore 7
    //   112: aload 14
    //   114: arraylength
    //   115: iconst_1
    //   116: if_icmpge +18 -> 134
    //   119: lload_3
    //   120: lstore 5
    //   122: lload_3
    //   123: lstore 7
    //   125: ldc 62
    //   127: ldc_w 276
    //   130: invokestatic 279	android/util/Log:e	(Ljava/lang/String;Ljava/lang/String;)I
    //   133: pop
    //   134: lload_3
    //   135: lstore 5
    //   137: lload_3
    //   138: lstore 7
    //   140: aload_0
    //   141: getfield 282	pc:b	Landroid/content/Context;
    //   144: invokevirtual 105	android/content/Context:getContentResolver	()Landroid/content/ContentResolver;
    //   147: aload_0
    //   148: getfield 52	pc:g	Landroid/net/Uri;
    //   151: iconst_3
    //   152: anewarray 18	java/lang/String
    //   155: dup
    //   156: iconst_0
    //   157: ldc -72
    //   159: aastore
    //   160: dup
    //   161: iconst_1
    //   162: ldc_w 284
    //   165: aastore
    //   166: dup
    //   167: iconst_2
    //   168: ldc_w 286
    //   171: aastore
    //   172: aconst_null
    //   173: aconst_null
    //   174: aconst_null
    //   175: invokevirtual 111	android/content/ContentResolver:query	(Landroid/net/Uri;[Ljava/lang/String;Ljava/lang/String;[Ljava/lang/String;Ljava/lang/String;)Landroid/database/Cursor;
    //   178: astore 13
    //   180: aload 13
    //   182: ifnull +2127 -> 2309
    //   185: aload 13
    //   187: invokeinterface 119 1 0
    //   192: ifle +2106 -> 2298
    //   195: aload 13
    //   197: invokeinterface 123 1 0
    //   202: ifeq +2096 -> 2298
    //   205: aload 13
    //   207: aload 13
    //   209: ldc -72
    //   211: invokeinterface 289 2 0
    //   216: invokeinterface 293 2 0
    //   221: lstore_3
    //   222: aload 13
    //   224: aload 13
    //   226: ldc_w 284
    //   229: invokeinterface 289 2 0
    //   234: invokeinterface 133 2 0
    //   239: astore 11
    //   241: aload 13
    //   243: aload 13
    //   245: ldc_w 286
    //   248: invokeinterface 289 2 0
    //   253: invokeinterface 133 2 0
    //   258: astore 12
    //   260: lload_3
    //   261: lstore 5
    //   263: lload_3
    //   264: lstore 7
    //   266: aload 13
    //   268: invokeinterface 136 1 0
    //   273: aload 12
    //   275: astore 15
    //   277: aload 11
    //   279: astore 13
    //   281: aload 10
    //   283: astore 11
    //   285: aload 10
    //   287: astore 12
    //   289: invokestatic 298	aba:a	()Laba;
    //   292: astore 16
    //   294: aload 14
    //   296: iconst_0
    //   297: aaload
    //   298: astore 17
    //   300: aload 10
    //   302: astore 11
    //   304: aload 10
    //   306: astore 12
    //   308: aload 14
    //   310: arraylength
    //   311: iconst_1
    //   312: if_icmple +484 -> 796
    //   315: aload 14
    //   317: iconst_1
    //   318: aaload
    //   319: astore 14
    //   321: aload 10
    //   323: astore 11
    //   325: aload 10
    //   327: astore 12
    //   329: aload 16
    //   331: aload 17
    //   333: aload 14
    //   335: aload_0
    //   336: getfield 88	pc:l	Ljava/lang/String;
    //   339: aload 13
    //   341: aload_0
    //   342: getfield 129	pc:r	J
    //   345: invokevirtual 301	aba:a	(Ljava/lang/String;Ljava/lang/String;Ljava/lang/String;Ljava/lang/String;J)Z
    //   348: istore 9
    //   350: iload 9
    //   352: ifeq +38 -> 390
    //   355: aload 10
    //   357: astore 11
    //   359: aload 10
    //   361: astore 12
    //   363: aload_0
    //   364: getfield 305	pc:i	Ljava/lang/Object;
    //   367: astore 13
    //   369: aload 10
    //   371: astore 11
    //   373: aload 10
    //   375: astore 12
    //   377: aload 13
    //   379: monitorenter
    //   380: aload_0
    //   381: getfield 305	pc:i	Ljava/lang/Object;
    //   384: invokevirtual 310	java/lang/Object:wait	()V
    //   387: aload 13
    //   389: monitorexit
    //   390: aload 10
    //   392: astore 11
    //   394: aload 10
    //   396: astore 12
    //   398: aload_0
    //   399: aload_0
    //   400: getfield 313	pc:j	I
    //   403: invokevirtual 315	pc:c	(I)V
    //   406: aload 10
    //   408: astore 11
    //   410: aload 10
    //   412: astore 12
    //   414: aload_0
    //   415: getfield 318	pc:d	Lpa;
    //   418: invokevirtual 322	pa:c	()[B
    //   421: astore 13
    //   423: aload 10
    //   425: astore 11
    //   427: aload 10
    //   429: astore 12
    //   431: ldc 62
    //   433: new 64	java/lang/StringBuilder
    //   436: dup
    //   437: invokespecial 66	java/lang/StringBuilder:<init>	()V
    //   440: ldc_w 324
    //   443: invokevirtual 72	java/lang/StringBuilder:append	(Ljava/lang/String;)Ljava/lang/StringBuilder;
    //   446: aload_0
    //   447: getfield 258	pc:m	I
    //   450: invokevirtual 261	java/lang/StringBuilder:append	(I)Ljava/lang/StringBuilder;
    //   453: ldc_w 263
    //   456: invokevirtual 72	java/lang/StringBuilder:append	(Ljava/lang/String;)Ljava/lang/StringBuilder;
    //   459: aload_0
    //   460: getfield 57	pc:p	Ljava/lang/String;
    //   463: invokevirtual 72	java/lang/StringBuilder:append	(Ljava/lang/String;)Ljava/lang/StringBuilder;
    //   466: ldc_w 326
    //   469: invokevirtual 72	java/lang/StringBuilder:append	(Ljava/lang/String;)Ljava/lang/StringBuilder;
    //   472: iload 9
    //   474: invokevirtual 329	java/lang/StringBuilder:append	(Z)Ljava/lang/StringBuilder;
    //   477: invokevirtual 76	java/lang/StringBuilder:toString	()Ljava/lang/String;
    //   480: invokestatic 268	android/util/Log:d	(Ljava/lang/String;Ljava/lang/String;)I
    //   483: pop
    //   484: aload 10
    //   486: astore 11
    //   488: aload 10
    //   490: astore 12
    //   492: new 331	com/meizu/android/mms/pdu/MzPduParser
    //   495: dup
    //   496: aload 13
    //   498: iconst_2
    //   499: invokespecial 334	com/meizu/android/mms/pdu/MzPduParser:<init>	([BI)V
    //   502: invokevirtual 337	com/meizu/android/mms/pdu/MzPduParser:parse	()Lcom/meizu/android/mms/pdu/MzGenericPdu;
    //   505: checkcast 170	com/meizu/android/mms/pdu/MzRetrieveConf
    //   508: astore 16
    //   510: aload 16
    //   512: ifnonnull +535 -> 1047
    //   515: aload 10
    //   517: astore 11
    //   519: aload 10
    //   521: astore 12
    //   523: new 138	com/google/android/mms/MmsException
    //   526: dup
    //   527: ldc_w 339
    //   530: invokespecial 144	com/google/android/mms/MmsException:<init>	(Ljava/lang/String;)V
    //   533: athrow
    //   534: astore 12
    //   536: iconst_1
    //   537: istore_1
    //   538: aload 11
    //   540: astore 10
    //   542: aload 12
    //   544: astore 11
    //   546: ldc 62
    //   548: aload 11
    //   550: invokestatic 343	android/util/Log:getStackTraceString	(Ljava/lang/Throwable;)Ljava/lang/String;
    //   553: invokestatic 279	android/util/Log:e	(Ljava/lang/String;Ljava/lang/String;)I
    //   556: pop
    //   557: aload_0
    //   558: getfield 318	pc:d	Lpa;
    //   561: invokevirtual 345	pa:a	()I
    //   564: iconst_1
    //   565: if_icmpeq +1470 -> 2035
    //   568: aload_0
    //   569: getfield 318	pc:d	Lpa;
    //   572: iconst_2
    //   573: invokevirtual 347	pa:a	(I)V
    //   576: aload_0
    //   577: getfield 318	pc:d	Lpa;
    //   580: aload_0
    //   581: getfield 52	pc:g	Landroid/net/Uri;
    //   584: invokevirtual 349	pa:a	(Landroid/net/Uri;)V
    //   587: ldc 62
    //   589: new 64	java/lang/StringBuilder
    //   592: dup
    //   593: invokespecial 66	java/lang/StringBuilder:<init>	()V
    //   596: ldc_w 351
    //   599: invokevirtual 72	java/lang/StringBuilder:append	(Ljava/lang/String;)Ljava/lang/StringBuilder;
    //   602: aload_0
    //   603: getfield 258	pc:m	I
    //   606: invokevirtual 261	java/lang/StringBuilder:append	(I)Ljava/lang/StringBuilder;
    //   609: ldc_w 353
    //   612: invokevirtual 72	java/lang/StringBuilder:append	(Ljava/lang/String;)Ljava/lang/StringBuilder;
    //   615: invokevirtual 76	java/lang/StringBuilder:toString	()Ljava/lang/String;
    //   618: invokestatic 268	android/util/Log:d	(Ljava/lang/String;Ljava/lang/String;)I
    //   621: pop
    //   622: iload_1
    //   623: ifeq +129 -> 752
    //   626: aload_0
    //   627: getfield 356	pc:k	I
    //   630: sipush 9528
    //   633: if_icmpne +1469 -> 2102
    //   636: invokestatic 250	zn:a	()Lzn;
    //   639: aload_0
    //   640: getfield 52	pc:g	Landroid/net/Uri;
    //   643: sipush 132
    //   646: iconst_m1
    //   647: invokevirtual 253	zn:b	(Landroid/net/Uri;II)V
    //   650: aload_0
    //   651: getfield 52	pc:g	Landroid/net/Uri;
    //   654: ifnull +98 -> 752
    //   657: aload_0
    //   658: invokevirtual 359	pc:m	()J
    //   661: lconst_0
    //   662: lcmp
    //   663: ifle +89 -> 752
    //   666: new 147	android/content/ContentValues
    //   669: dup
    //   670: iconst_1
    //   671: invokespecial 150	android/content/ContentValues:<init>	(I)V
    //   674: astore 10
    //   676: aload 10
    //   678: ldc_w 361
    //   681: aload_0
    //   682: invokevirtual 359	pc:m	()J
    //   685: invokestatic 366	java/lang/Long:valueOf	(J)Ljava/lang/Long;
    //   688: invokevirtual 369	android/content/ContentValues:put	(Ljava/lang/String;Ljava/lang/Long;)V
    //   691: ldc 62
    //   693: new 64	java/lang/StringBuilder
    //   696: dup
    //   697: invokespecial 66	java/lang/StringBuilder:<init>	()V
    //   700: ldc_w 371
    //   703: invokevirtual 72	java/lang/StringBuilder:append	(Ljava/lang/String;)Ljava/lang/StringBuilder;
    //   706: aload_0
    //   707: invokevirtual 359	pc:m	()J
    //   710: invokevirtual 374	java/lang/StringBuilder:append	(J)Ljava/lang/StringBuilder;
    //   713: ldc_w 265
    //   716: invokevirtual 72	java/lang/StringBuilder:append	(Ljava/lang/String;)Ljava/lang/StringBuilder;
    //   719: aload_0
    //   720: getfield 52	pc:g	Landroid/net/Uri;
    //   723: invokevirtual 143	java/lang/StringBuilder:append	(Ljava/lang/Object;)Ljava/lang/StringBuilder;
    //   726: invokevirtual 76	java/lang/StringBuilder:toString	()Ljava/lang/String;
    //   729: invokestatic 268	android/util/Log:d	(Ljava/lang/String;Ljava/lang/String;)I
    //   732: pop
    //   733: aload_0
    //   734: getfield 282	pc:b	Landroid/content/Context;
    //   737: invokevirtual 105	android/content/Context:getContentResolver	()Landroid/content/ContentResolver;
    //   740: aload_0
    //   741: getfield 52	pc:g	Landroid/net/Uri;
    //   744: aload 10
    //   746: aconst_null
    //   747: aconst_null
    //   748: invokevirtual 167	android/content/ContentResolver:update	(Landroid/net/Uri;Landroid/content/ContentValues;Ljava/lang/String;[Ljava/lang/String;)I
    //   751: pop
    //   752: getstatic 379	com/android/mms/view/MessageListItem:ac	J
    //   755: lload_3
    //   756: lcmp
    //   757: ifne +9 -> 766
    //   760: ldc2_w 380
    //   763: putstatic 379	com/android/mms/view/MessageListItem:ac	J
    //   766: iconst_0
    //   767: putstatic 384	com/android/mms/view/MessageListItem:ab	Z
    //   770: aload_0
    //   771: invokevirtual 386	pc:d	()V
    //   774: return
    //   775: astore 11
    //   777: lconst_0
    //   778: lstore_3
    //   779: aload 13
    //   781: invokeinterface 136 1 0
    //   786: aload 11
    //   788: athrow
    //   789: astore 11
    //   791: iconst_1
    //   792: istore_1
    //   793: goto -247 -> 546
    //   796: ldc -11
    //   798: astore 14
    //   800: goto -479 -> 321
    //   803: astore 14
    //   805: aload 13
    //   807: monitorexit
    //   808: aload 10
    //   810: astore 11
    //   812: aload 10
    //   814: astore 12
    //   816: aload 14
    //   818: athrow
    //   819: astore 11
    //   821: iload_2
    //   822: istore_1
    //   823: aload 12
    //   825: astore 10
    //   827: aload_0
    //   828: getfield 318	pc:d	Lpa;
    //   831: invokevirtual 345	pa:a	()I
    //   834: iconst_1
    //   835: if_icmpeq +1284 -> 2119
    //   838: aload_0
    //   839: getfield 318	pc:d	Lpa;
    //   842: iconst_2
    //   843: invokevirtual 347	pa:a	(I)V
    //   846: aload_0
    //   847: getfield 318	pc:d	Lpa;
    //   850: aload_0
    //   851: getfield 52	pc:g	Landroid/net/Uri;
    //   854: invokevirtual 349	pa:a	(Landroid/net/Uri;)V
    //   857: ldc 62
    //   859: new 64	java/lang/StringBuilder
    //   862: dup
    //   863: invokespecial 66	java/lang/StringBuilder:<init>	()V
    //   866: ldc_w 351
    //   869: invokevirtual 72	java/lang/StringBuilder:append	(Ljava/lang/String;)Ljava/lang/StringBuilder;
    //   872: aload_0
    //   873: getfield 258	pc:m	I
    //   876: invokevirtual 261	java/lang/StringBuilder:append	(I)Ljava/lang/StringBuilder;
    //   879: ldc_w 353
    //   882: invokevirtual 72	java/lang/StringBuilder:append	(Ljava/lang/String;)Ljava/lang/StringBuilder;
    //   885: invokevirtual 76	java/lang/StringBuilder:toString	()Ljava/lang/String;
    //   888: invokestatic 268	android/util/Log:d	(Ljava/lang/String;Ljava/lang/String;)I
    //   891: pop
    //   892: iload_1
    //   893: ifeq +129 -> 1022
    //   896: aload_0
    //   897: getfield 356	pc:k	I
    //   900: sipush 9528
    //   903: if_icmpne +1283 -> 2186
    //   906: invokestatic 250	zn:a	()Lzn;
    //   909: aload_0
    //   910: getfield 52	pc:g	Landroid/net/Uri;
    //   913: sipush 132
    //   916: iconst_m1
    //   917: invokevirtual 253	zn:b	(Landroid/net/Uri;II)V
    //   920: aload_0
    //   921: getfield 52	pc:g	Landroid/net/Uri;
    //   924: ifnull +98 -> 1022
    //   927: aload_0
    //   928: invokevirtual 359	pc:m	()J
    //   931: lconst_0
    //   932: lcmp
    //   933: ifle +89 -> 1022
    //   936: new 147	android/content/ContentValues
    //   939: dup
    //   940: iconst_1
    //   941: invokespecial 150	android/content/ContentValues:<init>	(I)V
    //   944: astore 10
    //   946: aload 10
    //   948: ldc_w 361
    //   951: aload_0
    //   952: invokevirtual 359	pc:m	()J
    //   955: invokestatic 366	java/lang/Long:valueOf	(J)Ljava/lang/Long;
    //   958: invokevirtual 369	android/content/ContentValues:put	(Ljava/lang/String;Ljava/lang/Long;)V
    //   961: ldc 62
    //   963: new 64	java/lang/StringBuilder
    //   966: dup
    //   967: invokespecial 66	java/lang/StringBuilder:<init>	()V
    //   970: ldc_w 371
    //   973: invokevirtual 72	java/lang/StringBuilder:append	(Ljava/lang/String;)Ljava/lang/StringBuilder;
    //   976: aload_0
    //   977: invokevirtual 359	pc:m	()J
    //   980: invokevirtual 374	java/lang/StringBuilder:append	(J)Ljava/lang/StringBuilder;
    //   983: ldc_w 265
    //   986: invokevirtual 72	java/lang/StringBuilder:append	(Ljava/lang/String;)Ljava/lang/StringBuilder;
    //   989: aload_0
    //   990: getfield 52	pc:g	Landroid/net/Uri;
    //   993: invokevirtual 143	java/lang/StringBuilder:append	(Ljava/lang/Object;)Ljava/lang/StringBuilder;
    //   996: invokevirtual 76	java/lang/StringBuilder:toString	()Ljava/lang/String;
    //   999: invokestatic 268	android/util/Log:d	(Ljava/lang/String;Ljava/lang/String;)I
    //   1002: pop
    //   1003: aload_0
    //   1004: getfield 282	pc:b	Landroid/content/Context;
    //   1007: invokevirtual 105	android/content/Context:getContentResolver	()Landroid/content/ContentResolver;
    //   1010: aload_0
    //   1011: getfield 52	pc:g	Landroid/net/Uri;
    //   1014: aload 10
    //   1016: aconst_null
    //   1017: aconst_null
    //   1018: invokevirtual 167	android/content/ContentResolver:update	(Landroid/net/Uri;Landroid/content/ContentValues;Ljava/lang/String;[Ljava/lang/String;)I
    //   1021: pop
    //   1022: getstatic 379	com/android/mms/view/MessageListItem:ac	J
    //   1025: lload_3
    //   1026: lcmp
    //   1027: ifne +9 -> 1036
    //   1030: ldc2_w 380
    //   1033: putstatic 379	com/android/mms/view/MessageListItem:ac	J
    //   1036: iconst_0
    //   1037: putstatic 384	com/android/mms/view/MessageListItem:ab	Z
    //   1040: aload_0
    //   1041: invokevirtual 386	pc:d	()V
    //   1044: aload 11
    //   1046: athrow
    //   1047: aconst_null
    //   1048: astore 14
    //   1050: aconst_null
    //   1051: astore 13
    //   1053: aload 10
    //   1055: astore 11
    //   1057: aload 10
    //   1059: astore 12
    //   1061: aload_0
    //   1062: getfield 282	pc:b	Landroid/content/Context;
    //   1065: aload 16
    //   1067: invokestatic 388	pc:a	(Landroid/content/Context;Lcom/meizu/android/mms/pdu/MzRetrieveConf;)Z
    //   1070: ifeq +163 -> 1233
    //   1073: aload 10
    //   1075: astore 11
    //   1077: aload 10
    //   1079: astore 12
    //   1081: aload_0
    //   1082: getfield 318	pc:d	Lpa;
    //   1085: iconst_2
    //   1086: invokevirtual 347	pa:a	(I)V
    //   1089: aload 10
    //   1091: astore 11
    //   1093: aload 10
    //   1095: astore 12
    //   1097: aload_0
    //   1098: getfield 318	pc:d	Lpa;
    //   1101: aload_0
    //   1102: getfield 52	pc:g	Landroid/net/Uri;
    //   1105: invokevirtual 349	pa:a	(Landroid/net/Uri;)V
    //   1108: aload 13
    //   1110: astore 11
    //   1112: iconst_0
    //   1113: istore_1
    //   1114: aload 11
    //   1116: ifnull +29 -> 1145
    //   1119: invokestatic 393	aat:b	()Laat$a;
    //   1122: aload_0
    //   1123: getfield 282	pc:b	Landroid/content/Context;
    //   1126: aload 11
    //   1128: invokevirtual 398	aat$a:a	(Landroid/content/Context;Landroid/net/Uri;)V
    //   1131: aload_0
    //   1132: getfield 282	pc:b	Landroid/content/Context;
    //   1135: invokestatic 401	aat:c	(Landroid/content/Context;)V
    //   1138: aload_0
    //   1139: getfield 282	pc:b	Landroid/content/Context;
    //   1142: invokestatic 405	aev:a	(Landroid/content/Context;)V
    //   1145: aload_0
    //   1146: getfield 318	pc:d	Lpa;
    //   1149: invokevirtual 345	pa:a	()I
    //   1152: iconst_1
    //   1153: if_icmpeq +815 -> 1968
    //   1156: aload_0
    //   1157: getfield 318	pc:d	Lpa;
    //   1160: iconst_2
    //   1161: invokevirtual 347	pa:a	(I)V
    //   1164: aload_0
    //   1165: getfield 318	pc:d	Lpa;
    //   1168: aload_0
    //   1169: getfield 52	pc:g	Landroid/net/Uri;
    //   1172: invokevirtual 349	pa:a	(Landroid/net/Uri;)V
    //   1175: ldc 62
    //   1177: new 64	java/lang/StringBuilder
    //   1180: dup
    //   1181: invokespecial 66	java/lang/StringBuilder:<init>	()V
    //   1184: ldc_w 351
    //   1187: invokevirtual 72	java/lang/StringBuilder:append	(Ljava/lang/String;)Ljava/lang/StringBuilder;
    //   1190: aload_0
    //   1191: getfield 258	pc:m	I
    //   1194: invokevirtual 261	java/lang/StringBuilder:append	(I)Ljava/lang/StringBuilder;
    //   1197: ldc_w 353
    //   1200: invokevirtual 72	java/lang/StringBuilder:append	(Ljava/lang/String;)Ljava/lang/StringBuilder;
    //   1203: invokevirtual 76	java/lang/StringBuilder:toString	()Ljava/lang/String;
    //   1206: invokestatic 268	android/util/Log:d	(Ljava/lang/String;Ljava/lang/String;)I
    //   1209: pop
    //   1210: getstatic 379	com/android/mms/view/MessageListItem:ac	J
    //   1213: lload_3
    //   1214: lcmp
    //   1215: ifne +9 -> 1224
    //   1218: ldc2_w 380
    //   1221: putstatic 379	com/android/mms/view/MessageListItem:ac	J
    //   1224: iconst_0
    //   1225: putstatic 384	com/android/mms/view/MessageListItem:ab	Z
    //   1228: aload_0
    //   1229: invokevirtual 386	pc:d	()V
    //   1232: return
    //   1233: aload 10
    //   1235: astore 11
    //   1237: aload 10
    //   1239: astore 12
    //   1241: aload 10
    //   1243: astore 13
    //   1245: aload 15
    //   1247: ldc_w 407
    //   1250: invokevirtual 229	java/lang/String:equals	(Ljava/lang/Object;)Z
    //   1253: ifne +561 -> 1814
    //   1256: aload 10
    //   1258: astore 11
    //   1260: aload 10
    //   1262: astore 12
    //   1264: aload_0
    //   1265: getfield 282	pc:b	Landroid/content/Context;
    //   1268: invokestatic 411	com/meizu/android/mms/pdu/MzPduPersister:getPduPersister	(Landroid/content/Context;)Lcom/meizu/android/mms/pdu/MzPduPersister;
    //   1271: astore 15
    //   1273: aload 10
    //   1275: astore 11
    //   1277: aload 10
    //   1279: astore 12
    //   1281: aload_0
    //   1282: getfield 282	pc:b	Landroid/content/Context;
    //   1285: invokevirtual 105	android/content/Context:getContentResolver	()Landroid/content/ContentResolver;
    //   1288: aload_0
    //   1289: getfield 52	pc:g	Landroid/net/Uri;
    //   1292: bipush 7
    //   1294: anewarray 18	java/lang/String
    //   1297: dup
    //   1298: iconst_0
    //   1299: ldc -72
    //   1301: aastore
    //   1302: dup
    //   1303: iconst_1
    //   1304: ldc 24
    //   1306: aastore
    //   1307: dup
    //   1308: iconst_2
    //   1309: ldc_w 284
    //   1312: aastore
    //   1313: dup
    //   1314: iconst_3
    //   1315: ldc_w 413
    //   1318: aastore
    //   1319: dup
    //   1320: iconst_4
    //   1321: ldc_w 286
    //   1324: aastore
    //   1325: dup
    //   1326: iconst_5
    //   1327: ldc_w 415
    //   1330: aastore
    //   1331: dup
    //   1332: bipush 6
    //   1334: ldc_w 417
    //   1337: aastore
    //   1338: aconst_null
    //   1339: aconst_null
    //   1340: aconst_null
    //   1341: invokevirtual 111	android/content/ContentResolver:query	(Landroid/net/Uri;[Ljava/lang/String;Ljava/lang/String;[Ljava/lang/String;Ljava/lang/String;)Landroid/database/Cursor;
    //   1344: astore 17
    //   1346: aload 17
    //   1348: ifnull +933 -> 2281
    //   1351: aload 17
    //   1353: invokeinterface 119 1 0
    //   1358: ifle +906 -> 2264
    //   1361: aload 17
    //   1363: invokeinterface 123 1 0
    //   1368: ifeq +896 -> 2264
    //   1371: aload 17
    //   1373: aload 17
    //   1375: ldc 24
    //   1377: invokeinterface 289 2 0
    //   1382: invokeinterface 293 2 0
    //   1387: lstore 5
    //   1389: aload 17
    //   1391: aload 17
    //   1393: ldc_w 284
    //   1396: invokeinterface 289 2 0
    //   1401: invokeinterface 133 2 0
    //   1406: astore 10
    //   1408: aload 17
    //   1410: aload 17
    //   1412: ldc_w 413
    //   1415: invokeinterface 289 2 0
    //   1420: invokeinterface 133 2 0
    //   1425: astore 14
    //   1427: aload 17
    //   1429: aload 17
    //   1431: ldc_w 286
    //   1434: invokeinterface 289 2 0
    //   1439: invokeinterface 133 2 0
    //   1444: pop
    //   1445: aload 17
    //   1447: aload 17
    //   1449: ldc_w 415
    //   1452: invokeinterface 289 2 0
    //   1457: invokeinterface 133 2 0
    //   1462: astore 13
    //   1464: aload 17
    //   1466: aload 17
    //   1468: ldc_w 417
    //   1471: invokeinterface 289 2 0
    //   1476: invokeinterface 127 2 0
    //   1481: istore_1
    //   1482: aload 10
    //   1484: astore 11
    //   1486: aload 10
    //   1488: astore 12
    //   1490: aload 17
    //   1492: invokeinterface 136 1 0
    //   1497: aload 10
    //   1499: astore 11
    //   1501: aload 10
    //   1503: astore 12
    //   1505: new 147	android/content/ContentValues
    //   1508: dup
    //   1509: invokespecial 418	android/content/ContentValues:<init>	()V
    //   1512: astore 17
    //   1514: aload 10
    //   1516: astore 11
    //   1518: aload 10
    //   1520: astore 12
    //   1522: aload 17
    //   1524: ldc 24
    //   1526: lload 5
    //   1528: invokestatic 366	java/lang/Long:valueOf	(J)Ljava/lang/Long;
    //   1531: invokevirtual 369	android/content/ContentValues:put	(Ljava/lang/String;Ljava/lang/Long;)V
    //   1534: aload 10
    //   1536: astore 11
    //   1538: aload 10
    //   1540: astore 12
    //   1542: aload 17
    //   1544: ldc_w 284
    //   1547: aload 10
    //   1549: invokevirtual 154	android/content/ContentValues:put	(Ljava/lang/String;Ljava/lang/String;)V
    //   1552: aload 10
    //   1554: astore 11
    //   1556: aload 10
    //   1558: astore 12
    //   1560: aload 17
    //   1562: ldc_w 420
    //   1565: iconst_2
    //   1566: invokestatic 425	java/lang/Integer:valueOf	(I)Ljava/lang/Integer;
    //   1569: invokevirtual 428	android/content/ContentValues:put	(Ljava/lang/String;Ljava/lang/Integer;)V
    //   1572: aload 10
    //   1574: astore 11
    //   1576: aload 10
    //   1578: astore 12
    //   1580: aload 17
    //   1582: ldc_w 413
    //   1585: aload 14
    //   1587: invokevirtual 154	android/content/ContentValues:put	(Ljava/lang/String;Ljava/lang/String;)V
    //   1590: aload 10
    //   1592: astore 11
    //   1594: aload 10
    //   1596: astore 12
    //   1598: aload 17
    //   1600: ldc_w 361
    //   1603: aload_0
    //   1604: invokevirtual 359	pc:m	()J
    //   1607: invokestatic 366	java/lang/Long:valueOf	(J)Ljava/lang/Long;
    //   1610: invokevirtual 369	android/content/ContentValues:put	(Ljava/lang/String;Ljava/lang/Long;)V
    //   1613: aload 10
    //   1615: astore 11
    //   1617: aload 10
    //   1619: astore 12
    //   1621: aload 17
    //   1623: ldc_w 430
    //   1626: new 363	java/lang/Long
    //   1629: dup
    //   1630: invokestatic 435	java/lang/System:currentTimeMillis	()J
    //   1633: invokespecial 438	java/lang/Long:<init>	(J)V
    //   1636: invokevirtual 369	android/content/ContentValues:put	(Ljava/lang/String;Ljava/lang/Long;)V
    //   1639: aload 10
    //   1641: astore 11
    //   1643: aload 10
    //   1645: astore 12
    //   1647: aload 17
    //   1649: ldc_w 415
    //   1652: aload 13
    //   1654: invokevirtual 154	android/content/ContentValues:put	(Ljava/lang/String;Ljava/lang/String;)V
    //   1657: aload 10
    //   1659: astore 11
    //   1661: aload 10
    //   1663: astore 12
    //   1665: aload 17
    //   1667: ldc_w 417
    //   1670: iload_1
    //   1671: invokestatic 425	java/lang/Integer:valueOf	(I)Ljava/lang/Integer;
    //   1674: invokevirtual 428	android/content/ContentValues:put	(Ljava/lang/String;Ljava/lang/Integer;)V
    //   1677: aload 10
    //   1679: astore 11
    //   1681: aload 10
    //   1683: astore 12
    //   1685: ldc 62
    //   1687: new 64	java/lang/StringBuilder
    //   1690: dup
    //   1691: invokespecial 66	java/lang/StringBuilder:<init>	()V
    //   1694: ldc_w 440
    //   1697: invokevirtual 72	java/lang/StringBuilder:append	(Ljava/lang/String;)Ljava/lang/StringBuilder;
    //   1700: aload_0
    //   1701: invokevirtual 359	pc:m	()J
    //   1704: invokevirtual 374	java/lang/StringBuilder:append	(J)Ljava/lang/StringBuilder;
    //   1707: ldc_w 442
    //   1710: invokevirtual 72	java/lang/StringBuilder:append	(Ljava/lang/String;)Ljava/lang/StringBuilder;
    //   1713: lload 5
    //   1715: invokevirtual 374	java/lang/StringBuilder:append	(J)Ljava/lang/StringBuilder;
    //   1718: invokevirtual 76	java/lang/StringBuilder:toString	()Ljava/lang/String;
    //   1721: invokestatic 268	android/util/Log:d	(Ljava/lang/String;Ljava/lang/String;)I
    //   1724: pop
    //   1725: aload 10
    //   1727: astore 11
    //   1729: aload 10
    //   1731: astore 12
    //   1733: aload_0
    //   1734: getfield 282	pc:b	Landroid/content/Context;
    //   1737: invokevirtual 105	android/content/Context:getContentResolver	()Landroid/content/ContentResolver;
    //   1740: aload_0
    //   1741: getfield 52	pc:g	Landroid/net/Uri;
    //   1744: new 64	java/lang/StringBuilder
    //   1747: dup
    //   1748: invokespecial 66	java/lang/StringBuilder:<init>	()V
    //   1751: ldc_w 444
    //   1754: invokevirtual 72	java/lang/StringBuilder:append	(Ljava/lang/String;)Ljava/lang/StringBuilder;
    //   1757: aload_0
    //   1758: getfield 57	pc:p	Ljava/lang/String;
    //   1761: invokevirtual 72	java/lang/StringBuilder:append	(Ljava/lang/String;)Ljava/lang/StringBuilder;
    //   1764: ldc_w 446
    //   1767: invokevirtual 72	java/lang/StringBuilder:append	(Ljava/lang/String;)Ljava/lang/StringBuilder;
    //   1770: invokevirtual 76	java/lang/StringBuilder:toString	()Ljava/lang/String;
    //   1773: aconst_null
    //   1774: invokevirtual 450	android/content/ContentResolver:delete	(Landroid/net/Uri;Ljava/lang/String;[Ljava/lang/String;)I
    //   1777: pop
    //   1778: aload 10
    //   1780: astore 11
    //   1782: aload 10
    //   1784: astore 12
    //   1786: aload 15
    //   1788: aload 16
    //   1790: getstatic 453	android/provider/Telephony$Mms$Inbox:CONTENT_URI	Landroid/net/Uri;
    //   1793: iconst_1
    //   1794: aload_0
    //   1795: getfield 282	pc:b	Landroid/content/Context;
    //   1798: invokestatic 458	com/android/mms/ui/MessagingPreferenceActivity:b	(Landroid/content/Context;)Z
    //   1801: aconst_null
    //   1802: iconst_2
    //   1803: aload 17
    //   1805: invokevirtual 462	com/meizu/android/mms/pdu/MzPduPersister:persist	(Lcom/meizu/android/mms/pdu/MzGenericPdu;Landroid/net/Uri;ZZLjava/util/HashMap;ILandroid/content/ContentValues;)Landroid/net/Uri;
    //   1808: astore 14
    //   1810: aload 10
    //   1812: astore 13
    //   1814: aload 13
    //   1816: astore 11
    //   1818: aload 13
    //   1820: astore 12
    //   1822: aload_0
    //   1823: getfield 318	pc:d	Lpa;
    //   1826: iconst_1
    //   1827: invokevirtual 347	pa:a	(I)V
    //   1830: aload 14
    //   1832: astore 10
    //   1834: aload 14
    //   1836: ifnonnull +42 -> 1878
    //   1839: aload 13
    //   1841: astore 11
    //   1843: aload 13
    //   1845: astore 12
    //   1847: new 64	java/lang/StringBuilder
    //   1850: dup
    //   1851: invokespecial 66	java/lang/StringBuilder:<init>	()V
    //   1854: getstatic 453	android/provider/Telephony$Mms$Inbox:CONTENT_URI	Landroid/net/Uri;
    //   1857: invokevirtual 143	java/lang/StringBuilder:append	(Ljava/lang/Object;)Ljava/lang/StringBuilder;
    //   1860: ldc_w 464
    //   1863: invokevirtual 72	java/lang/StringBuilder:append	(Ljava/lang/String;)Ljava/lang/StringBuilder;
    //   1866: lload_3
    //   1867: invokevirtual 374	java/lang/StringBuilder:append	(J)Ljava/lang/StringBuilder;
    //   1870: invokevirtual 76	java/lang/StringBuilder:toString	()Ljava/lang/String;
    //   1873: invokestatic 48	android/net/Uri:parse	(Ljava/lang/String;)Landroid/net/Uri;
    //   1876: astore 10
    //   1878: aload 13
    //   1880: astore 11
    //   1882: aload 13
    //   1884: astore 12
    //   1886: aload_0
    //   1887: getfield 318	pc:d	Lpa;
    //   1890: aload 10
    //   1892: invokevirtual 349	pa:a	(Landroid/net/Uri;)V
    //   1895: aload 13
    //   1897: astore 11
    //   1899: aload 13
    //   1901: astore 12
    //   1903: ldc2_w 380
    //   1906: putstatic 467	com/android/mms/view/MessageListItem:ad	J
    //   1909: aload 13
    //   1911: astore 11
    //   1913: aload 13
    //   1915: astore 12
    //   1917: aload_0
    //   1918: getfield 282	pc:b	Landroid/content/Context;
    //   1921: aload 10
    //   1923: aload_0
    //   1924: getfield 57	pc:p	Ljava/lang/String;
    //   1927: aload_0
    //   1928: getfield 113	pc:q	Z
    //   1931: invokestatic 469	pc:a	(Landroid/content/Context;Landroid/net/Uri;Ljava/lang/String;Z)V
    //   1934: aload 10
    //   1936: astore 11
    //   1938: aload 13
    //   1940: astore 10
    //   1942: goto -830 -> 1112
    //   1945: astore 11
    //   1947: ldc -11
    //   1949: astore 10
    //   1951: aload 17
    //   1953: invokeinterface 136 1 0
    //   1958: aload 11
    //   1960: athrow
    //   1961: astore 11
    //   1963: iconst_1
    //   1964: istore_1
    //   1965: goto -1419 -> 546
    //   1968: aload_0
    //   1969: getfield 282	pc:b	Landroid/content/Context;
    //   1972: new 471	android/content/Intent
    //   1975: dup
    //   1976: ldc_w 473
    //   1979: new 475	java/io/File
    //   1982: dup
    //   1983: aload 10
    //   1985: invokespecial 476	java/io/File:<init>	(Ljava/lang/String;)V
    //   1988: invokestatic 480	android/net/Uri:fromFile	(Ljava/io/File;)Landroid/net/Uri;
    //   1991: invokespecial 483	android/content/Intent:<init>	(Ljava/lang/String;Landroid/net/Uri;)V
    //   1994: invokevirtual 487	android/content/Context:sendBroadcast	(Landroid/content/Intent;)V
    //   1997: ldc 62
    //   1999: new 64	java/lang/StringBuilder
    //   2002: dup
    //   2003: invokespecial 66	java/lang/StringBuilder:<init>	()V
    //   2006: ldc_w 351
    //   2009: invokevirtual 72	java/lang/StringBuilder:append	(Ljava/lang/String;)Ljava/lang/StringBuilder;
    //   2012: aload_0
    //   2013: getfield 258	pc:m	I
    //   2016: invokevirtual 261	java/lang/StringBuilder:append	(I)Ljava/lang/StringBuilder;
    //   2019: ldc_w 489
    //   2022: invokevirtual 72	java/lang/StringBuilder:append	(Ljava/lang/String;)Ljava/lang/StringBuilder;
    //   2025: invokevirtual 76	java/lang/StringBuilder:toString	()Ljava/lang/String;
    //   2028: invokestatic 268	android/util/Log:d	(Ljava/lang/String;Ljava/lang/String;)I
    //   2031: pop
    //   2032: goto -822 -> 1210
    //   2035: aload_0
    //   2036: getfield 282	pc:b	Landroid/content/Context;
    //   2039: new 471	android/content/Intent
    //   2042: dup
    //   2043: ldc_w 473
    //   2046: new 475	java/io/File
    //   2049: dup
    //   2050: aload 10
    //   2052: invokespecial 476	java/io/File:<init>	(Ljava/lang/String;)V
    //   2055: invokestatic 480	android/net/Uri:fromFile	(Ljava/io/File;)Landroid/net/Uri;
    //   2058: invokespecial 483	android/content/Intent:<init>	(Ljava/lang/String;Landroid/net/Uri;)V
    //   2061: invokevirtual 487	android/content/Context:sendBroadcast	(Landroid/content/Intent;)V
    //   2064: ldc 62
    //   2066: new 64	java/lang/StringBuilder
    //   2069: dup
    //   2070: invokespecial 66	java/lang/StringBuilder:<init>	()V
    //   2073: ldc_w 351
    //   2076: invokevirtual 72	java/lang/StringBuilder:append	(Ljava/lang/String;)Ljava/lang/StringBuilder;
    //   2079: aload_0
    //   2080: getfield 258	pc:m	I
    //   2083: invokevirtual 261	java/lang/StringBuilder:append	(I)Ljava/lang/StringBuilder;
    //   2086: ldc_w 489
    //   2089: invokevirtual 72	java/lang/StringBuilder:append	(Ljava/lang/String;)Ljava/lang/StringBuilder;
    //   2092: invokevirtual 76	java/lang/StringBuilder:toString	()Ljava/lang/String;
    //   2095: invokestatic 268	android/util/Log:d	(Ljava/lang/String;Ljava/lang/String;)I
    //   2098: pop
    //   2099: goto -1477 -> 622
    //   2102: invokestatic 250	zn:a	()Lzn;
    //   2105: aload_0
    //   2106: getfield 52	pc:g	Landroid/net/Uri;
    //   2109: sipush 130
    //   2112: iconst_m1
    //   2113: invokevirtual 253	zn:b	(Landroid/net/Uri;II)V
    //   2116: goto -1466 -> 650
    //   2119: aload_0
    //   2120: getfield 282	pc:b	Landroid/content/Context;
    //   2123: new 471	android/content/Intent
    //   2126: dup
    //   2127: ldc_w 473
    //   2130: new 475	java/io/File
    //   2133: dup
    //   2134: aload 10
    //   2136: invokespecial 476	java/io/File:<init>	(Ljava/lang/String;)V
    //   2139: invokestatic 480	android/net/Uri:fromFile	(Ljava/io/File;)Landroid/net/Uri;
    //   2142: invokespecial 483	android/content/Intent:<init>	(Ljava/lang/String;Landroid/net/Uri;)V
    //   2145: invokevirtual 487	android/content/Context:sendBroadcast	(Landroid/content/Intent;)V
    //   2148: ldc 62
    //   2150: new 64	java/lang/StringBuilder
    //   2153: dup
    //   2154: invokespecial 66	java/lang/StringBuilder:<init>	()V
    //   2157: ldc_w 351
    //   2160: invokevirtual 72	java/lang/StringBuilder:append	(Ljava/lang/String;)Ljava/lang/StringBuilder;
    //   2163: aload_0
    //   2164: getfield 258	pc:m	I
    //   2167: invokevirtual 261	java/lang/StringBuilder:append	(I)Ljava/lang/StringBuilder;
    //   2170: ldc_w 489
    //   2173: invokevirtual 72	java/lang/StringBuilder:append	(Ljava/lang/String;)Ljava/lang/StringBuilder;
    //   2176: invokevirtual 76	java/lang/StringBuilder:toString	()Ljava/lang/String;
    //   2179: invokestatic 268	android/util/Log:d	(Ljava/lang/String;Ljava/lang/String;)I
    //   2182: pop
    //   2183: goto -1291 -> 892
    //   2186: invokestatic 250	zn:a	()Lzn;
    //   2189: aload_0
    //   2190: getfield 52	pc:g	Landroid/net/Uri;
    //   2193: sipush 130
    //   2196: iconst_m1
    //   2197: invokevirtual 253	zn:b	(Landroid/net/Uri;II)V
    //   2200: goto -1280 -> 920
    //   2203: astore 11
    //   2205: lload 5
    //   2207: lstore_3
    //   2208: iload_2
    //   2209: istore_1
    //   2210: goto -1383 -> 827
    //   2213: astore 11
    //   2215: iload_2
    //   2216: istore_1
    //   2217: goto -1390 -> 827
    //   2220: astore 11
    //   2222: iload_2
    //   2223: istore_1
    //   2224: goto -1397 -> 827
    //   2227: astore 11
    //   2229: iconst_0
    //   2230: istore_1
    //   2231: goto -1404 -> 827
    //   2234: astore 11
    //   2236: goto -1409 -> 827
    //   2239: astore 11
    //   2241: iconst_1
    //   2242: istore_1
    //   2243: lload 7
    //   2245: lstore_3
    //   2246: goto -1700 -> 546
    //   2249: astore 11
    //   2251: goto -1705 -> 546
    //   2254: astore 11
    //   2256: goto -305 -> 1951
    //   2259: astore 11
    //   2261: goto -1482 -> 779
    //   2264: iconst_m1
    //   2265: istore_1
    //   2266: ldc -11
    //   2268: astore 13
    //   2270: ldc_w 491
    //   2273: astore 14
    //   2275: lconst_0
    //   2276: lstore 5
    //   2278: goto -796 -> 1482
    //   2281: iconst_m1
    //   2282: istore_1
    //   2283: ldc -11
    //   2285: astore 13
    //   2287: ldc_w 491
    //   2290: astore 14
    //   2292: lconst_0
    //   2293: lstore 5
    //   2295: goto -798 -> 1497
    //   2298: ldc -11
    //   2300: astore 11
    //   2302: ldc -11
    //   2304: astore 12
    //   2306: goto -2046 -> 260
    //   2309: ldc -11
    //   2311: astore 13
    //   2313: ldc -11
    //   2315: astore 15
    //   2317: lconst_0
    //   2318: lstore_3
    //   2319: goto -2038 -> 281
    // Local variable table:
    //   start	length	slot	name	signature
    //   0	2322	0	this	pc
    //   537	1746	1	i	int
    //   1	2222	2	j	int
    //   3	2316	3	l1	long
    //   9	2285	5	l2	long
    //   12	2232	7	l3	long
    //   348	125	9	bool	boolean
    //   6	2129	10	localObject1	Object
    //   239	310	11	localObject2	Object
    //   775	12	11	localObject3	Object
    //   789	1	11	localThrowable1	Throwable
    //   810	1	11	localObject4	Object
    //   819	226	11	localObject5	Object
    //   1055	882	11	localObject6	Object
    //   1945	14	11	localObject7	Object
    //   1961	1	11	localThrowable2	Throwable
    //   2203	1	11	localObject8	Object
    //   2213	1	11	localObject9	Object
    //   2220	1	11	localObject10	Object
    //   2227	1	11	localObject11	Object
    //   2234	1	11	localObject12	Object
    //   2239	1	11	localThrowable3	Throwable
    //   2249	1	11	localThrowable4	Throwable
    //   2254	1	11	localObject13	Object
    //   2259	1	11	localObject14	Object
    //   2300	1	11	str	String
    //   258	264	12	localObject15	Object
    //   534	9	12	localThrowable5	Throwable
    //   814	1491	12	localObject16	Object
    //   178	2134	13	localObject17	Object
    //   104	695	14	localObject18	Object
    //   803	14	14	localObject19	Object
    //   1048	1243	14	localObject20	Object
    //   275	2041	15	localObject21	Object
    //   292	1497	16	localObject22	Object
    //   298	1654	17	localObject23	Object
    // Exception table:
    //   from	to	target	type
    //   289	294	534	java/lang/Throwable
    //   308	315	534	java/lang/Throwable
    //   329	350	534	java/lang/Throwable
    //   363	369	534	java/lang/Throwable
    //   377	380	534	java/lang/Throwable
    //   398	406	534	java/lang/Throwable
    //   414	423	534	java/lang/Throwable
    //   431	484	534	java/lang/Throwable
    //   492	510	534	java/lang/Throwable
    //   523	534	534	java/lang/Throwable
    //   816	819	534	java/lang/Throwable
    //   1061	1073	534	java/lang/Throwable
    //   1081	1089	534	java/lang/Throwable
    //   1097	1108	534	java/lang/Throwable
    //   1245	1256	534	java/lang/Throwable
    //   1264	1273	534	java/lang/Throwable
    //   1281	1346	534	java/lang/Throwable
    //   1490	1497	534	java/lang/Throwable
    //   1505	1514	534	java/lang/Throwable
    //   1522	1534	534	java/lang/Throwable
    //   1542	1552	534	java/lang/Throwable
    //   1560	1572	534	java/lang/Throwable
    //   1580	1590	534	java/lang/Throwable
    //   1598	1613	534	java/lang/Throwable
    //   1621	1639	534	java/lang/Throwable
    //   1647	1657	534	java/lang/Throwable
    //   1665	1677	534	java/lang/Throwable
    //   1685	1725	534	java/lang/Throwable
    //   1733	1778	534	java/lang/Throwable
    //   1786	1810	534	java/lang/Throwable
    //   1822	1830	534	java/lang/Throwable
    //   1847	1878	534	java/lang/Throwable
    //   1886	1895	534	java/lang/Throwable
    //   1903	1909	534	java/lang/Throwable
    //   1917	1934	534	java/lang/Throwable
    //   185	222	775	finally
    //   779	789	789	java/lang/Throwable
    //   380	390	803	finally
    //   805	808	803	finally
    //   289	294	819	finally
    //   308	315	819	finally
    //   329	350	819	finally
    //   363	369	819	finally
    //   377	380	819	finally
    //   398	406	819	finally
    //   414	423	819	finally
    //   431	484	819	finally
    //   492	510	819	finally
    //   523	534	819	finally
    //   816	819	819	finally
    //   1061	1073	819	finally
    //   1081	1089	819	finally
    //   1097	1108	819	finally
    //   1245	1256	819	finally
    //   1264	1273	819	finally
    //   1281	1346	819	finally
    //   1490	1497	819	finally
    //   1505	1514	819	finally
    //   1522	1534	819	finally
    //   1542	1552	819	finally
    //   1560	1572	819	finally
    //   1580	1590	819	finally
    //   1598	1613	819	finally
    //   1621	1639	819	finally
    //   1647	1657	819	finally
    //   1665	1677	819	finally
    //   1685	1725	819	finally
    //   1733	1778	819	finally
    //   1786	1810	819	finally
    //   1822	1830	819	finally
    //   1847	1878	819	finally
    //   1886	1895	819	finally
    //   1903	1909	819	finally
    //   1917	1934	819	finally
    //   1351	1408	1945	finally
    //   1951	1961	1961	java/lang/Throwable
    //   14	28	2203	finally
    //   34	88	2203	finally
    //   94	106	2203	finally
    //   112	119	2203	finally
    //   125	134	2203	finally
    //   140	180	2203	finally
    //   266	273	2203	finally
    //   779	789	2213	finally
    //   1951	1961	2220	finally
    //   1119	1145	2227	finally
    //   546	557	2234	finally
    //   14	28	2239	java/lang/Throwable
    //   34	88	2239	java/lang/Throwable
    //   94	106	2239	java/lang/Throwable
    //   112	119	2239	java/lang/Throwable
    //   125	134	2239	java/lang/Throwable
    //   140	180	2239	java/lang/Throwable
    //   266	273	2239	java/lang/Throwable
    //   1119	1145	2249	java/lang/Throwable
    //   1408	1482	2254	finally
    //   222	260	2259	finally
  }
}

/* Location:
 * Qualified Name:     pc
 * Java Class Version: 6 (50.0)
 * JD-Core Version:    0.7.1
 */