import android.content.Context;
import android.net.Uri;
import android.util.Log;
import com.meizu.android.mms.pdu.MzNotificationInd;
import com.meizu.android.mms.pdu.MzPduPersister;
import java.lang.reflect.InvocationTargetException;
import java.lang.reflect.Method;

public class pl
  extends ow
  implements Runnable
{
  private long a;
  
  public pl(Context paramContext, int paramInt1, oz paramoz, String paramString, int paramInt2)
  {
    super(paramContext, paramInt1, paramoz);
    g = Uri.parse(paramString);
    try
    {
      paramContext = (MzNotificationInd)MzPduPersister.getPduPersister(b).load(g);
      c = a(paramContext);
      a = paramContext.getMessageSize();
      h = paramInt2;
      l = a(g);
      return;
    }
    catch (Exception paramContext)
    {
      for (;;)
      {
        Log.e("SnsNotificationTransaction", "Exception", paramContext);
      }
    }
  }
  
  private String a(MzNotificationInd paramMzNotificationInd)
  {
    Class localClass = aau.c("org.apache.harmony.security.utils.Array");
    try
    {
      paramMzNotificationInd = String.valueOf(localClass.getDeclaredMethod("getBytesAsString", new Class[] { byte[].class }).invoke(localClass, new Object[] { paramMzNotificationInd.getContentLocation() }));
      return paramMzNotificationInd;
    }
    catch (NoSuchMethodException paramMzNotificationInd)
    {
      paramMzNotificationInd.printStackTrace();
      return null;
    }
    catch (InvocationTargetException paramMzNotificationInd)
    {
      paramMzNotificationInd.printStackTrace();
      return null;
    }
    catch (IllegalAccessException paramMzNotificationInd)
    {
      paramMzNotificationInd.printStackTrace();
    }
    return null;
  }
  
  public void a()
  {
    new Thread(this, "NotificationTransaction").start();
  }
  
  public int c()
  {
    return 0;
  }
  
  /* Error */
  public void run()
  {
    // Byte code:
    //   0: invokestatic 141	zn:a	()Lzn;
    //   3: astore 9
    //   5: invokestatic 146	com/android/mms/MmsApp:c	()Lcom/android/mms/MmsApp;
    //   8: invokevirtual 149	com/android/mms/MmsApp:g	()Landroid/telephony/TelephonyManager;
    //   11: invokevirtual 154	android/telephony/TelephonyManager:getDataState	()I
    //   14: iconst_3
    //   15: if_icmpne +244 -> 259
    //   18: iconst_1
    //   19: istore_1
    //   20: aload_0
    //   21: getfield 54	pl:a	J
    //   24: lstore_3
    //   25: aload_0
    //   26: getfield 29	pl:b	Landroid/content/Context;
    //   29: invokestatic 159	wd:h	(Landroid/content/Context;)Z
    //   32: istore 5
    //   34: aload_0
    //   35: getfield 29	pl:b	Landroid/content/Context;
    //   38: invokevirtual 165	android/content/Context:getContentResolver	()Landroid/content/ContentResolver;
    //   41: aload_0
    //   42: getfield 25	pl:g	Landroid/net/Uri;
    //   45: iconst_3
    //   46: anewarray 112	java/lang/String
    //   49: dup
    //   50: iconst_0
    //   51: ldc -89
    //   53: aastore
    //   54: dup
    //   55: iconst_1
    //   56: ldc -87
    //   58: aastore
    //   59: dup
    //   60: iconst_2
    //   61: ldc -85
    //   63: aastore
    //   64: aconst_null
    //   65: aconst_null
    //   66: aconst_null
    //   67: invokevirtual 177	android/content/ContentResolver:query	(Landroid/net/Uri;[Ljava/lang/String;Ljava/lang/String;[Ljava/lang/String;Ljava/lang/String;)Landroid/database/Cursor;
    //   70: astore 7
    //   72: aload 7
    //   74: ifnull +1329 -> 1403
    //   77: aload 7
    //   79: invokeinterface 182 1 0
    //   84: ifle +1311 -> 1395
    //   87: aload 7
    //   89: invokeinterface 186 1 0
    //   94: ifeq +1301 -> 1395
    //   97: aload 7
    //   99: aload 7
    //   101: ldc -87
    //   103: invokeinterface 190 2 0
    //   108: invokeinterface 194 2 0
    //   113: astore 6
    //   115: aload 7
    //   117: aload 7
    //   119: ldc -85
    //   121: invokeinterface 190 2 0
    //   126: invokeinterface 198 2 0
    //   131: pop2
    //   132: aload 7
    //   134: invokeinterface 201 1 0
    //   139: sipush 131
    //   142: istore_2
    //   143: ldc 66
    //   145: new 203	java/lang/StringBuilder
    //   148: dup
    //   149: invokespecial 205	java/lang/StringBuilder:<init>	()V
    //   152: ldc -49
    //   154: invokevirtual 211	java/lang/StringBuilder:append	(Ljava/lang/String;)Ljava/lang/StringBuilder;
    //   157: aload_0
    //   158: invokevirtual 214	java/lang/StringBuilder:append	(Ljava/lang/Object;)Ljava/lang/StringBuilder;
    //   161: invokevirtual 218	java/lang/StringBuilder:toString	()Ljava/lang/String;
    //   164: invokestatic 222	android/util/Log:v	(Ljava/lang/String;Ljava/lang/String;)I
    //   167: pop
    //   168: iload 5
    //   170: ifeq +7 -> 177
    //   173: iload_1
    //   174: ifeq +113 -> 287
    //   177: aload 9
    //   179: aload_0
    //   180: getfield 25	pl:g	Landroid/net/Uri;
    //   183: sipush 128
    //   186: iconst_m1
    //   187: invokevirtual 225	zn:a	(Landroid/net/Uri;II)V
    //   190: aload 9
    //   192: aload_0
    //   193: getfield 25	pl:g	Landroid/net/Uri;
    //   196: sipush 130
    //   199: iconst_m1
    //   200: invokevirtual 225	zn:a	(Landroid/net/Uri;II)V
    //   203: aload_0
    //   204: getfield 229	pl:d	Lpa;
    //   207: aload_0
    //   208: getfield 25	pl:g	Landroid/net/Uri;
    //   211: invokevirtual 234	pa:a	(Landroid/net/Uri;)V
    //   214: iload 5
    //   216: ifne +11 -> 227
    //   219: aload_0
    //   220: getfield 229	pl:d	Lpa;
    //   223: iconst_1
    //   224: invokevirtual 237	pa:a	(I)V
    //   227: aload_0
    //   228: getfield 229	pl:d	Lpa;
    //   231: invokevirtual 239	pa:a	()I
    //   234: iconst_1
    //   235: if_icmpeq +41 -> 276
    //   238: aload_0
    //   239: getfield 229	pl:d	Lpa;
    //   242: iconst_2
    //   243: invokevirtual 237	pa:a	(I)V
    //   246: ldc 66
    //   248: ldc -15
    //   250: invokestatic 243	android/util/Log:d	(Ljava/lang/String;Ljava/lang/String;)I
    //   253: pop
    //   254: aload_0
    //   255: invokevirtual 245	pl:d	()V
    //   258: return
    //   259: iconst_0
    //   260: istore_1
    //   261: goto -241 -> 20
    //   264: astore 6
    //   266: aload 7
    //   268: invokeinterface 201 1 0
    //   273: aload 6
    //   275: athrow
    //   276: ldc 66
    //   278: ldc -9
    //   280: invokestatic 243	android/util/Log:d	(Ljava/lang/String;Ljava/lang/String;)I
    //   283: pop
    //   284: goto -30 -> 254
    //   287: aload 9
    //   289: aload_0
    //   290: getfield 25	pl:g	Landroid/net/Uri;
    //   293: sipush 129
    //   296: iconst_m1
    //   297: invokevirtual 225	zn:a	(Landroid/net/Uri;II)V
    //   300: ldc 66
    //   302: new 203	java/lang/StringBuilder
    //   305: dup
    //   306: invokespecial 205	java/lang/StringBuilder:<init>	()V
    //   309: ldc -7
    //   311: invokevirtual 211	java/lang/StringBuilder:append	(Ljava/lang/String;)Ljava/lang/StringBuilder;
    //   314: aload_0
    //   315: getfield 25	pl:g	Landroid/net/Uri;
    //   318: invokevirtual 250	android/net/Uri:toString	()Ljava/lang/String;
    //   321: invokevirtual 211	java/lang/StringBuilder:append	(Ljava/lang/String;)Ljava/lang/StringBuilder;
    //   324: invokevirtual 218	java/lang/StringBuilder:toString	()Ljava/lang/String;
    //   327: invokestatic 243	android/util/Log:d	(Ljava/lang/String;Ljava/lang/String;)I
    //   330: pop
    //   331: aload_0
    //   332: getfield 29	pl:b	Landroid/content/Context;
    //   335: invokestatic 35	com/meizu/android/mms/pdu/MzPduPersister:getPduPersister	(Landroid/content/Context;)Lcom/meizu/android/mms/pdu/MzPduPersister;
    //   338: aload_0
    //   339: getfield 25	pl:g	Landroid/net/Uri;
    //   342: invokevirtual 39	com/meizu/android/mms/pdu/MzPduPersister:load	(Landroid/net/Uri;)Lcom/meizu/android/mms/pdu/MzGenericPdu;
    //   345: checkcast 41	com/meizu/android/mms/pdu/MzNotificationInd
    //   348: astore 7
    //   350: new 252	com/meizu/android/mms/pdu/MzPduComposer
    //   353: dup
    //   354: aload_0
    //   355: getfield 29	pl:b	Landroid/content/Context;
    //   358: aload 7
    //   360: aload_0
    //   361: getfield 58	pl:h	I
    //   364: invokespecial 255	com/meizu/android/mms/pdu/MzPduComposer:<init>	(Landroid/content/Context;Lcom/meizu/android/mms/pdu/MzGenericPdu;I)V
    //   367: astore 8
    //   369: invokestatic 260	abh:a	()Labh;
    //   372: aload_0
    //   373: getfield 64	pl:l	Ljava/lang/String;
    //   376: aload 8
    //   378: invokevirtual 263	com/meizu/android/mms/pdu/MzPduComposer:make	()[B
    //   381: aload 7
    //   383: invokevirtual 267	com/meizu/android/mms/pdu/MzNotificationInd:getSubject	()Lcom/meizu/android/mms/pdu/MzEncodedStringValue;
    //   386: invokevirtual 271	com/meizu/android/mms/pdu/MzEncodedStringValue:getString	()Ljava/lang/String;
    //   389: aload 6
    //   391: aload_0
    //   392: getfield 54	pl:a	J
    //   395: invokevirtual 274	abh:a	(Ljava/lang/String;[BLjava/lang/String;Ljava/lang/String;J)[B
    //   398: astore 7
    //   400: ldc 66
    //   402: new 203	java/lang/StringBuilder
    //   405: dup
    //   406: invokespecial 205	java/lang/StringBuilder:<init>	()V
    //   409: ldc_w 276
    //   412: invokevirtual 211	java/lang/StringBuilder:append	(Ljava/lang/String;)Ljava/lang/StringBuilder;
    //   415: aload_0
    //   416: getfield 25	pl:g	Landroid/net/Uri;
    //   419: invokevirtual 250	android/net/Uri:toString	()Ljava/lang/String;
    //   422: invokevirtual 211	java/lang/StringBuilder:append	(Ljava/lang/String;)Ljava/lang/StringBuilder;
    //   425: invokevirtual 218	java/lang/StringBuilder:toString	()Ljava/lang/String;
    //   428: invokestatic 243	android/util/Log:d	(Ljava/lang/String;Ljava/lang/String;)I
    //   431: pop
    //   432: aload 7
    //   434: ifnull +954 -> 1388
    //   437: new 278	com/meizu/android/mms/pdu/MzPduParser
    //   440: dup
    //   441: aload 7
    //   443: aload_0
    //   444: getfield 58	pl:h	I
    //   447: invokespecial 281	com/meizu/android/mms/pdu/MzPduParser:<init>	([BI)V
    //   450: invokevirtual 284	com/meizu/android/mms/pdu/MzPduParser:parse	()Lcom/meizu/android/mms/pdu/MzGenericPdu;
    //   453: astore 10
    //   455: aload 10
    //   457: ifnull +14 -> 471
    //   460: aload 10
    //   462: invokevirtual 289	com/meizu/android/mms/pdu/MzGenericPdu:getMessageType	()I
    //   465: sipush 132
    //   468: if_icmpeq +238 -> 706
    //   471: new 203	java/lang/StringBuilder
    //   474: dup
    //   475: invokespecial 205	java/lang/StringBuilder:<init>	()V
    //   478: ldc_w 291
    //   481: invokevirtual 211	java/lang/StringBuilder:append	(Ljava/lang/String;)Ljava/lang/StringBuilder;
    //   484: astore 7
    //   486: aload 10
    //   488: ifnull +210 -> 698
    //   491: new 203	java/lang/StringBuilder
    //   494: dup
    //   495: invokespecial 205	java/lang/StringBuilder:<init>	()V
    //   498: ldc_w 293
    //   501: invokevirtual 211	java/lang/StringBuilder:append	(Ljava/lang/String;)Ljava/lang/StringBuilder;
    //   504: aload 10
    //   506: invokevirtual 289	com/meizu/android/mms/pdu/MzGenericPdu:getMessageType	()I
    //   509: invokevirtual 296	java/lang/StringBuilder:append	(I)Ljava/lang/StringBuilder;
    //   512: invokevirtual 218	java/lang/StringBuilder:toString	()Ljava/lang/String;
    //   515: astore 6
    //   517: ldc 66
    //   519: aload 7
    //   521: aload 6
    //   523: invokevirtual 211	java/lang/StringBuilder:append	(Ljava/lang/String;)Ljava/lang/StringBuilder;
    //   526: invokevirtual 218	java/lang/StringBuilder:toString	()Ljava/lang/String;
    //   529: invokestatic 298	android/util/Log:e	(Ljava/lang/String;Ljava/lang/String;)I
    //   532: pop
    //   533: aload_0
    //   534: getfield 229	pl:d	Lpa;
    //   537: iconst_2
    //   538: invokevirtual 237	pa:a	(I)V
    //   541: sipush 132
    //   544: istore_1
    //   545: iload_1
    //   546: istore_2
    //   547: ldc 66
    //   549: new 203	java/lang/StringBuilder
    //   552: dup
    //   553: invokespecial 205	java/lang/StringBuilder:<init>	()V
    //   556: ldc_w 300
    //   559: invokevirtual 211	java/lang/StringBuilder:append	(Ljava/lang/String;)Ljava/lang/StringBuilder;
    //   562: iload_1
    //   563: invokestatic 305	java/lang/Integer:toHexString	(I)Ljava/lang/String;
    //   566: invokevirtual 211	java/lang/StringBuilder:append	(Ljava/lang/String;)Ljava/lang/StringBuilder;
    //   569: invokevirtual 218	java/lang/StringBuilder:toString	()Ljava/lang/String;
    //   572: invokestatic 222	android/util/Log:v	(Ljava/lang/String;Ljava/lang/String;)I
    //   575: pop
    //   576: iload_1
    //   577: tableswitch	default:+834->1411, 129:+621->1198, 130:+27->604, 131:+634->1211
    //   604: iload_1
    //   605: istore_2
    //   606: aload_0
    //   607: getfield 29	pl:b	Landroid/content/Context;
    //   610: invokestatic 310	aat:c	(Landroid/content/Context;)V
    //   613: iload_1
    //   614: istore_2
    //   615: aload_0
    //   616: getfield 29	pl:b	Landroid/content/Context;
    //   619: invokestatic 314	aev:a	(Landroid/content/Context;)V
    //   622: iload_1
    //   623: sipush 129
    //   626: if_icmpeq +16 -> 642
    //   629: aload 9
    //   631: aload_0
    //   632: getfield 25	pl:g	Landroid/net/Uri;
    //   635: sipush 130
    //   638: iconst_m1
    //   639: invokevirtual 225	zn:a	(Landroid/net/Uri;II)V
    //   642: aload_0
    //   643: getfield 229	pl:d	Lpa;
    //   646: aload_0
    //   647: getfield 25	pl:g	Landroid/net/Uri;
    //   650: invokevirtual 234	pa:a	(Landroid/net/Uri;)V
    //   653: iload 5
    //   655: ifne +11 -> 666
    //   658: aload_0
    //   659: getfield 229	pl:d	Lpa;
    //   662: iconst_1
    //   663: invokevirtual 237	pa:a	(I)V
    //   666: aload_0
    //   667: getfield 229	pl:d	Lpa;
    //   670: invokevirtual 239	pa:a	()I
    //   673: iconst_1
    //   674: if_icmpeq +642 -> 1316
    //   677: aload_0
    //   678: getfield 229	pl:d	Lpa;
    //   681: iconst_2
    //   682: invokevirtual 237	pa:a	(I)V
    //   685: ldc 66
    //   687: ldc -15
    //   689: invokestatic 243	android/util/Log:d	(Ljava/lang/String;Ljava/lang/String;)I
    //   692: pop
    //   693: aload_0
    //   694: invokevirtual 245	pl:d	()V
    //   697: return
    //   698: ldc_w 316
    //   701: astore 6
    //   703: goto -186 -> 517
    //   706: aload_0
    //   707: getfield 29	pl:b	Landroid/content/Context;
    //   710: invokestatic 35	com/meizu/android/mms/pdu/MzPduPersister:getPduPersister	(Landroid/content/Context;)Lcom/meizu/android/mms/pdu/MzPduPersister;
    //   713: astore 11
    //   715: ldc_w 318
    //   718: astore 7
    //   720: aload_0
    //   721: getfield 29	pl:b	Landroid/content/Context;
    //   724: invokevirtual 165	android/content/Context:getContentResolver	()Landroid/content/ContentResolver;
    //   727: aload_0
    //   728: getfield 25	pl:g	Landroid/net/Uri;
    //   731: iconst_4
    //   732: anewarray 112	java/lang/String
    //   735: dup
    //   736: iconst_0
    //   737: ldc -89
    //   739: aastore
    //   740: dup
    //   741: iconst_1
    //   742: ldc -85
    //   744: aastore
    //   745: dup
    //   746: iconst_2
    //   747: ldc -87
    //   749: aastore
    //   750: dup
    //   751: iconst_3
    //   752: ldc_w 320
    //   755: aastore
    //   756: aconst_null
    //   757: aconst_null
    //   758: aconst_null
    //   759: invokevirtual 177	android/content/ContentResolver:query	(Landroid/net/Uri;[Ljava/lang/String;Ljava/lang/String;[Ljava/lang/String;Ljava/lang/String;)Landroid/database/Cursor;
    //   762: astore 12
    //   764: aload 12
    //   766: ifnull +605 -> 1371
    //   769: aload 12
    //   771: invokeinterface 182 1 0
    //   776: ifle +578 -> 1354
    //   779: aload 12
    //   781: invokeinterface 186 1 0
    //   786: ifeq +568 -> 1354
    //   789: aload 12
    //   791: aload 12
    //   793: ldc -85
    //   795: invokeinterface 190 2 0
    //   800: invokeinterface 198 2 0
    //   805: lstore_3
    //   806: aload 12
    //   808: aload 12
    //   810: ldc -87
    //   812: invokeinterface 190 2 0
    //   817: invokeinterface 194 2 0
    //   822: astore 7
    //   824: aload 12
    //   826: aload 12
    //   828: ldc_w 320
    //   831: invokeinterface 190 2 0
    //   836: invokeinterface 194 2 0
    //   841: astore 6
    //   843: aload 12
    //   845: invokeinterface 201 1 0
    //   850: new 322	android/content/ContentValues
    //   853: dup
    //   854: iconst_4
    //   855: invokespecial 324	android/content/ContentValues:<init>	(I)V
    //   858: astore 8
    //   860: aload 8
    //   862: ldc -85
    //   864: lload_3
    //   865: invokestatic 329	java/lang/Long:valueOf	(J)Ljava/lang/Long;
    //   868: invokevirtual 333	android/content/ContentValues:put	(Ljava/lang/String;Ljava/lang/Long;)V
    //   871: aload 8
    //   873: ldc -87
    //   875: aload 7
    //   877: invokevirtual 336	android/content/ContentValues:put	(Ljava/lang/String;Ljava/lang/String;)V
    //   880: aload 8
    //   882: ldc_w 338
    //   885: aload_0
    //   886: getfield 58	pl:h	I
    //   889: invokestatic 341	java/lang/Integer:valueOf	(I)Ljava/lang/Integer;
    //   892: invokevirtual 344	android/content/ContentValues:put	(Ljava/lang/String;Ljava/lang/Integer;)V
    //   895: aload 8
    //   897: ldc_w 320
    //   900: aload 6
    //   902: invokevirtual 336	android/content/ContentValues:put	(Ljava/lang/String;Ljava/lang/String;)V
    //   905: aload 8
    //   907: ldc_w 346
    //   910: aload_0
    //   911: invokevirtual 349	pl:m	()J
    //   914: invokestatic 329	java/lang/Long:valueOf	(J)Ljava/lang/Long;
    //   917: invokevirtual 333	android/content/ContentValues:put	(Ljava/lang/String;Ljava/lang/Long;)V
    //   920: aload 8
    //   922: ldc_w 351
    //   925: new 326	java/lang/Long
    //   928: dup
    //   929: invokestatic 356	java/lang/System:currentTimeMillis	()J
    //   932: invokespecial 359	java/lang/Long:<init>	(J)V
    //   935: invokevirtual 333	android/content/ContentValues:put	(Ljava/lang/String;Ljava/lang/Long;)V
    //   938: aload 8
    //   940: ldc_w 361
    //   943: iconst_0
    //   944: invokestatic 365	zv:c	(I)Ljava/lang/String;
    //   947: invokevirtual 336	android/content/ContentValues:put	(Ljava/lang/String;Ljava/lang/String;)V
    //   950: ldc 66
    //   952: new 203	java/lang/StringBuilder
    //   955: dup
    //   956: invokespecial 205	java/lang/StringBuilder:<init>	()V
    //   959: ldc_w 367
    //   962: invokevirtual 211	java/lang/StringBuilder:append	(Ljava/lang/String;)Ljava/lang/StringBuilder;
    //   965: aload_0
    //   966: invokevirtual 349	pl:m	()J
    //   969: invokevirtual 370	java/lang/StringBuilder:append	(J)Ljava/lang/StringBuilder;
    //   972: ldc_w 372
    //   975: invokevirtual 211	java/lang/StringBuilder:append	(Ljava/lang/String;)Ljava/lang/StringBuilder;
    //   978: lload_3
    //   979: invokevirtual 370	java/lang/StringBuilder:append	(J)Ljava/lang/StringBuilder;
    //   982: invokevirtual 218	java/lang/StringBuilder:toString	()Ljava/lang/String;
    //   985: invokestatic 243	android/util/Log:d	(Ljava/lang/String;Ljava/lang/String;)I
    //   988: pop
    //   989: aload 11
    //   991: aload 10
    //   993: getstatic 377	android/provider/Telephony$Mms$Inbox:CONTENT_URI	Landroid/net/Uri;
    //   996: iconst_1
    //   997: aload_0
    //   998: getfield 29	pl:b	Landroid/content/Context;
    //   1001: invokestatic 381	com/android/mms/ui/MessagingPreferenceActivity:b	(Landroid/content/Context;)Z
    //   1004: aconst_null
    //   1005: aload_0
    //   1006: getfield 58	pl:h	I
    //   1009: aload 8
    //   1011: invokevirtual 385	com/meizu/android/mms/pdu/MzPduPersister:persist	(Lcom/meizu/android/mms/pdu/MzGenericPdu;Landroid/net/Uri;ZZLjava/util/HashMap;ILandroid/content/ContentValues;)Landroid/net/Uri;
    //   1014: astore 6
    //   1016: aload_0
    //   1017: getfield 29	pl:b	Landroid/content/Context;
    //   1020: invokevirtual 165	android/content/Context:getContentResolver	()Landroid/content/ContentResolver;
    //   1023: aload_0
    //   1024: getfield 25	pl:g	Landroid/net/Uri;
    //   1027: ldc_w 387
    //   1030: aconst_null
    //   1031: invokevirtual 391	android/content/ContentResolver:delete	(Landroid/net/Uri;Ljava/lang/String;[Ljava/lang/String;)I
    //   1034: pop
    //   1035: aload_0
    //   1036: getfield 29	pl:b	Landroid/content/Context;
    //   1039: invokevirtual 165	android/content/Context:getContentResolver	()Landroid/content/ContentResolver;
    //   1042: getstatic 396	android/provider/Telephony$Threads:OBSOLETE_THREADS_URI	Landroid/net/Uri;
    //   1045: aconst_null
    //   1046: aconst_null
    //   1047: invokevirtual 391	android/content/ContentResolver:delete	(Landroid/net/Uri;Ljava/lang/String;[Ljava/lang/String;)I
    //   1050: pop
    //   1051: ldc 66
    //   1053: new 203	java/lang/StringBuilder
    //   1056: dup
    //   1057: invokespecial 205	java/lang/StringBuilder:<init>	()V
    //   1060: ldc_w 398
    //   1063: invokevirtual 211	java/lang/StringBuilder:append	(Ljava/lang/String;)Ljava/lang/StringBuilder;
    //   1066: aload 6
    //   1068: invokevirtual 214	java/lang/StringBuilder:append	(Ljava/lang/Object;)Ljava/lang/StringBuilder;
    //   1071: invokevirtual 218	java/lang/StringBuilder:toString	()Ljava/lang/String;
    //   1074: invokestatic 222	android/util/Log:v	(Ljava/lang/String;Ljava/lang/String;)I
    //   1077: pop
    //   1078: aload_0
    //   1079: aload 6
    //   1081: putfield 25	pl:g	Landroid/net/Uri;
    //   1084: sipush 129
    //   1087: istore_1
    //   1088: goto -543 -> 545
    //   1091: astore 6
    //   1093: aload 12
    //   1095: invokeinterface 201 1 0
    //   1100: aload 6
    //   1102: athrow
    //   1103: astore 6
    //   1105: sipush 131
    //   1108: istore_1
    //   1109: iload_1
    //   1110: istore_2
    //   1111: ldc 66
    //   1113: aload 6
    //   1115: invokestatic 402	android/util/Log:getStackTraceString	(Ljava/lang/Throwable;)Ljava/lang/String;
    //   1118: invokestatic 298	android/util/Log:e	(Ljava/lang/String;Ljava/lang/String;)I
    //   1121: pop
    //   1122: iload_1
    //   1123: sipush 129
    //   1126: if_icmpeq +16 -> 1142
    //   1129: aload 9
    //   1131: aload_0
    //   1132: getfield 25	pl:g	Landroid/net/Uri;
    //   1135: sipush 130
    //   1138: iconst_m1
    //   1139: invokevirtual 225	zn:a	(Landroid/net/Uri;II)V
    //   1142: aload_0
    //   1143: getfield 229	pl:d	Lpa;
    //   1146: aload_0
    //   1147: getfield 25	pl:g	Landroid/net/Uri;
    //   1150: invokevirtual 234	pa:a	(Landroid/net/Uri;)V
    //   1153: iload 5
    //   1155: ifne +11 -> 1166
    //   1158: aload_0
    //   1159: getfield 229	pl:d	Lpa;
    //   1162: iconst_1
    //   1163: invokevirtual 237	pa:a	(I)V
    //   1166: aload_0
    //   1167: getfield 229	pl:d	Lpa;
    //   1170: invokevirtual 239	pa:a	()I
    //   1173: iconst_1
    //   1174: if_icmpeq +153 -> 1327
    //   1177: aload_0
    //   1178: getfield 229	pl:d	Lpa;
    //   1181: iconst_2
    //   1182: invokevirtual 237	pa:a	(I)V
    //   1185: ldc 66
    //   1187: ldc -15
    //   1189: invokestatic 243	android/util/Log:d	(Ljava/lang/String;Ljava/lang/String;)I
    //   1192: pop
    //   1193: aload_0
    //   1194: invokevirtual 245	pl:d	()V
    //   1197: return
    //   1198: iload_1
    //   1199: istore_2
    //   1200: aload_0
    //   1201: getfield 229	pl:d	Lpa;
    //   1204: iconst_1
    //   1205: invokevirtual 237	pa:a	(I)V
    //   1208: goto -604 -> 604
    //   1211: iload_1
    //   1212: istore_2
    //   1213: aload_0
    //   1214: getfield 229	pl:d	Lpa;
    //   1217: invokevirtual 239	pa:a	()I
    //   1220: ifne -616 -> 604
    //   1223: iload_1
    //   1224: istore_2
    //   1225: aload_0
    //   1226: getfield 229	pl:d	Lpa;
    //   1229: iconst_1
    //   1230: invokevirtual 237	pa:a	(I)V
    //   1233: goto -629 -> 604
    //   1236: astore 6
    //   1238: iload_2
    //   1239: sipush 129
    //   1242: if_icmpeq +16 -> 1258
    //   1245: aload 9
    //   1247: aload_0
    //   1248: getfield 25	pl:g	Landroid/net/Uri;
    //   1251: sipush 130
    //   1254: iconst_m1
    //   1255: invokevirtual 225	zn:a	(Landroid/net/Uri;II)V
    //   1258: aload_0
    //   1259: getfield 229	pl:d	Lpa;
    //   1262: aload_0
    //   1263: getfield 25	pl:g	Landroid/net/Uri;
    //   1266: invokevirtual 234	pa:a	(Landroid/net/Uri;)V
    //   1269: iload 5
    //   1271: ifne +11 -> 1282
    //   1274: aload_0
    //   1275: getfield 229	pl:d	Lpa;
    //   1278: iconst_1
    //   1279: invokevirtual 237	pa:a	(I)V
    //   1282: aload_0
    //   1283: getfield 229	pl:d	Lpa;
    //   1286: invokevirtual 239	pa:a	()I
    //   1289: iconst_1
    //   1290: if_icmpeq +48 -> 1338
    //   1293: aload_0
    //   1294: getfield 229	pl:d	Lpa;
    //   1297: iconst_2
    //   1298: invokevirtual 237	pa:a	(I)V
    //   1301: ldc 66
    //   1303: ldc -15
    //   1305: invokestatic 243	android/util/Log:d	(Ljava/lang/String;Ljava/lang/String;)I
    //   1308: pop
    //   1309: aload_0
    //   1310: invokevirtual 245	pl:d	()V
    //   1313: aload 6
    //   1315: athrow
    //   1316: ldc 66
    //   1318: ldc -9
    //   1320: invokestatic 243	android/util/Log:d	(Ljava/lang/String;Ljava/lang/String;)I
    //   1323: pop
    //   1324: goto -631 -> 693
    //   1327: ldc 66
    //   1329: ldc -9
    //   1331: invokestatic 243	android/util/Log:d	(Ljava/lang/String;Ljava/lang/String;)I
    //   1334: pop
    //   1335: goto -142 -> 1193
    //   1338: ldc 66
    //   1340: ldc -9
    //   1342: invokestatic 243	android/util/Log:d	(Ljava/lang/String;Ljava/lang/String;)I
    //   1345: pop
    //   1346: goto -37 -> 1309
    //   1349: astore 6
    //   1351: goto -113 -> 1238
    //   1354: aload 6
    //   1356: astore 8
    //   1358: lconst_0
    //   1359: lstore_3
    //   1360: aload 7
    //   1362: astore 6
    //   1364: aload 8
    //   1366: astore 7
    //   1368: goto -525 -> 843
    //   1371: aload 6
    //   1373: astore 8
    //   1375: lconst_0
    //   1376: lstore_3
    //   1377: aload 7
    //   1379: astore 6
    //   1381: aload 8
    //   1383: astore 7
    //   1385: goto -535 -> 850
    //   1388: sipush 131
    //   1391: istore_1
    //   1392: goto -847 -> 545
    //   1395: ldc_w 404
    //   1398: astore 6
    //   1400: goto -1268 -> 132
    //   1403: ldc_w 404
    //   1406: astore 6
    //   1408: goto -1269 -> 139
    //   1411: goto -807 -> 604
    //   1414: astore 6
    //   1416: goto -307 -> 1109
    // Local variable table:
    //   start	length	slot	name	signature
    //   0	1419	0	this	pl
    //   19	1373	1	i	int
    //   142	1101	2	j	int
    //   24	1353	3	l	long
    //   32	1238	5	bool	boolean
    //   113	1	6	str1	String
    //   264	126	6	str2	String
    //   515	565	6	localObject1	Object
    //   1091	10	6	localObject2	Object
    //   1103	11	6	localThrowable1	Throwable
    //   1236	78	6	localObject3	Object
    //   1349	6	6	localObject4	Object
    //   1362	45	6	localObject5	Object
    //   1414	1	6	localThrowable2	Throwable
    //   70	1314	7	localObject6	Object
    //   367	1015	8	localObject7	Object
    //   3	1243	9	localzn	zn
    //   453	539	10	localMzGenericPdu	com.meizu.android.mms.pdu.MzGenericPdu
    //   713	277	11	localMzPduPersister	MzPduPersister
    //   762	332	12	localCursor	android.database.Cursor
    // Exception table:
    //   from	to	target	type
    //   77	132	264	finally
    //   769	843	1091	finally
    //   143	168	1103	java/lang/Throwable
    //   177	190	1103	java/lang/Throwable
    //   287	432	1103	java/lang/Throwable
    //   437	455	1103	java/lang/Throwable
    //   460	471	1103	java/lang/Throwable
    //   471	486	1103	java/lang/Throwable
    //   491	517	1103	java/lang/Throwable
    //   517	541	1103	java/lang/Throwable
    //   706	715	1103	java/lang/Throwable
    //   720	764	1103	java/lang/Throwable
    //   843	850	1103	java/lang/Throwable
    //   850	1084	1103	java/lang/Throwable
    //   1093	1103	1103	java/lang/Throwable
    //   547	576	1236	finally
    //   606	613	1236	finally
    //   615	622	1236	finally
    //   1111	1122	1236	finally
    //   1200	1208	1236	finally
    //   1213	1223	1236	finally
    //   1225	1233	1236	finally
    //   143	168	1349	finally
    //   177	190	1349	finally
    //   287	432	1349	finally
    //   437	455	1349	finally
    //   460	471	1349	finally
    //   471	486	1349	finally
    //   491	517	1349	finally
    //   517	541	1349	finally
    //   706	715	1349	finally
    //   720	764	1349	finally
    //   843	850	1349	finally
    //   850	1084	1349	finally
    //   1093	1103	1349	finally
    //   547	576	1414	java/lang/Throwable
    //   606	613	1414	java/lang/Throwable
    //   615	622	1414	java/lang/Throwable
    //   1200	1208	1414	java/lang/Throwable
    //   1213	1223	1414	java/lang/Throwable
    //   1225	1233	1414	java/lang/Throwable
  }
}

/* Location:
 * Qualified Name:     pl
 * Java Class Version: 6 (50.0)
 * JD-Core Version:    0.7.1
 */