import android.content.Context;
import android.net.Uri;
import android.util.Log;
import org.json.JSONException;
import org.json.JSONObject;

public class pn
  extends ow
  implements Runnable
{
  private Thread a;
  
  public pn(Context paramContext, int paramInt1, oz paramoz, String paramString, int paramInt2)
  {
    super(paramContext, paramInt1, paramoz);
    g = Uri.parse(paramString);
    c = paramString;
    h = paramInt2;
    if ((h == 2) || (h == 3)) {
      l = a(g);
    }
    for (;;)
    {
      b(g);
      return;
      l = "";
      a(or.a(paramContext));
    }
  }
  
  private pn.a a(String paramString)
  {
    pn.a locala = new pn.a();
    try
    {
      JSONObject localJSONObject = new JSONObject(paramString);
      if (localJSONObject.has("id")) {
        e = localJSONObject.getString("id");
      }
      if (localJSONObject.has("fid")) {
        d = localJSONObject.getString("fid");
      }
      if (localJSONObject.has("error_code")) {
        b = localJSONObject.getInt("error_code");
      }
      if (localJSONObject.has("uuid")) {
        a = localJSONObject.getString("uuid");
      }
      if (localJSONObject.has("error_msg")) {
        c = localJSONObject.getString("error_msg");
      }
      return locala;
    }
    catch (JSONException localJSONException)
    {
      localJSONException.printStackTrace();
      Log.e("SendTransaction", "decodeSnsAttachmentInfo contentStr wrong, contentStr is " + paramString);
    }
    return null;
  }
  
  public void a()
  {
    a = new Thread(this, "SendTransaction");
    a.start();
  }
  
  public int c()
  {
    return 2;
  }
  
  /* Error */
  public void run()
  {
    // Byte code:
    //   0: aload_0
    //   1: getfield 140	pn:b	Landroid/content/Context;
    //   4: invokestatic 146	com/meizu/android/mms/pdu/MzPduPersister:getPduPersister	(Landroid/content/Context;)Lcom/meizu/android/mms/pdu/MzPduPersister;
    //   7: astore 6
    //   9: aload 6
    //   11: aload_0
    //   12: getfield 25	pn:g	Landroid/net/Uri;
    //   15: invokevirtual 150	com/meizu/android/mms/pdu/MzPduPersister:load	(Landroid/net/Uri;)Lcom/meizu/android/mms/pdu/MzGenericPdu;
    //   18: checkcast 152	com/meizu/android/mms/pdu/MzSendReq
    //   21: astore 7
    //   23: invokestatic 158	java/lang/System:currentTimeMillis	()J
    //   26: ldc2_w 159
    //   29: ldiv
    //   30: lstore_1
    //   31: aload 7
    //   33: lload_1
    //   34: invokevirtual 164	com/meizu/android/mms/pdu/MzSendReq:setDate	(J)V
    //   37: new 166	android/content/ContentValues
    //   40: dup
    //   41: iconst_1
    //   42: invokespecial 169	android/content/ContentValues:<init>	(I)V
    //   45: astore 4
    //   47: aload 4
    //   49: ldc -85
    //   51: lload_1
    //   52: invokestatic 177	java/lang/Long:valueOf	(J)Ljava/lang/Long;
    //   55: invokevirtual 181	android/content/ContentValues:put	(Ljava/lang/String;Ljava/lang/Long;)V
    //   58: aload_0
    //   59: getfield 140	pn:b	Landroid/content/Context;
    //   62: invokevirtual 187	android/content/Context:getContentResolver	()Landroid/content/ContentResolver;
    //   65: aload_0
    //   66: getfield 25	pn:g	Landroid/net/Uri;
    //   69: aload 4
    //   71: aconst_null
    //   72: aconst_null
    //   73: invokevirtual 193	android/content/ContentResolver:update	(Landroid/net/Uri;Landroid/content/ContentValues;Ljava/lang/String;[Ljava/lang/String;)I
    //   76: pop
    //   77: invokestatic 197	wd:a	()Ljava/lang/String;
    //   80: astore 4
    //   82: aload 4
    //   84: invokestatic 203	android/text/TextUtils:isEmpty	(Ljava/lang/CharSequence;)Z
    //   87: ifne +17 -> 104
    //   90: aload 7
    //   92: new 205	com/meizu/android/mms/pdu/MzEncodedStringValue
    //   95: dup
    //   96: aload 4
    //   98: invokespecial 206	com/meizu/android/mms/pdu/MzEncodedStringValue:<init>	(Ljava/lang/String;)V
    //   101: invokevirtual 210	com/meizu/android/mms/pdu/MzSendReq:setFrom	(Lcom/meizu/android/mms/pdu/MzEncodedStringValue;)V
    //   104: ldc 104
    //   106: new 106	java/lang/StringBuilder
    //   109: dup
    //   110: invokespecial 108	java/lang/StringBuilder:<init>	()V
    //   113: ldc -44
    //   115: invokevirtual 114	java/lang/StringBuilder:append	(Ljava/lang/String;)Ljava/lang/StringBuilder;
    //   118: aload_0
    //   119: getfield 215	pn:m	I
    //   122: invokevirtual 218	java/lang/StringBuilder:append	(I)Ljava/lang/StringBuilder;
    //   125: ldc -36
    //   127: invokevirtual 114	java/lang/StringBuilder:append	(Ljava/lang/String;)Ljava/lang/StringBuilder;
    //   130: aload_0
    //   131: getfield 25	pn:g	Landroid/net/Uri;
    //   134: invokevirtual 221	android/net/Uri:toString	()Ljava/lang/String;
    //   137: invokevirtual 114	java/lang/StringBuilder:append	(Ljava/lang/String;)Ljava/lang/StringBuilder;
    //   140: invokevirtual 118	java/lang/StringBuilder:toString	()Ljava/lang/String;
    //   143: invokestatic 223	android/util/Log:d	(Ljava/lang/String;Ljava/lang/String;)I
    //   146: pop
    //   147: ldc -31
    //   149: astore 5
    //   151: aload_0
    //   152: getfield 140	pn:b	Landroid/content/Context;
    //   155: invokevirtual 187	android/content/Context:getContentResolver	()Landroid/content/ContentResolver;
    //   158: aload_0
    //   159: getfield 25	pn:g	Landroid/net/Uri;
    //   162: iconst_3
    //   163: anewarray 227	java/lang/String
    //   166: dup
    //   167: iconst_0
    //   168: ldc -27
    //   170: aastore
    //   171: dup
    //   172: iconst_1
    //   173: ldc -25
    //   175: aastore
    //   176: dup
    //   177: iconst_2
    //   178: ldc -23
    //   180: aastore
    //   181: aconst_null
    //   182: aconst_null
    //   183: aconst_null
    //   184: invokevirtual 237	android/content/ContentResolver:query	(Landroid/net/Uri;[Ljava/lang/String;Ljava/lang/String;[Ljava/lang/String;Ljava/lang/String;)Landroid/database/Cursor;
    //   187: astore 8
    //   189: aload 8
    //   191: ifnull +1064 -> 1255
    //   194: aload 8
    //   196: invokeinterface 242 1 0
    //   201: ifle +1047 -> 1248
    //   204: aload 8
    //   206: invokeinterface 246 1 0
    //   211: ifeq +1037 -> 1248
    //   214: aload 8
    //   216: aload 8
    //   218: ldc -25
    //   220: invokeinterface 249 2 0
    //   225: invokeinterface 252 2 0
    //   230: astore 4
    //   232: aload 8
    //   234: aload 8
    //   236: ldc -23
    //   238: invokeinterface 249 2 0
    //   243: invokeinterface 252 2 0
    //   248: astore 5
    //   250: aload 8
    //   252: invokeinterface 255 1 0
    //   257: invokestatic 260	abh:a	()Labh;
    //   260: astore 8
    //   262: aload 7
    //   264: invokevirtual 264	com/meizu/android/mms/pdu/MzSendReq:getTo	()[Lcom/meizu/android/mms/pdu/MzEncodedStringValue;
    //   267: invokestatic 268	com/meizu/android/mms/pdu/MzEncodedStringValue:concat	([Lcom/meizu/android/mms/pdu/MzEncodedStringValue;)Ljava/lang/String;
    //   270: astore 9
    //   272: aload_0
    //   273: getfield 39	pn:l	Ljava/lang/String;
    //   276: astore 10
    //   278: new 270	com/meizu/android/mms/pdu/MzPduComposer
    //   281: dup
    //   282: aload_0
    //   283: getfield 140	pn:b	Landroid/content/Context;
    //   286: aload 7
    //   288: iconst_3
    //   289: invokespecial 273	com/meizu/android/mms/pdu/MzPduComposer:<init>	(Landroid/content/Context;Lcom/meizu/android/mms/pdu/MzGenericPdu;I)V
    //   292: invokevirtual 277	com/meizu/android/mms/pdu/MzPduComposer:make	()[B
    //   295: astore 11
    //   297: aload 7
    //   299: invokevirtual 280	com/meizu/android/mms/pdu/MzSendReq:getDeliveryReport	()I
    //   302: sipush 128
    //   305: if_icmpne +387 -> 692
    //   308: iconst_1
    //   309: istore_3
    //   310: aload 8
    //   312: aload 9
    //   314: aconst_null
    //   315: aload 10
    //   317: aload 11
    //   319: aload 4
    //   321: iload_3
    //   322: aload 5
    //   324: invokevirtual 283	abh:a	(Ljava/lang/String;Ljava/lang/String;Ljava/lang/String;[BLjava/lang/String;ZLjava/lang/String;)Ljava/lang/String;
    //   327: astore 4
    //   329: ldc 104
    //   331: new 106	java/lang/StringBuilder
    //   334: dup
    //   335: invokespecial 108	java/lang/StringBuilder:<init>	()V
    //   338: ldc_w 285
    //   341: invokevirtual 114	java/lang/StringBuilder:append	(Ljava/lang/String;)Ljava/lang/StringBuilder;
    //   344: aload_0
    //   345: getfield 215	pn:m	I
    //   348: invokevirtual 218	java/lang/StringBuilder:append	(I)Ljava/lang/StringBuilder;
    //   351: ldc -36
    //   353: invokevirtual 114	java/lang/StringBuilder:append	(Ljava/lang/String;)Ljava/lang/StringBuilder;
    //   356: aload_0
    //   357: getfield 25	pn:g	Landroid/net/Uri;
    //   360: invokevirtual 221	android/net/Uri:toString	()Ljava/lang/String;
    //   363: invokevirtual 114	java/lang/StringBuilder:append	(Ljava/lang/String;)Ljava/lang/StringBuilder;
    //   366: invokevirtual 118	java/lang/StringBuilder:toString	()Ljava/lang/String;
    //   369: invokestatic 223	android/util/Log:d	(Ljava/lang/String;Ljava/lang/String;)I
    //   372: pop
    //   373: aload 4
    //   375: invokestatic 203	android/text/TextUtils:isEmpty	(Ljava/lang/CharSequence;)Z
    //   378: ifeq +319 -> 697
    //   381: new 287	java/io/IOException
    //   384: dup
    //   385: ldc_w 289
    //   388: invokespecial 290	java/io/IOException:<init>	(Ljava/lang/String;)V
    //   391: athrow
    //   392: astore 4
    //   394: ldc 104
    //   396: aload 4
    //   398: invokestatic 294	android/util/Log:getStackTraceString	(Ljava/lang/Throwable;)Ljava/lang/String;
    //   401: invokestatic 123	android/util/Log:e	(Ljava/lang/String;Ljava/lang/String;)I
    //   404: pop
    //   405: new 166	android/content/ContentValues
    //   408: dup
    //   409: iconst_2
    //   410: invokespecial 169	android/content/ContentValues:<init>	(I)V
    //   413: astore 4
    //   415: aload 4
    //   417: ldc_w 296
    //   420: sipush 134
    //   423: invokestatic 301	java/lang/Integer:valueOf	(I)Ljava/lang/Integer;
    //   426: invokevirtual 304	android/content/ContentValues:put	(Ljava/lang/String;Ljava/lang/Integer;)V
    //   429: aload_0
    //   430: getfield 140	pn:b	Landroid/content/Context;
    //   433: invokevirtual 187	android/content/Context:getContentResolver	()Landroid/content/ContentResolver;
    //   436: aload_0
    //   437: getfield 25	pn:g	Landroid/net/Uri;
    //   440: aload 4
    //   442: aconst_null
    //   443: aconst_null
    //   444: invokevirtual 193	android/content/ContentResolver:update	(Landroid/net/Uri;Landroid/content/ContentValues;Ljava/lang/String;[Ljava/lang/String;)I
    //   447: pop
    //   448: new 166	android/content/ContentValues
    //   451: dup
    //   452: iconst_1
    //   453: invokespecial 169	android/content/ContentValues:<init>	(I)V
    //   456: astore 4
    //   458: aload_0
    //   459: getfield 25	pn:g	Landroid/net/Uri;
    //   462: invokestatic 310	android/content/ContentUris:parseId	(Landroid/net/Uri;)J
    //   465: lstore_1
    //   466: aload 4
    //   468: ldc_w 312
    //   471: bipush 19
    //   473: invokestatic 301	java/lang/Integer:valueOf	(I)Ljava/lang/Integer;
    //   476: invokevirtual 304	android/content/ContentValues:put	(Ljava/lang/String;Ljava/lang/Integer;)V
    //   479: aload_0
    //   480: getfield 140	pn:b	Landroid/content/Context;
    //   483: invokevirtual 187	android/content/Context:getContentResolver	()Landroid/content/ContentResolver;
    //   486: getstatic 317	android/provider/Telephony$MmsSms$PendingMessages:CONTENT_URI	Landroid/net/Uri;
    //   489: aload 4
    //   491: new 106	java/lang/StringBuilder
    //   494: dup
    //   495: invokespecial 108	java/lang/StringBuilder:<init>	()V
    //   498: ldc_w 319
    //   501: invokevirtual 114	java/lang/StringBuilder:append	(Ljava/lang/String;)Ljava/lang/StringBuilder;
    //   504: lload_1
    //   505: invokevirtual 322	java/lang/StringBuilder:append	(J)Ljava/lang/StringBuilder;
    //   508: invokevirtual 118	java/lang/StringBuilder:toString	()Ljava/lang/String;
    //   511: aconst_null
    //   512: invokevirtual 193	android/content/ContentResolver:update	(Landroid/net/Uri;Landroid/content/ContentValues;Ljava/lang/String;[Ljava/lang/String;)I
    //   515: pop
    //   516: aload_0
    //   517: getfield 325	pn:d	Lpa;
    //   520: invokevirtual 329	pa:a	()I
    //   523: iconst_1
    //   524: if_icmpeq +628 -> 1152
    //   527: aload_0
    //   528: getfield 325	pn:d	Lpa;
    //   531: iconst_2
    //   532: invokevirtual 331	pa:a	(I)V
    //   535: aload_0
    //   536: getfield 325	pn:d	Lpa;
    //   539: aload_0
    //   540: getfield 25	pn:g	Landroid/net/Uri;
    //   543: invokevirtual 333	pa:a	(Landroid/net/Uri;)V
    //   546: ldc 104
    //   548: new 106	java/lang/StringBuilder
    //   551: dup
    //   552: invokespecial 108	java/lang/StringBuilder:<init>	()V
    //   555: ldc_w 335
    //   558: invokevirtual 114	java/lang/StringBuilder:append	(Ljava/lang/String;)Ljava/lang/StringBuilder;
    //   561: aload_0
    //   562: getfield 215	pn:m	I
    //   565: invokevirtual 218	java/lang/StringBuilder:append	(I)Ljava/lang/StringBuilder;
    //   568: ldc_w 337
    //   571: invokevirtual 114	java/lang/StringBuilder:append	(Ljava/lang/String;)Ljava/lang/StringBuilder;
    //   574: aload_0
    //   575: getfield 25	pn:g	Landroid/net/Uri;
    //   578: invokevirtual 221	android/net/Uri:toString	()Ljava/lang/String;
    //   581: invokevirtual 114	java/lang/StringBuilder:append	(Ljava/lang/String;)Ljava/lang/StringBuilder;
    //   584: invokevirtual 118	java/lang/StringBuilder:toString	()Ljava/lang/String;
    //   587: invokestatic 223	android/util/Log:d	(Ljava/lang/String;Ljava/lang/String;)I
    //   590: pop
    //   591: aload_0
    //   592: invokevirtual 339	pn:d	()V
    //   595: return
    //   596: astore 4
    //   598: aload 8
    //   600: invokeinterface 255 1 0
    //   605: aload 4
    //   607: athrow
    //   608: astore 4
    //   610: aload_0
    //   611: getfield 325	pn:d	Lpa;
    //   614: invokevirtual 329	pa:a	()I
    //   617: iconst_1
    //   618: if_icmpeq +582 -> 1200
    //   621: aload_0
    //   622: getfield 325	pn:d	Lpa;
    //   625: iconst_2
    //   626: invokevirtual 331	pa:a	(I)V
    //   629: aload_0
    //   630: getfield 325	pn:d	Lpa;
    //   633: aload_0
    //   634: getfield 25	pn:g	Landroid/net/Uri;
    //   637: invokevirtual 333	pa:a	(Landroid/net/Uri;)V
    //   640: ldc 104
    //   642: new 106	java/lang/StringBuilder
    //   645: dup
    //   646: invokespecial 108	java/lang/StringBuilder:<init>	()V
    //   649: ldc_w 335
    //   652: invokevirtual 114	java/lang/StringBuilder:append	(Ljava/lang/String;)Ljava/lang/StringBuilder;
    //   655: aload_0
    //   656: getfield 215	pn:m	I
    //   659: invokevirtual 218	java/lang/StringBuilder:append	(I)Ljava/lang/StringBuilder;
    //   662: ldc_w 337
    //   665: invokevirtual 114	java/lang/StringBuilder:append	(Ljava/lang/String;)Ljava/lang/StringBuilder;
    //   668: aload_0
    //   669: getfield 25	pn:g	Landroid/net/Uri;
    //   672: invokevirtual 221	android/net/Uri:toString	()Ljava/lang/String;
    //   675: invokevirtual 114	java/lang/StringBuilder:append	(Ljava/lang/String;)Ljava/lang/StringBuilder;
    //   678: invokevirtual 118	java/lang/StringBuilder:toString	()Ljava/lang/String;
    //   681: invokestatic 223	android/util/Log:d	(Ljava/lang/String;Ljava/lang/String;)I
    //   684: pop
    //   685: aload_0
    //   686: invokevirtual 339	pn:d	()V
    //   689: aload 4
    //   691: athrow
    //   692: iconst_0
    //   693: istore_3
    //   694: goto -384 -> 310
    //   697: ldc 104
    //   699: new 106	java/lang/StringBuilder
    //   702: dup
    //   703: invokespecial 108	java/lang/StringBuilder:<init>	()V
    //   706: ldc_w 341
    //   709: invokevirtual 114	java/lang/StringBuilder:append	(Ljava/lang/String;)Ljava/lang/StringBuilder;
    //   712: aload 4
    //   714: invokevirtual 114	java/lang/StringBuilder:append	(Ljava/lang/String;)Ljava/lang/StringBuilder;
    //   717: invokevirtual 118	java/lang/StringBuilder:toString	()Ljava/lang/String;
    //   720: invokestatic 223	android/util/Log:d	(Ljava/lang/String;Ljava/lang/String;)I
    //   723: pop
    //   724: aload_0
    //   725: aload 4
    //   727: invokespecial 343	pn:a	(Ljava/lang/String;)Lpn$a;
    //   730: astore 4
    //   732: aload 4
    //   734: ifnonnull +14 -> 748
    //   737: new 287	java/io/IOException
    //   740: dup
    //   741: ldc_w 345
    //   744: invokespecial 290	java/io/IOException:<init>	(Ljava/lang/String;)V
    //   747: athrow
    //   748: aload 4
    //   750: getfield 91	pn$a:b	I
    //   753: ifeq +246 -> 999
    //   756: new 166	android/content/ContentValues
    //   759: dup
    //   760: iconst_2
    //   761: invokespecial 169	android/content/ContentValues:<init>	(I)V
    //   764: astore 5
    //   766: aload 5
    //   768: ldc_w 296
    //   771: sipush 9527
    //   774: invokestatic 301	java/lang/Integer:valueOf	(I)Ljava/lang/Integer;
    //   777: invokevirtual 304	android/content/ContentValues:put	(Ljava/lang/String;Ljava/lang/Integer;)V
    //   780: aload_0
    //   781: getfield 140	pn:b	Landroid/content/Context;
    //   784: invokevirtual 187	android/content/Context:getContentResolver	()Landroid/content/ContentResolver;
    //   787: aload_0
    //   788: getfield 25	pn:g	Landroid/net/Uri;
    //   791: aload 5
    //   793: aconst_null
    //   794: aconst_null
    //   795: invokevirtual 193	android/content/ContentResolver:update	(Landroid/net/Uri;Landroid/content/ContentValues;Ljava/lang/String;[Ljava/lang/String;)I
    //   798: pop
    //   799: new 166	android/content/ContentValues
    //   802: dup
    //   803: iconst_1
    //   804: invokespecial 169	android/content/ContentValues:<init>	(I)V
    //   807: astore 5
    //   809: aload_0
    //   810: getfield 25	pn:g	Landroid/net/Uri;
    //   813: invokestatic 310	android/content/ContentUris:parseId	(Landroid/net/Uri;)J
    //   816: lstore_1
    //   817: aload 5
    //   819: ldc_w 312
    //   822: bipush 19
    //   824: invokestatic 301	java/lang/Integer:valueOf	(I)Ljava/lang/Integer;
    //   827: invokevirtual 304	android/content/ContentValues:put	(Ljava/lang/String;Ljava/lang/Integer;)V
    //   830: aload_0
    //   831: getfield 140	pn:b	Landroid/content/Context;
    //   834: invokevirtual 187	android/content/Context:getContentResolver	()Landroid/content/ContentResolver;
    //   837: getstatic 317	android/provider/Telephony$MmsSms$PendingMessages:CONTENT_URI	Landroid/net/Uri;
    //   840: aload 5
    //   842: new 106	java/lang/StringBuilder
    //   845: dup
    //   846: invokespecial 108	java/lang/StringBuilder:<init>	()V
    //   849: ldc_w 319
    //   852: invokevirtual 114	java/lang/StringBuilder:append	(Ljava/lang/String;)Ljava/lang/StringBuilder;
    //   855: lload_1
    //   856: invokevirtual 322	java/lang/StringBuilder:append	(J)Ljava/lang/StringBuilder;
    //   859: invokevirtual 118	java/lang/StringBuilder:toString	()Ljava/lang/String;
    //   862: aconst_null
    //   863: invokevirtual 193	android/content/ContentResolver:update	(Landroid/net/Uri;Landroid/content/ContentValues;Ljava/lang/String;[Ljava/lang/String;)I
    //   866: pop
    //   867: aload_0
    //   868: getfield 140	pn:b	Landroid/content/Context;
    //   871: checkcast 347	com/android/mms/transaction/sns/SnsTransactionService
    //   874: getfield 350	com/android/mms/transaction/sns/SnsTransactionService:a	Landroid/os/Handler;
    //   877: iconst_1
    //   878: invokevirtual 356	android/os/Handler:obtainMessage	(I)Landroid/os/Message;
    //   881: astore 5
    //   883: aload 5
    //   885: aload_0
    //   886: getfield 140	pn:b	Landroid/content/Context;
    //   889: aload 4
    //   891: getfield 91	pn$a:b	I
    //   894: ldc_w 357
    //   897: invokestatic 362	abh$b:a	(Landroid/content/Context;II)Ljava/lang/String;
    //   900: putfield 368	android/os/Message:obj	Ljava/lang/Object;
    //   903: aload_0
    //   904: getfield 140	pn:b	Landroid/content/Context;
    //   907: checkcast 347	com/android/mms/transaction/sns/SnsTransactionService
    //   910: getfield 350	com/android/mms/transaction/sns/SnsTransactionService:a	Landroid/os/Handler;
    //   913: aload 5
    //   915: invokevirtual 372	android/os/Handler:sendMessage	(Landroid/os/Message;)Z
    //   918: pop
    //   919: aload_0
    //   920: getfield 325	pn:d	Lpa;
    //   923: invokevirtual 329	pa:a	()I
    //   926: iconst_1
    //   927: if_icmpeq +177 -> 1104
    //   930: aload_0
    //   931: getfield 325	pn:d	Lpa;
    //   934: iconst_2
    //   935: invokevirtual 331	pa:a	(I)V
    //   938: aload_0
    //   939: getfield 325	pn:d	Lpa;
    //   942: aload_0
    //   943: getfield 25	pn:g	Landroid/net/Uri;
    //   946: invokevirtual 333	pa:a	(Landroid/net/Uri;)V
    //   949: ldc 104
    //   951: new 106	java/lang/StringBuilder
    //   954: dup
    //   955: invokespecial 108	java/lang/StringBuilder:<init>	()V
    //   958: ldc_w 335
    //   961: invokevirtual 114	java/lang/StringBuilder:append	(Ljava/lang/String;)Ljava/lang/StringBuilder;
    //   964: aload_0
    //   965: getfield 215	pn:m	I
    //   968: invokevirtual 218	java/lang/StringBuilder:append	(I)Ljava/lang/StringBuilder;
    //   971: ldc_w 337
    //   974: invokevirtual 114	java/lang/StringBuilder:append	(Ljava/lang/String;)Ljava/lang/StringBuilder;
    //   977: aload_0
    //   978: getfield 25	pn:g	Landroid/net/Uri;
    //   981: invokevirtual 221	android/net/Uri:toString	()Ljava/lang/String;
    //   984: invokevirtual 114	java/lang/StringBuilder:append	(Ljava/lang/String;)Ljava/lang/StringBuilder;
    //   987: invokevirtual 118	java/lang/StringBuilder:toString	()Ljava/lang/String;
    //   990: invokestatic 223	android/util/Log:d	(Ljava/lang/String;Ljava/lang/String;)I
    //   993: pop
    //   994: aload_0
    //   995: invokevirtual 339	pn:d	()V
    //   998: return
    //   999: new 166	android/content/ContentValues
    //   1002: dup
    //   1003: iconst_3
    //   1004: invokespecial 169	android/content/ContentValues:<init>	(I)V
    //   1007: astore 5
    //   1009: aload 5
    //   1011: ldc_w 296
    //   1014: aload 4
    //   1016: getfield 91	pn$a:b	I
    //   1019: invokestatic 301	java/lang/Integer:valueOf	(I)Ljava/lang/Integer;
    //   1022: invokevirtual 304	android/content/ContentValues:put	(Ljava/lang/String;Ljava/lang/Integer;)V
    //   1025: aload 5
    //   1027: ldc_w 374
    //   1030: aload 4
    //   1032: getfield 78	pn$a:e	Ljava/lang/String;
    //   1035: invokevirtual 377	android/content/ContentValues:put	(Ljava/lang/String;Ljava/lang/String;)V
    //   1038: aload 5
    //   1040: ldc_w 379
    //   1043: aload 4
    //   1045: getfield 83	pn$a:d	Ljava/lang/String;
    //   1048: invokevirtual 377	android/content/ContentValues:put	(Ljava/lang/String;Ljava/lang/String;)V
    //   1051: aload_0
    //   1052: getfield 140	pn:b	Landroid/content/Context;
    //   1055: invokevirtual 187	android/content/Context:getContentResolver	()Landroid/content/ContentResolver;
    //   1058: aload_0
    //   1059: getfield 25	pn:g	Landroid/net/Uri;
    //   1062: aload 5
    //   1064: aconst_null
    //   1065: aconst_null
    //   1066: invokevirtual 193	android/content/ContentResolver:update	(Landroid/net/Uri;Landroid/content/ContentValues;Ljava/lang/String;[Ljava/lang/String;)I
    //   1069: pop
    //   1070: aload 6
    //   1072: aload_0
    //   1073: getfield 25	pn:g	Landroid/net/Uri;
    //   1076: getstatic 382	android/provider/Telephony$Mms$Sent:CONTENT_URI	Landroid/net/Uri;
    //   1079: invokevirtual 386	com/meizu/android/mms/pdu/MzPduPersister:move	(Landroid/net/Uri;Landroid/net/Uri;)Landroid/net/Uri;
    //   1082: astore 4
    //   1084: aload_0
    //   1085: getfield 325	pn:d	Lpa;
    //   1088: iconst_1
    //   1089: invokevirtual 331	pa:a	(I)V
    //   1092: aload_0
    //   1093: getfield 325	pn:d	Lpa;
    //   1096: aload 4
    //   1098: invokevirtual 333	pa:a	(Landroid/net/Uri;)V
    //   1101: goto -182 -> 919
    //   1104: ldc 104
    //   1106: new 106	java/lang/StringBuilder
    //   1109: dup
    //   1110: invokespecial 108	java/lang/StringBuilder:<init>	()V
    //   1113: ldc_w 335
    //   1116: invokevirtual 114	java/lang/StringBuilder:append	(Ljava/lang/String;)Ljava/lang/StringBuilder;
    //   1119: aload_0
    //   1120: getfield 215	pn:m	I
    //   1123: invokevirtual 218	java/lang/StringBuilder:append	(I)Ljava/lang/StringBuilder;
    //   1126: ldc_w 388
    //   1129: invokevirtual 114	java/lang/StringBuilder:append	(Ljava/lang/String;)Ljava/lang/StringBuilder;
    //   1132: aload_0
    //   1133: getfield 25	pn:g	Landroid/net/Uri;
    //   1136: invokevirtual 221	android/net/Uri:toString	()Ljava/lang/String;
    //   1139: invokevirtual 114	java/lang/StringBuilder:append	(Ljava/lang/String;)Ljava/lang/StringBuilder;
    //   1142: invokevirtual 118	java/lang/StringBuilder:toString	()Ljava/lang/String;
    //   1145: invokestatic 223	android/util/Log:d	(Ljava/lang/String;Ljava/lang/String;)I
    //   1148: pop
    //   1149: goto -155 -> 994
    //   1152: ldc 104
    //   1154: new 106	java/lang/StringBuilder
    //   1157: dup
    //   1158: invokespecial 108	java/lang/StringBuilder:<init>	()V
    //   1161: ldc_w 335
    //   1164: invokevirtual 114	java/lang/StringBuilder:append	(Ljava/lang/String;)Ljava/lang/StringBuilder;
    //   1167: aload_0
    //   1168: getfield 215	pn:m	I
    //   1171: invokevirtual 218	java/lang/StringBuilder:append	(I)Ljava/lang/StringBuilder;
    //   1174: ldc_w 388
    //   1177: invokevirtual 114	java/lang/StringBuilder:append	(Ljava/lang/String;)Ljava/lang/StringBuilder;
    //   1180: aload_0
    //   1181: getfield 25	pn:g	Landroid/net/Uri;
    //   1184: invokevirtual 221	android/net/Uri:toString	()Ljava/lang/String;
    //   1187: invokevirtual 114	java/lang/StringBuilder:append	(Ljava/lang/String;)Ljava/lang/StringBuilder;
    //   1190: invokevirtual 118	java/lang/StringBuilder:toString	()Ljava/lang/String;
    //   1193: invokestatic 223	android/util/Log:d	(Ljava/lang/String;Ljava/lang/String;)I
    //   1196: pop
    //   1197: goto -606 -> 591
    //   1200: ldc 104
    //   1202: new 106	java/lang/StringBuilder
    //   1205: dup
    //   1206: invokespecial 108	java/lang/StringBuilder:<init>	()V
    //   1209: ldc_w 335
    //   1212: invokevirtual 114	java/lang/StringBuilder:append	(Ljava/lang/String;)Ljava/lang/StringBuilder;
    //   1215: aload_0
    //   1216: getfield 215	pn:m	I
    //   1219: invokevirtual 218	java/lang/StringBuilder:append	(I)Ljava/lang/StringBuilder;
    //   1222: ldc_w 388
    //   1225: invokevirtual 114	java/lang/StringBuilder:append	(Ljava/lang/String;)Ljava/lang/StringBuilder;
    //   1228: aload_0
    //   1229: getfield 25	pn:g	Landroid/net/Uri;
    //   1232: invokevirtual 221	android/net/Uri:toString	()Ljava/lang/String;
    //   1235: invokevirtual 114	java/lang/StringBuilder:append	(Ljava/lang/String;)Ljava/lang/StringBuilder;
    //   1238: invokevirtual 118	java/lang/StringBuilder:toString	()Ljava/lang/String;
    //   1241: invokestatic 223	android/util/Log:d	(Ljava/lang/String;Ljava/lang/String;)I
    //   1244: pop
    //   1245: goto -560 -> 685
    //   1248: ldc 45
    //   1250: astore 4
    //   1252: goto -1002 -> 250
    //   1255: ldc 45
    //   1257: astore 4
    //   1259: goto -1002 -> 257
    // Local variable table:
    //   start	length	slot	name	signature
    //   0	1262	0	this	pn
    //   30	826	1	l	long
    //   309	385	3	bool	boolean
    //   45	329	4	localObject1	Object
    //   392	5	4	localThrowable	Throwable
    //   413	77	4	localContentValues	android.content.ContentValues
    //   596	10	4	localObject2	Object
    //   608	118	4	str1	String
    //   730	528	4	localObject3	Object
    //   149	914	5	localObject4	Object
    //   7	1064	6	localMzPduPersister	com.meizu.android.mms.pdu.MzPduPersister
    //   21	277	7	localMzSendReq	com.meizu.android.mms.pdu.MzSendReq
    //   187	412	8	localObject5	Object
    //   270	43	9	str2	String
    //   276	40	10	str3	String
    //   295	23	11	arrayOfByte	byte[]
    // Exception table:
    //   from	to	target	type
    //   0	104	392	java/lang/Throwable
    //   104	147	392	java/lang/Throwable
    //   151	189	392	java/lang/Throwable
    //   250	257	392	java/lang/Throwable
    //   257	308	392	java/lang/Throwable
    //   310	392	392	java/lang/Throwable
    //   598	608	392	java/lang/Throwable
    //   697	732	392	java/lang/Throwable
    //   737	748	392	java/lang/Throwable
    //   748	919	392	java/lang/Throwable
    //   999	1101	392	java/lang/Throwable
    //   194	250	596	finally
    //   0	104	608	finally
    //   104	147	608	finally
    //   151	189	608	finally
    //   250	257	608	finally
    //   257	308	608	finally
    //   310	392	608	finally
    //   394	516	608	finally
    //   598	608	608	finally
    //   697	732	608	finally
    //   737	748	608	finally
    //   748	919	608	finally
    //   999	1101	608	finally
  }
  
  class a
  {
    String a;
    int b;
    String c;
    String d;
    String e;
    
    a() {}
  }
}

/* Location:
 * Qualified Name:     pn
 * Java Class Version: 6 (50.0)
 * JD-Core Version:    0.7.1
 */