import android.content.Context;
import android.os.AsyncTask;

class wd$b
  extends AsyncTask<Void, Void, Void>
{
  Context a;
  
  public wd$b(Context paramContext)
  {
    a = paramContext;
  }
  
  /* Error */
  protected Void a(Void... paramVarArgs)
  {
    // Byte code:
    //   0: ldc 23
    //   2: ldc 25
    //   4: invokestatic 31	android/util/Log:v	(Ljava/lang/String;Ljava/lang/String;)I
    //   7: pop
    //   8: invokestatic 35	wd:m	()Ljava/lang/Object;
    //   11: astore 7
    //   13: aload 7
    //   15: monitorenter
    //   16: invokestatic 39	wd:n	()Ljava/util/HashMap;
    //   19: invokevirtual 44	java/util/HashMap:clear	()V
    //   22: invokestatic 47	wd:o	()Ljava/util/HashMap;
    //   25: invokevirtual 44	java/util/HashMap:clear	()V
    //   28: aload_0
    //   29: getfield 17	wd$b:a	Landroid/content/Context;
    //   32: invokevirtual 53	android/content/Context:getContentResolver	()Landroid/content/ContentResolver;
    //   35: astore 8
    //   37: aload 8
    //   39: getstatic 59	android/provider/Telephony$Sms:CONTENT_URI	Landroid/net/Uri;
    //   42: iconst_3
    //   43: anewarray 61	java/lang/String
    //   46: dup
    //   47: iconst_0
    //   48: ldc 63
    //   50: aastore
    //   51: dup
    //   52: iconst_1
    //   53: ldc 65
    //   55: aastore
    //   56: dup
    //   57: iconst_2
    //   58: ldc 67
    //   60: aastore
    //   61: ldc 69
    //   63: aconst_null
    //   64: aconst_null
    //   65: invokevirtual 75	android/content/ContentResolver:query	(Landroid/net/Uri;[Ljava/lang/String;Ljava/lang/String;[Ljava/lang/String;Ljava/lang/String;)Landroid/database/Cursor;
    //   68: astore_1
    //   69: aload_1
    //   70: ifnull +87 -> 157
    //   73: aload_1
    //   74: astore 5
    //   76: aload_1
    //   77: invokeinterface 81 1 0
    //   82: ifle +75 -> 157
    //   85: aload_1
    //   86: astore 5
    //   88: aload_1
    //   89: invokeinterface 85 1 0
    //   94: pop
    //   95: aload_1
    //   96: astore 5
    //   98: aload_1
    //   99: iconst_0
    //   100: invokeinterface 89 2 0
    //   105: lstore_2
    //   106: aload_1
    //   107: astore 5
    //   109: invokestatic 39	wd:n	()Ljava/util/HashMap;
    //   112: lload_2
    //   113: invokestatic 95	java/lang/Long:valueOf	(J)Ljava/lang/Long;
    //   116: new 97	wd$a
    //   119: dup
    //   120: aload_1
    //   121: iconst_1
    //   122: invokeinterface 101 2 0
    //   127: aload_1
    //   128: iconst_2
    //   129: invokeinterface 89 2 0
    //   134: invokespecial 104	wd$a:<init>	(Ljava/lang/String;J)V
    //   137: invokevirtual 108	java/util/HashMap:put	(Ljava/lang/Object;Ljava/lang/Object;)Ljava/lang/Object;
    //   140: pop
    //   141: aload_1
    //   142: astore 5
    //   144: aload_1
    //   145: invokeinterface 111 1 0
    //   150: istore 4
    //   152: iload 4
    //   154: ifne -59 -> 95
    //   157: aload_1
    //   158: astore 5
    //   160: aload_1
    //   161: ifnull +520 -> 681
    //   164: aload_1
    //   165: invokeinterface 114 1 0
    //   170: aload 8
    //   172: getstatic 117	android/provider/Telephony$Mms$Draft:CONTENT_URI	Landroid/net/Uri;
    //   175: iconst_4
    //   176: anewarray 61	java/lang/String
    //   179: dup
    //   180: iconst_0
    //   181: ldc 63
    //   183: aastore
    //   184: dup
    //   185: iconst_1
    //   186: ldc 119
    //   188: aastore
    //   189: dup
    //   190: iconst_2
    //   191: ldc 121
    //   193: aastore
    //   194: dup
    //   195: iconst_3
    //   196: ldc 67
    //   198: aastore
    //   199: aconst_null
    //   200: aconst_null
    //   201: aconst_null
    //   202: invokevirtual 75	android/content/ContentResolver:query	(Landroid/net/Uri;[Ljava/lang/String;Ljava/lang/String;[Ljava/lang/String;Ljava/lang/String;)Landroid/database/Cursor;
    //   205: astore 5
    //   207: aload 5
    //   209: ifnull +103 -> 312
    //   212: aload 5
    //   214: astore_1
    //   215: aload 5
    //   217: invokeinterface 81 1 0
    //   222: ifle +90 -> 312
    //   225: aload 5
    //   227: astore_1
    //   228: aload 5
    //   230: invokeinterface 85 1 0
    //   235: pop
    //   236: aload 5
    //   238: astore_1
    //   239: aload 5
    //   241: iconst_1
    //   242: iconst_2
    //   243: invokestatic 124	wd:a	(Landroid/database/Cursor;II)Ljava/lang/String;
    //   246: astore 6
    //   248: aload 5
    //   250: astore_1
    //   251: aload 5
    //   253: iconst_0
    //   254: invokeinterface 89 2 0
    //   259: lstore_2
    //   260: aload 5
    //   262: astore_1
    //   263: invokestatic 47	wd:o	()Ljava/util/HashMap;
    //   266: lload_2
    //   267: invokestatic 95	java/lang/Long:valueOf	(J)Ljava/lang/Long;
    //   270: new 97	wd$a
    //   273: dup
    //   274: aload 6
    //   276: aload 5
    //   278: iconst_3
    //   279: invokeinterface 89 2 0
    //   284: ldc2_w 125
    //   287: lmul
    //   288: invokespecial 104	wd$a:<init>	(Ljava/lang/String;J)V
    //   291: invokevirtual 108	java/util/HashMap:put	(Ljava/lang/Object;Ljava/lang/Object;)Ljava/lang/Object;
    //   294: pop
    //   295: aload 5
    //   297: astore_1
    //   298: aload 5
    //   300: invokeinterface 111 1 0
    //   305: istore 4
    //   307: iload 4
    //   309: ifne -73 -> 236
    //   312: aload 5
    //   314: ifnull +10 -> 324
    //   317: aload 5
    //   319: invokeinterface 114 1 0
    //   324: invokestatic 129	wd:p	()Ljava/util/HashMap;
    //   327: invokevirtual 132	java/util/HashMap:size	()I
    //   330: ifle +324 -> 654
    //   333: invokestatic 129	wd:p	()Ljava/util/HashMap;
    //   336: invokevirtual 136	java/util/HashMap:entrySet	()Ljava/util/Set;
    //   339: invokeinterface 142 1 0
    //   344: astore_1
    //   345: aload_1
    //   346: invokeinterface 147 1 0
    //   351: ifeq +303 -> 654
    //   354: aload_1
    //   355: invokeinterface 150 1 0
    //   360: checkcast 152	java/util/Map$Entry
    //   363: astore 5
    //   365: aload 5
    //   367: invokeinterface 155 1 0
    //   372: checkcast 91	java/lang/Long
    //   375: invokevirtual 159	java/lang/Long:longValue	()J
    //   378: lstore_2
    //   379: aload 5
    //   381: invokeinterface 162 1 0
    //   386: checkcast 97	wd$a
    //   389: getfield 165	wd$a:a	Ljava/lang/String;
    //   392: invokestatic 171	android/text/TextUtils:isEmpty	(Ljava/lang/CharSequence;)Z
    //   395: ifeq +132 -> 527
    //   398: invokestatic 39	wd:n	()Ljava/util/HashMap;
    //   401: lload_2
    //   402: invokestatic 95	java/lang/Long:valueOf	(J)Ljava/lang/Long;
    //   405: invokevirtual 175	java/util/HashMap:containsKey	(Ljava/lang/Object;)Z
    //   408: ifne -63 -> 345
    //   411: invokestatic 47	wd:o	()Ljava/util/HashMap;
    //   414: lload_2
    //   415: invokestatic 95	java/lang/Long:valueOf	(J)Ljava/lang/Long;
    //   418: invokevirtual 175	java/util/HashMap:containsKey	(Ljava/lang/Object;)Z
    //   421: ifne -76 -> 345
    //   424: invokestatic 129	wd:p	()Ljava/util/HashMap;
    //   427: lload_2
    //   428: invokestatic 95	java/lang/Long:valueOf	(J)Ljava/lang/Long;
    //   431: invokevirtual 179	java/util/HashMap:remove	(Ljava/lang/Object;)Ljava/lang/Object;
    //   434: pop
    //   435: goto -90 -> 345
    //   438: astore_1
    //   439: aload 7
    //   441: monitorexit
    //   442: aload_1
    //   443: athrow
    //   444: astore 6
    //   446: aconst_null
    //   447: astore_1
    //   448: aload_1
    //   449: astore 5
    //   451: aload 6
    //   453: invokevirtual 182	java/lang/Exception:printStackTrace	()V
    //   456: aload_1
    //   457: astore 5
    //   459: aload_1
    //   460: ifnull +221 -> 681
    //   463: aload_1
    //   464: invokeinterface 114 1 0
    //   469: goto -299 -> 170
    //   472: aload 5
    //   474: ifnull +10 -> 484
    //   477: aload 5
    //   479: invokeinterface 114 1 0
    //   484: aload_1
    //   485: athrow
    //   486: astore 6
    //   488: aload_1
    //   489: astore 5
    //   491: aload 5
    //   493: astore_1
    //   494: aload 6
    //   496: invokevirtual 182	java/lang/Exception:printStackTrace	()V
    //   499: aload 5
    //   501: ifnull -177 -> 324
    //   504: aload 5
    //   506: invokeinterface 114 1 0
    //   511: goto -187 -> 324
    //   514: aload_1
    //   515: ifnull +9 -> 524
    //   518: aload_1
    //   519: invokeinterface 114 1 0
    //   524: aload 5
    //   526: athrow
    //   527: invokestatic 39	wd:n	()Ljava/util/HashMap;
    //   530: lload_2
    //   531: invokestatic 95	java/lang/Long:valueOf	(J)Ljava/lang/Long;
    //   534: invokevirtual 185	java/util/HashMap:get	(Ljava/lang/Object;)Ljava/lang/Object;
    //   537: ifnull +52 -> 589
    //   540: invokestatic 39	wd:n	()Ljava/util/HashMap;
    //   543: lload_2
    //   544: invokestatic 95	java/lang/Long:valueOf	(J)Ljava/lang/Long;
    //   547: invokevirtual 185	java/util/HashMap:get	(Ljava/lang/Object;)Ljava/lang/Object;
    //   550: checkcast 97	wd$a
    //   553: getfield 165	wd$a:a	Ljava/lang/String;
    //   556: invokestatic 129	wd:p	()Ljava/util/HashMap;
    //   559: lload_2
    //   560: invokestatic 95	java/lang/Long:valueOf	(J)Ljava/lang/Long;
    //   563: invokevirtual 185	java/util/HashMap:get	(Ljava/lang/Object;)Ljava/lang/Object;
    //   566: checkcast 97	wd$a
    //   569: getfield 165	wd$a:a	Ljava/lang/String;
    //   572: invokevirtual 188	java/lang/String:equals	(Ljava/lang/Object;)Z
    //   575: ifeq +14 -> 589
    //   578: invokestatic 129	wd:p	()Ljava/util/HashMap;
    //   581: lload_2
    //   582: invokestatic 95	java/lang/Long:valueOf	(J)Ljava/lang/Long;
    //   585: invokevirtual 179	java/util/HashMap:remove	(Ljava/lang/Object;)Ljava/lang/Object;
    //   588: pop
    //   589: invokestatic 47	wd:o	()Ljava/util/HashMap;
    //   592: lload_2
    //   593: invokestatic 95	java/lang/Long:valueOf	(J)Ljava/lang/Long;
    //   596: invokevirtual 185	java/util/HashMap:get	(Ljava/lang/Object;)Ljava/lang/Object;
    //   599: ifnull -254 -> 345
    //   602: invokestatic 47	wd:o	()Ljava/util/HashMap;
    //   605: lload_2
    //   606: invokestatic 95	java/lang/Long:valueOf	(J)Ljava/lang/Long;
    //   609: invokevirtual 185	java/util/HashMap:get	(Ljava/lang/Object;)Ljava/lang/Object;
    //   612: checkcast 97	wd$a
    //   615: getfield 165	wd$a:a	Ljava/lang/String;
    //   618: invokestatic 129	wd:p	()Ljava/util/HashMap;
    //   621: lload_2
    //   622: invokestatic 95	java/lang/Long:valueOf	(J)Ljava/lang/Long;
    //   625: invokevirtual 185	java/util/HashMap:get	(Ljava/lang/Object;)Ljava/lang/Object;
    //   628: checkcast 97	wd$a
    //   631: getfield 165	wd$a:a	Ljava/lang/String;
    //   634: invokevirtual 188	java/lang/String:equals	(Ljava/lang/Object;)Z
    //   637: ifeq -292 -> 345
    //   640: invokestatic 129	wd:p	()Ljava/util/HashMap;
    //   643: lload_2
    //   644: invokestatic 95	java/lang/Long:valueOf	(J)Ljava/lang/Long;
    //   647: invokevirtual 179	java/util/HashMap:remove	(Ljava/lang/Object;)Ljava/lang/Object;
    //   650: pop
    //   651: goto -306 -> 345
    //   654: invokestatic 191	wd:q	()V
    //   657: aload 7
    //   659: monitorexit
    //   660: aconst_null
    //   661: areturn
    //   662: astore 5
    //   664: goto -150 -> 514
    //   667: astore 6
    //   669: goto -178 -> 491
    //   672: astore_1
    //   673: goto -201 -> 472
    //   676: astore 6
    //   678: goto -230 -> 448
    //   681: aload 5
    //   683: astore_1
    //   684: goto -514 -> 170
    //   687: astore_1
    //   688: aconst_null
    //   689: astore 5
    //   691: goto -219 -> 472
    //   694: astore 5
    //   696: goto -182 -> 514
    // Local variable table:
    //   start	length	slot	name	signature
    //   0	699	0	this	b
    //   0	699	1	paramVarArgs	Void[]
    //   105	539	2	l	long
    //   150	158	4	bool	boolean
    //   74	451	5	localObject1	Object
    //   662	20	5	localObject2	Object
    //   689	1	5	localObject3	Object
    //   694	1	5	localObject4	Object
    //   246	29	6	str	String
    //   444	8	6	localException1	Exception
    //   486	9	6	localException2	Exception
    //   667	1	6	localException3	Exception
    //   676	1	6	localException4	Exception
    //   11	647	7	localObject5	Object
    //   35	136	8	localContentResolver	android.content.ContentResolver
    // Exception table:
    //   from	to	target	type
    //   16	37	438	finally
    //   164	170	438	finally
    //   317	324	438	finally
    //   324	345	438	finally
    //   345	435	438	finally
    //   439	442	438	finally
    //   463	469	438	finally
    //   477	484	438	finally
    //   484	486	438	finally
    //   504	511	438	finally
    //   518	524	438	finally
    //   524	527	438	finally
    //   527	589	438	finally
    //   589	651	438	finally
    //   654	660	438	finally
    //   37	69	444	java/lang/Exception
    //   170	207	486	java/lang/Exception
    //   215	225	662	finally
    //   228	236	662	finally
    //   239	248	662	finally
    //   251	260	662	finally
    //   263	295	662	finally
    //   298	307	662	finally
    //   494	499	662	finally
    //   215	225	667	java/lang/Exception
    //   228	236	667	java/lang/Exception
    //   239	248	667	java/lang/Exception
    //   251	260	667	java/lang/Exception
    //   263	295	667	java/lang/Exception
    //   298	307	667	java/lang/Exception
    //   76	85	672	finally
    //   88	95	672	finally
    //   98	106	672	finally
    //   109	141	672	finally
    //   144	152	672	finally
    //   451	456	672	finally
    //   76	85	676	java/lang/Exception
    //   88	95	676	java/lang/Exception
    //   98	106	676	java/lang/Exception
    //   109	141	676	java/lang/Exception
    //   144	152	676	java/lang/Exception
    //   37	69	687	finally
    //   170	207	694	finally
  }
}

/* Location:
 * Qualified Name:     wd.b
 * Java Class Version: 6 (50.0)
 * JD-Core Version:    0.7.1
 */