package cn.com.xy.sms.sdk.util;

import android.content.Context;
import cn.com.xy.sms.sdk.constant.Constant;
import java.io.Closeable;
import java.io.File;
import java.io.FileInputStream;
import java.io.InputStream;
import java.net.HttpURLConnection;
import java.util.ArrayList;
import java.util.Arrays;
import java.util.Iterator;
import java.util.List;
import java.util.zip.ZipFile;

public final class d
{
  private static String a = "FileUtils";
  
  /* Error */
  public static File a(String paramString1, String paramString2, InputStream paramInputStream)
  {
    // Byte code:
    //   0: aload_2
    //   1: ifnonnull +5 -> 6
    //   4: aconst_null
    //   5: areturn
    //   6: new 21	java/io/File
    //   9: dup
    //   10: new 23	java/lang/StringBuilder
    //   13: dup
    //   14: aload_0
    //   15: invokestatic 29	java/lang/String:valueOf	(Ljava/lang/Object;)Ljava/lang/String;
    //   18: invokespecial 32	java/lang/StringBuilder:<init>	(Ljava/lang/String;)V
    //   21: aload_1
    //   22: invokevirtual 36	java/lang/StringBuilder:append	(Ljava/lang/String;)Ljava/lang/StringBuilder;
    //   25: invokevirtual 40	java/lang/StringBuilder:toString	()Ljava/lang/String;
    //   28: invokespecial 41	java/io/File:<init>	(Ljava/lang/String;)V
    //   31: astore 7
    //   33: new 43	java/io/FileOutputStream
    //   36: dup
    //   37: aload 7
    //   39: invokespecial 46	java/io/FileOutputStream:<init>	(Ljava/io/File;)V
    //   42: astore 4
    //   44: aload 4
    //   46: astore 5
    //   48: sipush 1024
    //   51: newarray <illegal type>
    //   53: astore 6
    //   55: aload 4
    //   57: astore 5
    //   59: aload_2
    //   60: aload 6
    //   62: invokevirtual 52	java/io/InputStream:read	([B)I
    //   65: istore_3
    //   66: iload_3
    //   67: ifgt +24 -> 91
    //   70: aload 4
    //   72: astore 5
    //   74: aload 4
    //   76: invokevirtual 57	java/io/OutputStream:flush	()V
    //   79: aload 4
    //   81: invokestatic 60	cn/com/xy/sms/sdk/util/d:a	(Ljava/io/Closeable;)V
    //   84: aload_2
    //   85: invokestatic 60	cn/com/xy/sms/sdk/util/d:a	(Ljava/io/Closeable;)V
    //   88: aload 7
    //   90: areturn
    //   91: aload 4
    //   93: astore 5
    //   95: aload 4
    //   97: aload 6
    //   99: iconst_0
    //   100: iload_3
    //   101: invokevirtual 64	java/io/OutputStream:write	([BII)V
    //   104: goto -49 -> 55
    //   107: astore 6
    //   109: aload 4
    //   111: astore 5
    //   113: aload 6
    //   115: invokevirtual 67	java/lang/Throwable:printStackTrace	()V
    //   118: aload 4
    //   120: astore 5
    //   122: new 23	java/lang/StringBuilder
    //   125: dup
    //   126: ldc 69
    //   128: invokespecial 32	java/lang/StringBuilder:<init>	(Ljava/lang/String;)V
    //   131: aload 6
    //   133: invokevirtual 72	java/lang/Throwable:getLocalizedMessage	()Ljava/lang/String;
    //   136: invokevirtual 36	java/lang/StringBuilder:append	(Ljava/lang/String;)Ljava/lang/StringBuilder;
    //   139: pop
    //   140: aload 4
    //   142: astore 5
    //   144: new 23	java/lang/StringBuilder
    //   147: dup
    //   148: aload_0
    //   149: invokestatic 29	java/lang/String:valueOf	(Ljava/lang/Object;)Ljava/lang/String;
    //   152: invokespecial 32	java/lang/StringBuilder:<init>	(Ljava/lang/String;)V
    //   155: aload_1
    //   156: invokevirtual 36	java/lang/StringBuilder:append	(Ljava/lang/String;)Ljava/lang/StringBuilder;
    //   159: invokevirtual 40	java/lang/StringBuilder:toString	()Ljava/lang/String;
    //   162: invokestatic 75	cn/com/xy/sms/sdk/util/d:a	(Ljava/lang/String;)Z
    //   165: ifeq +29 -> 194
    //   168: aload 4
    //   170: astore 5
    //   172: new 23	java/lang/StringBuilder
    //   175: dup
    //   176: aload_0
    //   177: invokestatic 29	java/lang/String:valueOf	(Ljava/lang/Object;)Ljava/lang/String;
    //   180: invokespecial 32	java/lang/StringBuilder:<init>	(Ljava/lang/String;)V
    //   183: aload_1
    //   184: invokevirtual 36	java/lang/StringBuilder:append	(Ljava/lang/String;)Ljava/lang/StringBuilder;
    //   187: invokevirtual 40	java/lang/StringBuilder:toString	()Ljava/lang/String;
    //   190: invokestatic 78	cn/com/xy/sms/sdk/util/d:c	(Ljava/lang/String;)Z
    //   193: pop
    //   194: aload 4
    //   196: invokestatic 60	cn/com/xy/sms/sdk/util/d:a	(Ljava/io/Closeable;)V
    //   199: aload_2
    //   200: invokestatic 60	cn/com/xy/sms/sdk/util/d:a	(Ljava/io/Closeable;)V
    //   203: aload 7
    //   205: areturn
    //   206: astore_0
    //   207: aconst_null
    //   208: astore 5
    //   210: aload 5
    //   212: invokestatic 60	cn/com/xy/sms/sdk/util/d:a	(Ljava/io/Closeable;)V
    //   215: aload_2
    //   216: invokestatic 60	cn/com/xy/sms/sdk/util/d:a	(Ljava/io/Closeable;)V
    //   219: aload_0
    //   220: athrow
    //   221: astore_0
    //   222: goto -12 -> 210
    //   225: astore 6
    //   227: aconst_null
    //   228: astore 4
    //   230: aconst_null
    //   231: astore 7
    //   233: goto -124 -> 109
    //   236: astore 6
    //   238: aconst_null
    //   239: astore 4
    //   241: goto -132 -> 109
    // Local variable table:
    //   start	length	slot	name	signature
    //   0	244	0	paramString1	String
    //   0	244	1	paramString2	String
    //   0	244	2	paramInputStream	InputStream
    //   65	36	3	i	int
    //   42	198	4	localFileOutputStream1	java.io.FileOutputStream
    //   46	165	5	localFileOutputStream2	java.io.FileOutputStream
    //   53	45	6	arrayOfByte	byte[]
    //   107	25	6	localThrowable1	Throwable
    //   225	1	6	localThrowable2	Throwable
    //   236	1	6	localThrowable3	Throwable
    //   31	201	7	localFile	File
    // Exception table:
    //   from	to	target	type
    //   48	55	107	java/lang/Throwable
    //   59	66	107	java/lang/Throwable
    //   74	79	107	java/lang/Throwable
    //   95	104	107	java/lang/Throwable
    //   6	33	206	finally
    //   33	44	206	finally
    //   48	55	221	finally
    //   59	66	221	finally
    //   74	79	221	finally
    //   95	104	221	finally
    //   113	118	221	finally
    //   122	140	221	finally
    //   144	168	221	finally
    //   172	194	221	finally
    //   6	33	225	java/lang/Throwable
    //   33	44	236	java/lang/Throwable
  }
  
  public static String a(int paramInt)
  {
    if (paramInt == 1) {
      return "X8448A";
    }
    return "X4667U";
  }
  
  public static String a(InputStream paramInputStream)
  {
    try
    {
      paramInputStream = new String(b(paramInputStream), "UTF-8");
      return paramInputStream;
    }
    catch (Throwable paramInputStream)
    {
      paramInputStream.printStackTrace();
    }
    return "";
  }
  
  public static void a(Closeable paramCloseable)
  {
    if (paramCloseable != null) {}
    try
    {
      paramCloseable.close();
      return;
    }
    catch (Throwable paramCloseable)
    {
      paramCloseable.printStackTrace();
    }
  }
  
  public static void a(File paramFile)
  {
    if (paramFile.exists())
    {
      if (!paramFile.isFile()) {
        break label20;
      }
      paramFile.delete();
    }
    label20:
    while (!paramFile.isDirectory()) {
      return;
    }
    File[] arrayOfFile = paramFile.listFiles();
    if (arrayOfFile == null)
    {
      paramFile.delete();
      return;
    }
    int i = 0;
    for (;;)
    {
      if (i >= arrayOfFile.length)
      {
        paramFile.delete();
        return;
      }
      a(arrayOfFile[i]);
      i += 1;
    }
  }
  
  public static void a(String paramString1, String paramString2, String paramString3)
  {
    try
    {
      new StringBuilder("dir=").append(paramString1).append("oldFileName=").append(paramString2).append("newFileName=").append(paramString3);
      paramString2 = new File(paramString1 + paramString2);
      if (paramString2.exists()) {
        paramString2.renameTo(new File(paramString1 + paramString3));
      }
      return;
    }
    catch (Throwable paramString1)
    {
      paramString1.printStackTrace();
    }
  }
  
  public static void a(String paramString1, String paramString2, String paramString3, String paramString4)
  {
    try
    {
      paramString1 = e(paramString1, paramString2, paramString3);
      a = "deleteFile";
      a(paramString1, paramString4);
      return;
    }
    catch (Throwable paramString1)
    {
      paramString1.printStackTrace();
    }
  }
  
  private static void a(HttpURLConnection paramHttpURLConnection)
  {
    if (paramHttpURLConnection != null) {}
    try
    {
      paramHttpURLConnection.disconnect();
      return;
    }
    catch (Throwable paramHttpURLConnection)
    {
      paramHttpURLConnection.printStackTrace();
    }
  }
  
  private static void a(List<File> paramList, String paramString)
  {
    if (paramList != null) {
      for (;;)
      {
        File localFile;
        try
        {
          if (paramList.isEmpty()) {
            break;
          }
          paramList = paramList.iterator();
          if (paramList == null) {
            break;
          }
          if (!paramList.hasNext()) {
            return;
          }
          localFile = (File)paramList.next();
          if (localFile.getName().equals(paramString))
          {
            str = a;
            new StringBuilder("不删除").append(localFile.getAbsolutePath());
            continue;
          }
          localFile.delete();
        }
        catch (Throwable paramList)
        {
          paramList.printStackTrace();
          return;
        }
        String str = a;
        new StringBuilder(String.valueOf(a)).append("=").append(localFile.getAbsolutePath());
      }
    }
  }
  
  public static void a(ZipFile paramZipFile)
  {
    if (paramZipFile != null) {}
    try
    {
      paramZipFile.close();
      return;
    }
    catch (Throwable paramZipFile)
    {
      paramZipFile.printStackTrace();
    }
  }
  
  public static boolean a(String paramString)
  {
    boolean bool = false;
    if (new File(paramString).exists()) {
      bool = true;
    }
    return bool;
  }
  
  public static InputStream b(String paramString)
  {
    try
    {
      paramString = new File(paramString);
      if (paramString.exists())
      {
        paramString = new FileInputStream(paramString);
        return paramString;
      }
    }
    catch (Throwable paramString)
    {
      paramString.printStackTrace();
    }
    return null;
  }
  
  public static void b(String paramString1, String paramString2, String paramString3)
  {
    try
    {
      File localFile = Constant.getContext().getDir("outdex", 0);
      if (localFile != null)
      {
        paramString1 = e(localFile.getCanonicalPath(), paramString1, paramString2);
        a = "deleteDex";
        a(paramString1, paramString3);
      }
      return;
    }
    catch (Throwable paramString1)
    {
      paramString1.printStackTrace();
    }
  }
  
  /* Error */
  public static byte[] b(InputStream paramInputStream)
  {
    // Byte code:
    //   0: sipush 2560
    //   3: newarray <illegal type>
    //   5: astore 6
    //   7: new 209	java/io/ByteArrayOutputStream
    //   10: dup
    //   11: invokespecial 210	java/io/ByteArrayOutputStream:<init>	()V
    //   14: astore 5
    //   16: new 212	java/io/DataInputStream
    //   19: dup
    //   20: aload_0
    //   21: invokespecial 215	java/io/DataInputStream:<init>	(Ljava/io/InputStream;)V
    //   24: astore_3
    //   25: aload_3
    //   26: astore_2
    //   27: aload_3
    //   28: aload 6
    //   30: invokevirtual 216	java/io/DataInputStream:read	([B)I
    //   33: istore_1
    //   34: iload_1
    //   35: ifgt +28 -> 63
    //   38: aload_3
    //   39: astore_2
    //   40: aload 5
    //   42: invokevirtual 220	java/io/ByteArrayOutputStream:toByteArray	()[B
    //   45: astore 4
    //   47: aload_3
    //   48: invokestatic 60	cn/com/xy/sms/sdk/util/d:a	(Ljava/io/Closeable;)V
    //   51: aload_0
    //   52: invokestatic 60	cn/com/xy/sms/sdk/util/d:a	(Ljava/io/Closeable;)V
    //   55: aload 5
    //   57: invokestatic 60	cn/com/xy/sms/sdk/util/d:a	(Ljava/io/Closeable;)V
    //   60: aload 4
    //   62: areturn
    //   63: aload_3
    //   64: astore_2
    //   65: aload 5
    //   67: aload 6
    //   69: iconst_0
    //   70: iload_1
    //   71: invokevirtual 221	java/io/ByteArrayOutputStream:write	([BII)V
    //   74: goto -49 -> 25
    //   77: astore 4
    //   79: aload_3
    //   80: astore_2
    //   81: aload 4
    //   83: invokevirtual 67	java/lang/Throwable:printStackTrace	()V
    //   86: aload_3
    //   87: invokestatic 60	cn/com/xy/sms/sdk/util/d:a	(Ljava/io/Closeable;)V
    //   90: aload_0
    //   91: invokestatic 60	cn/com/xy/sms/sdk/util/d:a	(Ljava/io/Closeable;)V
    //   94: aload 5
    //   96: invokestatic 60	cn/com/xy/sms/sdk/util/d:a	(Ljava/io/Closeable;)V
    //   99: aload 6
    //   101: areturn
    //   102: astore_3
    //   103: aconst_null
    //   104: astore_2
    //   105: aload_2
    //   106: invokestatic 60	cn/com/xy/sms/sdk/util/d:a	(Ljava/io/Closeable;)V
    //   109: aload_0
    //   110: invokestatic 60	cn/com/xy/sms/sdk/util/d:a	(Ljava/io/Closeable;)V
    //   113: aload 5
    //   115: invokestatic 60	cn/com/xy/sms/sdk/util/d:a	(Ljava/io/Closeable;)V
    //   118: aload_3
    //   119: athrow
    //   120: astore_3
    //   121: goto -16 -> 105
    //   124: astore 4
    //   126: aconst_null
    //   127: astore_3
    //   128: goto -49 -> 79
    // Local variable table:
    //   start	length	slot	name	signature
    //   0	131	0	paramInputStream	InputStream
    //   33	38	1	i	int
    //   26	80	2	localDataInputStream1	java.io.DataInputStream
    //   24	63	3	localDataInputStream2	java.io.DataInputStream
    //   102	17	3	localObject1	Object
    //   120	1	3	localObject2	Object
    //   127	1	3	localObject3	Object
    //   45	16	4	arrayOfByte1	byte[]
    //   77	5	4	localThrowable1	Throwable
    //   124	1	4	localThrowable2	Throwable
    //   14	100	5	localByteArrayOutputStream	java.io.ByteArrayOutputStream
    //   5	95	6	arrayOfByte2	byte[]
    // Exception table:
    //   from	to	target	type
    //   27	34	77	java/lang/Throwable
    //   40	47	77	java/lang/Throwable
    //   65	74	77	java/lang/Throwable
    //   16	25	102	finally
    //   27	34	120	finally
    //   40	47	120	finally
    //   65	74	120	finally
    //   81	86	120	finally
    //   16	25	124	java/lang/Throwable
  }
  
  public static boolean c(String paramString)
  {
    boolean bool2 = false;
    boolean bool1 = bool2;
    try
    {
      if (!StringUtils.isNull(paramString))
      {
        paramString = new File(paramString);
        bool1 = bool2;
        if (paramString.exists())
        {
          bool1 = bool2;
          if (paramString.isFile())
          {
            paramString.delete();
            bool1 = true;
          }
        }
      }
      return bool1;
    }
    catch (Throwable paramString) {}
    return false;
  }
  
  public static boolean c(String paramString1, String paramString2, String paramString3)
  {
    try
    {
      paramString1 = new File(paramString1);
      if (!paramString1.exists()) {
        paramString1.mkdir();
      }
      paramString1 = paramString1.listFiles(new n(paramString2, paramString3));
      if (paramString1 != null)
      {
        int i = paramString1.length;
        if (i > 0) {
          return true;
        }
      }
    }
    catch (Throwable paramString1)
    {
      paramString1.printStackTrace();
    }
    return false;
  }
  
  public static String d(String paramString1, String paramString2, String paramString3)
  {
    try
    {
      paramString1 = new File(paramString1);
      if (!paramString1.exists()) {
        paramString1.mkdir();
      }
      paramString1 = paramString1.listFiles(new n(paramString2, paramString3));
      if ((paramString1 != null) && (paramString1.length > 0))
      {
        paramString1 = paramString1[0].getCanonicalPath();
        return paramString1;
      }
    }
    catch (Throwable paramString1)
    {
      paramString1.printStackTrace();
    }
    return "";
  }
  
  public static void d(String paramString)
  {
    a(new File(paramString));
  }
  
  public static List<File> e(String paramString1, String paramString2, String paramString3)
  {
    ArrayList localArrayList = new ArrayList();
    try
    {
      paramString1 = new File(paramString1);
      if (!paramString1.exists()) {
        paramString1.mkdir();
      }
      paramString2 = paramString1.listFiles(new n(paramString2, paramString3));
      paramString1 = localArrayList;
      if (paramString2 != null)
      {
        paramString1 = localArrayList;
        if (paramString2.length > 0) {
          paramString1 = Arrays.asList(paramString2);
        }
      }
      return paramString1;
    }
    catch (Throwable paramString1)
    {
      paramString1.printStackTrace();
    }
    return localArrayList;
  }
  
  public static byte[] e(String paramString)
  {
    return b(new FileInputStream(paramString));
  }
  
  /* Error */
  public static int f(String paramString1, String paramString2, String paramString3)
  {
    // Byte code:
    //   0: aconst_null
    //   1: astore 7
    //   3: aconst_null
    //   4: astore 8
    //   6: aconst_null
    //   7: astore 9
    //   9: aconst_null
    //   10: astore 6
    //   12: aload_0
    //   13: invokestatic 226	cn/com/xy/sms/sdk/util/StringUtils:isNull	(Ljava/lang/String;)Z
    //   16: istore 4
    //   18: iload 4
    //   20: ifeq +13 -> 33
    //   23: aconst_null
    //   24: invokestatic 60	cn/com/xy/sms/sdk/util/d:a	(Ljava/io/Closeable;)V
    //   27: aconst_null
    //   28: invokestatic 260	cn/com/xy/sms/sdk/util/d:a	(Ljava/net/HttpURLConnection;)V
    //   31: iconst_m1
    //   32: ireturn
    //   33: new 23	java/lang/StringBuilder
    //   36: dup
    //   37: aload_1
    //   38: invokestatic 29	java/lang/String:valueOf	(Ljava/lang/Object;)Ljava/lang/String;
    //   41: invokespecial 32	java/lang/StringBuilder:<init>	(Ljava/lang/String;)V
    //   44: aload_2
    //   45: invokevirtual 36	java/lang/StringBuilder:append	(Ljava/lang/String;)Ljava/lang/StringBuilder;
    //   48: invokevirtual 40	java/lang/StringBuilder:toString	()Ljava/lang/String;
    //   51: invokestatic 75	cn/com/xy/sms/sdk/util/d:a	(Ljava/lang/String;)Z
    //   54: ifeq +25 -> 79
    //   57: new 23	java/lang/StringBuilder
    //   60: dup
    //   61: aload_1
    //   62: invokestatic 29	java/lang/String:valueOf	(Ljava/lang/Object;)Ljava/lang/String;
    //   65: invokespecial 32	java/lang/StringBuilder:<init>	(Ljava/lang/String;)V
    //   68: aload_2
    //   69: invokevirtual 36	java/lang/StringBuilder:append	(Ljava/lang/String;)Ljava/lang/StringBuilder;
    //   72: invokevirtual 40	java/lang/StringBuilder:toString	()Ljava/lang/String;
    //   75: invokestatic 78	cn/com/xy/sms/sdk/util/d:c	(Ljava/lang/String;)Z
    //   78: pop
    //   79: aload_0
    //   80: ldc_w 262
    //   83: invokevirtual 265	java/lang/String:startsWith	(Ljava/lang/String;)Z
    //   86: ifne +13 -> 99
    //   89: aload_0
    //   90: ldc_w 267
    //   93: invokevirtual 265	java/lang/String:startsWith	(Ljava/lang/String;)Z
    //   96: ifeq +123 -> 219
    //   99: aload_0
    //   100: iconst_0
    //   101: invokestatic 272	cn/com/xy/sms/sdk/net/b:a	(Ljava/lang/String;I)Ljavax/net/ssl/HttpsURLConnection;
    //   104: astore 5
    //   106: aload 5
    //   108: ifnull +542 -> 650
    //   111: aload 5
    //   113: invokevirtual 276	java/net/HttpURLConnection:getResponseCode	()I
    //   116: istore_3
    //   117: ldc_w 278
    //   120: new 23	java/lang/StringBuilder
    //   123: dup
    //   124: ldc_w 280
    //   127: invokespecial 32	java/lang/StringBuilder:<init>	(Ljava/lang/String;)V
    //   130: iload_3
    //   131: invokevirtual 283	java/lang/StringBuilder:append	(I)Ljava/lang/StringBuilder;
    //   134: invokevirtual 40	java/lang/StringBuilder:toString	()Ljava/lang/String;
    //   137: aconst_null
    //   138: invokestatic 288	cn/com/xy/sms/sdk/log/LogManager:e	(Ljava/lang/String;Ljava/lang/String;Ljava/lang/Throwable;)V
    //   141: aload 5
    //   143: invokevirtual 292	java/net/HttpURLConnection:getInputStream	()Ljava/io/InputStream;
    //   146: astore 7
    //   148: aload 7
    //   150: astore 6
    //   152: aload 5
    //   154: astore 7
    //   156: aload 6
    //   158: astore 5
    //   160: aload 7
    //   162: astore 6
    //   164: aload 6
    //   166: ifnull +19 -> 185
    //   169: aload 6
    //   171: astore 8
    //   173: aload 5
    //   175: astore 7
    //   177: aload 6
    //   179: ldc_w 293
    //   182: invokevirtual 297	java/net/HttpURLConnection:setConnectTimeout	(I)V
    //   185: aload 6
    //   187: astore 8
    //   189: aload 5
    //   191: astore 7
    //   193: aload_1
    //   194: aload_2
    //   195: aload 5
    //   197: invokestatic 299	cn/com/xy/sms/sdk/util/d:a	(Ljava/lang/String;Ljava/lang/String;Ljava/io/InputStream;)Ljava/io/File;
    //   200: astore 9
    //   202: aload 9
    //   204: ifnonnull +54 -> 258
    //   207: aload 5
    //   209: invokestatic 60	cn/com/xy/sms/sdk/util/d:a	(Ljava/io/Closeable;)V
    //   212: aload 6
    //   214: invokestatic 260	cn/com/xy/sms/sdk/util/d:a	(Ljava/net/HttpURLConnection;)V
    //   217: iconst_m1
    //   218: ireturn
    //   219: new 301	java/net/URL
    //   222: dup
    //   223: aload_0
    //   224: invokespecial 302	java/net/URL:<init>	(Ljava/lang/String;)V
    //   227: invokevirtual 306	java/net/URL:openConnection	()Ljava/net/URLConnection;
    //   230: checkcast 143	java/net/HttpURLConnection
    //   233: astore 5
    //   235: aload 5
    //   237: ifnull +399 -> 636
    //   240: aload 5
    //   242: invokevirtual 292	java/net/HttpURLConnection:getInputStream	()Ljava/io/InputStream;
    //   245: astore 7
    //   247: aload 5
    //   249: astore 6
    //   251: aload 7
    //   253: astore 5
    //   255: goto -91 -> 164
    //   258: aload 6
    //   260: astore 8
    //   262: aload 5
    //   264: astore 7
    //   266: getstatic 310	cn/com/xy/sms/sdk/log/LogManager:debug	Z
    //   269: ifeq +60 -> 329
    //   272: aload 6
    //   274: astore 8
    //   276: aload 5
    //   278: astore 7
    //   280: new 23	java/lang/StringBuilder
    //   283: dup
    //   284: ldc_w 312
    //   287: invokespecial 32	java/lang/StringBuilder:<init>	(Ljava/lang/String;)V
    //   290: aload_2
    //   291: invokevirtual 36	java/lang/StringBuilder:append	(Ljava/lang/String;)Ljava/lang/StringBuilder;
    //   294: ldc_w 314
    //   297: invokevirtual 36	java/lang/StringBuilder:append	(Ljava/lang/String;)Ljava/lang/StringBuilder;
    //   300: aload_1
    //   301: invokevirtual 36	java/lang/StringBuilder:append	(Ljava/lang/String;)Ljava/lang/StringBuilder;
    //   304: ldc_w 316
    //   307: invokevirtual 36	java/lang/StringBuilder:append	(Ljava/lang/String;)Ljava/lang/StringBuilder;
    //   310: aload_0
    //   311: invokevirtual 36	java/lang/StringBuilder:append	(Ljava/lang/String;)Ljava/lang/StringBuilder;
    //   314: ldc_w 318
    //   317: invokevirtual 36	java/lang/StringBuilder:append	(Ljava/lang/String;)Ljava/lang/StringBuilder;
    //   320: aload 9
    //   322: invokevirtual 322	java/io/File:length	()J
    //   325: invokevirtual 325	java/lang/StringBuilder:append	(J)Ljava/lang/StringBuilder;
    //   328: pop
    //   329: aload 5
    //   331: invokestatic 60	cn/com/xy/sms/sdk/util/d:a	(Ljava/io/Closeable;)V
    //   334: aload 6
    //   336: invokestatic 260	cn/com/xy/sms/sdk/util/d:a	(Ljava/net/HttpURLConnection;)V
    //   339: iconst_0
    //   340: ireturn
    //   341: astore_1
    //   342: aconst_null
    //   343: astore_0
    //   344: aload 6
    //   346: astore_2
    //   347: aload_1
    //   348: invokevirtual 326	java/net/MalformedURLException:printStackTrace	()V
    //   351: new 23	java/lang/StringBuilder
    //   354: dup
    //   355: ldc 69
    //   357: invokespecial 32	java/lang/StringBuilder:<init>	(Ljava/lang/String;)V
    //   360: aload_1
    //   361: invokevirtual 327	java/net/MalformedURLException:getLocalizedMessage	()Ljava/lang/String;
    //   364: invokevirtual 36	java/lang/StringBuilder:append	(Ljava/lang/String;)Ljava/lang/StringBuilder;
    //   367: pop
    //   368: aload_2
    //   369: invokestatic 60	cn/com/xy/sms/sdk/util/d:a	(Ljava/io/Closeable;)V
    //   372: aload_0
    //   373: invokestatic 260	cn/com/xy/sms/sdk/util/d:a	(Ljava/net/HttpURLConnection;)V
    //   376: iconst_m1
    //   377: ireturn
    //   378: astore_0
    //   379: aconst_null
    //   380: astore 5
    //   382: aload 7
    //   384: astore 6
    //   386: aload 6
    //   388: astore 8
    //   390: aload 5
    //   392: astore 7
    //   394: aload_0
    //   395: invokevirtual 328	java/io/IOException:printStackTrace	()V
    //   398: aload 6
    //   400: astore 8
    //   402: aload 5
    //   404: astore 7
    //   406: new 23	java/lang/StringBuilder
    //   409: dup
    //   410: ldc 69
    //   412: invokespecial 32	java/lang/StringBuilder:<init>	(Ljava/lang/String;)V
    //   415: aload_0
    //   416: invokevirtual 329	java/io/IOException:getLocalizedMessage	()Ljava/lang/String;
    //   419: invokevirtual 36	java/lang/StringBuilder:append	(Ljava/lang/String;)Ljava/lang/StringBuilder;
    //   422: pop
    //   423: aload 5
    //   425: invokestatic 60	cn/com/xy/sms/sdk/util/d:a	(Ljava/io/Closeable;)V
    //   428: aload 6
    //   430: invokestatic 260	cn/com/xy/sms/sdk/util/d:a	(Ljava/net/HttpURLConnection;)V
    //   433: iconst_m1
    //   434: ireturn
    //   435: astore_0
    //   436: aconst_null
    //   437: astore 5
    //   439: aload 8
    //   441: astore 6
    //   443: aload 6
    //   445: astore 8
    //   447: aload 5
    //   449: astore 7
    //   451: aload_0
    //   452: invokevirtual 67	java/lang/Throwable:printStackTrace	()V
    //   455: aload 6
    //   457: astore 8
    //   459: aload 5
    //   461: astore 7
    //   463: new 23	java/lang/StringBuilder
    //   466: dup
    //   467: ldc 69
    //   469: invokespecial 32	java/lang/StringBuilder:<init>	(Ljava/lang/String;)V
    //   472: aload_0
    //   473: invokevirtual 72	java/lang/Throwable:getLocalizedMessage	()Ljava/lang/String;
    //   476: invokevirtual 36	java/lang/StringBuilder:append	(Ljava/lang/String;)Ljava/lang/StringBuilder;
    //   479: pop
    //   480: aload 5
    //   482: invokestatic 60	cn/com/xy/sms/sdk/util/d:a	(Ljava/io/Closeable;)V
    //   485: aload 6
    //   487: invokestatic 260	cn/com/xy/sms/sdk/util/d:a	(Ljava/net/HttpURLConnection;)V
    //   490: iconst_m1
    //   491: ireturn
    //   492: astore_0
    //   493: aconst_null
    //   494: astore_2
    //   495: aload 9
    //   497: astore_1
    //   498: aload_2
    //   499: invokestatic 60	cn/com/xy/sms/sdk/util/d:a	(Ljava/io/Closeable;)V
    //   502: aload_1
    //   503: invokestatic 260	cn/com/xy/sms/sdk/util/d:a	(Ljava/net/HttpURLConnection;)V
    //   506: aload_0
    //   507: athrow
    //   508: astore_0
    //   509: aconst_null
    //   510: astore_2
    //   511: aload 5
    //   513: astore_1
    //   514: goto -16 -> 498
    //   517: astore_0
    //   518: aconst_null
    //   519: astore_2
    //   520: aload 5
    //   522: astore_1
    //   523: goto -25 -> 498
    //   526: astore_0
    //   527: aload 8
    //   529: astore_1
    //   530: aload 7
    //   532: astore_2
    //   533: goto -35 -> 498
    //   536: astore 5
    //   538: aload_0
    //   539: astore_1
    //   540: aload 5
    //   542: astore_0
    //   543: goto -45 -> 498
    //   546: astore_0
    //   547: aconst_null
    //   548: astore_1
    //   549: aload 5
    //   551: astore 6
    //   553: aload_1
    //   554: astore 5
    //   556: goto -113 -> 443
    //   559: astore_0
    //   560: aconst_null
    //   561: astore_1
    //   562: aload 5
    //   564: astore 6
    //   566: aload_1
    //   567: astore 5
    //   569: goto -126 -> 443
    //   572: astore_0
    //   573: goto -130 -> 443
    //   576: astore_0
    //   577: aconst_null
    //   578: astore_1
    //   579: aload 5
    //   581: astore 6
    //   583: aload_1
    //   584: astore 5
    //   586: goto -200 -> 386
    //   589: astore_0
    //   590: aconst_null
    //   591: astore_1
    //   592: aload 5
    //   594: astore 6
    //   596: aload_1
    //   597: astore 5
    //   599: goto -213 -> 386
    //   602: astore_0
    //   603: goto -217 -> 386
    //   606: astore_1
    //   607: aload 5
    //   609: astore_0
    //   610: aload 6
    //   612: astore_2
    //   613: goto -266 -> 347
    //   616: astore_1
    //   617: aload 5
    //   619: astore_0
    //   620: aload 6
    //   622: astore_2
    //   623: goto -276 -> 347
    //   626: astore_1
    //   627: aload 6
    //   629: astore_0
    //   630: aload 5
    //   632: astore_2
    //   633: goto -286 -> 347
    //   636: aconst_null
    //   637: astore 7
    //   639: aload 5
    //   641: astore 6
    //   643: aload 7
    //   645: astore 5
    //   647: goto -483 -> 164
    //   650: aconst_null
    //   651: astore 7
    //   653: aload 5
    //   655: astore 6
    //   657: aload 7
    //   659: astore 5
    //   661: goto -497 -> 164
    // Local variable table:
    //   start	length	slot	name	signature
    //   0	664	0	paramString1	String
    //   0	664	1	paramString2	String
    //   0	664	2	paramString3	String
    //   116	15	3	i	int
    //   16	3	4	bool	boolean
    //   104	417	5	localObject1	Object
    //   536	14	5	localObject2	Object
    //   554	106	5	localObject3	Object
    //   10	646	6	localObject4	Object
    //   1	657	7	localObject5	Object
    //   4	524	8	localObject6	Object
    //   7	489	9	localFile	File
    // Exception table:
    //   from	to	target	type
    //   12	18	341	java/net/MalformedURLException
    //   33	79	341	java/net/MalformedURLException
    //   79	99	341	java/net/MalformedURLException
    //   99	106	341	java/net/MalformedURLException
    //   219	235	341	java/net/MalformedURLException
    //   12	18	378	java/io/IOException
    //   33	79	378	java/io/IOException
    //   79	99	378	java/io/IOException
    //   99	106	378	java/io/IOException
    //   219	235	378	java/io/IOException
    //   12	18	435	java/lang/Throwable
    //   33	79	435	java/lang/Throwable
    //   79	99	435	java/lang/Throwable
    //   99	106	435	java/lang/Throwable
    //   219	235	435	java/lang/Throwable
    //   12	18	492	finally
    //   33	79	492	finally
    //   79	99	492	finally
    //   99	106	492	finally
    //   219	235	492	finally
    //   111	148	508	finally
    //   240	247	517	finally
    //   177	185	526	finally
    //   193	202	526	finally
    //   266	272	526	finally
    //   280	329	526	finally
    //   394	398	526	finally
    //   406	423	526	finally
    //   451	455	526	finally
    //   463	480	526	finally
    //   347	368	536	finally
    //   111	148	546	java/lang/Throwable
    //   240	247	559	java/lang/Throwable
    //   177	185	572	java/lang/Throwable
    //   193	202	572	java/lang/Throwable
    //   266	272	572	java/lang/Throwable
    //   280	329	572	java/lang/Throwable
    //   111	148	576	java/io/IOException
    //   240	247	589	java/io/IOException
    //   177	185	602	java/io/IOException
    //   193	202	602	java/io/IOException
    //   266	272	602	java/io/IOException
    //   280	329	602	java/io/IOException
    //   111	148	606	java/net/MalformedURLException
    //   240	247	616	java/net/MalformedURLException
    //   177	185	626	java/net/MalformedURLException
    //   193	202	626	java/net/MalformedURLException
    //   266	272	626	java/net/MalformedURLException
    //   280	329	626	java/net/MalformedURLException
  }
  
  /* Error */
  public static String f(String paramString)
  {
    // Byte code:
    //   0: aconst_null
    //   1: astore_2
    //   2: invokestatic 194	cn/com/xy/sms/sdk/constant/Constant:getContext	()Landroid/content/Context;
    //   5: invokevirtual 334	android/content/Context:getResources	()Landroid/content/res/Resources;
    //   8: invokevirtual 340	android/content/res/Resources:getAssets	()Landroid/content/res/AssetManager;
    //   11: aload_0
    //   12: invokevirtual 345	android/content/res/AssetManager:open	(Ljava/lang/String;)Ljava/io/InputStream;
    //   15: astore_0
    //   16: aload_0
    //   17: astore_2
    //   18: aload_0
    //   19: invokevirtual 348	java/io/InputStream:available	()I
    //   22: newarray <illegal type>
    //   24: astore_3
    //   25: aload_0
    //   26: astore_2
    //   27: aload_0
    //   28: aload_3
    //   29: invokevirtual 52	java/io/InputStream:read	([B)I
    //   32: pop
    //   33: aload_0
    //   34: astore_2
    //   35: aload_0
    //   36: invokevirtual 349	java/io/InputStream:close	()V
    //   39: aload_0
    //   40: astore_2
    //   41: new 25	java/lang/String
    //   44: dup
    //   45: aload_3
    //   46: ldc_w 351
    //   49: invokespecial 93	java/lang/String:<init>	([BLjava/lang/String;)V
    //   52: astore_3
    //   53: aload_0
    //   54: astore_2
    //   55: aload_3
    //   56: invokestatic 226	cn/com/xy/sms/sdk/util/StringUtils:isNull	(Ljava/lang/String;)Z
    //   59: istore_1
    //   60: iload_1
    //   61: ifne +45 -> 106
    //   64: aload_0
    //   65: invokestatic 60	cn/com/xy/sms/sdk/util/d:a	(Ljava/io/Closeable;)V
    //   68: aload_3
    //   69: areturn
    //   70: astore_0
    //   71: aload_2
    //   72: astore_0
    //   73: aload_0
    //   74: invokestatic 60	cn/com/xy/sms/sdk/util/d:a	(Ljava/io/Closeable;)V
    //   77: ldc_w 353
    //   80: areturn
    //   81: astore_3
    //   82: aconst_null
    //   83: astore_0
    //   84: aload_0
    //   85: astore_2
    //   86: aload_3
    //   87: invokevirtual 67	java/lang/Throwable:printStackTrace	()V
    //   90: aload_0
    //   91: invokestatic 60	cn/com/xy/sms/sdk/util/d:a	(Ljava/io/Closeable;)V
    //   94: goto -17 -> 77
    //   97: astore_0
    //   98: aconst_null
    //   99: astore_2
    //   100: aload_2
    //   101: invokestatic 60	cn/com/xy/sms/sdk/util/d:a	(Ljava/io/Closeable;)V
    //   104: aload_0
    //   105: athrow
    //   106: aload_0
    //   107: invokestatic 60	cn/com/xy/sms/sdk/util/d:a	(Ljava/io/Closeable;)V
    //   110: goto -33 -> 77
    //   113: astore_0
    //   114: goto -14 -> 100
    //   117: astore_3
    //   118: goto -34 -> 84
    //   121: astore_2
    //   122: goto -49 -> 73
    // Local variable table:
    //   start	length	slot	name	signature
    //   0	125	0	paramString	String
    //   59	2	1	bool	boolean
    //   1	100	2	str	String
    //   121	1	2	localIOException	java.io.IOException
    //   24	45	3	localObject	Object
    //   81	6	3	localThrowable1	Throwable
    //   117	1	3	localThrowable2	Throwable
    // Exception table:
    //   from	to	target	type
    //   2	16	70	java/io/IOException
    //   2	16	81	java/lang/Throwable
    //   2	16	97	finally
    //   18	25	113	finally
    //   27	33	113	finally
    //   35	39	113	finally
    //   41	53	113	finally
    //   55	60	113	finally
    //   86	90	113	finally
    //   18	25	117	java/lang/Throwable
    //   27	33	117	java/lang/Throwable
    //   35	39	117	java/lang/Throwable
    //   41	53	117	java/lang/Throwable
    //   55	60	117	java/lang/Throwable
    //   18	25	121	java/io/IOException
    //   27	33	121	java/io/IOException
    //   35	39	121	java/io/IOException
    //   41	53	121	java/io/IOException
    //   55	60	121	java/io/IOException
  }
  
  /* Error */
  public static int g(String paramString1, String paramString2, String paramString3)
  {
    // Byte code:
    //   0: aconst_null
    //   1: astore 8
    //   3: aconst_null
    //   4: astore 9
    //   6: aconst_null
    //   7: astore 11
    //   9: aconst_null
    //   10: astore 13
    //   12: aload_0
    //   13: invokestatic 226	cn/com/xy/sms/sdk/util/StringUtils:isNull	(Ljava/lang/String;)Z
    //   16: istore 5
    //   18: iload 5
    //   20: ifeq +17 -> 37
    //   23: aconst_null
    //   24: invokestatic 60	cn/com/xy/sms/sdk/util/d:a	(Ljava/io/Closeable;)V
    //   27: aconst_null
    //   28: invokestatic 60	cn/com/xy/sms/sdk/util/d:a	(Ljava/io/Closeable;)V
    //   31: aconst_null
    //   32: invokestatic 260	cn/com/xy/sms/sdk/util/d:a	(Ljava/net/HttpURLConnection;)V
    //   35: iconst_m1
    //   36: ireturn
    //   37: new 23	java/lang/StringBuilder
    //   40: dup
    //   41: aload_1
    //   42: invokestatic 29	java/lang/String:valueOf	(Ljava/lang/Object;)Ljava/lang/String;
    //   45: invokespecial 32	java/lang/StringBuilder:<init>	(Ljava/lang/String;)V
    //   48: aload_2
    //   49: invokevirtual 36	java/lang/StringBuilder:append	(Ljava/lang/String;)Ljava/lang/StringBuilder;
    //   52: invokevirtual 40	java/lang/StringBuilder:toString	()Ljava/lang/String;
    //   55: invokestatic 75	cn/com/xy/sms/sdk/util/d:a	(Ljava/lang/String;)Z
    //   58: ifeq +25 -> 83
    //   61: new 23	java/lang/StringBuilder
    //   64: dup
    //   65: aload_1
    //   66: invokestatic 29	java/lang/String:valueOf	(Ljava/lang/Object;)Ljava/lang/String;
    //   69: invokespecial 32	java/lang/StringBuilder:<init>	(Ljava/lang/String;)V
    //   72: aload_2
    //   73: invokevirtual 36	java/lang/StringBuilder:append	(Ljava/lang/String;)Ljava/lang/StringBuilder;
    //   76: invokevirtual 40	java/lang/StringBuilder:toString	()Ljava/lang/String;
    //   79: invokestatic 78	cn/com/xy/sms/sdk/util/d:c	(Ljava/lang/String;)Z
    //   82: pop
    //   83: new 23	java/lang/StringBuilder
    //   86: dup
    //   87: aload_1
    //   88: invokestatic 29	java/lang/String:valueOf	(Ljava/lang/Object;)Ljava/lang/String;
    //   91: invokespecial 32	java/lang/StringBuilder:<init>	(Ljava/lang/String;)V
    //   94: aload_2
    //   95: invokevirtual 36	java/lang/StringBuilder:append	(Ljava/lang/String;)Ljava/lang/StringBuilder;
    //   98: ldc_w 356
    //   101: invokevirtual 36	java/lang/StringBuilder:append	(Ljava/lang/String;)Ljava/lang/StringBuilder;
    //   104: invokevirtual 40	java/lang/StringBuilder:toString	()Ljava/lang/String;
    //   107: invokestatic 75	cn/com/xy/sms/sdk/util/d:a	(Ljava/lang/String;)Z
    //   110: ifeq +31 -> 141
    //   113: new 23	java/lang/StringBuilder
    //   116: dup
    //   117: aload_1
    //   118: invokestatic 29	java/lang/String:valueOf	(Ljava/lang/Object;)Ljava/lang/String;
    //   121: invokespecial 32	java/lang/StringBuilder:<init>	(Ljava/lang/String;)V
    //   124: aload_2
    //   125: invokevirtual 36	java/lang/StringBuilder:append	(Ljava/lang/String;)Ljava/lang/StringBuilder;
    //   128: ldc_w 356
    //   131: invokevirtual 36	java/lang/StringBuilder:append	(Ljava/lang/String;)Ljava/lang/StringBuilder;
    //   134: invokevirtual 40	java/lang/StringBuilder:toString	()Ljava/lang/String;
    //   137: invokestatic 78	cn/com/xy/sms/sdk/util/d:c	(Ljava/lang/String;)Z
    //   140: pop
    //   141: aload_0
    //   142: ldc_w 262
    //   145: invokevirtual 265	java/lang/String:startsWith	(Ljava/lang/String;)Z
    //   148: ifne +13 -> 161
    //   151: aload_0
    //   152: ldc_w 267
    //   155: invokevirtual 265	java/lang/String:startsWith	(Ljava/lang/String;)Z
    //   158: ifeq +287 -> 445
    //   161: aload_0
    //   162: iconst_0
    //   163: invokestatic 272	cn/com/xy/sms/sdk/net/b:a	(Ljava/lang/String;I)Ljavax/net/ssl/HttpsURLConnection;
    //   166: astore_0
    //   167: aload_0
    //   168: invokevirtual 292	java/net/HttpURLConnection:getInputStream	()Ljava/io/InputStream;
    //   171: astore 10
    //   173: aload 10
    //   175: astore 8
    //   177: aload_0
    //   178: astore 9
    //   180: aload 8
    //   182: astore_0
    //   183: aload 9
    //   185: astore 8
    //   187: aload 11
    //   189: astore 12
    //   191: aload 8
    //   193: astore 10
    //   195: aload_0
    //   196: astore 9
    //   198: aload 8
    //   200: ldc_w 293
    //   203: invokevirtual 297	java/net/HttpURLConnection:setConnectTimeout	(I)V
    //   206: iconst_0
    //   207: istore_3
    //   208: aload 11
    //   210: astore 12
    //   212: aload 8
    //   214: astore 10
    //   216: aload_0
    //   217: astore 9
    //   219: sipush 8192
    //   222: newarray <illegal type>
    //   224: astore 15
    //   226: aload 11
    //   228: astore 12
    //   230: aload 8
    //   232: astore 10
    //   234: aload_0
    //   235: astore 9
    //   237: aload 8
    //   239: invokevirtual 359	java/net/HttpURLConnection:getContentLength	()I
    //   242: i2l
    //   243: lstore 6
    //   245: aload 11
    //   247: astore 12
    //   249: aload 8
    //   251: astore 10
    //   253: aload_0
    //   254: astore 9
    //   256: new 21	java/io/File
    //   259: dup
    //   260: new 23	java/lang/StringBuilder
    //   263: dup
    //   264: aload_1
    //   265: invokestatic 29	java/lang/String:valueOf	(Ljava/lang/Object;)Ljava/lang/String;
    //   268: invokespecial 32	java/lang/StringBuilder:<init>	(Ljava/lang/String;)V
    //   271: aload_2
    //   272: invokevirtual 36	java/lang/StringBuilder:append	(Ljava/lang/String;)Ljava/lang/StringBuilder;
    //   275: ldc_w 356
    //   278: invokevirtual 36	java/lang/StringBuilder:append	(Ljava/lang/String;)Ljava/lang/StringBuilder;
    //   281: invokevirtual 40	java/lang/StringBuilder:toString	()Ljava/lang/String;
    //   284: invokespecial 41	java/io/File:<init>	(Ljava/lang/String;)V
    //   287: astore 14
    //   289: aload 11
    //   291: astore 12
    //   293: aload 8
    //   295: astore 10
    //   297: aload_0
    //   298: astore 9
    //   300: new 361	java/io/BufferedOutputStream
    //   303: dup
    //   304: new 43	java/io/FileOutputStream
    //   307: dup
    //   308: aload 14
    //   310: invokespecial 46	java/io/FileOutputStream:<init>	(Ljava/io/File;)V
    //   313: invokespecial 364	java/io/BufferedOutputStream:<init>	(Ljava/io/OutputStream;)V
    //   316: astore 11
    //   318: invokestatic 369	java/lang/Thread:interrupted	()Z
    //   321: ifne +17 -> 338
    //   324: aload_0
    //   325: aload 15
    //   327: invokevirtual 52	java/io/InputStream:read	([B)I
    //   330: istore 4
    //   332: iload 4
    //   334: iconst_m1
    //   335: if_icmpne +144 -> 479
    //   338: aload 11
    //   340: invokevirtual 370	java/io/BufferedOutputStream:flush	()V
    //   343: aload_2
    //   344: iconst_0
    //   345: aload_2
    //   346: ldc_w 372
    //   349: invokevirtual 376	java/lang/String:lastIndexOf	(Ljava/lang/String;)I
    //   352: invokevirtual 380	java/lang/String:substring	(II)Ljava/lang/String;
    //   355: astore 9
    //   357: iload_3
    //   358: i2l
    //   359: lload 6
    //   361: lcmp
    //   362: ifne +135 -> 497
    //   365: aload 9
    //   367: aload 14
    //   369: invokestatic 385	cn/com/xy/sms/sdk/util/l:a	(Ljava/io/File;)Ljava/lang/String;
    //   372: invokevirtual 171	java/lang/String:equals	(Ljava/lang/Object;)Z
    //   375: ifeq +372 -> 747
    //   378: new 23	java/lang/StringBuilder
    //   381: dup
    //   382: ldc_w 387
    //   385: invokespecial 32	java/lang/StringBuilder:<init>	(Ljava/lang/String;)V
    //   388: lload 6
    //   390: invokevirtual 325	java/lang/StringBuilder:append	(J)Ljava/lang/StringBuilder;
    //   393: ldc_w 389
    //   396: invokevirtual 36	java/lang/StringBuilder:append	(Ljava/lang/String;)Ljava/lang/StringBuilder;
    //   399: iload_3
    //   400: invokevirtual 283	java/lang/StringBuilder:append	(I)Ljava/lang/StringBuilder;
    //   403: pop
    //   404: aload_1
    //   405: new 23	java/lang/StringBuilder
    //   408: dup
    //   409: aload_2
    //   410: invokestatic 29	java/lang/String:valueOf	(Ljava/lang/Object;)Ljava/lang/String;
    //   413: invokespecial 32	java/lang/StringBuilder:<init>	(Ljava/lang/String;)V
    //   416: ldc_w 356
    //   419: invokevirtual 36	java/lang/StringBuilder:append	(Ljava/lang/String;)Ljava/lang/StringBuilder;
    //   422: invokevirtual 40	java/lang/StringBuilder:toString	()Ljava/lang/String;
    //   425: aload_2
    //   426: invokestatic 391	cn/com/xy/sms/sdk/util/d:a	(Ljava/lang/String;Ljava/lang/String;Ljava/lang/String;)V
    //   429: aload_0
    //   430: invokestatic 60	cn/com/xy/sms/sdk/util/d:a	(Ljava/io/Closeable;)V
    //   433: aload 11
    //   435: invokestatic 60	cn/com/xy/sms/sdk/util/d:a	(Ljava/io/Closeable;)V
    //   438: aload 8
    //   440: invokestatic 260	cn/com/xy/sms/sdk/util/d:a	(Ljava/net/HttpURLConnection;)V
    //   443: iconst_0
    //   444: ireturn
    //   445: new 301	java/net/URL
    //   448: dup
    //   449: aload_0
    //   450: invokespecial 302	java/net/URL:<init>	(Ljava/lang/String;)V
    //   453: invokevirtual 306	java/net/URL:openConnection	()Ljava/net/URLConnection;
    //   456: checkcast 143	java/net/HttpURLConnection
    //   459: astore_0
    //   460: aload_0
    //   461: invokevirtual 292	java/net/HttpURLConnection:getInputStream	()Ljava/io/InputStream;
    //   464: astore 10
    //   466: aload 10
    //   468: astore 9
    //   470: aload_0
    //   471: astore 8
    //   473: aload 9
    //   475: astore_0
    //   476: goto -289 -> 187
    //   479: aload 11
    //   481: aload 15
    //   483: iconst_0
    //   484: iload 4
    //   486: invokevirtual 392	java/io/BufferedOutputStream:write	([BII)V
    //   489: iload_3
    //   490: iload 4
    //   492: iadd
    //   493: istore_3
    //   494: goto -176 -> 318
    //   497: new 23	java/lang/StringBuilder
    //   500: dup
    //   501: aload_1
    //   502: invokestatic 29	java/lang/String:valueOf	(Ljava/lang/Object;)Ljava/lang/String;
    //   505: invokespecial 32	java/lang/StringBuilder:<init>	(Ljava/lang/String;)V
    //   508: aload_2
    //   509: invokevirtual 36	java/lang/StringBuilder:append	(Ljava/lang/String;)Ljava/lang/StringBuilder;
    //   512: invokevirtual 40	java/lang/StringBuilder:toString	()Ljava/lang/String;
    //   515: invokestatic 75	cn/com/xy/sms/sdk/util/d:a	(Ljava/lang/String;)Z
    //   518: ifeq +25 -> 543
    //   521: new 23	java/lang/StringBuilder
    //   524: dup
    //   525: aload_1
    //   526: invokestatic 29	java/lang/String:valueOf	(Ljava/lang/Object;)Ljava/lang/String;
    //   529: invokespecial 32	java/lang/StringBuilder:<init>	(Ljava/lang/String;)V
    //   532: aload_2
    //   533: invokevirtual 36	java/lang/StringBuilder:append	(Ljava/lang/String;)Ljava/lang/StringBuilder;
    //   536: invokevirtual 40	java/lang/StringBuilder:toString	()Ljava/lang/String;
    //   539: invokestatic 78	cn/com/xy/sms/sdk/util/d:c	(Ljava/lang/String;)Z
    //   542: pop
    //   543: new 23	java/lang/StringBuilder
    //   546: dup
    //   547: aload_1
    //   548: invokestatic 29	java/lang/String:valueOf	(Ljava/lang/Object;)Ljava/lang/String;
    //   551: invokespecial 32	java/lang/StringBuilder:<init>	(Ljava/lang/String;)V
    //   554: aload_2
    //   555: invokevirtual 36	java/lang/StringBuilder:append	(Ljava/lang/String;)Ljava/lang/StringBuilder;
    //   558: ldc_w 356
    //   561: invokevirtual 36	java/lang/StringBuilder:append	(Ljava/lang/String;)Ljava/lang/StringBuilder;
    //   564: invokevirtual 40	java/lang/StringBuilder:toString	()Ljava/lang/String;
    //   567: invokestatic 75	cn/com/xy/sms/sdk/util/d:a	(Ljava/lang/String;)Z
    //   570: ifeq +31 -> 601
    //   573: new 23	java/lang/StringBuilder
    //   576: dup
    //   577: aload_1
    //   578: invokestatic 29	java/lang/String:valueOf	(Ljava/lang/Object;)Ljava/lang/String;
    //   581: invokespecial 32	java/lang/StringBuilder:<init>	(Ljava/lang/String;)V
    //   584: aload_2
    //   585: invokevirtual 36	java/lang/StringBuilder:append	(Ljava/lang/String;)Ljava/lang/StringBuilder;
    //   588: ldc_w 356
    //   591: invokevirtual 36	java/lang/StringBuilder:append	(Ljava/lang/String;)Ljava/lang/StringBuilder;
    //   594: invokevirtual 40	java/lang/StringBuilder:toString	()Ljava/lang/String;
    //   597: invokestatic 78	cn/com/xy/sms/sdk/util/d:c	(Ljava/lang/String;)Z
    //   600: pop
    //   601: aload_0
    //   602: invokestatic 60	cn/com/xy/sms/sdk/util/d:a	(Ljava/io/Closeable;)V
    //   605: aload 11
    //   607: invokestatic 60	cn/com/xy/sms/sdk/util/d:a	(Ljava/io/Closeable;)V
    //   610: aload 8
    //   612: invokestatic 260	cn/com/xy/sms/sdk/util/d:a	(Ljava/net/HttpURLConnection;)V
    //   615: iconst_m1
    //   616: ireturn
    //   617: astore_2
    //   618: aconst_null
    //   619: astore_1
    //   620: aconst_null
    //   621: astore_0
    //   622: aload_2
    //   623: invokevirtual 326	java/net/MalformedURLException:printStackTrace	()V
    //   626: new 23	java/lang/StringBuilder
    //   629: dup
    //   630: ldc 69
    //   632: invokespecial 32	java/lang/StringBuilder:<init>	(Ljava/lang/String;)V
    //   635: aload_2
    //   636: invokevirtual 327	java/net/MalformedURLException:getLocalizedMessage	()Ljava/lang/String;
    //   639: invokevirtual 36	java/lang/StringBuilder:append	(Ljava/lang/String;)Ljava/lang/StringBuilder;
    //   642: pop
    //   643: aload 8
    //   645: invokestatic 60	cn/com/xy/sms/sdk/util/d:a	(Ljava/io/Closeable;)V
    //   648: aload_0
    //   649: invokestatic 60	cn/com/xy/sms/sdk/util/d:a	(Ljava/io/Closeable;)V
    //   652: aload_1
    //   653: invokestatic 260	cn/com/xy/sms/sdk/util/d:a	(Ljava/net/HttpURLConnection;)V
    //   656: iconst_m1
    //   657: ireturn
    //   658: astore_1
    //   659: aconst_null
    //   660: astore_0
    //   661: aconst_null
    //   662: astore 8
    //   664: aload 13
    //   666: astore_2
    //   667: aload_2
    //   668: astore 12
    //   670: aload 8
    //   672: astore 10
    //   674: aload_0
    //   675: astore 9
    //   677: aload_1
    //   678: invokevirtual 67	java/lang/Throwable:printStackTrace	()V
    //   681: aload_2
    //   682: astore 12
    //   684: aload 8
    //   686: astore 10
    //   688: aload_0
    //   689: astore 9
    //   691: new 23	java/lang/StringBuilder
    //   694: dup
    //   695: ldc 69
    //   697: invokespecial 32	java/lang/StringBuilder:<init>	(Ljava/lang/String;)V
    //   700: aload_1
    //   701: invokevirtual 72	java/lang/Throwable:getLocalizedMessage	()Ljava/lang/String;
    //   704: invokevirtual 36	java/lang/StringBuilder:append	(Ljava/lang/String;)Ljava/lang/StringBuilder;
    //   707: pop
    //   708: aload_0
    //   709: invokestatic 60	cn/com/xy/sms/sdk/util/d:a	(Ljava/io/Closeable;)V
    //   712: aload_2
    //   713: invokestatic 60	cn/com/xy/sms/sdk/util/d:a	(Ljava/io/Closeable;)V
    //   716: aload 8
    //   718: invokestatic 260	cn/com/xy/sms/sdk/util/d:a	(Ljava/net/HttpURLConnection;)V
    //   721: iconst_m1
    //   722: ireturn
    //   723: astore_1
    //   724: aconst_null
    //   725: astore_0
    //   726: aconst_null
    //   727: astore 8
    //   729: aload 9
    //   731: astore_2
    //   732: aload_0
    //   733: invokestatic 60	cn/com/xy/sms/sdk/util/d:a	(Ljava/io/Closeable;)V
    //   736: aload_2
    //   737: invokestatic 60	cn/com/xy/sms/sdk/util/d:a	(Ljava/io/Closeable;)V
    //   740: aload 8
    //   742: invokestatic 260	cn/com/xy/sms/sdk/util/d:a	(Ljava/net/HttpURLConnection;)V
    //   745: aload_1
    //   746: athrow
    //   747: aload_0
    //   748: invokestatic 60	cn/com/xy/sms/sdk/util/d:a	(Ljava/io/Closeable;)V
    //   751: aload 11
    //   753: invokestatic 60	cn/com/xy/sms/sdk/util/d:a	(Ljava/io/Closeable;)V
    //   756: aload 8
    //   758: invokestatic 260	cn/com/xy/sms/sdk/util/d:a	(Ljava/net/HttpURLConnection;)V
    //   761: iconst_m1
    //   762: ireturn
    //   763: astore_1
    //   764: aconst_null
    //   765: astore 10
    //   767: aload 9
    //   769: astore_2
    //   770: aload_0
    //   771: astore 8
    //   773: aload 10
    //   775: astore_0
    //   776: goto -44 -> 732
    //   779: astore_1
    //   780: aconst_null
    //   781: astore 10
    //   783: aload 9
    //   785: astore_2
    //   786: aload_0
    //   787: astore 8
    //   789: aload 10
    //   791: astore_0
    //   792: goto -60 -> 732
    //   795: astore_1
    //   796: aload 12
    //   798: astore_2
    //   799: aload 10
    //   801: astore 8
    //   803: aload 9
    //   805: astore_0
    //   806: goto -74 -> 732
    //   809: astore_1
    //   810: aload 11
    //   812: astore_2
    //   813: goto -81 -> 732
    //   816: astore_2
    //   817: aload 8
    //   819: astore 9
    //   821: aload_1
    //   822: astore 8
    //   824: aload_2
    //   825: astore_1
    //   826: aload_0
    //   827: astore_2
    //   828: aload 9
    //   830: astore_0
    //   831: goto -99 -> 732
    //   834: astore_1
    //   835: aconst_null
    //   836: astore 9
    //   838: aload 13
    //   840: astore_2
    //   841: aload_0
    //   842: astore 8
    //   844: aload 9
    //   846: astore_0
    //   847: goto -180 -> 667
    //   850: astore_1
    //   851: aconst_null
    //   852: astore 9
    //   854: aload 13
    //   856: astore_2
    //   857: aload_0
    //   858: astore 8
    //   860: aload 9
    //   862: astore_0
    //   863: goto -196 -> 667
    //   866: astore_1
    //   867: aload 13
    //   869: astore_2
    //   870: goto -203 -> 667
    //   873: astore_1
    //   874: aload 11
    //   876: astore_2
    //   877: goto -210 -> 667
    //   880: astore_2
    //   881: aload_0
    //   882: astore_1
    //   883: aconst_null
    //   884: astore_0
    //   885: goto -263 -> 622
    //   888: astore_2
    //   889: aconst_null
    //   890: astore 9
    //   892: aload_0
    //   893: astore_1
    //   894: aload 9
    //   896: astore_0
    //   897: goto -275 -> 622
    //   900: astore_2
    //   901: aconst_null
    //   902: astore 9
    //   904: aload 8
    //   906: astore_1
    //   907: aload_0
    //   908: astore 8
    //   910: aload 9
    //   912: astore_0
    //   913: goto -291 -> 622
    //   916: astore_2
    //   917: aload 8
    //   919: astore_1
    //   920: aload_0
    //   921: astore 8
    //   923: aload 11
    //   925: astore_0
    //   926: goto -304 -> 622
    // Local variable table:
    //   start	length	slot	name	signature
    //   0	929	0	paramString1	String
    //   0	929	1	paramString2	String
    //   0	929	2	paramString3	String
    //   207	287	3	i	int
    //   330	163	4	j	int
    //   16	3	5	bool	boolean
    //   243	146	6	l	long
    //   1	921	8	localObject1	Object
    //   4	907	9	localObject2	Object
    //   171	629	10	localObject3	Object
    //   7	917	11	localBufferedOutputStream	java.io.BufferedOutputStream
    //   189	608	12	localObject4	Object
    //   10	858	13	localObject5	Object
    //   287	81	14	localFile	File
    //   224	258	15	arrayOfByte	byte[]
    // Exception table:
    //   from	to	target	type
    //   12	18	617	java/net/MalformedURLException
    //   37	83	617	java/net/MalformedURLException
    //   83	141	617	java/net/MalformedURLException
    //   141	161	617	java/net/MalformedURLException
    //   161	167	617	java/net/MalformedURLException
    //   445	460	617	java/net/MalformedURLException
    //   12	18	658	java/lang/Throwable
    //   37	83	658	java/lang/Throwable
    //   83	141	658	java/lang/Throwable
    //   141	161	658	java/lang/Throwable
    //   161	167	658	java/lang/Throwable
    //   445	460	658	java/lang/Throwable
    //   12	18	723	finally
    //   37	83	723	finally
    //   83	141	723	finally
    //   141	161	723	finally
    //   161	167	723	finally
    //   445	460	723	finally
    //   167	173	763	finally
    //   460	466	779	finally
    //   198	206	795	finally
    //   219	226	795	finally
    //   237	245	795	finally
    //   256	289	795	finally
    //   300	318	795	finally
    //   677	681	795	finally
    //   691	708	795	finally
    //   318	332	809	finally
    //   338	357	809	finally
    //   365	429	809	finally
    //   479	489	809	finally
    //   497	543	809	finally
    //   543	601	809	finally
    //   622	643	816	finally
    //   167	173	834	java/lang/Throwable
    //   460	466	850	java/lang/Throwable
    //   198	206	866	java/lang/Throwable
    //   219	226	866	java/lang/Throwable
    //   237	245	866	java/lang/Throwable
    //   256	289	866	java/lang/Throwable
    //   300	318	866	java/lang/Throwable
    //   318	332	873	java/lang/Throwable
    //   338	357	873	java/lang/Throwable
    //   365	429	873	java/lang/Throwable
    //   479	489	873	java/lang/Throwable
    //   497	543	873	java/lang/Throwable
    //   543	601	873	java/lang/Throwable
    //   167	173	880	java/net/MalformedURLException
    //   460	466	888	java/net/MalformedURLException
    //   198	206	900	java/net/MalformedURLException
    //   219	226	900	java/net/MalformedURLException
    //   237	245	900	java/net/MalformedURLException
    //   256	289	900	java/net/MalformedURLException
    //   300	318	900	java/net/MalformedURLException
    //   318	332	916	java/net/MalformedURLException
    //   338	357	916	java/net/MalformedURLException
    //   365	429	916	java/net/MalformedURLException
    //   479	489	916	java/net/MalformedURLException
    //   497	543	916	java/net/MalformedURLException
    //   543	601	916	java/net/MalformedURLException
  }
  
  /* Error */
  public static List<String> g(String paramString)
  {
    // Byte code:
    //   0: aconst_null
    //   1: astore_3
    //   2: invokestatic 194	cn/com/xy/sms/sdk/constant/Constant:getContext	()Landroid/content/Context;
    //   5: invokevirtual 334	android/content/Context:getResources	()Landroid/content/res/Resources;
    //   8: invokevirtual 340	android/content/res/Resources:getAssets	()Landroid/content/res/AssetManager;
    //   11: aload_0
    //   12: invokevirtual 345	android/content/res/AssetManager:open	(Ljava/lang/String;)Ljava/io/InputStream;
    //   15: astore_0
    //   16: new 395	java/io/BufferedReader
    //   19: dup
    //   20: new 397	java/io/InputStreamReader
    //   23: dup
    //   24: aload_0
    //   25: ldc_w 351
    //   28: invokespecial 400	java/io/InputStreamReader:<init>	(Ljava/io/InputStream;Ljava/lang/String;)V
    //   31: invokespecial 403	java/io/BufferedReader:<init>	(Ljava/io/Reader;)V
    //   34: astore_1
    //   35: aload_1
    //   36: astore_3
    //   37: aload_0
    //   38: astore_2
    //   39: new 242	java/util/ArrayList
    //   42: dup
    //   43: invokespecial 243	java/util/ArrayList:<init>	()V
    //   46: astore 4
    //   48: aload_1
    //   49: astore_3
    //   50: aload_0
    //   51: astore_2
    //   52: aload_1
    //   53: invokevirtual 406	java/io/BufferedReader:readLine	()Ljava/lang/String;
    //   56: astore 5
    //   58: aload 5
    //   60: ifnonnull +14 -> 74
    //   63: aload_1
    //   64: invokestatic 60	cn/com/xy/sms/sdk/util/d:a	(Ljava/io/Closeable;)V
    //   67: aload_0
    //   68: invokestatic 60	cn/com/xy/sms/sdk/util/d:a	(Ljava/io/Closeable;)V
    //   71: aload 4
    //   73: areturn
    //   74: aload_1
    //   75: astore_3
    //   76: aload_0
    //   77: astore_2
    //   78: aload 4
    //   80: aload 5
    //   82: invokeinterface 409 2 0
    //   87: pop
    //   88: goto -40 -> 48
    //   91: astore_2
    //   92: aload_1
    //   93: astore_2
    //   94: aload_0
    //   95: astore_1
    //   96: aload_2
    //   97: astore_0
    //   98: aload_0
    //   99: invokestatic 60	cn/com/xy/sms/sdk/util/d:a	(Ljava/io/Closeable;)V
    //   102: aload_1
    //   103: invokestatic 60	cn/com/xy/sms/sdk/util/d:a	(Ljava/io/Closeable;)V
    //   106: aconst_null
    //   107: areturn
    //   108: astore 4
    //   110: aconst_null
    //   111: astore_1
    //   112: aconst_null
    //   113: astore_0
    //   114: aload_1
    //   115: astore_3
    //   116: aload_0
    //   117: astore_2
    //   118: aload 4
    //   120: invokevirtual 67	java/lang/Throwable:printStackTrace	()V
    //   123: aload_1
    //   124: invokestatic 60	cn/com/xy/sms/sdk/util/d:a	(Ljava/io/Closeable;)V
    //   127: aload_0
    //   128: invokestatic 60	cn/com/xy/sms/sdk/util/d:a	(Ljava/io/Closeable;)V
    //   131: goto -25 -> 106
    //   134: astore_1
    //   135: aconst_null
    //   136: astore_0
    //   137: aload_3
    //   138: invokestatic 60	cn/com/xy/sms/sdk/util/d:a	(Ljava/io/Closeable;)V
    //   141: aload_0
    //   142: invokestatic 60	cn/com/xy/sms/sdk/util/d:a	(Ljava/io/Closeable;)V
    //   145: aload_1
    //   146: athrow
    //   147: astore_1
    //   148: goto -11 -> 137
    //   151: astore_1
    //   152: aload_2
    //   153: astore_0
    //   154: goto -17 -> 137
    //   157: astore 4
    //   159: aconst_null
    //   160: astore_1
    //   161: goto -47 -> 114
    //   164: astore 4
    //   166: goto -52 -> 114
    //   169: astore_0
    //   170: aconst_null
    //   171: astore_0
    //   172: aconst_null
    //   173: astore_1
    //   174: goto -76 -> 98
    //   177: astore_1
    //   178: aconst_null
    //   179: astore_2
    //   180: aload_0
    //   181: astore_1
    //   182: aload_2
    //   183: astore_0
    //   184: goto -86 -> 98
    // Local variable table:
    //   start	length	slot	name	signature
    //   0	187	0	paramString	String
    //   34	90	1	localObject1	Object
    //   134	12	1	localObject2	Object
    //   147	1	1	localObject3	Object
    //   151	1	1	localObject4	Object
    //   160	14	1	localObject5	Object
    //   177	1	1	localIOException1	java.io.IOException
    //   181	1	1	str1	String
    //   38	40	2	str2	String
    //   91	1	2	localIOException2	java.io.IOException
    //   93	90	2	localObject6	Object
    //   1	137	3	localObject7	Object
    //   46	33	4	localArrayList	ArrayList
    //   108	11	4	localThrowable1	Throwable
    //   157	1	4	localThrowable2	Throwable
    //   164	1	4	localThrowable3	Throwable
    //   56	25	5	str3	String
    // Exception table:
    //   from	to	target	type
    //   39	48	91	java/io/IOException
    //   52	58	91	java/io/IOException
    //   78	88	91	java/io/IOException
    //   2	16	108	java/lang/Throwable
    //   2	16	134	finally
    //   16	35	147	finally
    //   39	48	151	finally
    //   52	58	151	finally
    //   78	88	151	finally
    //   118	123	151	finally
    //   16	35	157	java/lang/Throwable
    //   39	48	164	java/lang/Throwable
    //   52	58	164	java/lang/Throwable
    //   78	88	164	java/lang/Throwable
    //   2	16	169	java/io/IOException
    //   16	35	177	java/io/IOException
  }
  
  /* Error */
  private static int h(String paramString1, String paramString2, String paramString3)
  {
    // Byte code:
    //   0: aconst_null
    //   1: astore 12
    //   3: aconst_null
    //   4: astore 13
    //   6: aconst_null
    //   7: astore 11
    //   9: aload_0
    //   10: invokestatic 226	cn/com/xy/sms/sdk/util/StringUtils:isNull	(Ljava/lang/String;)Z
    //   13: istore 5
    //   15: iload 5
    //   17: ifeq +25 -> 42
    //   20: aconst_null
    //   21: astore 10
    //   23: aconst_null
    //   24: astore 9
    //   26: aload 9
    //   28: invokestatic 60	cn/com/xy/sms/sdk/util/d:a	(Ljava/io/Closeable;)V
    //   31: aconst_null
    //   32: invokestatic 60	cn/com/xy/sms/sdk/util/d:a	(Ljava/io/Closeable;)V
    //   35: aload 10
    //   37: invokestatic 260	cn/com/xy/sms/sdk/util/d:a	(Ljava/net/HttpURLConnection;)V
    //   40: iconst_m1
    //   41: ireturn
    //   42: new 23	java/lang/StringBuilder
    //   45: dup
    //   46: aload_1
    //   47: invokestatic 29	java/lang/String:valueOf	(Ljava/lang/Object;)Ljava/lang/String;
    //   50: invokespecial 32	java/lang/StringBuilder:<init>	(Ljava/lang/String;)V
    //   53: aload_2
    //   54: invokevirtual 36	java/lang/StringBuilder:append	(Ljava/lang/String;)Ljava/lang/StringBuilder;
    //   57: invokevirtual 40	java/lang/StringBuilder:toString	()Ljava/lang/String;
    //   60: invokestatic 75	cn/com/xy/sms/sdk/util/d:a	(Ljava/lang/String;)Z
    //   63: ifeq +25 -> 88
    //   66: new 23	java/lang/StringBuilder
    //   69: dup
    //   70: aload_1
    //   71: invokestatic 29	java/lang/String:valueOf	(Ljava/lang/Object;)Ljava/lang/String;
    //   74: invokespecial 32	java/lang/StringBuilder:<init>	(Ljava/lang/String;)V
    //   77: aload_2
    //   78: invokevirtual 36	java/lang/StringBuilder:append	(Ljava/lang/String;)Ljava/lang/StringBuilder;
    //   81: invokevirtual 40	java/lang/StringBuilder:toString	()Ljava/lang/String;
    //   84: invokestatic 78	cn/com/xy/sms/sdk/util/d:c	(Ljava/lang/String;)Z
    //   87: pop
    //   88: new 23	java/lang/StringBuilder
    //   91: dup
    //   92: aload_1
    //   93: invokestatic 29	java/lang/String:valueOf	(Ljava/lang/Object;)Ljava/lang/String;
    //   96: invokespecial 32	java/lang/StringBuilder:<init>	(Ljava/lang/String;)V
    //   99: aload_2
    //   100: invokevirtual 36	java/lang/StringBuilder:append	(Ljava/lang/String;)Ljava/lang/StringBuilder;
    //   103: ldc_w 356
    //   106: invokevirtual 36	java/lang/StringBuilder:append	(Ljava/lang/String;)Ljava/lang/StringBuilder;
    //   109: invokevirtual 40	java/lang/StringBuilder:toString	()Ljava/lang/String;
    //   112: invokestatic 75	cn/com/xy/sms/sdk/util/d:a	(Ljava/lang/String;)Z
    //   115: ifeq +31 -> 146
    //   118: new 23	java/lang/StringBuilder
    //   121: dup
    //   122: aload_1
    //   123: invokestatic 29	java/lang/String:valueOf	(Ljava/lang/Object;)Ljava/lang/String;
    //   126: invokespecial 32	java/lang/StringBuilder:<init>	(Ljava/lang/String;)V
    //   129: aload_2
    //   130: invokevirtual 36	java/lang/StringBuilder:append	(Ljava/lang/String;)Ljava/lang/StringBuilder;
    //   133: ldc_w 356
    //   136: invokevirtual 36	java/lang/StringBuilder:append	(Ljava/lang/String;)Ljava/lang/StringBuilder;
    //   139: invokevirtual 40	java/lang/StringBuilder:toString	()Ljava/lang/String;
    //   142: invokestatic 78	cn/com/xy/sms/sdk/util/d:c	(Ljava/lang/String;)Z
    //   145: pop
    //   146: aload_0
    //   147: ldc_w 262
    //   150: invokevirtual 265	java/lang/String:startsWith	(Ljava/lang/String;)Z
    //   153: ifne +13 -> 166
    //   156: aload_0
    //   157: ldc_w 267
    //   160: invokevirtual 265	java/lang/String:startsWith	(Ljava/lang/String;)Z
    //   163: ifeq +213 -> 376
    //   166: aload_0
    //   167: iconst_0
    //   168: invokestatic 272	cn/com/xy/sms/sdk/net/b:a	(Ljava/lang/String;I)Ljavax/net/ssl/HttpsURLConnection;
    //   171: astore 8
    //   173: aload 8
    //   175: ifnull +674 -> 849
    //   178: aload 8
    //   180: invokevirtual 292	java/net/HttpURLConnection:getInputStream	()Ljava/io/InputStream;
    //   183: astore_0
    //   184: aload 8
    //   186: astore 9
    //   188: aload_0
    //   189: astore 8
    //   191: aload 9
    //   193: astore_0
    //   194: aload_0
    //   195: astore 10
    //   197: aload 8
    //   199: astore 9
    //   201: aload_0
    //   202: ifnull -176 -> 26
    //   205: aload_0
    //   206: ldc_w 293
    //   209: invokevirtual 297	java/net/HttpURLConnection:setConnectTimeout	(I)V
    //   212: sipush 8192
    //   215: newarray <illegal type>
    //   217: astore 10
    //   219: aload_0
    //   220: invokevirtual 359	java/net/HttpURLConnection:getContentLength	()I
    //   223: i2l
    //   224: lstore 6
    //   226: new 361	java/io/BufferedOutputStream
    //   229: dup
    //   230: new 43	java/io/FileOutputStream
    //   233: dup
    //   234: new 21	java/io/File
    //   237: dup
    //   238: new 23	java/lang/StringBuilder
    //   241: dup
    //   242: aload_1
    //   243: invokestatic 29	java/lang/String:valueOf	(Ljava/lang/Object;)Ljava/lang/String;
    //   246: invokespecial 32	java/lang/StringBuilder:<init>	(Ljava/lang/String;)V
    //   249: aload_2
    //   250: invokevirtual 36	java/lang/StringBuilder:append	(Ljava/lang/String;)Ljava/lang/StringBuilder;
    //   253: ldc_w 356
    //   256: invokevirtual 36	java/lang/StringBuilder:append	(Ljava/lang/String;)Ljava/lang/StringBuilder;
    //   259: invokevirtual 40	java/lang/StringBuilder:toString	()Ljava/lang/String;
    //   262: invokespecial 41	java/io/File:<init>	(Ljava/lang/String;)V
    //   265: invokespecial 46	java/io/FileOutputStream:<init>	(Ljava/io/File;)V
    //   268: invokespecial 364	java/io/BufferedOutputStream:<init>	(Ljava/io/OutputStream;)V
    //   271: astore 9
    //   273: iconst_0
    //   274: istore_3
    //   275: invokestatic 369	java/lang/Thread:interrupted	()Z
    //   278: ifne +18 -> 296
    //   281: aload 8
    //   283: aload 10
    //   285: invokevirtual 52	java/io/InputStream:read	([B)I
    //   288: istore 4
    //   290: iload 4
    //   292: iconst_m1
    //   293: if_icmpne +107 -> 400
    //   296: aload 9
    //   298: invokevirtual 370	java/io/BufferedOutputStream:flush	()V
    //   301: iload_3
    //   302: i2l
    //   303: lload 6
    //   305: lcmp
    //   306: ifne +112 -> 418
    //   309: new 23	java/lang/StringBuilder
    //   312: dup
    //   313: ldc_w 387
    //   316: invokespecial 32	java/lang/StringBuilder:<init>	(Ljava/lang/String;)V
    //   319: lload 6
    //   321: invokevirtual 325	java/lang/StringBuilder:append	(J)Ljava/lang/StringBuilder;
    //   324: ldc_w 389
    //   327: invokevirtual 36	java/lang/StringBuilder:append	(Ljava/lang/String;)Ljava/lang/StringBuilder;
    //   330: iload_3
    //   331: invokevirtual 283	java/lang/StringBuilder:append	(I)Ljava/lang/StringBuilder;
    //   334: pop
    //   335: aload_1
    //   336: new 23	java/lang/StringBuilder
    //   339: dup
    //   340: aload_2
    //   341: invokestatic 29	java/lang/String:valueOf	(Ljava/lang/Object;)Ljava/lang/String;
    //   344: invokespecial 32	java/lang/StringBuilder:<init>	(Ljava/lang/String;)V
    //   347: ldc_w 356
    //   350: invokevirtual 36	java/lang/StringBuilder:append	(Ljava/lang/String;)Ljava/lang/StringBuilder;
    //   353: invokevirtual 40	java/lang/StringBuilder:toString	()Ljava/lang/String;
    //   356: aload_2
    //   357: invokestatic 391	cn/com/xy/sms/sdk/util/d:a	(Ljava/lang/String;Ljava/lang/String;Ljava/lang/String;)V
    //   360: aload 8
    //   362: invokestatic 60	cn/com/xy/sms/sdk/util/d:a	(Ljava/io/Closeable;)V
    //   365: aload 9
    //   367: invokestatic 60	cn/com/xy/sms/sdk/util/d:a	(Ljava/io/Closeable;)V
    //   370: aload_0
    //   371: invokestatic 260	cn/com/xy/sms/sdk/util/d:a	(Ljava/net/HttpURLConnection;)V
    //   374: iconst_0
    //   375: ireturn
    //   376: new 301	java/net/URL
    //   379: dup
    //   380: aload_0
    //   381: invokespecial 302	java/net/URL:<init>	(Ljava/lang/String;)V
    //   384: invokevirtual 306	java/net/URL:openConnection	()Ljava/net/URLConnection;
    //   387: checkcast 143	java/net/HttpURLConnection
    //   390: astore_0
    //   391: aload_0
    //   392: invokevirtual 292	java/net/HttpURLConnection:getInputStream	()Ljava/io/InputStream;
    //   395: astore 8
    //   397: goto -203 -> 194
    //   400: aload 9
    //   402: aload 10
    //   404: iconst_0
    //   405: iload 4
    //   407: invokevirtual 392	java/io/BufferedOutputStream:write	([BII)V
    //   410: iload_3
    //   411: iload 4
    //   413: iadd
    //   414: istore_3
    //   415: goto -140 -> 275
    //   418: new 23	java/lang/StringBuilder
    //   421: dup
    //   422: aload_1
    //   423: invokestatic 29	java/lang/String:valueOf	(Ljava/lang/Object;)Ljava/lang/String;
    //   426: invokespecial 32	java/lang/StringBuilder:<init>	(Ljava/lang/String;)V
    //   429: aload_2
    //   430: invokevirtual 36	java/lang/StringBuilder:append	(Ljava/lang/String;)Ljava/lang/StringBuilder;
    //   433: invokevirtual 40	java/lang/StringBuilder:toString	()Ljava/lang/String;
    //   436: invokestatic 75	cn/com/xy/sms/sdk/util/d:a	(Ljava/lang/String;)Z
    //   439: ifeq +25 -> 464
    //   442: new 23	java/lang/StringBuilder
    //   445: dup
    //   446: aload_1
    //   447: invokestatic 29	java/lang/String:valueOf	(Ljava/lang/Object;)Ljava/lang/String;
    //   450: invokespecial 32	java/lang/StringBuilder:<init>	(Ljava/lang/String;)V
    //   453: aload_2
    //   454: invokevirtual 36	java/lang/StringBuilder:append	(Ljava/lang/String;)Ljava/lang/StringBuilder;
    //   457: invokevirtual 40	java/lang/StringBuilder:toString	()Ljava/lang/String;
    //   460: invokestatic 78	cn/com/xy/sms/sdk/util/d:c	(Ljava/lang/String;)Z
    //   463: pop
    //   464: new 23	java/lang/StringBuilder
    //   467: dup
    //   468: aload_1
    //   469: invokestatic 29	java/lang/String:valueOf	(Ljava/lang/Object;)Ljava/lang/String;
    //   472: invokespecial 32	java/lang/StringBuilder:<init>	(Ljava/lang/String;)V
    //   475: aload_2
    //   476: invokevirtual 36	java/lang/StringBuilder:append	(Ljava/lang/String;)Ljava/lang/StringBuilder;
    //   479: ldc_w 356
    //   482: invokevirtual 36	java/lang/StringBuilder:append	(Ljava/lang/String;)Ljava/lang/StringBuilder;
    //   485: invokevirtual 40	java/lang/StringBuilder:toString	()Ljava/lang/String;
    //   488: invokestatic 75	cn/com/xy/sms/sdk/util/d:a	(Ljava/lang/String;)Z
    //   491: ifeq +31 -> 522
    //   494: new 23	java/lang/StringBuilder
    //   497: dup
    //   498: aload_1
    //   499: invokestatic 29	java/lang/String:valueOf	(Ljava/lang/Object;)Ljava/lang/String;
    //   502: invokespecial 32	java/lang/StringBuilder:<init>	(Ljava/lang/String;)V
    //   505: aload_2
    //   506: invokevirtual 36	java/lang/StringBuilder:append	(Ljava/lang/String;)Ljava/lang/StringBuilder;
    //   509: ldc_w 356
    //   512: invokevirtual 36	java/lang/StringBuilder:append	(Ljava/lang/String;)Ljava/lang/StringBuilder;
    //   515: invokevirtual 40	java/lang/StringBuilder:toString	()Ljava/lang/String;
    //   518: invokestatic 78	cn/com/xy/sms/sdk/util/d:c	(Ljava/lang/String;)Z
    //   521: pop
    //   522: aload 8
    //   524: invokestatic 60	cn/com/xy/sms/sdk/util/d:a	(Ljava/io/Closeable;)V
    //   527: aload 9
    //   529: invokestatic 60	cn/com/xy/sms/sdk/util/d:a	(Ljava/io/Closeable;)V
    //   532: aload_0
    //   533: invokestatic 260	cn/com/xy/sms/sdk/util/d:a	(Ljava/net/HttpURLConnection;)V
    //   536: iconst_m1
    //   537: ireturn
    //   538: astore_2
    //   539: aconst_null
    //   540: astore_0
    //   541: aconst_null
    //   542: astore_1
    //   543: aload 11
    //   545: astore 9
    //   547: aload 9
    //   549: astore 11
    //   551: aload_0
    //   552: astore 10
    //   554: aload_1
    //   555: astore 8
    //   557: aload_2
    //   558: invokevirtual 326	java/net/MalformedURLException:printStackTrace	()V
    //   561: aload 9
    //   563: astore 11
    //   565: aload_0
    //   566: astore 10
    //   568: aload_1
    //   569: astore 8
    //   571: new 23	java/lang/StringBuilder
    //   574: dup
    //   575: ldc 69
    //   577: invokespecial 32	java/lang/StringBuilder:<init>	(Ljava/lang/String;)V
    //   580: aload_2
    //   581: invokevirtual 327	java/net/MalformedURLException:getLocalizedMessage	()Ljava/lang/String;
    //   584: invokevirtual 36	java/lang/StringBuilder:append	(Ljava/lang/String;)Ljava/lang/StringBuilder;
    //   587: pop
    //   588: aload_1
    //   589: invokestatic 60	cn/com/xy/sms/sdk/util/d:a	(Ljava/io/Closeable;)V
    //   592: aload 9
    //   594: invokestatic 60	cn/com/xy/sms/sdk/util/d:a	(Ljava/io/Closeable;)V
    //   597: aload_0
    //   598: invokestatic 260	cn/com/xy/sms/sdk/util/d:a	(Ljava/net/HttpURLConnection;)V
    //   601: iconst_m1
    //   602: ireturn
    //   603: astore_2
    //   604: aconst_null
    //   605: astore_0
    //   606: aconst_null
    //   607: astore_1
    //   608: aload 12
    //   610: astore 9
    //   612: aload 9
    //   614: astore 11
    //   616: aload_0
    //   617: astore 10
    //   619: aload_1
    //   620: astore 8
    //   622: aload_2
    //   623: invokevirtual 67	java/lang/Throwable:printStackTrace	()V
    //   626: aload 9
    //   628: astore 11
    //   630: aload_0
    //   631: astore 10
    //   633: aload_1
    //   634: astore 8
    //   636: new 23	java/lang/StringBuilder
    //   639: dup
    //   640: ldc 69
    //   642: invokespecial 32	java/lang/StringBuilder:<init>	(Ljava/lang/String;)V
    //   645: aload_2
    //   646: invokevirtual 72	java/lang/Throwable:getLocalizedMessage	()Ljava/lang/String;
    //   649: invokevirtual 36	java/lang/StringBuilder:append	(Ljava/lang/String;)Ljava/lang/StringBuilder;
    //   652: pop
    //   653: aload_1
    //   654: invokestatic 60	cn/com/xy/sms/sdk/util/d:a	(Ljava/io/Closeable;)V
    //   657: aload 9
    //   659: invokestatic 60	cn/com/xy/sms/sdk/util/d:a	(Ljava/io/Closeable;)V
    //   662: aload_0
    //   663: invokestatic 260	cn/com/xy/sms/sdk/util/d:a	(Ljava/net/HttpURLConnection;)V
    //   666: iconst_m1
    //   667: ireturn
    //   668: astore_0
    //   669: aconst_null
    //   670: astore_1
    //   671: aconst_null
    //   672: astore_2
    //   673: aload 13
    //   675: astore 9
    //   677: aload_2
    //   678: invokestatic 60	cn/com/xy/sms/sdk/util/d:a	(Ljava/io/Closeable;)V
    //   681: aload 9
    //   683: invokestatic 60	cn/com/xy/sms/sdk/util/d:a	(Ljava/io/Closeable;)V
    //   686: aload_1
    //   687: invokestatic 260	cn/com/xy/sms/sdk/util/d:a	(Ljava/net/HttpURLConnection;)V
    //   690: aload_0
    //   691: athrow
    //   692: astore_0
    //   693: aconst_null
    //   694: astore_2
    //   695: aload 13
    //   697: astore 9
    //   699: aload 8
    //   701: astore_1
    //   702: goto -25 -> 677
    //   705: astore_2
    //   706: aconst_null
    //   707: astore 8
    //   709: aload_0
    //   710: astore_1
    //   711: aload_2
    //   712: astore_0
    //   713: aload 13
    //   715: astore 9
    //   717: aload 8
    //   719: astore_2
    //   720: goto -43 -> 677
    //   723: astore 9
    //   725: aload 8
    //   727: astore_2
    //   728: aload_0
    //   729: astore_1
    //   730: aload 9
    //   732: astore_0
    //   733: aload 13
    //   735: astore 9
    //   737: goto -60 -> 677
    //   740: astore 10
    //   742: aload 8
    //   744: astore_2
    //   745: aload_0
    //   746: astore_1
    //   747: aload 10
    //   749: astore_0
    //   750: goto -73 -> 677
    //   753: astore_0
    //   754: aload 11
    //   756: astore 9
    //   758: aload 10
    //   760: astore_1
    //   761: aload 8
    //   763: astore_2
    //   764: goto -87 -> 677
    //   767: astore_2
    //   768: aconst_null
    //   769: astore_1
    //   770: aload 12
    //   772: astore 9
    //   774: aload 8
    //   776: astore_0
    //   777: goto -165 -> 612
    //   780: astore_2
    //   781: aconst_null
    //   782: astore_1
    //   783: aload 12
    //   785: astore 9
    //   787: goto -175 -> 612
    //   790: astore_2
    //   791: aload 8
    //   793: astore_1
    //   794: aload 12
    //   796: astore 9
    //   798: goto -186 -> 612
    //   801: astore_2
    //   802: aload 8
    //   804: astore_1
    //   805: goto -193 -> 612
    //   808: astore_2
    //   809: aconst_null
    //   810: astore_1
    //   811: aload 11
    //   813: astore 9
    //   815: aload 8
    //   817: astore_0
    //   818: goto -271 -> 547
    //   821: astore_2
    //   822: aconst_null
    //   823: astore_1
    //   824: aload 11
    //   826: astore 9
    //   828: goto -281 -> 547
    //   831: astore_2
    //   832: aload 8
    //   834: astore_1
    //   835: aload 11
    //   837: astore 9
    //   839: goto -292 -> 547
    //   842: astore_2
    //   843: aload 8
    //   845: astore_1
    //   846: goto -299 -> 547
    //   849: aconst_null
    //   850: astore_0
    //   851: goto -667 -> 184
    // Local variable table:
    //   start	length	slot	name	signature
    //   0	854	0	paramString1	String
    //   0	854	1	paramString2	String
    //   0	854	2	paramString3	String
    //   274	141	3	i	int
    //   288	126	4	j	int
    //   13	3	5	bool	boolean
    //   224	96	6	l	long
    //   171	673	8	localObject1	Object
    //   24	692	9	localObject2	Object
    //   723	8	9	localObject3	Object
    //   735	103	9	localObject4	Object
    //   21	611	10	localObject5	Object
    //   740	19	10	localObject6	Object
    //   7	829	11	localObject7	Object
    //   1	794	12	localObject8	Object
    //   4	730	13	localObject9	Object
    // Exception table:
    //   from	to	target	type
    //   9	15	538	java/net/MalformedURLException
    //   42	88	538	java/net/MalformedURLException
    //   88	146	538	java/net/MalformedURLException
    //   146	166	538	java/net/MalformedURLException
    //   166	173	538	java/net/MalformedURLException
    //   376	391	538	java/net/MalformedURLException
    //   9	15	603	java/lang/Throwable
    //   42	88	603	java/lang/Throwable
    //   88	146	603	java/lang/Throwable
    //   146	166	603	java/lang/Throwable
    //   166	173	603	java/lang/Throwable
    //   376	391	603	java/lang/Throwable
    //   9	15	668	finally
    //   42	88	668	finally
    //   88	146	668	finally
    //   146	166	668	finally
    //   166	173	668	finally
    //   376	391	668	finally
    //   178	184	692	finally
    //   391	397	705	finally
    //   205	273	723	finally
    //   275	290	740	finally
    //   296	301	740	finally
    //   309	360	740	finally
    //   400	410	740	finally
    //   418	464	740	finally
    //   464	522	740	finally
    //   557	561	753	finally
    //   571	588	753	finally
    //   622	626	753	finally
    //   636	653	753	finally
    //   178	184	767	java/lang/Throwable
    //   391	397	780	java/lang/Throwable
    //   205	273	790	java/lang/Throwable
    //   275	290	801	java/lang/Throwable
    //   296	301	801	java/lang/Throwable
    //   309	360	801	java/lang/Throwable
    //   400	410	801	java/lang/Throwable
    //   418	464	801	java/lang/Throwable
    //   464	522	801	java/lang/Throwable
    //   178	184	808	java/net/MalformedURLException
    //   391	397	821	java/net/MalformedURLException
    //   205	273	831	java/net/MalformedURLException
    //   275	290	842	java/net/MalformedURLException
    //   296	301	842	java/net/MalformedURLException
    //   309	360	842	java/net/MalformedURLException
    //   400	410	842	java/net/MalformedURLException
    //   418	464	842	java/net/MalformedURLException
    //   464	522	842	java/net/MalformedURLException
  }
}

/* Location:
 * Qualified Name:     cn.com.xy.sms.sdk.util.d
 * Java Class Version: 6 (50.0)
 * JD-Core Version:    0.7.1
 */