package com.android.mms.transaction;

import android.content.Context;
import android.content.Intent;
import android.os.AsyncTask;
import android.util.Log;

class PushReceiver$a
  extends AsyncTask<Intent, Void, Integer>
{
  private Context b;
  
  public PushReceiver$a(PushReceiver paramPushReceiver, Context paramContext)
  {
    b = paramContext;
  }
  
  /* Error */
  protected Integer a(Intent... paramVarArgs)
  {
    // Byte code:
    //   0: aload_1
    //   1: iconst_0
    //   2: aaload
    //   3: astore 14
    //   5: getstatic 32	android/os/Build$VERSION:SDK_INT	I
    //   8: bipush 21
    //   10: if_icmple +75 -> 85
    //   13: ldc 34
    //   15: new 36	java/lang/StringBuilder
    //   18: dup
    //   19: invokespecial 37	java/lang/StringBuilder:<init>	()V
    //   22: ldc 39
    //   24: invokevirtual 43	java/lang/StringBuilder:append	(Ljava/lang/String;)Ljava/lang/StringBuilder;
    //   27: aload 14
    //   29: ldc 45
    //   31: iconst_m1
    //   32: invokevirtual 51	android/content/Intent:getIntExtra	(Ljava/lang/String;I)I
    //   35: invokevirtual 54	java/lang/StringBuilder:append	(I)Ljava/lang/StringBuilder;
    //   38: invokevirtual 58	java/lang/StringBuilder:toString	()Ljava/lang/String;
    //   41: invokestatic 64	android/util/Log:d	(Ljava/lang/String;Ljava/lang/String;)I
    //   44: pop
    //   45: ldc 66
    //   47: aload 14
    //   49: invokevirtual 69	android/content/Intent:getType	()Ljava/lang/String;
    //   52: invokevirtual 75	java/lang/String:equals	(Ljava/lang/Object;)Z
    //   55: ifne +16 -> 71
    //   58: ldc 77
    //   60: aload 14
    //   62: invokevirtual 69	android/content/Intent:getType	()Ljava/lang/String;
    //   65: invokevirtual 75	java/lang/String:equals	(Ljava/lang/Object;)Z
    //   68: ifeq +54 -> 122
    //   71: aload_0
    //   72: getfield 20	com/android/mms/transaction/PushReceiver$a:b	Landroid/content/Context;
    //   75: aload 14
    //   77: invokestatic 82	aja:a	(Landroid/content/Context;Landroid/content/Intent;)V
    //   80: iconst_0
    //   81: invokestatic 88	java/lang/Integer:valueOf	(I)Ljava/lang/Integer;
    //   84: areturn
    //   85: ldc 34
    //   87: new 36	java/lang/StringBuilder
    //   90: dup
    //   91: invokespecial 37	java/lang/StringBuilder:<init>	()V
    //   94: ldc 39
    //   96: invokevirtual 43	java/lang/StringBuilder:append	(Ljava/lang/String;)Ljava/lang/StringBuilder;
    //   99: aload 14
    //   101: ldc 45
    //   103: ldc2_w 89
    //   106: invokevirtual 94	android/content/Intent:getLongExtra	(Ljava/lang/String;J)J
    //   109: invokevirtual 97	java/lang/StringBuilder:append	(J)Ljava/lang/StringBuilder;
    //   112: invokevirtual 58	java/lang/StringBuilder:toString	()Ljava/lang/String;
    //   115: invokestatic 64	android/util/Log:d	(Ljava/lang/String;Ljava/lang/String;)I
    //   118: pop
    //   119: goto -74 -> 45
    //   122: new 99	com/meizu/android/mms/pdu/MzPduParser
    //   125: dup
    //   126: aload 14
    //   128: ldc 101
    //   130: invokevirtual 105	android/content/Intent:getByteArrayExtra	(Ljava/lang/String;)[B
    //   133: invokespecial 108	com/meizu/android/mms/pdu/MzPduParser:<init>	([B)V
    //   136: invokevirtual 112	com/meizu/android/mms/pdu/MzPduParser:parse	()Lcom/meizu/android/mms/pdu/MzGenericPdu;
    //   139: astore_1
    //   140: aload_1
    //   141: ifnonnull +16 -> 157
    //   144: ldc 34
    //   146: ldc 114
    //   148: invokestatic 117	android/util/Log:e	(Ljava/lang/String;Ljava/lang/String;)I
    //   151: pop
    //   152: iconst_0
    //   153: invokestatic 88	java/lang/Integer:valueOf	(I)Ljava/lang/Integer;
    //   156: areturn
    //   157: aload_0
    //   158: getfield 20	com/android/mms/transaction/PushReceiver$a:b	Landroid/content/Context;
    //   161: invokestatic 123	com/meizu/android/mms/pdu/MzPduPersister:getPduPersister	(Landroid/content/Context;)Lcom/meizu/android/mms/pdu/MzPduPersister;
    //   164: astore 12
    //   166: aload_0
    //   167: getfield 20	com/android/mms/transaction/PushReceiver$a:b	Landroid/content/Context;
    //   170: invokevirtual 129	android/content/Context:getContentResolver	()Landroid/content/ContentResolver;
    //   173: astore 13
    //   175: aload_1
    //   176: invokevirtual 135	com/meizu/android/mms/pdu/MzGenericPdu:getMessageType	()I
    //   179: istore_3
    //   180: aload 14
    //   182: invokestatic 140	zv:a	(Landroid/content/Intent;)J
    //   185: lstore 5
    //   187: lload 5
    //   189: invokestatic 145	aac:a	(J)I
    //   192: istore_2
    //   193: ldc 34
    //   195: new 36	java/lang/StringBuilder
    //   198: dup
    //   199: invokespecial 37	java/lang/StringBuilder:<init>	()V
    //   202: ldc -109
    //   204: invokevirtual 43	java/lang/StringBuilder:append	(Ljava/lang/String;)Ljava/lang/StringBuilder;
    //   207: iload_3
    //   208: invokevirtual 54	java/lang/StringBuilder:append	(I)Ljava/lang/StringBuilder;
    //   211: ldc -107
    //   213: invokevirtual 43	java/lang/StringBuilder:append	(Ljava/lang/String;)Ljava/lang/StringBuilder;
    //   216: lload 5
    //   218: invokevirtual 97	java/lang/StringBuilder:append	(J)Ljava/lang/StringBuilder;
    //   221: ldc -105
    //   223: invokevirtual 43	java/lang/StringBuilder:append	(Ljava/lang/String;)Ljava/lang/StringBuilder;
    //   226: iload_2
    //   227: invokevirtual 54	java/lang/StringBuilder:append	(I)Ljava/lang/StringBuilder;
    //   230: invokevirtual 58	java/lang/StringBuilder:toString	()Ljava/lang/String;
    //   233: invokestatic 64	android/util/Log:d	(Ljava/lang/String;Ljava/lang/String;)I
    //   236: pop
    //   237: iload_3
    //   238: lookupswitch	default:+34->272, 130:+607->845, 134:+47->285, 136:+47->285
    //   272: ldc 34
    //   274: ldc -103
    //   276: invokestatic 117	android/util/Log:e	(Ljava/lang/String;Ljava/lang/String;)I
    //   279: pop
    //   280: iconst_0
    //   281: invokestatic 88	java/lang/Integer:valueOf	(I)Ljava/lang/Integer;
    //   284: areturn
    //   285: aload_0
    //   286: getfield 20	com/android/mms/transaction/PushReceiver$a:b	Landroid/content/Context;
    //   289: aload_1
    //   290: iload_3
    //   291: invokestatic 156	com/android/mms/transaction/PushReceiver:a	(Landroid/content/Context;Lcom/meizu/android/mms/pdu/MzGenericPdu;I)Lcom/android/mms/transaction/PushReceiver$b;
    //   294: astore 14
    //   296: aload 14
    //   298: getfield 161	com/android/mms/transaction/PushReceiver$b:a	J
    //   301: lstore 7
    //   303: lload 7
    //   305: ldc2_w 89
    //   308: lcmp
    //   309: ifeq -29 -> 280
    //   312: new 163	android/content/ContentValues
    //   315: dup
    //   316: iconst_5
    //   317: invokespecial 166	android/content/ContentValues:<init>	(I)V
    //   320: astore 15
    //   322: aload 15
    //   324: ldc -88
    //   326: lload 7
    //   328: invokestatic 173	java/lang/Long:valueOf	(J)Ljava/lang/Long;
    //   331: invokevirtual 177	android/content/ContentValues:put	(Ljava/lang/String;Ljava/lang/Long;)V
    //   334: aload 15
    //   336: ldc -77
    //   338: iconst_1
    //   339: invokestatic 88	java/lang/Integer:valueOf	(I)Ljava/lang/Integer;
    //   342: invokevirtual 182	android/content/ContentValues:put	(Ljava/lang/String;Ljava/lang/Integer;)V
    //   345: aload 15
    //   347: ldc -72
    //   349: aload_0
    //   350: getfield 20	com/android/mms/transaction/PushReceiver$a:b	Landroid/content/Context;
    //   353: iload_2
    //   354: invokestatic 187	aac:d	(Landroid/content/Context;I)Ljava/lang/String;
    //   357: invokevirtual 190	android/content/ContentValues:put	(Ljava/lang/String;Ljava/lang/String;)V
    //   360: aload 15
    //   362: ldc -64
    //   364: iload_2
    //   365: invokestatic 88	java/lang/Integer:valueOf	(I)Ljava/lang/Integer;
    //   368: invokevirtual 182	android/content/ContentValues:put	(Ljava/lang/String;Ljava/lang/Integer;)V
    //   371: aload 15
    //   373: ldc -62
    //   375: lload 5
    //   377: invokestatic 173	java/lang/Long:valueOf	(J)Ljava/lang/Long;
    //   380: invokevirtual 177	android/content/ContentValues:put	(Ljava/lang/String;Ljava/lang/Long;)V
    //   383: aload 12
    //   385: aload_1
    //   386: getstatic 200	android/provider/Telephony$Mms$Inbox:CONTENT_URI	Landroid/net/Uri;
    //   389: iconst_1
    //   390: aload_0
    //   391: getfield 20	com/android/mms/transaction/PushReceiver$a:b	Landroid/content/Context;
    //   394: invokestatic 205	com/android/mms/ui/MessagingPreferenceActivity:b	(Landroid/content/Context;)Z
    //   397: aconst_null
    //   398: iconst_1
    //   399: aload 15
    //   401: invokevirtual 209	com/meizu/android/mms/pdu/MzPduPersister:persist	(Lcom/meizu/android/mms/pdu/MzGenericPdu;Landroid/net/Uri;ZZLjava/util/HashMap;ILandroid/content/ContentValues;)Landroid/net/Uri;
    //   404: pop
    //   405: sipush 134
    //   408: iload_3
    //   409: if_icmpne +282 -> 691
    //   412: aload 13
    //   414: getstatic 214	android/provider/Telephony$Mms:REPORT_REQUEST_URI	Landroid/net/Uri;
    //   417: aload 14
    //   419: getfield 216	com/android/mms/transaction/PushReceiver$b:b	J
    //   422: invokestatic 219	java/lang/String:valueOf	(J)Ljava/lang/String;
    //   425: invokestatic 225	android/net/Uri:withAppendedPath	(Landroid/net/Uri;Ljava/lang/String;)Landroid/net/Uri;
    //   428: getstatic 228	com/android/mms/transaction/PushReceiver:b	[Ljava/lang/String;
    //   431: aconst_null
    //   432: aconst_null
    //   433: aconst_null
    //   434: invokevirtual 234	android/content/ContentResolver:query	(Landroid/net/Uri;[Ljava/lang/String;Ljava/lang/String;[Ljava/lang/String;Ljava/lang/String;)Landroid/database/Cursor;
    //   437: astore_1
    //   438: aload_1
    //   439: ifnonnull +8 -> 447
    //   442: iconst_0
    //   443: invokestatic 88	java/lang/Integer:valueOf	(I)Ljava/lang/Integer;
    //   446: areturn
    //   447: aload_1
    //   448: invokeinterface 239 1 0
    //   453: istore 4
    //   455: aload_1
    //   456: invokeinterface 242 1 0
    //   461: aload 13
    //   463: getstatic 245	android/provider/Telephony$Mms:REPORT_STATUS_URI	Landroid/net/Uri;
    //   466: aload 14
    //   468: getfield 216	com/android/mms/transaction/PushReceiver$b:b	J
    //   471: invokestatic 219	java/lang/String:valueOf	(J)Ljava/lang/String;
    //   474: invokestatic 225	android/net/Uri:withAppendedPath	(Landroid/net/Uri;Ljava/lang/String;)Landroid/net/Uri;
    //   477: getstatic 247	com/android/mms/transaction/PushReceiver:a	[Ljava/lang/String;
    //   480: aconst_null
    //   481: aconst_null
    //   482: aconst_null
    //   483: invokevirtual 234	android/content/ContentResolver:query	(Landroid/net/Uri;[Ljava/lang/String;Ljava/lang/String;[Ljava/lang/String;Ljava/lang/String;)Landroid/database/Cursor;
    //   486: astore_1
    //   487: aload_1
    //   488: ifnonnull +1106 -> 1594
    //   491: iconst_0
    //   492: invokestatic 88	java/lang/Integer:valueOf	(I)Ljava/lang/Integer;
    //   495: areturn
    //   496: astore 12
    //   498: aload_1
    //   499: invokeinterface 242 1 0
    //   504: aload 12
    //   506: athrow
    //   507: astore_1
    //   508: ldc 34
    //   510: new 36	java/lang/StringBuilder
    //   513: dup
    //   514: invokespecial 37	java/lang/StringBuilder:<init>	()V
    //   517: ldc -7
    //   519: invokevirtual 43	java/lang/StringBuilder:append	(Ljava/lang/String;)Ljava/lang/StringBuilder;
    //   522: iload_3
    //   523: invokevirtual 54	java/lang/StringBuilder:append	(I)Ljava/lang/StringBuilder;
    //   526: invokevirtual 58	java/lang/StringBuilder:toString	()Ljava/lang/String;
    //   529: aload_1
    //   530: invokestatic 252	android/util/Log:e	(Ljava/lang/String;Ljava/lang/String;Ljava/lang/Throwable;)I
    //   533: pop
    //   534: goto -254 -> 280
    //   537: aload_1
    //   538: invokeinterface 239 1 0
    //   543: iload 4
    //   545: if_icmpne +27 -> 572
    //   548: aload_1
    //   549: invokeinterface 256 1 0
    //   554: ifeq +18 -> 572
    //   557: iload_2
    //   558: aload_1
    //   559: iconst_1
    //   560: invokeinterface 260 2 0
    //   565: invokestatic 265	wd:a	(II)I
    //   568: istore_2
    //   569: goto -32 -> 537
    //   572: aload_1
    //   573: invokeinterface 242 1 0
    //   578: ldc 34
    //   580: new 36	java/lang/StringBuilder
    //   583: dup
    //   584: invokespecial 37	java/lang/StringBuilder:<init>	()V
    //   587: ldc_w 267
    //   590: invokevirtual 43	java/lang/StringBuilder:append	(Ljava/lang/String;)Ljava/lang/StringBuilder;
    //   593: iload_2
    //   594: invokevirtual 54	java/lang/StringBuilder:append	(I)Ljava/lang/StringBuilder;
    //   597: invokevirtual 58	java/lang/StringBuilder:toString	()Ljava/lang/String;
    //   600: invokestatic 64	android/util/Log:d	(Ljava/lang/String;Ljava/lang/String;)I
    //   603: pop
    //   604: iload_2
    //   605: ifeq -325 -> 280
    //   608: new 163	android/content/ContentValues
    //   611: dup
    //   612: iconst_1
    //   613: invokespecial 166	android/content/ContentValues:<init>	(I)V
    //   616: astore_1
    //   617: aload_1
    //   618: ldc_w 269
    //   621: iload_2
    //   622: invokestatic 88	java/lang/Integer:valueOf	(I)Ljava/lang/Integer;
    //   625: invokevirtual 182	android/content/ContentValues:put	(Ljava/lang/String;Ljava/lang/Integer;)V
    //   628: aload 13
    //   630: getstatic 272	android/provider/Telephony$Mms$Outbox:CONTENT_URI	Landroid/net/Uri;
    //   633: aload_1
    //   634: new 36	java/lang/StringBuilder
    //   637: dup
    //   638: invokespecial 37	java/lang/StringBuilder:<init>	()V
    //   641: ldc_w 274
    //   644: invokevirtual 43	java/lang/StringBuilder:append	(Ljava/lang/String;)Ljava/lang/StringBuilder;
    //   647: aload 14
    //   649: getfield 216	com/android/mms/transaction/PushReceiver$b:b	J
    //   652: invokevirtual 97	java/lang/StringBuilder:append	(J)Ljava/lang/StringBuilder;
    //   655: invokevirtual 58	java/lang/StringBuilder:toString	()Ljava/lang/String;
    //   658: aconst_null
    //   659: invokevirtual 278	android/content/ContentResolver:update	(Landroid/net/Uri;Landroid/content/ContentValues;Ljava/lang/String;[Ljava/lang/String;)I
    //   662: pop
    //   663: goto -383 -> 280
    //   666: astore_1
    //   667: ldc 34
    //   669: ldc_w 280
    //   672: aload_1
    //   673: invokestatic 252	android/util/Log:e	(Ljava/lang/String;Ljava/lang/String;Ljava/lang/Throwable;)I
    //   676: pop
    //   677: goto -397 -> 280
    //   680: astore 12
    //   682: aload_1
    //   683: invokeinterface 242 1 0
    //   688: aload 12
    //   690: athrow
    //   691: getstatic 285	com/android/mms/MmsApp:a	Z
    //   694: ifne +9 -> 703
    //   697: getstatic 287	com/android/mms/MmsApp:b	Z
    //   700: ifeq -420 -> 280
    //   703: aconst_null
    //   704: astore 12
    //   706: aload_1
    //   707: checkcast 289	com/meizu/android/mms/pdu/MzReadOrigInd
    //   710: astore 13
    //   712: aload 12
    //   714: astore_1
    //   715: aload 13
    //   717: invokevirtual 293	com/meizu/android/mms/pdu/MzReadOrigInd:getTo	()[Lcom/meizu/android/mms/pdu/MzEncodedStringValue;
    //   720: ifnull +33 -> 753
    //   723: aload 13
    //   725: invokevirtual 293	com/meizu/android/mms/pdu/MzReadOrigInd:getTo	()[Lcom/meizu/android/mms/pdu/MzEncodedStringValue;
    //   728: iconst_0
    //   729: aaload
    //   730: astore 14
    //   732: aload 12
    //   734: astore_1
    //   735: aload 14
    //   737: ifnull +16 -> 753
    //   740: aload 14
    //   742: invokevirtual 298	com/meizu/android/mms/pdu/MzEncodedStringValue:getString	()Ljava/lang/String;
    //   745: iconst_0
    //   746: invokestatic 303	gm:a	(Ljava/lang/String;Z)Lgm;
    //   749: invokevirtual 306	gm:g	()Ljava/lang/String;
    //   752: astore_1
    //   753: aload 13
    //   755: invokevirtual 309	com/meizu/android/mms/pdu/MzReadOrigInd:getReadStatus	()I
    //   758: sipush 128
    //   761: if_icmpne +59 -> 820
    //   764: aload_0
    //   765: getfield 20	com/android/mms/transaction/PushReceiver$a:b	Landroid/content/Context;
    //   768: ldc_w 310
    //   771: invokevirtual 313	android/content/Context:getString	(I)Ljava/lang/String;
    //   774: iconst_1
    //   775: anewarray 315	java/lang/Object
    //   778: dup
    //   779: iconst_0
    //   780: aload_1
    //   781: aastore
    //   782: invokestatic 319	java/lang/String:format	(Ljava/lang/String;[Ljava/lang/Object;)Ljava/lang/String;
    //   785: astore_1
    //   786: new 47	android/content/Intent
    //   789: dup
    //   790: ldc_w 321
    //   793: invokespecial 324	android/content/Intent:<init>	(Ljava/lang/String;)V
    //   796: astore 12
    //   798: aload 12
    //   800: ldc_w 326
    //   803: aload_1
    //   804: invokevirtual 330	android/content/Intent:putExtra	(Ljava/lang/String;Ljava/lang/String;)Landroid/content/Intent;
    //   807: pop
    //   808: aload_0
    //   809: getfield 20	com/android/mms/transaction/PushReceiver$a:b	Landroid/content/Context;
    //   812: aload 12
    //   814: invokevirtual 334	android/content/Context:sendBroadcast	(Landroid/content/Intent;)V
    //   817: goto -537 -> 280
    //   820: aload_0
    //   821: getfield 20	com/android/mms/transaction/PushReceiver$a:b	Landroid/content/Context;
    //   824: ldc_w 335
    //   827: invokevirtual 313	android/content/Context:getString	(I)Ljava/lang/String;
    //   830: iconst_1
    //   831: anewarray 315	java/lang/Object
    //   834: dup
    //   835: iconst_0
    //   836: aload_1
    //   837: aastore
    //   838: invokestatic 319	java/lang/String:format	(Ljava/lang/String;[Ljava/lang/Object;)Ljava/lang/String;
    //   841: astore_1
    //   842: goto -56 -> 786
    //   845: aload_1
    //   846: checkcast 337	com/meizu/android/mms/pdu/MzNotificationInd
    //   849: astore 13
    //   851: aload 13
    //   853: new 295	com/meizu/android/mms/pdu/MzEncodedStringValue
    //   856: dup
    //   857: aload_0
    //   858: getfield 20	com/android/mms/transaction/PushReceiver$a:b	Landroid/content/Context;
    //   861: ldc_w 338
    //   864: invokevirtual 313	android/content/Context:getString	(I)Ljava/lang/String;
    //   867: invokespecial 339	com/meizu/android/mms/pdu/MzEncodedStringValue:<init>	(Ljava/lang/String;)V
    //   870: invokevirtual 343	com/meizu/android/mms/pdu/MzNotificationInd:setSubject	(Lcom/meizu/android/mms/pdu/MzEncodedStringValue;)V
    //   873: invokestatic 348	ga:h	()Z
    //   876: ifeq +74 -> 950
    //   879: aload 13
    //   881: invokevirtual 352	com/meizu/android/mms/pdu/MzNotificationInd:getContentLocation	()[B
    //   884: astore 14
    //   886: bipush 61
    //   888: aload 14
    //   890: aload 14
    //   892: arraylength
    //   893: iconst_1
    //   894: isub
    //   895: baload
    //   896: if_icmpne +54 -> 950
    //   899: aload 13
    //   901: invokevirtual 355	com/meizu/android/mms/pdu/MzNotificationInd:getTransactionId	()[B
    //   904: astore 15
    //   906: aload 14
    //   908: arraylength
    //   909: aload 15
    //   911: arraylength
    //   912: iadd
    //   913: newarray <illegal type>
    //   915: astore 16
    //   917: aload 14
    //   919: iconst_0
    //   920: aload 16
    //   922: iconst_0
    //   923: aload 14
    //   925: arraylength
    //   926: invokestatic 361	java/lang/System:arraycopy	(Ljava/lang/Object;ILjava/lang/Object;II)V
    //   929: aload 15
    //   931: iconst_0
    //   932: aload 16
    //   934: aload 14
    //   936: arraylength
    //   937: aload 15
    //   939: arraylength
    //   940: invokestatic 361	java/lang/System:arraycopy	(Ljava/lang/Object;ILjava/lang/Object;II)V
    //   943: aload 13
    //   945: aload 16
    //   947: invokevirtual 364	com/meizu/android/mms/pdu/MzNotificationInd:setContentLocation	([B)V
    //   950: aload_0
    //   951: getfield 20	com/android/mms/transaction/PushReceiver$a:b	Landroid/content/Context;
    //   954: aload 13
    //   956: invokestatic 367	com/android/mms/transaction/PushReceiver:a	(Landroid/content/Context;Lcom/meizu/android/mms/pdu/MzNotificationInd;)Z
    //   959: ifne +595 -> 1554
    //   962: aload 13
    //   964: invokevirtual 371	com/meizu/android/mms/pdu/MzNotificationInd:getFrom	()Lcom/meizu/android/mms/pdu/MzEncodedStringValue;
    //   967: invokevirtual 298	com/meizu/android/mms/pdu/MzEncodedStringValue:getString	()Ljava/lang/String;
    //   970: astore 13
    //   972: invokestatic 375	java/lang/System:currentTimeMillis	()J
    //   975: lstore 7
    //   977: lload 5
    //   979: invokestatic 378	aac:b	(J)Z
    //   982: ifne +15 -> 997
    //   985: ldc 34
    //   987: ldc_w 380
    //   990: invokestatic 117	android/util/Log:e	(Ljava/lang/String;Ljava/lang/String;)I
    //   993: pop
    //   994: goto -714 -> 280
    //   997: aload 13
    //   999: aconst_null
    //   1000: lload 7
    //   1002: invokestatic 385	abl:a	(Ljava/lang/String;Ljava/lang/String;J)Labl$a;
    //   1005: astore 14
    //   1007: aload 14
    //   1009: getfield 388	abl$a:b	Z
    //   1012: ifeq +140 -> 1152
    //   1015: new 163	android/content/ContentValues
    //   1018: dup
    //   1019: invokespecial 389	android/content/ContentValues:<init>	()V
    //   1022: astore_1
    //   1023: aload_1
    //   1024: ldc_w 391
    //   1027: aload 13
    //   1029: invokevirtual 190	android/content/ContentValues:put	(Ljava/lang/String;Ljava/lang/String;)V
    //   1032: aload_1
    //   1033: ldc_w 393
    //   1036: lload 7
    //   1038: invokestatic 173	java/lang/Long:valueOf	(J)Ljava/lang/Long;
    //   1041: invokevirtual 177	android/content/ContentValues:put	(Ljava/lang/String;Ljava/lang/Long;)V
    //   1044: aload_1
    //   1045: ldc_w 395
    //   1048: new 170	java/lang/Long
    //   1051: dup
    //   1052: lload 7
    //   1054: invokespecial 398	java/lang/Long:<init>	(J)V
    //   1057: invokevirtual 177	android/content/ContentValues:put	(Ljava/lang/String;Ljava/lang/Long;)V
    //   1060: aload_1
    //   1061: ldc -72
    //   1063: aload_0
    //   1064: getfield 20	com/android/mms/transaction/PushReceiver$a:b	Landroid/content/Context;
    //   1067: iload_2
    //   1068: invokestatic 187	aac:d	(Landroid/content/Context;I)Ljava/lang/String;
    //   1071: invokevirtual 190	android/content/ContentValues:put	(Ljava/lang/String;Ljava/lang/String;)V
    //   1074: aload_1
    //   1075: ldc -64
    //   1077: iload_2
    //   1078: invokestatic 88	java/lang/Integer:valueOf	(I)Ljava/lang/Integer;
    //   1081: invokevirtual 182	android/content/ContentValues:put	(Ljava/lang/String;Ljava/lang/Integer;)V
    //   1084: aload_1
    //   1085: ldc_w 400
    //   1088: iconst_0
    //   1089: invokestatic 88	java/lang/Integer:valueOf	(I)Ljava/lang/Integer;
    //   1092: invokevirtual 182	android/content/ContentValues:put	(Ljava/lang/String;Ljava/lang/Integer;)V
    //   1095: aload_1
    //   1096: ldc -77
    //   1098: iconst_0
    //   1099: invokestatic 88	java/lang/Integer:valueOf	(I)Ljava/lang/Integer;
    //   1102: invokevirtual 182	android/content/ContentValues:put	(Ljava/lang/String;Ljava/lang/Integer;)V
    //   1105: aload_1
    //   1106: ldc_w 402
    //   1109: iconst_0
    //   1110: invokestatic 88	java/lang/Integer:valueOf	(I)Ljava/lang/Integer;
    //   1113: invokevirtual 182	android/content/ContentValues:put	(Ljava/lang/String;Ljava/lang/Integer;)V
    //   1116: aload_1
    //   1117: ldc_w 404
    //   1120: ldc_w 406
    //   1123: invokevirtual 190	android/content/ContentValues:put	(Ljava/lang/String;Ljava/lang/String;)V
    //   1126: aload_1
    //   1127: ldc_w 408
    //   1130: iconst_1
    //   1131: invokestatic 88	java/lang/Integer:valueOf	(I)Ljava/lang/Integer;
    //   1134: invokevirtual 182	android/content/ContentValues:put	(Ljava/lang/String;Ljava/lang/Integer;)V
    //   1137: invokestatic 412	com/android/mms/MmsApp:c	()Lcom/android/mms/MmsApp;
    //   1140: aload_1
    //   1141: aload 14
    //   1143: invokestatic 415	abl:a	(Landroid/content/Context;Landroid/content/ContentValues;Labl$a;)Landroid/net/Uri;
    //   1146: pop
    //   1147: iconst_0
    //   1148: invokestatic 88	java/lang/Integer:valueOf	(I)Ljava/lang/Integer;
    //   1151: areturn
    //   1152: invokestatic 420	zn:a	()Lzn;
    //   1155: lload 5
    //   1157: invokevirtual 422	zn:a	(J)Z
    //   1160: istore 9
    //   1162: aload_0
    //   1163: getfield 20	com/android/mms/transaction/PushReceiver$a:b	Landroid/content/Context;
    //   1166: invokestatic 428	android/preference/PreferenceManager:getDefaultSharedPreferences	(Landroid/content/Context;)Landroid/content/SharedPreferences;
    //   1169: ldc_w 430
    //   1172: iconst_1
    //   1173: invokeinterface 436 3 0
    //   1178: istore 10
    //   1180: aload_0
    //   1181: getfield 20	com/android/mms/transaction/PushReceiver$a:b	Landroid/content/Context;
    //   1184: iload_2
    //   1185: invokestatic 439	wd:c	(Landroid/content/Context;I)Z
    //   1188: istore 11
    //   1190: iconst_1
    //   1191: invokestatic 442	wd:b	(Z)V
    //   1194: new 163	android/content/ContentValues
    //   1197: dup
    //   1198: invokespecial 389	android/content/ContentValues:<init>	()V
    //   1201: astore 13
    //   1203: aload 13
    //   1205: ldc_w 444
    //   1208: sipush 131
    //   1211: invokestatic 88	java/lang/Integer:valueOf	(I)Ljava/lang/Integer;
    //   1214: invokevirtual 182	android/content/ContentValues:put	(Ljava/lang/String;Ljava/lang/Integer;)V
    //   1217: aload 13
    //   1219: ldc_w 395
    //   1222: new 170	java/lang/Long
    //   1225: dup
    //   1226: invokestatic 375	java/lang/System:currentTimeMillis	()J
    //   1229: invokespecial 398	java/lang/Long:<init>	(J)V
    //   1232: invokevirtual 177	android/content/ContentValues:put	(Ljava/lang/String;Ljava/lang/Long;)V
    //   1235: aload 13
    //   1237: ldc -72
    //   1239: aload_0
    //   1240: getfield 20	com/android/mms/transaction/PushReceiver$a:b	Landroid/content/Context;
    //   1243: iload_2
    //   1244: invokestatic 187	aac:d	(Landroid/content/Context;I)Ljava/lang/String;
    //   1247: invokevirtual 190	android/content/ContentValues:put	(Ljava/lang/String;Ljava/lang/String;)V
    //   1250: aload 13
    //   1252: ldc -64
    //   1254: iload_2
    //   1255: invokestatic 88	java/lang/Integer:valueOf	(I)Ljava/lang/Integer;
    //   1258: invokevirtual 182	android/content/ContentValues:put	(Ljava/lang/String;Ljava/lang/Integer;)V
    //   1261: aload 13
    //   1263: ldc -62
    //   1265: lload 5
    //   1267: invokestatic 173	java/lang/Long:valueOf	(J)Ljava/lang/Long;
    //   1270: invokevirtual 177	android/content/ContentValues:put	(Ljava/lang/String;Ljava/lang/Long;)V
    //   1273: aload 12
    //   1275: aload_1
    //   1276: getstatic 200	android/provider/Telephony$Mms$Inbox:CONTENT_URI	Landroid/net/Uri;
    //   1279: iconst_1
    //   1280: aload_0
    //   1281: getfield 20	com/android/mms/transaction/PushReceiver$a:b	Landroid/content/Context;
    //   1284: invokestatic 205	com/android/mms/ui/MessagingPreferenceActivity:b	(Landroid/content/Context;)Z
    //   1287: aconst_null
    //   1288: iconst_1
    //   1289: aload 13
    //   1291: invokevirtual 209	com/meizu/android/mms/pdu/MzPduPersister:persist	(Lcom/meizu/android/mms/pdu/MzGenericPdu;Landroid/net/Uri;ZZLjava/util/HashMap;ILandroid/content/ContentValues;)Landroid/net/Uri;
    //   1294: astore_1
    //   1295: iconst_0
    //   1296: invokestatic 442	wd:b	(Z)V
    //   1299: new 47	android/content/Intent
    //   1302: dup
    //   1303: aload_0
    //   1304: getfield 20	com/android/mms/transaction/PushReceiver$a:b	Landroid/content/Context;
    //   1307: ldc_w 446
    //   1310: invokespecial 449	android/content/Intent:<init>	(Landroid/content/Context;Ljava/lang/Class;)V
    //   1313: astore 12
    //   1315: aload 12
    //   1317: ldc_w 451
    //   1320: aload_1
    //   1321: invokevirtual 452	android/net/Uri:toString	()Ljava/lang/String;
    //   1324: invokevirtual 330	android/content/Intent:putExtra	(Ljava/lang/String;Ljava/lang/String;)Landroid/content/Intent;
    //   1327: pop
    //   1328: aload 12
    //   1330: ldc_w 454
    //   1333: iconst_0
    //   1334: invokevirtual 457	android/content/Intent:putExtra	(Ljava/lang/String;I)Landroid/content/Intent;
    //   1337: pop
    //   1338: aload 12
    //   1340: ldc 45
    //   1342: lload 5
    //   1344: invokevirtual 460	android/content/Intent:putExtra	(Ljava/lang/String;J)Landroid/content/Intent;
    //   1347: pop
    //   1348: iload 9
    //   1350: ifeq +34 -> 1384
    //   1353: iload 11
    //   1355: ifeq +29 -> 1384
    //   1358: iload 10
    //   1360: ifeq +24 -> 1384
    //   1363: aload_0
    //   1364: getfield 20	com/android/mms/transaction/PushReceiver$a:b	Landroid/content/Context;
    //   1367: aload 12
    //   1369: invokevirtual 464	android/content/Context:startService	(Landroid/content/Intent;)Landroid/content/ComponentName;
    //   1372: ifnull +145 -> 1517
    //   1375: ldc 34
    //   1377: ldc_w 466
    //   1380: invokestatic 64	android/util/Log:d	(Ljava/lang/String;Ljava/lang/String;)I
    //   1383: pop
    //   1384: ldc 34
    //   1386: new 36	java/lang/StringBuilder
    //   1389: dup
    //   1390: invokespecial 37	java/lang/StringBuilder:<init>	()V
    //   1393: ldc_w 468
    //   1396: invokevirtual 43	java/lang/StringBuilder:append	(Ljava/lang/String;)Ljava/lang/StringBuilder;
    //   1399: iload 11
    //   1401: invokevirtual 471	java/lang/StringBuilder:append	(Z)Ljava/lang/StringBuilder;
    //   1404: ldc_w 473
    //   1407: invokevirtual 43	java/lang/StringBuilder:append	(Ljava/lang/String;)Ljava/lang/StringBuilder;
    //   1410: iload 9
    //   1412: invokevirtual 471	java/lang/StringBuilder:append	(Z)Ljava/lang/StringBuilder;
    //   1415: ldc_w 475
    //   1418: invokevirtual 43	java/lang/StringBuilder:append	(Ljava/lang/String;)Ljava/lang/StringBuilder;
    //   1421: iload 10
    //   1423: invokevirtual 471	java/lang/StringBuilder:append	(Z)Ljava/lang/StringBuilder;
    //   1426: ldc_w 477
    //   1429: invokevirtual 43	java/lang/StringBuilder:append	(Ljava/lang/String;)Ljava/lang/StringBuilder;
    //   1432: invokevirtual 58	java/lang/StringBuilder:toString	()Ljava/lang/String;
    //   1435: invokestatic 64	android/util/Log:d	(Ljava/lang/String;Ljava/lang/String;)I
    //   1438: pop
    //   1439: iload 11
    //   1441: ifeq +13 -> 1454
    //   1444: iload 9
    //   1446: ifeq +8 -> 1454
    //   1449: iload 10
    //   1451: ifne -1171 -> 280
    //   1454: aload_0
    //   1455: getfield 20	com/android/mms/transaction/PushReceiver$a:b	Landroid/content/Context;
    //   1458: aload_1
    //   1459: invokestatic 482	com/android/mms/transaction/MessagingNotification:b	(Landroid/content/Context;Landroid/net/Uri;)J
    //   1462: lstore 5
    //   1464: invokestatic 412	com/android/mms/MmsApp:c	()Lcom/android/mms/MmsApp;
    //   1467: lload 5
    //   1469: iconst_0
    //   1470: aload_1
    //   1471: iconst_0
    //   1472: iconst_0
    //   1473: invokestatic 485	com/android/mms/transaction/MessagingNotification:b	(Landroid/content/Context;JZLandroid/net/Uri;ZZ)V
    //   1476: iload 9
    //   1478: ifeq +18 -> 1496
    //   1481: getstatic 285	com/android/mms/MmsApp:a	Z
    //   1484: ifne +115 -> 1599
    //   1487: getstatic 287	com/android/mms/MmsApp:b	Z
    //   1490: ifeq +50 -> 1540
    //   1493: goto +106 -> 1599
    //   1496: invokestatic 420	zn:a	()Lzn;
    //   1499: aload_1
    //   1500: sipush 128
    //   1503: iload_2
    //   1504: invokevirtual 488	zn:a	(Landroid/net/Uri;II)V
    //   1507: iload 10
    //   1509: ifne -1229 -> 280
    //   1512: iconst_m1
    //   1513: invokestatic 88	java/lang/Integer:valueOf	(I)Ljava/lang/Integer;
    //   1516: areturn
    //   1517: ldc 34
    //   1519: ldc_w 490
    //   1522: invokestatic 117	android/util/Log:e	(Ljava/lang/String;Ljava/lang/String;)I
    //   1525: pop
    //   1526: invokestatic 420	zn:a	()Lzn;
    //   1529: aload_1
    //   1530: sipush 130
    //   1533: iload_2
    //   1534: invokevirtual 488	zn:a	(Landroid/net/Uri;II)V
    //   1537: goto -153 -> 1384
    //   1540: invokestatic 420	zn:a	()Lzn;
    //   1543: aload_1
    //   1544: sipush 130
    //   1547: iload_2
    //   1548: invokevirtual 488	zn:a	(Landroid/net/Uri;II)V
    //   1551: goto -1271 -> 280
    //   1554: ldc 34
    //   1556: new 36	java/lang/StringBuilder
    //   1559: dup
    //   1560: invokespecial 37	java/lang/StringBuilder:<init>	()V
    //   1563: ldc_w 492
    //   1566: invokevirtual 43	java/lang/StringBuilder:append	(Ljava/lang/String;)Ljava/lang/StringBuilder;
    //   1569: new 71	java/lang/String
    //   1572: dup
    //   1573: aload 13
    //   1575: invokevirtual 352	com/meizu/android/mms/pdu/MzNotificationInd:getContentLocation	()[B
    //   1578: invokespecial 493	java/lang/String:<init>	([B)V
    //   1581: invokevirtual 43	java/lang/StringBuilder:append	(Ljava/lang/String;)Ljava/lang/StringBuilder;
    //   1584: invokevirtual 58	java/lang/StringBuilder:toString	()Ljava/lang/String;
    //   1587: invokestatic 496	android/util/Log:v	(Ljava/lang/String;Ljava/lang/String;)I
    //   1590: pop
    //   1591: goto -1311 -> 280
    //   1594: iconst_0
    //   1595: istore_2
    //   1596: goto -1059 -> 537
    //   1599: iload 11
    //   1601: ifne -61 -> 1540
    //   1604: goto -108 -> 1496
    // Local variable table:
    //   start	length	slot	name	signature
    //   0	1607	0	this	a
    //   0	1607	1	paramVarArgs	Intent[]
    //   192	1404	2	i	int
    //   179	344	3	j	int
    //   453	93	4	k	int
    //   185	1283	5	l1	long
    //   301	752	7	l2	long
    //   1160	317	9	bool1	boolean
    //   1178	330	10	bool2	boolean
    //   1188	412	11	bool3	boolean
    //   164	220	12	localMzPduPersister	com.meizu.android.mms.pdu.MzPduPersister
    //   496	9	12	localObject1	Object
    //   680	9	12	localObject2	Object
    //   704	664	12	localIntent	Intent
    //   173	1401	13	localObject3	Object
    //   3	1139	14	localObject4	Object
    //   320	618	15	localObject5	Object
    //   915	31	16	arrayOfByte	byte[]
    // Exception table:
    //   from	to	target	type
    //   447	455	496	finally
    //   272	280	507	com/google/android/mms/MmsException
    //   285	303	507	com/google/android/mms/MmsException
    //   312	405	507	com/google/android/mms/MmsException
    //   412	438	507	com/google/android/mms/MmsException
    //   455	487	507	com/google/android/mms/MmsException
    //   491	496	507	com/google/android/mms/MmsException
    //   498	507	507	com/google/android/mms/MmsException
    //   572	604	507	com/google/android/mms/MmsException
    //   608	663	507	com/google/android/mms/MmsException
    //   682	691	507	com/google/android/mms/MmsException
    //   691	703	507	com/google/android/mms/MmsException
    //   706	712	507	com/google/android/mms/MmsException
    //   715	732	507	com/google/android/mms/MmsException
    //   740	753	507	com/google/android/mms/MmsException
    //   753	786	507	com/google/android/mms/MmsException
    //   786	817	507	com/google/android/mms/MmsException
    //   820	842	507	com/google/android/mms/MmsException
    //   845	950	507	com/google/android/mms/MmsException
    //   950	994	507	com/google/android/mms/MmsException
    //   997	1152	507	com/google/android/mms/MmsException
    //   1152	1348	507	com/google/android/mms/MmsException
    //   1363	1384	507	com/google/android/mms/MmsException
    //   1384	1439	507	com/google/android/mms/MmsException
    //   1454	1476	507	com/google/android/mms/MmsException
    //   1481	1493	507	com/google/android/mms/MmsException
    //   1496	1507	507	com/google/android/mms/MmsException
    //   1512	1517	507	com/google/android/mms/MmsException
    //   1517	1537	507	com/google/android/mms/MmsException
    //   1540	1551	507	com/google/android/mms/MmsException
    //   1554	1591	507	com/google/android/mms/MmsException
    //   272	280	666	java/lang/RuntimeException
    //   285	303	666	java/lang/RuntimeException
    //   312	405	666	java/lang/RuntimeException
    //   412	438	666	java/lang/RuntimeException
    //   455	487	666	java/lang/RuntimeException
    //   491	496	666	java/lang/RuntimeException
    //   498	507	666	java/lang/RuntimeException
    //   572	604	666	java/lang/RuntimeException
    //   608	663	666	java/lang/RuntimeException
    //   682	691	666	java/lang/RuntimeException
    //   691	703	666	java/lang/RuntimeException
    //   706	712	666	java/lang/RuntimeException
    //   715	732	666	java/lang/RuntimeException
    //   740	753	666	java/lang/RuntimeException
    //   753	786	666	java/lang/RuntimeException
    //   786	817	666	java/lang/RuntimeException
    //   820	842	666	java/lang/RuntimeException
    //   845	950	666	java/lang/RuntimeException
    //   950	994	666	java/lang/RuntimeException
    //   997	1152	666	java/lang/RuntimeException
    //   1152	1348	666	java/lang/RuntimeException
    //   1363	1384	666	java/lang/RuntimeException
    //   1384	1439	666	java/lang/RuntimeException
    //   1454	1476	666	java/lang/RuntimeException
    //   1481	1493	666	java/lang/RuntimeException
    //   1496	1507	666	java/lang/RuntimeException
    //   1512	1517	666	java/lang/RuntimeException
    //   1517	1537	666	java/lang/RuntimeException
    //   1540	1551	666	java/lang/RuntimeException
    //   1554	1591	666	java/lang/RuntimeException
    //   537	569	680	finally
  }
  
  protected void a(Integer paramInteger)
  {
    if (paramInteger.intValue() == -1) {
      Log.i("PushReceiver", "PushReceiver onPostExecute mms_full_body");
    }
  }
}

/* Location:
 * Qualified Name:     com.android.mms.transaction.PushReceiver.a
 * Java Class Version: 6 (50.0)
 * JD-Core Version:    0.7.1
 */