package cn.com.xy.sms.sdk.db;

final class e
  extends Thread
{
  /* Error */
  public final void run()
  {
    // Byte code:
    //   0: aload_0
    //   1: ldc 14
    //   3: invokevirtual 18	cn/com/xy/sms/sdk/db/e:setName	(Ljava/lang/String;)V
    //   6: iconst_0
    //   7: ldc 20
    //   9: iconst_1
    //   10: anewarray 22	java/lang/String
    //   13: dup
    //   14: iconst_0
    //   15: ldc 24
    //   17: aastore
    //   18: aconst_null
    //   19: aconst_null
    //   20: aconst_null
    //   21: aconst_null
    //   22: aconst_null
    //   23: ldc 26
    //   25: invokestatic 32	cn/com/xy/sms/sdk/db/a/a:a	(ZLjava/lang/String;[Ljava/lang/String;Ljava/lang/String;[Ljava/lang/String;Ljava/lang/String;Ljava/lang/String;Ljava/lang/String;Ljava/lang/String;)Lcn/com/xy/sms/sdk/db/XyCursor;
    //   28: astore_2
    //   29: aload_2
    //   30: ifnull +96 -> 126
    //   33: aload_2
    //   34: astore_1
    //   35: aload_2
    //   36: invokevirtual 38	cn/com/xy/sms/sdk/db/XyCursor:getCount	()I
    //   39: ifle +6 -> 45
    //   42: goto +84 -> 126
    //   45: aload_2
    //   46: astore_1
    //   47: ldc 40
    //   49: ldc 26
    //   51: iconst_1
    //   52: invokestatic 45	cn/com/xy/sms/sdk/db/entity/e:a	(Ljava/lang/String;Ljava/lang/String;I)V
    //   55: aload_2
    //   56: astore_1
    //   57: getstatic 51	cn/com/xy/sms/sdk/db/entity/SysParamEntityManager:cacheMap	Ljava/util/HashMap;
    //   60: invokevirtual 56	java/util/HashMap:clear	()V
    //   63: aload_2
    //   64: astore_1
    //   65: invokestatic 61	cn/com/xy/sms/sdk/util/e:c	()V
    //   68: aload_2
    //   69: astore_1
    //   70: invokestatic 67	cn/com/xy/sms/sdk/constant/Constant:getInidb_PATH	()Ljava/lang/String;
    //   73: invokestatic 72	cn/com/xy/sms/sdk/util/d:a	(Ljava/lang/String;)Z
    //   76: ifeq +11 -> 87
    //   79: aload_2
    //   80: astore_1
    //   81: invokestatic 76	cn/com/xy/sms/sdk/constant/Constant:getContext	()Landroid/content/Context;
    //   84: invokestatic 82	cn/com/xy/sms/sdk/db/ParseItemManager:updateParse	(Landroid/content/Context;)V
    //   87: aload_2
    //   88: iconst_1
    //   89: invokestatic 86	cn/com/xy/sms/sdk/db/XyCursor:closeCursor	(Lcn/com/xy/sms/sdk/db/XyCursor;Z)V
    //   92: return
    //   93: astore_3
    //   94: aconst_null
    //   95: astore_2
    //   96: aload_2
    //   97: astore_1
    //   98: aload_3
    //   99: invokevirtual 89	java/lang/Throwable:printStackTrace	()V
    //   102: aload_2
    //   103: iconst_1
    //   104: invokestatic 86	cn/com/xy/sms/sdk/db/XyCursor:closeCursor	(Lcn/com/xy/sms/sdk/db/XyCursor;Z)V
    //   107: return
    //   108: astore_2
    //   109: aconst_null
    //   110: astore_1
    //   111: aload_1
    //   112: iconst_1
    //   113: invokestatic 86	cn/com/xy/sms/sdk/db/XyCursor:closeCursor	(Lcn/com/xy/sms/sdk/db/XyCursor;Z)V
    //   116: aload_2
    //   117: athrow
    //   118: astore_2
    //   119: goto -8 -> 111
    //   122: astore_3
    //   123: goto -27 -> 96
    //   126: aload_2
    //   127: ifnonnull -40 -> 87
    //   130: goto -85 -> 45
    // Local variable table:
    //   start	length	slot	name	signature
    //   0	133	0	this	e
    //   34	78	1	localXyCursor1	XyCursor
    //   28	75	2	localXyCursor2	XyCursor
    //   108	9	2	localObject1	Object
    //   118	9	2	localObject2	Object
    //   93	6	3	localThrowable1	Throwable
    //   122	1	3	localThrowable2	Throwable
    // Exception table:
    //   from	to	target	type
    //   6	29	93	java/lang/Throwable
    //   6	29	108	finally
    //   35	42	118	finally
    //   47	55	118	finally
    //   57	63	118	finally
    //   65	68	118	finally
    //   70	79	118	finally
    //   81	87	118	finally
    //   98	102	118	finally
    //   35	42	122	java/lang/Throwable
    //   47	55	122	java/lang/Throwable
    //   57	63	122	java/lang/Throwable
    //   65	68	122	java/lang/Throwable
    //   70	79	122	java/lang/Throwable
    //   81	87	122	java/lang/Throwable
  }
}

/* Location:
 * Qualified Name:     cn.com.xy.sms.sdk.db.e
 * Java Class Version: 6 (50.0)
 * JD-Core Version:    0.7.1
 */