package com.amap.api.mapcore2d;

class k
  implements Runnable
{
  k(j paramj) {}
  
  /* Error */
  public void run()
  {
    // Byte code:
    //   0: invokestatic 29	java/lang/Thread:currentThread	()Ljava/lang/Thread;
    //   3: astore_2
    //   4: aload_2
    //   5: ifnull +9 -> 14
    //   8: aload_2
    //   9: ldc 31
    //   11: invokevirtual 35	java/lang/Thread:setName	(Ljava/lang/String;)V
    //   14: aload_0
    //   15: getfield 12	com/amap/api/mapcore2d/k:a	Lcom/amap/api/mapcore2d/j;
    //   18: invokestatic 40	com/amap/api/mapcore2d/j:a	(Lcom/amap/api/mapcore2d/j;)Ljava/util/Vector;
    //   21: ifnull +351 -> 372
    //   24: aload_0
    //   25: getfield 12	com/amap/api/mapcore2d/k:a	Lcom/amap/api/mapcore2d/j;
    //   28: invokestatic 40	com/amap/api/mapcore2d/j:a	(Lcom/amap/api/mapcore2d/j;)Ljava/util/Vector;
    //   31: aload_2
    //   32: invokevirtual 46	java/util/Vector:add	(Ljava/lang/Object;)Z
    //   35: pop
    //   36: goto +336 -> 372
    //   39: aload_0
    //   40: getfield 12	com/amap/api/mapcore2d/k:a	Lcom/amap/api/mapcore2d/j;
    //   43: invokestatic 50	com/amap/api/mapcore2d/j:b	(Lcom/amap/api/mapcore2d/j;)Z
    //   46: ifeq +40 -> 86
    //   49: invokestatic 54	java/lang/Thread:interrupted	()Z
    //   52: ifne +34 -> 86
    //   55: aload_0
    //   56: getfield 12	com/amap/api/mapcore2d/k:a	Lcom/amap/api/mapcore2d/j;
    //   59: getfield 57	com/amap/api/mapcore2d/j:b	Lcom/amap/api/mapcore2d/bl;
    //   62: ifnonnull +25 -> 87
    //   65: aload_0
    //   66: getfield 12	com/amap/api/mapcore2d/k:a	Lcom/amap/api/mapcore2d/j;
    //   69: iconst_0
    //   70: invokestatic 60	com/amap/api/mapcore2d/j:a	(Lcom/amap/api/mapcore2d/j;Z)Z
    //   73: pop
    //   74: goto -35 -> 39
    //   77: astore_2
    //   78: aload_2
    //   79: ldc 62
    //   81: ldc 63
    //   83: invokestatic 68	com/amap/api/mapcore2d/cy:a	(Ljava/lang/Throwable;Ljava/lang/String;Ljava/lang/String;)V
    //   86: return
    //   87: invokestatic 73	com/amap/api/maps2d/MapsInitializer:getNetworkEnable	()Z
    //   90: istore_1
    //   91: iload_1
    //   92: ifne +49 -> 141
    //   95: invokestatic 54	java/lang/Thread:interrupted	()Z
    //   98: ifne -59 -> 39
    //   101: ldc2_w 74
    //   104: invokestatic 79	java/lang/Thread:sleep	(J)V
    //   107: goto -68 -> 39
    //   110: astore 4
    //   112: invokestatic 29	java/lang/Thread:currentThread	()Ljava/lang/Thread;
    //   115: invokevirtual 82	java/lang/Thread:interrupt	()V
    //   118: goto -79 -> 39
    //   121: astore 4
    //   123: aload 4
    //   125: ldc 62
    //   127: ldc 63
    //   129: invokestatic 68	com/amap/api/mapcore2d/cy:a	(Ljava/lang/Throwable;Ljava/lang/String;Ljava/lang/String;)V
    //   132: invokestatic 29	java/lang/Thread:currentThread	()Ljava/lang/Thread;
    //   135: invokevirtual 82	java/lang/Thread:interrupt	()V
    //   138: goto -99 -> 39
    //   141: aload_3
    //   142: astore 4
    //   144: aload_0
    //   145: getfield 12	com/amap/api/mapcore2d/k:a	Lcom/amap/api/mapcore2d/j;
    //   148: getfield 85	com/amap/api/mapcore2d/j:a	Lcom/amap/api/mapcore2d/bx;
    //   151: ifnull +23 -> 174
    //   154: aload_0
    //   155: getfield 12	com/amap/api/mapcore2d/k:a	Lcom/amap/api/mapcore2d/j;
    //   158: getfield 85	com/amap/api/mapcore2d/j:a	Lcom/amap/api/mapcore2d/bx;
    //   161: aload_0
    //   162: getfield 12	com/amap/api/mapcore2d/k:a	Lcom/amap/api/mapcore2d/j;
    //   165: invokevirtual 89	com/amap/api/mapcore2d/j:f	()I
    //   168: iconst_0
    //   169: invokevirtual 94	com/amap/api/mapcore2d/bx:a	(IZ)Ljava/util/ArrayList;
    //   172: astore 4
    //   174: aload 4
    //   176: ifnull +14 -> 190
    //   179: aload 4
    //   181: astore_3
    //   182: aload 4
    //   184: invokevirtual 99	java/util/ArrayList:size	()I
    //   187: ifeq -148 -> 39
    //   190: aload_0
    //   191: getfield 12	com/amap/api/mapcore2d/k:a	Lcom/amap/api/mapcore2d/j;
    //   194: invokestatic 50	com/amap/api/mapcore2d/j:b	(Lcom/amap/api/mapcore2d/j;)Z
    //   197: ifeq -111 -> 86
    //   200: aload 4
    //   202: ifnull +167 -> 369
    //   205: aload_0
    //   206: getfield 12	com/amap/api/mapcore2d/k:a	Lcom/amap/api/mapcore2d/j;
    //   209: invokestatic 50	com/amap/api/mapcore2d/j:b	(Lcom/amap/api/mapcore2d/j;)Z
    //   212: ifeq -126 -> 86
    //   215: aload 4
    //   217: astore_3
    //   218: aload_0
    //   219: getfield 12	com/amap/api/mapcore2d/k:a	Lcom/amap/api/mapcore2d/j;
    //   222: getfield 57	com/amap/api/mapcore2d/j:b	Lcom/amap/api/mapcore2d/bl;
    //   225: ifnull -186 -> 39
    //   228: aload_0
    //   229: getfield 12	com/amap/api/mapcore2d/k:a	Lcom/amap/api/mapcore2d/j;
    //   232: getfield 57	com/amap/api/mapcore2d/j:b	Lcom/amap/api/mapcore2d/bl;
    //   235: getfield 105	com/amap/api/mapcore2d/bl:e	Lcom/amap/api/mapcore2d/bl$c;
    //   238: astore 5
    //   240: aload 4
    //   242: astore_3
    //   243: aload 5
    //   245: ifnull -206 -> 39
    //   248: aload_0
    //   249: getfield 12	com/amap/api/mapcore2d/k:a	Lcom/amap/api/mapcore2d/j;
    //   252: aload 4
    //   254: invokevirtual 108	com/amap/api/mapcore2d/j:a	(Ljava/util/ArrayList;)Ljava/util/ArrayList;
    //   257: astore_3
    //   258: aload_3
    //   259: astore_2
    //   260: aload_3
    //   261: ifnull +29 -> 290
    //   264: aload_3
    //   265: astore_2
    //   266: aload_0
    //   267: getfield 12	com/amap/api/mapcore2d/k:a	Lcom/amap/api/mapcore2d/j;
    //   270: getfield 85	com/amap/api/mapcore2d/j:a	Lcom/amap/api/mapcore2d/bx;
    //   273: ifnull +17 -> 290
    //   276: aload_0
    //   277: getfield 12	com/amap/api/mapcore2d/k:a	Lcom/amap/api/mapcore2d/j;
    //   280: getfield 85	com/amap/api/mapcore2d/j:a	Lcom/amap/api/mapcore2d/bx;
    //   283: aload_3
    //   284: iconst_0
    //   285: invokevirtual 111	com/amap/api/mapcore2d/bx:a	(Ljava/util/List;Z)V
    //   288: aload_3
    //   289: astore_2
    //   290: aload_0
    //   291: getfield 12	com/amap/api/mapcore2d/k:a	Lcom/amap/api/mapcore2d/j;
    //   294: invokestatic 50	com/amap/api/mapcore2d/j:b	(Lcom/amap/api/mapcore2d/j;)Z
    //   297: iconst_1
    //   298: if_icmpne +65 -> 363
    //   301: invokestatic 54	java/lang/Thread:interrupted	()Z
    //   304: istore_1
    //   305: iload_1
    //   306: ifne +57 -> 363
    //   309: ldc2_w 112
    //   312: invokestatic 79	java/lang/Thread:sleep	(J)V
    //   315: aload 4
    //   317: astore_3
    //   318: goto -279 -> 39
    //   321: astore_3
    //   322: aload_3
    //   323: ldc 62
    //   325: ldc 63
    //   327: invokestatic 68	com/amap/api/mapcore2d/cy:a	(Ljava/lang/Throwable;Ljava/lang/String;Ljava/lang/String;)V
    //   330: aload_2
    //   331: astore_3
    //   332: goto -74 -> 258
    //   335: astore_3
    //   336: invokestatic 29	java/lang/Thread:currentThread	()Ljava/lang/Thread;
    //   339: invokevirtual 82	java/lang/Thread:interrupt	()V
    //   342: aload 4
    //   344: astore_3
    //   345: goto -306 -> 39
    //   348: astore_3
    //   349: aload_3
    //   350: ldc 62
    //   352: ldc 63
    //   354: invokestatic 68	com/amap/api/mapcore2d/cy:a	(Ljava/lang/Throwable;Ljava/lang/String;Ljava/lang/String;)V
    //   357: aload 4
    //   359: astore_3
    //   360: goto -321 -> 39
    //   363: aload 4
    //   365: astore_3
    //   366: goto -327 -> 39
    //   369: goto -79 -> 290
    //   372: aconst_null
    //   373: astore_2
    //   374: aconst_null
    //   375: astore_3
    //   376: goto -337 -> 39
    // Local variable table:
    //   start	length	slot	name	signature
    //   0	379	0	this	k
    //   90	216	1	bool	boolean
    //   3	29	2	localThread	Thread
    //   77	2	2	localException1	Exception
    //   259	115	2	localObject1	Object
    //   141	177	3	localObject2	Object
    //   321	2	3	localAMapException	com.amap.api.maps2d.AMapException
    //   331	1	3	localObject3	Object
    //   335	1	3	localInterruptedException1	InterruptedException
    //   344	1	3	localObject4	Object
    //   348	2	3	localException2	Exception
    //   359	17	3	localObject5	Object
    //   110	1	4	localInterruptedException2	InterruptedException
    //   121	3	4	localException3	Exception
    //   142	222	4	localObject6	Object
    //   238	6	5	localc	bl.c
    // Exception table:
    //   from	to	target	type
    //   14	36	77	java/lang/Exception
    //   39	74	77	java/lang/Exception
    //   87	91	77	java/lang/Exception
    //   112	118	77	java/lang/Exception
    //   123	138	77	java/lang/Exception
    //   144	174	77	java/lang/Exception
    //   182	190	77	java/lang/Exception
    //   190	200	77	java/lang/Exception
    //   205	215	77	java/lang/Exception
    //   218	240	77	java/lang/Exception
    //   248	258	77	java/lang/Exception
    //   266	288	77	java/lang/Exception
    //   290	305	77	java/lang/Exception
    //   322	330	77	java/lang/Exception
    //   336	342	77	java/lang/Exception
    //   349	357	77	java/lang/Exception
    //   95	107	110	java/lang/InterruptedException
    //   95	107	121	java/lang/Exception
    //   248	258	321	com/amap/api/maps2d/AMapException
    //   309	315	335	java/lang/InterruptedException
    //   309	315	348	java/lang/Exception
  }
}

/* Location:
 * Qualified Name:     com.amap.api.mapcore2d.k
 * Java Class Version: 6 (50.0)
 * JD-Core Version:    0.7.1
 */