package cn.com.xy.sms.util;

import cn.com.xy.sms.sdk.Iservice.XyCallBack;

final class k
  implements XyCallBack
{
  k(String paramString1, String paramString2, String paramString3, String paramString4, String paramString5, SdkCallBack paramSdkCallBack, String paramString6, String paramString7, String paramString8, String paramString9, String paramString10) {}
  
  /* Error */
  public final void execute(Object... paramVarArgs)
  {
    // Byte code:
    //   0: aconst_null
    //   1: astore 21
    //   3: aconst_null
    //   4: astore 20
    //   6: aload_0
    //   7: getfield 23	cn/com/xy/sms/util/k:a	Ljava/lang/String;
    //   10: invokestatic 57	cn/com/xy/sms/sdk/util/StringUtils:isNull	(Ljava/lang/String;)Z
    //   13: ifne +68 -> 81
    //   16: new 59	org/json/JSONObject
    //   19: dup
    //   20: aload_0
    //   21: getfield 23	cn/com/xy/sms/util/k:a	Ljava/lang/String;
    //   24: invokespecial 62	org/json/JSONObject:<init>	(Ljava/lang/String;)V
    //   27: astore 19
    //   29: aload_1
    //   30: ifnull +29 -> 59
    //   33: aload 21
    //   35: astore_3
    //   36: aload_1
    //   37: arraylength
    //   38: iconst_2
    //   39: if_icmplt +20 -> 59
    //   42: aload 21
    //   44: astore_3
    //   45: aload_1
    //   46: iconst_1
    //   47: aaload
    //   48: invokevirtual 66	java/lang/Object:toString	()Ljava/lang/String;
    //   51: ldc 68
    //   53: invokevirtual 74	java/lang/String:indexOf	(Ljava/lang/String;)I
    //   56: ifeq +70 -> 126
    //   59: aload 21
    //   61: astore_3
    //   62: aload_0
    //   63: getfield 33	cn/com/xy/sms/util/k:f	Lcn/com/xy/sms/util/SdkCallBack;
    //   66: aconst_null
    //   67: invokestatic 80	cn/com/xy/sms/sdk/util/XyUtil:doXycallBackResult	(Lcn/com/xy/sms/sdk/Iservice/XyCallBack;[Ljava/lang/Object;)V
    //   70: aload 19
    //   72: ifnonnull +15 -> 87
    //   75: return
    //   76: astore_3
    //   77: aload_3
    //   78: invokevirtual 83	org/json/JSONException:printStackTrace	()V
    //   81: aconst_null
    //   82: astore 19
    //   84: goto -55 -> 29
    //   87: aload 19
    //   89: ldc 85
    //   91: invokestatic 91	java/lang/System:currentTimeMillis	()J
    //   94: invokevirtual 95	org/json/JSONObject:put	(Ljava/lang/String;J)Lorg/json/JSONObject;
    //   97: pop
    //   98: aload_0
    //   99: getfield 25	cn/com/xy/sms/util/k:b	Ljava/lang/String;
    //   102: aload_0
    //   103: getfield 27	cn/com/xy/sms/util/k:c	Ljava/lang/String;
    //   106: aload_0
    //   107: getfield 29	cn/com/xy/sms/util/k:d	Ljava/lang/String;
    //   110: aload 19
    //   112: aload_0
    //   113: getfield 31	cn/com/xy/sms/util/k:e	Ljava/lang/String;
    //   116: invokestatic 101	cn/com/xy/sms/util/ParseManager:updateMatchCacheManager	(Ljava/lang/String;Ljava/lang/String;Ljava/lang/String;Lorg/json/JSONObject;Ljava/lang/String;)V
    //   119: return
    //   120: astore_1
    //   121: aload_1
    //   122: invokevirtual 83	org/json/JSONException:printStackTrace	()V
    //   125: return
    //   126: aload 21
    //   128: astore_3
    //   129: new 103	org/json/JSONArray
    //   132: dup
    //   133: aload_1
    //   134: iconst_1
    //   135: aaload
    //   136: checkcast 70	java/lang/String
    //   139: invokespecial 104	org/json/JSONArray:<init>	(Ljava/lang/String;)V
    //   142: astore 22
    //   144: ldc 106
    //   146: astore 4
    //   148: ldc 106
    //   150: astore 5
    //   152: ldc 106
    //   154: astore 6
    //   156: ldc 106
    //   158: astore 8
    //   160: ldc 106
    //   162: astore_1
    //   163: ldc 106
    //   165: astore 10
    //   167: ldc 106
    //   169: astore 7
    //   171: iconst_0
    //   172: istore_2
    //   173: ldc 106
    //   175: astore 18
    //   177: aload 21
    //   179: astore_3
    //   180: iload_2
    //   181: aload 22
    //   183: invokevirtual 110	org/json/JSONArray:length	()I
    //   186: if_icmplt +208 -> 394
    //   189: aload 8
    //   191: astore 12
    //   193: aload_1
    //   194: astore 14
    //   196: aload 10
    //   198: astore 15
    //   200: aload 7
    //   202: astore 17
    //   204: goto +1139 -> 1343
    //   207: aload 21
    //   209: astore_3
    //   210: aload 10
    //   212: invokestatic 57	cn/com/xy/sms/sdk/util/StringUtils:isNull	(Ljava/lang/String;)Z
    //   215: ifne +924 -> 1139
    //   218: aload 21
    //   220: astore_3
    //   221: new 59	org/json/JSONObject
    //   224: dup
    //   225: invokespecial 111	org/json/JSONObject:<init>	()V
    //   228: astore 11
    //   230: aload 11
    //   232: ldc 113
    //   234: aload 10
    //   236: invokevirtual 116	org/json/JSONObject:put	(Ljava/lang/String;Ljava/lang/Object;)Lorg/json/JSONObject;
    //   239: pop
    //   240: aload 11
    //   242: ldc 118
    //   244: aload 9
    //   246: invokevirtual 116	org/json/JSONObject:put	(Ljava/lang/String;Ljava/lang/Object;)Lorg/json/JSONObject;
    //   249: pop
    //   250: aload 11
    //   252: ldc 120
    //   254: aload 8
    //   256: invokevirtual 116	org/json/JSONObject:put	(Ljava/lang/String;Ljava/lang/Object;)Lorg/json/JSONObject;
    //   259: pop
    //   260: aload 11
    //   262: ldc 122
    //   264: aload 7
    //   266: invokevirtual 116	org/json/JSONObject:put	(Ljava/lang/String;Ljava/lang/Object;)Lorg/json/JSONObject;
    //   269: pop
    //   270: aload 11
    //   272: ldc 124
    //   274: aload 6
    //   276: invokevirtual 116	org/json/JSONObject:put	(Ljava/lang/String;Ljava/lang/Object;)Lorg/json/JSONObject;
    //   279: pop
    //   280: aload 11
    //   282: ldc 126
    //   284: aload 5
    //   286: invokevirtual 116	org/json/JSONObject:put	(Ljava/lang/String;Ljava/lang/Object;)Lorg/json/JSONObject;
    //   289: pop
    //   290: aload 11
    //   292: ldc -128
    //   294: invokestatic 91	java/lang/System:currentTimeMillis	()J
    //   297: invokevirtual 95	org/json/JSONObject:put	(Ljava/lang/String;J)Lorg/json/JSONObject;
    //   300: pop
    //   301: aload 11
    //   303: ldc -126
    //   305: aload_1
    //   306: invokevirtual 116	org/json/JSONObject:put	(Ljava/lang/String;Ljava/lang/Object;)Lorg/json/JSONObject;
    //   309: pop
    //   310: aload 11
    //   312: ldc -124
    //   314: aload 4
    //   316: invokevirtual 116	org/json/JSONObject:put	(Ljava/lang/String;Ljava/lang/Object;)Lorg/json/JSONObject;
    //   319: pop
    //   320: aload_0
    //   321: getfield 33	cn/com/xy/sms/util/k:f	Lcn/com/xy/sms/util/SdkCallBack;
    //   324: iconst_2
    //   325: anewarray 4	java/lang/Object
    //   328: dup
    //   329: iconst_0
    //   330: aload_0
    //   331: getfield 43	cn/com/xy/sms/util/k:k	Ljava/lang/String;
    //   334: aastore
    //   335: dup
    //   336: iconst_1
    //   337: aload 11
    //   339: aastore
    //   340: invokestatic 80	cn/com/xy/sms/sdk/util/XyUtil:doXycallBackResult	(Lcn/com/xy/sms/sdk/Iservice/XyCallBack;[Ljava/lang/Object;)V
    //   343: aload 19
    //   345: ifnull -270 -> 75
    //   348: aload 19
    //   350: ldc 85
    //   352: invokestatic 91	java/lang/System:currentTimeMillis	()J
    //   355: invokevirtual 95	org/json/JSONObject:put	(Ljava/lang/String;J)Lorg/json/JSONObject;
    //   358: pop
    //   359: aload 19
    //   361: aload 11
    //   363: invokestatic 138	cn/com/xy/sms/sdk/util/JsonUtil:JSONCombine	(Lorg/json/JSONObject;Lorg/json/JSONObject;)V
    //   366: aload_0
    //   367: getfield 25	cn/com/xy/sms/util/k:b	Ljava/lang/String;
    //   370: aload_0
    //   371: getfield 27	cn/com/xy/sms/util/k:c	Ljava/lang/String;
    //   374: aload_0
    //   375: getfield 29	cn/com/xy/sms/util/k:d	Ljava/lang/String;
    //   378: aload 19
    //   380: aload_0
    //   381: getfield 31	cn/com/xy/sms/util/k:e	Ljava/lang/String;
    //   384: invokestatic 101	cn/com/xy/sms/util/ParseManager:updateMatchCacheManager	(Ljava/lang/String;Ljava/lang/String;Ljava/lang/String;Lorg/json/JSONObject;Ljava/lang/String;)V
    //   387: return
    //   388: astore_1
    //   389: aload_1
    //   390: invokevirtual 83	org/json/JSONException:printStackTrace	()V
    //   393: return
    //   394: aload 21
    //   396: astore_3
    //   397: aload 22
    //   399: iload_2
    //   400: invokevirtual 142	org/json/JSONArray:get	(I)Ljava/lang/Object;
    //   403: checkcast 59	org/json/JSONObject
    //   406: astore 4
    //   408: aload 21
    //   410: astore_3
    //   411: aload 4
    //   413: ldc 113
    //   415: invokevirtual 146	org/json/JSONObject:getString	(Ljava/lang/String;)Ljava/lang/String;
    //   418: astore 16
    //   420: aload 21
    //   422: astore_3
    //   423: aload 4
    //   425: ldc 118
    //   427: invokevirtual 146	org/json/JSONObject:getString	(Ljava/lang/String;)Ljava/lang/String;
    //   430: astore 7
    //   432: aload 21
    //   434: astore_3
    //   435: aload 4
    //   437: ldc 120
    //   439: invokevirtual 146	org/json/JSONObject:getString	(Ljava/lang/String;)Ljava/lang/String;
    //   442: astore 10
    //   444: aload 21
    //   446: astore_3
    //   447: aload 4
    //   449: ldc 122
    //   451: invokevirtual 146	org/json/JSONObject:getString	(Ljava/lang/String;)Ljava/lang/String;
    //   454: astore_1
    //   455: aload 21
    //   457: astore_3
    //   458: aload 4
    //   460: ldc 124
    //   462: invokevirtual 146	org/json/JSONObject:getString	(Ljava/lang/String;)Ljava/lang/String;
    //   465: astore 8
    //   467: aload 21
    //   469: astore_3
    //   470: aload 4
    //   472: ldc 126
    //   474: invokevirtual 146	org/json/JSONObject:getString	(Ljava/lang/String;)Ljava/lang/String;
    //   477: astore 11
    //   479: aload 21
    //   481: astore_3
    //   482: aload 4
    //   484: ldc -126
    //   486: invokevirtual 146	org/json/JSONObject:getString	(Ljava/lang/String;)Ljava/lang/String;
    //   489: astore 9
    //   491: aload 21
    //   493: astore_3
    //   494: aload 4
    //   496: ldc -124
    //   498: invokevirtual 146	org/json/JSONObject:getString	(Ljava/lang/String;)Ljava/lang/String;
    //   501: astore 13
    //   503: aload 21
    //   505: astore_3
    //   506: aload_0
    //   507: getfield 35	cn/com/xy/sms/util/k:g	Ljava/lang/String;
    //   510: invokestatic 57	cn/com/xy/sms/sdk/util/StringUtils:isNull	(Ljava/lang/String;)Z
    //   513: ifeq +73 -> 586
    //   516: aload 21
    //   518: astore_3
    //   519: aload_0
    //   520: getfield 37	cn/com/xy/sms/util/k:h	Ljava/lang/String;
    //   523: invokestatic 57	cn/com/xy/sms/sdk/util/StringUtils:isNull	(Ljava/lang/String;)Z
    //   526: ifeq +60 -> 586
    //   529: aload 21
    //   531: astore_3
    //   532: aload_0
    //   533: getfield 39	cn/com/xy/sms/util/k:i	Ljava/lang/String;
    //   536: invokestatic 57	cn/com/xy/sms/sdk/util/StringUtils:isNull	(Ljava/lang/String;)Z
    //   539: ifeq +47 -> 586
    //   542: aload 21
    //   544: astore_3
    //   545: aload 13
    //   547: astore 4
    //   549: aload 9
    //   551: astore 5
    //   553: aload 11
    //   555: astore 6
    //   557: aload 8
    //   559: astore 12
    //   561: aload_1
    //   562: astore 14
    //   564: aload 10
    //   566: astore 15
    //   568: aload 7
    //   570: astore 17
    //   572: aload 16
    //   574: astore 18
    //   576: aload_0
    //   577: getfield 41	cn/com/xy/sms/util/k:j	Ljava/lang/String;
    //   580: invokestatic 57	cn/com/xy/sms/sdk/util/StringUtils:isNull	(Ljava/lang/String;)Z
    //   583: ifne +760 -> 1343
    //   586: aload 21
    //   588: astore_3
    //   589: aload_0
    //   590: getfield 35	cn/com/xy/sms/util/k:g	Ljava/lang/String;
    //   593: invokestatic 57	cn/com/xy/sms/sdk/util/StringUtils:isNull	(Ljava/lang/String;)Z
    //   596: ifne +77 -> 673
    //   599: aload 21
    //   601: astore_3
    //   602: aload_0
    //   603: getfield 37	cn/com/xy/sms/util/k:h	Ljava/lang/String;
    //   606: invokestatic 57	cn/com/xy/sms/sdk/util/StringUtils:isNull	(Ljava/lang/String;)Z
    //   609: ifne +64 -> 673
    //   612: aload 21
    //   614: astore_3
    //   615: aload_0
    //   616: getfield 35	cn/com/xy/sms/util/k:g	Ljava/lang/String;
    //   619: aload 8
    //   621: invokevirtual 150	java/lang/String:equals	(Ljava/lang/Object;)Z
    //   624: ifeq +49 -> 673
    //   627: aload 21
    //   629: astore_3
    //   630: aload 13
    //   632: astore 4
    //   634: aload 9
    //   636: astore 5
    //   638: aload 11
    //   640: astore 6
    //   642: aload 8
    //   644: astore 12
    //   646: aload_1
    //   647: astore 14
    //   649: aload 10
    //   651: astore 15
    //   653: aload 7
    //   655: astore 17
    //   657: aload 16
    //   659: astore 18
    //   661: aload_0
    //   662: getfield 37	cn/com/xy/sms/util/k:h	Ljava/lang/String;
    //   665: aload 11
    //   667: invokevirtual 150	java/lang/String:equals	(Ljava/lang/Object;)Z
    //   670: ifne +673 -> 1343
    //   673: aload 21
    //   675: astore_3
    //   676: aload_0
    //   677: getfield 35	cn/com/xy/sms/util/k:g	Ljava/lang/String;
    //   680: invokestatic 57	cn/com/xy/sms/sdk/util/StringUtils:isNull	(Ljava/lang/String;)Z
    //   683: ifne +70 -> 753
    //   686: aload 21
    //   688: astore_3
    //   689: aload_0
    //   690: getfield 37	cn/com/xy/sms/util/k:h	Ljava/lang/String;
    //   693: invokestatic 57	cn/com/xy/sms/sdk/util/StringUtils:isNull	(Ljava/lang/String;)Z
    //   696: ifeq +57 -> 753
    //   699: aload 21
    //   701: astore_3
    //   702: aload_0
    //   703: getfield 35	cn/com/xy/sms/util/k:g	Ljava/lang/String;
    //   706: aload 8
    //   708: invokevirtual 150	java/lang/String:equals	(Ljava/lang/Object;)Z
    //   711: ifeq +42 -> 753
    //   714: ldc 106
    //   716: astore 4
    //   718: aload 16
    //   720: astore 10
    //   722: aload 7
    //   724: astore_3
    //   725: ldc 106
    //   727: astore 11
    //   729: aload_1
    //   730: astore 7
    //   732: aload 8
    //   734: astore 6
    //   736: ldc 106
    //   738: astore 5
    //   740: aload 9
    //   742: astore_1
    //   743: aload 11
    //   745: astore 8
    //   747: aload_3
    //   748: astore 9
    //   750: goto -543 -> 207
    //   753: aload 21
    //   755: astore_3
    //   756: aload_0
    //   757: getfield 37	cn/com/xy/sms/util/k:h	Ljava/lang/String;
    //   760: invokestatic 57	cn/com/xy/sms/sdk/util/StringUtils:isNull	(Ljava/lang/String;)Z
    //   763: ifne +64 -> 827
    //   766: aload 21
    //   768: astore_3
    //   769: aload_0
    //   770: getfield 35	cn/com/xy/sms/util/k:g	Ljava/lang/String;
    //   773: invokestatic 57	cn/com/xy/sms/sdk/util/StringUtils:isNull	(Ljava/lang/String;)Z
    //   776: ifeq +51 -> 827
    //   779: aload 21
    //   781: astore_3
    //   782: aload_0
    //   783: getfield 37	cn/com/xy/sms/util/k:h	Ljava/lang/String;
    //   786: aload 11
    //   788: invokevirtual 150	java/lang/String:equals	(Ljava/lang/Object;)Z
    //   791: ifeq +36 -> 827
    //   794: ldc 106
    //   796: astore 9
    //   798: aload 10
    //   800: astore 8
    //   802: aload_1
    //   803: astore 7
    //   805: ldc 106
    //   807: astore 6
    //   809: aload 11
    //   811: astore 5
    //   813: ldc 106
    //   815: astore_1
    //   816: aload 13
    //   818: astore 4
    //   820: aload 16
    //   822: astore 10
    //   824: goto -617 -> 207
    //   827: aload 21
    //   829: astore_3
    //   830: aload_0
    //   831: getfield 35	cn/com/xy/sms/util/k:g	Ljava/lang/String;
    //   834: invokestatic 57	cn/com/xy/sms/sdk/util/StringUtils:isNull	(Ljava/lang/String;)Z
    //   837: ifeq +103 -> 940
    //   840: aload 21
    //   842: astore_3
    //   843: aload_0
    //   844: getfield 37	cn/com/xy/sms/util/k:h	Ljava/lang/String;
    //   847: invokestatic 57	cn/com/xy/sms/sdk/util/StringUtils:isNull	(Ljava/lang/String;)Z
    //   850: ifeq +90 -> 940
    //   853: aload 21
    //   855: astore_3
    //   856: aload_0
    //   857: getfield 39	cn/com/xy/sms/util/k:i	Ljava/lang/String;
    //   860: invokestatic 57	cn/com/xy/sms/sdk/util/StringUtils:isNull	(Ljava/lang/String;)Z
    //   863: ifne +77 -> 940
    //   866: aload 21
    //   868: astore_3
    //   869: aload_0
    //   870: getfield 41	cn/com/xy/sms/util/k:j	Ljava/lang/String;
    //   873: invokestatic 57	cn/com/xy/sms/sdk/util/StringUtils:isNull	(Ljava/lang/String;)Z
    //   876: ifne +64 -> 940
    //   879: aload 21
    //   881: astore_3
    //   882: aload 9
    //   884: aload_0
    //   885: getfield 39	cn/com/xy/sms/util/k:i	Ljava/lang/String;
    //   888: invokevirtual 154	java/lang/String:contains	(Ljava/lang/CharSequence;)Z
    //   891: ifeq +49 -> 940
    //   894: aload 21
    //   896: astore_3
    //   897: aload 13
    //   899: astore 4
    //   901: aload 9
    //   903: astore 5
    //   905: aload 11
    //   907: astore 6
    //   909: aload 8
    //   911: astore 12
    //   913: aload_1
    //   914: astore 14
    //   916: aload 10
    //   918: astore 15
    //   920: aload 7
    //   922: astore 17
    //   924: aload 16
    //   926: astore 18
    //   928: aload 13
    //   930: aload_0
    //   931: getfield 41	cn/com/xy/sms/util/k:j	Ljava/lang/String;
    //   934: invokevirtual 154	java/lang/String:contains	(Ljava/lang/CharSequence;)Z
    //   937: ifne +406 -> 1343
    //   940: aload 21
    //   942: astore_3
    //   943: aload_0
    //   944: getfield 35	cn/com/xy/sms/util/k:g	Ljava/lang/String;
    //   947: invokestatic 57	cn/com/xy/sms/sdk/util/StringUtils:isNull	(Ljava/lang/String;)Z
    //   950: ifeq +88 -> 1038
    //   953: aload 21
    //   955: astore_3
    //   956: aload_0
    //   957: getfield 37	cn/com/xy/sms/util/k:h	Ljava/lang/String;
    //   960: invokestatic 57	cn/com/xy/sms/sdk/util/StringUtils:isNull	(Ljava/lang/String;)Z
    //   963: ifeq +75 -> 1038
    //   966: aload 21
    //   968: astore_3
    //   969: aload_0
    //   970: getfield 41	cn/com/xy/sms/util/k:j	Ljava/lang/String;
    //   973: invokestatic 57	cn/com/xy/sms/sdk/util/StringUtils:isNull	(Ljava/lang/String;)Z
    //   976: ifeq +62 -> 1038
    //   979: aload 21
    //   981: astore_3
    //   982: aload_0
    //   983: getfield 39	cn/com/xy/sms/util/k:i	Ljava/lang/String;
    //   986: invokestatic 57	cn/com/xy/sms/sdk/util/StringUtils:isNull	(Ljava/lang/String;)Z
    //   989: ifne +49 -> 1038
    //   992: aload 21
    //   994: astore_3
    //   995: aload 13
    //   997: astore 4
    //   999: aload 9
    //   1001: astore 5
    //   1003: aload 11
    //   1005: astore 6
    //   1007: aload 8
    //   1009: astore 12
    //   1011: aload_1
    //   1012: astore 14
    //   1014: aload 10
    //   1016: astore 15
    //   1018: aload 7
    //   1020: astore 17
    //   1022: aload 16
    //   1024: astore 18
    //   1026: aload 9
    //   1028: aload_0
    //   1029: getfield 39	cn/com/xy/sms/util/k:i	Ljava/lang/String;
    //   1032: invokevirtual 154	java/lang/String:contains	(Ljava/lang/CharSequence;)Z
    //   1035: ifne +308 -> 1343
    //   1038: aload 21
    //   1040: astore_3
    //   1041: aload_0
    //   1042: getfield 35	cn/com/xy/sms/util/k:g	Ljava/lang/String;
    //   1045: invokestatic 57	cn/com/xy/sms/sdk/util/StringUtils:isNull	(Ljava/lang/String;)Z
    //   1048: ifeq +325 -> 1373
    //   1051: aload 21
    //   1053: astore_3
    //   1054: aload_0
    //   1055: getfield 37	cn/com/xy/sms/util/k:h	Ljava/lang/String;
    //   1058: invokestatic 57	cn/com/xy/sms/sdk/util/StringUtils:isNull	(Ljava/lang/String;)Z
    //   1061: ifeq +312 -> 1373
    //   1064: aload 21
    //   1066: astore_3
    //   1067: aload_0
    //   1068: getfield 39	cn/com/xy/sms/util/k:i	Ljava/lang/String;
    //   1071: invokestatic 57	cn/com/xy/sms/sdk/util/StringUtils:isNull	(Ljava/lang/String;)Z
    //   1074: ifeq +299 -> 1373
    //   1077: aload 21
    //   1079: astore_3
    //   1080: aload_0
    //   1081: getfield 41	cn/com/xy/sms/util/k:j	Ljava/lang/String;
    //   1084: invokestatic 57	cn/com/xy/sms/sdk/util/StringUtils:isNull	(Ljava/lang/String;)Z
    //   1087: ifne +286 -> 1373
    //   1090: aload 21
    //   1092: astore_3
    //   1093: aload 13
    //   1095: astore 4
    //   1097: aload 9
    //   1099: astore 5
    //   1101: aload 11
    //   1103: astore 6
    //   1105: aload 8
    //   1107: astore 12
    //   1109: aload_1
    //   1110: astore 14
    //   1112: aload 10
    //   1114: astore 15
    //   1116: aload 7
    //   1118: astore 17
    //   1120: aload 16
    //   1122: astore 18
    //   1124: aload 13
    //   1126: aload_0
    //   1127: getfield 41	cn/com/xy/sms/util/k:j	Ljava/lang/String;
    //   1130: invokevirtual 154	java/lang/String:contains	(Ljava/lang/CharSequence;)Z
    //   1133: ifne +210 -> 1343
    //   1136: goto +237 -> 1373
    //   1139: aload 21
    //   1141: astore_3
    //   1142: aload_0
    //   1143: getfield 33	cn/com/xy/sms/util/k:f	Lcn/com/xy/sms/util/SdkCallBack;
    //   1146: aconst_null
    //   1147: invokestatic 80	cn/com/xy/sms/sdk/util/XyUtil:doXycallBackResult	(Lcn/com/xy/sms/sdk/Iservice/XyCallBack;[Ljava/lang/Object;)V
    //   1150: aload 19
    //   1152: ifnull -1077 -> 75
    //   1155: aload 19
    //   1157: ldc 85
    //   1159: invokestatic 91	java/lang/System:currentTimeMillis	()J
    //   1162: invokevirtual 95	org/json/JSONObject:put	(Ljava/lang/String;J)Lorg/json/JSONObject;
    //   1165: pop
    //   1166: aload_0
    //   1167: getfield 25	cn/com/xy/sms/util/k:b	Ljava/lang/String;
    //   1170: aload_0
    //   1171: getfield 27	cn/com/xy/sms/util/k:c	Ljava/lang/String;
    //   1174: aload_0
    //   1175: getfield 29	cn/com/xy/sms/util/k:d	Ljava/lang/String;
    //   1178: aload 19
    //   1180: aload_0
    //   1181: getfield 31	cn/com/xy/sms/util/k:e	Ljava/lang/String;
    //   1184: invokestatic 101	cn/com/xy/sms/util/ParseManager:updateMatchCacheManager	(Ljava/lang/String;Ljava/lang/String;Ljava/lang/String;Lorg/json/JSONObject;Ljava/lang/String;)V
    //   1187: return
    //   1188: astore_1
    //   1189: aload_1
    //   1190: invokevirtual 83	org/json/JSONException:printStackTrace	()V
    //   1193: return
    //   1194: astore 4
    //   1196: aload 20
    //   1198: astore_1
    //   1199: aload_1
    //   1200: astore_3
    //   1201: aload 4
    //   1203: invokevirtual 83	org/json/JSONException:printStackTrace	()V
    //   1206: aload_1
    //   1207: astore_3
    //   1208: aload_0
    //   1209: getfield 33	cn/com/xy/sms/util/k:f	Lcn/com/xy/sms/util/SdkCallBack;
    //   1212: aconst_null
    //   1213: invokestatic 80	cn/com/xy/sms/sdk/util/XyUtil:doXycallBackResult	(Lcn/com/xy/sms/sdk/Iservice/XyCallBack;[Ljava/lang/Object;)V
    //   1216: aload 19
    //   1218: ifnull -1143 -> 75
    //   1221: aload 19
    //   1223: ldc 85
    //   1225: invokestatic 91	java/lang/System:currentTimeMillis	()J
    //   1228: invokevirtual 95	org/json/JSONObject:put	(Ljava/lang/String;J)Lorg/json/JSONObject;
    //   1231: pop
    //   1232: aload_1
    //   1233: ifnull +9 -> 1242
    //   1236: aload 19
    //   1238: aload_1
    //   1239: invokestatic 138	cn/com/xy/sms/sdk/util/JsonUtil:JSONCombine	(Lorg/json/JSONObject;Lorg/json/JSONObject;)V
    //   1242: aload_0
    //   1243: getfield 25	cn/com/xy/sms/util/k:b	Ljava/lang/String;
    //   1246: aload_0
    //   1247: getfield 27	cn/com/xy/sms/util/k:c	Ljava/lang/String;
    //   1250: aload_0
    //   1251: getfield 29	cn/com/xy/sms/util/k:d	Ljava/lang/String;
    //   1254: aload 19
    //   1256: aload_0
    //   1257: getfield 31	cn/com/xy/sms/util/k:e	Ljava/lang/String;
    //   1260: invokestatic 101	cn/com/xy/sms/util/ParseManager:updateMatchCacheManager	(Ljava/lang/String;Ljava/lang/String;Ljava/lang/String;Lorg/json/JSONObject;Ljava/lang/String;)V
    //   1263: return
    //   1264: astore_1
    //   1265: aload_1
    //   1266: invokevirtual 83	org/json/JSONException:printStackTrace	()V
    //   1269: return
    //   1270: astore_1
    //   1271: aload 19
    //   1273: ifnull -1198 -> 75
    //   1276: aload 19
    //   1278: ldc 85
    //   1280: invokestatic 91	java/lang/System:currentTimeMillis	()J
    //   1283: invokevirtual 95	org/json/JSONObject:put	(Ljava/lang/String;J)Lorg/json/JSONObject;
    //   1286: pop
    //   1287: aload_3
    //   1288: ifnull +9 -> 1297
    //   1291: aload 19
    //   1293: aload_3
    //   1294: invokestatic 138	cn/com/xy/sms/sdk/util/JsonUtil:JSONCombine	(Lorg/json/JSONObject;Lorg/json/JSONObject;)V
    //   1297: aload_0
    //   1298: getfield 25	cn/com/xy/sms/util/k:b	Ljava/lang/String;
    //   1301: aload_0
    //   1302: getfield 27	cn/com/xy/sms/util/k:c	Ljava/lang/String;
    //   1305: aload_0
    //   1306: getfield 29	cn/com/xy/sms/util/k:d	Ljava/lang/String;
    //   1309: aload 19
    //   1311: aload_0
    //   1312: getfield 31	cn/com/xy/sms/util/k:e	Ljava/lang/String;
    //   1315: invokestatic 101	cn/com/xy/sms/util/ParseManager:updateMatchCacheManager	(Ljava/lang/String;Ljava/lang/String;Ljava/lang/String;Lorg/json/JSONObject;Ljava/lang/String;)V
    //   1318: aload_1
    //   1319: athrow
    //   1320: astore_3
    //   1321: aload_3
    //   1322: invokevirtual 83	org/json/JSONException:printStackTrace	()V
    //   1325: goto -7 -> 1318
    //   1328: astore_1
    //   1329: aload 11
    //   1331: astore_3
    //   1332: goto -61 -> 1271
    //   1335: astore 4
    //   1337: aload 11
    //   1339: astore_1
    //   1340: goto -141 -> 1199
    //   1343: aload 18
    //   1345: astore 10
    //   1347: aload 17
    //   1349: astore 9
    //   1351: aload 15
    //   1353: astore 8
    //   1355: aload 14
    //   1357: astore 7
    //   1359: aload 5
    //   1361: astore_1
    //   1362: aload 6
    //   1364: astore 5
    //   1366: aload 12
    //   1368: astore 6
    //   1370: goto -1163 -> 207
    //   1373: iload_2
    //   1374: iconst_1
    //   1375: iadd
    //   1376: istore_2
    //   1377: aload 13
    //   1379: astore 4
    //   1381: aload 9
    //   1383: astore 5
    //   1385: aload 11
    //   1387: astore 6
    //   1389: goto -1216 -> 173
    // Local variable table:
    //   start	length	slot	name	signature
    //   0	1392	0	this	k
    //   0	1392	1	paramVarArgs	Object[]
    //   172	1205	2	m	int
    //   35	27	3	localObject1	Object
    //   76	2	3	localJSONException1	org.json.JSONException
    //   128	1166	3	localObject2	Object
    //   1320	2	3	localJSONException2	org.json.JSONException
    //   1331	1	3	localObject3	Object
    //   146	950	4	localObject4	Object
    //   1194	8	4	localJSONException3	org.json.JSONException
    //   1335	1	4	localJSONException4	org.json.JSONException
    //   1379	1	4	localObject5	Object
    //   150	1234	5	localObject6	Object
    //   154	1234	6	localObject7	Object
    //   169	1189	7	localObject8	Object
    //   158	1196	8	localObject9	Object
    //   244	1138	9	localObject10	Object
    //   165	1181	10	localObject11	Object
    //   228	1158	11	localObject12	Object
    //   191	1176	12	localObject13	Object
    //   501	877	13	str1	String
    //   194	1162	14	arrayOfObject	Object[]
    //   198	1154	15	localObject14	Object
    //   418	703	16	str2	String
    //   202	1146	17	localObject15	Object
    //   175	1169	18	localObject16	Object
    //   27	1283	19	localJSONObject	org.json.JSONObject
    //   4	1193	20	localObject17	Object
    //   1	1139	21	localObject18	Object
    //   142	256	22	localJSONArray	org.json.JSONArray
    // Exception table:
    //   from	to	target	type
    //   16	29	76	org/json/JSONException
    //   87	119	120	org/json/JSONException
    //   348	387	388	org/json/JSONException
    //   1155	1187	1188	org/json/JSONException
    //   36	42	1194	org/json/JSONException
    //   45	59	1194	org/json/JSONException
    //   62	70	1194	org/json/JSONException
    //   129	144	1194	org/json/JSONException
    //   180	189	1194	org/json/JSONException
    //   210	218	1194	org/json/JSONException
    //   221	230	1194	org/json/JSONException
    //   397	408	1194	org/json/JSONException
    //   411	420	1194	org/json/JSONException
    //   423	432	1194	org/json/JSONException
    //   435	444	1194	org/json/JSONException
    //   447	455	1194	org/json/JSONException
    //   458	467	1194	org/json/JSONException
    //   470	479	1194	org/json/JSONException
    //   482	491	1194	org/json/JSONException
    //   494	503	1194	org/json/JSONException
    //   506	516	1194	org/json/JSONException
    //   519	529	1194	org/json/JSONException
    //   532	542	1194	org/json/JSONException
    //   576	586	1194	org/json/JSONException
    //   589	599	1194	org/json/JSONException
    //   602	612	1194	org/json/JSONException
    //   615	627	1194	org/json/JSONException
    //   661	673	1194	org/json/JSONException
    //   676	686	1194	org/json/JSONException
    //   689	699	1194	org/json/JSONException
    //   702	714	1194	org/json/JSONException
    //   756	766	1194	org/json/JSONException
    //   769	779	1194	org/json/JSONException
    //   782	794	1194	org/json/JSONException
    //   830	840	1194	org/json/JSONException
    //   843	853	1194	org/json/JSONException
    //   856	866	1194	org/json/JSONException
    //   869	879	1194	org/json/JSONException
    //   882	894	1194	org/json/JSONException
    //   928	940	1194	org/json/JSONException
    //   943	953	1194	org/json/JSONException
    //   956	966	1194	org/json/JSONException
    //   969	979	1194	org/json/JSONException
    //   982	992	1194	org/json/JSONException
    //   1026	1038	1194	org/json/JSONException
    //   1041	1051	1194	org/json/JSONException
    //   1054	1064	1194	org/json/JSONException
    //   1067	1077	1194	org/json/JSONException
    //   1080	1090	1194	org/json/JSONException
    //   1124	1136	1194	org/json/JSONException
    //   1142	1150	1194	org/json/JSONException
    //   1221	1232	1264	org/json/JSONException
    //   1236	1242	1264	org/json/JSONException
    //   1242	1263	1264	org/json/JSONException
    //   36	42	1270	finally
    //   45	59	1270	finally
    //   62	70	1270	finally
    //   129	144	1270	finally
    //   180	189	1270	finally
    //   210	218	1270	finally
    //   221	230	1270	finally
    //   397	408	1270	finally
    //   411	420	1270	finally
    //   423	432	1270	finally
    //   435	444	1270	finally
    //   447	455	1270	finally
    //   458	467	1270	finally
    //   470	479	1270	finally
    //   482	491	1270	finally
    //   494	503	1270	finally
    //   506	516	1270	finally
    //   519	529	1270	finally
    //   532	542	1270	finally
    //   576	586	1270	finally
    //   589	599	1270	finally
    //   602	612	1270	finally
    //   615	627	1270	finally
    //   661	673	1270	finally
    //   676	686	1270	finally
    //   689	699	1270	finally
    //   702	714	1270	finally
    //   756	766	1270	finally
    //   769	779	1270	finally
    //   782	794	1270	finally
    //   830	840	1270	finally
    //   843	853	1270	finally
    //   856	866	1270	finally
    //   869	879	1270	finally
    //   882	894	1270	finally
    //   928	940	1270	finally
    //   943	953	1270	finally
    //   956	966	1270	finally
    //   969	979	1270	finally
    //   982	992	1270	finally
    //   1026	1038	1270	finally
    //   1041	1051	1270	finally
    //   1054	1064	1270	finally
    //   1067	1077	1270	finally
    //   1080	1090	1270	finally
    //   1124	1136	1270	finally
    //   1142	1150	1270	finally
    //   1201	1206	1270	finally
    //   1208	1216	1270	finally
    //   1276	1287	1320	org/json/JSONException
    //   1291	1297	1320	org/json/JSONException
    //   1297	1318	1320	org/json/JSONException
    //   230	343	1328	finally
    //   230	343	1335	org/json/JSONException
  }
}

/* Location:
 * Qualified Name:     cn.com.xy.sms.util.k
 * Java Class Version: 6 (50.0)
 * JD-Core Version:    0.7.1
 */