package cn.com.xy.sms.sdk.db;

import cn.com.xy.sms.sdk.Iservice.XyCallBack;
import cn.com.xy.sms.sdk.db.entity.f;
import java.util.Map;

final class d
  implements XyCallBack
{
  d(boolean paramBoolean, Map paramMap, f paramf, XyCallBack paramXyCallBack) {}
  
  /* Error */
  public final void execute(Object... paramVarArgs)
  {
    // Byte code:
    //   0: aload_1
    //   1: ifnull +362 -> 363
    //   4: aload_1
    //   5: iconst_0
    //   6: aaload
    //   7: invokevirtual 36	java/lang/Object:toString	()Ljava/lang/String;
    //   10: ldc 38
    //   12: invokevirtual 44	java/lang/String:equals	(Ljava/lang/Object;)Z
    //   15: ifeq +759 -> 774
    //   18: aload_1
    //   19: arraylength
    //   20: iconst_2
    //   21: if_icmpne +753 -> 774
    //   24: aload_1
    //   25: iconst_1
    //   26: aaload
    //   27: invokevirtual 36	java/lang/Object:toString	()Ljava/lang/String;
    //   30: invokestatic 49	cn/com/xy/sms/sdk/db/c:b	(Ljava/lang/String;)Lcn/com/xy/sms/sdk/db/entity/f;
    //   33: astore_1
    //   34: new 51	java/lang/StringBuilder
    //   37: dup
    //   38: ldc 53
    //   40: invokespecial 56	java/lang/StringBuilder:<init>	(Ljava/lang/String;)V
    //   43: aload_1
    //   44: invokevirtual 60	java/lang/StringBuilder:append	(Ljava/lang/Object;)Ljava/lang/StringBuilder;
    //   47: pop
    //   48: aload_1
    //   49: ifnull +624 -> 673
    //   52: invokestatic 66	java/lang/System:currentTimeMillis	()J
    //   55: lstore_3
    //   56: new 51	java/lang/StringBuilder
    //   59: dup
    //   60: ldc 68
    //   62: invokespecial 56	java/lang/StringBuilder:<init>	(Ljava/lang/String;)V
    //   65: aload_1
    //   66: invokevirtual 60	java/lang/StringBuilder:append	(Ljava/lang/Object;)Ljava/lang/StringBuilder;
    //   69: pop
    //   70: aload_1
    //   71: getfield 73	cn/com/xy/sms/sdk/db/entity/f:c	Ljava/lang/String;
    //   74: invokestatic 79	cn/com/xy/sms/sdk/util/StringUtils:isNull	(Ljava/lang/String;)Z
    //   77: ifne +371 -> 448
    //   80: aload_1
    //   81: getfield 81	cn/com/xy/sms/sdk/db/entity/f:d	Ljava/lang/String;
    //   84: invokestatic 79	cn/com/xy/sms/sdk/util/StringUtils:isNull	(Ljava/lang/String;)Z
    //   87: ifne +361 -> 448
    //   90: aload_1
    //   91: getfield 73	cn/com/xy/sms/sdk/db/entity/f:c	Ljava/lang/String;
    //   94: aload_0
    //   95: getfield 22	cn/com/xy/sms/sdk/db/d:c	Lcn/com/xy/sms/sdk/db/entity/f;
    //   98: getfield 73	cn/com/xy/sms/sdk/db/entity/f:c	Ljava/lang/String;
    //   101: invokevirtual 44	java/lang/String:equals	(Ljava/lang/Object;)Z
    //   104: ifne +344 -> 448
    //   107: aload_0
    //   108: getfield 22	cn/com/xy/sms/sdk/db/d:c	Lcn/com/xy/sms/sdk/db/entity/f;
    //   111: aload_1
    //   112: getfield 81	cn/com/xy/sms/sdk/db/entity/f:d	Ljava/lang/String;
    //   115: putfield 81	cn/com/xy/sms/sdk/db/entity/f:d	Ljava/lang/String;
    //   118: aload_0
    //   119: getfield 22	cn/com/xy/sms/sdk/db/d:c	Lcn/com/xy/sms/sdk/db/entity/f;
    //   122: invokestatic 66	java/lang/System:currentTimeMillis	()J
    //   125: putfield 85	cn/com/xy/sms/sdk/db/entity/f:e	J
    //   128: aload_0
    //   129: getfield 22	cn/com/xy/sms/sdk/db/d:c	Lcn/com/xy/sms/sdk/db/entity/f;
    //   132: aload_1
    //   133: getfield 73	cn/com/xy/sms/sdk/db/entity/f:c	Ljava/lang/String;
    //   136: putfield 73	cn/com/xy/sms/sdk/db/entity/f:c	Ljava/lang/String;
    //   139: aload_0
    //   140: getfield 22	cn/com/xy/sms/sdk/db/d:c	Lcn/com/xy/sms/sdk/db/entity/f;
    //   143: iconst_0
    //   144: putfield 89	cn/com/xy/sms/sdk/db/entity/f:f	I
    //   147: aload_0
    //   148: getfield 22	cn/com/xy/sms/sdk/db/d:c	Lcn/com/xy/sms/sdk/db/entity/f;
    //   151: aload_1
    //   152: getfield 92	cn/com/xy/sms/sdk/db/entity/f:h	J
    //   155: lload_3
    //   156: ladd
    //   157: putfield 92	cn/com/xy/sms/sdk/db/entity/f:h	J
    //   160: aload_0
    //   161: getfield 22	cn/com/xy/sms/sdk/db/d:c	Lcn/com/xy/sms/sdk/db/entity/f;
    //   164: lload_3
    //   165: aload_1
    //   166: getfield 95	cn/com/xy/sms/sdk/db/entity/f:i	J
    //   169: ladd
    //   170: putfield 95	cn/com/xy/sms/sdk/db/entity/f:i	J
    //   173: aload_0
    //   174: getfield 22	cn/com/xy/sms/sdk/db/d:c	Lcn/com/xy/sms/sdk/db/entity/f;
    //   177: getfield 97	cn/com/xy/sms/sdk/db/entity/f:b	Ljava/lang/String;
    //   180: astore_1
    //   181: aload_0
    //   182: getfield 22	cn/com/xy/sms/sdk/db/d:c	Lcn/com/xy/sms/sdk/db/entity/f;
    //   185: getfield 73	cn/com/xy/sms/sdk/db/entity/f:c	Ljava/lang/String;
    //   188: astore 9
    //   190: aload_0
    //   191: getfield 22	cn/com/xy/sms/sdk/db/d:c	Lcn/com/xy/sms/sdk/db/entity/f;
    //   194: getfield 81	cn/com/xy/sms/sdk/db/entity/f:d	Ljava/lang/String;
    //   197: astore 10
    //   199: aload_0
    //   200: getfield 22	cn/com/xy/sms/sdk/db/d:c	Lcn/com/xy/sms/sdk/db/entity/f;
    //   203: getfield 85	cn/com/xy/sms/sdk/db/entity/f:e	J
    //   206: lstore_3
    //   207: aload_0
    //   208: getfield 22	cn/com/xy/sms/sdk/db/d:c	Lcn/com/xy/sms/sdk/db/entity/f;
    //   211: getfield 89	cn/com/xy/sms/sdk/db/entity/f:f	I
    //   214: istore_2
    //   215: aload_0
    //   216: getfield 22	cn/com/xy/sms/sdk/db/d:c	Lcn/com/xy/sms/sdk/db/entity/f;
    //   219: getfield 92	cn/com/xy/sms/sdk/db/entity/f:h	J
    //   222: lstore 5
    //   224: aload_0
    //   225: getfield 22	cn/com/xy/sms/sdk/db/d:c	Lcn/com/xy/sms/sdk/db/entity/f;
    //   228: getfield 95	cn/com/xy/sms/sdk/db/entity/f:i	J
    //   231: lstore 7
    //   233: new 99	android/content/ContentValues
    //   236: dup
    //   237: invokespecial 100	android/content/ContentValues:<init>	()V
    //   240: astore 11
    //   242: aload 11
    //   244: ldc 102
    //   246: aload 9
    //   248: invokevirtual 106	android/content/ContentValues:put	(Ljava/lang/String;Ljava/lang/String;)V
    //   251: aload 11
    //   253: ldc 108
    //   255: aload 10
    //   257: invokevirtual 106	android/content/ContentValues:put	(Ljava/lang/String;Ljava/lang/String;)V
    //   260: aload 11
    //   262: ldc 110
    //   264: iload_2
    //   265: invokestatic 116	java/lang/Integer:valueOf	(I)Ljava/lang/Integer;
    //   268: invokevirtual 119	android/content/ContentValues:put	(Ljava/lang/String;Ljava/lang/Integer;)V
    //   271: aload 11
    //   273: ldc 121
    //   275: new 51	java/lang/StringBuilder
    //   278: dup
    //   279: lload_3
    //   280: invokestatic 124	java/lang/String:valueOf	(J)Ljava/lang/String;
    //   283: invokespecial 56	java/lang/StringBuilder:<init>	(Ljava/lang/String;)V
    //   286: invokevirtual 125	java/lang/StringBuilder:toString	()Ljava/lang/String;
    //   289: invokevirtual 106	android/content/ContentValues:put	(Ljava/lang/String;Ljava/lang/String;)V
    //   292: aload 11
    //   294: ldc 127
    //   296: new 51	java/lang/StringBuilder
    //   299: dup
    //   300: lload 5
    //   302: invokestatic 124	java/lang/String:valueOf	(J)Ljava/lang/String;
    //   305: invokespecial 56	java/lang/StringBuilder:<init>	(Ljava/lang/String;)V
    //   308: invokevirtual 125	java/lang/StringBuilder:toString	()Ljava/lang/String;
    //   311: invokevirtual 106	android/content/ContentValues:put	(Ljava/lang/String;Ljava/lang/String;)V
    //   314: aload 11
    //   316: ldc -127
    //   318: new 51	java/lang/StringBuilder
    //   321: dup
    //   322: lload 7
    //   324: invokestatic 124	java/lang/String:valueOf	(J)Ljava/lang/String;
    //   327: invokespecial 56	java/lang/StringBuilder:<init>	(Ljava/lang/String;)V
    //   330: invokevirtual 125	java/lang/StringBuilder:toString	()Ljava/lang/String;
    //   333: invokevirtual 106	android/content/ContentValues:put	(Ljava/lang/String;Ljava/lang/String;)V
    //   336: ldc -125
    //   338: aload 11
    //   340: ldc -123
    //   342: iconst_1
    //   343: anewarray 40	java/lang/String
    //   346: dup
    //   347: iconst_0
    //   348: aload_1
    //   349: aastore
    //   350: invokestatic 139	cn/com/xy/sms/sdk/db/DBManager:update	(Ljava/lang/String;Landroid/content/ContentValues;Ljava/lang/String;[Ljava/lang/String;)I
    //   353: pop
    //   354: aload_0
    //   355: getfield 24	cn/com/xy/sms/sdk/db/d:d	Lcn/com/xy/sms/sdk/Iservice/XyCallBack;
    //   358: ldc -115
    //   360: invokestatic 147	cn/com/xy/sms/sdk/util/XyUtil:doXycallBack	(Lcn/com/xy/sms/sdk/Iservice/XyCallBack;Ljava/lang/String;)V
    //   363: aload_0
    //   364: getfield 18	cn/com/xy/sms/sdk/db/d:a	Z
    //   367: ifeq +31 -> 398
    //   370: invokestatic 153	cn/com/xy/sms/sdk/constant/Constant:getContext	()Landroid/content/Context;
    //   373: ldc -101
    //   375: invokestatic 161	cn/com/xy/sms/sdk/db/entity/SysParamEntityManager:getIntParam	(Landroid/content/Context;Ljava/lang/String;)I
    //   378: ifne +20 -> 398
    //   381: aload_0
    //   382: getfield 20	cn/com/xy/sms/sdk/db/d:b	Ljava/util/Map;
    //   385: invokestatic 167	cn/com/xy/sms/sdk/net/NetUtil:checkAccessNetWork	(Ljava/util/Map;)Z
    //   388: ifeq +10 -> 398
    //   391: aload_0
    //   392: getfield 22	cn/com/xy/sms/sdk/db/d:c	Lcn/com/xy/sms/sdk/db/entity/f;
    //   395: invokestatic 170	cn/com/xy/sms/sdk/db/c:b	(Lcn/com/xy/sms/sdk/db/entity/f;)V
    //   398: return
    //   399: astore_1
    //   400: aload_1
    //   401: invokevirtual 173	java/lang/Throwable:printStackTrace	()V
    //   404: goto -50 -> 354
    //   407: astore_1
    //   408: aload_1
    //   409: invokevirtual 173	java/lang/Throwable:printStackTrace	()V
    //   412: aload_0
    //   413: getfield 18	cn/com/xy/sms/sdk/db/d:a	Z
    //   416: ifeq -18 -> 398
    //   419: invokestatic 153	cn/com/xy/sms/sdk/constant/Constant:getContext	()Landroid/content/Context;
    //   422: ldc -101
    //   424: invokestatic 161	cn/com/xy/sms/sdk/db/entity/SysParamEntityManager:getIntParam	(Landroid/content/Context;Ljava/lang/String;)I
    //   427: ifne -29 -> 398
    //   430: aload_0
    //   431: getfield 20	cn/com/xy/sms/sdk/db/d:b	Ljava/util/Map;
    //   434: invokestatic 167	cn/com/xy/sms/sdk/net/NetUtil:checkAccessNetWork	(Ljava/util/Map;)Z
    //   437: ifeq -39 -> 398
    //   440: aload_0
    //   441: getfield 22	cn/com/xy/sms/sdk/db/d:c	Lcn/com/xy/sms/sdk/db/entity/f;
    //   444: invokestatic 170	cn/com/xy/sms/sdk/db/c:b	(Lcn/com/xy/sms/sdk/db/entity/f;)V
    //   447: return
    //   448: aload_0
    //   449: getfield 22	cn/com/xy/sms/sdk/db/d:c	Lcn/com/xy/sms/sdk/db/entity/f;
    //   452: aload_1
    //   453: getfield 92	cn/com/xy/sms/sdk/db/entity/f:h	J
    //   456: lload_3
    //   457: ladd
    //   458: putfield 92	cn/com/xy/sms/sdk/db/entity/f:h	J
    //   461: aload_0
    //   462: getfield 22	cn/com/xy/sms/sdk/db/d:c	Lcn/com/xy/sms/sdk/db/entity/f;
    //   465: lload_3
    //   466: aload_1
    //   467: getfield 95	cn/com/xy/sms/sdk/db/entity/f:i	J
    //   470: ladd
    //   471: putfield 95	cn/com/xy/sms/sdk/db/entity/f:i	J
    //   474: aload_0
    //   475: getfield 22	cn/com/xy/sms/sdk/db/d:c	Lcn/com/xy/sms/sdk/db/entity/f;
    //   478: getfield 97	cn/com/xy/sms/sdk/db/entity/f:b	Ljava/lang/String;
    //   481: astore_1
    //   482: aload_0
    //   483: getfield 22	cn/com/xy/sms/sdk/db/d:c	Lcn/com/xy/sms/sdk/db/entity/f;
    //   486: getfield 92	cn/com/xy/sms/sdk/db/entity/f:h	J
    //   489: lstore_3
    //   490: aload_0
    //   491: getfield 22	cn/com/xy/sms/sdk/db/d:c	Lcn/com/xy/sms/sdk/db/entity/f;
    //   494: getfield 95	cn/com/xy/sms/sdk/db/entity/f:i	J
    //   497: lstore 5
    //   499: new 99	android/content/ContentValues
    //   502: dup
    //   503: invokespecial 100	android/content/ContentValues:<init>	()V
    //   506: astore 9
    //   508: aload 9
    //   510: ldc 121
    //   512: new 51	java/lang/StringBuilder
    //   515: dup
    //   516: invokestatic 66	java/lang/System:currentTimeMillis	()J
    //   519: invokestatic 124	java/lang/String:valueOf	(J)Ljava/lang/String;
    //   522: invokespecial 56	java/lang/StringBuilder:<init>	(Ljava/lang/String;)V
    //   525: invokevirtual 125	java/lang/StringBuilder:toString	()Ljava/lang/String;
    //   528: invokevirtual 106	android/content/ContentValues:put	(Ljava/lang/String;Ljava/lang/String;)V
    //   531: aload 9
    //   533: ldc 127
    //   535: new 51	java/lang/StringBuilder
    //   538: dup
    //   539: lload_3
    //   540: invokestatic 124	java/lang/String:valueOf	(J)Ljava/lang/String;
    //   543: invokespecial 56	java/lang/StringBuilder:<init>	(Ljava/lang/String;)V
    //   546: invokevirtual 125	java/lang/StringBuilder:toString	()Ljava/lang/String;
    //   549: invokevirtual 106	android/content/ContentValues:put	(Ljava/lang/String;Ljava/lang/String;)V
    //   552: aload 9
    //   554: ldc -127
    //   556: new 51	java/lang/StringBuilder
    //   559: dup
    //   560: lload 5
    //   562: invokestatic 124	java/lang/String:valueOf	(J)Ljava/lang/String;
    //   565: invokespecial 56	java/lang/StringBuilder:<init>	(Ljava/lang/String;)V
    //   568: invokevirtual 125	java/lang/StringBuilder:toString	()Ljava/lang/String;
    //   571: invokevirtual 106	android/content/ContentValues:put	(Ljava/lang/String;Ljava/lang/String;)V
    //   574: ldc -125
    //   576: aload 9
    //   578: ldc -123
    //   580: iconst_1
    //   581: anewarray 40	java/lang/String
    //   584: dup
    //   585: iconst_0
    //   586: aload_1
    //   587: aastore
    //   588: invokestatic 139	cn/com/xy/sms/sdk/db/DBManager:update	(Ljava/lang/String;Landroid/content/ContentValues;Ljava/lang/String;[Ljava/lang/String;)I
    //   591: pop
    //   592: new 51	java/lang/StringBuilder
    //   595: dup
    //   596: aload_0
    //   597: getfield 22	cn/com/xy/sms/sdk/db/d:c	Lcn/com/xy/sms/sdk/db/entity/f;
    //   600: getfield 97	cn/com/xy/sms/sdk/db/entity/f:b	Ljava/lang/String;
    //   603: invokestatic 176	java/lang/String:valueOf	(Ljava/lang/Object;)Ljava/lang/String;
    //   606: invokespecial 56	java/lang/StringBuilder:<init>	(Ljava/lang/String;)V
    //   609: ldc -78
    //   611: invokevirtual 181	java/lang/StringBuilder:append	(Ljava/lang/String;)Ljava/lang/StringBuilder;
    //   614: pop
    //   615: aload_0
    //   616: getfield 24	cn/com/xy/sms/sdk/db/d:d	Lcn/com/xy/sms/sdk/Iservice/XyCallBack;
    //   619: ldc 38
    //   621: invokestatic 147	cn/com/xy/sms/sdk/util/XyUtil:doXycallBack	(Lcn/com/xy/sms/sdk/Iservice/XyCallBack;Ljava/lang/String;)V
    //   624: goto -261 -> 363
    //   627: astore_1
    //   628: aload_0
    //   629: getfield 18	cn/com/xy/sms/sdk/db/d:a	Z
    //   632: ifeq +31 -> 663
    //   635: invokestatic 153	cn/com/xy/sms/sdk/constant/Constant:getContext	()Landroid/content/Context;
    //   638: ldc -101
    //   640: invokestatic 161	cn/com/xy/sms/sdk/db/entity/SysParamEntityManager:getIntParam	(Landroid/content/Context;Ljava/lang/String;)I
    //   643: ifne +20 -> 663
    //   646: aload_0
    //   647: getfield 20	cn/com/xy/sms/sdk/db/d:b	Ljava/util/Map;
    //   650: invokestatic 167	cn/com/xy/sms/sdk/net/NetUtil:checkAccessNetWork	(Ljava/util/Map;)Z
    //   653: ifeq +10 -> 663
    //   656: aload_0
    //   657: getfield 22	cn/com/xy/sms/sdk/db/d:c	Lcn/com/xy/sms/sdk/db/entity/f;
    //   660: invokestatic 170	cn/com/xy/sms/sdk/db/c:b	(Lcn/com/xy/sms/sdk/db/entity/f;)V
    //   663: aload_1
    //   664: athrow
    //   665: astore_1
    //   666: aload_1
    //   667: invokevirtual 173	java/lang/Throwable:printStackTrace	()V
    //   670: goto -78 -> 592
    //   673: aload_0
    //   674: getfield 22	cn/com/xy/sms/sdk/db/d:c	Lcn/com/xy/sms/sdk/db/entity/f;
    //   677: getfield 97	cn/com/xy/sms/sdk/db/entity/f:b	Ljava/lang/String;
    //   680: astore_1
    //   681: new 99	android/content/ContentValues
    //   684: dup
    //   685: invokespecial 100	android/content/ContentValues:<init>	()V
    //   688: astore 9
    //   690: aload 9
    //   692: ldc 121
    //   694: new 51	java/lang/StringBuilder
    //   697: dup
    //   698: invokestatic 66	java/lang/System:currentTimeMillis	()J
    //   701: invokestatic 124	java/lang/String:valueOf	(J)Ljava/lang/String;
    //   704: invokespecial 56	java/lang/StringBuilder:<init>	(Ljava/lang/String;)V
    //   707: invokevirtual 125	java/lang/StringBuilder:toString	()Ljava/lang/String;
    //   710: invokevirtual 106	android/content/ContentValues:put	(Ljava/lang/String;Ljava/lang/String;)V
    //   713: ldc -125
    //   715: aload 9
    //   717: ldc -123
    //   719: iconst_1
    //   720: anewarray 40	java/lang/String
    //   723: dup
    //   724: iconst_0
    //   725: aload_1
    //   726: aastore
    //   727: invokestatic 139	cn/com/xy/sms/sdk/db/DBManager:update	(Ljava/lang/String;Landroid/content/ContentValues;Ljava/lang/String;[Ljava/lang/String;)I
    //   730: pop
    //   731: new 51	java/lang/StringBuilder
    //   734: dup
    //   735: aload_0
    //   736: getfield 22	cn/com/xy/sms/sdk/db/d:c	Lcn/com/xy/sms/sdk/db/entity/f;
    //   739: getfield 97	cn/com/xy/sms/sdk/db/entity/f:b	Ljava/lang/String;
    //   742: invokestatic 176	java/lang/String:valueOf	(Ljava/lang/Object;)Ljava/lang/String;
    //   745: invokespecial 56	java/lang/StringBuilder:<init>	(Ljava/lang/String;)V
    //   748: ldc -78
    //   750: invokevirtual 181	java/lang/StringBuilder:append	(Ljava/lang/String;)Ljava/lang/StringBuilder;
    //   753: pop
    //   754: aload_0
    //   755: getfield 24	cn/com/xy/sms/sdk/db/d:d	Lcn/com/xy/sms/sdk/Iservice/XyCallBack;
    //   758: ldc 38
    //   760: invokestatic 147	cn/com/xy/sms/sdk/util/XyUtil:doXycallBack	(Lcn/com/xy/sms/sdk/Iservice/XyCallBack;Ljava/lang/String;)V
    //   763: goto -400 -> 363
    //   766: astore_1
    //   767: aload_1
    //   768: invokevirtual 173	java/lang/Throwable:printStackTrace	()V
    //   771: goto -40 -> 731
    //   774: aload_0
    //   775: getfield 24	cn/com/xy/sms/sdk/db/d:d	Lcn/com/xy/sms/sdk/Iservice/XyCallBack;
    //   778: ldc -73
    //   780: invokestatic 147	cn/com/xy/sms/sdk/util/XyUtil:doXycallBack	(Lcn/com/xy/sms/sdk/Iservice/XyCallBack;Ljava/lang/String;)V
    //   783: goto -420 -> 363
    // Local variable table:
    //   start	length	slot	name	signature
    //   0	786	0	this	d
    //   0	786	1	paramVarArgs	Object[]
    //   214	51	2	i	int
    //   55	485	3	l1	long
    //   222	339	5	l2	long
    //   231	92	7	l3	long
    //   188	528	9	localObject	Object
    //   197	59	10	str	String
    //   240	99	11	localContentValues	android.content.ContentValues
    // Exception table:
    //   from	to	target	type
    //   233	354	399	java/lang/Throwable
    //   4	48	407	java/lang/Throwable
    //   52	233	407	java/lang/Throwable
    //   354	363	407	java/lang/Throwable
    //   400	404	407	java/lang/Throwable
    //   448	499	407	java/lang/Throwable
    //   592	624	407	java/lang/Throwable
    //   666	670	407	java/lang/Throwable
    //   673	681	407	java/lang/Throwable
    //   731	763	407	java/lang/Throwable
    //   767	771	407	java/lang/Throwable
    //   774	783	407	java/lang/Throwable
    //   4	48	627	finally
    //   52	233	627	finally
    //   233	354	627	finally
    //   354	363	627	finally
    //   400	404	627	finally
    //   408	412	627	finally
    //   448	499	627	finally
    //   499	592	627	finally
    //   592	624	627	finally
    //   666	670	627	finally
    //   673	681	627	finally
    //   681	731	627	finally
    //   731	763	627	finally
    //   767	771	627	finally
    //   774	783	627	finally
    //   499	592	665	java/lang/Throwable
    //   681	731	766	java/lang/Throwable
  }
}

/* Location:
 * Qualified Name:     cn.com.xy.sms.sdk.db.d
 * Java Class Version: 6 (50.0)
 * JD-Core Version:    0.7.1
 */